Workbook

Sheet Anleitung
A1: LoopforgeLab GmbH – Financial Projection Model
A3: Projektionszeitraum: 52 Monate (ca. 4,3 Jahre)
A5: INHALTSVERZEICHNIS
A6: Sheet 1: Anleitung – Diese Seite mit Übersicht und Legende
A7: Sheet 2: Inputs – Zentrale Eingabewerte (HIER STARTEN)
A8: Sheet 3: P&L – Gewinn- und Verlustrechnung (monatlich + jährlich)
A9: Sheet 4: Revenue – Detaillierte Umsatzmodellierung
A10: Sheet 5: Costs – Detaillierte Kostenaufschlüsselung
A11: Sheet 6: Balance Sheet – Vereinfachte Bilanz
A12: Sheet 7: Cash Flow – Kapitalflussrechnung mit Runway
A14: FARBCODIERUNG
A15: Blau | B15: Editierbare Eingabefelder
A16: Schwarz | B16: Formeln – nicht manuell ändern
A17: Grün | B17: Verweise auf andere Sheets
A18: Gelb hinterlegt | B18: Kritische Annahmen
A20: KURZANLEITUNG
A21: 1. Gehen Sie zum Sheet 'Inputs' und passen Sie alle blau markierten Werte an.
A22: 2. Alle anderen Sheets berechnen sich automatisch aus den Inputs.
A23: 3. Prüfen Sie die P&L, Revenue und Cash Flow Sheets auf Plausibilität.
A24: 4. Achten Sie auf rot markierte Warnungen (z.B. Runway < 6 Monate).
A25: 5. Exportieren Sie relevante Sheets als PDF für Investoren-Präsentationen.
A27: DISCLAIMER: Diese Projektion dient ausschließlich der Planung.
A28: Tatsächliche Ergebnisse können erheblich abweichen. Keine Garantie.

Sheet Inputs
A1: ZENTRALE EINGABEWERTE | B1: Wert | C1: Erklärung / Hinweis | D1: Bemerkungen
A3: ALLGEMEINE EINSTELLUNGEN
A4: Firmenname | B4: LoopforgeLab GmbH | C4: Name des Unternehmens
A5: Startdatum | B5: 46113 | C5: Beginn der Projektionen
A6: Währung | B6: EUR | C6: EUR für DACH-Startups
A7: Steuersatz | B7: 0.3 | C7: KSt + GewSt (~30% in DE) | D7: Übernahme des Standardsatzes (KSt + GewSt in Deutschland).
A9: FINANZIERUNGSRUNDEN
A10: Ideation Phase | B10: 90000 | C10: Typisch: 100.000-500.000€ | D10: Phase: 1.4.26 bis 15.7.2026 MVP-Anschubfinanzierung; stellt keine Unternehmensbewertung dar.
A11: Ideation Phase | B11: 1 | C11: Monat der Einzahlung | D11: MVP-Entwicklung und IP-Aufbau starten unmittelbar.
A12: Pre-Seed Betrag | B12: 1500000 | C12: Typisch: 500.000-2.000.000€ | D12: Pre-Seed Phase ab VC Pitch im Juli '26 (1.5M-3M Bewertung).
A13: Pre-Seed Monat | B13: 5 | C13: Typisch: Monat 5 | D13: Juli 2026 entspricht Monat 5 Fokus auf Pilot-Traction.
A14: Seed Betrag | B14: 6000000 | C14: Typisch: 3.000.000-10.000.000€ | D14: Abhängig von Pilotprojekten und Reife des Produktes
A15: Seed Monat | B15: 17 | C15: Typisch: Monat 17 | D15: Geplant für Mitte 2027.
A16: Series A Betrag | B16: 15000000 | C16: Typisch: 10.000.000-25.000.000€ | D16: Vorerst unverändert als langfristige Wachstumsambition.
A17: Series A Monat | B17: 35 | C17: Typisch: Monat 35 | D17: Geplant für Herbst 2028.
A19: REVENUE-ANNAHMEN (SaaS/ARR)
A20: Startpreis pro Seat/Jahr | B20: 12000 | C20: Jährliche Lizenzgebühr pro Nutzer | D20: 1. Realistisch? Hängt auch ab vom Business Modell..Pricing basierend auf Wettbewerb oder auf voraussichtlichem Einsparpotential? 2. weitere Erlösquellen? Beratung? Implementierungsaufwand? Hybrid-Modell: Deckt Fixkosten und partizipiert am TCO-Einsparwert. [1] | E20: 2. Regulatory Moat (DPP): JE nach Branche (hier: Annahme von neuen Zielbranche in Bezuf auf DPP Verpflichtung) Die Zielbranchen Batterien und Elektronik unterliegen ab 2027 der DPP-Pflicht. Dies rechtfertigt höhere Preise und eine stärkere NRR, da LFL hiermit zur "Compliance Engine" des Kunden wird. -->"Compliance" könnte aber auch durch andere Benefits ersetzt werden
A21: Preiserhöhung/Jahr | B21: 0.08 | C21: Typisch: 3-5% p.a. | D21: Standard für AI-SaaS 2026 (Kompensation Inferenz/Innovation). [4]
A22: Erste zahlende Kunden Monat | B22: 9 | C22: Wann erster Umsatz? | D22: Erster Umsatz in Monat 8 (Start: 04/26)…Realistisch? Wie lange Lead-Time? Zielkunden? Beachhead-Market? Weitere Begründung: wenn im Automotivebereich: Puffer für Sales-Zyklen (9-12 Mon.) und TISAX im Mittelstand. [1
A23: Initiale Seats | B23: 5 | C23: Anzahl Seats beim ersten Kunden | D23: Realistisch? Hängt von Kundengrösse ab. Implementierungsaufwand je Kunde mit einkalkulieren weitere Aspekte: Kalkulieren mit 1-2 Projekten/ Start mit Pilotprojekten (Werke) zur ROI-Validierung ("Land&Expand")
A24: Monatliche Seat-Wachstumsrate | B24: 0.05 | C24: Wachstum neue Seats/Monat | D24: -->hier eine Annahme bzgll Vertriebsplanung treffen. Wie hoch ist die Zahl der Verkauften Sitze nach 1, 2, 3 Jahren? Gibt es noch andere Erlösströme? ALTERNATIVE: Account-basierte Planng: Wechsel auf "Stufenfunktion" beim Aufbau des Geschäfts (Roll-out pro Werk statt linearer Rate)
A25: Enterprise-Deals ab Monat | B25: 24 | C25: Wann starten große Verträge? Wenn Automotive: Verschiebung durch längere Technical Validation und Compliance-Hürden. | E25: 3. Vertriebsrealismus: Der Start des Umsatzes wurde nach hinten geschoben da der industrielle Mittelstand ("Hidden Champions") langsame Entscheidungsprozesse und hohe Sicherheitsanforderungen (TISAX) hat. Die Zeit bis zum Juli 2026 wird für die Validierung der TCO-Einsparungen (Ausschuss-Reduktion) bei Pilotkunden genutzt.
A26: Durchschnitt Enterprise ARR | B26: 150000 | C26: Typisch: 50.000-200.000€/Jahr | D26: Höheres Volumen durch Tiefe der Integration: hier Annahme von weiteren Benefits wie Einbeziehung von DPP & Sustainability
A27: Enterprise Deals pro Quartal | B27: 1 | C27: Neue Enterprise-Deals pro Quartal
A28: Jährliche Churn Rate | B28: 0.08 | C28: Typisch SaaS: 5-10% | D28: Konservative Planung für komplexe industrielle Buying Center. Plausibel im Mittel (höher im Pilot-Jahr 1; niedriger ab Jahr 3).
A29: Net Revenue Retention | B29: 1.18 | C29: Expansion - Churn, typisch: 100-120% | D29: Erklärung: Realisierbar durch DPP-Zusatzmodule und Material-Analytics-Upgrades, ergo weiteren monetarisierbaren Benefits
A31: GEHÄLTER (Brutto/Jahr)
A32: CEO Gehalt | B32: 72000 | C32: Typisch Startup: 60.000-90.000€ | D32: Gründer-Satz Pre-Seed); Anpassung ab Seed-Runde. Muss noch genauer präzisiert werden
A33: CTO Gehalt | B33: 72000 | C33: Typisch Startup: 60.000-90.000€ | D33: Gründer-Satz Pre-Seed); Anpassung ab Seed-Runde. Muss noch genauer präzisiert werden
A34: CCO Gehalt | B34: 72000 | C34: Typisch Startup: 60.000-90.000€ | D34: Gründer-Satz Pre-Seed); Anpassung ab Seed-Runde. Muss noch genauer präzisiert werden
A35: Senior Engineer Gehalt | B35: 90000 | C35: Typisch: 70.000-90.000€ | D35: Berliner Tech-Benchmark 2025/26 für Senior-Fullstack/Backends. [9]
A36: Junior Engineer Gehalt | B36: 60000 | C36: Typisch: 45.000-60.000€ | D36: Anpassung an gestiegene Einstiegsgehälter für Top-Tech-Talente. [9]
A37: ML/AI Engineer Gehalt | B37: 110000 | C37: Typisch: 75.000-100.000€ | D37: Höchste Marktnachfrage; KI-Experten in Berlin deutlich über SWE-Schnitt. [10]
A38: Product Manager Gehalt | B38: 80000 | C38: Typisch: 65.000-85.000€ | D38: Durchschnitt für Technical PMs (Industrial AI) am Standort Berlin
A39: Sales Representative Gehalt | B39: 130000 | C39: Typisch: 50.000-70.000€ + Provision | D39: Split 50/50 (65k fix + 65k var); zwingend für Enterprise-Vertrieb. [12
A40: Marketing Manager Gehalt | B40: 65000 | C40: Typisch: 55.000-75.000€ | D40: Anpassung an Marktniveau für B2B-Industrie-Spezialisten.
A41: Customer Success Gehalt | B41: 65000 | C41: Typisch: 45.000-60.000€ | D41: Shift hin zu Solution Architect Profil (techn. Implementierung). [13]
A42: Office/Admin Gehalt | B42: 45000 | C42: Typisch: 40.000-50.000€ | D42: (marktüblich für Berlin).
A43: Jährliche Gehaltserhöhung | B43: 0.05 | C43: Typisch: 3-5% | D43: Berücksichtigt Inflations- und Kompetenzentwicklung im Tech-Sektor.
A44: Lohnnebenkosten | B44: 0.21 | C44: AG-Anteil Sozialversicherung ~20-21% | D44: Übernahme des gesetzlichen AG-Anteils.
A46: EINSTELLUNGSPLAN (Eintrittsmonat)
A47: 1. Senior Engineer | B47: 7 | C47: Erste technische Verstärkung | D47: Kern-Dev für MVP-Finalisierung und Deep IP.
A48: 2. Senior Engineer | B48: 10 | C48: Zweite technische Verstärkung | D48: Skalierung der Kern-Architektur.
A49: 1. Junior Engineer | B49: 9 | C49: Junior Developer | D49: Support bei Feature-Entwicklung.
A50: 1. ML/AI Engineer | B50: 8 | C50: ML/AI Spezialist | D50: Fokus auf agentische Systeme und Design-Algorithmen.
A51: 2. ML/AI Engineer | B51: 14 | C51: Zweiter ML Engineer | D51: Vertiefung der Material-Analytics-Funktionen.
A52: 1. Sales Rep | B52: 10 | C52: Erster Vertriebsmitarbeiter | D52: KI-AGENT Substitution durch AI-SDR (Lead Gen/Outbound) @ ca. 500 EUR/Mo. [14 | E52: 1. AI-First Economics: Durch den Einsatz von KI-Agenten in der Akquise (SDR) und im Support senken wir die Fixkosten (Burn Rate), müssen aber die variablen Cloud-Kosten (COGS) höher gewichten. Dies führt zu einer realistischeren Bruttomarge von ca. 70 % im Vergleich zu den klassischen 90 % bei Standard-SaaS.
A53: 2. Sales Rep | B53: 18 | C53: Zweiter Vertrieb | D53: Human-in-the-Loop für komplexe Enterprise-Abschlüsse.
A54: 1. Customer Success | B54: 12 | C54: Erster CS Manager | D54: KI-AGENT Substitution durch Wissens-Agent (RAG) für Support & Doku. [15]
A55: 1. Marketing Manager | B55: 11 | C55: Marketing | D55: Fokus auf Content (ROI-Case Studies) und Industry-Partner.
A56: 1. Product Manager | B56: 13 | C56: Product Management | D56: Überführung der Pilot-Learnings in das Kernprodukt.
A57: 1. Office Manager | B57: 14 | C57: Admin/Office | D57: Übernahme zur administrativen Entlastung der Gründer.
A58: 3. Senior Engineer | B58: 18 | C58: Dritter Senior Engineer | D58: Ausbau der Enterprise-Readiness (SSO; Audit Logs).
A59: 4. Senior Engineer | B59: 24 | C59: Vierter Senior Engineer | D59: Zweite Dev-Squad zur Skalierung.
A60: 2. Junior Engineer | B60: 20 | C60: Zweiter Junior | D60: Team-Erweiterung.
A61: 3. ML/AI Engineer | B61: 22 | C61: Dritter ML Engineer | D61: Optimierung der Inferenzkosten (COGS-Effizienz).
A62: 3. Sales Rep | B62: 26 | C62: Dritter Vertrieb | D62: Marktausweitung (Batterie- & Elektronik-Sektor).
A63: 2. Customer Success | B63: 24 | C63: Zweiter CS Manager | D63: First Hire für komplexes Solution Architecting vor Ort. [13]
A64: 2. Marketing Manager | B64: 28 | C64: Zweiter Marketing | D64: Expansion des Partner-Netzwerks (Engineering Services).
... A69: 4. Sales Rep | B69: 36 | C69: Vierter Vertrieb | D69: Vertriebsskalierung.
A70: 3. Customer Success | B70: 36 | C70: Dritter CS
A71: Finance Manager | B71: 18 | C71: Finance/Controlling | D71: Notwendig für professionelles Reporting ab Seed-Phase.
A72: 6. Senior Engineer | B72: 38 | C72: Sechster Senior
A73: 7. Senior Engineer | B73: 42 | C73: Siebter Senior
A74: 4. Junior Engineer | B74: 40 | C74: Vierter Junior
A75: 5. ML/AI Engineer | B75: 44 | C75: Fünfter ML Engineer
A76: 5. Sales Rep | B76: 42 | C76: Fünfter Vertrieb
A77: 4. Customer Success | B77: 44 | C77: Vierter CS
A78: 3. Marketing Manager | B78: 40 | C78: Dritter Marketing
A80: TECHNOLOGIE & CLOUD KOSTEN
A81: Cloud/Hosting Basis | B81: 1200 | C81: AWS/Azure/GCP Grundkosten €/Monat | D81: Höhere Last durch GPU-Inferenz und Vektordatenbanken.
A82: Cloud Skalierung pro Seat | B82: 50 | C82: Variable Kosten €/Seat/Monat | D82: Wechsel von Seat- auf Projekt-Basis (AI-intensive Rechenlast).
A83: AI/ML APIs Basis | B83: 1000 | C83: OpenAI/Anthropic etc. €/Monat | D83: Nutzung von Frontier Models (GPT-5/Claude) für Design-Logic.
A84: AI Kosten Wachstum/Monat | B84: 0.05 | C84: Steigerung mit Nutzung | D84: Skalierung proportional zur Nutzung und Datentiefe.
A85: SaaS Tools intern Basis | B85: 400 | C85: Slack, Notion, GitHub etc. €/Monat | D85: Slack; Notion; GitHub etc. (unverändert).
A86: SaaS Tools pro MA | B86: 100 | C86: Zusätzliche Lizenzen €/MA/Monat | D86: Inklusive KI-Coding-Tools (Copilot/Cursor) für Dev-Effizienz.
A87: Software-Lizenzen Dev | B87: 5000 | C87: IDE, Frameworks €/Jahr | D87: Spezialisierte Engineering-Tools und Frameworks (IDE).
A88: Sicherheit & Compliance | B88: 3500 | C88: Security Tools €/Monat | D88: Puffer für TISAX-Audits und laufendes Compliance-Monitoring. [17
A90: HARDWARE & EQUIPMENT
A91: Laptop pro MA | B91: 2500 | C91: Typisch: 1.500-3.000€ | D91: High-End Hardware zwingend für KI-Entwicklung (lokale Inferenz).
A92: Monitor & Peripherie | B92: 800 | C92: Typisch: 500-1.000€ | D92: Standard-Setup für Tech-Mitarbeiter.
A93: Ersatz-Zyklus Monate | B93: 36 | C93: Typisch: 36-48 Monate | D93: Branchenüblicher Turnus.
A94: Sonstige IT-Ausstattung/Jahr | B94: 2000 | C94: Server, Netzwerk etc. | D94: Puffer für Serverkomponenten/Netzwerk.
A96: BÜRO & FACILITIES
A97: Büromiete | B97: 1500 | C97: Coworking anfangs €/Monat | D97: Coworking-Fokus in der ersten Phase (Berlin Mitte/Kreuzberg).
A98: Büro-Upgrade ab Monat | B98: 18 | C98: Wann größeres Büro? | D98: Shift analog zur Einstellung von Solution Architects (Teamgröße).
A99: Neue Büromiete | B99: 4500 | C99: Kosten nach Upgrade €/Monat | D99: Anpassung an Berliner Marktpreise für ca. 15-20 Personen.
A100: Nebenkosten | B100: 300 | C100: Strom, Wasser, Heizung €/Monat | D100: Übernahme.
A101: Internet & Telefon | B101: 150 | C101: €/Monat | D101: Übernahme.
A102: Büroausstattung Initial | B102: 5000 | C102: Möbel, Einrichtung € | D102: Möbel und IT-Grundausstattung für Erst-Team.
A103: Bürobedarf pro MA | B103: 30 | C103: Verbrauchsmaterial €/MA/Monat | D103: Verbrauchsmaterial (unverändert).
A105: PROFESSIONAL SERVICES
A106: Rechtsanwalt Basis/Jahr | B106: 8000 | C106: Laufende Beratung €/Jahr
A107: RA pro Finanzierung | B107: 15000 | C107: Zusätzlich bei Funding €
A108: Steuerberater | B108: 800 | C108: Laufende Buchhaltung €/Monat
A109: Wirtschaftsprüfer/Jahr | B109: 12000 | C109: Ab Series A €/Jahr
A110: WP ab Monat | B110: 17 | C110: Ab wann Wirtschaftsprüfer? Start mit tatsächlicher Seed-Phase Mitte 2027.
A111: Unternehmensberater/Jahr | B111: 5000 | C111: Optional €/Jahr Optionaler Puffer für Spezialberatung (DPP/MDR).
A113: VERSICHERUNGEN & BANK
A114: D&O Versicherung/Jahr | B114: 3000 | C114: Directors & Officers €/Jahr Schutz für Management (Standard-Satz).
...

Sheet P&L
A1: GEWINN- UND VERLUSTRECHNUNG (P&L)
A3: Position | B3: M1 | C3: M2 | D3: M3 | E3: M4 | F3: M5 | G3: M6 | H3: M7 | I3: M8 | J3: M9 | K3: M10 | L3: M11 | M3: M12 | N3: M13 | O3: M14 | P3: M15 | Q3: M16 | R3: M17 | S3: M18 | T3: M19 | U3: M20 | V3: M21 | W3: M22 | X3: M23 | Y3: M24 | Z3: M25 | AA3: M26 | AB3: M27 | AC3: M28 | AD3: M29 | AE3: M30 | AF3: M31 | AG3: M32 | AH3: M33 | AI3: M34 | AJ3: M35 | AK3: M36 | AL3: M37 | AM3: M38 | AN3: M39 | AO3: M40 | AP3: M41 | AQ3: M42 | AR3: M43 | AS3: M44 | AT3: M45 | AU3: M46 | AV3: M47 | AW3: M48 | AX3: M49 | AY3: M50 | AZ3: M51 | BA3: M52
A4: REVENUE
A5: Subscription Revenue | B5: =Revenue!B9 -> 0 | C5: =Revenue!C9 -> 0 | D5: =Revenue!D9 -> 0 | E5: =Revenue!E9 -> 0 | F5: =Revenue!F9 -> 0 | G5: =Revenue!G9 -> 0 | H5: =Revenue!H9 -> 0 | I5: =Revenue!I9 -> 0 | ... BA5: =Revenue!BA9 -> 6802.4448
A6: Enterprise Revenue | B6: =Revenue!B16 -> 0 | C6: =Revenue!C16 -> 0 | D6: =Revenue!D16 -> 0 | E6: =Revenue!E16 -> 0 | F6: =Revenue!F16 -> 0 | G6: =Revenue!G16 -> 0 | H6: =Revenue!H16 -> 0 | I6: =Revenue!I16 -> 0 | ... BA6: =Revenue!BA16 -> 153055.01
A7: TOTAL REVENUE | B7: =B5+B6 -> 0 | C7: =C5+C6 -> 0 | D7: =D5+D6 -> 0 | E7: =E5+E6 -> 0 | F7: =F5+F6 -> 0 | G7: =G5+G6 -> 0 | H7: =H5+H6 -> 0 | I7: =I5+I6 -> 0 | ... BA7: =BA5+BA6 -> 159857.45
A9: COST OF GOODS SOLD (COGS)
A10: Cloud Hosting (variable) | B10: =Costs!B82 -> 0 | C10: =Costs!C82 -> 0 | D10: =Costs!D82 -> 0 | E10: =Costs!E82 -> 0 | F10: =Costs!F82 -> 0 | G10: =Costs!G82 -> 0 | H10: =Costs!H82 -> 0 | I10: =Costs!I82 -> 0 | ... BA10: =Costs!BA82 -> 250
A11: AI/ML API Kosten | B11: =Costs!B83 -> 1000 | C11: =Costs!C83 -> 1050 | D11: =Costs!D83 -> 1102.5 | E11: =Costs!E83 -> 1157.625 | F11: =Costs!F83 -> 1215.5062 | G11: =Costs!G83 -> 1276.2816 | H11: =Costs!H83 -> 1340.0956 | I11: =Costs!I83 -> 1407.1004 | ... BA11: =Costs!BA83 -> 12040.77
A12: Payment Processing | B12: =Costs!B128 -> 0 | C12: =Costs!C128 -> 0 | D12: =Costs!D128 -> 0 | E12: =Costs!E128 -> 0 | F12: =Costs!F128 -> 0 | G12: =Costs!G128 -> 0 | H12: =Costs!H128 -> 0 | I12: =Costs!I128 -> 0 | ... BA12: =Costs!BA128 -> 3996.4363
A13: TOTAL COGS | B13: =SUM(B10:B12) -> 1000 | C13: =SUM(C10:C12) -> 1050 | D13: =SUM(D10:D12) -> 1102.5 | E13: =SUM(E10:E12) -> 1157.625 | F13: =SUM(F10:F12) -> 1215.5062 | G13: =SUM(G10:G12) -> 1276.2816 | H13: =SUM(H10:H12) -> 1340.0956 | I13: =SUM(I10:I12) -> 1407.1004 | ... BA13: =SUM(BA10:BA12) -> 16287.206
A15: GROSS PROFIT | B15: =B7-B13 -> -1000 | C15: =C7-C13 -> -1050 | D15: =D7-D13 -> -1102.5 | E15: =E7-E13 -> -1157.625 | F15: =F7-F13 -> -1215.5062 | G15: =G7-G13 -> -1276.2816 | H15: =H7-H13 -> -1340.0956 | I15: =I7-I13 -> -1407.1004 | ... BA15: =BA7-BA13 -> 143570.25
A16: Gross Margin % | B16: =IFERROR(B15/B7,0) -> 0 | C16: =IFERROR(C15/C7,0) -> 0 | D16: =IFERROR(D15/D7,0) -> 0 | E16: =IFERROR(E15/E7,0) -> 0 | F16: =IFERROR(F15/F7,0) -> 0 | G16: =IFERROR(G15/G7,0) -> 0 | H16: =IFERROR(H15/H7,0) -> 0 | I16: =IFERROR(I15/I7,0) -> 0 | ... BA16: =IFERROR(BA15/BA7,0) -> 0.89811419
A18: OPERATING EXPENSES
A19: Total Personnel | B19: =Costs!B78 -> 21780 | C19: =Costs!C78 -> 21780 | D19: =Costs!D78 -> 21780 | E19: =Costs!E78 -> 21780 | F19: =Costs!F78 -> 21780 | G19: =Costs!G78 -> 21780 | H19: =Costs!H78 -> 30855 | I19: =Costs!I78 -> 41946.667 | ... BA19: =Costs!BA78 -> 366587.57
A20: Total Technology | B20: =Costs!B87 -> 6816.6667 | C20: =Costs!C87 -> 6866.6667 | D20: =Costs!D87 -> 6919.1667 | E20: =Costs!E87 -> 6974.2917 | F20: =Costs!F87 -> 7032.1729 | G20: =Costs!G87 -> 7092.9482 | H20: =Costs!H87 -> 7256.7623 | I20: =Costs!I87 -> 7423.7671 | ... BA20: =Costs!BA87 -> 21307.436
A21: Total Office/Facilities | B21: =Costs!B94 -> 2040 | C21: =Costs!C94 -> 2040 | D21: =Costs!D94 -> 2040 | E21: =Costs!E94 -> 2040 | F21: =Costs!F94 -> 2040 | G21: =Costs!G94 -> 2040 | H21: =Costs!H94 -> 2070 | I21: =Costs!I94 -> 2100 | ... BA21: =Costs!BA94 -> 6000
A22: Total Professional Services | B22: =Costs!B101 -> 16883.333 | C22: =Costs!C101 -> 1883.3333 | D22: =Costs!D101 -> 1883.3333 | E22: =Costs!E101 -> 1883.3333 | F22: =Costs!F101 -> 16883.333 | G22: =Costs!G101 -> 1883.3333 | H22: =Costs!H101 -> 1883.3333 | I22: =Costs!I101 -> 1883.3333 | ... BA22: =Costs!BA101 -> 2883.3333
A23: Total Insurance & Bank | B23: =Costs!B108 -> 591.66667 | C23: =Costs!C108 -> 591.66667 | D23: =Costs!D108 -> 591.66667 | E23: =Costs!E108 -> 591.66667 | F23: =Costs!F108 -> 591.66667 | G23: =Costs!G108 -> 591.66667 | H23: =Costs!H108 -> 591.66667 | I23: =Costs!I108 -> 591.66667 | ... BA23: =Costs!BA108 -> 591.66667
A24: Total Marketing & Sales | B24: =Costs!B117 -> 4383.3333 | C24: =Costs!C117 -> 4408.3333 | D24: =Costs!D117 -> 4434.5833 | E24: =Costs!E117 -> 4462.1458 | F24: =Costs!F117 -> 4491.0865 | G24: =Costs!G117 -> 4521.4741 | H24: =Costs!H117 -> 4553.3812 | I24: =Costs!I117 -> 4586.8835 | ... BA24: =Costs!BA117 -> 12403.718
A25: Total Other OpEx | B25: =Costs!B125 -> 11191.667 | C25: =Costs!C125 -> 1291.6667 | D25: =Costs!D125 -> 1291.6667 | E25: =Costs!E125 -> 1291.6667 | F25: =Costs!F125 -> 1291.6667 | G25: =Costs!G125 -> 1291.6667 | H25: =Costs!H125 -> 4966.6667 | I25: =Costs!I125 -> 5341.6667 | ... BA25: =Costs!BA125 -> 13291.667
A26: Contingency/Buffer | B26: =Costs!B130 -> 3184.3333 | C26: =Costs!C130 -> 1943.0833 | D26: =Costs!D130 -> 1947.0208 | E26: =Costs!E130 -> 1951.1552 | F26: =Costs!F130 -> 2705.4963 | G26: =Costs!G130 -> 1960.0545 | H26: =Costs!H130 -> 2608.8405 | I26: =Costs!I130 -> 3193.6992 | ... BA26: =Costs!BA130 -> 21153.27
A27: TOTAL OPERATING EXPENSES | B27: =SUM(B19:B26) -> 66871 | C27: =SUM(C19:C26) -> 40804.75 | D27: =SUM(D19:D26) -> 40887.438 | E27: =SUM(E19:E26) -> 40974.259 | F27: =SUM(F19:F26) -> 56815.422 | G27: =SUM(G19:G26) -> 41161.143 | H27: =SUM(H19:H26) -> 54785.651 | I27: =SUM(I19:I26) -> 67067.683 | ... BA27: =SUM(BA19:BA26) -> 444218.66
A29: EBITDA | B29: =B15-B27 -> -67871 | C29: =C15-C27 -> -41854.75 | D29: =D15-D27 -> -41989.938 | E29: =E15-E27 -> -42131.884 | F29: =F15-F27 -> -58030.929 | G29: =G15-G27 -> -42437.425 | H29: =H15-H27 -> -56125.746 | I29: =I15-I27 -> -68474.784 | ... BA29: =BA15-BA27 -> -300648.41
A30: EBITDA Margin % | B30: =IFERROR(B29/B7,0) -> 0 | C30: =IFERROR(C29/C7,0) -> 0 | D30: =IFERROR(D29/D7,0) -> 0 | E30: =IFERROR(E29/E7,0) -> 0 | F30: =IFERROR(F29/F7,0) -> 0 | G30: =IFERROR(G29/G7,0) -> 0 | H30: =IFERROR(H29/H7,0) -> 0 | I30: =IFERROR(I29/I7,0) -> 0 | ... BA30: =IFERROR(BA29/BA7,0) -> -1.8807282
A32: Depreciation & Amortization | B32: =Costs!B123/Inputs!$B$134/12 -> 275 | C32: =Costs!C123/Inputs!$B$134/12 -> 0 | D32: =Costs!D123/Inputs!$B$134/12 -> 0 | E32: =Costs!E123/Inputs!$B$134/12 -> 0 | F32: =Costs!F123/Inputs!$B$134/12 -> 0 | G32: =Costs!G123/Inputs!$B$134/12 -> 0 | H32: =Costs!H123/Inputs!$B$134/12 -> 91.666667 | I32: =Costs!I123/Inputs!$B$134/12 -> 91.666667 | ... BA32: =Costs!BA123/Inputs!$B$134/12 -> 0
A34: EBIT (Operating Income) | B34: =B29-B32 -> -68146 | C34: =C29-C32 -> -41854.75 | D34: =D29-D32 -> -41989.938 | E34: =E29-E32 -> -42131.884 | F34: =F29-F32 -> -58030.929 | G34: =G29-G32 -> -42437.425 | H34: =H29-H32 -> -56217.413 | I34: =I29-I32 -> -68566.45 | ... BA34: =BA29-BA32 -> -300648.41
A36: EBT (Earnings Before Tax) | B36: =B34 -> -68146 | C36: =C34 -> -41854.75 | D36: =D34 -> -41989.938 | E36: =E34 -> -42131.884 | F36: =F34 -> -58030.929 | G36: =G34 -> -42437.425 | H36: =H34 -> -56217.413 | I36: =I34 -> -68566.45 | ... BA36: =BA34 -> -300648.41
A37: Income Tax | B37: =IF(B36>0,B36*Inputs!$B$7,0) -> 0 | C37: =IF(C36>0,C36*Inputs!$B$7,0) -> 0 | D37: =IF(D36>0,D36*Inputs!$B$7,0) -> 0 | E37: =IF(E36>0,E36*Inputs!$B$7,0) -> 0 | F37: =IF(F36>0,F36*Inputs!$B$7,0) -> 0 | G37: =IF(G36>0,G36*Inputs!$B$7,0) -> 0 | H37: =IF(H36>0,H36*Inputs!$B$7,0) -> 0 | I37: =IF(I36>0,I36*Inputs!$B$7,0) -> 0 | ... BA37: =IF(BA36>0,BA36*Inputs!$B$7,0) -> 0
A39: NET INCOME | B39: =B36-B37 -> -68146 | C39: =C36-C37 -> -41854.75 | D39: =D36-D37 -> -41989.938 | E39: =E36-E37 -> -42131.884 | F39: =F36-F37 -> -58030.929 | G39: =G36-G37 -> -42437.425 | H39: =H36-H37 -> -56217.413 | I39: =I36-I37 -> -68566.45 | ... BA39: =BA36-BA37 -> -300648.41
A40: Net Margin % | B40: =IFERROR(B39/B7,0) -> 0 | C40: =IFERROR(C39/C7,0) -> 0 | D40: =IFERROR(D39/D7,0) -> 0 | E40: =IFERROR(E39/E7,0) -> 0 | F40: =IFERROR(F39/F7,0) -> 0 | G40: =IFERROR(G39/G7,0) -> 0 | H40: =IFERROR(H39/H7,0) -> 0 | I40: =IFERROR(I39/I7,0) -> 0 | ... BA40: =IFERROR(BA39/BA7,0) -> -1.8807282

Sheet Revenue
A1: UMSATZMODELL - Detaillierte Aufschlüsselung
B2: 46113 | C2: 46143 | D2: 46174 | E2: 46204 | F2: 46235 | G2: 46266 | H2: 46296 | I2: 46327 | J2: 46357 | K2: 46388 | L2: 46419 | M2: 46447 | N2: 46478 | O2: 46508 | P2: 46539 | Q2: 46569 | R2: 46600 | S2: 46631 | T2: 46661 | U2: 46692 | V2: 46722 | W2: 46753 | X2: 46784 | Y2: 46813 | Z2: 46844 | AA2: 46874 | AB2: 46905 | AC2: 46935 | AD2: 46966 | AE2: 46997 | AF2: 47027 | AG2: 47058 | AH2: 47088 | AI2: 47119 | AJ2: 47150 | AK2: 47178 | AL2: 47209 | AM2: 47239 | AN2: 47270 | AO2: 47300 | AP2: 47331 | AQ2: 47362 | AR2: 47392 | AS2: 47423 | AT2: 47453 | AU2: 47484 | AV2: 47515 | AW2: 47543 | AX2: 47574 | AY2: 47604 | AZ2: 47635 | BA2: 47665
A3: Kennzahl | B3: M1 | C3: M2 | D3: M3 | E3: M4 | F3: M5 | G3: M6 | H3: M7 | I3: M8 | J3: M9 | K3: M10 | L3: M11 | M3: M12 | N3: M13 | O3: M14 | P3: M15 | Q3: M16 | R3: M17 | S3: M18 | T3: M19 | U3: M20 | V3: M21 | W3: M22 | X3: M23 | Y3: M24 | Z3: M25 | AA3: M26 | AB3: M27 | AC3: M28 | AD3: M29 | AE3: M30 | AF3: M31 | AG3: M32 | AH3: M33 | AI3: M34 | AJ3: M35 | AK3: M36 | AL3: M37 | AM3: M38 | AN3: M39 | AO3: M40 | AP3: M41 | AQ3: M42 | AR3: M43 | AS3: M44 | AT3: M45 | AU3: M46 | AV3: M47 | AW3: M48 | AX3: M49 | AY3: M50 | AZ3: M51 | BA3: M52
A4: Preis pro Seat/Monat (€) | B4: =IFERROR(Inputs!$B$20/12*(1+Inputs!$B$21)^(INT((1-1)/12)),0) -> 1000 | C4: =Inputs!$B$20/12*(1+Inputs!$B$21)^INT((2-1)/12) -> 1000 | D4: =Inputs!$B$20/12*(1+Inputs!$B$21)^INT((3-1)/12) -> 1000 | E4: =Inputs!$B$20/12*(1+Inputs!$B$21)^INT((4-1)/12) -> 1000 | F4: =Inputs!$B$20/12*(1+Inputs!$B$21)^INT((5-1)/12) -> 1000 | G4: =Inputs!$B$20/12*(1+Inputs!$B$21)^INT((6-1)/12) -> 1000 | H4: =Inputs!$B$20/12*(1+Inputs!$B$21)^INT((7-1)/12) -> 1000 | I4: =Inputs!$B$20/12*(1+Inputs!$B$21)^INT((8-1)/12) -> 1000 | J4: =Inputs!$B$20/12*(1+Inputs!$B$21)^INT((9-1)/12) -> 1000 | K4: =Inputs!$B$20/12*(1+Inputs!$B$21)^INT((10-1)/12) -> 1000 | L4: =Inputs!$B$20/12*(1+Inputs!$B$21)^INT((11-1)/12) -> 1000 | M4: =Inputs!$B$20/12*(1+Inputs!$B$21)^INT((12-1)/12) -> 1000 | N4: =Inputs!$B$20/12*(1+Inputs!$B$21)^INT((13-1)/12) -> 1080 | O4: =Inputs!$B$20/12*(1+Inputs!$B$21)^INT((14-1)/12) -> 1080 | P4: =Inputs!$B$20/12*(1+Inputs!$B$21)^INT((15-1)/12) -> 1080 | Q4: =Inputs!$B$20/12*(1+Inputs!$B$21)^INT((16-1)/12) -> 1080 | R4: =Inputs!$B$20/12*(1+Inputs!$B$21)^INT((17-1)/12) -> 1080 | S4: =Inputs!$B$20/12*(1+Inputs!$B$21)^INT((18-1)/12) -> 1080 | T4: =Inputs!$B$20/12*(1+Inputs!$B$21)^INT((19-1)/12) -> 1080 | U4: =Inputs!$B$20/12*(1+Inputs!$B$21)^INT((20-1)/12) -> 1080 | V4: =Inputs!$B$20/12*(1+Inputs!$B$21)^INT((21-1)/12) -> 1080 | W4: =Inputs!$B$20/12*(1+Inputs!$B$21)^INT((22-1)/12) -> 1080 | X4: =Inputs!$B$20/12*(1+Inputs!$B$21)^INT((23-1)/12) -> 1080 | Y4: =Inputs!$B$20/12*(1+Inputs!$B$21)^INT((24-1)/12) -> 1080 | Z4: =Inputs!$B$20/12*(1+Inputs!$B$21)^INT((25-1)/12) -> 1166.4 | AA4: =Inputs!$B$20/12*(1+Inputs!$B$21)^INT((26-1)/12) -> 1166.4 | AB4: =Inputs!$B$20/12*(1+Inputs!$B$21)^INT((27-1)/12) -> 1166.4 | AC4: =Inputs!$B$20/12*(1+Inputs!$B$21)^INT((28-1)/12) -> 1166.4 | AD4: =Inputs!$B$20/12*(1+Inputs!$B$21)^INT((29-1)/12) -> 1166.4 | AE4: =Inputs!$B$20/12*(1+Inputs!$B$21)^INT((30-1)/12) -> 1166.4 | AF4: =Inputs!$B$20/12*(1+Inputs!$B$21)^INT((31-1)/12) -> 1166.4 | AG4: =Inputs!$B$20/12*(1+Inputs!$B$21)^INT((32-1)/12) -> 1166.4 | AH4: =Inputs!$B$20/12*(1+Inputs!$B$21)^INT((33-1)/12) -> 1166.4 | AI4: =Inputs!$B$20/12*(1+Inputs!$B$21)^INT((34-1)/12) -> 1166.4 | AJ4: =Inputs!$B$20/12*(1+Inputs!$B$21)^INT((35-1)/12) -> 1166.4 | AK4: =Inputs!$B$20/12*(1+Inputs!$B$21)^INT((36-1)/12) -> 1166.4 | AL4: =Inputs!$B$20/12*(1+Inputs!$B$21)^INT((37-1)/12) -> 1259.712 | AM4: =Inputs!$B$20/12*(1+Inputs!$B$21)^INT((38-1)/12) -> 1259.712 | AN4: =Inputs!$B$20/12*(1+Inputs!$B$21)^INT((39-1)/12) -> 1259.712 | AO4: =Inputs!$B$20/12*(1+Inputs!$B$21)^INT((40-1)/12) -> 1259.712 | AP4: =Inputs!$B$20/12*(1+Inputs!$B$21)^INT((41-1)/12) -> 1259.712 | AQ4: =Inputs!$B$20/12*(1+Inputs!$B$21)^INT((42-1)/12) -> 1259.712 | AR4: =Inputs!$B$20/12*(1+Inputs!$B$21)^INT((43-1)/12) -> 1259.712 | AS4: =Inputs!$B$20/12*(1+Inputs!$B$21)^INT((44-1)/12) -> 1259.712 | AT4: =Inputs!$B$20/12*(1+Inputs!$B$21)^INT((45-1)/12) -> 1259.712 | AU4: =Inputs!$B$20/12*(1+Inputs!$B$21)^INT((46-1)/12) -> 1259.712 | AV4: =Inputs!$B$20/12*(1+Inputs!$B$21)^INT((47-1)/12) -> 1259.712 | AW4: =Inputs!$B$20/12*(1+Inputs!$B$21)^INT((48-1)/12) -> 1259.712 | AX4: =Inputs!$B$20/12*(1+Inputs!$B$21)^INT((49-1)/12) -> 1360.489 | AY4: =Inputs!$B$20/12*(1+Inputs!$B$21)^INT((50-1)/12) -> 1360.489 | AZ4: =Inputs!$B$20/12*(1+Inputs!$B$21)^INT((51-1)/12) -> 1360.489 | BA4: =Inputs!$B$20/12*(1+Inputs!$B$21)^INT((52-1)/12) -> 1360.489
A5: Neue Seats | B5: =IF(1>=Inputs!$B$22,Inputs!$B$23,0) -> 0 | C5: =IF(2>=Inputs!$B$22,IF(2=Inputs!$B$22,Inputs!$B$23,ROUND(B8*Inputs!$B$24,0)),0) -> 0 | D5: =IF(3>=Inputs!$B$22,IF(3=Inputs!$B$22,Inputs!$B$23,ROUND(C8*Inputs!$B$24,0)),0) -> 0 | E5: =IF(4>=Inputs!$B$22,IF(4=Inputs!$B$22,Inputs!$B$23,ROUND(D8*Inputs!$B$24,0)),0) -> 0 | F5: =IF(5>=Inputs!$B$22,IF(5=Inputs!$B$22,Inputs!$B$23,ROUND(E8*Inputs!$B$24,0)),0) -> 0 | G5: =IF(6>=Inputs!$B$22,IF(6=Inputs!$B$22,Inputs!$B$23,ROUND(F8*Inputs!$B$24,0)),0) -> 0 | H5: =IF(7>=Inputs!$B$22,IF(7=Inputs!$B$22,Inputs!$B$23,ROUND(G8*Inputs!$B$24,0)),0) -> 0 | I5: =IF(8>=Inputs!$B$22,IF(8=Inputs!$B$22,Inputs!$B$23,ROUND(H8*Inputs!$B$24,0)),0) -> 0 | J5: =IF(9>=Inputs!$B$22,IF(9=Inputs!$B$22,Inputs!$B$23,ROUND(I8*Inputs!$B$24,0)),0) -> 5 | K5: =IF(10>=Inputs!$B$22,IF(10=Inputs!$B$22,Inputs!$B$23,ROUND(J8*Inputs!$B$24,0)),0) -> 0 | L5: =IF(11>=Inputs!$B$22,IF(11=Inputs!$B$22,Inputs!$B$23,ROUND(K8*Inputs!$B$24,0)),0) -> 0 | M5: =IF(12>=Inputs!$B$22,IF(12=Inputs!$B$22,Inputs!$B$23,ROUND(L8*Inputs!$B$24,0)),0) -> 0 | N5: =IF(13>=Inputs!$B$22,IF(13=Inputs!$B$22,Inputs!$B$23,ROUND(M8*Inputs!$B$24,0)),0) -> 0 | O5: =IF(14>=Inputs!$B$22,IF(14=Inputs!$B$22,Inputs!$B$23,ROUND(N8*Inputs!$B$24,0)),0) -> 0 | P5: =IF(15>=Inputs!$B$22,IF(15=Inputs!$B$22,Inputs!$B$23,ROUND(O8*Inputs!$B$24,0)),0) -> 0 | Q5: =IF(16>=Inputs!$B$22,IF(16=Inputs!$B$22,Inputs!$B$23,ROUND(P8*Inputs!$B$24,0)),0) -> 0 | R5: =IF(17>=Inputs!$B$22,IF(17=Inputs!$B$22,Inputs!$B$23,ROUND(Q8*Inputs!$B$24,0)),0) -> 0 | S5: =IF(18>=Inputs!$B$22,IF(18=Inputs!$B$22,Inputs!$B$23,ROUND(R8*Inputs!$B$24,0)),0) -> 0 | T5: =IF(19>=Inputs!$B$22,IF(19=Inputs!$B$22,Inputs!$B$23,ROUND(S8*Inputs!$B$24,0)),0) -> 0 | U5: =IF(20>=Inputs!$B$22,IF(20=Inputs!$B$22,Inputs!$B$23,ROUND(T8*Inputs!$B$24,0)),0) -> 0 | V5: =IF(21>=Inputs!$B$22,IF(21=Inputs!$B$22,Inputs!$B$23,ROUND(U8*Inputs!$B$24,0)),0) -> 0 | W5: =IF(22>=Inputs!$B$22,IF(22=Inputs!$B$22,Inputs!$B$23,ROUND(V8*Inputs!$B$24,0)),0) -> 0 | X5: =IF(23>=Inputs!$B$22,IF(23=Inputs!$B$22,Inputs!$B$23,ROUND(W8*Inputs!$B$24,0)),0) -> 0 | Y5: =IF(24>=Inputs!$B$22,IF(24=Inputs!$B$22,Inputs!$B$23,ROUND(X8*Inputs!$B$24,0)),0) -> 0 | Z5: =IF(25>=Inputs!$B$22,IF(25=Inputs!$B$22,Inputs!$B$23,ROUND(Y8*Inputs!$B$24,0)),0) -> 0 | AA5: =IF(26>=Inputs!$B$22,IF(26=Inputs!$B$22,Inputs!$B$23,ROUND(Z8*Inputs!$B$24,0)),0) -> 0 | AB5: =IF(27>=Inputs!$B$22,IF(27=Inputs!$B$22,Inputs!$B$23,ROUND(AA8*Inputs!$B$24,0)),0) -> 0 | AC5: =IF(28>=Inputs!$B$22,IF(28=Inputs!$B$22,Inputs!$B$23,ROUND(AB8*Inputs!$B$24,0)),0) -> 0 | AD5: =IF(29>=Inputs!$B$22,IF(29=Inputs!$B$22,Inputs!$B$23,ROUND(AC8*Inputs!$B$24,0)),0) -> 0 | AE5: =IF(30>=Inputs!$B$22,IF(30=Inputs!$B$22,Inputs!$B$23,ROUND(AD8*Inputs!$B$24,0)),0) -> 0 | AF5: =IF(31>=Inputs!$B$22,IF(31=Inputs!$B$22,Inputs!$B$23,ROUND(AE8*Inputs!$B$24,0)),0) -> 0 | AG5: =IF(32>=Inputs!$B$22,IF(32=Inputs!$B$22,Inputs!$B$23,ROUND(AF8*Inputs!$B$24,0)),0) -> 0 | AH5: =IF(33>=Inputs!$B$22,IF(33=Inputs!$B$22,Inputs!$B$23,ROUND(AG8*Inputs!$B$24,0)),0) -> 0 | AI5: =IF(34>=Inputs!$B$22,IF(34=Inputs!$B$22,Inputs!$B$23,ROUND(AH8*Inputs!$B$24,0)),0) -> 0 | AJ5: =IF(35>=Inputs!$B$22,IF(35=Inputs!$B$22,Inputs!$B$23,ROUND(AI8*Inputs!$B$24,0)),0) -> 0 | AK5: =IF(36>=Inputs!$B$22,IF(36=Inputs!$B$22,Inputs!$B$23,ROUND(AJ8*Inputs!$B$24,0)),0) -> 0 | AL5: =IF(37>=Inputs!$B$22,IF(37=Inputs!$B$22,Inputs!$B$23,ROUND(AK8*Inputs!$B$24,0)),0) -> 0 | AM5: =IF(38>=Inputs!$B$22,IF(38=Inputs!$B$22,Inputs!$B$23,ROUND(AL8*Inputs!$B$24,0)),0) -> 0 | AN5: =IF(39>=Inputs!$B$22,IF(39=Inputs!$B$22,Inputs!$B$23,ROUND(AM8*Inputs!$B$24,0)),0) -> 0 | AO5: =IF(40>=Inputs!$B$22,IF(40=Inputs!$B$22,Inputs!$B$23,ROUND(AN8*Inputs!$B$24,0)),0) -> 0 | AP5: =IF(41>=Inputs!$B$22,IF(41=Inputs!$B$22,Inputs!$B$23,ROUND(AO8*Inputs!$B$24,0)),0) -> 0 | AQ5: =IF(42>=Inputs!$B$22,IF(42=Inputs!$B$22,Inputs!$B$23,ROUND(AP8*Inputs!$B$24,0)),0) -> 0 | AR5: =IF(43>=Inputs!$B$22,IF(43=Inputs!$B$22,Inputs!$B$23,ROUND(AQ8*Inputs!$B$24,0)),0) -> 0 | AS5: =IF(44>=Inputs!$B$22,IF(44=Inputs!$B$22,Inputs!$B$23,ROUND(AR8*Inputs!$B$24,0)),0) -> 0 | AT5: =IF(45>=Inputs!$B$22,IF(45=Inputs!$B$22,Inputs!$B$23,ROUND(AS8*Inputs!$B$24,0)),0) -> 0 | AU5: =IF(46>=Inputs!$B$22,IF(46=Inputs!$B$22,Inputs!$B$23,ROUND(AT8*Inputs!$B$24,0)),0) -> 0 | AV5: =IF(47>=Inputs!$B$22,IF(47=Inputs!$B$22,Inputs!$B$23,ROUND(AU8*Inputs!$B$24,0)),0) -> 0 | AW5: =IF(48>=Inputs!$B$22,IF(48=Inputs!$B$22,Inputs!$B$23,ROUND(AV8*Inputs!$B$24,0)),0) -> 0 | AX5: =IF(49>=Inputs!$B$22,IF(49=Inputs!$B$22,Inputs!$B$23,ROUND(AW8*Inputs!$B$24,0)),0) -> 0 | AY5: =IF(50>=Inputs!$B$22,IF(50=Inputs!$B$22,Inputs!$B$23,ROUND(AX8*Inputs!$B$24,0)),0) -> 0 | AZ5: =IF(51>=Inputs!$B$22,IF(51=Inputs!$B$22,Inputs!$B$23,ROUND(AY8*Inputs!$B$24,0)),0) -> 0 | BA5: =IF(52>=Inputs!$B$22,IF(52=Inputs!$B$22,Inputs!$B$23,ROUND(AZ8*Inputs!$B$24,0)),0) -> 0
A6: Churned Seats | B6: =0 -> 0 | C6: =IF(B8>0,ROUND(B8*Inputs!$B$28/12,0),0) -> 0 | D6: =IF(C8>0,ROUND(C8*Inputs!$B$28/12,0),0) -> 0 | E6: =IF(D8>0,ROUND(D8*Inputs!$B$28/12,0),0) -> 0 | F6: =IF(E8>0,ROUND(E8*Inputs!$B$28/12,0),0) -> 0 | G6: =IF(F8>0,ROUND(F8*Inputs!$B$28/12,0),0) -> 0 | H6: =IF(G8>0,ROUND(G8*Inputs!$B$28/12,0),0) -> 0 | I6: =IF(H8>0,ROUND(H8*Inputs!$B$28/12,0),0) -> 0 | J6: =IF(I8>0,ROUND(I8*Inputs!$B$28/12,0),0) -> 0 | ... BA6: =IF(AZ8>0,ROUND(AZ8*Inputs!$B$28/12,0),0) -> 0
A7: Net New Seats | B7: =B5-B6 -> 0 | C7: =C5-C6 -> 0 | D7: =D5-D6 -> 0 | E7: =E5-E6 -> 0 | F7: =F5-F6 -> 0 | G7: =G5-G6 -> 0 | H7: =H5-H6 -> 0 | I7: =I5-I6 -> 0 | ... BA7: =BA5-BA6 -> 0
A8: Total Active Seats | B8: =B7 -> 0 | C8: =B8+C7 -> 0 | D8: =C8+D7 -> 0 | E8: =D8+E7 -> 0 | F8: =E8+F7 -> 0 | G8: =F8+G7 -> 0 | H8: =G8+H7 -> 0 | I8: =H8+I7 -> 0 | J8: =I8+J7 -> 5 | ... BA8: =AZ8+BA7 -> 5
A9: Monthly Subscription Revenue (€) | B9: =B8*B4 -> 0 | C9: =C8*C4 -> 0 | D9: =D8*D4 -> 0 | E9: =E8*E4 -> 0 | F9: =F8*F4 -> 0 | G9: =G8*G4 -> 0 | H9: =H8*H4 -> 0 | I9: =I8*I4 -> 0 | ... BA9: =BA8*BA4 -> 6802.4448
A10: Subscription ARR (€) | B10: =B9*12 -> 0 | C10: =C9*12 -> 0 | D10: =D9*12 -> 0 | E10: =E9*12 -> 0 | F10: =F9*12 -> 0 | G10: =G9*12 -> 0 | H10: =H9*12 -> 0 | I10: =I9*12 -> 0 | ... BA10: =BA9*12 -> 81629.338
A12: Neue Enterprise Deals | B12: =IF(AND(1>=Inputs!$B$25,MOD(1-Inputs!$B$25,3)=0),Inputs!$B$27,0) -> 0 | C12: =IF(AND(2>=Inputs!$B$25,MOD(2-Inputs!$B$25,3)=0),Inputs!$B$27,0) -> 0 | D12: =IF(AND(3>=Inputs!$B$25,MOD(3-Inputs!$B$25,3)=0),Inputs!$B$27,0) -> 0 | E12: =IF(AND(4>=Inputs!$B$25,MOD(4-Inputs!$B$25,3)=0),Inputs!$B$27,0) -> 0 | F12: =IF(AND(5>=Inputs!$B$25,MOD(5-Inputs!$B$25,3)=0),Inputs!$B$27,0) -> 0 | G12: =IF(AND(6>=Inputs!$B$25,MOD(6-Inputs!$B$25,3)=0),Inputs!$B$27,0) -> 0 | H12: =IF(AND(7>=Inputs!$B$25,MOD(7-Inputs!$B$25,3)=0),Inputs!$B$27,0) -> 0 | I12: =IF(AND(8>=Inputs!$B$25,MOD(8-Inputs!$B$25,3)=0),Inputs!$B$27,0) -> 0 | J12: =IF(AND(9>=Inputs!$B$25,MOD(9-Inputs!$B$25,3)=0),Inputs!$B$27,0) -> 0 | K12: =IF(AND(10>=Inputs!$B$25,MOD(10-Inputs!$B$25,3)=0),Inputs!$B$27,0) -> 0 | L12: =IF(AND(11>=Inputs!$B$25,MOD(11-Inputs!$B$25,3)=0),Inputs!$B$27,0) -> 0 | M12: =IF(AND(12>=Inputs!$B$25,MOD(12-Inputs!$B$25,3)=0),Inputs!$B$27,0) -> 0 | N12: =IF(AND(13>=Inputs!$B$25,MOD(13-Inputs!$B$25,3)=0),Inputs!$B$27,0) -> 0 | O12: =IF(AND(14>=Inputs!$B$25,MOD(14-Inputs!$B$25,3)=0),Inputs!$B$27,0) -> 0 | P12: =IF(AND(15>=Inputs!$B$25,MOD(15-Inputs!$B$25,3)=0),Inputs!$B$27,0) -> 0 | Q12: =IF(AND(16>=Inputs!$B$25,MOD(16-Inputs!$B$25,3)=0),Inputs!$B$27,0) -> 0 | R12: =IF(AND(17>=Inputs!$B$25,MOD(17-Inputs!$B$25,3)=0),Inputs!$B$27,0) -> 0 | S12: =IF(AND(18>=Inputs!$B$25,MOD(18-Inputs!$B$25,3)=0),Inputs!$B$27,0) -> 0 | T12: =IF(AND(19>=Inputs!$B$25,MOD(19-Inputs!$B$25,3)=0),Inputs!$B$27,0) -> 0 | U12: =IF(AND(20>=Inputs!$B$25,MOD(20-Inputs!$B$25,3)=0),Inputs!$B$27,0) -> 0 | V12: =IF(AND(21>=Inputs!$B$25,MOD(21-Inputs!$B$25,3)=0),Inputs!$B$27,0) -> 0 | W12: =IF(AND(22>=Inputs!$B$25,MOD(22-Inputs!$B$25,3)=0),Inputs!$B$27,0) -> 0 | X12: =IF(AND(23>=Inputs!$B$25,MOD(23-Inputs!$B$25,3)=0),Inputs!$B$27,0) -> 0 | Y12: =IF(AND(24>=Inputs!$B$25,MOD(24-Inputs!$B$25,3)=0),Inputs!$B$27,0) -> 1 | Z12: =IF(AND(25>=Inputs!$B$25,MOD(25-Inputs!$B$25,3)=0),Inputs!$B$27,0) -> 0 | AA12: =IF(AND(26>=Inputs!$B$25,MOD(26-Inputs!$B$25,3)=0),Inputs!$B$27,0) -> 0 | AB12: =IF(AND(27>=Inputs!$B$25,MOD(27-Inputs!$B$25,3)=0),Inputs!$B$27,0) -> 1 | AC12: =IF(AND(28>=Inputs!$B$25,MOD(28-Inputs!$B$25,3)=0),Inputs!$B$27,0) -> 0 | AD12: =IF(AND(29>=Inputs!$B$25,MOD(29-Inputs!$B$25,3)=0),Inputs!$B$27,0) -> 0 | AE12: =IF(AND(30>=Inputs!$B$25,MOD(30-Inputs!$B$25,3)=0),Inputs!$B$27,0) -> 1 | AF12: =IF(AND(31>=Inputs!$B$25,MOD(31-Inputs!$B$25,3)=0),Inputs!$B$27,0) -> 0 | AG12: =IF(AND(32>=Inputs!$B$25,MOD(32-Inputs!$B$25,3)=0),Inputs!$B$27,0) -> 0 | AH12: =IF(AND(33>=Inputs!$B$25,MOD(33-Inputs!$B$25,3)=0),Inputs!$B$27,0) -> 1 | AI12: =IF(AND(34>=Inputs!$B$25,MOD(34-Inputs!$B$25,3)=0),Inputs!$B$27,0) -> 0 | AJ12: =IF(AND(35>=Inputs!$B$25,MOD(35-Inputs!$B$25,3)=0),Inputs!$B$27,0) -> 0 | AK12: =IF(AND(36>=Inputs!$B$25,MOD(36-Inputs!$B$25,3)=0),Inputs!$B$27,0) -> 1 | AL12: =IF(AND(37>=Inputs!$B$25,MOD(37-Inputs!$B$25,3)=0),Inputs!$B$27,0) -> 0 | AM12: =IF(AND(38>=Inputs!$B$25,MOD(38-Inputs!$B$25,3)=0),Inputs!$B$27,0) -> 0 | AN12: =IF(AND(39>=Inputs!$B$25,MOD(39-Inputs!$B$25,3)=0),Inputs!$B$27,0) -> 1 | AO12: =IF(AND(40>=Inputs!$B$25,MOD(40-Inputs!$B$25,3)=0),Inputs!$B$27,0) -> 0 | AP12: =IF(AND(41>=Inputs!$B$25,MOD(41-Inputs!$B$25,3)=0),Inputs!$B$27,0) -> 0 | AQ12: =IF(AND(42>=Inputs!$B$25,MOD(42-Inputs!$B$25,3)=0),Inputs!$B$27,0) -> 1 | AR12: =IF(AND(43>=Inputs!$B$25,MOD(43-Inputs!$B$25,3)=0),Inputs!$B$27,0) -> 0 | AS12: =IF(AND(44>=Inputs!$B$25,MOD(44-Inputs!$B$25,3)=0),Inputs!$B$27,0) -> 0 | AT12: =IF(AND(45>=Inputs!$B$25,MOD(45-Inputs!$B$25,3)=0),Inputs!$B$27,0) -> 1 | AU12: =IF(AND(46>=Inputs!$B$25,MOD(46-Inputs!$B$25,3)=0),Inputs!$B$27,0) -> 0 | AV12: =IF(AND(47>=Inputs!$B$25,MOD(47-Inputs!$B$25,3)=0),Inputs!$B$27,0) -> 0 | AW12: =IF(AND(48>=Inputs!$B$25,MOD(48-Inputs!$B$25,3)=0),Inputs!$B$27,0) -> 1 | AX12: =IF(AND(49>=Inputs!$B$25,MOD(49-Inputs!$B$25,3)=0),Inputs!$B$27,0) -> 0 | AY12: =IF(AND(50>=Inputs!$B$25,MOD(50-Inputs!$B$25,3)=0),Inputs!$B$27,0) -> 0 | AZ12: =IF(AND(51>=Inputs!$B$25,MOD(51-Inputs!$B$25,3)=0),Inputs!$B$27,0) -> 1 | BA12: =IF(AND(52>=Inputs!$B$25,MOD(52-Inputs!$B$25,3)=0),Inputs!$B$27,0) -> 0
A13: Churned Enterprise | B13: =0 -> 0 | C13: =IF(B14>0,IF(MOD(2,12)=0,ROUND(B14*Inputs!$B$28,0),0),0) -> 0 | D13: =IF(C14>0,IF(MOD(3,12)=0,ROUND(C14*Inputs!$B$28,0),0),0) -> 0 | E13: =IF(D14>0,IF(MOD(4,12)=0,ROUND(D14*Inputs!$B$28,0),0),0) -> 0 | F13: =IF(E14>0,IF(MOD(5,12)=0,ROUND(E14*Inputs!$B$28,0),0),0) -> 0 | G13: =IF(F14>0,IF(MOD(6,12)=0,ROUND(F14*Inputs!$B$28,0),0),0) -> 0 | H13: =IF(G14>0,IF(MOD(7,12)=0,ROUND(G14*Inputs!$B$28,0),0),0) -> 0 | I13: =IF(H14>0,IF(MOD(8,12)=0,ROUND(H14*Inputs!$B$28,0),0),0) -> 0 | J13: =IF(I14>0,IF(MOD(9,12)=0,ROUND(I14*Inputs!$B$28,0),0),0) -> 0 | K13: =IF(J14>0,IF(MOD(10,12)=0,ROUND(J14*Inputs!$B$28,0),0),0) -> 0 | L13: =IF(K14>0,IF(MOD(11,12)=0,ROUND(K14*Inputs!$B$28,0),0),0) -> 0 | M13: =IF(L14>0,IF(MOD(12,12)=0,ROUND(L14*Inputs!$B$28,0),0),0) -> 0 | N13: =IF(M14>0,IF(MOD(13,12)=0,ROUND(M14*Inputs!$B$28,0),0),0) -> 0 | O13: =IF(N14>0,IF(MOD(14,12)=0,ROUND(N14*Inputs!$B$28,0),0),0) -> 0 | P13: =IF(O14>0,IF(MOD(15,12)=0,ROUND(O14*Inputs!$B$28,0),0),0) -> 0 | Q13: =IF(P14>0,IF(MOD(16,12)=0,ROUND(P14*Inputs!$B$28,0),0),0) -> 0 | R13: =IF(Q14>0,IF(MOD(17,12)=0,ROUND(Q14*Inputs!$B$28,0),0),0) -> 0 | S13: =IF(R14>0,IF(MOD(18,12)=0,ROUND(R14*Inputs!$B$28,0),0),0) -> 0 | T13: =IF(S14>0,IF(MOD(19,12)=0,ROUND(S14*Inputs!$B$28,0),0),0) -> 0 | U13: =IF(T14>0,IF(MOD(20,12)=0,ROUND(T14*Inputs!$B$28,0),0),0) -> 0 | V13: =IF(U14>0,IF(MOD(21,12)=0,ROUND(U14*Inputs!$B$28,0),0),0) -> 0 | W13: =IF(V14>0,IF(MOD(22,12)=0,ROUND(V14*Inputs!$B$28,0),0),0) -> 0 | X13: =IF(W14>0,IF(MOD(23,12)=0,ROUND(W14*Inputs!$B$28,0),0),0) -> 0 | Y13: =IF(X14>0,IF(MOD(24,12)=0,ROUND(X14*Inputs!$B$28,0),0),0) -> 0 | Z13: =IF(Y14>0,IF(MOD(25,12)=0,ROUND(Y14*Inputs!$B$28,0),0),0) -> 0 | AA13: =IF(Z14>0,IF(MOD(26,12)=0,ROUND(Z14*Inputs!$B$28,0),0),0) -> 0 | AB13: =IF(AA14>0,IF(MOD(27,12)=0,ROUND(AA14*Inputs!$B$28,0),0),0) -> 0 | AC13: =IF(AB14>0,IF(MOD(28,12)=0,ROUND(AB14*Inputs!$B$28,0),0),0) -> 0 | AD13: =IF(AC14>0,IF(MOD(29,12)=0,ROUND(AC14*Inputs!$B$28,0),0),0) -> 0 | AE13: =IF(AD14>0,IF(MOD(30,12)=0,ROUND(AD14*Inputs!$B$28,0),0),0) -> 0 | AF13: =IF(AE14>0,IF(MOD(31,12)=0,ROUND(AE14*Inputs!$B$28,0),0),0) -> 0 | AG13: =IF(AF14>0,IF(MOD(32,12)=0,ROUND(AF14*Inputs!$B$28,0),0),0) -> 0 | AH13: =IF(AG14>0,IF(MOD(33,12)=0,ROUND(AG14*Inputs!$B$28,0),0),0) -> 0 | AI13: =IF(AH14>0,IF(MOD(34,12)=0,ROUND(AH14*Inputs!$B$28,0),0),0) -> 0 | AJ13: =IF(AI14>0,IF(MOD(35,12)=0,ROUND(AI14*Inputs!$B$28,0),0),0) -> 0 | AK13: =IF(AJ14>0,IF(MOD(36,12)=0,ROUND(AJ14*Inputs!$B$28,0),0),0) -> 0 | AL13: =IF(AK14>0,IF(MOD(37,12)=0,ROUND(AK14*Inputs!$B$28,0),0),0) -> 0 | AM13: =IF(AL14>0,IF(MOD(38,12)=0,ROUND(AL14*Inputs!$B$28,0),0),0) -> 0 | AN13: =IF(AM14>0,IF(MOD(39,12)=0,ROUND(AM14*Inputs!$B$28,0),0),0) -> 0 | AO13: =IF(AN14>0,IF(MOD(40,12)=0,ROUND(AN14*Inputs!$B$28,0),0),0) -> 0 | AP13: =IF(AO14>0,IF(MOD(41,12)=0,ROUND(AO14*Inputs!$B$28,0),0),0) -> 0 | AQ13: =IF(AP14>0,IF(MOD(42,12)=0,ROUND(AP14*Inputs!$B$28,0),0),0) -> 0 | AR13: =IF(AQ14>0,IF(MOD(43,12)=0,ROUND(AQ14*Inputs!$B$28,0),0),0) -> 0 | AS13: =IF(AR14>0,IF(MOD(44,12)=0,ROUND(AR14*Inputs!$B$28,0),0),0) -> 0 | AT13: =IF(AS14>0,IF(MOD(45,12)=0,ROUND(AS14*Inputs!$B$28,0),0),0) -> 0 | AU13: =IF(AT14>0,IF(MOD(46,12)=0,ROUND(AT14*Inputs!$B$28,0),0),0) -> 0 | AV13: =IF(AU14>0,IF(MOD(47,12)=0,ROUND(AU14*Inputs!$B$28,0),0),0) -> 0 | AW13: =IF(AV14>0,IF(MOD(48,12)=0,ROUND(AV14*Inputs!$B$28,0),0),0) -> 1 | AX13: =IF(AW14>0,IF(MOD(49,12)=0,ROUND(AW14*Inputs!$B$28,0),0),0) -> 0 | AY13: =IF(AX14>0,IF(MOD(50,12)=0,ROUND(AX14*Inputs!$B$28,0),0),0) -> 0 | AZ13: =IF(AY14>0,IF(MOD(51,12)=0,ROUND(AY14*Inputs!$B$28,0),0),0) -> 0 | BA13: =IF(AZ14>0,IF(MOD(52,12)=0,ROUND(AZ14*Inputs!$B$28,0),0),0) -> 0
A14: Active Enterprise Contracts | B14: =B12-B13 -> 0 | C14: =B14+C12-C13 -> 0 | D14: =C14+D12-D13 -> 0 | E14: =D14+E12-E13 -> 0 | F14: =E14+F12-F13 -> 0 | G14: =F14+G12-G13 -> 0 | H14: =G14+H12-H13 -> 0 | I14: =H14+I12-I13 -> 0 | J14: =I14+J12-J13 -> 0 | ... BA14: =AZ14+BA12-BA13 -> 9
A15: Avg Enterprise ACV (€) | B15: =Inputs!$B$26*(1+Inputs!$B$21)^INT((1-1)/12) -> 150000 | C15: =Inputs!$B$26*(1+Inputs!$B$21)^INT((2-1)/12) -> 150000 | D15: =Inputs!$B$26*(1+Inputs!$B$21)^INT((3-1)/12) -> 150000 | E15: =Inputs!$B$26*(1+Inputs!$B$21)^INT((4-1)/12) -> 150000 | F15: =Inputs!$B$26*(1+Inputs!$B$21)^INT((5-1)/12) -> 150000 | G15: =Inputs!$B$26*(1+Inputs!$B$21)^INT((6-1)/12) -> 150000 | H15: =Inputs!$B$26*(1+Inputs!$B$21)^INT((7-1)/12) -> 150000 | I15: =Inputs!$B$26*(1+Inputs!$B$21)^INT((8-1)/12) -> 150000 | J15: =Inputs!$B$26*(1+Inputs!$B$21)^INT((9-1)/12) -> 150000 | K15: =Inputs!$B$26*(1+Inputs!$B$21)^INT((10-1)/12) -> 150000 | L15: =Inputs!$B$26*(1+Inputs!$B$21)^INT((11-1)/12) -> 150000 | M15: =Inputs!$B$26*(1+Inputs!$B$21)^INT((12-1)/12) -> 150000 | N15: =Inputs!$B$26*(1+Inputs!$B$21)^INT((13-1)/12) -> 162000 | O15: =Inputs!$B$26*(1+Inputs!$B$21)^INT((14-1)/12) -> 162000 | P15: =Inputs!$B$26*(1+Inputs!$B$21)^INT((15-1)/12) -> 162000 | Q15: =Inputs!$B$26*(1+Inputs!$B$21)^INT((16-1)/12) -> 162000 | R15: =Inputs!$B$26*(1+Inputs!$B$21)^INT((17-1)/12) -> 162000 | S15: =Inputs!$B$26*(1+Inputs!$B$21)^INT((18-1)/12) -> 162000 | T15: =Inputs!$B$26*(1+Inputs!$B$21)^INT((19-1)/12) -> 162000 | U15: =Inputs!$B$26*(1+Inputs!$B$21)^INT((20-1)/12) -> 162000 | V15: =Inputs!$B$26*(1+Inputs!$B$21)^INT((21-1)/12) -> 162000 | W15: =Inputs!$B$26*(1+Inputs!$B$21)^INT((22-1)/12) -> 162000 | X15: =Inputs!$B$26*(1+Inputs!$B$21)^INT((23-1)/12) -> 162000 | Y15: =Inputs!$B$26*(1+Inputs!$B$21)^INT((24-1)/12) -> 162000 | Z15: =Inputs!$B$26*(1+Inputs!$B$21)^INT((25-1)/12) -> 174960 | AA15: =Inputs!$B$26*(1+Inputs!$B$21)^INT((26-1)/12) -> 174960 | AB15: =Inputs!$B$26*(1+Inputs!$B$21)^INT((27-1)/12) -> 174960 | AC15: =Inputs!$B$26*(1+Inputs!$B$21)^INT((28-1)/12) -> 174960 | AD15: =Inputs!$B$26*(1+Inputs!$B$21)^INT((29-1)/12) -> 174960 | AE15: =Inputs!$B$26*(1+Inputs!$B$21)^INT((30-1)/12) -> 174960 | AF15: =Inputs!$B$26*(1+Inputs!$B$21)^INT((31-1)/12) -> 174960 | AG15: =Inputs!$B$26*(1+Inputs!$B$21)^INT((32-1)/12) -> 174960 | AH15: =Inputs!$B$26*(1+Inputs!$B$21)^INT((33-1)/12) -> 174960 | AI15: =Inputs!$B$26*(1+Inputs!$B$21)^INT((34-1)/12) -> 174960 | AJ15: =Inputs!$B$26*(1+Inputs!$B$21)^INT((35-1)/12) -> 174960 | AK15: =Inputs!$B$26*(1+Inputs!$B$21)^INT((36-1)/12) -> 174960 | AL15: =Inputs!$B$26*(1+Inputs!$B$21)^INT((37-1)/12) -> 188956.8 | AM15: =Inputs!$B$26*(1+Inputs!$B$21)^INT((38-1)/12) -> 188956.8 | AN15: =Inputs!$B$26*(1+Inputs!$B$21)^INT((39-1)/12) -> 188956.8 | AO15: =Inputs!$B$26*(1+Inputs!$B$21)^INT((40-1)/12) -> 188956.8 | AP15: =Inputs!$B$26*(1+Inputs!$B$21)^INT((41-1)/12) -> 188956.8 | AQ15: =Inputs!$B$26*(1+Inputs!$B$21)^INT((42-1)/12) -> 188956.8 | AR15: =Inputs!$B$26*(1+Inputs!$B$21)^INT((43-1)/12) -> 188956.8 | AS15: =Inputs!$B$26*(1+Inputs!$B$21)^INT((44-1)/12) -> 188956.8 | AT15: =Inputs!$B$26*(1+Inputs!$B$21)^INT((45-1)/12) -> 188956.8 | AU15: =Inputs!$B$26*(1+Inputs!$B$21)^INT((46-1)/12) -> 188956.8 | AV15: =Inputs!$B$26*(1+Inputs!$B$21)^INT((47-1)/12) -> 188956.8 | AW15: =Inputs!$B$26*(1+Inputs!$B$21)^INT((48-1)/12) -> 188956.8 | AX15: =Inputs!$B$26*(1+Inputs!$B$21)^INT((49-1)/12) -> 204073.34 | AY15: =Inputs!$B$26*(1+Inputs!$B$21)^INT((50-1)/12) -> 204073.34 | AZ15: =Inputs!$B$26*(1+Inputs!$B$21)^INT((51-1)/12) -> 204073.34 | BA15: =Inputs!$B$26*(1+Inputs!$B$21)^INT((52-1)/12) -> 204073.34
A16: Enterprise Monthly Revenue (€) | B16: =B14*B15/12 -> 0 | C16: =C14*C15/12 -> 0 | D16: =D14*D15/12 -> 0 | E16: =E14*E15/12 -> 0 | F16: =F14*F15/12 -> 0 | G16: =G14*G15/12 -> 0 | H16: =H14*H15/12 -> 0 | I16: =I14*I15/12 -> 0 | ... BA16: =BA14*BA15/12 -> 153055.01
A18: TOTAL MRR (€) | B18: =B9+B16 -> 0 | C18: =C9+C16 -> 0 | D18: =D9+D16 -> 0 | E18: =E9+E16 -> 0 | F18: =F9+F16 -> 0 | G18: =G9+G16 -> 0 | H18: =H9+H16 -> 0 | I18: =I9+I16 -> 0 | ... BA18: =BA9+BA16 -> 159857.45
A19: TOTAL ARR (€) | B19: =B18*12 -> 0 | C19: =C18*12 -> 0 | D19: =D18*12 -> 0 | E19: =E18*12 -> 0 | F19: =F18*12 -> 0 | G19: =G18*12 -> 0 | H19: =H18*12 -> 0 | I19: =I18*12 -> 0 | ... BA19: =BA18*12 -> 1918289.4
A20: Total Monthly Revenue (€) | B20: =B18 -> 0 | C20: =C18 -> 0 | D20: =D18 -> 0 | E20: =E18 -> 0 | F20: =F18 -> 0 | G20: =G18 -> 0 | H20: =H18 -> 0 | I20: =I18 -> 0 | ... BA20: =BA18 -> 159857.45
A21: ARR Growth % (MoM) | B21: ="" | C21: =IFERROR(C19/B19-1,"") | D21: =IFERROR(D19/C19-1,"") | E21: =IFERROR(E19/D19-1,"") | F21: =IFERROR(F19/E19-1,"") | G21: =IFERROR(G19/F19-1,"") | H21: =IFERROR(H19/G19-1,"") | I21: =IFERROR(I19/H19-1,"") | J21: =IFERROR(J19/I19-1,"") | ... BA21: =IFERROR(BA19/AZ19-1,"") -> 0
A22: Net Revenue Retention % | B22: =Inputs!$B$29 -> 1.18 | C22: =Inputs!$B$29 -> 1.18 | D22: =Inputs!$B$29 -> 1.18 | E22: =Inputs!$B$29 -> 1.18 | F22: =Inputs!$B$29 -> 1.18 | G22: =Inputs!$B$29 -> 1.18 | H22: =Inputs!$B$29 -> 1.18 | I22: =Inputs!$B$29 -> 1.18 | ... BA22: =Inputs!$B$29 -> 1.18
A23: Gross New ARR (€) | B23: =B5*B4*12+B12*B15 -> 0 | C23: =C5*C4*12+C12*C15 -> 0 | D23: =D5*D4*12+D12*D15 -> 0 | E23: =E5*E4*12+E12*E15 -> 0 | F23: =F5*F4*12+F12*F15 -> 0 | G23: =G5*G4*12+G12*G15 -> 0 | H23: =H5*H4*12+H12*H15 -> 0 | I23: =I5*I4*12+I12*I15 -> 0 | ... BA23: =BA5*BA4*12+BA12*BA15 -> 0

Sheet Costs
A1: KOSTENDETAILS
B2: 46113 | C2: 46143 | D2: 46174 | E2: 46204 | F2: 46235 | G2: 46266 | H2: 46296 | I2: 46327 | J2: 46357 | K2: 46388 | L2: 46419 | M2: 46447 | N2: 46478 | O2: 46508 | P2: 46539 | Q2: 46569 | R2: 46600 | S2: 46631 | T2: 46661 | U2: 46692 | V2: 46722 | W2: 46753 | X2: 46784 | Y2: 46813 | Z2: 46844 | AA2: 46874 | AB2: 46905 | AC2: 46935 | AD2: 46966 | AE2: 46997 | AF2: 47027 | AG2: 47058 | AH2: 47088 | AI2: 47119 | AJ2: 47150 | AK2: 47178 | AL2: 47209 | AM2: 47239 | AN2: 47270 | AO2: 47300 | AP2: 47331 | AQ2: 47362 | AR2: 47392 | AS2: 47423 | AT2: 47453 | AU2: 47484 | AV2: 47515 | AW2: 47543 | AX2: 47574 | AY2: 47604 | AZ2: 47635 | BA2: 47665
A3: Kostenposition | B3: M1 | C3: M2 | D3: M3 | E3: M4 | F3: M5 | G3: M6 | H3: M7 | I3: M8 | J3: M9 | K3: M10 | L3: M11 | M3: M12 | N3: M13 | O3: M14 | P3: M15 | Q3: M16 | R3: M17 | S3: M18 | T3: M19 | U3: M20 | V3: M21 | W3: M22 | X3: M23 | Y3: M24 | Z3: M25 | AA3: M26 | AB3: M27 | AC3: M28 | AD3: M29 | AE3: M30 | AF3: M31 | AG3: M32 | AH3: M33 | AI3: M34 | AJ3: M35 | AK3: M36 | AL3: M37 | AM3: M38 | AN3: M39 | AO3: M40 | AP3: M41 | AQ3: M42 | AR3: M43 | AS3: M44 | AT3: M45 | AU3: M46 | AV3: M47 | AW3: M48 | AX3: M49 | AY3: M50 | AZ3: M51 | BA3: M52
A4: HEADCOUNT PLAN
A5: Executives (CEO, CTO, CCO) | B5: 3 | C5: 3 | D5: 3 | E5: 3 | F5: 3 | G5: 3 | H5: 3 | I5: 3 | J5: 3 | K5: 3 | L5: 3 | M5: 3 | N5: 3 | O5: 3 | P5: 3 | Q5: 3 | R5: 3 | S5: 3 | T5: 3 | U5: 3 | V5: 3 | W5: 3 | X5: 3 | Y5: 3 | Z5: 3 | AA5: 3 | AB5: 3 | AC5: 3 | AD5: 3 | AE5: 3 | AF5: 3 | AG5: 3 | AH5: 3 | AI5: 3 | AJ5: 3 | AK5: 3 | AL5: 3 | AM5: 3 | AN5: 3 | AO5: 3 | AP5: 3 | AQ5: 3 | AR5: 3 | AS5: 3 | AT5: 3 | AU5: 3 | AV5: 3 | AW5: 3 | AX5: 3 | AY5: 3 | AZ5: 3 | BA5: 3
A6: 1. Senior Engineer | B6: =IF(1>=Inputs!$B$47,1,0) -> 0 | C6: =IF(2>=Inputs!$B$47,1,0) -> 0 | D6: =IF(3>=Inputs!$B$47,1,0) -> 0 | E6: =IF(4>=Inputs!$B$47,1,0) -> 0 | F6: =IF(5>=Inputs!$B$47,1,0) -> 0 | G6: =IF(6>=Inputs!$B$47,1,0) -> 0 | H6: =IF(7>=Inputs!$B$47,1,0) -> 1 | I6: =IF(8>=Inputs!$B$47,1,0) -> 1 | J6: =IF(9>=Inputs!$B$47,1,0) -> 1 | K6: =IF(10>=Inputs!$B$47,1,0) -> 1 | L6: =IF(11>=Inputs!$B$47,1,0) -> 1 | M6: =IF(12>=Inputs!$B$47,1,0) -> 1 | N6: =IF(13>=Inputs!$B$47,1,0) -> 1 | O6: =IF(14>=Inputs!$B$47,1,0) -> 1 | P6: =IF(15>=Inputs!$B$47,1,0) -> 1 | Q6: =IF(16>=Inputs!$B$47,1,0) -> 1 | R6: =IF(17>=Inputs!$B$47,1,0) -> 1 | S6: =IF(18>=Inputs!$B$47,1,0) -> 1 | T6: =IF(19>=Inputs!$B$47,1,0) -> 1 | U6: =IF(20>=Inputs!$B$47,1,0) -> 1 | V6: =IF(21>=Inputs!$B$47,1,0) -> 1 | W6: =IF(22>=Inputs!$B$47,1,0) -> 1 | X6: =IF(23>=Inputs!$B$47,1,0) -> 1 | Y6: =IF(24>=Inputs!$B$47,1,0) -> 1 | Z6: =IF(25>=Inputs!$B$47,1,0) -> 1 | AA6: =IF(26>=Inputs!$B$47,1,0) -> 1 | AB6: =IF(27>=Inputs!$B$47,1,0) -> 1 | AC6: =IF(28>=Inputs!$B$47,1,0) -> 1 | AD6: =IF(29>=Inputs!$B$47,1,0) -> 1 | AE6: =IF(30>=Inputs!$B$47,1,0) -> 1 | AF6: =IF(31>=Inputs!$B$47,1,0) -> 1 | AG6: =IF(32>=Inputs!$B$47,1,0) -> 1 | AH6: =IF(33>=Inputs!$B$47,1,0) -> 1 | AI6: =IF(34>=Inputs!$B$47,1,0) -> 1 | AJ6: =IF(35>=Inputs!$B$47,1,0) -> 1 | AK6: =IF(36>=Inputs!$B$47,1,0) -> 1 | AL6: =IF(37>=Inputs!$B$47,1,0) -> 1 | AM6: =IF(38>=Inputs!$B$47,1,0) -> 1 | AN6: =IF(39>=Inputs!$B$47,1,0) -> 1 | AO6: =IF(40>=Inputs!$B$47,1,0) -> 1 | AP6: =IF(41>=Inputs!$B$47,1,0) -> 1 | AQ6: =IF(42>=Inputs!$B$47,1,0) -> 1 | AR6: =IF(43>=Inputs!$B$47,1,0) -> 1 | AS6: =IF(44>=Inputs!$B$47,1,0) -> 1 | AT6: =IF(45>=Inputs!$B$47,1,0) -> 1 | AU6: =IF(46>=Inputs!$B$47,1,0) -> 1 | AV6: =IF(47>=Inputs!$B$47,1,0) -> 1 | AW6: =IF(48>=Inputs!$B$47,1,0) -> 1 | AX6: =IF(49>=Inputs!$B$47,1,0) -> 1 | AY6: =IF(50>=Inputs!$B$47,1,0) -> 1 | AZ6: =IF(51>=Inputs!$B$47,1,0) -> 1 | BA6: =IF(52>=Inputs!$B$47,1,0) -> 1
A7: 2. Senior Engineer | B7: =IF(1>=Inputs!$B$48,1,0) -> 0 | C7: =IF(2>=Inputs!$B$48,1,0) -> 0 | D7: =IF(3>=Inputs!$B$48,1,0) -> 0 | E7: =IF(4>=Inputs!$B$48,1,0) -> 0 | F7: =IF(5>=Inputs!$B$48,1,0) -> 0 | G7: =IF(6>=Inputs!$B$48,1,0) -> 0 | H7: =IF(7>=Inputs!$B$48,1,0) -> 0 | I7: =IF(8>=Inputs!$B$48,1,0) -> 0 | J7: =IF(9>=Inputs!$B$48,1,0) -> 0 | K7: =IF(10>=Inputs!$B$48,1,0) -> 1 | L7: =IF(11>=Inputs!$B$48,1,0) -> 1 | M7: =IF(12>=Inputs!$B$48,1,0) -> 1 | N7: =IF(13>=Inputs!$B$48,1,0) -> 1 | O7: =IF(14>=Inputs!$B$48,1,0) -> 1 | P7: =IF(15>=Inputs!$B$48,1,0) -> 1 | Q7: =IF(16>=Inputs!$B$48,1,0) -> 1 | R7: =IF(17>=Inputs!$B$48,1,0) -> 1 | S7: =IF(18>=Inputs!$B$48,1,0) -> 1 | T7: =IF(19>=Inputs!$B$48,1,0) -> 1 | U7: =IF(20>=Inputs!$B$48,1,0) -> 1 | V7: =IF(21>=Inputs!$B$48,1,0) -> 1 | W7: =IF(22>=Inputs!$B$48,1,0) -> 1 | X7: =IF(23>=Inputs!$B$48,1,0) -> 1 | Y7: =IF(24>=Inputs!$B$48,1,0) -> 1 | Z7: =IF(25>=Inputs!$B$48,1,0) -> 1 | AA7: =IF(26>=Inputs!$B$48,1,0) -> 1 | AB7: =IF(27>=Inputs!$B$48,1,0) -> 1 | AC7: =IF(28>=Inputs!$B$48,1,0) -> 1 | AD7: =IF(29>=Inputs!$B$48,1,0) -> 1 | AE7: =IF(30>=Inputs!$B$48,1,0) -> 1 | AF7: =IF(31>=Inputs!$B$48,1,0) -> 1 | AG7: =IF(32>=Inputs!$B$48,1,0) -> 1 | AH7: =IF(33>=Inputs!$B$48,1,0) -> 1 | AI7: =IF(34>=Inputs!$B$48,1,0) -> 1 | AJ7: =IF(35>=Inputs!$B$48,1,0) -> 1 | AK7: =IF(36>=Inputs!$B$48,1,0) -> 1 | AL7: =IF(37>=Inputs!$B$48,1,0) -> 1 | AM7: =IF(38>=Inputs!$B$48,1,0) -> 1 | AN7: =IF(39>=Inputs!$B$48,1,0) -> 1 | AO7: =IF(40>=Inputs!$B$48,1,0) -> 1 | AP7: =IF(41>=Inputs!$B$48,1,0) -> 1 | AQ7: =IF(42>=Inputs!$B$48,1,0) -> 1 | AR7: =IF(43>=Inputs!$B$48,1,0) -> 1 | AS7: =IF(44>=Inputs!$B$48,1,0) -> 1 | AT7: =IF(45>=Inputs!$B$48,1,0) -> 1 | AU7: =IF(46>=Inputs!$B$48,1,0) -> 1 | AV7: =IF(47>=Inputs!$B$48,1,0) -> 1 | AW7: =IF(48>=Inputs!$B$48,1,0) -> 1 | AX7: =IF(49>=Inputs!$B$48,1,0) -> 1 | AY7: =IF(50>=Inputs!$B$48,1,0) -> 1 | AZ7: =IF(51>=Inputs!$B$48,1,0) -> 1 | BA7: =IF(52>=Inputs!$B$48,1,0) -> 1
A8: 1. Junior Engineer | B8: =IF(1>=Inputs!$B$49,1,0) -> 0 | C8: =IF(2>=Inputs!$B$49,1,0) -> 0 | D8: =IF(3>=Inputs!$B$49,1,0) -> 0 | E8: =IF(4>=Inputs!$B$49,1,0) -> 0 | F8: =IF(5>=Inputs!$B$49,1,0) -> 0 | G8: =IF(6>=Inputs!$B$49,1,0) -> 0 | H8: =IF(7>=Inputs!$B$49,1,0) -> 0 | I8: =IF(8>=Inputs!$B$49,1,0) -> 0 | J8: =IF(9>=Inputs!$B$49,1,0) -> 1 | K8: =IF(10>=Inputs!$B$49,1,0) -> 1 | L8: =IF(11>=Inputs!$B$49,1,0) -> 1 | M8: =IF(12>=Inputs!$B$49,1,0) -> 1 | N8: =IF(13>=Inputs!$B$49,1,0) -> 1 | O8: =IF(14>=Inputs!$B$49,1,0) -> 1 | P8: =IF(15>=Inputs!$B$49,1,0) -> 1 | Q8: =IF(16>=Inputs!$B$49,1,0) -> 1 | R8: =IF(17>=Inputs!$B$49,1,0) -> 1 | S8: =IF(18>=Inputs!$B$49,1,0) -> 1 | T8: =IF(19>=Inputs!$B$49,1,0) -> 1 | U8: =IF(20>=Inputs!$B$49,1,0) -> 1 | V8: =IF(21>=Inputs!$B$49,1,0) -> 1 | W8: =IF(22>=Inputs!$B$49,1,0) -> 1 | X8: =IF(23>=Inputs!$B$49,1,0) -> 1 | Y8: =IF(24>=Inputs!$B$49,1,0) -> 1 | Z8: =IF(25>=Inputs!$B$49,1,0) -> 1 | AA8: =IF(26>=Inputs!$B$49,1,0) -> 1 | AB8: =IF(27>=Inputs!$B$49,1,0) -> 1 | AC8: =IF(28>=Inputs!$B$49,1,0) -> 1 | AD8: =IF(29>=Inputs!$B$49,1,0) -> 1 | AE8: =IF(30>=Inputs!$B$49,1,0) -> 1 | AF8: =IF(31>=Inputs!$B$49,1,0) -> 1 | AG8: =IF(32>=Inputs!$B$49,1,0) -> 1 | AH8: =IF(33>=Inputs!$B$49,1,0) -> 1 | AI8: =IF(34>=Inputs!$B$49,1,0) -> 1 | AJ8: =IF(35>=Inputs!$B$49,1,0) -> 1 | AK8: =IF(36>=Inputs!$B$49,1,0) -> 1 | AL8: =IF(37>=Inputs!$B$49,1,0) -> 1 | AM8: =IF(38>=Inputs!$B$49,1,0) -> 1 | AN8: =IF(39>=Inputs!$B$49,1,0) -> 1 | AO8: =IF(40>=Inputs!$B$49,1,0) -> 1 | AP8: =IF(41>=Inputs!$B$49,1,0) -> 1 | AQ8: =IF(42>=Inputs!$B$49,1,0) -> 1 | AR8: =IF(43>=Inputs!$B$49,1,0) -> 1 | AS8: =IF(44>=Inputs!$B$49,1,0) -> 1 | AT8: =IF(45>=Inputs!$B$49,1,0) -> 1 | AU8: =IF(46>=Inputs!$B$49,1,0) -> 1 | AV8: =IF(47>=Inputs!$B$49,1,0) -> 1 | AW8: =IF(48>=Inputs!$B$49,1,0) -> 1 | AX8: =IF(49>=Inputs!$B$49,1,0) -> 1 | AY8: =IF(50>=Inputs!$B$49,1,0) -> 1 | AZ8: =IF(51>=Inputs!$B$49,1,0) -> 1 | BA8: =IF(52>=Inputs!$B$49,1,0) -> 1
A9: 1. ML/AI Engineer | B9: =IF(1>=Inputs!$B$50,1,0) -> 0 | C9: =IF(2>=Inputs!$B$50,1,0) -> 0 | D9: =IF(3>=Inputs!$B$50,1,0) -> 0 | E9: =IF(4>=Inputs!$B$50,1,0) -> 0 | F9: =IF(5>=Inputs!$B$50,1,0) -> 0 | G9: =IF(6>=Inputs!$B$50,1,0) -> 0 | H9: =IF(7>=Inputs!$B$50,1,0) -> 0 | I9: =IF(8>=Inputs!$B$50,1,0) -> 1 | J9: =IF(9>=Inputs!$B$50,1,0) -> 1 | K9: =IF(10>=Inputs!$B$50,1,0) -> 1 | L9: =IF(11>=Inputs!$B$50,1,0) -> 1 | M9: =IF(12>=Inputs!$B$50,1,0) -> 1 | N9: =IF(13>=Inputs!$B$50,1,0) -> 1 | O9: =IF(14>=Inputs!$B$50,1,0) -> 1 | P9: =IF(15>=Inputs!$B$50,1,0) -> 1 | Q9: =IF(16>=Inputs!$B$50,1,0) -> 1 | R9: =IF(17>=Inputs!$B$50,1,0) -> 1 | S9: =IF(18>=Inputs!$B$50,1,0) -> 1 | T9: =IF(19>=Inputs!$B$50,1,0) -> 1 | U9: =IF(20>=Inputs!$B$50,1,0) -> 1 | V9: =IF(21>=Inputs!$B$50,1,0) -> 1 | W9: =IF(22>=Inputs!$B$50,1,0) -> 1 | X9: =IF(23>=Inputs!$B$50,1,0) -> 1 | Y9: =IF(24>=Inputs!$B$50,1,0) -> 1 | Z9: =IF(25>=Inputs!$B$50,1,0) -> 1 | AA9: =IF(26>=Inputs!$B$50,1,0) -> 1 | AB9: =IF(27>=Inputs!$B$50,1,0) -> 1 | AC9: =IF(28>=Inputs!$B$50,1,0) -> 1 | AD9: =IF(29>=Inputs!$B$50,1,0) -> 1 | AE9: =IF(30>=Inputs!$B$50,1,0) -> 1 | AF9: =IF(31>=Inputs!$B$50,1,0) -> 1 | AG9: =IF(32>=Inputs!$B$50,1,0) -> 1 | AH9: =IF(33>=Inputs!$B$50,1,0) -> 1 | AI9: =IF(34>=Inputs!$B$50,1,0) -> 1 | AJ9: =IF(35>=Inputs!$B$50,1,0) -> 1 | AK9: =IF(36>=Inputs!$B$50,1,0) -> 1 | AL9: =IF(37>=Inputs!$B$50,1,0) -> 1 | AM9: =IF(38>=Inputs!$B$50,1,0) -> 1 | AN9: =IF(39>=Inputs!$B$50,1,0) -> 1 | AO9: =IF(40>=Inputs!$B$50,1,0) -> 1 | AP9: =IF(41>=Inputs!$B$50,1,0) -> 1 | AQ9: =IF(42>=Inputs!$B$50,1,0) -> 1 | AR9: =IF(43>=Inputs!$B$50,1,0) -> 1 | AS9: =IF(44>=Inputs!$B$50,1,0) -> 1 | AT9: =IF(45>=Inputs!$B$50,1,0) -> 1 | AU9: =IF(46>=Inputs!$B$50,1,0) -> 1 | AV9: =IF(47>=Inputs!$B$50,1,0) -> 1 | AW9: =IF(48>=Inputs!$B$50,1,0) -> 1 | AX9: =IF(49>=Inputs!$B$50,1,0) -> 1 | AY9: =IF(50>=Inputs!$B$50,1,0) -> 1 | AZ9: =IF(51>=Inputs!$B$50,1,0) -> 1 | BA9: =IF(52>=Inputs!$B$50,1,0) -> 1
A10: 2. ML/AI Engineer | B10: =IF(1>=Inputs!$B$51,1,0) -> 0 | C10: =IF(2>=Inputs!$B$51,1,0) -> 0 | D10: =IF(3>=Inputs!$B$51,1,0) -> 0 | E10: =IF(4>=Inputs!$B$51,1,0) -> 0 | F10: =IF(5>=Inputs!$B$51,1,0) -> 0 | G10: =IF(6>=Inputs!$B$51,1,0) -> 0 | H10: =IF(7>=Inputs!$B$51,1,0) -> 0 | I10: =IF(8>=Inputs!$B$51,1,0) -> 0 | J10: =IF(9>=Inputs!$B$51,1,0) -> 0 | K10: =IF(10>=Inputs!$B$51,1,0) -> 0 | L10: =IF(11>=Inputs!$B$51,1,0) -> 0 | M10: =IF(12>=Inputs!$B$51,1,0) -> 0 | N10: =IF(13>=Inputs!$B$51,1,0) -> 0 | O10: =IF(14>=Inputs!$B$51,1,0) -> 1 | P10: =IF(15>=Inputs!$B$51,1,0) -> 1 | Q10: =IF(16>=Inputs!$B$51,1,0) -> 1 | R10: =IF(17>=Inputs!$B$51,1,0) -> 1 | S10: =IF(18>=Inputs!$B$51,1,0) -> 1 | T10: =IF(19>=Inputs!$B$51,1,0) -> 1 | U10: =IF(20>=Inputs!$B$51,1,0) -> 1 | V10: =IF(21>=Inputs!$B$51,1,0) -> 1 | W10: =IF(22>=Inputs!$B$51,1,0) -> 1 | X10: =IF(23>=Inputs!$B$51,1,0) -> 1 | Y10: =IF(24>=Inputs!$B$51,1,0) -> 1 | Z10: =IF(25>=Inputs!$B$51,1,0) -> 1 | AA10: =IF(26>=Inputs!$B$51,1,0) -> 1 | AB10: =IF(27>=Inputs!$B$51,1,0) -> 1 | AC10: =IF(28>=Inputs!$B$51,1,0) -> 1 | AD10: =IF(29>=Inputs!$B$51,1,0) -> 1 | AE10: =IF(30>=Inputs!$B$51,1,0) -> 1 | AF10: =IF(31>=Inputs!$B$51,1,0) -> 1 | AG10: =IF(32>=Inputs!$B$51,1,0) -> 1 | AH10: =IF(33>=Inputs!$B$51,1,0) -> 1 | AI10: =IF(34>=Inputs!$B$51,1,0) -> 1 | AJ10: =IF(35>=Inputs!$B$51,1,0) -> 1 | AK10: =IF(36>=Inputs!$B$51,1,0) -> 1 | AL10: =IF(37>=Inputs!$B$51,1,0) -> 1 | AM10: =IF(38>=Inputs!$B$51,1,0) -> 1 | AN10: =IF(39>=Inputs!$B$51,1,0) -> 1 | AO10: =IF(40>=Inputs!$B$51,1,0) -> 1 | AP10: =IF(41>=Inputs!$B$51,1,0) -> 1 | AQ10: =IF(42>=Inputs!$B$51,1,0) -> 1 | AR10: =IF(43>=Inputs!$B$51,1,0) -> 1 | AS10: =IF(44>=Inputs!$B$51,1,0) -> 1 | AT10: =IF(45>=Inputs!$B$51,1,0) -> 1 | AU10: =IF(46>=Inputs!$B$51,1,0) -> 1 | AV10: =IF(47>=Inputs!$B$51,1,0) -> 1 | AW10: =IF(48>=Inputs!$B$51,1,0) -> 1 | AX10: =IF(49>=Inputs!$B$51,1,0) -> 1 | AY10: =IF(50>=Inputs!$B$51,1,0) -> 1 | AZ10: =IF(51>=Inputs!$B$51,1,0) -> 1 | BA10: =IF(52>=Inputs!$B$51,1,0) -> 1
A11: 1. Sales Rep | B11: =IF(1>=Inputs!$B$52,1,0) -> 0 | C11: =IF(2>=Inputs!$B$52,1,0) -> 0 | D11: =IF(3>=Inputs!$B$52,1,0) -> 0 | E11: =IF(4>=Inputs!$B$52,1,0) -> 0 | F11: =IF(5>=Inputs!$B$52,1,0) -> 0 | G11: =IF(6>=Inputs!$B$52,1,0) -> 0 | H11: =IF(7>=Inputs!$B$52,1,0) -> 0 | I11: =IF(8>=Inputs!$B$52,1,0) -> 0 | J11: =IF(9>=Inputs!$B$52,1,0) -> 0 | K11: =IF(10>=Inputs!$B$52,1,0) -> 1 | L11: =IF(11>=Inputs!$B$52,1,0) -> 1 | M11: =IF(12>=Inputs!$B$52,1,0) -> 1 | N11: =IF(13>=Inputs!$B$52,1,0) -> 1 | O11: =IF(14>=Inputs!$B$52,1,0) -> 1 | P11: =IF(15>=Inputs!$B$52,1,0) -> 1 | Q11: =IF(16>=Inputs!$B$52,1,0) -> 1 | R11: =IF(17>=Inputs!$B$52,1,0) -> 1 | S11: =IF(18>=Inputs!$B$52,1,0) -> 1 | T11: =IF(19>=Inputs!$B$52,1,0) -> 1 | U11: =IF(20>=Inputs!$B$52,1,0) -> 1 | V11: =IF(21>=Inputs!$B$52,1,0) -> 1 | W11: =IF(22>=Inputs!$B$52,1,0) -> 1 | X11: =IF(23>=Inputs!$B$52,1,0) -> 1 | Y11: =IF(24>=Inputs!$B$52,1,0) -> 1 | Z11: =IF(25>=Inputs!$B$52,1,0) -> 1 | AA11: =IF(26>=Inputs!$B$52,1,0) -> 1 | AB11: =IF(27>=Inputs!$B$52,1,0) -> 1 | AC11: =IF(28>=Inputs!$B$52,1,0) -> 1 | AD11: =IF(29>=Inputs!$B$52,1,0) -> 1 | AE11: =IF(30>=Inputs!$B$52,1,0) -> 1 | AF11: =IF(31>=Inputs!$B$52,1,0) -> 1 | AG11: =IF(32>=Inputs!$B$52,1,0) -> 1 | AH11: =IF(33>=Inputs!$B$52,1,0) -> 1 | AI11: =IF(34>=Inputs!$B$52,1,0) -> 1 | AJ11: =IF(35>=Inputs!$B$52,1,0) -> 1 | AK11: =IF(36>=Inputs!$B$52,1,0) -> 1 | AL11: =IF(37>=Inputs!$B$52,1,0) -> 1 | AM11: =IF(38>=Inputs!$B$52,1,0) -> 1 | AN11: =IF(39>=Inputs!$B$52,1,0) -> 1 | AO11: =IF(40>=Inputs!$B$52,1,0) -> 1 | AP11: =IF(41>=Inputs!$B$52,1,0) -> 1 | AQ11: =IF(42>=Inputs!$B$52,1,0) -> 1 | AR11: =IF(43>=Inputs!$B$52,1,0) -> 1 | AS11: =IF(44>=Inputs!$B$52,1,0) -> 1 | AT11: =IF(45>=Inputs!$B$52,1,0) -> 1 | AU11: =IF(46>=Inputs!$B$52,1,0) -> 1 | AV11: =IF(47>=Inputs!$B$52,1,0) -> 1 | AW11: =IF(48>=Inputs!$B$52,1,0) -> 1 | AX11: =IF(49>=Inputs!$B$52,1,0) -> 1 | AY11: =IF(50>=Inputs!$B$52,1,0) -> 1 | AZ11: =IF(51>=Inputs!$B$52,1,0) -> 1 | BA11: =IF(52>=Inputs!$B$52,1,0) -> 1
A12: 2. Sales Rep | B12: =IF(1>=Inputs!$B$53,1,0) -> 0 | C12: =IF(2>=Inputs!$B$53,1,0) -> 0 | D12: =IF(3>=Inputs!$B$53,1,0) -> 0 | E12: =IF(4>=Inputs!$B$53,1,0) -> 0 | F12: =IF(5>=Inputs!$B$53,1,0) -> 0 | G12: =IF(6>=Inputs!$B$53,1,0) -> 0 | H12: =IF(7>=Inputs!$B$53,1,0) -> 0 | I12: =IF(8>=Inputs!$B$53,1,0) -> 0 | J12: =IF(9>=Inputs!$B$53,1,0) -> 0 | K12: =IF(10>=Inputs!$B$53,1,0) -> 0 | L12: =IF(11>=Inputs!$B$53,1,0) -> 0 | M12: =IF(12>=Inputs!$B$53,1,0) -> 0 | N12: =IF(13>=Inputs!$B$53,1,0) -> 0 | O12: =IF(14>=Inputs!$B$53,1,0) -> 0 | P12: =IF(15>=Inputs!$B$53,1,0) -> 0 | Q12: =IF(16>=Inputs!$B$53,1,0) -> 0 | R12: =IF(17>=Inputs!$B$53,1,0) -> 0 | S12: =IF(18>=Inputs!$B$53,1,0) -> 1 | T12: =IF(19>=Inputs!$B$53,1,0) -> 1 | U12: =IF(20>=Inputs!$B$53,1,0) -> 1 | V12: =IF(21>=Inputs!$B$53,1,0) -> 1 | W12: =IF(22>=Inputs!$B$53,1,0) -> 1 | X12: =IF(23>=Inputs!$B$53,1,0) -> 1 | Y12: =IF(24>=Inputs!$B$53,1,0) -> 1 | Z12: =IF(25>=Inputs!$B$53,1,0) -> 1 | AA12: =IF(26>=Inputs!$B$53,1,0) -> 1 | AB12: =IF(27>=Inputs!$B$53,1,0) -> 1 | AC12: =IF(28>=Inputs!$B$53,1,0) -> 1 | AD12: =IF(29>=Inputs!$B$53,1,0) -> 1 | AE12: =IF(30>=Inputs!$B$53,1,0) -> 1 | AF12: =IF(31>=Inputs!$B$53,1,0) -> 1 | AG12: =IF(32>=Inputs!$B$53,1,0) -> 1 | AH12: =IF(33>=Inputs!$B$53,1,0) -> 1 | AI12: =IF(34>=Inputs!$B$53,1,0) -> 1 | AJ12: =IF(35>=Inputs!$B$53,1,0) -> 1 | AK12: =IF(36>=Inputs!$B$53,1,0) -> 1 | AL12: =IF(37>=Inputs!$B$53,1,0) -> 1 | AM12: =IF(38>=Inputs!$B$53,1,0) -> 1 | AN12: =IF(39>=Inputs!$B$53,1,0) -> 1 | AO12: =IF(40>=Inputs!$B$53,1,0) -> 1 | AP12: =IF(41>=Inputs!$B$53,1,0) -> 1 | AQ12: =IF(42>=Inputs!$B$53,1,0) -> 1 | AR12: =IF(43>=Inputs!$B$53,1,0) -> 1 | AS12: =IF(44>=Inputs!$B$53,1,0) -> 1 | AT12: =IF(45>=Inputs!$B$53,1,0) -> 1 | AU12: =IF(46>=Inputs!$B$53,1,0) -> 1 | AV12: =IF(47>=Inputs!$B$53,1,0) -> 1 | AW12: =IF(48>=Inputs!$B$53,1,0) -> 1 | AX12: =IF(49>=Inputs!$B$53,1,0) -> 1 | AY12: =IF(50>=Inputs!$B$53,1,0) -> 1 | AZ12: =IF(51>=Inputs!$B$53,1,0) -> 1 | BA12: =IF(52>=Inputs!$B$53,1,0) -> 1
A13: 1. Customer Success | B13: =IF(1>=Inputs!$B$54,1,0) -> 0 | C13: =IF(2>=Inputs!$B$54,1,0) -> 0 | D13: =IF(3>=Inputs!$B$54,1,0) -> 0 | E13: =IF(4>=Inputs!$B$54,1,0) -> 0 | F13: =IF(5>=Inputs!$B$54,1,0) -> 0 | G13: =IF(6>=Inputs!$B$54,1,0) -> 0 | H13: =IF(7>=Inputs!$B$54,1,0) -> 0 | I13: =IF(8>=Inputs!$B$54,1,0) -> 0 | J13: =IF(9>=Inputs!$B$54,1,0) -> 0 | K13: =IF(10>=Inputs!$B$54,1,0) -> 0 | L13: =IF(11>=Inputs!$B$54,1,0) -> 0 | M13: =IF(12>=Inputs!$B$54,1,0) -> 1 | N13: =IF(13>=Inputs!$B$54,1,0) -> 1 | O13: =IF(14>=Inputs!$B$54,1,0) -> 1 | P13: =IF(15>=Inputs!$B$54,1,0) -> 1 | Q13: =IF(16>=Inputs!$B$54,1,0) -> 1 | R13: =IF(17>=Inputs!$B$54,1,0) -> 1 | S13: =IF(18>=Inputs!$B$54,1,0) -> 1 | T13: =IF(19>=Inputs!$B$54,1,0) -> 1 | U13: =IF(20>=Inputs!$B$54,1,0) -> 1 | V13: =IF(21>=Inputs!$B$54,1,0) -> 1 | W13: =IF(22>=Inputs!$B$54,1,0) -> 1 | X13: =IF(23>=Inputs!$B$54,1,0) -> 1 | Y13: =IF(24>=Inputs!$B$54,1,0) -> 1 | Z13: =IF(25>=Inputs!$B$54,1,0) -> 1 | AA13: =IF(26>=Inputs!$B$54,1,0) -> 1 | AB13: =IF(27>=Inputs!$B$54,1,0) -> 1 | AC13: =IF(28>=Inputs!$B$54,1,0) -> 1 | AD13: =IF(29>=Inputs!$B$54,1,0) -> 1 | AE13: =IF(30>=Inputs!$B$54,1,0) -> 1 | AF13: =IF(31>=Inputs!$B$54,1,0) -> 1 | AG13: =IF(32>=Inputs!$B$54,1,0) -> 1 | AH13: =IF(33>=Inputs!$B$54,1,0) -> 1 | AI13: =IF(34>=Inputs!$B$54,1,0) -> 1 | AJ13: =IF(35>=Inputs!$B$54,1,0) -> 1 | AK13: =IF(36>=Inputs!$B$54,1,0) -> 1 | AL13: =IF(37>=Inputs!$B$54,1,0) -> 1 | AM13: =IF(38>=Inputs!$B$54,1,0) -> 1 | AN13: =IF(39>=Inputs!$B$54,1,0) -> 1 | AO13: =IF(40>=Inputs!$B$54,1,0) -> 1 | AP13: =IF(41>=Inputs!$B$54,1,0) -> 1 | AQ13: =IF(42>=Inputs!$B$54,1,0) -> 1 | AR13: =IF(43>=Inputs!$B$54,1,0) -> 1 | AS13: =IF(44>=Inputs!$B$54,1,0) -> 1 | AT13: =IF(45>=Inputs!$B$54,1,0) -> 1 | AU13: =IF(46>=Inputs!$B$54,1,0) -> 1 | AV13: =IF(47>=Inputs!$B$54,1,0) -> 1 | AW13: =IF(48>=Inputs!$B$54,1,0) -> 1 | AX13: =IF(49>=Inputs!$B$54,1,0) -> 1 | AY13: =IF(50>=Inputs!$B$54,1,0) -> 1 | AZ13: =IF(51>=Inputs!$B$54,1,0) -> 1 | BA13: =IF(52>=Inputs!$B$54,1,0) -> 1
A14: 1. Marketing Manager | B14: =IF(1>=Inputs!$B$55,1,0) -> 0 | C14: =IF(2>=Inputs!$B$55,1,0) -> 0 | D14: =IF(3>=Inputs!$B$55,1,0) -> 0 | E14: =IF(4>=Inputs!$B$55,1,0) -> 0 | F14: =IF(5>=Inputs!$B$55,1,0) -> 0 | G14: =IF(6>=Inputs!$B$55,1,0) -> 0 | H14: =IF(7>=Inputs!$B$55,1,0) -> 0 | I14: =IF(8>=Inputs!$B$55,1,0) -> 0 | J14: =IF(9>=Inputs!$B$55,1,0) -> 0 | K14: =IF(10>=Inputs!$B$55,1,0) -> 0 | L14: =IF(11>=Inputs!$B$55,1,0) -> 1 | M14: =IF(12>=Inputs!$B$55,1,0) -> 1 | N14: =IF(13>=Inputs!$B$55,1,0) -> 1 | O14: =IF(14>=Inputs!$B$55,1,0) -> 1 | P14: =IF(15>=Inputs!$B$55,1,0) -> 1 | Q14: =IF(16>=Inputs!$B$55,1,0) -> 1 | R14: =IF(17>=Inputs!$B$55,1,0) -> 1 | S14: =IF(18>=Inputs!$B$55,1,0) -> 1 | T14: =IF(19>=Inputs!$B$55,1,0) -> 1 | U14: =IF(20>=Inputs!$B$55,1,0) -> 1 | V14: =IF(21>=Inputs!$B$55,1,0) -> 1 | W14: =IF(22>=Inputs!$B$55,1,0) -> 1 | X14: =IF(23>=Inputs!$B$55,1,0) -> 1 | Y14: =IF(24>=Inputs!$B$55,1,0) -> 1 | Z14: =IF(25>=Inputs!$B$55,1,0) -> 1 | AA14: =IF(26>=Inputs!$B$55,1,0) -> 1 | AB14: =IF(27>=Inputs!$B$55,1,0) -> 1 | AC14: =IF(28>=Inputs!$B$55,1,0) -> 1 | AD14: =IF(29>=Inputs!$B$55,1,0) -> 1 | AE14: =IF(30>=Inputs!$B$55,1,0) -> 1 | AF14: =IF(31>=Inputs!$B$55,1,0) -> 1 | AG14: =IF(32>=Inputs!$B$55,1,0) -> 1 | AH14: =IF(33>=Inputs!$B$55,1,0) -> 1 | AI14: =IF(34>=Inputs!$B$55,1,0) -> 1 | AJ14: =IF(35>=Inputs!$B$55,1,0) -> 1 | AK14: =IF(36>=Inputs!$B$55,1,0) -> 1 | AL14: =IF(37>=Inputs!$B$55,1,0) -> 1 | AM14: =IF(38>=Inputs!$B$55,1,0) -> 1 | AN14: =IF(39>=Inputs!$B$55,1,0) -> 1 | AO14: =IF(40>=Inputs!$B$55,1,0) -> 1 | AP14: =IF(41>=Inputs!$B$55,1,0) -> 1 | AQ14: =IF(42>=Inputs!$B$55,1,0) -> 1 | AR14: =IF(43>=Inputs!$B$55,1,0) -> 1 | AS14: =IF(44>=Inputs!$B$55,1,0) -> 1 | AT14: =IF(45>=Inputs!$B$55,1,0) -> 1 | AU14: =IF(46>=Inputs!$B$55,1,0) -> 1 | AV14: =IF(47>=Inputs!$B$55,1,0) -> 1 | AW14: =IF(48>=Inputs!$B$55,1,0) -> 1 | AX14: =IF(49>=Inputs!$B$55,1,0) -> 1 | AY14: =IF(50>=Inputs!$B$55,1,0) -> 1 | AZ14: =IF(51>=Inputs!$B$55,1,0) -> 1 | BA14: =IF(52>=Inputs!$B$55,1,0) -> 1
A15: 1. Product Manager | B15: =IF(1>=Inputs!$B$56,1,0) -> 0 | C15: =IF(2>=Inputs!$B$56,1,0) -> 0 | D15: =IF(3>=Inputs!$B$56,1,0) -> 0 | E15: =IF(4>=Inputs!$B$56,1,0) -> 0 | F15: =IF(5>=Inputs!$B$56,1,0) -> 0 | G15: =IF(6>=Inputs!$B$56,1,0) -> 0 | H15: =IF(7>=Inputs!$B$56,1,0) -> 0 | I15: =IF(8>=Inputs!$B$56,1,0) -> 0 | J15: =IF(9>=Inputs!$B$56,1,0) -> 0 | K15: =IF(10>=Inputs!$B$56,1,0) -> 0 | L15: =IF(11>=Inputs!$B$56,1,0) -> 0 | M15: =IF(12>=Inputs!$B$56,1,0) -> 0 | N15: =IF(13>=Inputs!$B$56,1,0) -> 1 | O15: =IF(14>=Inputs!$B$56,1,0) -> 1 | P15: =IF(15>=Inputs!$B$56,1,0) -> 1 | Q15: =IF(16>=Inputs!$B$56,1,0) -> 1 | R15: =IF(17>=Inputs!$B$56,1,0) -> 1 | S15: =IF(18>=Inputs!$B$56,1,0) -> 1 | T15: =IF(19>=Inputs!$B$56,1,0) -> 1 | U15: =IF(20>=Inputs!$B$56,1,0) -> 1 | V15: =IF(21>=Inputs!$B$56,1,0) -> 1 | W15: =IF(22>=Inputs!$B$56,1,0) -> 1 | X15: =IF(23>=Inputs!$B$56,1,0) -> 1 | Y15: =IF(24>=Inputs!$B$56,1,0) -> 1 | Z15: =IF(25>=Inputs!$B$56,1,0) -> 1 | AA15: =IF(26>=Inputs!$B$56,1,0) -> 1 | AB15: =IF(27>=Inputs!$B$56,1,0) -> 1 | AC15: =IF(28>=Inputs!$B$56,1,0) -> 1 | AD15: =IF(29>=Inputs!$B$56,1,0) -> 1 | AE15: =IF(30>=Inputs!$B$56,1,0) -> 1 | AF15: =IF(31>=Inputs!$B$56,1,0) -> 1 | AG15: =IF(32>=Inputs!$B$56,1,0) -> 1 | AH15: =IF(33>=Inputs!$B$56,1,0) -> 1 | AI15: =IF(34>=Inputs!$B$56,1,0) -> 1 | AJ15: =IF(35>=Inputs!$B$56,1,0) -> 1 | AK15: =IF(36>=Inputs!$B$56,1,0) -> 1 | AL15: =IF(37>=Inputs!$B$56,1,0) -> 1 | AM15: =IF(38>=Inputs!$B$56,1,0) -> 1 | AN15: =IF(39>=Inputs!$B$56,1,0) -> 1 | AO15: =IF(40>=Inputs!$B$56,1,0) -> 1 | AP15: =IF(41>=Inputs!$B$56,1,0) -> 1 | AQ15: =IF(42>=Inputs!$B$56,1,0) -> 1 | AR15: =IF(43>=Inputs!$B$56,1,0) -> 1 | AS15: =IF(44>=Inputs!$B$56,1,0) -> 1 | AT15: =IF(45>=Inputs!$B$56,1,0) -> 1 | AU15: =IF(46>=Inputs!$B$56,1,0) -> 1 | AV15: =IF(47>=Inputs!$B$56,1,0) -> 1 | AW15: =IF(48>=Inputs!$B$56,1,0) -> 1 | AX15: =IF(49>=Inputs!$B$56,1,0) -> 1 | AY15: =IF(50>=Inputs!$B$56,1,0) -> 1 | AZ15: =IF(51>=Inputs!$B$56,1,0) -> 1 | BA15: =IF(52>=Inputs!$B$56,1,0) -> 1
A16: 1. Office Manager | B16: =IF(1>=Inputs!$B$57,1,0) -> 0 | C16: =IF(2>=Inputs!$B$57,1,0) -> 0 | D16: =IF(3>=Inputs!$B$57,1,0) -> 0 | E16: =IF(4>=Inputs!$B$57,1,0) -> 0 | F16: =IF(5>=Inputs!$B$57,1,0) -> 0 | G16: =IF(6>=Inputs!$B$57,1,0) -> 0 | H16: =IF(7>=Inputs!$B$57,1,0) -> 0 | I16: =IF(8>=Inputs!$B$57,1,0) -> 0 | J16: =IF(9>=Inputs!$B$57,1,0) -> 0 | K16: =IF(10>=Inputs!$B$57,1,0) -> 0 | L16: =IF(11>=Inputs!$B$57,1,0) -> 0 | M16: =IF(12>=Inputs!$B$57,1,0) -> 0 | N16: =IF(13>=Inputs!$B$57,1,0) -> 0 | O16: =IF(14>=Inputs!$B$57,1,0) -> 1 | P16: =IF(15>=Inputs!$B$57,1,0) -> 1 | Q16: =IF(16>=Inputs!$B$57,1,0) -> 1 | R16: =IF(17>=Inputs!$B$57,1,0) -> 1 | S16: =IF(18>=Inputs!$B$57,1,0) -> 1 | T16: =IF(19>=Inputs!$B$57,1,0) -> 1 | U16: =IF(20>=Inputs!$B$57,1,0) -> 1 | V16: =IF(21>=Inputs!$B$57,1,0) -> 1 | W16: =IF(22>=Inputs!$B$57,1,0) -> 1 | X16: =IF(23>=Inputs!$B$57,1,0) -> 1 | Y16: =IF(24>=Inputs!$B$57,1,0) -> 1 | Z16: =IF(25>=Inputs!$B$57,1,0) -> 1 | AA16: =IF(26>=Inputs!$B$57,1,0) -> 1 | AB16: =IF(27>=Inputs!$B$57,1,0) -> 1 | AC16: =IF(28>=Inputs!$B$57,1,0) -> 1 | AD16: =IF(29>=Inputs!$B$57,1,0) -> 1 | AE16: =IF(30>=Inputs!$B$57,1,0) -> 1 | AF16: =IF(31>=Inputs!$B$57,1,0) -> 1 | AG16: =IF(32>=Inputs!$B$57,1,0) -> 1 | AH16: =IF(33>=Inputs!$B$57,1,0) -> 1 | AI16: =IF(34>=Inputs!$B$57,1,0) -> 1 | AJ16: =IF(35>=Inputs!$B$57,1,0) -> 1 | AK16: =IF(36>=Inputs!$B$57,1,0) -> 1 | AL16: =IF(37>=Inputs!$B$57,1,0) -> 1 | AM16: =IF(38>=Inputs!$B$57,1,0) -> 1 | AN16: =IF(39>=Inputs!$B$57,1,0) -> 1 | AO16: =IF(40>=Inputs!$B$57,1,0) -> 1 | AP16: =IF(41>=Inputs!$B$57,1,0) -> 1 | AQ16: =IF(42>=Inputs!$B$57,1,0) -> 1 | AR16: =IF(43>=Inputs!$B$57,1,0) -> 1 | AS16: =IF(44>=Inputs!$B$57,1,0) -> 1 | AT16: =IF(45>=Inputs!$B$57,1,0) -> 1 | AU16: =IF(46>=Inputs!$B$57,1,0) -> 1 | AV16: =IF(47>=Inputs!$B$57,1,0) -> 1 | AW16: =IF(48>=Inputs!$B$57,1,0) -> 1 | AX16: =IF(49>=Inputs!$B$57,1,0) -> 1 | AY16: =IF(50>=Inputs!$B$57,1,0) -> 1 | AZ16: =IF(51>=Inputs!$B$57,1,0) -> 1 | BA16: =IF(52>=Inputs!$B$57,1,0) -> 1
A17: 3. Senior Engineer | B17: =IF(1>=Inputs!$B$58,1,0) -> 0 | C17: =IF(2>=Inputs!$B$58,1,0) -> 0 | D17: =IF(3>=Inputs!$B$58,1,0) -> 0 | E17: =IF(4>=Inputs!$B$58,1,0) -> 0 | F17: =IF(5>=Inputs!$B$58,1,0) -> 0 | G17: =IF(6>=Inputs!$B$58,1,0) -> 0 | H17: =IF(7>=Inputs!$B$58,1,0) -> 0 | I17: =IF(8>=Inputs!$B$58,1,0) -> 0 | J17: =IF(9>=Inputs!$B$58,1,0) -> 0 | K17: =IF(10>=Inputs!$B$58,1,0) -> 0 | L17: =IF(11>=Inputs!$B$58,1,0) -> 0 | M17: =IF(12>=Inputs!$B$58,1,0) -> 0 | N17: =IF(13>=Inputs!$B$58,1,0) -> 0 | O17: =IF(14>=Inputs!$B$58,1,0) -> 0 | P17: =IF(15>=Inputs!$B$58,1,0) -> 0 | Q17: =IF(16>=Inputs!$B$58,1,0) -> 0 | R17: =IF(17>=Inputs!$B$58,1,0) -> 0 | S17: =IF(18>=Inputs!$B$58,1,0) -> 1 | T17: =IF(19>=Inputs!$B$58,1,0) -> 1 | U17: =IF(20>=Inputs!$B$58,1,0) -> 1 | V17: =IF(21>=Inputs!$B$58,1,0) -> 1 | W17: =IF(22>=Inputs!$B$58,1,0) -> 1 | X17: =IF(23>=Inputs!$B$58,1,0) -> 1 | Y17: =IF(24>=Inputs!$B$58,1,0) -> 1 | Z17: =IF(25>=Inputs!$B$58,1,0) -> 1 | AA17: =IF(26>=Inputs!$B$58,1,0) -> 1 | AB17: =IF(27>=Inputs!$B$58,1,0) -> 1 | AC17: =IF(28>=Inputs!$B$58,1,0) -> 1 | AD17: =IF(29>=Inputs!$B$58,1,0) -> 1 | AE17: =IF(30>=Inputs!$B$58,1,0) -> 1 | AF17: =IF(31>=Inputs!$B$58,1,0) -> 1 | AG17: =IF(32>=Inputs!$B$58,1,0) -> 1 | AH17: =IF(33>=Inputs!$B$58,1,0) -> 1 | AI17: =IF(34>=Inputs!$B$58,1,0) -> 1 | AJ17: =IF(35>=Inputs!$B$58,1,0) -> 1 | AK17: =IF(36>=Inputs!$B$58,1,0) -> 1 | AL17: =IF(37>=Inputs!$B$58,1,0) -> 1 | AM17: =IF(38>=Inputs!$B$58,1,0) -> 1 | AN17: =IF(39>=Inputs!$B$58,1,0) -> 1 | AO17: =IF(40>=Inputs!$B$58,1,0) -> 1 | AP17: =IF(41>=Inputs!$B$58,1,0) -> 1 | AQ17: =IF(42>=Inputs!$B$58,1,0) -> 1 | AR17: =IF(43>=Inputs!$B$58,1,0) -> 1 | AS17: =IF(44>=Inputs!$B$58,1,0) -> 1 | AT17: =IF(45>=Inputs!$B$58,1,0) -> 1 | AU17: =IF(46>=Inputs!$B$58,1,0) -> 1 | AV17: =IF(47>=Inputs!$B$58,1,0) -> 1 | AW17: =IF(48>=Inputs!$B$58,1,0) -> 1 | AX17: =IF(49>=Inputs!$B$58,1,0) -> 1 | AY17: =IF(50>=Inputs!$B$58,1,0) -> 1 | AZ17: =IF(51>=Inputs!$B$58,1,0) -> 1 | BA17: =IF(52>=Inputs!$B$58,1,0) -> 1
A18: 4. Senior Engineer | B18: =IF(1>=Inputs!$B$59,1,0) -> 0 | C18: =IF(2>=Inputs!$B$59,1,0) -> 0 | D18: =IF(3>=Inputs!$B$59,1,0) -> 0 | E18: =IF(4>=Inputs!$B$59,1,0) -> 0 | F18: =IF(5>=Inputs!$B$59,1,0) -> 0 | G18: =IF(6>=Inputs!$B$59,1,0) -> 0 | H18: =IF(7>=Inputs!$B$59,1,0) -> 0 | I18: =IF(8>=Inputs!$B$59,1,0) -> 0 | J18: =IF(9>=Inputs!$B$59,1,0) -> 0 | K18: =IF(10>=Inputs!$B$59,1,0) -> 0 | L18: =IF(11>=Inputs!$B$59,1,0) -> 0 | M18: =IF(12>=Inputs!$B$59,1,0) -> 0 | N18: =IF(13>=Inputs!$B$59,1,0) -> 0 | O18: =IF(14>=Inputs!$B$59,1,0) -> 0 | P18: =IF(15>=Inputs!$B$59,1,0) -> 0 | Q18: =IF(16>=Inputs!$B$59,1,0) -> 0 | R18: =IF(17>=Inputs!$B$59,1,0) -> 0 | S18: =IF(18>=Inputs!$B$59,1,0) -> 0 | T18: =IF(19>=Inputs!$B$59,1,0) -> 0 | U18: =IF(20>=Inputs!$B$59,1,0) -> 0 | V18: =IF(21>=Inputs!$B$59,1,0) -> 0 | W18: =IF(22>=Inputs!$B$59,1,0) -> 0 | X18: =IF(23>=Inputs!$B$59,1,0) -> 0 | Y18: =IF(24>=Inputs!$B$59,1,0) -> 1 | Z18: =IF(25>=Inputs!$B$59,1,0) -> 1 | AA18: =IF(26>=Inputs!$B$59,1,0) -> 1 | AB18: =IF(27>=Inputs!$B$59,1,0) -> 1 | AC18: =IF(28>=Inputs!$B$59,1,0) -> 1 | AD18: =IF(29>=Inputs!$B$59,1,0) -> 1 | AE18: =IF(30>=Inputs!$B$59,1,0) -> 1 | AF18: =IF(31>=Inputs!$B$59,1,0) -> 1 | AG18: =IF(32>=Inputs!$B$59,1,0) -> 1 | AH18: =IF(33>=Inputs!$B$59,1,0) -> 1 | AI18: =IF(34>=Inputs!$B$59,1,0) -> 1 | AJ18: =IF(35>=Inputs!$B$59,1,0) -> 1 | AK18: =IF(36>=Inputs!$B$59,1,0) -> 1 | AL18: =IF(37>=Inputs!$B$59,1,0) -> 1 | AM18: =IF(38>=Inputs!$B$59,1,0) -> 1 | AN18: =IF(39>=Inputs!$B$59,1,0) -> 1 | AO18: =IF(40>=Inputs!$B$59,1,0) -> 1 | AP18: =IF(41>=Inputs!$B$59,1,0) -> 1 | AQ18: =IF(42>=Inputs!$B$59,1,0) -> 1 | AR18: =IF(43>=Inputs!$B$59,1,0) -> 1 | AS18: =IF(44>=Inputs!$B$59,1,0) -> 1 | AT18: =IF(45>=Inputs!$B$59,1,0) -> 1 | AU18: =IF(46>=Inputs!$B$59,1,0) -> 1 | AV18: =IF(47>=Inputs!$B$59,1,0) -> 1 | AW18: =IF(48>=Inputs!$B$59,1,0) -> 1 | AX18: =IF(49>=Inputs!$B$59,1,0) -> 1 | AY18: =IF(50>=Inputs!$B$59,1,0) -> 1 | AZ18: =IF(51>=Inputs!$B$59,1,0) -> 1 | BA18: =IF(52>=Inputs!$B$59,1,0) -> 1
A19: 2. Junior Engineer | B19: =IF(1>=Inputs!$B$60,1,0) -> 0 | C19: =IF(2>=Inputs!$B$60,1,0) -> 0 | D19: =IF(3>=Inputs!$B$60,1,0) -> 0 | E19: =IF(4>=Inputs!$B$60,1,0) -> 0 | F19: =IF(5>=Inputs!$B$60,1,0) -> 0 | G19: =IF(6>=Inputs!$B$60,1,0) -> 0 | H19: =IF(7>=Inputs!$B$60,1,0) -> 0 | I19: =IF(8>=Inputs!$B$60,1,0) -> 0 | J19: =IF(9>=Inputs!$B$60,1,0) -> 0 | K19: =IF(10>=Inputs!$B$60,1,0) -> 0 | L19: =IF(11>=Inputs!$B$60,1,0) -> 0 | M19: =IF(12>=Inputs!$B$60,1,0) -> 0 | N19: =IF(13>=Inputs!$B$60,1,0) -> 0 | O19: =IF(14>=Inputs!$B$60,1,0) -> 0 | P19: =IF(15>=Inputs!$B$60,1,0) -> 0 | Q19: =IF(16>=Inputs!$B$60,1,0) -> 0 | R19: =IF(17>=Inputs!$B$60,1,0) -> 0 | S19: =IF(18>=Inputs!$B$60,1,0) -> 0 | T19: =IF(19>=Inputs!$B$60,1,0) -> 0 | U19: =IF(20>=Inputs!$B$60,1,0) -> 1 | V19: =IF(21>=Inputs!$B$60,1,0) -> 1 | W19: =IF(22>=Inputs!$B$60,1,0) -> 1 | X19: =IF(23>=Inputs!$B$60,1,0) -> 1 | Y19: =IF(24>=Inputs!$B$60,1,0) -> 1 | Z19: =IF(25>=Inputs!$B$60,1,0) -> 1 | AA19: =IF(26>=Inputs!$B$60,1,0) -> 1 | AB19: =IF(27>=Inputs!$B$60,1,0) -> 1 | AC19: =IF(28>=Inputs!$B$60,1,0) -> 1 | AD19: =IF(29>=Inputs!$B$60,1,0) -> 1 | AE19: =IF(30>=Inputs!$B$60,1,0) -> 1 | AF19: =IF(31>=Inputs!$B$60,1,0) -> 1 | AG19: =IF(32>=Inputs!$B$60,1,0) -> 1 | AH19: =IF(33>=Inputs!$B$60,1,0) -> 1 | AI19: =IF(34>=Inputs!$B$60,1,0) -> 1 | AJ19: =IF(35>=Inputs!$B$60,1,0) -> 1 | AK19: =IF(36>=Inputs!$B$60,1,0) -> 1 | AL19: =IF(37>=Inputs!$B$60,1,0) -> 1 | AM19: =IF(38>=Inputs!$B$60,1,0) -> 1 | AN19: =IF(39>=Inputs!$B$60,1,0) -> 1 | AO19: =IF(40>=Inputs!$B$60,1,0) -> 1 | AP19: =IF(41>=Inputs!$B$60,1,0) -> 1 | AQ19: =IF(42>=Inputs!$B$60,1,0) -> 1 | AR19: =IF(43>=Inputs!$B$60,1,0) -> 1 | AS19: =IF(44>=Inputs!$B$60,1,0) -> 1 | AT19: =IF(45>=Inputs!$B$60,1,0) -> 1 | AU19: =IF(46>=Inputs!$B$60,1,0) -> 1 | AV19: =IF(47>=Inputs!$B$60,1,0) -> 1 | AW19: =IF(48>=Inputs!$B$60,1,0) -> 1 | AX19: =IF(49>=Inputs!$B$60,1,0) -> 1 | AY19: =IF(50>=Inputs!$B$60,1,0) -> 1 | AZ19: =IF(51>=Inputs!$B$60,1,0) -> 1 | BA19: =IF(52>=Inputs!$B$60,1,0) -> 1
A20: 3. ML/AI Engineer | B20: =IF(1>=Inputs!$B$61,1,0) -> 0 | C20: =IF(2>=Inputs!$B$61,1,0) -> 0 | D20: =IF(3>=Inputs!$B$61,1,0) -> 0 | E20: =IF(4>=Inputs!$B$61,1,0) -> 0 | F20: =IF(5>=Inputs!$B$61,1,0) -> 0 | G20: =IF(6>=Inputs!$B$61,1,0) -> 0 | H20: =IF(7>=Inputs!$B$61,1,0) -> 0 | I20: =IF(8>=Inputs!$B$61,1,0) -> 0 | J20: =IF(9>=Inputs!$B$61,1,0) -> 0 | K20: =IF(10>=Inputs!$B$61,1,0) -> 0 | L20: =IF(11>=Inputs!$B$61,1,0) -> 0 | M20: =IF(12>=Inputs!$B$61,1,0) -> 0 | N20: =IF(13>=Inputs!$B$61,1,0) -> 0 | O20: =IF(14>=Inputs!$B$61,1,0) -> 0 | P20: =IF(15>=Inputs!$B$61,1,0) -> 0 | Q20: =IF(16>=Inputs!$B$61,1,0) -> 0 | R20: =IF(17>=Inputs!$B$61,1,0) -> 0 | S20: =IF(18>=Inputs!$B$61,1,0) -> 0 | T20: =IF(19>=Inputs!$B$61,1,0) -> 0 | U20: =IF(20>=Inputs!$B$61,1,0) -> 0 | V20: =IF(21>=Inputs!$B$61,1,0) -> 0 | W20: =IF(22>=Inputs!$B$61,1,0) -> 1 | X20: =IF(23>=Inputs!$B$61,1,0) -> 1 | Y20: =IF(24>=Inputs!$B$61,1,0) -> 1 | Z20: =IF(25>=Inputs!$B$61,1,0) -> 1 | AA20: =IF(26>=Inputs!$B$61,1,0) -> 1 | AB20: =IF(27>=Inputs!$B$61,1,0) -> 1 | AC20: =IF(28>=Inputs!$B$61,1,0) -> 1 | AD20: =IF(29>=Inputs!$B$61,1,0) -> 1 | AE20: =IF(30>=Inputs!$B$61,1,0) -> 1 | AF20: =IF(31>=Inputs!$B$61,1,0) -> 1 | AG20: =IF(32>=Inputs!$B$61,1,0) -> 1 | AH20: =IF(33>=Inputs!$B$61,1,0) -> 1 | AI20: =IF(34>=Inputs!$B$61,1,0) -> 1 | AJ20: =IF(35>=Inputs!$B$61,1,0) -> 1 | AK20: =IF(36>=Inputs!$B$61,1,0) -> 1 | AL20: =IF(37>=Inputs!$B$61,1,0) -> 1 | AM20: =IF(38>=Inputs!$B$61,1,0) -> 1 | AN20: =IF(39>=Inputs!$B$61,1,0) -> 1 | AO20: =IF(40>=Inputs!$B$61,1,0) -> 1 | AP20: =IF(41>=Inputs!$B$61,1,0) -> 1 | AQ20: =IF(42>=Inputs!$B$61,1,0) -> 1 | AR20: =IF(43>=Inputs!$B$61,1,0) -> 1 | AS20: =IF(44>=Inputs!$B$61,1,0) -> 1 | AT20: =IF(45>=Inputs!$B$61,1,0) -> 1 | AU20: =IF(46>=Inputs!$B$61,1,0) -> 1 | AV20: =IF(47>=Inputs!$B$61,1,0) -> 1 | AW20: =IF(48>=Inputs!$B$61,1,0) -> 1 | AX20: =IF(49>=Inputs!$B$61,1,0) -> 1 | AY20: =IF(50>=Inputs!$B$61,1,0) -> 1 | AZ20: =IF(51>=Inputs!$B$61,1,0) -> 1 | BA20: =IF(52>=Inputs!$B$61,1,0) -> 1
A21: 3. Sales Rep | B21: =IF(1>=Inputs!$B$62,1,0) -> 0 | C21: =IF(2>=Inputs!$B$62,1,0) -> 0 | D21: =IF(3>=Inputs!$B$62,1,0) -> 0 | E21: =IF(4>=Inputs!$B$62,1,0) -> 0 | F21: =IF(5>=Inputs!$B$62,1,0) -> 0 | G21: =IF(6>=Inputs!$B$62,1,0) -> 0 | H21: =IF(7>=Inputs!$B$62,1,0) -> 0 | I21: =IF(8>=Inputs!$B$62,1,0) -> 0 | J21: =IF(9>=Inputs!$B$62,1,0) -> 0 | K21: =IF(10>=Inputs!$B$62,1,0) -> 0 | L21: =IF(11>=Inputs!$B$62,1,0) -> 0 | M21: =IF(12>=Inputs!$B$62,1,0) -> 0 | N21: =IF(13>=Inputs!$B$62,1,0) -> 0 | O21: =IF(14>=Inputs!$B$62,1,0) -> 0 | P21: =IF(15>=Inputs!$B$62,1,0) -> 0 | Q21: =IF(16>=Inputs!$B$62,1,0) -> 0 | R21: =IF(17>=Inputs!$B$62,1,0) -> 0 | S21: =IF(18>=Inputs!$B$62,1,0) -> 0 | T21: =IF(19>=Inputs!$B$62,1,0) -> 0 | U21: =IF(20>=Inputs!$B$62,1,0) -> 0 | V21: =IF(21>=Inputs!$B$62,1,0) -> 0 | W21: =IF(22>=Inputs!$B$62,1,0) -> 0 | X21: =IF(23>=Inputs!$B$62,1,0) -> 0 | Y21: =IF(24>=Inputs!$B$62,1,0) -> 0 | Z21: =IF(25>=Inputs!$B$62,1,0) -> 0 | AA21: =IF(26>=Inputs!$B$62,1,0) -> 1 | AB21: =IF(27>=Inputs!$B$62,1,0) -> 1 | AC21: =IF(28>=Inputs!$B$62,1,0) -> 1 | AD21: =IF(29>=Inputs!$B$62,1,0) -> 1 | AE21: =IF(30>=Inputs!$B$62,1,0) -> 1 | AF21: =IF(31>=Inputs!$B$62,1,0) -> 1 | AG21: =IF(32>=Inputs!$B$62,1,0) -> 1 | AH21: =IF(33>=Inputs!$B$62,1,0) -> 1 | AI21: =IF(34>=Inputs!$B$62,1,0) -> 1 | AJ21: =IF(35>=Inputs!$B$62,1,0) -> 1 | AK21: =IF(36>=Inputs!$B$62,1,0) -> 1 | AL21: =IF(37>=Inputs!$B$62,1,0) -> 1 | AM21: =IF(38>=Inputs!$B$62,1,0) -> 1 | AN21: =IF(39>=Inputs!$B$62,1,0) -> 1 | AO21: =IF(40>=Inputs!$B$62,1,0) -> 1 | AP21: =IF(41>=Inputs!$B$62,1,0) -> 1 | AQ21: =IF(42>=Inputs!$B$62,1,0) -> 1 | AR21: =IF(43>=Inputs!$B$62,1,0) -> 1 | AS21: =IF(44>=Inputs!$B$62,1,0) -> 1 | AT21: =IF(45>=Inputs!$B$62,1,0) -> 1 | AU21: =IF(46>=Inputs!$B$62,1,0) -> 1 | AV21: =IF(47>=Inputs!$B$62,1,0) -> 1 | AW21: =IF(48>=Inputs!$B$62,1,0) -> 1 | AX21: =IF(49>=Inputs!$B$62,1,0) -> 1 | AY21: =IF(50>=Inputs!$B$62,1,0) -> 1 | AZ21: =IF(51>=Inputs!$B$62,1,0) -> 1 | BA21: =IF(52>=Inputs!$B$62,1,0) -> 1
A22: 2. Customer Success | B22: =IF(1>=Inputs!$B$63,1,0) -> 0 | C22: =IF(2>=Inputs!$B$63,1,0) -> 0 | D22: =IF(3>=Inputs!$B$63,1,0) -> 0 | E22: =IF(4>=Inputs!$B$63,1,0) -> 0 | F22: =IF(5>=Inputs!$B$63,1,0) -> 0 | G22: =IF(6>=Inputs!$B$63,1,0) -> 0 | H22: =IF(7>=Inputs!$B$63,1,0) -> 0 | I22: =IF(8>=Inputs!$B$63,1,0) -> 0 | J22: =IF(9>=Inputs!$B$63,1,0) -> 0 | K22: =IF(10>=Inputs!$B$63,1,0) -> 0 | L22: =IF(11>=Inputs!$B$63,1,0) -> 0 | M22: =IF(12>=Inputs!$B$63,1,0) -> 0 | N22: =IF(13>=Inputs!$B$63,1,0) -> 0 | O22: =IF(14>=Inputs!$B$63,1,0) -> 0 | P22: =IF(15>=Inputs!$B$63,1,0) -> 0 | Q22: =IF(16>=Inputs!$B$63,1,0) -> 0 | R22: =IF(17>=Inputs!$B$63,1,0) -> 0 | S22: =IF(18>=Inputs!$B$63,1,0) -> 0 | T22: =IF(19>=Inputs!$B$63,1,0) -> 0 | U22: =IF(20>=Inputs!$B$63,1,0) -> 0 | V22: =IF(21>=Inputs!$B$63,1,0) -> 0 | W22: =IF(22>=Inputs!$B$63,1,0) -> 0 | X22: =IF(23>=Inputs!$B$63,1,0) -> 0 | Y22: =IF(24>=Inputs!$B$63,1,0) -> 1 | Z22: =IF(25>=Inputs!$B$63,1,0) -> 1 | AA22: =IF(26>=Inputs!$B$63,1,0) -> 1 | AB22: =IF(27>=Inputs!$B$63,1,0) -> 1 | AC22: =IF(28>=Inputs!$B$63,1,0) -> 1 | AD22: =IF(29>=Inputs!$B$63,1,0) -> 1 | AE22: =IF(30>=Inputs!$B$63,1,0) -> 1 | AF22: =IF(31>=Inputs!$B$63,1,0) -> 1 | AG22: =IF(32>=Inputs!$B$63,1,0) -> 1 | AH22: =IF(33>=Inputs!$B$63,1,0) -> 1 | AI22: =IF(34>=Inputs!$B$63,1,0) -> 1 | AJ22: =IF(35>=Inputs!$B$63,1,0) -> 1 | AK22: =IF(36>=Inputs!$B$63,1,0) -> 1 | AL22: =IF(37>=Inputs!$B$63,1,0) -> 1 | AM22: =IF(38>=Inputs!$B$63,1,0) -> 1 | AN22: =IF(39>=Inputs!$B$63,1,0) -> 1 | AO22: =IF(40>=Inputs!$B$63,1,0) -> 1 | AP22: =IF(41>=Inputs!$B$63,1,0) -> 1 | AQ22: =IF(42>=Inputs!$B$63,1,0) -> 1 | AR22: =IF(43>=Inputs!$B$63,1,0) -> 1 | AS22: =IF(44>=Inputs!$B$63,1,0) -> 1 | AT22: =IF(45>=Inputs!$B$63,1,0) -> 1 | AU22: =IF(46>=Inputs!$B$63,1,0) -> 1 | AV22: =IF(47>=Inputs!$B$63,1,0) -> 1 | AW22: =IF(48>=Inputs!$B$63,1,0) -> 1 | AX22: =IF(49>=Inputs!$B$63,1,0) -> 1 | AY22: =IF(50>=Inputs!$B$63,1,0) -> 1 | AZ22: =IF(51>=Inputs!$B$63,1,0) -> 1 | BA22: =IF(52>=Inputs!$B$63,1,0) -> 1
A23: 2. Marketing Manager | B23: =IF(1>=Inputs!$B$64,1,0) -> 0 | C23: =IF(2>=Inputs!$B$64,1,0) -> 0 | D23: =IF(3>=Inputs!$B$64,1,0) -> 0 | E23: =IF(4>=Inputs!$B$64,1,0) -> 0 | F23: =IF(5>=Inputs!$B$64,1,0) -> 0 | G23: =IF(6>=Inputs!$B$64,1,0) -> 0 | H23: =IF(7>=Inputs!$B$64,1,0) -> 0 | I23: =IF(8>=Inputs!$B$64,1,0) -> 0 | J23: =IF(9>=Inputs!$B$64,1,0) -> 0 | K23: =IF(10>=Inputs!$B$64,1,0) -> 0 | L23: =IF(11>=Inputs!$B$64,1,0) -> 0 | M23: =IF(12>=Inputs!$B$64,1,0) -> 0 | N23: =IF(13>=Inputs!$B$64,1,0) -> 0 | O23: =IF(14>=Inputs!$B$64,1,0) -> 0 | P23: =IF(15>=Inputs!$B$64,1,0) -> 0 | Q23: =IF(16>=Inputs!$B$64,1,0) -> 0 | R23: =IF(17>=Inputs!$B$64,1,0) -> 0 | S23: =IF(18>=Inputs!$B$64,1,0) -> 0 | T23: =IF(19>=Inputs!$B$64,1,0) -> 0 | U23: =IF(20>=Inputs!$B$64,1,0) -> 0 | V23: =IF(21>=Inputs!$B$64,1,0) -> 0 | W23: =IF(22>=Inputs!$B$64,1,0) -> 0 | X23: =IF(23>=Inputs!$B$64,1,0) -> 0 | Y23: =IF(24>=Inputs!$B$64,1,0) -> 0 | Z23: =IF(25>=Inputs!$B$64,1,0) -> 0 | AA23: =IF(26>=Inputs!$B$64,1,0) -> 0 | AB23: =IF(27>=Inputs!$B$64,1,0) -> 0 | AC23: =IF(28>=Inputs!$B$64,1,0) -> 1 | AD23: =IF(29>=Inputs!$B$64,1,0) -> 1 | AE23: =IF(30>=Inputs!$B$64,1,0) -> 1 | AF23: =IF(31>=Inputs!$B$64,1,0) -> 1 | AG23: =IF(32>=Inputs!$B$64,1,0) -> 1 | AH23: =IF(33>=Inputs!$B$64,1,0) -> 1 | AI23: =IF(34>=Inputs!$B$64,1,0) -> 1 | AJ23: =IF(35>=Inputs!$B$64,1,0) -> 1 | AK23: =IF(36>=Inputs!$B$64,1,0) -> 1 | AL23: =IF(37>=Inputs!$B$64,1,0) -> 1 | AM23: =IF(38>=Inputs!$B$64,1,0) -> 1 | AN23: =IF(39>=Inputs!$B$64,1,0) -> 1 | AO23: =IF(40>=Inputs!$B$64,1,0) -> 1 | AP23: =IF(41>=Inputs!$B$64,1,0) -> 1 | AQ23: =IF(42>=Inputs!$B$64,1,0) -> 1 | AR23: =IF(43>=Inputs!$B$64,1,0) -> 1 | AS23: =IF(44>=Inputs!$B$64,1,0) -> 1 | AT23: =IF(45>=Inputs!$B$64,1,0) -> 1 | AU23: =IF(46>=Inputs!$B$64,1,0) -> 1 | AV23: =IF(47>=Inputs!$B$64,1,0) -> 1 | AW23: =IF(48>=Inputs!$B$64,1,0) -> 1 | AX23: =IF(49>=Inputs!$B$64,1,0) -> 1 | AY23: =IF(50>=Inputs!$B$64,1,0) -> 1 | AZ23: =IF(51>=Inputs!$B$64,1,0) -> 1 | BA23: =IF(52>=Inputs!$B$64,1,0) -> 1
A24: 5. Senior Engineer | B24: =IF(1>=Inputs!$B$65,1,0) -> 0 | C24: =IF(2>=Inputs!$B$65,1,0) -> 0 | D24: =IF(3>=Inputs!$B$65,1,0) -> 0 | E24: =IF(4>=Inputs!$B$65,1,0) -> 0 | F24: =IF(5>=Inputs!$B$65,1,0) -> 0 | G24: =IF(6>=Inputs!$B$65,1,0) -> 0 | H24: =IF(7>=Inputs!$B$65,1,0) -> 0 | I24: =IF(8>=Inputs!$B$65,1,0) -> 0 | J24: =IF(9>=Inputs!$B$65,1,0) -> 0 | K24: =IF(10>=Inputs!$B$65,1,0) -> 0 | L24: =IF(11>=Inputs!$B$65,1,0) -> 0 | M24: =IF(12>=Inputs!$B$65,1,0) -> 0 | N24: =IF(13>=Inputs!$B$65,1,0) -> 0 | O24: =IF(14>=Inputs!$B$65,1,0) -> 0 | P24: =IF(15>=Inputs!$B$65,1,0) -> 0 | Q24: =IF(16>=Inputs!$B$65,1,0) -> 0 | R24: =IF(17>=Inputs!$B$65,1,0) -> 0 | S24: =IF(18>=Inputs!$B$65,1,0) -> 0 | T24: =IF(19>=Inputs!$B$65,1,0) -> 0 | U24: =IF(20>=Inputs!$B$65,1,0) -> 0 | V24: =IF(21>=Inputs!$B$65,1,0) -> 0 | W24: =IF(22>=Inputs!$B$65,1,0) -> 0 | X24: =IF(23>=Inputs!$B$65,1,0) -> 0 | Y24: =IF(24>=Inputs!$B$65,1,0) -> 0 | Z24: =IF(25>=Inputs!$B$65,1,0) -> 0 | AA24: =IF(26>=Inputs!$B$65,1,0) -> 0 | AB24: =IF(27>=Inputs!$B$65,1,0) -> 0 | AC24: =IF(28>=Inputs!$B$65,1,0) -> 0 | AD24: =IF(29>=Inputs!$B$65,1,0) -> 0 | AE24: =IF(30>=Inputs!$B$65,1,0) -> 1 | AF24: =IF(31>=Inputs!$B$65,1,0) -> 1 | AG24: =IF(32>=Inputs!$B$65,1,0) -> 1 | AH24: =IF(33>=Inputs!$B$65,1,0) -> 1 | AI24: =IF(34>=Inputs!$B$65,1,0) -> 1 | AJ24: =IF(35>=Inputs!$B$65,1,0) -> 1 | AK24: =IF(36>=Inputs!$B$65,1,0) -> 1 | AL24: =IF(37>=Inputs!$B$65,1,0) -> 1 | AM24: =IF(38>=Inputs!$B$65,1,0) -> 1 | AN24: =IF(39>=Inputs!$B$65,1,0) -> 1 | AO24: =IF(40>=Inputs!$B$65,1,0) -> 1 | AP24: =IF(41>=Inputs!$B$65,1,0) -> 1 | AQ24: =IF(42>=Inputs!$B$65,1,0) -> 1 | AR24: =IF(43>=Inputs!$B$65,1,0) -> 1 | AS24: =IF(44>=Inputs!$B$65,1,0) -> 1 | AT24: =IF(45>=Inputs!$B$65,1,0) -> 1 | AU24: =IF(46>=Inputs!$B$65,1,0) -> 1 | AV24: =IF(47>=Inputs!$B$65,1,0) -> 1 | AW24: =IF(48>=Inputs!$B$65,1,0) -> 1 | AX24: =IF(49>=Inputs!$B$65,1,0) -> 1 | AY24: =IF(50>=Inputs!$B$65,1,0) -> 1 | AZ24: =IF(51>=Inputs!$B$65,1,0) -> 1 | BA24: =IF(52>=Inputs!$B$65,1,0) -> 1
A25: 3. Junior Engineer | B25: =IF(1>=Inputs!$B$66,1,0) -> 0 | C25: =IF(2>=Inputs!$B$66,1,0) -> 0 | D25: =IF(3>=Inputs!$B$66,1,0) -> 0 | E25: =IF(4>=Inputs!$B$66,1,0) -> 0 | F25: =IF(5>=Inputs!$B$66,1,0) -> 0 | G25: =IF(6>=Inputs!$B$66,1,0) -> 0 | H25: =IF(7>=Inputs!$B$66,1,0) -> 0 | I25: =IF(8>=Inputs!$B$66,1,0) -> 0 | J25: =IF(9>=Inputs!$B$66,1,0) -> 0 | K25: =IF(10>=Inputs!$B$66,1,0) -> 0 | L25: =IF(11>=Inputs!$B$66,1,0) -> 0 | M25: =IF(12>=Inputs!$B$66,1,0) -> 0 | N25: =IF(13>=Inputs!$B$66,1,0) -> 0 | O25: =IF(14>=Inputs!$B$66,1,0) -> 0 | P25: =IF(15>=Inputs!$B$66,1,0) -> 0 | Q25: =IF(16>=Inputs!$B$66,1,0) -> 0 | R25: =IF(17>=Inputs!$B$66,1,0) -> 0 | S25: =IF(18>=Inputs!$B$66,1,0) -> 0 | T25: =IF(19>=Inputs!$B$66,1,0) -> 0 | U25: =IF(20>=Inputs!$B$66,1,0) -> 0 | V25: =IF(21>=Inputs!$B$66,1,0) -> 0 | W25: =IF(22>=Inputs!$B$66,1,0) -> 0 | X25: =IF(23>=Inputs!$B$66,1,0) -> 0 | Y25: =IF(24>=Inputs!$B$66,1,0) -> 0 | Z25: =IF(25>=Inputs!$B$66,1,0) -> 0 | AA25: =IF(26>=Inputs!$B$66,1,0) -> 0 | AB25: =IF(27>=Inputs!$B$66,1,0) -> 0 | AC25: =IF(28>=Inputs!$B$66,1,0) -> 0 | AD25: =IF(29>=Inputs!$B$66,1,0) -> 0 | AE25: =IF(30>=Inputs!$B$66,1,0) -> 0 | AF25: =IF(31>=Inputs!$B$66,1,0) -> 0 | AG25: =IF(32>=Inputs!$B$66,1,0) -> 1 | AH25: =IF(33>=Inputs!$B$66,1,0) -> 1 | AI25: =IF(34>=Inputs!$B$66,1,0) -> 1 | AJ25: =IF(35>=Inputs!$B$66,1,0) -> 1 | AK25: =IF(36>=Inputs!$B$66,1,0) -> 1 | AL25: =IF(37>=Inputs!$B$66,1,0) -> 1 | AM25: =IF(38>=Inputs!$B$66,1,0) -> 1 | AN25: =IF(39>=Inputs!$B$66,1,0) -> 1 | AO25: =IF(40>=Inputs!$B$66,1,0) -> 1 | AP25: =IF(41>=Inputs!$B$66,1,0) -> 1 | AQ25: =IF(42>=Inputs!$B$66,1,0) -> 1 | AR25: =IF(43>=Inputs!$B$66,1,0) -> 1 | AS25: =IF(44>=Inputs!$B$66,1,0) -> 1 | AT25: =IF(45>=Inputs!$B$66,1,0) -> 1 | AU25: =IF(46>=Inputs!$B$66,1,0) -> 1 | AV25: =IF(47>=Inputs!$B$66,1,0) -> 1 | AW25: =IF(48>=Inputs!$B$66,1,0) -> 1 | AX25: =IF(49>=Inputs!$B$66,1,0) -> 1 | AY25: =IF(50>=Inputs!$B$66,1,0) -> 1 | AZ25: =IF(51>=Inputs!$B$66,1,0) -> 1 | BA25: =IF(52>=Inputs!$B$66,1,0) -> 1
A26: 4. ML/AI Engineer | B26: =IF(1>=Inputs!$B$67,1,0) -> 0 | C26: =IF(2>=Inputs!$B$67,1,0) -> 0 | D26: =IF(3>=Inputs!$B$67,1,0) -> 0 | E26: =IF(4>=Inputs!$B$67,1,0) -> 0 | F26: =IF(5>=Inputs!$B$67,1,0) -> 0 | G26: =IF(6>=Inputs!$B$67,1,0) -> 0 | H26: =IF(7>=Inputs!$B$67,1,0) -> 0 | I26: =IF(8>=Inputs!$B$67,1,0) -> 0 | J26: =IF(9>=Inputs!$B$67,1,0) -> 0 | K26: =IF(10>=Inputs!$B$67,1,0) -> 0 | L26: =IF(11>=Inputs!$B$67,1,0) -> 0 | M26: =IF(12>=Inputs!$B$67,1,0) -> 0 | N26: =IF(13>=Inputs!$B$67,1,0) -> 0 | O26: =IF(14>=Inputs!$B$67,1,0) -> 0 | P26: =IF(15>=Inputs!$B$67,1,0) -> 0 | Q26: =IF(16>=Inputs!$B$67,1,0) -> 0 | R26: =IF(17>=Inputs!$B$67,1,0) -> 0 | S26: =IF(18>=Inputs!$B$67,1,0) -> 0 | T26: =IF(19>=Inputs!$B$67,1,0) -> 0 | U26: =IF(20>=Inputs!$B$67,1,0) -> 0 | V26: =IF(21>=Inputs!$B$67,1,0) -> 0 | W26: =IF(22>=Inputs!$B$67,1,0) -> 0 | X26: =IF(23>=Inputs!$B$67,1,0) -> 0 | Y26: =IF(24>=Inputs!$B$67,1,0) -> 0 | Z26: =IF(25>=Inputs!$B$67,1,0) -> 0 | AA26: =IF(26>=Inputs!$B$67,1,0) -> 0 | AB26: =IF(27>=Inputs!$B$67,1,0) -> 0 | AC26: =IF(28>=Inputs!$B$67,1,0) -> 0 | AD26: =IF(29>=Inputs!$B$67,1,0) -> 0 | AE26: =IF(30>=Inputs!$B$67,1,0) -> 0 | AF26: =IF(31>=Inputs!$B$67,1,0) -> 0 | AG26: =IF(32>=Inputs!$B$67,1,0) -> 0 | AH26: =IF(33>=Inputs!$B$67,1,0) -> 0 | AI26: =IF(34>=Inputs!$B$67,1,0) -> 1 | AJ26: =IF(35>=Inputs!$B$67,1,0) -> 1 | AK26: =IF(36>=Inputs!$B$67,1,0) -> 1 | AL26: =IF(37>=Inputs!$B$67,1,0) -> 1 | AM26: =IF(38>=Inputs!$B$67,1,0) -> 1 | AN26: =IF(39>=Inputs!$B$67,1,0) -> 1 | AO26: =IF(40>=Inputs!$B$67,1,0) -> 1 | AP26: =IF(41>=Inputs!$B$67,1,0) -> 1 | AQ26: =IF(42>=Inputs!$B$67,1,0) -> 1 | AR26: =IF(43>=Inputs!$B$67,1,0) -> 1 | AS26: =IF(44>=Inputs!$B$67,1,0) -> 1 | AT26: =IF(45>=Inputs!$B$67,1,0) -> 1 | AU26: =IF(46>=Inputs!$B$67,1,0) -> 1 | AV26: =IF(47>=Inputs!$B$67,1,0) -> 1 | AW26: =IF(48>=Inputs!$B$67,1,0) -> 1 | AX26: =IF(49>=Inputs!$B$67,1,0) -> 1 | AY26: =IF(50>=Inputs!$B$67,1,0) -> 1 | AZ26: =IF(51>=Inputs!$B$67,1,0) -> 1 | BA26: =IF(52>=Inputs!$B$67,1,0) -> 1
A27: 2. Product Manager | B27: =IF(1>=Inputs!$B$68,1,0) -> 0 | C27: =IF(2>=Inputs!$B$68,1,0) -> 0 | D27: =IF(3>=Inputs!$B$68,1,0) -> 0 | E27: =IF(4>=Inputs!$B$68,1,0) -> 0 | F27: =IF(5>=Inputs!$B$68,1,0) -> 0 | G27: =IF(6>=Inputs!$B$68,1,0) -> 0 | H27: =IF(7>=Inputs!$B$68,1,0) -> 0 | I27: =IF(8>=Inputs!$B$68,1,0) -> 0 | J27: =IF(9>=Inputs!$B$68,1,0) -> 0 | K27: =IF(10>=Inputs!$B$68,1,0) -> 0 | L27: =IF(11>=Inputs!$B$68,1,0) -> 0 | M27: =IF(12>=Inputs!$B$68,1,0) -> 0 | N27: =IF(13>=Inputs!$B$68,1,0) -> 0 | O27: =IF(14>=Inputs!$B$68,1,0) -> 0 | P27: =IF(15>=Inputs!$B$68,1,0) -> 0 | Q27: =IF(16>=Inputs!$B$68,1,0) -> 0 | R27: =IF(17>=Inputs!$B$68,1,0) -> 0 | S27: =IF(18>=Inputs!$B$68,1,0) -> 0 | T27: =IF(19>=Inputs!$B$68,1,0) -> 0 | U27: =IF(20>=Inputs!$B$68,1,0) -> 0 | V27: =IF(21>=Inputs!$B$68,1,0) -> 0 | W27: =IF(22>=Inputs!$B$68,1,0) -> 0 | X27: =IF(23>=Inputs!$B$68,1,0) -> 0 | Y27: =IF(24>=Inputs!$B$68,1,0) -> 0 | Z27: =IF(25>=Inputs!$B$68,1,0) -> 0 | AA27: =IF(26>=Inputs!$B$68,1,0) -> 0 | AB27: =IF(27>=Inputs!$B$68,1,0) -> 0 | AC27: =IF(28>=Inputs!$B$68,1,0) -> 0 | AD27: =IF(29>=Inputs!$B$68,1,0) -> 0 | AE27: =IF(30>=Inputs!$B$68,1,0) -> 1 | AF27: =IF(31>=Inputs!$B$68,1,0) -> 1 | AG27: =IF(32>=Inputs!$B$68,1,0) -> 1 | AH27: =IF(33>=Inputs!$B$68,1,0) -> 1 | AI27: =IF(34>=Inputs!$B$68,1,0) -> 1 | AJ27: =IF(35>=Inputs!$B$68,1,0) -> 1 | AK27: =IF(36>=Inputs!$B$68,1,0) -> 1 | AL27: =IF(37>=Inputs!$B$68,1,0) -> 1 | AM27: =IF(38>=Inputs!$B$68,1,0) -> 1 | AN27: =IF(39>=Inputs!$B$68,1,0) -> 1 | AO27: =IF(40>=Inputs!$B$68,1,0) -> 1 | AP27: =IF(41>=Inputs!$B$68,1,0) -> 1 | AQ27: =IF(42>=Inputs!$B$68,1,0) -> 1 | AR27: =IF(43>=Inputs!$B$68,1,0) -> 1 | AS27: =IF(44>=Inputs!$B$68,1,0) -> 1 | AT27: =IF(45>=Inputs!$B$68,1,0) -> 1 | AU27: =IF(46>=Inputs!$B$68,1,0) -> 1 | AV27: =IF(47>=Inputs!$B$68,1,0) -> 1 | AW27: =IF(48>=Inputs!$B$68,1,0) -> 1 | AX27: =IF(49>=Inputs!$B$68,1,0) -> 1 | AY27: =IF(50>=Inputs!$B$68,1,0) -> 1 | AZ27: =IF(51>=Inputs!$B$68,1,0) -> 1 | BA27: =IF(52>=Inputs!$B$68,1,0) -> 1
A28: 4. Sales Rep | B28: =IF(1>=Inputs!$B$69,1,0) -> 0 | C28: =IF(2>=Inputs!$B$69,1,0) -> 0 | D28: =IF(3>=Inputs!$B$69,1,0) -> 0 | E28: =IF(4>=Inputs!$B$69,1,0) -> 0 | F28: =IF(5>=Inputs!$B$69,1,0) -> 0 | G28: =IF(6>=Inputs!$B$69,1,0) -> 0 | H28: =IF(7>=Inputs!$B$69,1,0) -> 0 | I28: =IF(8>=Inputs!$B$69,1,0) -> 0 | J28: =IF(9>=Inputs!$B$69,1,0) -> 0 | K28: =IF(10>=Inputs!$B$69,1,0) -> 0 | L28: =IF(11>=Inputs!$B$69,1,0) -> 0 | M28: =IF(12>=Inputs!$B$69,1,0) -> 0 | N28: =IF(13>=Inputs!$B$69,1,0) -> 0 | O28: =IF(14>=Inputs!$B$69,1,0) -> 0 | P28: =IF(15>=Inputs!$B$69,1,0) -> 0 | Q28: =IF(16>=Inputs!$B$69,1,0) -> 0 | R28: =IF(17>=Inputs!$B$69,1,0) -> 0 | S28: =IF(18>=Inputs!$B$69,1,0) -> 0 | T28: =IF(19>=Inputs!$B$69,1,0) -> 0 | U28: =IF(20>=Inputs!$B$69,1,0) -> 0 | V28: =IF(21>=Inputs!$B$69,1,0) -> 0 | W28: =IF(22>=Inputs!$B$69,1,0) -> 0 | X28: =IF(23>=Inputs!$B$69,1,0) -> 0 | Y28: =IF(24>=Inputs!$B$69,1,0) -> 0 | Z28: =IF(25>=Inputs!$B$69,1,0) -> 0 | AA28: =IF(26>=Inputs!$B$69,1,0) -> 0 | AB28: =IF(27>=Inputs!$B$69,1,0) -> 0 | AC28: =IF(28>=Inputs!$B$69,1,0) -> 0 | AD28: =IF(29>=Inputs!$B$69,1,0) -> 0 | AE28: =IF(30>=Inputs!$B$69,1,0) -> 0 | AF28: =IF(31>=Inputs!$B$69,1,0) -> 0 | AG28: =IF(32>=Inputs!$B$69,1,0) -> 0 | AH28: =IF(33>=Inputs!$B$69,1,0) -> 0 | AI28: =IF(34>=Inputs!$B$69,1,0) -> 0 | AJ28: =IF(35>=Inputs!$B$69,1,0) -> 0 | AK28: =IF(36>=Inputs!$B$69,1,0) -> 1 | AL28: =IF(37>=Inputs!$B$69,1,0) -> 1 | AM28: =IF(38>=Inputs!$B$69,1,0) -> 1 | AN28: =IF(39>=Inputs!$B$69,1,0) -> 1 | AO28: =IF(40>=Inputs!$B$69,1,0) -> 1 | AP28: =IF(41>=Inputs!$B$69,1,0) -> 1 | AQ28: =IF(42>=Inputs!$B$69,1,0) -> 1 | AR28: =IF(43>=Inputs!$B$69,1,0) -> 1 | AS28: =IF(44>=Inputs!$B$69,1,0) -> 1 | AT28: =IF(45>=Inputs!$B$69,1,0) -> 1 | AU28: =IF(46>=Inputs!$B$69,1,0) -> 1 | AV28: =IF(47>=Inputs!$B$69,1,0) -> 1 | AW28: =IF(48>=Inputs!$B$69,1,0) -> 1 | AX28: =IF(49>=Inputs!$B$69,1,0) -> 1 | AY28: =IF(50>=Inputs!$B$69,1,0) -> 1 | AZ28: =IF(51>=Inputs!$B$69,1,0) -> 1 | BA28: =IF(52>=Inputs!$B$69,1,0) -> 1
A29: 3. Customer Success | B29: =IF(1>=Inputs!$B$70,1,0) -> 0 | C29: =IF(2>=Inputs!$B$70,1,0) -> 0 | D29: =IF(3>=Inputs!$B$70,1,0) -> 0 | E29: =IF(4>=Inputs!$B$70,1,0) -> 0 | F29: =IF(5>=Inputs!$B$70,1,0) -> 0 | G29: =IF(6>=Inputs!$B$70,1,0) -> 0 | H29: =IF(7>=Inputs!$B$70,1,0) -> 0 | I29: =IF(8>=Inputs!$B$70,1,0) -> 0 | J29: =IF(9>=Inputs!$B$70,1,0) -> 0 | K29: =IF(10>=Inputs!$B$70,1,0) -> 0 | L29: =IF(11>=Inputs!$B$70,1,0) -> 0 | M29: =IF(12>=Inputs!$B$70,1,0) -> 0 | N29: =IF(13>=Inputs!$B$70,1,0) -> 0 | O29: =IF(14>=Inputs!$B$70,1,0) -> 0 | P29: =IF(15>=Inputs!$B$70,1,0) -> 0 | Q29: =IF(16>=Inputs!$B$70,1,0) -> 0 | R29: =IF(17>=Inputs!$B$70,1,0) -> 0 | S29: =IF(18>=Inputs!$B$70,1,0) -> 0 | T29: =IF(19>=Inputs!$B$70,1,0) -> 0 | U29: =IF(20>=Inputs!$B$70,1,0) -> 0 | V29: =IF(21>=Inputs!$B$70,1,0) -> 0 | W29: =IF(22>=Inputs!$B$70,1,0) -> 0 | X29: =IF(23>=Inputs!$B$70,1,0) -> 0 | Y29: =IF(24>=Inputs!$B$70,1,0) -> 0 | Z29: =IF(25>=Inputs!$B$70,1,0) -> 0 | AA29: =IF(26>=Inputs!$B$70,1,0) -> 0 | AB29: =IF(27>=Inputs!$B$70,1,0) -> 0 | AC29: =IF(28>=Inputs!$B$70,1,0) -> 0 | AD29: =IF(29>=Inputs!$B$70,1,0) -> 0 | AE29: =IF(30>=Inputs!$B$70,1,0) -> 0 | AF29: =IF(31>=Inputs!$B$70,1,0) -> 0 | AG29: =IF(32>=Inputs!$B$70,1,0) -> 0 | AH29: =IF(33>=Inputs!$B$70,1,0) -> 0 | AI29: =IF(34>=Inputs!$B$70,1,0) -> 0 | AJ29: =IF(35>=Inputs!$B$70,1,0) -> 0 | AK29: =IF(36>=Inputs!$B$70,1,0) -> 1 | AL29: =IF(37>=Inputs!$B$70,1,0) -> 1 | AM29: =IF(38>=Inputs!$B$70,1,0) -> 1 | AN29: =IF(39>=Inputs!$B$70,1,0) -> 1 | AO29: =IF(40>=Inputs!$B$70,1,0) -> 1 | AP29: =IF(41>=Inputs!$B$70,1,0) -> 1 | AQ29: =IF(42>=Inputs!$B$70,1,0) -> 1 | AR29: =IF(43>=Inputs!$B$70,1,0) -> 1 | AS29: =IF(44>=Inputs!$B$70,1,0) -> 1 | AT29: =IF(45>=Inputs!$B$70,1,0) -> 1 | AU29: =IF(46>=Inputs!$B$70,1,0) -> 1 | AV29: =IF(47>=Inputs!$B$70,1,0) -> 1 | AW29: =IF(48>=Inputs!$B$70,1,0) -> 1 | AX29: =IF(49>=Inputs!$B$70,1,0) -> 1 | AY29: =IF(50>=Inputs!$B$70,1,0) -> 1 | AZ29: =IF(51>=Inputs!$B$70,1,0) -> 1 | BA29: =IF(52>=Inputs!$B$70,1,0) -> 1
A30: Finance Manager | B30: =IF(1>=Inputs!$B$71,1,0) -> 0 | C30: =IF(2>=Inputs!$B$71,1,0) -> 0 | D30: =IF(3>=Inputs!$B$71,1,0) -> 0 | E30: =IF(4>=Inputs!$B$71,1,0) -> 0 | F30: =IF(5>=Inputs!$B$71,1,0) -> 0 | G30: =IF(6>=Inputs!$B$71,1,0) -> 0 | H30: =IF(7>=Inputs!$B$71,1,0) -> 0 | I30: =IF(8>=Inputs!$B$71,1,0) -> 0 | J30: =IF(9>=Inputs!$B$71,1,0) -> 0 | K30: =IF(10>=Inputs!$B$71,1,0) -> 0 | L30: =IF(11>=Inputs!$B$71,1,0) -> 0 | M30: =IF(12>=Inputs!$B$71,1,0) -> 0 | N30: =IF(13>=Inputs!$B$71,1,0) -> 0 | O30: =IF(14>=Inputs!$B$71,1,0) -> 0 | P30: =IF(15>=Inputs!$B$71,1,0) -> 0 | Q30: =IF(16>=Inputs!$B$71,1,0) -> 0 | R30: =IF(17>=Inputs!$B$71,1,0) -> 0 | S30: =IF(18>=Inputs!$B$71,1,0) -> 1 | T30: =IF(19>=Inputs!$B$71,1,0) -> 1 | U30: =IF(20>=Inputs!$B$71,1,0) -> 1 | V30: =IF(21>=Inputs!$B$71,1,0) -> 1 | W30: =IF(22>=Inputs!$B$71,1,0) -> 1 | X30: =IF(23>=Inputs!$B$71,1,0) -> 1 | Y30: =IF(24>=Inputs!$B$71,1,0) -> 1 | Z30: =IF(25>=Inputs!$B$71,1,0) -> 1 | AA30: =IF(26>=Inputs!$B$71,1,0) -> 1 | AB30: =IF(27>=Inputs!$B$71,1,0) -> 1 | AC30: =IF(28>=Inputs!$B$71,1,0) -> 1 | AD30: =IF(29>=Inputs!$B$71,1,0) -> 1 | AE30: =IF(30>=Inputs!$B$71,1,0) -> 1 | AF30: =IF(31>=Inputs!$B$71,1,0) -> 1 | AG30: =IF(32>=Inputs!$B$71,1,0) -> 1 | AH30: =IF(33>=Inputs!$B$71,1,0) -> 1 | AI30: =IF(34>=Inputs!$B$71,1,0) -> 1 | AJ30: =IF(35>=Inputs!$B$71,1,0) -> 1 | AK30: =IF(36>=Inputs!$B$71,1,0) -> 1 | AL30: =IF(37>=Inputs!$B$71,1,0) -> 1 | AM30: =IF(38>=Inputs!$B$71,1,0) -> 1 | AN30: =IF(39>=Inputs!$B$71,1,0) -> 1 | AO30: =IF(40>=Inputs!$B$71,1,0) -> 1 | AP30: =IF(41>=Inputs!$B$71,1,0) -> 1 | AQ30: =IF(42>=Inputs!$B$71,1,0) -> 1 | AR30: =IF(43>=Inputs!$B$71,1,0) -> 1 | AS30: =IF(44>=Inputs!$B$71,1,0) -> 1 | AT30: =IF(45>=Inputs!$B$71,1,0) -> 1 | AU30: =IF(46>=Inputs!$B$71,1,0) -> 1 | AV30: =IF(47>=Inputs!$B$71,1,0) -> 1 | AW30: =IF(48>=Inputs!$B$71,1,0) -> 1 | AX30: =IF(49>=Inputs!$B$71,1,0) -> 1 | AY30: =IF(50>=Inputs!$B$71,1,0) -> 1 | AZ30: =IF(51>=Inputs!$B$71,1,0) -> 1 | BA30: =IF(52>=Inputs!$B$71,1,0) -> 1
A31: 6. Senior Engineer | B31: =IF(1>=Inputs!$B$72,1,0) -> 0 | C31: =IF(2>=Inputs!$B$72,1,0) -> 0 | D31: =IF(3>=Inputs!$B$72,1,0) -> 0 | E31: =IF(4>=Inputs!$B$72,1,0) -> 0 | F31: =IF(5>=Inputs!$B$72,1,0) -> 0 | G31: =IF(6>=Inputs!$B$72,1,0) -> 0 | H31: =IF(7>=Inputs!$B$72,1,0) -> 0 | I31: =IF(8>=Inputs!$B$72,1,0) -> 0 | J31: =IF(9>=Inputs!$B$72,1,0) -> 0 | K31: =IF(10>=Inputs!$B$72,1,0) -> 0 | L31: =IF(11>=Inputs!$B$72,1,0) -> 0 | M31: =IF(12>=Inputs!$B$72,1,0) -> 0 | N31: =IF(13>=Inputs!$B$72,1,0) -> 0 | O31: =IF(14>=Inputs!$B$72,1,0) -> 0 | P31: =IF(15>=Inputs!$B$72,1,0) -> 0 | Q31: =IF(16>=Inputs!$B$72,1,0) -> 0 | R31: =IF(17>=Inputs!$B$72,1,0) -> 0 | S31: =IF(18>=Inputs!$B$72,1,0) -> 0 | T31: =IF(19>=Inputs!$B$72,1,0) -> 0 | U31: =IF(20>=Inputs!$B$72,1,0) -> 0 | V31: =IF(21>=Inputs!$B$72,1,0) -> 0 | W31: =IF(22>=Inputs!$B$72,1,0) -> 0 | X31: =IF(23>=Inputs!$B$72,1,0) -> 0 | Y31: =IF(24>=Inputs!$B$72,1,0) -> 0 | Z31: =IF(25>=Inputs!$B$72,1,0) -> 0 | AA31: =IF(26>=Inputs!$B$72,1,0) -> 0 | AB31: =IF(27>=Inputs!$B$72,1,0) -> 0 | AC31: =IF(28>=Inputs!$B$72,1,0) -> 0 | AD31: =IF(29>=Inputs!$B$72,1,0) -> 0 | AE31: =IF(30>=Inputs!$B$72,1,0) -> 0 | AF31: =IF(31>=Inputs!$B$72,1,0) -> 0 | AG31: =IF(32>=Inputs!$B$72,1,0) -> 0 | AH31: =IF(33>=Inputs!$B$72,1,0) -> 0 | AI31: =IF(34>=Inputs!$B$72,1,0) -> 0 | AJ31: =IF(35>=Inputs!$B$72,1,0) -> 0 | AK31: =IF(36>=Inputs!$B$72,1,0) -> 0 | AL31: =IF(37>=Inputs!$B$72,1,0) -> 0 | AM31: =IF(38>=Inputs!$B$72,1,0) -> 1 | AN31: =IF(39>=Inputs!$B$72,1,0) -> 1 | AO31: =IF(40>=Inputs!$B$72,1,0) -> 1 | AP31: =IF(41>=Inputs!$B$72,1,0) -> 1 | AQ31: =IF(42>=Inputs!$B$72,1,0) -> 1 | AR31: =IF(43>=Inputs!$B$72,1,0) -> 1 | AS31: =IF(44>=Inputs!$B$72,1,0) -> 1 | AT31: =IF(45>=Inputs!$B$72,1,0) -> 1 | AU31: =IF(46>=Inputs!$B$72,1,0) -> 1 | AV31: =IF(47>=Inputs!$B$72,1,0) -> 1 | AW31: =IF(48>=Inputs!$B$72,1,0) -> 1 | AX31: =IF(49>=Inputs!$B$72,1,0) -> 1 | AY31: =IF(50>=Inputs!$B$72,1,0) -> 1 | AZ31: =IF(51>=Inputs!$B$72,1,0) -> 1 | BA31: =IF(52>=Inputs!$B$72,1,0) -> 1
A32: 7. Senior Engineer | B32: =IF(1>=Inputs!$B$73,1,0) -> 0 | C32: =IF(2>=Inputs!$B$73,1,0) -> 0 | D32: =IF(3>=Inputs!$B$73,1,0) -> 0 | E32: =IF(4>=Inputs!$B$73,1,0) -> 0 | F32: =IF(5>=Inputs!$B$73,1,0) -> 0 | G32: =IF(6>=Inputs!$B$73,1,0) -> 0 | H32: =IF(7>=Inputs!$B$73,1,0) -> 0 | I32: =IF(8>=Inputs!$B$73,1,0) -> 0 | J32: =IF(9>=Inputs!$B$73,1,0) -> 0 | K32: =IF(10>=Inputs!$B$73,1,0) -> 0 | L32: =IF(11>=Inputs!$B$73,1,0) -> 0 | M32: =IF(12>=Inputs!$B$73,1,0) -> 0 | N32: =IF(13>=Inputs!$B$73,1,0) -> 0 | O32: =IF(14>=Inputs!$B$73,1,0) -> 0 | P32: =IF(15>=Inputs!$B$73,1,0) -> 0 | Q32: =IF(16>=Inputs!$B$73,1,0) -> 0 | R32: =IF(17>=Inputs!$B$73,1,0) -> 0 | S32: =IF(18>=Inputs!$B$73,1,0) -> 0 | T32: =IF(19>=Inputs!$B$73,1,0) -> 0 | U32: =IF(20>=Inputs!$B$73,1,0) -> 0 | V32: =IF(21>=Inputs!$B$73,1,0) -> 0 | W32: =IF(22>=Inputs!$B$73,1,0) -> 0 | X32: =IF(23>=Inputs!$B$73,1,0) -> 0 | Y32: =IF(24>=Inputs!$B$73,1,0) -> 0 | Z32: =IF(25>=Inputs!$B$73,1,0) -> 0 | AA32: =IF(26>=Inputs!$B$73,1,0) -> 0 | AB32: =IF(27>=Inputs!$B$73,1,0) -> 0 | AC32: =IF(28>=Inputs!$B$73,1,0) -> 0 | AD32: =IF(29>=Inputs!$B$73,1,0) -> 0 | AE32: =IF(30>=Inputs!$B$73,1,0) -> 0 | AF32: =IF(31>=Inputs!$B$73,1,0) -> 0 | AG32: =IF(32>=Inputs!$B$73,1,0) -> 0 | AH32: =IF(33>=Inputs!$B$73,1,0) -> 0 | AI32: =IF(34>=Inputs!$B$73,1,0) -> 0 | AJ32: =IF(35>=Inputs!$B$73,1,0) -> 0 | AK32: =IF(36>=Inputs!$B$73,1,0) -> 0 | AL32: =IF(37>=Inputs!$B$73,1,0) -> 0 | AM32: =IF(38>=Inputs!$B$73,1,0) -> 0 | AN32: =IF(39>=Inputs!$B$73,1,0) -> 0 | AO32: =IF(40>=Inputs!$B$73,1,0) -> 0 | AP32: =IF(41>=Inputs!$B$73,1,0) -> 0 | AQ32: =IF(42>=Inputs!$B$73,1,0) -> 1 | AR32: =IF(43>=Inputs!$B$73,1,0) -> 1 | AS32: =IF(44>=Inputs!$B$73,1,0) -> 1 | AT32: =IF(45>=Inputs!$B$73,1,0) -> 1 | AU32: =IF(46>=Inputs!$B$73,1,0) -> 1 | AV32: =IF(47>=Inputs!$B$73,1,0) -> 1 | AW32: =IF(48>=Inputs!$B$73,1,0) -> 1 | AX32: =IF(49>=Inputs!$B$73,1,0) -> 1 | AY32: =IF(50>=Inputs!$B$73,1,0) -> 1 | AZ32: =IF(51>=Inputs!$B$73,1,0) -> 1 | BA32: =IF(52>=Inputs!$B$73,1,0) -> 1
A33: 4. Junior Engineer | B33: =IF(1>=Inputs!$B$74,1,0) -> 0 | C33: =IF(2>=Inputs!$B$74,1,0) -> 0 | D33: =IF(3>=Inputs!$B$74,1,0) -> 0 | E33: =IF(4>=Inputs!$B$74,1,0) -> 0 | F33: =IF(5>=Inputs!$B$74,1,0) -> 0 | G33: =IF(6>=Inputs!$B$74,1,0) -> 0 | H33: =IF(7>=Inputs!$B$74,1,0) -> 0 | I33: =IF(8>=Inputs!$B$74,1,0) -> 0 | J33: =IF(9>=Inputs!$B$74,1,0) -> 0 | K33: =IF(10>=Inputs!$B$74,1,0) -> 0 | L33: =IF(11>=Inputs!$B$74,1,0) -> 0 | M33: =IF(12>=Inputs!$B$74,1,0) -> 0 | N33: =IF(13>=Inputs!$B$74,1,0) -> 0 | O33: =IF(14>=Inputs!$B$74,1,0) -> 0 | P33: =IF(15>=Inputs!$B$74,1,0) -> 0 | Q33: =IF(16>=Inputs!$B$74,1,0) -> 0 | R33: =IF(17>=Inputs!$B$74,1,0) -> 0 | S33: =IF(18>=Inputs!$B$74,1,0) -> 0 | T33: =IF(19>=Inputs!$B$74,1,0) -> 0 | U33: =IF(20>=Inputs!$B$74,1,0) -> 0 | V33: =IF(21>=Inputs!$B$74,1,0) -> 0 | W33: =IF(22>=Inputs!$B$74,1,0) -> 0 | X33: =IF(23>=Inputs!$B$74,1,0) -> 0 | Y33: =IF(24>=Inputs!$B$74,1,0) -> 0 | Z33: =IF(25>=Inputs!$B$74,1,0) -> 0 | AA33: =IF(26>=Inputs!$B$74,1,0) -> 0 | AB33: =IF(27>=Inputs!$B$74,1,0) -> 0 | AC33: =IF(28>=Inputs!$B$74,1,0) -> 0 | AD33: =IF(29>=Inputs!$B$74,1,0) -> 0 | AE33: =IF(30>=Inputs!$B$74,1,0) -> 0 | AF33: =IF(31>=Inputs!$B$74,1,0) -> 0 | AG33: =IF(32>=Inputs!$B$74,1,0) -> 0 | AH33: =IF(33>=Inputs!$B$74,1,0) -> 0 | AI33: =IF(34>=Inputs!$B$74,1,0) -> 0 | AJ33: =IF(35>=Inputs!$B$74,1,0) -> 0 | AK33: =IF(36>=Inputs!$B$74,1,0) -> 0 | AL33: =IF(37>=Inputs!$B$74,1,0) -> 0 | AM33: =IF(38>=Inputs!$B$74,1,0) -> 0 | AN33: =IF(39>=Inputs!$B$74,1,0) -> 0 | AO33: =IF(40>=Inputs!$B$74,1,0) -> 1 | AP33: =IF(41>=Inputs!$B$74,1,0) -> 1 | AQ33: =IF(42>=Inputs!$B$74,1,0) -> 1 | AR33: =IF(43>=Inputs!$B$74,1,0) -> 1 | AS33: =IF(44>=Inputs!$B$74,1,0) -> 1 | AT33: =IF(45>=Inputs!$B$74,1,0) -> 1 | AU33: =IF(46>=Inputs!$B$74,1,0) -> 1 | AV33: =IF(47>=Inputs!$B$74,1,0) -> 1 | AW33: =IF(48>=Inputs!$B$74,1,0) -> 1 | AX33: =IF(49>=Inputs!$B$74,1,0) -> 1 | AY33: =IF(50>=Inputs!$B$74,1,0) -> 1 | AZ33: =IF(51>=Inputs!$B$74,1,0) -> 1 | BA33: =IF(52>=Inputs!$B$74,1,0) -> 1
A34: 5. ML/AI Engineer | B34: =IF(1>=Inputs!$B$75,1,0) -> 0 | C34: =IF(2>=Inputs!$B$75,1,0) -> 0 | D34: =IF(3>=Inputs!$B$75,1,0) -> 0 | E34: =IF(4>=Inputs!$B$75,1,0) -> 0 | F34: =IF(5>=Inputs!$B$75,1,0) -> 0 | G34: =IF(6>=Inputs!$B$75,1,0) -> 0 | H34: =IF(7>=Inputs!$B$75,1,0) -> 0 | I34: =IF(8>=Inputs!$B$75,1,0) -> 0 | J34: =IF(9>=Inputs!$B$75,1,0) -> 0 | K34: =IF(10>=Inputs!$B$75,1,0) -> 0 | L34: =IF(11>=Inputs!$B$75,1,0) -> 0 | M34: =IF(12>=Inputs!$B$75,1,0) -> 0 | N34: =IF(13>=Inputs!$B$75,1,0) -> 0 | O34: =IF(14>=Inputs!$B$75,1,0) -> 0 | P34: =IF(15>=Inputs!$B$75,1,0) -> 0 | Q34: =IF(16>=Inputs!$B$75,1,0) -> 0 | R34: =IF(17>=Inputs!$B$75,1,0) -> 0 | S34: =IF(18>=Inputs!$B$75,1,0) -> 0 | T34: =IF(19>=Inputs!$B$75,1,0) -> 0 | U34: =IF(20>=Inputs!$B$75,1,0) -> 0 | V34: =IF(21>=Inputs!$B$75,1,0) -> 0 | W34: =IF(22>=Inputs!$B$75,1,0) -> 0 | X34: =IF(23>=Inputs!$B$75,1,0) -> 0 | Y34: =IF(24>=Inputs!$B$75,1,0) -> 0 | Z34: =IF(25>=Inputs!$B$75,1,0) -> 0 | AA34: =IF(26>=Inputs!$B$75,1,0) -> 0 | AB34: =IF(27>=Inputs!$B$75,1,0) -> 0 | AC34: =IF(28>=Inputs!$B$75,1,0) -> 0 | AD34: =IF(29>=Inputs!$B$75,1,0) -> 0 | AE34: =IF(30>=Inputs!$B$75,1,0) -> 0 | AF34: =IF(31>=Inputs!$B$75,1,0) -> 0 | AG34: =IF(32>=Inputs!$B$75,1,0) -> 0 | AH34: =IF(33>=Inputs!$B$75,1,0) -> 0 | AI34: =IF(34>=Inputs!$B$75,1,0) -> 0 | AJ34: =IF(35>=Inputs!$B$75,1,0) -> 0 | AK34: =IF(36>=Inputs!$B$75,1,0) -> 0 | AL34: =IF(37>=Inputs!$B$75,1,0) -> 0 | AM34: =IF(38>=Inputs!$B$75,1,0) -> 0 | AN34: =IF(39>=Inputs!$B$75,1,0) -> 0 | AO34: =IF(40>=Inputs!$B$75,1,0) -> 0 | AP34: =IF(41>=Inputs!$B$75,1,0) -> 0 | AQ34: =IF(42>=Inputs!$B$75,1,0) -> 0 | AR34: =IF(43>=Inputs!$B$75,1,0) -> 0 | AS34: =IF(44>=Inputs!$B$75,1,0) -> 1 | AT34: =IF(45>=Inputs!$B$75,1,0) -> 1 | AU34: =IF(46>=Inputs!$B$75,1,0) -> 1 | AV34: =IF(47>=Inputs!$B$75,1,0) -> 1 | AW34: =IF(48>=Inputs!$B$75,1,0) -> 1 | AX34: =IF(49>=Inputs!$B$75,1,0) -> 1 | AY34: =IF(50>=Inputs!$B$75,1,0) -> 1 | AZ34: =IF(51>=Inputs!$B$75,1,0) -> 1 | BA34: =IF(52>=Inputs!$B$75,1,0) -> 1
A35: 5. Sales Rep | B35: =IF(1>=Inputs!$B$76,1,0) -> 0 | C35: =IF(2>=Inputs!$B$76,1,0) -> 0 | D35: =IF(3>=Inputs!$B$76,1,0) -> 0 | E35: =IF(4>=Inputs!$B$76,1,0) -> 0 | F35: =IF(5>=Inputs!$B$76,1,0) -> 0 | G35: =IF(6>=Inputs!$B$76,1,0) -> 0 | H35: =IF(7>=Inputs!$B$76,1,0) -> 0 | I35: =IF(8>=Inputs!$B$76,1,0) -> 0 | J35: =IF(9>=Inputs!$B$76,1,0) -> 0 | K35: =IF(10>=Inputs!$B$76,1,0) -> 0 | L35: =IF(11>=Inputs!$B$76,1,0) -> 0 | M35: =IF(12>=Inputs!$B$76,1,0) -> 0 | N35: =IF(13>=Inputs!$B$76,1,0) -> 0 | O35: =IF(14>=Inputs!$B$76,1,0) -> 0 | P35: =IF(15>=Inputs!$B$76,1,0) -> 0 | Q35: =IF(16>=Inputs!$B$76,1,0) -> 0 | R35: =IF(17>=Inputs!$B$76,1,0) -> 0 | S35: =IF(18>=Inputs!$B$76,1,0) -> 0 | T35: =IF(19>=Inputs!$B$76,1,0) -> 0 | U35: =IF(20>=Inputs!$B$76,1,0) -> 0 | V35: =IF(21>=Inputs!$B$76,1,0) -> 0 | W35: =IF(22>=Inputs!$B$76,1,0) -> 0 | X35: =IF(23>=Inputs!$B$76,1,0) -> 0 | Y35: =IF(24>=Inputs!$B$76,1,0) -> 0 | Z35: =IF(25>=Inputs!$B$76,1,0) -> 0 | AA35: =IF(26>=Inputs!$B$76,1,0) -> 0 | AB35: =IF(27>=Inputs!$B$76,1,0) -> 0 | AC35: =IF(28>=Inputs!$B$76,1,0) -> 0 | AD35: =IF(29>=Inputs!$B$76,1,0) -> 0 | AE35: =IF(30>=Inputs!$B$76,1,0) -> 0 | AF35: =IF(31>=Inputs!$B$76,1,0) -> 0 | AG35: =IF(32>=Inputs!$B$76,1,0) -> 0 | AH35: =IF(33>=Inputs!$B$76,1,0) -> 0 | AI35: =IF(34>=Inputs!$B$76,1,0) -> 0 | AJ35: =IF(35>=Inputs!$B$76,1,0) -> 0 | AK35: =IF(36>=Inputs!$B$76,1,0) -> 0 | AL35: =IF(37>=Inputs!$B$76,1,0) -> 0 | AM35: =IF(38>=Inputs!$B$76,1,0) -> 0 | AN35: =IF(39>=Inputs!$B$76,1,0) -> 0 | AO35: =IF(40>=Inputs!$B$76,1,0) -> 0 | AP35: =IF(41>=Inputs!$B$76,1,0) -> 0 | AQ35: =IF(42>=Inputs!$B$76,1,0) -> 1 | AR35: =IF(43>=Inputs!$B$76,1,0) -> 1 | AS35: =IF(44>=Inputs!$B$76,1,0) -> 1 | AT35: =IF(45>=Inputs!$B$76,1,0) -> 1 | AU35: =IF(46>=Inputs!$B$76,1,0) -> 1 | AV35: =IF(47>=Inputs!$B$76,1,0) -> 1 | AW35: =IF(48>=Inputs!$B$76,1,0) -> 1 | AX35: =IF(49>=Inputs!$B$76,1,0) -> 1 | AY35: =IF(50>=Inputs!$B$76,1,0) -> 1 | AZ35: =IF(51>=Inputs!$B$76,1,0) -> 1 | BA35: =IF(52>=Inputs!$B$76,1,0) -> 1
A36: 4. Customer Success | B36: =IF(1>=Inputs!$B$77,1,0) -> 0 | C36: =IF(2>=Inputs!$B$77,1,0) -> 0 | D36: =IF(3>=Inputs!$B$77,1,0) -> 0 | E36: =IF(4>=Inputs!$B$77,1,0) -> 0 | F36: =IF(5>=Inputs!$B$77,1,0) -> 0 | G36: =IF(6>=Inputs!$B$77,1,0) -> 0 | H36: =IF(7>=Inputs!$B$77,1,0) -> 0 | I36: =IF(8>=Inputs!$B$77,1,0) -> 0 | J36: =IF(9>=Inputs!$B$77,1,0) -> 0 | K36: =IF(10>=Inputs!$B$77,1,0) -> 0 | L36: =IF(11>=Inputs!$B$77,1,0) -> 0 | M36: =IF(12>=Inputs!$B$77,1,0) -> 0 | N36: =IF(13>=Inputs!$B$77,1,0) -> 0 | O36: =IF(14>=Inputs!$B$77,1,0) -> 0 | P36: =IF(15>=Inputs!$B$77,1,0) -> 0 | Q36: =IF(16>=Inputs!$B$77,1,0) -> 0 | R36: =IF(17>=Inputs!$B$77,1,0) -> 0 | S36: =IF(18>=Inputs!$B$77,1,0) -> 0 | T36: =IF(19>=Inputs!$B$77,1,0) -> 0 | U36: =IF(20>=Inputs!$B$77,1,0) -> 0 | V36: =IF(21>=Inputs!$B$77,1,0) -> 0 | W36: =IF(22>=Inputs!$B$77,1,0) -> 0 | X36: =IF(23>=Inputs!$B$77,1,0) -> 0 | Y36: =IF(24>=Inputs!$B$77,1,0) -> 0 | Z36: =IF(25>=Inputs!$B$77,1,0) -> 0 | AA36: =IF(26>=Inputs!$B$77,1,0) -> 0 | AB36: =IF(27>=Inputs!$B$77,1,0) -> 0 | AC36: =IF(28>=Inputs!$B$77,1,0) -> 0 | AD36: =IF(29>=Inputs!$B$77,1,0) -> 0 | AE36: =IF(30>=Inputs!$B$77,1,0) -> 0 | AF36: =IF(31>=Inputs!$B$77,1,0) -> 0 | AG36: =IF(32>=Inputs!$B$77,1,0) -> 0 | AH36: =IF(33>=Inputs!$B$77,1,0) -> 0 | AI36: =IF(34>=Inputs!$B$77,1,0) -> 0 | AJ36: =IF(35>=Inputs!$B$77,1,0) -> 0 | AK36: =IF(36>=Inputs!$B$77,1,0) -> 0 | AL36: =IF(37>=Inputs!$B$77,1,0) -> 0 | AM36: =IF(38>=Inputs!$B$77,1,0) -> 0 | AN36: =IF(39>=Inputs!$B$77,1,0) -> 0 | AO36: =IF(40>=Inputs!$B$77,1,0) -> 0 | AP36: =IF(41>=Inputs!$B$77,1,0) -> 0 | AQ36: =IF(42>=Inputs!$B$77,1,0) -> 0 | AR36: =IF(43>=Inputs!$B$77,1,0) -> 0 | AS36: =IF(44>=Inputs!$B$77,1,0) -> 1 | AT36: =IF(45>=Inputs!$B$77,1,0) -> 1 | AU36: =IF(46>=Inputs!$B$77,1,0) -> 1 | AV36: =IF(47>=Inputs!$B$77,1,0) -> 1 | AW36: =IF(48>=Inputs!$B$77,1,0) -> 1 | AX36: =IF(49>=Inputs!$B$77,1,0) -> 1 | AY36: =IF(50>=Inputs!$B$77,1,0) -> 1 | AZ36: =IF(51>=Inputs!$B$77,1,0) -> 1 | BA36: =IF(52>=Inputs!$B$77,1,0) -> 1
A37: 3. Marketing Manager | B37: =IF(1>=Inputs!$B$78,1,0) -> 0 | C37: =IF(2>=Inputs!$B$78,1,0) -> 0 | D37: =IF(3>=Inputs!$B$78,1,0) -> 0 | E37: =IF(4>=Inputs!$B$78,1,0) -> 0 | F37: =IF(5>=Inputs!$B$78,1,0) -> 0 | G37: =IF(6>=Inputs!$B$78,1,0) -> 0 | H37: =IF(7>=Inputs!$B$78,1,0) -> 0 | I37: =IF(8>=Inputs!$B$78,1,0) -> 0 | J37: =IF(9>=Inputs!$B$78,1,0) -> 0 | K37: =IF(10>=Inputs!$B$78,1,0) -> 0 | L37: =IF(11>=Inputs!$B$78,1,0) -> 0 | M37: =IF(12>=Inputs!$B$78,1,0) -> 0 | N37: =IF(13>=Inputs!$B$78,1,0) -> 0 | O37: =IF(14>=Inputs!$B$78,1,0) -> 0 | P37: =IF(15>=Inputs!$B$78,1,0) -> 0 | Q37: =IF(16>=Inputs!$B$78,1,0) -> 0 | R37: =IF(17>=Inputs!$B$78,1,0) -> 0 | S37: =IF(18>=Inputs!$B$78,1,0) -> 0 | T37: =IF(19>=Inputs!$B$78,1,0) -> 0 | U37: =IF(20>=Inputs!$B$78,1,0) -> 0 | V37: =IF(21>=Inputs!$B$78,1,0) -> 0 | W37: =IF(22>=Inputs!$B$78,1,0) -> 0 | X37: =IF(23>=Inputs!$B$78,1,0) -> 0 | Y37: =IF(24>=Inputs!$B$78,1,0) -> 0 | Z37: =IF(25>=Inputs!$B$78,1,0) -> 0 | AA37: =IF(26>=Inputs!$B$78,1,0) -> 0 | AB37: =IF(27>=Inputs!$B$78,1,0) -> 0 | AC37: =IF(28>=Inputs!$B$78,1,0) -> 0 | AD37: =IF(29>=Inputs!$B$78,1,0) -> 0 | AE37: =IF(30>=Inputs!$B$78,1,0) -> 0 | AF37: =IF(31>=Inputs!$B$78,1,0) -> 0 | AG37: =IF(32>=Inputs!$B$78,1,0) -> 0 | AH37: =IF(33>=Inputs!$B$78,1,0) -> 0 | AI37: =IF(34>=Inputs!$B$78,1,0) -> 0 | AJ37: =IF(35>=Inputs!$B$78,1,0) -> 0 | AK37: =IF(36>=Inputs!$B$78,1,0) -> 0 | AL37: =IF(37>=Inputs!$B$78,1,0) -> 0 | AM37: =IF(38>=Inputs!$B$78,1,0) -> 0 | AN37: =IF(39>=Inputs!$B$78,1,0) -> 0 | AO37: =IF(40>=Inputs!$B$78,1,0) -> 1 | AP37: =IF(41>=Inputs!$B$78,1,0) -> 1 | AQ37: =IF(42>=Inputs!$B$78,1,0) -> 1 | AR37: =IF(43>=Inputs!$B$78,1,0) -> 1 | AS37: =IF(44>=Inputs!$B$78,1,0) -> 1 | AT37: =IF(45>=Inputs!$B$78,1,0) -> 1 | AU37: =IF(46>=Inputs!$B$78,1,0) -> 1 | AV37: =IF(47>=Inputs!$B$78,1,0) -> 1 | AW37: =IF(48>=Inputs!$B$78,1,0) -> 1 | AX37: =IF(49>=Inputs!$B$78,1,0) -> 1 | AY37: =IF(50>=Inputs!$B$78,1,0) -> 1 | AZ37: =IF(51>=Inputs!$B$78,1,0) -> 1 | BA37: =IF(52>=Inputs!$B$78,1,0) -> 1
A38: TOTAL HEADCOUNT | B38: =SUM(B5:B37) -> 3 | C38: =SUM(C5:C37) -> 3 | D38: =SUM(D5:D37) -> 3 | E38: =SUM(E5:E37) -> 3 | F38: =SUM(F5:F37) -> 3 | G38: =SUM(G5:G37) -> 3 | H38: =SUM(H5:H37) -> 4 | I38: =SUM(I5:I37) -> 5 | ... BA38: =SUM(BA5:BA37) -> 35
A40: GEHÄLTER & PERSONALKOSTEN
A41: CEO Gehalt | B41: =Inputs!$B$32/12*(1+Inputs!$B$43)^INT((1-1)/12) -> 6000 | C41: =Inputs!$B$32/12*(1+Inputs!$B$43)^INT((2-1)/12) -> 6000 | D41: =Inputs!$B$32/12*(1+Inputs!$B$43)^INT((3-1)/12) -> 6000 | E41: =Inputs!$B$32/12*(1+Inputs!$B$43)^INT((4-1)/12) -> 6000 | F41: =Inputs!$B$32/12*(1+Inputs!$B$43)^INT((5-1)/12) -> 6000 | G41: =Inputs!$B$32/12*(1+Inputs!$B$43)^INT((6-1)/12) -> 6000 | H41: =Inputs!$B$32/12*(1+Inputs!$B$43)^INT((7-1)/12) -> 6000 | I41: =Inputs!$B$32/12*(1+Inputs!$B$43)^INT((8-1)/12) -> 6000 | J41: =Inputs!$B$32/12*(1+Inputs!$B$43)^INT((9-1)/12) -> 6000 | K41: =Inputs!$B$32/12*(1+Inputs!$B$43)^INT((10-1)/12) -> 6000 | L41: =Inputs!$B$32/12*(1+Inputs!$B$43)^INT((11-1)/12) -> 6000 | M41: =Inputs!$B$32/12*(1+Inputs!$B$43)^INT((12-1)/12) -> 6000 | N41: =Inputs!$B$32/12*(1+Inputs!$B$43)^INT((13-1)/12) -> 6300 | O41: =Inputs!$B$32/12*(1+Inputs!$B$43)^INT((14-1)/12) -> 6300 | P41: =Inputs!$B$32/12*(1+Inputs!$B$43)^INT((15-1)/12) -> 6300 | Q41: =Inputs!$B$32/12*(1+Inputs!$B$43)^INT((16-1)/12) -> 6300 | R41: =Inputs!$B$32/12*(1+Inputs!$B$43)^INT((17-1)/12) -> 6300 | S41: =Inputs!$B$32/12*(1+Inputs!$B$43)^INT((18-1)/12) -> 6300 | T41: =Inputs!$B$32/12*(1+Inputs!$B$43)^INT((19-1)/12) -> 6300 | U41: =Inputs!$B$32/12*(1+Inputs!$B$43)^INT((20-1)/12) -> 6300 | V41: =Inputs!$B$32/12*(1+Inputs!$B$43)^INT((21-1)/12) -> 6300 | W41: =Inputs!$B$32/12*(1+Inputs!$B$43)^INT((22-1)/12) -> 6300 | X41: =Inputs!$B$32/12*(1+Inputs!$B$43)^INT((23-1)/12) -> 6300 | Y41: =Inputs!$B$32/12*(1+Inputs!$B$43)^INT((24-1)/12) -> 6300 | Z41: =Inputs!$B$32/12*(1+Inputs!$B$43)^INT((25-1)/12) -> 6615 | AA41: =Inputs!$B$32/12*(1+Inputs!$B$43)^INT((26-1)/12) -> 6615 | AB41: =Inputs!$B$32/12*(1+Inputs!$B$43)^INT((27-1)/12) -> 6615 | AC41: =Inputs!$B$32/12*(1+Inputs!$B$43)^INT((28-1)/12) -> 6615 | AD41: =Inputs!$B$32/12*(1+Inputs!$B$43)^INT((29-1)/12) -> 6615 | AE41: =Inputs!$B$32/12*(1+Inputs!$B$43)^INT((30-1)/12) -> 6615 | AF41: =Inputs!$B$32/12*(1+Inputs!$B$43)^INT((31-1)/12) -> 6615 | AG41: =Inputs!$B$32/12*(1+Inputs!$B$43)^INT((32-1)/12) -> 6615 | AH41: =Inputs!$B$32/12*(1+Inputs!$B$43)^INT((33-1)/12) -> 6615 | AI41: =Inputs!$B$32/12*(1+Inputs!$B$43)^INT((34-1)/12) -> 6615 | AJ41: =Inputs!$B$32/12*(1+Inputs!$B$43)^INT((35-1)/12) -> 6615 | AK41: =Inputs!$B$32/12*(1+Inputs!$B$43)^INT((36-1)/12) -> 6615 | AL41: =Inputs!$B$32/12*(1+Inputs!$B$43)^INT((37-1)/12) -> 6945.75 | AM41: =Inputs!$B$32/12*(1+Inputs!$B$43)^INT((38-1)/12) -> 6945.75 | AN41: =Inputs!$B$32/12*(1+Inputs!$B$43)^INT((39-1)/12) -> 6945.75 | AO41: =Inputs!$B$32/12*(1+Inputs!$B$43)^INT((40-1)/12) -> 6945.75 | AP41: =Inputs!$B$32/12*(1+Inputs!$B$43)^INT((41-1)/12) -> 6945.75 | AQ41: =Inputs!$B$32/12*(1+Inputs!$B$43)^INT((42-1)/12) -> 6945.75 | AR41: =Inputs!$B$32/12*(1+Inputs!$B$43)^INT((43-1)/12) -> 6945.75 | AS41: =Inputs!$B$32/12*(1+Inputs!$B$43)^INT((44-1)/12) -> 6945.75 | AT41: =Inputs!$B$32/12*(1+Inputs!$B$43)^INT((45-1)/12) -> 6945.75 | AU41: =Inputs!$B$32/12*(1+Inputs!$B$43)^INT((46-1)/12) -> 6945.75 | AV41: =Inputs!$B$32/12*(1+Inputs!$B$43)^INT((47-1)/12) -> 6945.75 | AW41: =Inputs!$B$32/12*(1+Inputs!$B$43)^INT((48-1)/12) -> 6945.75 | AX41: =Inputs!$B$32/12*(1+Inputs!$B$43)^INT((49-1)/12) -> 7293.0375 | AY41: =Inputs!$B$32/12*(1+Inputs!$B$43)^INT((50-1)/12) -> 7293.0375 | AZ41: =Inputs!$B$32/12*(1+Inputs!$B$43)^INT((51-1)/12) -> 7293.0375 | BA41: =Inputs!$B$32/12*(1+Inputs!$B$43)^INT((52-1)/12) -> 7293.0375
A42: CTO Gehalt | B42: =Inputs!$B$33/12*(1+Inputs!$B$43)^INT((1-1)/12) -> 6000 | C42: =Inputs!$B$33/12*(1+Inputs!$B$43)^INT((2-1)/12) -> 6000 | D42: =Inputs!$B$33/12*(1+Inputs!$B$43)^INT((3-1)/12) -> 6000 | E42: =Inputs!$B$33/12*(1+Inputs!$B$43)^INT((4-1)/12) -> 6000 | F42: =Inputs!$B$33/12*(1+Inputs!$B$43)^INT((5-1)/12) -> 6000 | G42: =Inputs!$B$33/12*(1+Inputs!$B$43)^INT((6-1)/12) -> 6000 | H42: =Inputs!$B$33/12*(1+Inputs!$B$43)^INT((7-1)/12) -> 6000 | I42: =Inputs!$B$33/12*(1+Inputs!$B$43)^INT((8-1)/12) -> 6000 | J42: =Inputs!$B$33/12*(1+Inputs!$B$43)^INT((9-1)/12) -> 6000 | K42: =Inputs!$B$33/12*(1+Inputs!$B$43)^INT((10-1)/12) -> 6000 | L42: =Inputs!$B$33/12*(1+Inputs!$B$43)^INT((11-1)/12) -> 6000 | M42: =Inputs!$B$33/12*(1+Inputs!$B$43)^INT((12-1)/12) -> 6000 | N42: =Inputs!$B$33/12*(1+Inputs!$B$43)^INT((13-1)/12) -> 6300 | O42: =Inputs!$B$33/12*(1+Inputs!$B$43)^INT((14-1)/12) -> 6300 | P42: =Inputs!$B$33/12*(1+Inputs!$B$43)^INT((15-1)/12) -> 6300 | Q42: =Inputs!$B$33/12*(1+Inputs!$B$43)^INT((16-1)/12) -> 6300 | R42: =Inputs!$B$33/12*(1+Inputs!$B$43)^INT((17-1)/12) -> 6300 | S42: =Inputs!$B$33/12*(1+Inputs!$B$43)^INT((18-1)/12) -> 6300 | T42: =Inputs!$B$33/12*(1+Inputs!$B$43)^INT((19-1)/12) -> 6300 | U42: =Inputs!$B$33/12*(1+Inputs!$B$43)^INT((20-1)/12) -> 6300 | V42: =Inputs!$B$33/12*(1+Inputs!$B$43)^INT((21-1)/12) -> 6300 | W42: =Inputs!$B$33/12*(1+Inputs!$B$43)^INT((22-1)/12) -> 6300 | X42: =Inputs!$B$33/12*(1+Inputs!$B$43)^INT((23-1)/12) -> 6300 | Y42: =Inputs!$B$33/12*(1+Inputs!$B$43)^INT((24-1)/12) -> 6300 | Z42: =Inputs!$B$33/12*(1+Inputs!$B$43)^INT((25-1)/12) -> 6615 | AA42: =Inputs!$B$33/12*(1+Inputs!$B$43)^INT((26-1)/12) -> 6615 | AB42: =Inputs!$B$33/12*(1+Inputs!$B$43)^INT((27-1)/12) -> 6615 | AC42: =Inputs!$B$33/12*(1+Inputs!$B$43)^INT((28-1)/12) -> 6615 | AD42: =Inputs!$B$33/12*(1+Inputs!$B$43)^INT((29-1)/12) -> 6615 | AE42: =Inputs!$B$33/12*(1+Inputs!$B$43)^INT((30-1)/12) -> 6615 | AF42: =Inputs!$B$33/12*(1+Inputs!$B$43)^INT((31-1)/12) -> 6615 | AG42: =Inputs!$B$33/12*(1+Inputs!$B$43)^INT((32-1)/12) -> 6615 | AH42: =Inputs!$B$33/12*(1+Inputs!$B$43)^INT((33-1)/12) -> 6615 | AI42: =Inputs!$B$33/12*(1+Inputs!$B$43)^INT((34-1)/12) -> 6615 | AJ42: =Inputs!$B$33/12*(1+Inputs!$B$43)^INT((35-1)/12) -> 6615 | AK42: =Inputs!$B$33/12*(1+Inputs!$B$43)^INT((36-1)/12) -> 6615 | AL42: =Inputs!$B$33/12*(1+Inputs!$B$43)^INT((37-1)/12) -> 6945.75 | AM42: =Inputs!$B$33/12*(1+Inputs!$B$43)^INT((38-1)/12) -> 6945.75 | AN42: =Inputs!$B$33/12*(1+Inputs!$B$43)^INT((39-1)/12) -> 6945.75 | AO42: =Inputs!$B$33/12*(1+Inputs!$B$43)^INT((40-1)/12) -> 6945.75 | AP42: =Inputs!$B$33/12*(1+Inputs!$B$43)^INT((41-1)/12) -> 6945.75 | AQ42: =Inputs!$B$33/12*(1+Inputs!$B$43)^INT((42-1)/12) -> 6945.75 | AR42: =Inputs!$B$33/12*(1+Inputs!$B$43)^INT((43-1)/12) -> 6945.75 | AS42: =Inputs!$B$33/12*(1+Inputs!$B$43)^INT((44-1)/12) -> 6945.75 | AT42: =Inputs!$B$33/12*(1+Inputs!$B$43)^INT((45-1)/12) -> 6945.75 | AU42: =Inputs!$B$33/12*(1+Inputs!$B$43)^INT((46-1)/12) -> 6945.75 | AV42: =Inputs!$B$33/12*(1+Inputs!$B$43)^INT((47-1)/12) -> 6945.75 | AW42: =Inputs!$B$33/12*(1+Inputs!$B$43)^INT((48-1)/12) -> 6945.75 | AX42: =Inputs!$B$33/12*(1+Inputs!$B$43)^INT((49-1)/12) -> 7293.0375 | AY42: =Inputs!$B$33/12*(1+Inputs!$B$43)^INT((50-1)/12) -> 7293.0375 | AZ42: =Inputs!$B$33/12*(1+Inputs!$B$43)^INT((51-1)/12) -> 7293.0375 | BA42: =Inputs!$B$33/12*(1+Inputs!$B$43)^INT((52-1)/12) -> 7293.0375
A43: CCO Gehalt | B43: =Inputs!$B$34/12*(1+Inputs!$B$43)^INT((1-1)/12) -> 6000 | C43: =Inputs!$B$34/12*(1+Inputs!$B$43)^INT((2-1)/12) -> 6000 | D43: =Inputs!$B$34/12*(1+Inputs!$B$43)^INT((3-1)/12) -> 6000 | E43: =Inputs!$B$34/12*(1+Inputs!$B$43)^INT((4-1)/12) -> 6000 | F43: =Inputs!$B$34/12*(1+Inputs!$B$43)^INT((5-1)/12) -> 6000 | G43: =Inputs!$B$34/12*(1+Inputs!$B$43)^INT((6-1)/12) -> 6000 | H43: =Inputs!$B$34/12*(1+Inputs!$B$43)^INT((7-1)/12) -> 6000 | I43: =Inputs!$B$34/12*(1+Inputs!$B$43)^INT((8-1)/12) -> 6000 | J43: =Inputs!$B$34/12*(1+Inputs!$B$43)^INT((9-1)/12) -> 6000 | K43: =Inputs!$B$34/12*(1+Inputs!$B$43)^INT((10-1)/12) -> 6000 | L43: =Inputs!$B$34/12*(1+Inputs!$B$43)^INT((11-1)/12) -> 6000 | M43: =Inputs!$B$34/12*(1+Inputs!$B$43)^INT((12-1)/12) -> 6000 | N43: =Inputs!$B$34/12*(1+Inputs!$B$43)^INT((13-1)/12) -> 6300 | O43: =Inputs!$B$34/12*(1+Inputs!$B$43)^INT((14-1)/12) -> 6300 | P43: =Inputs!$B$34/12*(1+Inputs!$B$43)^INT((15-1)/12) -> 6300 | Q43: =Inputs!$B$34/12*(1+Inputs!$B$43)^INT((16-1)/12) -> 6300 | R43: =Inputs!$B$34/12*(1+Inputs!$B$43)^INT((17-1)/12) -> 6300 | S43: =Inputs!$B$34/12*(1+Inputs!$B$43)^INT((18-1)/12) -> 6300 | T43: =Inputs!$B$34/12*(1+Inputs!$B$43)^INT((19-1)/12) -> 6300 | U43: =Inputs!$B$34/12*(1+Inputs!$B$43)^INT((20-1)/12) -> 6300 | V43: =Inputs!$B$34/12*(1+Inputs!$B$43)^INT((21-1)/12) -> 6300 | W43: =Inputs!$B$34/12*(1+Inputs!$B$43)^INT((22-1)/12) -> 6300 | X43: =Inputs!$B$34/12*(1+Inputs!$B$43)^INT((23-1)/12) -> 6300 | Y43: =Inputs!$B$34/12*(1+Inputs!$B$43)^INT((24-1)/12) -> 6300 | Z43: =Inputs!$B$34/12*(1+Inputs!$B$43)^INT((25-1)/12) -> 6615 | AA43: =Inputs!$B$34/12*(1+Inputs!$B$43)^INT((26-1)/12) -> 6615 | AB43: =Inputs!$B$34/12*(1+Inputs!$B$43)^INT((27-1)/12) -> 6615 | AC43: =Inputs!$B$34/12*(1+Inputs!$B$43)^INT((28-1)/12) -> 6615 | AD43: =Inputs!$B$34/12*(1+Inputs!$B$43)^INT((29-1)/12) -> 6615 | AE43: =Inputs!$B$34/12*(1+Inputs!$B$43)^INT((30-1)/12) -> 6615 | AF43: =Inputs!$B$34/12*(1+Inputs!$B$43)^INT((31-1)/12) -> 6615 | AG43: =Inputs!$B$34/12*(1+Inputs!$B$43)^INT((32-1)/12) -> 6615 | AH43: =Inputs!$B$34/12*(1+Inputs!$B$43)^INT((33-1)/12) -> 6615 | AI43: =Inputs!$B$34/12*(1+Inputs!$B$43)^INT((34-1)/12) -> 6615 | AJ43: =Inputs!$B$34/12*(1+Inputs!$B$43)^INT((35-1)/12) -> 6615 | AK43: =Inputs!$B$34/12*(1+Inputs!$B$43)^INT((36-1)/12) -> 6615 | AL43: =Inputs!$B$34/12*(1+Inputs!$B$43)^INT((37-1)/12) -> 6945.75 | AM43: =Inputs!$B$34/12*(1+Inputs!$B$43)^INT((38-1)/12) -> 6945.75 | AN43: =Inputs!$B$34/12*(1+Inputs!$B$43)^INT((39-1)/12) -> 6945.75 | AO43: =Inputs!$B$34/12*(1+Inputs!$B$43)^INT((40-1)/12) -> 6945.75 | AP43: =Inputs!$B$34/12*(1+Inputs!$B$43)^INT((41-1)/12) -> 6945.75 | AQ43: =Inputs!$B$34/12*(1+Inputs!$B$43)^INT((42-1)/12) -> 6945.75 | AR43: =Inputs!$B$34/12*(1+Inputs!$B$43)^INT((43-1)/12) -> 6945.75 | AS43: =Inputs!$B$34/12*(1+Inputs!$B$43)^INT((44-1)/12) -> 6945.75 | AT43: =Inputs!$B$34/12*(1+Inputs!$B$43)^INT((45-1)/12) -> 6945.75 | AU43: =Inputs!$B$34/12*(1+Inputs!$B$43)^INT((46-1)/12) -> 6945.75 | AV43: =Inputs!$B$34/12*(1+Inputs!$B$43)^INT((47-1)/12) -> 6945.75 | AW43: =Inputs!$B$34/12*(1+Inputs!$B$43)^INT((48-1)/12) -> 6945.75 | AX43: =Inputs!$B$34/12*(1+Inputs!$B$43)^INT((49-1)/12) -> 7293.0375 | AY43: =Inputs!$B$34/12*(1+Inputs!$B$43)^INT((50-1)/12) -> 7293.0375 | AZ43: =Inputs!$B$34/12*(1+Inputs!$B$43)^INT((51-1)/12) -> 7293.0375 | BA43: =Inputs!$B$34/12*(1+Inputs!$B$43)^INT((52-1)/12) -> 7293.0375
A44: 1. Senior Engineer Gehalt | B44: =B6*Inputs!$B$35/12*(1+Inputs!$B$43)^INT((1-1)/12) -> 0 | C44: =C6*Inputs!$B$35/12*(1+Inputs!$B$43)^INT((2-1)/12) -> 0 | D44: =D6*Inputs!$B$35/12*(1+Inputs!$B$43)^INT((3-1)/12) -> 0 | E44: =E6*Inputs!$B$35/12*(1+Inputs!$B$43)^INT((4-1)/12) -> 0 | F44: =F6*Inputs!$B$35/12*(1+Inputs!$B$43)^INT((5-1)/12) -> 0 | G44: =G6*Inputs!$B$35/12*(1+Inputs!$B$43)^INT((6-1)/12) -> 0 | H44: =H6*Inputs!$B$35/12*(1+Inputs!$B$43)^INT((7-1)/12) -> 7500 | I44: =I6*Inputs!$B$35/12*(1+Inputs!$B$43)^INT((8-1)/12) -> 7500 | J44: =J6*Inputs!$B$35/12*(1+Inputs!$B$43)^INT((9-1)/12) -> 7500 | K44: =K6*Inputs!$B$35/12*(1+Inputs!$B$43)^INT((10-1)/12) -> 7500 | L44: =L6*Inputs!$B$35/12*(1+Inputs!$B$43)^INT((11-1)/12) -> 7500 | M44: =M6*Inputs!$B$35/12*(1+Inputs!$B$43)^INT((12-1)/12) -> 7500 | N44: =N6*Inputs!$B$35/12*(1+Inputs!$B$43)^INT((13-1)/12) -> 7875 | O44: =O6*Inputs!$B$35/12*(1+Inputs!$B$43)^INT((14-1)/12) -> 7875 | P44: =P6*Inputs!$B$35/12*(1+Inputs!$B$43)^INT((15-1)/12) -> 7875 | Q44: =Q6*Inputs!$B$35/12*(1+Inputs!$B$43)^INT((16-1)/12) -> 7875 | R44: =R6*Inputs!$B$35/12*(1+Inputs!$B$43)^INT((17-1)/12) -> 7875 | S44: =S6*Inputs!$B$35/12*(1+Inputs!$B$43)^INT((18-1)/12) -> 7875 | T44: =T6*Inputs!$B$35/12*(1+Inputs!$B$43)^INT((19-1)/12) -> 7875 | U44: =U6*Inputs!$B$35/12*(1+Inputs!$B$43)^INT((20-1)/12) -> 7875 | V44: =V6*Inputs!$B$35/12*(1+Inputs!$B$43)^INT((21-1)/12) -> 7875 | W44: =W6*Inputs!$B$35/12*(1+Inputs!$B$43)^INT((22-1)/12) -> 7875 | X44: =X6*Inputs!$B$35/12*(1+Inputs!$B$43)^INT((23-1)/12) -> 7875 | Y44: =Y6*Inputs!$B$35/12*(1+Inputs!$B$43)^INT((24-1)/12) -> 7875 | Z44: =Z6*Inputs!$B$35/12*(1+Inputs!$B$43)^INT((25-1)/12) -> 8268.75 | AA44: =AA6*Inputs!$B$35/12*(1+Inputs!$B$43)^INT((26-1)/12) -> 8268.75 | AB44: =AB6*Inputs!$B$35/12*(1+Inputs!$B$43)^INT((27-1)/12) -> 8268.75 | AC44: =AC6*Inputs!$B$35/12*(1+Inputs!$B$43)^INT((28-1)/12) -> 8268.75 | AD44: =AD6*Inputs!$B$35/12*(1+Inputs!$B$43)^INT((29-1)/12) -> 8268.75 | AE44: =AE6*Inputs!$B$35/12*(1+Inputs!$B$43)^INT((30-1)/12) -> 8268.75 | AF44: =AF6*Inputs!$B$35/12*(1+Inputs!$B$43)^INT((31-1)/12) -> 8268.75 | AG44: =AG6*Inputs!$B$35/12*(1+Inputs!$B$43)^INT((32-1)/12) -> 8268.75 | AH44: =AH6*Inputs!$B$35/12*(1+Inputs!$B$43)^INT((33-1)/12) -> 8268.75 | AI44: =AI6*Inputs!$B$35/12*(1+Inputs!$B$43)^INT((34-1)/12) -> 8268.75 | AJ44: =AJ6*Inputs!$B$35/12*(1+Inputs!$B$43)^INT((35-1)/12) -> 8268.75 | AK44: =AK6*Inputs!$B$35/12*(1+Inputs!$B$43)^INT((36-1)/12) -> 8268.75 | AL44: =AL6*Inputs!$B$35/12*(1+Inputs!$B$43)^INT((37-1)/12) -> 8682.1875 | AM44: =AM6*Inputs!$B$35/12*(1+Inputs!$B$43)^INT((38-1)/12) -> 8682.1875 | AN44: =AN6*Inputs!$B$35/12*(1+Inputs!$B$43)^INT((39-1)/12) -> 8682.1875 | AO44: =AO6*Inputs!$B$35/12*(1+Inputs!$B$43)^INT((40-1)/12) -> 8682.1875 | AP44: =AP6*Inputs!$B$35/12*(1+Inputs!$B$43)^INT((41-1)/12) -> 8682.1875 | AQ44: =AQ6*Inputs!$B$35/12*(1+Inputs!$B$43)^INT((42-1)/12) -> 8682.1875 | AR44: =AR6*Inputs!$B$35/12*(1+Inputs!$B$43)^INT((43-1)/12) -> 8682.1875 | AS44: =AS6*Inputs!$B$35/12*(1+Inputs!$B$43)^INT((44-1)/12) -> 8682.1875 | AT44: =AT6*Inputs!$B$35/12*(1+Inputs!$B$43)^INT((45-1)/12) -> 8682.1875 | AU44: =AU6*Inputs!$B$35/12*(1+Inputs!$B$43)^INT((46-1)/12) -> 8682.1875 | AV44: =AV6*Inputs!$B$35/12*(1+Inputs!$B$43)^INT((47-1)/12) -> 8682.1875 | AW44: =AW6*Inputs!$B$35/12*(1+Inputs!$B$43)^INT((48-1)/12) -> 8682.1875 | AX44: =AX6*Inputs!$B$35/12*(1+Inputs!$B$43)^INT((49-1)/12) -> 9116.2969 | AY44: =AY6*Inputs!$B$35/12*(1+Inputs!$B$43)^INT((50-1)/12) -> 9116.2969 | AZ44: =AZ6*Inputs!$B$35/12*(1+Inputs!$B$43)^INT((51-1)/12) -> 9116.2969 | BA44: =BA6*Inputs!$B$35/12*(1+Inputs!$B$43)^INT((52-1)/12) -> 9116.2969
A45: 2. Senior Engineer Gehalt | B45: =B7*Inputs!$B$35/12*(1+Inputs!$B$43)^INT((1-1)/12) -> 0 | C45: =C7*Inputs!$B$35/12*(1+Inputs!$B$43)^INT((2-1)/12) -> 0 | D45: =D7*Inputs!$B$35/12*(1+Inputs!$B$43)^INT((3-1)/12) -> 0 | E45: =E7*Inputs!$B$35/12*(1+Inputs!$B$43)^INT((4-1)/12) -> 0 | F45: =F7*Inputs!$B$35/12*(1+Inputs!$B$43)^INT((5-1)/12) -> 0 | G45: =G7*Inputs!$B$35/12*(1+Inputs!$B$43)^INT((6-1)/12) -> 0 | H45: =H7*Inputs!$B$35/12*(1+Inputs!$B$43)^INT((7-1)/12) -> 0 | I45: =I7*Inputs!$B$35/12*(1+Inputs!$B$43)^INT((8-1)/12) -> 0 | J45: =J7*Inputs!$B$35/12*(1+Inputs!$B$43)^INT((9-1)/12) -> 0 | K45: =K7*Inputs!$B$35/12*(1+Inputs!$B$43)^INT((10-1)/12) -> 7500 | L45: =L7*Inputs!$B$35/12*(1+Inputs!$B$43)^INT((11-1)/12) -> 7500 | M45: =M7*Inputs!$B$35/12*(1+Inputs!$B$43)^INT((12-1)/12) -> 7500 | N45: =N7*Inputs!$B$35/12*(1+Inputs!$B$43)^INT((13-1)/12) -> 7875 | O45: =O7*Inputs!$B$35/12*(1+Inputs!$B$43)^INT((14-1)/12) -> 7875 | P45: =P7*Inputs!$B$35/12*(1+Inputs!$B$43)^INT((15-1)/12) -> 7875 | Q45: =Q7*Inputs!$B$35/12*(1+Inputs!$B$43)^INT((16-1)/12) -> 7875 | R45: =R7*Inputs!$B$35/12*(1+Inputs!$B$43)^INT((17-1)/12) -> 7875 | S45: =S7*Inputs!$B$35/12*(1+Inputs!$B$43)^INT((18-1)/12) -> 7875 | T45: =T7*Inputs!$B$35/12*(1+Inputs!$B$43)^INT((19-1)/12) -> 7875 | U45: =U7*Inputs!$B$35/12*(1+Inputs!$B$43)^INT((20-1)/12) -> 7875 | V45: =V7*Inputs!$B$35/12*(1+Inputs!$B$43)^INT((21-1)/12) -> 7875 | W45: =W7*Inputs!$B$35/12*(1+Inputs!$B$43)^INT((22-1)/12) -> 7875 | X45: =X7*Inputs!$B$35/12*(1+Inputs!$B$43)^INT((23-1)/12) -> 7875 | Y45: =Y7*Inputs!$B$35/12*(1+Inputs!$B$43)^INT((24-1)/12) -> 7875 | Z45: =Z7*Inputs!$B$35/12*(1+Inputs!$B$43)^INT((25-1)/12) -> 8268.75 | AA45: =AA7*Inputs!$B$35/12*(1+Inputs!$B$43)^INT((26-1)/12) -> 8268.75 | AB45: =AB7*Inputs!$B$35/12*(1+Inputs!$B$43)^INT((27-1)/12) -> 8268.75 | AC45: =AC7*Inputs!$B$35/12*(1+Inputs!$B$43)^INT((28-1)/12) -> 8268.75 | AD45: =AD7*Inputs!$B$35/12*(1+Inputs!$B$43)^INT((29-1)/12) -> 8268.75 | AE45: =AE7*Inputs!$B$35/12*(1+Inputs!$B$43)^INT((30-1)/12) -> 8268.75 | AF45: =AF7*Inputs!$B$35/12*(1+Inputs!$B$43)^INT((31-1)/12) -> 8268.75 | AG45: =AG7*Inputs!$B$35/12*(1+Inputs!$B$43)^INT((32-1)/12) -> 8268.75 | AH45: =AH7*Inputs!$B$35/12*(1+Inputs!$B$43)^INT((33-1)/12) -> 8268.75 | AI45: =AI7*Inputs!$B$35/12*(1+Inputs!$B$43)^INT((34-1)/12) -> 8268.75 | AJ45: =AJ7*Inputs!$B$35/12*(1+Inputs!$B$43)^INT((35-1)/12) -> 8268.75 | AK45: =AK7*Inputs!$B$35/12*(1+Inputs!$B$43)^INT((36-1)/12) -> 8268.75 | AL45: =AL7*Inputs!$B$35/12*(1+Inputs!$B$43)^INT((37-1)/12) -> 8682.1875 | AM45: =AM7*Inputs!$B$35/12*(1+Inputs!$B$43)^INT((38-1)/12) -> 8682.1875 | AN45: =AN7*Inputs!$B$35/12*(1+Inputs!$B$43)^INT((39-1)/12) -> 8682.1875 | AO45: =AO7*Inputs!$B$35/12*(1+Inputs!$B$43)^INT((40-1)/12) -> 8682.1875 | AP45: =AP7*Inputs!$B$35/12*(1+Inputs!$B$43)^INT((41-1)/12) -> 8682.1875 | AQ45: =AQ7*Inputs!$B$35/12*(1+Inputs!$B$43)^INT((42-1)/12) -> 8682.1875 | AR45: =AR7*Inputs!$B$35/12*(1+Inputs!$B$43)^INT((43-1)/12) -> 8682.1875 | AS45: =AS7*Inputs!$B$35/12*(1+Inputs!$B$43)^INT((44-1)/12) -> 8682.1875 | AT45: =AT7*Inputs!$B$35/12*(1+Inputs!$B$43)^INT((45-1)/12) -> 8682.1875 | AU45: =AU7*Inputs!$B$35/12*(1+Inputs!$B$43)^INT((46-1)/12) -> 8682.1875 | AV45: =AV7*Inputs!$B$35/12*(1+Inputs!$B$43)^INT((47-1)/12) -> 8682.1875 | AW45: =AW7*Inputs!$B$35/12*(1+Inputs!$B$43)^INT((48-1)/12) -> 8682.1875 | AX45: =AX7*Inputs!$B$35/12*(1+Inputs!$B$43)^INT((49-1)/12) -> 9116.2969 | AY45: =AY7*Inputs!$B$35/12*(1+Inputs!$B$43)^INT((50-1)/12) -> 9116.2969 | AZ45: =AZ7*Inputs!$B$35/12*(1+Inputs!$B$43)^INT((51-1)/12) -> 9116.2969 | BA45: =BA7*Inputs!$B$35/12*(1+Inputs!$B$43)^INT((52-1)/12) -> 9116.2969
A46: 1. Junior Engineer Gehalt | B46: =B8*Inputs!$B$36/12*(1+Inputs!$B$43)^INT((1-1)/12) -> 0 | C46: =C8*Inputs!$B$36/12*(1+Inputs!$B$43)^INT((2-1)/12) -> 0 | D46: =D8*Inputs!$B$36/12*(1+Inputs!$B$43)^INT((3-1)/12) -> 0 | E46: =E8*Inputs!$B$36/12*(1+Inputs!$B$43)^INT((4-1)/12) -> 0 | F46: =F8*Inputs!$B$36/12*(1+Inputs!$B$43)^INT((5-1)/12) -> 0 | G46: =G8*Inputs!$B$36/12*(1+Inputs!$B$43)^INT((6-1)/12) -> 0 | H46: =H8*Inputs!$B$36/12*(1+Inputs!$B$43)^INT((7-1)/12) -> 0 | I46: =I8*Inputs!$B$36/12*(1+Inputs!$B$43)^INT((8-1)/12) -> 0 | J46: =J8*Inputs!$B$36/12*(1+Inputs!$B$43)^INT((9-1)/12) -> 5000 | K46: =K8*Inputs!$B$36/12*(1+Inputs!$B$43)^INT((10-1)/12) -> 5000 | L46: =L8*Inputs!$B$36/12*(1+Inputs!$B$43)^INT((11-1)/12) -> 5000 | M46: =M8*Inputs!$B$36/12*(1+Inputs!$B$43)^INT((12-1)/12) -> 5000 | N46: =N8*Inputs!$B$36/12*(1+Inputs!$B$43)^INT((13-1)/12) -> 5250 | O46: =O8*Inputs!$B$36/12*(1+Inputs!$B$43)^INT((14-1)/12) -> 5250 | P46: =P8*Inputs!$B$36/12*(1+Inputs!$B$43)^INT((15-1)/12) -> 5250 | Q46: =Q8*Inputs!$B$36/12*(1+Inputs!$B$43)^INT((16-1)/12) -> 5250 | R46: =R8*Inputs!$B$36/12*(1+Inputs!$B$43)^INT((17-1)/12) -> 5250 | S46: =S8*Inputs!$B$36/12*(1+Inputs!$B$43)^INT((18-1)/12) -> 5250 | T46: =T8*Inputs!$B$36/12*(1+Inputs!$B$43)^INT((19-1)/12) -> 5250 | U46: =U8*Inputs!$B$36/12*(1+Inputs!$B$43)^INT((20-1)/12) -> 5250 | V46: =V8*Inputs!$B$36/12*(1+Inputs!$B$43)^INT((21-1)/12) -> 5250 | W46: =W8*Inputs!$B$36/12*(1+Inputs!$B$43)^INT((22-1)/12) -> 5250 | X46: =X8*Inputs!$B$36/12*(1+Inputs!$B$43)^INT((23-1)/12) -> 5250 | Y46: =Y8*Inputs!$B$36/12*(1+Inputs!$B$43)^INT((24-1)/12) -> 5250 | Z46: =Z8*Inputs!$B$36/12*(1+Inputs!$B$43)^INT((25-1)/12) -> 5512.5 | AA46: =AA8*Inputs!$B$36/12*(1+Inputs!$B$43)^INT((26-1)/12) -> 5512.5 | AB46: =AB8*Inputs!$B$36/12*(1+Inputs!$B$43)^INT((27-1)/12) -> 5512.5 | AC46: =AC8*Inputs!$B$36/12*(1+Inputs!$B$43)^INT((28-1)/12) -> 5512.5 | AD46: =AD8*Inputs!$B$36/12*(1+Inputs!$B$43)^INT((29-1)/12) -> 5512.5 | AE46: =AE8*Inputs!$B$36/12*(1+Inputs!$B$43)^INT((30-1)/12) -> 5512.5 | AF46: =AF8*Inputs!$B$36/12*(1+Inputs!$B$43)^INT((31-1)/12) -> 5512.5 | AG46: =AG8*Inputs!$B$36/12*(1+Inputs!$B$43)^INT((32-1)/12) -> 5512.5 | AH46: =AH8*Inputs!$B$36/12*(1+Inputs!$B$43)^INT((33-1)/12) -> 5512.5 | AI46: =AI8*Inputs!$B$36/12*(1+Inputs!$B$43)^INT((34-1)/12) -> 5512.5 | AJ46: =AJ8*Inputs!$B$36/12*(1+Inputs!$B$43)^INT((35-1)/12) -> 5512.5 | AK46: =AK8*Inputs!$B$36/12*(1+Inputs!$B$43)^INT((36-1)/12) -> 5512.5 | AL46: =AL8*Inputs!$B$36/12*(1+Inputs!$B$43)^INT((37-1)/12) -> 5788.125 | AM46: =AM8*Inputs!$B$36/12*(1+Inputs!$B$43)^INT((38-1)/12) -> 5788.125 | AN46: =AN8*Inputs!$B$36/12*(1+Inputs!$B$43)^INT((39-1)/12) -> 5788.125 | AO46: =AO8*Inputs!$B$36/12*(1+Inputs!$B$43)^INT((40-1)/12) -> 5788.125 | AP46: =AP8*Inputs!$B$36/12*(1+Inputs!$B$43)^INT((41-1)/12) -> 5788.125 | AQ46: =AQ8*Inputs!$B$36/12*(1+Inputs!$B$43)^INT((42-1)/12) -> 5788.125 | AR46: =AR8*Inputs!$B$36/12*(1+Inputs!$B$43)^INT((43-1)/12) -> 5788.125 | AS46: =AS8*Inputs!$B$36/12*(1+Inputs!$B$43)^INT((44-1)/12) -> 5788.125 | AT46: =AT8*Inputs!$B$36/12*(1+Inputs!$B$43)^INT((45-1)/12) -> 5788.125 | AU46: =AU8*Inputs!$B$36/12*(1+Inputs!$B$43)^INT((46-1)/12) -> 5788.125 | AV46: =AV8*Inputs!$B$36/12*(1+Inputs!$B$43)^INT((47-1)/12) -> 5788.125 | AW46: =AW8*Inputs!$B$36/12*(1+Inputs!$B$43)^INT((48-1)/12) -> 5788.125 | AX46: =AX8*Inputs!$B$36/12*(1+Inputs!$B$43)^INT((49-1)/12) -> 6077.5312 | AY46: =AY8*Inputs!$B$36/12*(1+Inputs!$B$43)^INT((50-1)/12) -> 6077.5312 | AZ46: =AZ8*Inputs!$B$36/12*(1+Inputs!$B$43)^INT((51-1)/12) -> 6077.5312 | BA46: =BA8*Inputs!$B$36/12*(1+Inputs!$B$43)^INT((52-1)/12) -> 6077.5312
A47: 1. ML/AI Engineer Gehalt | B47: =B9*Inputs!$B$37/12*(1+Inputs!$B$43)^INT((1-1)/12) -> 0 | C47: =C9*Inputs!$B$37/12*(1+Inputs!$B$43)^INT((2-1)/12) -> 0 | D47: =D9*Inputs!$B$37/12*(1+Inputs!$B$43)^INT((3-1)/12) -> 0 | E47: =E9*Inputs!$B$37/12*(1+Inputs!$B$43)^INT((4-1)/12) -> 0 | F47: =F9*Inputs!$B$37/12*(1+Inputs!$B$43)^INT((5-1)/12) -> 0 | G47: =G9*Inputs!$B$37/12*(1+Inputs!$B$43)^INT((6-1)/12) -> 0 | H47: =H9*Inputs!$B$37/12*(1+Inputs!$B$43)^INT((7-1)/12) -> 0 | I47: =I9*Inputs!$B$37/12*(1+Inputs!$B$43)^INT((8-1)/12) -> 9166.6667 | J47: =J9*Inputs!$B$37/12*(1+Inputs!$B$43)^INT((9-1)/12) -> 9166.6667 | K47: =K9*Inputs!$B$37/12*(1+Inputs!$B$43)^INT((10-1)/12) -> 9166.6667 | L47: =L9*Inputs!$B$37/12*(1+Inputs!$B$43)^INT((11-1)/12) -> 9166.6667 | M47: =M9*Inputs!$B$37/12*(1+Inputs!$B$43)^INT((12-1)/12) -> 9166.6667 | N47: =N9*Inputs!$B$37/12*(1+Inputs!$B$43)^INT((13-1)/12) -> 9625 | O47: =O9*Inputs!$B$37/12*(1+Inputs!$B$43)^INT((14-1)/12) -> 9625 | P47: =P9*Inputs!$B$37/12*(1+Inputs!$B$43)^INT((15-1)/12) -> 9625 | Q47: =Q9*Inputs!$B$37/12*(1+Inputs!$B$43)^INT((16-1)/12) -> 9625 | R47: =R9*Inputs!$B$37/12*(1+Inputs!$B$43)^INT((17-1)/12) -> 9625 | S47: =S9*Inputs!$B$37/12*(1+Inputs!$B$43)^INT((18-1)/12) -> 9625 | T47: =T9*Inputs!$B$37/12*(1+Inputs!$B$43)^INT((19-1)/12) -> 9625 | U47: =U9*Inputs!$B$37/12*(1+Inputs!$B$43)^INT((20-1)/12) -> 9625 | V47: =V9*Inputs!$B$37/12*(1+Inputs!$B$43)^INT((21-1)/12) -> 9625 | W47: =W9*Inputs!$B$37/12*(1+Inputs!$B$43)^INT((22-1)/12) -> 9625 | X47: =X9*Inputs!$B$37/12*(1+Inputs!$B$43)^INT((23-1)/12) -> 9625 | Y47: =Y9*Inputs!$B$37/12*(1+Inputs!$B$43)^INT((24-1)/12) -> 9625 | Z47: =Z9*Inputs!$B$37/12*(1+Inputs!$B$43)^INT((25-1)/12) -> 10106.25 | AA47: =AA9*Inputs!$B$37/12*(1+Inputs!$B$43)^INT((26-1)/12) -> 10106.25 | AB47: =AB9*Inputs!$B$37/12*(1+Inputs!$B$43)^INT((27-1)/12) -> 10106.25 | AC47: =AC9*Inputs!$B$37/12*(1+Inputs!$B$43)^INT((28-1)/12) -> 10106.25 | AD47: =AD9*Inputs!$B$37/12*(1+Inputs!$B$43)^INT((29-1)/12) -> 10106.25 | AE47: =AE9*Inputs!$B$37/12*(1+Inputs!$B$43)^INT((30-1)/12) -> 10106.25 | AF47: =AF9*Inputs!$B$37/12*(1+Inputs!$B$43)^INT((31-1)/12) -> 10106.25 | AG47: =AG9*Inputs!$B$37/12*(1+Inputs!$B$43)^INT((32-1)/12) -> 10106.25 | AH47: =AH9*Inputs!$B$37/12*(1+Inputs!$B$43)^INT((33-1)/12) -> 10106.25 | AI47: =AI9*Inputs!$B$37/12*(1+Inputs!$B$43)^INT((34-1)/12) -> 10106.25 | AJ47: =AJ9*Inputs!$B$37/12*(1+Inputs!$B$43)^INT((35-1)/12) -> 10106.25 | AK47: =AK9*Inputs!$B$37/12*(1+Inputs!$B$43)^INT((36-1)/12) -> 10106.25 | AL47: =AL9*Inputs!$B$37/12*(1+Inputs!$B$43)^INT((37-1)/12) -> 10611.562 | AM47: =AM9*Inputs!$B$37/12*(1+Inputs!$B$43)^INT((38-1)/12) -> 10611.562 | AN47: =AN9*Inputs!$B$37/12*(1+Inputs!$B$43)^INT((39-1)/12) -> 10611.562 | AO47: =AO9*Inputs!$B$37/12*(1+Inputs!$B$43)^INT((40-1)/12) -> 10611.562 | AP47: =AP9*Inputs!$B$37/12*(1+Inputs!$B$43)^INT((41-1)/12) -> 10611.562 | AQ47: =AQ9*Inputs!$B$37/12*(1+Inputs!$B$43)^INT((42-1)/12) -> 10611.562 | AR47: =AR9*Inputs!$B$37/12*(1+Inputs!$B$43)^INT((43-1)/12) -> 10611.562 | AS47: =AS9*Inputs!$B$37/12*(1+Inputs!$B$43)^INT((44-1)/12) -> 10611.562 | AT47: =AT9*Inputs!$B$37/12*(1+Inputs!$B$43)^INT((45-1)/12) -> 10611.562 | AU47: =AU9*Inputs!$B$37/12*(1+Inputs!$B$43)^INT((46-1)/12) -> 10611.562 | AV47: =AV9*Inputs!$B$37/12*(1+Inputs!$B$43)^INT((47-1)/12) -> 10611.562 | AW47: =AW9*Inputs!$B$37/12*(1+Inputs!$B$43)^INT((48-1)/12) -> 10611.562 | AX47: =AX9*Inputs!$B$37/12*(1+Inputs!$B$43)^INT((49-1)/12) -> 11142.141 | AY47: =AY9*Inputs!$B$37/12*(1+Inputs!$B$43)^INT((50-1)/12) -> 11142.141 | AZ47: =AZ9*Inputs!$B$37/12*(1+Inputs!$B$43)^INT((51-1)/12) -> 11142.141 | BA47: =BA9*Inputs!$B$37/12*(1+Inputs!$B$43)^INT((52-1)/12) -> 11142.141
A48: 2. ML/AI Engineer Gehalt | B48: =B10*Inputs!$B$37/12*(1+Inputs!$B$43)^INT((1-1)/12) -> 0 | C48: =C10*Inputs!$B$37/12*(1+Inputs!$B$43)^INT((2-1)/12) -> 0 | D48: =D10*Inputs!$B$37/12*(1+Inputs!$B$43)^INT((3-1)/12) -> 0 | E48: =E10*Inputs!$B$37/12*(1+Inputs!$B$43)^INT((4-1)/12) -> 0 | F48: =F10*Inputs!$B$37/12*(1+Inputs!$B$43)^INT((5-1)/12) -> 0 | G48: =G10*Inputs!$B$37/12*(1+Inputs!$B$43)^INT((6-1)/12) -> 0 | H48: =H10*Inputs!$B$37/12*(1+Inputs!$B$43)^INT((7-1)/12) -> 0 | I48: =I10*Inputs!$B$37/12*(1+Inputs!$B$43)^INT((8-1)/12) -> 0 | J48: =J10*Inputs!$B$37/12*(1+Inputs!$B$43)^INT((9-1)/12) -> 0 | K48: =K10*Inputs!$B$37/12*(1+Inputs!$B$43)^INT((10-1)/12) -> 0 | L48: =L10*Inputs!$B$37/12*(1+Inputs!$B$43)^INT((11-1)/12) -> 0 | M48: =M10*Inputs!$B$37/12*(1+Inputs!$B$43)^INT((12-1)/12) -> 0 | N48: =N10*Inputs!$B$37/12*(1+Inputs!$B$43)^INT((13-1)/12) -> 0 | O48: =O10*Inputs!$B$37/12*(1+Inputs!$B$43)^INT((14-1)/12) -> 9625 | P48: =P10*Inputs!$B$37/12*(1+Inputs!$B$43)^INT((15-1)/12) -> 9625 | Q48: =Q10*Inputs!$B$37/12*(1+Inputs!$B$43)^INT((16-1)/12) -> 9625 | R48: =R10*Inputs!$B$37/12*(1+Inputs!$B$43)^INT((17-1)/12) -> 9625 | S48: =S10*Inputs!$B$37/12*(1+Inputs!$B$43)^INT((18-1)/12) -> 9625 | T48: =T10*Inputs!$B$37/12*(1+Inputs!$B$43)^INT((19-1)/12) -> 9625 | U48: =U10*Inputs!$B$37/12*(1+Inputs!$B$43)^INT((20-1)/12) -> 9625 | V48: =V10*Inputs!$B$37/12*(1+Inputs!$B$43)^INT((21-1)/12) -> 9625 | W48: =W10*Inputs!$B$37/12*(1+Inputs!$B$43)^INT((22-1)/12) -> 9625 | X48: =X10*Inputs!$B$37/12*(1+Inputs!$B$43)^INT((23-1)/12) -> 9625 | Y48: =Y10*Inputs!$B$37/12*(1+Inputs!$B$43)^INT((24-1)/12) -> 9625 | Z48: =Z10*Inputs!$B$37/12*(1+Inputs!$B$43)^INT((25-1)/12) -> 10106.25 | AA48: =AA10*Inputs!$B$37/12*(1+Inputs!$B$43)^INT((26-1)/12) -> 10106.25 | AB48: =AB10*Inputs!$B$37/12*(1+Inputs!$B$43)^INT((27-1)/12) -> 10106.25 | AC48: =AC10*Inputs!$B$37/12*(1+Inputs!$B$43)^INT((28-1)/12) -> 10106.25 | AD48: =AD10*Inputs!$B$37/12*(1+Inputs!$B$43)^INT((29-1)/12) -> 10106.25 | AE48: =AE10*Inputs!$B$37/12*(1+Inputs!$B$43)^INT((30-1)/12) -> 10106.25 | AF48: =AF10*Inputs!$B$37/12*(1+Inputs!$B$43)^INT((31-1)/12) -> 10106.25 | AG48: =AG10*Inputs!$B$37/12*(1+Inputs!$B$43)^INT((32-1)/12) -> 10106.25 | AH48: =AH10*Inputs!$B$37/12*(1+Inputs!$B$43)^INT((33-1)/12) -> 10106.25 | AI48: =AI10*Inputs!$B$37/12*(1+Inputs!$B$43)^INT((34-1)/12) -> 10106.25 | AJ48: =AJ10*Inputs!$B$37/12*(1+Inputs!$B$43)^INT((35-1)/12) -> 10106.25 | AK48: =AK10*Inputs!$B$37/12*(1+Inputs!$B$43)^INT((36-1)/12) -> 10106.25 | AL48: =AL10*Inputs!$B$37/12*(1+Inputs!$B$43)^INT((37-1)/12) -> 10611.562 | AM48: =AM10*Inputs!$B$37/12*(1+Inputs!$B$43)^INT((38-1)/12) -> 10611.562 | AN48: =AN10*Inputs!$B$37/12*(1+Inputs!$B$43)^INT((39-1)/12) -> 10611.562 | AO48: =AO10*Inputs!$B$37/12*(1+Inputs!$B$43)^INT((40-1)/12) -> 10611.562 | AP48: =AP10*Inputs!$B$37/12*(1+Inputs!$B$43)^INT((41-1)/12) -> 10611.562 | AQ48: =AQ10*Inputs!$B$37/12*(1+Inputs!$B$43)^INT((42-1)/12) -> 10611.562 | AR48: =AR10*Inputs!$B$37/12*(1+Inputs!$B$43)^INT((43-1)/12) -> 10611.562 | AS48: =AS10*Inputs!$B$37/12*(1+Inputs!$B$43)^INT((44-1)/12) -> 10611.562 | AT48: =AT10*Inputs!$B$37/12*(1+Inputs!$B$43)^INT((45-1)/12) -> 10611.562 | AU48: =AU10*Inputs!$B$37/12*(1+Inputs!$B$43)^INT((46-1)/12) -> 10611.562 | AV48: =AV10*Inputs!$B$37/12*(1+Inputs!$B$43)^INT((47-1)/12) -> 10611.562 | AW48: =AW10*Inputs!$B$37/12*(1+Inputs!$B$43)^INT((48-1)/12) -> 10611.562 | AX48: =AX10*Inputs!$B$37/12*(1+Inputs!$B$43)^INT((49-1)/12) -> 11142.141 | AY48: =AY10*Inputs!$B$37/12*(1+Inputs!$B$43)^INT((50-1)/12) -> 11142.141 | AZ48: =AZ10*Inputs!$B$37/12*(1+Inputs!$B$43)^INT((51-1)/12) -> 11142.141 | BA48: =BA10*Inputs!$B$37/12*(1+Inputs!$B$43)^INT((52-1)/12) -> 11142.141
A49: 1. Sales Rep Gehalt | B49: =B11*Inputs!$B$39/12*(1+Inputs!$B$43)^INT((1-1)/12) -> 0 | C49: =C11*Inputs!$B$39/12*(1+Inputs!$B$43)^INT((2-1)/12) -> 0 | D49: =D11*Inputs!$B$39/12*(1+Inputs!$B$43)^INT((3-1)/12) -> 0 | E49: =E11*Inputs!$B$39/12*(1+Inputs!$B$43)^INT((4-1)/12) -> 0 | F49: =F11*Inputs!$B$39/12*(1+Inputs!$B$43)^INT((5-1)/12) -> 0 | G49: =G11*Inputs!$B$39/12*(1+Inputs!$B$43)^INT((6-1)/12) -> 0 | H49: =H11*Inputs!$B$39/12*(1+Inputs!$B$43)^INT((7-1)/12) -> 0 | I49: =I11*Inputs!$B$39/12*(1+Inputs!$B$43)^INT((8-1)/12) -> 0 | J49: =J11*Inputs!$B$39/12*(1+Inputs!$B$43)^INT((9-1)/12) -> 0 | K49: =K11*Inputs!$B$39/12*(1+Inputs!$B$43)^INT((10-1)/12) -> 10833.333 | L49: =L11*Inputs!$B$39/12*(1+Inputs!$B$43)^INT((11-1)/12) -> 10833.333 | M49: =M11*Inputs!$B$39/12*(1+Inputs!$B$43)^INT((12-1)/12) -> 10833.333 | N49: =N11*Inputs!$B$39/12*(1+Inputs!$B$43)^INT((13-1)/12) -> 11375 | O49: =O11*Inputs!$B$39/12*(1+Inputs!$B$43)^INT((14-1)/12) -> 11375 | P49: =P11*Inputs!$B$39/12*(1+Inputs!$B$43)^INT((15-1)/12) -> 11375 | Q49: =Q11*Inputs!$B$39/12*(1+Inputs!$B$43)^INT((16-1)/12) -> 11375 | R49: =R11*Inputs!$B$39/12*(1+Inputs!$B$43)^INT((17-1)/12) -> 11375 | S49: =S11*Inputs!$B$39/12*(1+Inputs!$B$43)^INT((18-1)/12) -> 11375 | T49: =T11*Inputs!$B$39/12*(1+Inputs!$B$43)^INT((19-1)/12) -> 11375 | U49: =U11*Inputs!$B$39/12*(1+Inputs!$B$43)^INT((20-1)/12) -> 11375 | V49: =V11*Inputs!$B$39/12*(1+Inputs!$B$43)^INT((21-1)/12) -> 11375 | W49: =W11*Inputs!$B$39/12*(1+Inputs!$B$43)^INT((22-1)/12) -> 11375 | X49: =X11*Inputs!$B$39/12*(1+Inputs!$B$43)^INT((23-1)/12) -> 11375 | Y49: =Y11*Inputs!$B$39/12*(1+Inputs!$B$43)^INT((24-1)/12) -> 11375 | Z49: =Z11*Inputs!$B$39/12*(1+Inputs!$B$43)^INT((25-1)/12) -> 11943.75 | AA49: =AA11*Inputs!$B$39/12*(1+Inputs!$B$43)^INT((26-1)/12) -> 11943.75 | AB49: =AB11*Inputs!$B$39/12*(1+Inputs!$B$43)^INT((27-1)/12) -> 11943.75 | AC49: =AC11*Inputs!$B$39/12*(1+Inputs!$B$43)^INT((28-1)/12) -> 11943.75 | AD49: =AD11*Inputs!$B$39/12*(1+Inputs!$B$43)^INT((29-1)/12) -> 11943.75 | AE49: =AE11*Inputs!$B$39/12*(1+Inputs!$B$43)^INT((30-1)/12) -> 11943.75 | AF49: =AF11*Inputs!$B$39/12*(1+Inputs!$B$43)^INT((31-1)/12) -> 11943.75 | AG49: =AG11*Inputs!$B$39/12*(1+Inputs!$B$43)^INT((32-1)/12) -> 11943.75 | AH49: =AH11*Inputs!$B$39/12*(1+Inputs!$B$43)^INT((33-1)/12) -> 11943.75 | AI49: =AI11*Inputs!$B$39/12*(1+Inputs!$B$43)^INT((34-1)/12) -> 11943.75 | AJ49: =AJ11*Inputs!$B$39/12*(1+Inputs!$B$43)^INT((35-1)/12) -> 11943.75 | AK49: =AK11*Inputs!$B$39/12*(1+Inputs!$B$43)^INT((36-1)/12) -> 11943.75 | AL49: =AL11*Inputs!$B$39/12*(1+Inputs!$B$43)^INT((37-1)/12) -> 12540.938 | AM49: =AM11*Inputs!$B$39/12*(1+Inputs!$B$43)^INT((38-1)/12) -> 12540.938 | AN49: =AN11*Inputs!$B$39/12*(1+Inputs!$B$43)^INT((39-1)/12) -> 12540.938 | AO49: =AO11*Inputs!$B$39/12*(1+Inputs!$B$43)^INT((40-1)/12) -> 12540.938 | AP49: =AP11*Inputs!$B$39/12*(1+Inputs!$B$43)^INT((41-1)/12) -> 12540.938 | AQ49: =AQ11*Inputs!$B$39/12*(1+Inputs!$B$43)^INT((42-1)/12) -> 12540.938 | AR49: =AR11*Inputs!$B$39/12*(1+Inputs!$B$43)^INT((43-1)/12) -> 12540.938 | AS49: =AS11*Inputs!$B$39/12*(1+Inputs!$B$43)^INT((44-1)/12) -> 12540.938 | AT49: =AT11*Inputs!$B$39/12*(1+Inputs!$B$43)^INT((45-1)/12) -> 12540.938 | AU49: =AU11*Inputs!$B$39/12*(1+Inputs!$B$43)^INT((46-1)/12) -> 12540.938 | AV49: =AV11*Inputs!$B$39/12*(1+Inputs!$B$43)^INT((47-1)/12) -> 12540.938 | AW49: =AW11*Inputs!$B$39/12*(1+Inputs!$B$43)^INT((48-1)/12) -> 12540.938 | AX49: =AX11*Inputs!$B$39/12*(1+Inputs!$B$43)^INT((49-1)/12) -> 13167.984 | AY49: =AY11*Inputs!$B$39/12*(1+Inputs!$B$43)^INT((50-1)/12) -> 13167.984 | AZ49: =AZ11*Inputs!$B$39/12*(1+Inputs!$B$43)^INT((51-1)/12) -> 13167.984 | BA49: =BA11*Inputs!$B$39/12*(1+Inputs!$B$43)^INT((52-1)/12) -> 13167.984
A50: 2. Sales Rep Gehalt | B50: =B12*Inputs!$B$39/12*(1+Inputs!$B$43)^INT((1-1)/12) -> 0 | C50: =C12*Inputs!$B$39/12*(1+Inputs!$B$43)^INT((2-1)/12) -> 0 | D50: =D12*Inputs!$B$39/12*(1+Inputs!$B$43)^INT((3-1)/12) -> 0 | E50: =E12*Inputs!$B$39/12*(1+Inputs!$B$43)^INT((4-1)/12) -> 0 | F50: =F12*Inputs!$B$39/12*(1+Inputs!$B$43)^INT((5-1)/12) -> 0 | G50: =G12*Inputs!$B$39/12*(1+Inputs!$B$43)^INT((6-1)/12) -> 0 | H50: =H12*Inputs!$B$39/12*(1+Inputs!$B$43)^INT((7-1)/12) -> 0 | I50: =I12*Inputs!$B$39/12*(1+Inputs!$B$43)^INT((8-1)/12) -> 0 | J50: =J12*Inputs!$B$39/12*(1+Inputs!$B$43)^INT((9-1)/12) -> 0 | K50: =K12*Inputs!$B$39/12*(1+Inputs!$B$43)^INT((10-1)/12) -> 0 | L50: =L12*Inputs!$B$39/12*(1+Inputs!$B$43)^INT((11-1)/12) -> 0 | M50: =M12*Inputs!$B$39/12*(1+Inputs!$B$43)^INT((12-1)/12) -> 0 | N50: =N12*Inputs!$B$39/12*(1+Inputs!$B$43)^INT((13-1)/12) -> 0 | O50: =O12*Inputs!$B$39/12*(1+Inputs!$B$43)^INT((14-1)/12) -> 0 | P50: =P12*Inputs!$B$39/12*(1+Inputs!$B$43)^INT((15-1)/12) -> 0 | Q50: =Q12*Inputs!$B$39/12*(1+Inputs!$B$43)^INT((16-1)/12) -> 0 | R50: =R12*Inputs!$B$39/12*(1+Inputs!$B$43)^INT((17-1)/12) -> 0 | S50: =S12*Inputs!$B$39/12*(1+Inputs!$B$43)^INT((18-1)/12) -> 11375 | T50: =T12*Inputs!$B$39/12*(1+Inputs!$B$43)^INT((19-1)/12) -> 11375 | U50: =U12*Inputs!$B$39/12*(1+Inputs!$B$43)^INT((20-1)/12) -> 11375 | V50: =V12*Inputs!$B$39/12*(1+Inputs!$B$43)^INT((21-1)/12) -> 11375 | W50: =W12*Inputs!$B$39/12*(1+Inputs!$B$43)^INT((22-1)/12) -> 11375 | X50: =X12*Inputs!$B$39/12*(1+Inputs!$B$43)^INT((23-1)/12) -> 11375 | Y50: =Y12*Inputs!$B$39/12*(1+Inputs!$B$43)^INT((24-1)/12) -> 11375 | Z50: =Z12*Inputs!$B$39/12*(1+Inputs!$B$43)^INT((25-1)/12) -> 11943.75 | AA50: =AA12*Inputs!$B$39/12*(1+Inputs!$B$43)^INT((26-1)/12) -> 11943.75 | AB50: =AB12*Inputs!$B$39/12*(1+Inputs!$B$43)^INT((27-1)/12) -> 11943.75 | AC50: =AC12*Inputs!$B$39/12*(1+Inputs!$B$43)^INT((28-1)/12) -> 11943.75 | AD50: =AD12*Inputs!$B$39/12*(1+Inputs!$B$43)^INT((29-1)/12) -> 11943.75 | AE50: =AE12*Inputs!$B$39/12*(1+Inputs!$B$43)^INT((30-1)/12) -> 11943.75 | AF50: =AF12*Inputs!$B$39/12*(1+Inputs!$B$43)^INT((31-1)/12) -> 11943.75 | AG50: =AG12*Inputs!$B$39/12*(1+Inputs!$B$43)^INT((32-1)/12) -> 11943.75 | AH50: =AH12*Inputs!$B$39/12*(1+Inputs!$B$43)^INT((33-1)/12) -> 11943.75 | AI50: =AI12*Inputs!$B$39/12*(1+Inputs!$B$43)^INT((34-1)/12) -> 11943.75 | AJ50: =AJ12*Inputs!$B$39/12*(1+Inputs!$B$43)^INT((35-1)/12) -> 11943.75 | AK50: =AK12*Inputs!$B$39/12*(1+Inputs!$B$43)^INT((36-1)/12) -> 11943.75 | AL50: =AL12*Inputs!$B$39/12*(1+Inputs!$B$43)^INT((37-1)/12) -> 12540.938 | AM50: =AM12*Inputs!$B$39/12*(1+Inputs!$B$43)^INT((38-1)/12) -> 12540.938 | AN50: =AN12*Inputs!$B$39/12*(1+Inputs!$B$43)^INT((39-1)/12) -> 12540.938 | AO50: =AO12*Inputs!$B$39/12*(1+Inputs!$B$43)^INT((40-1)/12) -> 12540.938 | AP50: =AP12*Inputs!$B$39/12*(1+Inputs!$B$43)^INT((41-1)/12) -> 12540.938 | AQ50: =AQ12*Inputs!$B$39/12*(1+Inputs!$B$43)^INT((42-1)/12) -> 12540.938 | AR50: =AR12*Inputs!$B$39/12*(1+Inputs!$B$43)^INT((43-1)/12) -> 12540.938 | AS50: =AS12*Inputs!$B$39/12*(1+Inputs!$B$43)^INT((44-1)/12) -> 12540.938 | AT50: =AT12*Inputs!$B$39/12*(1+Inputs!$B$43)^INT((45-1)/12) -> 12540.938 | AU50: =AU12*Inputs!$B$39/12*(1+Inputs!$B$43)^INT((46-1)/12) -> 12540.938 | AV50: =AV12*Inputs!$B$39/12*(1+Inputs!$B$43)^INT((47-1)/12) -> 12540.938 | AW50: =AW12*Inputs!$B$39/12*(1+Inputs!$B$43)^INT((48-1)/12) -> 12540.938 | AX50: =AX12*Inputs!$B$39/12*(1+Inputs!$B$43)^INT((49-1)/12) -> 13167.984 | AY50: =AY12*Inputs!$B$39/12*(1+Inputs!$B$43)^INT((50-1)/12) -> 13167.984 | AZ50: =AZ12*Inputs!$B$39/12*(1+Inputs!$B$43)^INT((51-1)/12) -> 13167.984 | BA50: =BA12*Inputs!$B$39/12*(1+Inputs!$B$43)^INT((52-1)/12) -> 13167.984
A51: 1. Customer Success Gehalt | B51: =B13*Inputs!$B$41/12*(1+Inputs!$B$43)^INT((1-1)/12) -> 0 | C51: =C13*Inputs!$B$41/12*(1+Inputs!$B$43)^INT((2-1)/12) -> 0 | D51: =D13*Inputs!$B$41/12*(1+Inputs!$B$43)^INT((3-1)/12) -> 0 | E51: =E13*Inputs!$B$41/12*(1+Inputs!$B$43)^INT((4-1)/12) -> 0 | F51: =F13*Inputs!$B$41/12*(1+Inputs!$B$43)^INT((5-1)/12) -> 0 | G51: =G13*Inputs!$B$41/12*(1+Inputs!$B$43)^INT((6-1)/12) -> 0 | H51: =H13*Inputs!$B$41/12*(1+Inputs!$B$43)^INT((7-1)/12) -> 0 | I51: =I13*Inputs!$B$41/12*(1+Inputs!$B$43)^INT((8-1)/12) -> 0 | J51: =J13*Inputs!$B$41/12*(1+Inputs!$B$43)^INT((9-1)/12) -> 0 | K51: =K13*Inputs!$B$41/12*(1+Inputs!$B$43)^INT((10-1)/12) -> 0 | L51: =L13*Inputs!$B$41/12*(1+Inputs!$B$43)^INT((11-1)/12) -> 0 | M51: =M13*Inputs!$B$41/12*(1+Inputs!$B$43)^INT((12-1)/12) -> 5416.6667 | N51: =N13*Inputs!$B$41/12*(1+Inputs!$B$43)^INT((13-1)/12) -> 5687.5 | O51: =O13*Inputs!$B$41/12*(1+Inputs!$B$43)^INT((14-1)/12) -> 5687.5 | P51: =P13*Inputs!$B$41/12*(1+Inputs!$B$43)^INT((15-1)/12) -> 5687.5 | Q51: =Q13*Inputs!$B$41/12*(1+Inputs!$B$43)^INT((16-1)/12) -> 5687.5 | R51: =R13*Inputs!$B$41/12*(1+Inputs!$B$43)^INT((17-1)/12) -> 5687.5 | S51: =S13*Inputs!$B$41/12*(1+Inputs!$B$43)^INT((18-1)/12) -> 5687.5 | T51: =T13*Inputs!$B$41/12*(1+Inputs!$B$43)^INT((19-1)/12) -> 5687.5 | U51: =U13*Inputs!$B$41/12*(1+Inputs!$B$43)^INT((20-1)/12) -> 5687.5 | V51: =V13*Inputs!$B$41/12*(1+Inputs!$B$43)^INT((21-1)/12) -> 5687.5 | W51: =W13*Inputs!$B$41/12*(1+Inputs!$B$43)^INT((22-1)/12) -> 5687.5 | X51: =X13*Inputs!$B$41/12*(1+Inputs!$B$43)^INT((23-1)/12) -> 5687.5 | Y51: =Y13*Inputs!$B$41/12*(1+Inputs!$B$43)^INT((24-1)/12) -> 5687.5 | Z51: =Z13*Inputs!$B$41/12*(1+Inputs!$B$43)^INT((25-1)/12) -> 5971.875 | AA51: =AA13*Inputs!$B$41/12*(1+Inputs!$B$43)^INT((26-1)/12) -> 5971.875 | AB51: =AB13*Inputs!$B$41/12*(1+Inputs!$B$43)^INT((27-1)/12) -> 5971.875 | AC51: =AC13*Inputs!$B$41/12*(1+Inputs!$B$43)^INT((28-1)/12) -> 5971.875 | AD51: =AD13*Inputs!$B$41/12*(1+Inputs!$B$43)^INT((29-1)/12) -> 5971.875 | AE51: =AE13*Inputs!$B$41/12*(1+Inputs!$B$43)^INT((30-1)/12) -> 5971.875 | AF51: =AF13*Inputs!$B$41/12*(1+Inputs!$B$43)^INT((31-1)/12) -> 5971.875 | AG51: =AG13*Inputs!$B$41/12*(1+Inputs!$B$43)^INT((32-1)/12) -> 5971.875 | AH51: =AH13*Inputs!$B$41/12*(1+Inputs!$B$43)^INT((33-1)/12) -> 5971.875 | AI51: =AI13*Inputs!$B$41/12*(1+Inputs!$B$43)^INT((34-1)/12) -> 5971.875 | AJ51: =AJ13*Inputs!$B$41/12*(1+Inputs!$B$43)^INT((35-1)/12) -> 5971.875 | AK51: =AK13*Inputs!$B$41/12*(1+Inputs!$B$43)^INT((36-1)/12) -> 5971.875 | AL51: =AL13*Inputs!$B$41/12*(1+Inputs!$B$43)^INT((37-1)/12) -> 6270.4688 | AM51: =AM13*Inputs!$B$41/12*(1+Inputs!$B$43)^INT((38-1)/12) -> 6270.4688 | AN51: =AN13*Inputs!$B$41/12*(1+Inputs!$B$43)^INT((39-1)/12) -> 6270.4688 | AO51: =AO13*Inputs!$B$41/12*(1+Inputs!$B$43)^INT((40-1)/12) -> 6270.4688 | AP51: =AP13*Inputs!$B$41/12*(1+Inputs!$B$43)^INT((41-1)/12) -> 6270.4688 | AQ51: =AQ13*Inputs!$B$41/12*(1+Inputs!$B$43)^INT((42-1)/12) -> 6270.4688 | AR51: =AR13*Inputs!$B$41/12*(1+Inputs!$B$43)^INT((43-1)/12) -> 6270.4688 | AS51: =AS13*Inputs!$B$41/12*(1+Inputs!$B$43)^INT((44-1)/12) -> 6270.4688 | AT51: =AT13*Inputs!$B$41/12*(1+Inputs!$B$43)^INT((45-1)/12) -> 6270.4688 | AU51: =AU13*Inputs!$B$41/12*(1+Inputs!$B$43)^INT((46-1)/12) -> 6270.4688 | AV51: =AV13*Inputs!$B$41/12*(1+Inputs!$B$43)^INT((47-1)/12) -> 6270.4688 | AW51: =AW13*Inputs!$B$41/12*(1+Inputs!$B$43)^INT((48-1)/12) -> 6270.4688 | AX51: =AX13*Inputs!$B$41/12*(1+Inputs!$B$43)^INT((49-1)/12) -> 6583.9922 | AY51: =AY13*Inputs!$B$41/12*(1+Inputs!$B$43)^INT((50-1)/12) -> 6583.9922 | AZ51: =AZ13*Inputs!$B$41/12*(1+Inputs!$B$43)^INT((51-1)/12) -> 6583.9922 | BA51: =BA13*Inputs!$B$41/12*(1+Inputs!$B$43)^INT((52-1)/12) -> 6583.9922
A52: 1. Marketing Manager Gehalt | B52: =B14*Inputs!$B$40/12*(1+Inputs!$B$43)^INT((1-1)/12) -> 0 | C52: =C14*Inputs!$B$40/12*(1+Inputs!$B$43)^INT((2-1)/12) -> 0 | D52: =D14*Inputs!$B$40/12*(1+Inputs!$B$43)^INT((3-1)/12) -> 0 | E52: =E14*Inputs!$B$40/12*(1+Inputs!$B$43)^INT((4-1)/12) -> 0 | F52: =F14*Inputs!$B$40/12*(1+Inputs!$B$43)^INT((5-1)/12) -> 0 | G52: =G14*Inputs!$B$40/12*(1+Inputs!$B$43)^INT((6-1)/12) -> 0 | H52: =H14*Inputs!$B$40/12*(1+Inputs!$B$43)^INT((7-1)/12) -> 0 | I52: =I14*Inputs!$B$40/12*(1+Inputs!$B$43)^INT((8-1)/12) -> 0 | J52: =J14*Inputs!$B$40/12*(1+Inputs!$B$43)^INT((9-1)/12) -> 0 | K52: =K14*Inputs!$B$40/12*(1+Inputs!$B$43)^INT((10-1)/12) -> 0 | L52: =L14*Inputs!$B$40/12*(1+Inputs!$B$43)^INT((11-1)/12) -> 5416.6667 | M52: =M14*Inputs!$B$40/12*(1+Inputs!$B$43)^INT((12-1)/12) -> 5416.6667 | N52: =N14*Inputs!$B$40/12*(1+Inputs!$B$43)^INT((13-1)/12) -> 5687.5 | O52: =O14*Inputs!$B$40/12*(1+Inputs!$B$43)^INT((14-1)/12) -> 5687.5 | P52: =P14*Inputs!$B$40/12*(1+Inputs!$B$43)^INT((15-1)/12) -> 5687.5 | Q52: =Q14*Inputs!$B$40/12*(1+Inputs!$B$43)^INT((16-1)/12) -> 5687.5 | R52: =R14*Inputs!$B$40/12*(1+Inputs!$B$43)^INT((17-1)/12) -> 5687.5 | S52: =S14*Inputs!$B$40/12*(1+Inputs!$B$43)^INT((18-1)/12) -> 5687.5 | T52: =T14*Inputs!$B$40/12*(1+Inputs!$B$43)^INT((19-1)/12) -> 5687.5 | U52: =U14*Inputs!$B$40/12*(1+Inputs!$B$43)^INT((20-1)/12) -> 5687.5 | V52: =V14*Inputs!$B$40/12*(1+Inputs!$B$43)^INT((21-1)/12) -> 5687.5 | W52: =W14*Inputs!$B$40/12*(1+Inputs!$B$43)^INT((22-1)/12) -> 5687.5 | X52: =X14*Inputs!$B$40/12*(1+Inputs!$B$43)^INT((23-1)/12) -> 5687.5 | Y52: =Y14*Inputs!$B$40/12*(1+Inputs!$B$43)^INT((24-1)/12) -> 5687.5 | Z52: =Z14*Inputs!$B$40/12*(1+Inputs!$B$43)^INT((25-1)/12) -> 5971.875 | AA52: =AA14*Inputs!$B$40/12*(1+Inputs!$B$43)^INT((26-1)/12) -> 5971.875 | AB52: =AB14*Inputs!$B$40/12*(1+Inputs!$B$43)^INT((27-1)/12) -> 5971.875 | AC52: =AC14*Inputs!$B$40/12*(1+Inputs!$B$43)^INT((28-1)/12) -> 5971.875 | AD52: =AD14*Inputs!$B$40/12*(1+Inputs!$B$43)^INT((29-1)/12) -> 5971.875 | AE52: =AE14*Inputs!$B$40/12*(1+Inputs!$B$43)^INT((30-1)/12) -> 5971.875 | AF52: =AF14*Inputs!$B$40/12*(1+Inputs!$B$43)^INT((31-1)/12) -> 5971.875 | AG52: =AG14*Inputs!$B$40/12*(1+Inputs!$B$43)^INT((32-1)/12) -> 5971.875 | AH52: =AH14*Inputs!$B$40/12*(1+Inputs!$B$43)^INT((33-1)/12) -> 5971.875 | AI52: =AI14*Inputs!$B$40/12*(1+Inputs!$B$43)^INT((34-1)/12) -> 5971.875 | AJ52: =AJ14*Inputs!$B$40/12*(1+Inputs!$B$43)^INT((35-1)/12) -> 5971.875 | AK52: =AK14*Inputs!$B$40/12*(1+Inputs!$B$43)^INT((36-1)/12) -> 5971.875 | AL52: =AL14*Inputs!$B$40/12*(1+Inputs!$B$43)^INT((37-1)/12) -> 6270.4688 | AM52: =AM14*Inputs!$B$40/12*(1+Inputs!$B$43)^INT((38-1)/12) -> 6270.4688 | AN52: =AN14*Inputs!$B$40/12*(1+Inputs!$B$43)^INT((39-1)/12) -> 6270.4688 | AO52: =AO14*Inputs!$B$40/12*(1+Inputs!$B$43)^INT((40-1)/12) -> 6270.4688 | AP52: =AP14*Inputs!$B$40/12*(1+Inputs!$B$43)^INT((41-1)/12) -> 6270.4688 | AQ52: =AQ14*Inputs!$B$40/12*(1+Inputs!$B$43)^INT((42-1)/12) -> 6270.4688 | AR52: =AR14*Inputs!$B$40/12*(1+Inputs!$B$43)^INT((43-1)/12) -> 6270.4688 | AS52: =AS14*Inputs!$B$40/12*(1+Inputs!$B$43)^INT((44-1)/12) -> 6270.4688 | AT52: =AT14*Inputs!$B$40/12*(1+Inputs!$B$43)^INT((45-1)/12) -> 6270.4688 | AU52: =AU14*Inputs!$B$40/12*(1+Inputs!$B$43)^INT((46-1)/12) -> 6270.4688 | AV52: =AV14*Inputs!$B$40/12*(1+Inputs!$B$43)^INT((47-1)/12) -> 6270.4688 | AW52: =AW14*Inputs!$B$40/12*(1+Inputs!$B$43)^INT((48-1)/12) -> 6270.4688 | AX52: =AX14*Inputs!$B$40/12*(1+Inputs!$B$43)^INT((49-1)/12) -> 6583.9922 | AY52: =AY14*Inputs!$B$40/12*(1+Inputs!$B$43)^INT((50-1)/12) -> 6583.9922 | AZ52: =AZ14*Inputs!$B$40/12*(1+Inputs!$B$43)^INT((51-1)/12) -> 6583.9922 | BA52: =BA14*Inputs!$B$40/12*(1+Inputs!$B$43)^INT((52-1)/12) -> 6583.9922
A53: 1. Product Manager Gehalt | B53: =B15*Inputs!$B$38/12*(1+Inputs!$B$43)^INT((1-1)/12) -> 0 | C53: =C15*Inputs!$B$38/12*(1+Inputs!$B$43)^INT((2-1)/12) -> 0 | D53: =D15*Inputs!$B$38/12*(1+Inputs!$B$43)^INT((3-1)/12) -> 0 | E53: =E15*Inputs!$B$38/12*(1+Inputs!$B$43)^INT((4-1)/12) -> 0 | F53: =F15*Inputs!$B$38/12*(1+Inputs!$B$43)^INT((5-1)/12) -> 0 | G53: =G15*Inputs!$B$38/12*(1+Inputs!$B$43)^INT((6-1)/12) -> 0 | H53: =H15*Inputs!$B$38/12*(1+Inputs!$B$43)^INT((7-1)/12) -> 0 | I53: =I15*Inputs!$B$38/12*(1+Inputs!$B$43)^INT((8-1)/12) -> 0 | J53: =J15*Inputs!$B$38/12*(1+Inputs!$B$43)^INT((9-1)/12) -> 0 | K53: =K15*Inputs!$B$38/12*(1+Inputs!$B$43)^INT((10-1)/12) -> 0 | L53: =L15*Inputs!$B$38/12*(1+Inputs!$B$43)^INT((11-1)/12) -> 0 | M53: =M15*Inputs!$B$38/12*(1+Inputs!$B$43)^INT((12-1)/12) -> 0 | N53: =N15*Inputs!$B$38/12*(1+Inputs!$B$43)^INT((13-1)/12) -> 7000 | O53: =O15*Inputs!$B$38/12*(1+Inputs!$B$43)^INT((14-1)/12) -> 7000 | P53: =P15*Inputs!$B$38/12*(1+Inputs!$B$43)^INT((15-1)/12) -> 7000 | Q53: =Q15*Inputs!$B$38/12*(1+Inputs!$B$43)^INT((16-1)/12) -> 7000 | R53: =R15*Inputs!$B$38/12*(1+Inputs!$B$43)^INT((17-1)/12) -> 7000 | S53: =S15*Inputs!$B$38/12*(1+Inputs!$B$43)^INT((18-1)/12) -> 7000 | T53: =T15*Inputs!$B$38/12*(1+Inputs!$B$43)^INT((19-1)/12) -> 7000 | U53: =U15*Inputs!$B$38/12*(1+Inputs!$B$43)^INT((20-1)/12) -> 7000 | V53: =V15*Inputs!$B$38/12*(1+Inputs!$B$43)^INT((21-1)/12) -> 7000 | W53: =W15*Inputs!$B$38/12*(1+Inputs!$B$43)^INT((22-1)/12) -> 7000 | X53: =X15*Inputs!$B$38/12*(1+Inputs!$B$43)^INT((23-1)/12) -> 7000 | Y53: =Y15*Inputs!$B$38/12*(1+Inputs!$B$43)^INT((24-1)/12) -> 7000 | Z53: =Z15*Inputs!$B$38/12*(1+Inputs!$B$43)^INT((25-1)/12) -> 7350 | AA53: =AA15*Inputs!$B$38/12*(1+Inputs!$B$43)^INT((26-1)/12) -> 7350 | AB53: =AB15*Inputs!$B$38/12*(1+Inputs!$B$43)^INT((27-1)/12) -> 7350 | AC53: =AC15*Inputs!$B$38/12*(1+Inputs!$B$43)^INT((28-1)/12) -> 7350 | AD53: =AD15*Inputs!$B$38/12*(1+Inputs!$B$43)^INT((29-1)/12) -> 7350 | AE53: =AE15*Inputs!$B$38/12*(1+Inputs!$B$43)^INT((30-1)/12) -> 7350 | AF53: =AF15*Inputs!$B$38/12*(1+Inputs!$B$43)^INT((31-1)/12) -> 7350 | AG53: =AG15*Inputs!$B$38/12*(1+Inputs!$B$43)^INT((32-1)/12) -> 7350 | AH53: =AH15*Inputs!$B$38/12*(1+Inputs!$B$43)^INT((33-1)/12) -> 7350 | AI53: =AI15*Inputs!$B$38/12*(1+Inputs!$B$43)^INT((34-1)/12) -> 7350 | AJ53: =AJ15*Inputs!$B$38/12*(1+Inputs!$B$43)^INT((35-1)/12) -> 7350 | AK53: =AK15*Inputs!$B$38/12*(1+Inputs!$B$43)^INT((36-1)/12) -> 7350 | AL53: =AL15*Inputs!$B$38/12*(1+Inputs!$B$43)^INT((37-1)/12) -> 7717.5 | AM53: =AM15*Inputs!$B$38/12*(1+Inputs!$B$43)^INT((38-1)/12) -> 7717.5 | AN53: =AN15*Inputs!$B$38/12*(1+Inputs!$B$43)^INT((39-1)/12) -> 7717.5 | AO53: =AO15*Inputs!$B$38/12*(1+Inputs!$B$43)^INT((40-1)/12) -> 7717.5 | AP53: =AP15*Inputs!$B$38/12*(1+Inputs!$B$43)^INT((41-1)/12) -> 7717.5 | AQ53: =AQ15*Inputs!$B$38/12*(1+Inputs!$B$43)^INT((42-1)/12) -> 7717.5 | AR53: =AR15*Inputs!$B$38/12*(1+Inputs!$B$43)^INT((43-1)/12) -> 7717.5 | AS53: =AS15*Inputs!$B$38/12*(1+Inputs!$B$43)^INT((44-1)/12) -> 7717.5 | AT53: =AT15*Inputs!$B$38/12*(1+Inputs!$B$43)^INT((45-1)/12) -> 7717.5 | AU53: =AU15*Inputs!$B$38/12*(1+Inputs!$B$43)^INT((46-1)/12) -> 7717.5 | AV53: =AV15*Inputs!$B$38/12*(1+Inputs!$B$43)^INT((47-1)/12) -> 7717.5 | AW53: =AW15*Inputs!$B$38/12*(1+Inputs!$B$43)^INT((48-1)/12) -> 7717.5 | AX53: =AX15*Inputs!$B$38/12*(1+Inputs!$B$43)^INT((49-1)/12) -> 8103.375 | AY53: =AY15*Inputs!$B$38/12*(1+Inputs!$B$43)^INT((50-1)/12) -> 8103.375 | AZ53: =AZ15*Inputs!$B$38/12*(1+Inputs!$B$43)^INT((51-1)/12) -> 8103.375 | BA53: =BA15*Inputs!$B$38/12*(1+Inputs!$B$43)^INT((52-1)/12) -> 8103.375
A54: 1. Office Manager Gehalt | B54: =B16*Inputs!$B$42/12*(1+Inputs!$B$43)^INT((1-1)/12) -> 0 | C54: =C16*Inputs!$B$42/12*(1+Inputs!$B$43)^INT((2-1)/12) -> 0 | D54: =D16*Inputs!$B$42/12*(1+Inputs!$B$43)^INT((3-1)/12) -> 0 | E54: =E16*Inputs!$B$42/12*(1+Inputs!$B$43)^INT((4-1)/12) -> 0 | F54: =F16*Inputs!$B$42/12*(1+Inputs!$B$43)^INT((5-1)/12) -> 0 | G54: =G16*Inputs!$B$42/12*(1+Inputs!$B$43)^INT((6-1)/12) -> 0 | H54: =H16*Inputs!$B$42/12*(1+Inputs!$B$43)^INT((7-1)/12) -> 0 | I54: =I16*Inputs!$B$42/12*(1+Inputs!$B$43)^INT((8-1)/12) -> 0 | J54: =J16*Inputs!$B$42/12*(1+Inputs!$B$43)^INT((9-1)/12) -> 0 | K54: =K16*Inputs!$B$42/12*(1+Inputs!$B$43)^INT((10-1)/12) -> 0 | L54: =L16*Inputs!$B$42/12*(1+Inputs!$B$43)^INT((11-1)/12) -> 0 | M54: =M16*Inputs!$B$42/12*(1+Inputs!$B$43)^INT((12-1)/12) -> 0 | N54: =N16*Inputs!$B$42/12*(1+Inputs!$B$43)^INT((13-1)/12) -> 0 | O54: =O16*Inputs!$B$42/12*(1+Inputs!$B$43)^INT((14-1)/12) -> 3937.5 | P54: =P16*Inputs!$B$42/12*(1+Inputs!$B$43)^INT((15-1)/12) -> 3937.5 | Q54: =Q16*Inputs!$B$42/12*(1+Inputs!$B$43)^INT((16-1)/12) -> 3937.5 | R54: =R16*Inputs!$B$42/12*(1+Inputs!$B$43)^INT((17-1)/12) -> 3937.5 | S54: =S16*Inputs!$B$42/12*(1+Inputs!$B$43)^INT((18-1)/12) -> 3937.5 | T54: =T16*Inputs!$B$42/12*(1+Inputs!$B$43)^INT((19-1)/12) -> 3937.5 | U54: =U16*Inputs!$B$42/12*(1+Inputs!$B$43)^INT((20-1)/12) -> 3937.5 | V54: =V16*Inputs!$B$42/12*(1+Inputs!$B$43)^INT((21-1)/12) -> 3937.5 | W54: =W16*Inputs!$B$42/12*(1+Inputs!$B$43)^INT((22-1)/12) -> 3937.5 | X54: =X16*Inputs!$B$42/12*(1+Inputs!$B$43)^INT((23-1)/12) -> 3937.5 | Y54: =Y16*Inputs!$B$42/12*(1+Inputs!$B$43)^INT((24-1)/12) -> 3937.5 | Z54: =Z16*Inputs!$B$42/12*(1+Inputs!$B$43)^INT((25-1)/12) -> 4134.375 | AA54: =AA16*Inputs!$B$42/12*(1+Inputs!$B$43)^INT((26-1)/12) -> 4134.375 | AB54: =AB16*Inputs!$B$42/12*(1+Inputs!$B$43)^INT((27-1)/12) -> 4134.375 | AC54: =AC16*Inputs!$B$42/12*(1+Inputs!$B$43)^INT((28-1)/12) -> 4134.375 | AD54: =AD16*Inputs!$B$42/12*(1+Inputs!$B$43)^INT((29-1)/12) -> 4134.375 | AE54: =AE16*Inputs!$B$42/12*(1+Inputs!$B$43)^INT((30-1)/12) -> 4134.375 | AF54: =AF16*Inputs!$B$42/12*(1+Inputs!$B$43)^INT((31-1)/12) -> 4134.375 | AG54: =AG16*Inputs!$B$42/12*(1+Inputs!$B$43)^INT((32-1)/12) -> 4134.375 | AH54: =AH16*Inputs!$B$42/12*(1+Inputs!$B$43)^INT((33-1)/12) -> 4134.375 | AI54: =AI16*Inputs!$B$42/12*(1+Inputs!$B$43)^INT((34-1)/12) -> 4134.375 | AJ54: =AJ16*Inputs!$B$42/12*(1+Inputs!$B$43)^INT((35-1)/12) -> 4134.375 | AK54: =AK16*Inputs!$B$42/12*(1+Inputs!$B$43)^INT((36-1)/12) -> 4134.375 | AL54: =AL16*Inputs!$B$42/12*(1+Inputs!$B$43)^INT((37-1)/12) -> 4341.0938 | AM54: =AM16*Inputs!$B$42/12*(1+Inputs!$B$43)^INT((38-1)/12) -> 4341.0938 | AN54: =AN16*Inputs!$B$42/12*(1+Inputs!$B$43)^INT((39-1)/12) -> 4341.0938 | AO54: =AO16*Inputs!$B$42/12*(1+Inputs!$B$43)^INT((40-1)/12) -> 4341.0938 | AP54: =AP16*Inputs!$B$42/12*(1+Inputs!$B$43)^INT((41-1)/12) -> 4341.0938 | AQ54: =AQ16*Inputs!$B$42/12*(1+Inputs!$B$43)^INT((42-1)/12) -> 4341.0938 | AR54: =AR16*Inputs!$B$42/12*(1+Inputs!$B$43)^INT((43-1)/12) -> 4341.0938 | AS54: =AS16*Inputs!$B$42/12*(1+Inputs!$B$43)^INT((44-1)/12) -> 4341.0938 | AT54: =AT16*Inputs!$B$42/12*(1+Inputs!$B$43)^INT((45-1)/12) -> 4341.0938 | AU54: =AU16*Inputs!$B$42/12*(1+Inputs!$B$43)^INT((46-1)/12) -> 4341.0938 | AV54: =AV16*Inputs!$B$42/12*(1+Inputs!$B$43)^INT((47-1)/12) -> 4341.0938 | AW54: =AW16*Inputs!$B$42/12*(1+Inputs!$B$43)^INT((48-1)/12) -> 4341.0938 | AX54: =AX16*Inputs!$B$42/12*(1+Inputs!$B$43)^INT((49-1)/12) -> 4558.1484 | AY54: =AY16*Inputs!$B$42/12*(1+Inputs!$B$43)^INT((50-1)/12) -> 4558.1484 | AZ54: =AZ16*Inputs!$B$42/12*(1+Inputs!$B$43)^INT((51-1)/12) -> 4558.1484 | BA54: =BA16*Inputs!$B$42/12*(1+Inputs!$B$43)^INT((52-1)/12) -> 4558.1484
A55: 3. Senior Engineer Gehalt | B55: =B17*Inputs!$B$35/12*(1+Inputs!$B$43)^INT((1-1)/12) -> 0 | C55: =C17*Inputs!$B$35/12*(1+Inputs!$B$43)^INT((2-1)/12) -> 0 | D55: =D17*Inputs!$B$35/12*(1+Inputs!$B$43)^INT((3-1)/12) -> 0 | E55: =E17*Inputs!$B$35/12*(1+Inputs!$B$43)^INT((4-1)/12) -> 0 | F55: =F17*Inputs!$B$35/12*(1+Inputs!$B$43)^INT((5-1)/12) -> 0 | G55: =G17*Inputs!$B$35/12*(1+Inputs!$B$43)^INT((6-1)/12) -> 0 | H55: =H17*Inputs!$B$35/12*(1+Inputs!$B$43)^INT((7-1)/12) -> 0 | I55: =I17*Inputs!$B$35/12*(1+Inputs!$B$43)^INT((8-1)/12) -> 0 | J55: =J17*Inputs!$B$35/12*(1+Inputs!$B$43)^INT((9-1)/12) -> 0 | K55: =K17*Inputs!$B$35/12*(1+Inputs!$B$43)^INT((10-1)/12) -> 0 | L55: =L17*Inputs!$B$35/12*(1+Inputs!$B$43)^INT((11-1)/12) -> 0 | M55: =M17*Inputs!$B$35/12*(1+Inputs!$B$43)^INT((12-1)/12) -> 0 | N55: =N17*Inputs!$B$35/12*(1+Inputs!$B$43)^INT((13-1)/12) -> 0 | O55: =O17*Inputs!$B$35/12*(1+Inputs!$B$43)^INT((14-1)/12) -> 0 | P55: =P17*Inputs!$B$35/12*(1+Inputs!$B$43)^INT((15-1)/12) -> 0 | Q55: =Q17*Inputs!$B$35/12*(1+Inputs!$B$43)^INT((16-1)/12) -> 0 | R55: =R17*Inputs!$B$35/12*(1+Inputs!$B$43)^INT((17-1)/12) -> 0 | S55: =S17*Inputs!$B$35/12*(1+Inputs!$B$43)^INT((18-1)/12) -> 7875 | T55: =T17*Inputs!$B$35/12*(1+Inputs!$B$43)^INT((19-1)/12) -> 7875 | U55: =U17*Inputs!$B$35/12*(1+Inputs!$B$43)^INT((20-1)/12) -> 7875 | V55: =V17*Inputs!$B$35/12*(1+Inputs!$B$43)^INT((21-1)/12) -> 7875 | W55: =W17*Inputs!$B$35/12*(1+Inputs!$B$43)^INT((22-1)/12) -> 7875 | X55: =X17*Inputs!$B$35/12*(1+Inputs!$B$43)^INT((23-1)/12) -> 7875 | Y55: =Y17*Inputs!$B$35/12*(1+Inputs!$B$43)^INT((24-1)/12) -> 7875 | Z55: =Z17*Inputs!$B$35/12*(1+Inputs!$B$43)^INT((25-1)/12) -> 8268.75 | AA55: =AA17*Inputs!$B$35/12*(1+Inputs!$B$43)^INT((26-1)/12) -> 8268.75 | AB55: =AB17*Inputs!$B$35/12*(1+Inputs!$B$43)^INT((27-1)/12) -> 8268.75 | AC55: =AC17*Inputs!$B$35/12*(1+Inputs!$B$43)^INT((28-1)/12) -> 8268.75 | AD55: =AD17*Inputs!$B$35/12*(1+Inputs!$B$43)^INT((29-1)/12) -> 8268.75 | AE55: =AE17*Inputs!$B$35/12*(1+Inputs!$B$43)^INT((30-1)/12) -> 8268.75 | AF55: =AF17*Inputs!$B$35/12*(1+Inputs!$B$43)^INT((31-1)/12) -> 8268.75 | AG55: =AG17*Inputs!$B$35/12*(1+Inputs!$B$43)^INT((32-1)/12) -> 8268.75 | AH55: =AH17*Inputs!$B$35/12*(1+Inputs!$B$43)^INT((33-1)/12) -> 8268.75 | AI55: =AI17*Inputs!$B$35/12*(1+Inputs!$B$43)^INT((34-1)/12) -> 8268.75 | AJ55: =AJ17*Inputs!$B$35/12*(1+Inputs!$B$43)^INT((35-1)/12) -> 8268.75 | AK55: =AK17*Inputs!$B$35/12*(1+Inputs!$B$43)^INT((36-1)/12) -> 8268.75 | AL55: =AL17*Inputs!$B$35/12*(1+Inputs!$B$43)^INT((37-1)/12) -> 8682.1875 | AM55: =AM17*Inputs!$B$35/12*(1+Inputs!$B$43)^INT((38-1)/12) -> 8682.1875 | AN55: =AN17*Inputs!$B$35/12*(1+Inputs!$B$43)^INT((39-1)/12) -> 8682.1875 | AO55: =AO17*Inputs!$B$35/12*(1+Inputs!$B$43)^INT((40-1)/12) -> 8682.1875 | AP55: =AP17*Inputs!$B$35/12*(1+Inputs!$B$43)^INT((41-1)/12) -> 8682.1875 | AQ55: =AQ17*Inputs!$B$35/12*(1+Inputs!$B$43)^INT((42-1)/12) -> 8682.1875 | AR55: =AR17*Inputs!$B$35/12*(1+Inputs!$B$43)^INT((43-1)/12) -> 8682.1875 | AS55: =AS17*Inputs!$B$35/12*(1+Inputs!$B$43)^INT((44-1)/12) -> 8682.1875 | AT55: =AT17*Inputs!$B$35/12*(1+Inputs!$B$43)^INT((45-1)/12) -> 8682.1875 | AU55: =AU17*Inputs!$B$35/12*(1+Inputs!$B$43)^INT((46-1)/12) -> 8682.1875 | AV55: =AV17*Inputs!$B$35/12*(1+Inputs!$B$43)^INT((47-1)/12) -> 8682.1875 | AW55: =AW17*Inputs!$B$35/12*(1+Inputs!$B$43)^INT((48-1)/12) -> 8682.1875 | AX55: =AX17*Inputs!$B$35/12*(1+Inputs!$B$43)^INT((49-1)/12) -> 9116.2969 | AY55: =AY17*Inputs!$B$35/12*(1+Inputs!$B$43)^INT((50-1)/12) -> 9116.2969 | AZ55: =AZ17*Inputs!$B$35/12*(1+Inputs!$B$43)^INT((51-1)/12) -> 9116.2969 | BA55: =BA17*Inputs!$B$35/12*(1+Inputs!$B$43)^INT((52-1)/12) -> 9116.2969
A56: 4. Senior Engineer Gehalt | B56: =B18*Inputs!$B$35/12*(1+Inputs!$B$43)^INT((1-1)/12) -> 0 | C56: =C18*Inputs!$B$35/12*(1+Inputs!$B$43)^INT((2-1)/12) -> 0 | D56: =D18*Inputs!$B$35/12*(1+Inputs!$B$43)^INT((3-1)/12) -> 0 | E56: =E18*Inputs!$B$35/12*(1+Inputs!$B$43)^INT((4-1)/12) -> 0 | F56: =F18*Inputs!$B$35/12*(1+Inputs!$B$43)^INT((5-1)/12) -> 0 | G56: =G18*Inputs!$B$35/12*(1+Inputs!$B$43)^INT((6-1)/12) -> 0 | H56: =H18*Inputs!$B$35/12*(1+Inputs!$B$43)^INT((7-1)/12) -> 0 | I56: =I18*Inputs!$B$35/12*(1+Inputs!$B$43)^INT((8-1)/12) -> 0 | J56: =J18*Inputs!$B$35/12*(1+Inputs!$B$43)^INT((9-1)/12) -> 0 | K56: =K18*Inputs!$B$35/12*(1+Inputs!$B$43)^INT((10-1)/12) -> 0 | L56: =L18*Inputs!$B$35/12*(1+Inputs!$B$43)^INT((11-1)/12) -> 0 | M56: =M18*Inputs!$B$35/12*(1+Inputs!$B$43)^INT((12-1)/12) -> 0 | N56: =N18*Inputs!$B$35/12*(1+Inputs!$B$43)^INT((13-1)/12) -> 0 | O56: =O18*Inputs!$B$35/12*(1+Inputs!$B$43)^INT((14-1)/12) -> 0 | P56: =P18*Inputs!$B$35/12*(1+Inputs!$B$43)^INT((15-1)/12) -> 0 | Q56: =Q18*Inputs!$B$35/12*(1+Inputs!$B$43)^INT((16-1)/12) -> 0 | R56: =R18*Inputs!$B$35/12*(1+Inputs!$B$43)^INT((17-1)/12) -> 0 | S56: =S18*Inputs!$B$35/12*(1+Inputs!$B$43)^INT((18-1)/12) -> 0 | T56: =T18*Inputs!$B$35/12*(1+Inputs!$B$43)^INT((19-1)/12) -> 0 | U56: =U18*Inputs!$B$35/12*(1+Inputs!$B$43)^INT((20-1)/12) -> 0 | V56: =V18*Inputs!$B$35/12*(1+Inputs!$B$43)^INT((21-1)/12) -> 0 | W56: =W18*Inputs!$B$35/12*(1+Inputs!$B$43)^INT((22-1)/12) -> 0 | X56: =X18*Inputs!$B$35/12*(1+Inputs!$B$43)^INT((23-1)/12) -> 0 | Y56: =Y18*Inputs!$B$35/12*(1+Inputs!$B$43)^INT((24-1)/12) -> 7875 | Z56: =Z18*Inputs!$B$35/12*(1+Inputs!$B$43)^INT((25-1)/12) -> 8268.75 | AA56: =AA18*Inputs!$B$35/12*(1+Inputs!$B$43)^INT((26-1)/12) -> 8268.75 | AB56: =AB18*Inputs!$B$35/12*(1+Inputs!$B$43)^INT((27-1)/12) -> 8268.75 | AC56: =AC18*Inputs!$B$35/12*(1+Inputs!$B$43)^INT((28-1)/12) -> 8268.75 | AD56: =AD18*Inputs!$B$35/12*(1+Inputs!$B$43)^INT((29-1)/12) -> 8268.75 | AE56: =AE18*Inputs!$B$35/12*(1+Inputs!$B$43)^INT((30-1)/12) -> 8268.75 | AF56: =AF18*Inputs!$B$35/12*(1+Inputs!$B$43)^INT((31-1)/12) -> 8268.75 | AG56: =AG18*Inputs!$B$35/12*(1+Inputs!$B$43)^INT((32-1)/12) -> 8268.75 | AH56: =AH18*Inputs!$B$35/12*(1+Inputs!$B$43)^INT((33-1)/12) -> 8268.75 | AI56: =AI18*Inputs!$B$35/12*(1+Inputs!$B$43)^INT((34-1)/12) -> 8268.75 | AJ56: =AJ18*Inputs!$B$35/12*(1+Inputs!$B$43)^INT((35-1)/12) -> 8268.75 | AK56: =AK18*Inputs!$B$35/12*(1+Inputs!$B$43)^INT((36-1)/12) -> 8268.75 | AL56: =AL18*Inputs!$B$35/12*(1+Inputs!$B$43)^INT((37-1)/12) -> 8682.1875 | AM56: =AM18*Inputs!$B$35/12*(1+Inputs!$B$43)^INT((38-1)/12) -> 8682.1875 | AN56: =AN18*Inputs!$B$35/12*(1+Inputs!$B$43)^INT((39-1)/12) -> 8682.1875 | AO56: =AO18*Inputs!$B$35/12*(1+Inputs!$B$43)^INT((40-1)/12) -> 8682.1875 | AP56: =AP18*Inputs!$B$35/12*(1+Inputs!$B$43)^INT((41-1)/12) -> 8682.1875 | AQ56: =AQ18*Inputs!$B$35/12*(1+Inputs!$B$43)^INT((42-1)/12) -> 8682.1875 | AR56: =AR18*Inputs!$B$35/12*(1+Inputs!$B$43)^INT((43-1)/12) -> 8682.1875 | AS56: =AS18*Inputs!$B$35/12*(1+Inputs!$B$43)^INT((44-1)/12) -> 8682.1875 | AT56: =AT18*Inputs!$B$35/12*(1+Inputs!$B$43)^INT((45-1)/12) -> 8682.1875 | AU56: =AU18*Inputs!$B$35/12*(1+Inputs!$B$43)^INT((46-1)/12) -> 8682.1875 | AV56: =AV18*Inputs!$B$35/12*(1+Inputs!$B$43)^INT((47-1)/12) -> 8682.1875 | AW56: =AW18*Inputs!$B$35/12*(1+Inputs!$B$43)^INT((48-1)/12) -> 8682.1875 | AX56: =AX18*Inputs!$B$35/12*(1+Inputs!$B$43)^INT((49-1)/12) -> 9116.2969 | AY56: =AY18*Inputs!$B$35/12*(1+Inputs!$B$43)^INT((50-1)/12) -> 9116.2969 | AZ56: =AZ18*Inputs!$B$35/12*(1+Inputs!$B$43)^INT((51-1)/12) -> 9116.2969 | BA56: =BA18*Inputs!$B$35/12*(1+Inputs!$B$43)^INT((52-1)/12) -> 9116.2969
A57: 2. Junior Engineer Gehalt | B57: =B19*Inputs!$B$36/12*(1+Inputs!$B$43)^INT((1-1)/12) -> 0 | C57: =C19*Inputs!$B$36/12*(1+Inputs!$B$43)^INT((2-1)/12) -> 0 | D57: =D19*Inputs!$B$36/12*(1+Inputs!$B$43)^INT((3-1)/12) -> 0 | E57: =E19*Inputs!$B$36/12*(1+Inputs!$B$43)^INT((4-1)/12) -> 0 | F57: =F19*Inputs!$B$36/12*(1+Inputs!$B$43)^INT((5-1)/12) -> 0 | G57: =G19*Inputs!$B$36/12*(1+Inputs!$B$43)^INT((6-1)/12) -> 0 | H57: =H19*Inputs!$B$36/12*(1+Inputs!$B$43)^INT((7-1)/12) -> 0 | I57: =I19*Inputs!$B$36/12*(1+Inputs!$B$43)^INT((8-1)/12) -> 0 | J57: =J19*Inputs!$B$36/12*(1+Inputs!$B$43)^INT((9-1)/12) -> 0 | K57: =K19*Inputs!$B$36/12*(1+Inputs!$B$43)^INT((10-1)/12) -> 0 | L57: =L19*Inputs!$B$36/12*(1+Inputs!$B$43)^INT((11-1)/12) -> 0 | M57: =M19*Inputs!$B$36/12*(1+Inputs!$B$43)^INT((12-1)/12) -> 0 | N57: =N19*Inputs!$B$36/12*(1+Inputs!$B$43)^INT((13-1)/12) -> 0 | O57: =O19*Inputs!$B$36/12*(1+Inputs!$B$43)^INT((14-1)/12) -> 0 | P57: =P19*Inputs!$B$36/12*(1+Inputs!$B$43)^INT((15-1)/12) -> 0 | Q57: =Q19*Inputs!$B$36/12*(1+Inputs!$B$43)^INT((16-1)/12) -> 0 | R57: =R19*Inputs!$B$36/12*(1+Inputs!$B$43)^INT((17-1)/12) -> 0 | S57: =S19*Inputs!$B$36/12*(1+Inputs!$B$43)^INT((18-1)/12) -> 0 | T57: =T19*Inputs!$B$36/12*(1+Inputs!$B$43)^INT((19-1)/12) -> 0 | U57: =U19*Inputs!$B$36/12*(1+Inputs!$B$43)^INT((20-1)/12) -> 5250 | V57: =V19*Inputs!$B$36/12*(1+Inputs!$B$43)^INT((21-1)/12) -> 5250 | W57: =W19*Inputs!$B$36/12*(1+Inputs!$B$43)^INT((22-1)/12) -> 5250 | X57: =X19*Inputs!$B$36/12*(1+Inputs!$B$43)^INT((23-1)/12) -> 5250 | Y57: =Y19*Inputs!$B$36/12*(1+Inputs!$B$43)^INT((24-1)/12) -> 5250 | Z57: =Z19*Inputs!$B$36/12*(1+Inputs!$B$43)^INT((25-1)/12) -> 5512.5 | AA57: =AA19*Inputs!$B$36/12*(1+Inputs!$B$43)^INT((26-1)/12) -> 5512.5 | AB57: =AB19*Inputs!$B$36/12*(1+Inputs!$B$43)^INT((27-1)/12) -> 5512.5 | AC57: =AC19*Inputs!$B$36/12*(1+Inputs!$B$43)^INT((28-1)/12) -> 5512.5 | AD57: =AD19*Inputs!$B$36/12*(1+Inputs!$B$43)^INT((29-1)/12) -> 5512.5 | AE57: =AE19*Inputs!$B$36/12*(1+Inputs!$B$43)^INT((30-1)/12) -> 5512.5 | AF57: =AF19*Inputs!$B$36/12*(1+Inputs!$B$43)^INT((31-1)/12) -> 5512.5 | AG57: =AG19*Inputs!$B$36/12*(1+Inputs!$B$43)^INT((32-1)/12) -> 5512.5 | AH57: =AH19*Inputs!$B$36/12*(1+Inputs!$B$43)^INT((33-1)/12) -> 5512.5 | AI57: =AI19*Inputs!$B$36/12*(1+Inputs!$B$43)^INT((34-1)/12) -> 5512.5 | AJ57: =AJ19*Inputs!$B$36/12*(1+Inputs!$B$43)^INT((35-1)/12) -> 5512.5 | AK57: =AK19*Inputs!$B$36/12*(1+Inputs!$B$43)^INT((36-1)/12) -> 5512.5 | AL57: =AL19*Inputs!$B$36/12*(1+Inputs!$B$43)^INT((37-1)/12) -> 5788.125 | AM57: =AM19*Inputs!$B$36/12*(1+Inputs!$B$43)^INT((38-1)/12) -> 5788.125 | AN57: =AN19*Inputs!$B$36/12*(1+Inputs!$B$43)^INT((39-1)/12) -> 5788.125 | AO57: =AO19*Inputs!$B$36/12*(1+Inputs!$B$43)^INT((40-1)/12) -> 5788.125 | AP57: =AP19*Inputs!$B$36/12*(1+Inputs!$B$43)^INT((41-1)/12) -> 5788.125 | AQ57: =AQ19*Inputs!$B$36/12*(1+Inputs!$B$43)^INT((42-1)/12) -> 5788.125 | AR57: =AR19*Inputs!$B$36/12*(1+Inputs!$B$43)^INT((43-1)/12) -> 5788.125 | AS57: =AS19*Inputs!$B$36/12*(1+Inputs!$B$43)^INT((44-1)/12) -> 5788.125 | AT57: =AT19*Inputs!$B$36/12*(1+Inputs!$B$43)^INT((45-1)/12) -> 5788.125 | AU57: =AU19*Inputs!$B$36/12*(1+Inputs!$B$43)^INT((46-1)/12) -> 5788.125 | AV57: =AV19*Inputs!$B$36/12*(1+Inputs!$B$43)^INT((47-1)/12) -> 5788.125 | AW57: =AW19*Inputs!$B$36/12*(1+Inputs!$B$43)^INT((48-1)/12) -> 5788.125 | AX57: =AX19*Inputs!$B$36/12*(1+Inputs!$B$43)^INT((49-1)/12) -> 6077.5312 | AY57: =AY19*Inputs!$B$36/12*(1+Inputs!$B$43)^INT((50-1)/12) -> 6077.5312 | AZ57: =AZ19*Inputs!$B$36/12*(1+Inputs!$B$43)^INT((51-1)/12) -> 6077.5312 | BA57: =BA19*Inputs!$B$36/12*(1+Inputs!$B$43)^INT((52-1)/12) -> 6077.5312
A58: 3. ML/AI Engineer Gehalt | B58: =B20*Inputs!$B$37/12*(1+Inputs!$B$43)^INT((1-1)/12) -> 0 | C58: =C20*Inputs!$B$37/12*(1+Inputs!$B$43)^INT((2-1)/12) -> 0 | D58: =D20*Inputs!$B$37/12*(1+Inputs!$B$43)^INT((3-1)/12) -> 0 | E58: =E20*Inputs!$B$37/12*(1+Inputs!$B$43)^INT((4-1)/12) -> 0 | F58: =F20*Inputs!$B$37/12*(1+Inputs!$B$43)^INT((5-1)/12) -> 0 | G58: =G20*Inputs!$B$37/12*(1+Inputs!$B$43)^INT((6-1)/12) -> 0 | H58: =H20*Inputs!$B$37/12*(1+Inputs!$B$43)^INT((7-1)/12) -> 0 | I58: =I20*Inputs!$B$37/12*(1+Inputs!$B$43)^INT((8-1)/12) -> 0 | J58: =J20*Inputs!$B$37/12*(1+Inputs!$B$43)^INT((9-1)/12) -> 0 | K58: =K20*Inputs!$B$37/12*(1+Inputs!$B$43)^INT((10-1)/12) -> 0 | L58: =L20*Inputs!$B$37/12*(1+Inputs!$B$43)^INT((11-1)/12) -> 0 | M58: =M20*Inputs!$B$37/12*(1+Inputs!$B$43)^INT((12-1)/12) -> 0 | N58: =N20*Inputs!$B$37/12*(1+Inputs!$B$43)^INT((13-1)/12) -> 0 | O58: =O20*Inputs!$B$37/12*(1+Inputs!$B$43)^INT((14-1)/12) -> 0 | P58: =P20*Inputs!$B$37/12*(1+Inputs!$B$43)^INT((15-1)/12) -> 0 | Q58: =Q20*Inputs!$B$37/12*(1+Inputs!$B$43)^INT((16-1)/12) -> 0 | R58: =R20*Inputs!$B$37/12*(1+Inputs!$B$43)^INT((17-1)/12) -> 0 | S58: =S20*Inputs!$B$37/12*(1+Inputs!$B$43)^INT((18-1)/12) -> 0 | T58: =T20*Inputs!$B$37/12*(1+Inputs!$B$43)^INT((19-1)/12) -> 0 | U58: =U20*Inputs!$B$37/12*(1+Inputs!$B$43)^INT((20-1)/12) -> 0 | V58: =V20*Inputs!$B$37/12*(1+Inputs!$B$43)^INT((21-1)/12) -> 0 | W58: =W20*Inputs!$B$37/12*(1+Inputs!$B$43)^INT((22-1)/12) -> 9625 | X58: =X20*Inputs!$B$37/12*(1+Inputs!$B$43)^INT((23-1)/12) -> 9625 | Y58: =Y20*Inputs!$B$37/12*(1+Inputs!$B$43)^INT((24-1)/12) -> 9625 | Z58: =Z20*Inputs!$B$37/12*(1+Inputs!$B$43)^INT((25-1)/12) -> 10106.25 | AA58: =AA20*Inputs!$B$37/12*(1+Inputs!$B$43)^INT((26-1)/12) -> 10106.25 | AB58: =AB20*Inputs!$B$37/12*(1+Inputs!$B$43)^INT((27-1)/12) -> 10106.25 | AC58: =AC20*Inputs!$B$37/12*(1+Inputs!$B$43)^INT((28-1)/12) -> 10106.25 | AD58: =AD20*Inputs!$B$37/12*(1+Inputs!$B$43)^INT((29-1)/12) -> 10106.25 | AE58: =AE20*Inputs!$B$37/12*(1+Inputs!$B$43)^INT((30-1)/12) -> 10106.25 | AF58: =AF20*Inputs!$B$37/12*(1+Inputs!$B$43)^INT((31-1)/12) -> 10106.25 | AG58: =AG20*Inputs!$B$37/12*(1+Inputs!$B$43)^INT((32-1)/12) -> 10106.25 | AH58: =AH20*Inputs!$B$37/12*(1+Inputs!$B$43)^INT((33-1)/12) -> 10106.25 | AI58: =AI20*Inputs!$B$37/12*(1+Inputs!$B$43)^INT((34-1)/12) -> 10106.25 | AJ58: =AJ20*Inputs!$B$37/12*(1+Inputs!$B$43)^INT((35-1)/12) -> 10106.25 | AK58: =AK20*Inputs!$B$37/12*(1+Inputs!$B$43)^INT((36-1)/12) -> 10106.25 | AL58: =AL20*Inputs!$B$37/12*(1+Inputs!$B$43)^INT((37-1)/12) -> 10611.562 | AM58: =AM20*Inputs!$B$37/12*(1+Inputs!$B$43)^INT((38-1)/12) -> 10611.562 | AN58: =AN20*Inputs!$B$37/12*(1+Inputs!$B$43)^INT((39-1)/12) -> 10611.562 | AO58: =AO20*Inputs!$B$37/12*(1+Inputs!$B$43)^INT((40-1)/12) -> 10611.562 | AP58: =AP20*Inputs!$B$37/12*(1+Inputs!$B$43)^INT((41-1)/12) -> 10611.562 | AQ58: =AQ20*Inputs!$B$37/12*(1+Inputs!$B$43)^INT((42-1)/12) -> 10611.562 | AR58: =AR20*Inputs!$B$37/12*(1+Inputs!$B$43)^INT((43-1)/12) -> 10611.562 | AS58: =AS20*Inputs!$B$37/12*(1+Inputs!$B$43)^INT((44-1)/12) -> 10611.562 | AT58: =AT20*Inputs!$B$37/12*(1+Inputs!$B$43)^INT((45-1)/12) -> 10611.562 | AU58: =AU20*Inputs!$B$37/12*(1+Inputs!$B$43)^INT((46-1)/12) -> 10611.562 | AV58: =AV20*Inputs!$B$37/12*(1+Inputs!$B$43)^INT((47-1)/12) -> 10611.562 | AW58: =AW20*Inputs!$B$37/12*(1+Inputs!$B$43)^INT((48-1)/12) -> 10611.562 | AX58: =AX20*Inputs!$B$37/12*(1+Inputs!$B$43)^INT((49-1)/12) -> 11142.141 | AY58: =AY20*Inputs!$B$37/12*(1+Inputs!$B$43)^INT((50-1)/12) -> 11142.141 | AZ58: =AZ20*Inputs!$B$37/12*(1+Inputs!$B$43)^INT((51-1)/12) -> 11142.141 | BA58: =BA20*Inputs!$B$37/12*(1+Inputs!$B$43)^INT((52-1)/12) -> 11142.141
A59: 3. Sales Rep Gehalt | B59: =B21*Inputs!$B$39/12*(1+Inputs!$B$43)^INT((1-1)/12) -> 0 | C59: =C21*Inputs!$B$39/12*(1+Inputs!$B$43)^INT((2-1)/12) -> 0 | D59: =D21*Inputs!$B$39/12*(1+Inputs!$B$43)^INT((3-1)/12) -> 0 | E59: =E21*Inputs!$B$39/12*(1+Inputs!$B$43)^INT((4-1)/12) -> 0 | F59: =F21*Inputs!$B$39/12*(1+Inputs!$B$43)^INT((5-1)/12) -> 0 | G59: =G21*Inputs!$B$39/12*(1+Inputs!$B$43)^INT((6-1)/12) -> 0 | H59: =H21*Inputs!$B$39/12*(1+Inputs!$B$43)^INT((7-1)/12) -> 0 | I59: =I21*Inputs!$B$39/12*(1+Inputs!$B$43)^INT((8-1)/12) -> 0 | J59: =J21*Inputs!$B$39/12*(1+Inputs!$B$43)^INT((9-1)/12) -> 0 | K59: =K21*Inputs!$B$39/12*(1+Inputs!$B$43)^INT((10-1)/12) -> 0 | L59: =L21*Inputs!$B$39/12*(1+Inputs!$B$43)^INT((11-1)/12) -> 0 | M59: =M21*Inputs!$B$39/12*(1+Inputs!$B$43)^INT((12-1)/12) -> 0 | N59: =N21*Inputs!$B$39/12*(1+Inputs!$B$43)^INT((13-1)/12) -> 0 | O59: =O21*Inputs!$B$39/12*(1+Inputs!$B$43)^INT((14-1)/12) -> 0 | P59: =P21*Inputs!$B$39/12*(1+Inputs!$B$43)^INT((15-1)/12) -> 0 | Q59: =Q21*Inputs!$B$39/12*(1+Inputs!$B$43)^INT((16-1)/12) -> 0 | R59: =R21*Inputs!$B$39/12*(1+Inputs!$B$43)^INT((17-1)/12) -> 0 | S59: =S21*Inputs!$B$39/12*(1+Inputs!$B$43)^INT((18-1)/12) -> 0 | T59: =T21*Inputs!$B$39/12*(1+Inputs!$B$43)^INT((19-1)/12) -> 0 | U59: =U21*Inputs!$B$39/12*(1+Inputs!$B$43)^INT((20-1)/12) -> 0 | V59: =V21*Inputs!$B$39/12*(1+Inputs!$B$43)^INT((21-1)/12) -> 0 | W59: =W21*Inputs!$B$39/12*(1+Inputs!$B$43)^INT((22-1)/12) -> 0 | X59: =X21*Inputs!$B$39/12*(1+Inputs!$B$43)^INT((23-1)/12) -> 0 | Y59: =Y21*Inputs!$B$39/12*(1+Inputs!$B$43)^INT((24-1)/12) -> 0 | Z59: =Z21*Inputs!$B$39/12*(1+Inputs!$B$43)^INT((25-1)/12) -> 0 | AA59: =AA21*Inputs!$B$39/12*(1+Inputs!$B$43)^INT((26-1)/12) -> 11943.75 | AB59: =AB21*Inputs!$B$39/12*(1+Inputs!$B$43)^INT((27-1)/12) -> 11943.75 | AC59: =AC21*Inputs!$B$39/12*(1+Inputs!$B$43)^INT((28-1)/12) -> 11943.75 | AD59: =AD21*Inputs!$B$39/12*(1+Inputs!$B$43)^INT((29-1)/12) -> 11943.75 | AE59: =AE21*Inputs!$B$39/12*(1+Inputs!$B$43)^INT((30-1)/12) -> 11943.75 | AF59: =AF21*Inputs!$B$39/12*(1+Inputs!$B$43)^INT((31-1)/12) -> 11943.75 | AG59: =AG21*Inputs!$B$39/12*(1+Inputs!$B$43)^INT((32-1)/12) -> 11943.75 | AH59: =AH21*Inputs!$B$39/12*(1+Inputs!$B$43)^INT((33-1)/12) -> 11943.75 | AI59: =AI21*Inputs!$B$39/12*(1+Inputs!$B$43)^INT((34-1)/12) -> 11943.75 | AJ59: =AJ21*Inputs!$B$39/12*(1+Inputs!$B$43)^INT((35-1)/12) -> 11943.75 | AK59: =AK21*Inputs!$B$39/12*(1+Inputs!$B$43)^INT((36-1)/12) -> 11943.75 | AL59: =AL21*Inputs!$B$39/12*(1+Inputs!$B$43)^INT((37-1)/12) -> 12540.938 | AM59: =AM21*Inputs!$B$39/12*(1+Inputs!$B$43)^INT((38-1)/12) -> 12540.938 | AN59: =AN21*Inputs!$B$39/12*(1+Inputs!$B$43)^INT((39-1)/12) -> 12540.938 | AO59: =AO21*Inputs!$B$39/12*(1+Inputs!$B$43)^INT((40-1)/12) -> 12540.938 | AP59: =AP21*Inputs!$B$39/12*(1+Inputs!$B$43)^INT((41-1)/12) -> 12540.938 | AQ59: =AQ21*Inputs!$B$39/12*(1+Inputs!$B$43)^INT((42-1)/12) -> 12540.938 | AR59: =AR21*Inputs!$B$39/12*(1+Inputs!$B$43)^INT((43-1)/12) -> 12540.938 | AS59: =AS21*Inputs!$B$39/12*(1+Inputs!$B$43)^INT((44-1)/12) -> 12540.938 | AT59: =AT21*Inputs!$B$39/12*(1+Inputs!$B$43)^INT((45-1)/12) -> 12540.938 | AU59: =AU21*Inputs!$B$39/12*(1+Inputs!$B$43)^INT((46-1)/12) -> 12540.938 | AV59: =AV21*Inputs!$B$39/12*(1+Inputs!$B$43)^INT((47-1)/12) -> 12540.938 | AW59: =AW21*Inputs!$B$39/12*(1+Inputs!$B$43)^INT((48-1)/12) -> 12540.938 | AX59: =AX21*Inputs!$B$39/12*(1+Inputs!$B$43)^INT((49-1)/12) -> 13167.984 | AY59: =AY21*Inputs!$B$39/12*(1+Inputs!$B$43)^INT((50-1)/12) -> 13167.984 | AZ59: =AZ21*Inputs!$B$39/12*(1+Inputs!$B$43)^INT((51-1)/12) -> 13167.984 | BA59: =BA21*Inputs!$B$39/12*(1+Inputs!$B$43)^INT((52-1)/12) -> 13167.984
A60: 2. Customer Success Gehalt | B60: =B22*Inputs!$B$41/12*(1+Inputs!$B$43)^INT((1-1)/12) -> 0 | C60: =C22*Inputs!$B$41/12*(1+Inputs!$B$43)^INT((2-1)/12) -> 0 | D60: =D22*Inputs!$B$41/12*(1+Inputs!$B$43)^INT((3-1)/12) -> 0 | E60: =E22*Inputs!$B$41/12*(1+Inputs!$B$43)^INT((4-1)/12) -> 0 | F60: =F22*Inputs!$B$41/12*(1+Inputs!$B$43)^INT((5-1)/12) -> 0 | G60: =G22*Inputs!$B$41/12*(1+Inputs!$B$43)^INT((6-1)/12) -> 0 | H60: =H22*Inputs!$B$41/12*(1+Inputs!$B$43)^INT((7-1)/12) -> 0 | I60: =I22*Inputs!$B$41/12*(1+Inputs!$B$43)^INT((8-1)/12) -> 0 | J60: =J22*Inputs!$B$41/12*(1+Inputs!$B$43)^INT((9-1)/12) -> 0 | K60: =K22*Inputs!$B$41/12*(1+Inputs!$B$43)^INT((10-1)/12) -> 0 | L60: =L22*Inputs!$B$41/12*(1+Inputs!$B$43)^INT((11-1)/12) -> 0 | M60: =M22*Inputs!$B$41/12*(1+Inputs!$B$43)^INT((12-1)/12) -> 0 | N60: =N22*Inputs!$B$41/12*(1+Inputs!$B$43)^INT((13-1)/12) -> 0 | O60: =O22*Inputs!$B$41/12*(1+Inputs!$B$43)^INT((14-1)/12) -> 0 | P60: =P22*Inputs!$B$41/12*(1+Inputs!$B$43)^INT((15-1)/12) -> 0 | Q60: =Q22*Inputs!$B$41/12*(1+Inputs!$B$43)^INT((16-1)/12) -> 0 | R60: =R22*Inputs!$B$41/12*(1+Inputs!$B$43)^INT((17-1)/12) -> 0 | S60: =S22*Inputs!$B$41/12*(1+Inputs!$B$43)^INT((18-1)/12) -> 0 | T60: =T22*Inputs!$B$41/12*(1+Inputs!$B$43)^INT((19-1)/12) -> 0 | U60: =U22*Inputs!$B$41/12*(1+Inputs!$B$43)^INT((20-1)/12) -> 0 | V60: =V22*Inputs!$B$41/12*(1+Inputs!$B$43)^INT((21-1)/12) -> 0 | W60: =W22*Inputs!$B$41/12*(1+Inputs!$B$43)^INT((22-1)/12) -> 0 | X60: =X22*Inputs!$B$41/12*(1+Inputs!$B$43)^INT((23-1)/12) -> 0 | Y60: =Y22*Inputs!$B$41/12*(1+Inputs!$B$43)^INT((24-1)/12) -> 5687.5 | Z60: =Z22*Inputs!$B$41/12*(1+Inputs!$B$43)^INT((25-1)/12) -> 5971.875 | AA60: =AA22*Inputs!$B$41/12*(1+Inputs!$B$43)^INT((26-1)/12) -> 5971.875 | AB60: =AB22*Inputs!$B$41/12*(1+Inputs!$B$43)^INT((27-1)/12) -> 5971.875 | AC60: =AC22*Inputs!$B$41/12*(1+Inputs!$B$43)^INT((28-1)/12) -> 5971.875 | AD60: =AD22*Inputs!$B$41/12*(1+Inputs!$B$43)^INT((29-1)/12) -> 5971.875 | AE60: =AE22*Inputs!$B$41/12*(1+Inputs!$B$43)^INT((30-1)/12) -> 5971.875 | AF60: =AF22*Inputs!$B$41/12*(1+Inputs!$B$43)^INT((31-1)/12) -> 5971.875 | AG60: =AG22*Inputs!$B$41/12*(1+Inputs!$B$43)^INT((32-1)/12) -> 5971.875 | AH60: =AH22*Inputs!$B$41/12*(1+Inputs!$B$43)^INT((33-1)/12) -> 5971.875 | AI60: =AI22*Inputs!$B$41/12*(1+Inputs!$B$43)^INT((34-1)/12) -> 5971.875 | AJ60: =AJ22*Inputs!$B$41/12*(1+Inputs!$B$43)^INT((35-1)/12) -> 5971.875 | AK60: =AK22*Inputs!$B$41/12*(1+Inputs!$B$43)^INT((36-1)/12) -> 5971.875 | AL60: =AL22*Inputs!$B$41/12*(1+Inputs!$B$43)^INT((37-1)/12) -> 6270.4688 | AM60: =AM22*Inputs!$B$41/12*(1+Inputs!$B$43)^INT((38-1)/12) -> 6270.4688 | AN60: =AN22*Inputs!$B$41/12*(1+Inputs!$B$43)^INT((39-1)/12) -> 6270.4688 | AO60: =AO22*Inputs!$B$41/12*(1+Inputs!$B$43)^INT((40-1)/12) -> 6270.4688 | AP60: =AP22*Inputs!$B$41/12*(1+Inputs!$B$43)^INT((41-1)/12) -> 6270.4688 | AQ60: =AQ22*Inputs!$B$41/12*(1+Inputs!$B$43)^INT((42-1)/12) -> 6270.4688 | AR60: =AR22*Inputs!$B$41/12*(1+Inputs!$B$43)^INT((43-1)/12) -> 6270.4688 | AS60: =AS22*Inputs!$B$41/12*(1+Inputs!$B$43)^INT((44-1)/12) -> 6270.4688 | AT60: =AT22*Inputs!$B$41/12*(1+Inputs!$B$43)^INT((45-1)/12) -> 6270.4688 | AU60: =AU22*Inputs!$B$41/12*(1+Inputs!$B$43)^INT((46-1)/12) -> 6270.4688 | AV60: =AV22*Inputs!$B$41/12*(1+Inputs!$B$43)^INT((47-1)/12) -> 6270.4688 | AW60: =AW22*Inputs!$B$41/12*(1+Inputs!$B$43)^INT((48-1)/12) -> 6270.4688 | AX60: =AX22*Inputs!$B$41/12*(1+Inputs!$B$43)^INT((49-1)/12) -> 6583.9922 | AY60: =AY22*Inputs!$B$41/12*(1+Inputs!$B$43)^INT((50-1)/12) -> 6583.9922 | AZ60: =AZ22*Inputs!$B$41/12*(1+Inputs!$B$43)^INT((51-1)/12) -> 6583.9922 | BA60: =BA22*Inputs!$B$41/12*(1+Inputs!$B$43)^INT((52-1)/12) -> 6583.9922
A61: 2. Marketing Manager Gehalt | B61: =B23*Inputs!$B$40/12*(1+Inputs!$B$43)^INT((1-1)/12) -> 0 | C61: =C23*Inputs!$B$40/12*(1+Inputs!$B$43)^INT((2-1)/12) -> 0 | D61: =D23*Inputs!$B$40/12*(1+Inputs!$B$43)^INT((3-1)/12) -> 0 | E61: =E23*Inputs!$B$40/12*(1+Inputs!$B$43)^INT((4-1)/12) -> 0 | F61: =F23*Inputs!$B$40/12*(1+Inputs!$B$43)^INT((5-1)/12) -> 0 | G61: =G23*Inputs!$B$40/12*(1+Inputs!$B$43)^INT((6-1)/12) -> 0 | H61: =H23*Inputs!$B$40/12*(1+Inputs!$B$43)^INT((7-1)/12) -> 0 | I61: =I23*Inputs!$B$40/12*(1+Inputs!$B$43)^INT((8-1)/12) -> 0 | J61: =J23*Inputs!$B$40/12*(1+Inputs!$B$43)^INT((9-1)/12) -> 0 | K61: =K23*Inputs!$B$40/12*(1+Inputs!$B$43)^INT((10-1)/12) -> 0 | L61: =L23*Inputs!$B$40/12*(1+Inputs!$B$43)^INT((11-1)/12) -> 0 | M61: =M23*Inputs!$B$40/12*(1+Inputs!$B$43)^INT((12-1)/12) -> 0 | N61: =N23*Inputs!$B$40/12*(1+Inputs!$B$43)^INT((13-1)/12) -> 0 | O61: =O23*Inputs!$B$40/12*(1+Inputs!$B$43)^INT((14-1)/12) -> 0 | P61: =P23*Inputs!$B$40/12*(1+Inputs!$B$43)^INT((15-1)/12) -> 0 | Q61: =Q23*Inputs!$B$40/12*(1+Inputs!$B$43)^INT((16-1)/12) -> 0 | R61: =R23*Inputs!$B$40/12*(1+Inputs!$B$43)^INT((17-1)/12) -> 0 | S61: =S23*Inputs!$B$40/12*(1+Inputs!$B$43)^INT((18-1)/12) -> 0 | T61: =T23*Inputs!$B$40/12*(1+Inputs!$B$43)^INT((19-1)/12) -> 0 | U61: =U23*Inputs!$B$40/12*(1+Inputs!$B$43)^INT((20-1)/12) -> 0 | V61: =V23*Inputs!$B$40/12*(1+Inputs!$B$43)^INT((21-1)/12) -> 0 | W61: =W23*Inputs!$B$40/12*(1+Inputs!$B$43)^INT((22-1)/12) -> 0 | X61: =X23*Inputs!$B$40/12*(1+Inputs!$B$43)^INT((23-1)/12) -> 0 | Y61: =Y23*Inputs!$B$40/12*(1+Inputs!$B$43)^INT((24-1)/12) -> 0 | Z61: =Z23*Inputs!$B$40/12*(1+Inputs!$B$43)^INT((25-1)/12) -> 0 | AA61: =AA23*Inputs!$B$40/12*(1+Inputs!$B$43)^INT((26-1)/12) -> 0 | AB61: =AB23*Inputs!$B$40/12*(1+Inputs!$B$43)^INT((27-1)/12) -> 0 | AC61: =AC23*Inputs!$B$40/12*(1+Inputs!$B$43)^INT((28-1)/12) -> 5971.875 | AD61: =AD23*Inputs!$B$40/12*(1+Inputs!$B$43)^INT((29-1)/12) -> 5971.875 | AE61: =AE23*Inputs!$B$40/12*(1+Inputs!$B$43)^INT((30-1)/12) -> 5971.875 | AF61: =AF23*Inputs!$B$40/12*(1+Inputs!$B$43)^INT((31-1)/12) -> 5971.875 | AG61: =AG23*Inputs!$B$40/12*(1+Inputs!$B$43)^INT((32-1)/12) -> 5971.875 | AH61: =AH23*Inputs!$B$40/12*(1+Inputs!$B$43)^INT((33-1)/12) -> 5971.875 | AI61: =AI23*Inputs!$B$40/12*(1+Inputs!$B$43)^INT((34-1)/12) -> 5971.875 | AJ61: =AJ23*Inputs!$B$40/12*(1+Inputs!$B$43)^INT((35-1)/12) -> 5971.875 | AK61: =AK23*Inputs!$B$40/12*(1+Inputs!$B$43)^INT((36-1)/12) -> 5971.875 | AL61: =AL23*Inputs!$B$40/12*(1+Inputs!$B$43)^INT((37-1)/12) -> 6270.4688 | AM61: =AM23*Inputs!$B$40/12*(1+Inputs!$B$43)^INT((38-1)/12) -> 6270.4688 | AN61: =AN23*Inputs!$B$40/12*(1+Inputs!$B$43)^INT((39-1)/12) -> 6270.4688 | AO61: =AO23*Inputs!$B$40/12*(1+Inputs!$B$43)^INT((40-1)/12) -> 6270.4688 | AP61: =AP23*Inputs!$B$40/12*(1+Inputs!$B$43)^INT((41-1)/12) -> 6270.4688 | AQ61: =AQ23*Inputs!$B$40/12*(1+Inputs!$B$43)^INT((42-1)/12) -> 6270.4688 | AR61: =AR23*Inputs!$B$40/12*(1+Inputs!$B$43)^INT((43-1)/12) -> 6270.4688 | AS61: =AS23*Inputs!$B$40/12*(1+Inputs!$B$43)^INT((44-1)/12) -> 6270.4688 | AT61: =AT23*Inputs!$B$40/12*(1+Inputs!$B$43)^INT((45-1)/12) -> 6270.4688 | AU61: =AU23*Inputs!$B$40/12*(1+Inputs!$B$43)^INT((46-1)/12) -> 6270.4688 | AV61: =AV23*Inputs!$B$40/12*(1+Inputs!$B$43)^INT((47-1)/12) -> 6270.4688 | AW61: =AW23*Inputs!$B$40/12*(1+Inputs!$B$43)^INT((48-1)/12) -> 6270.4688 | AX61: =AX23*Inputs!$B$40/12*(1+Inputs!$B$43)^INT((49-1)/12) -> 6583.9922 | AY61: =AY23*Inputs!$B$40/12*(1+Inputs!$B$43)^INT((50-1)/12) -> 6583.9922 | AZ61: =AZ23*Inputs!$B$40/12*(1+Inputs!$B$43)^INT((51-1)/12) -> 6583.9922 | BA61: =BA23*Inputs!$B$40/12*(1+Inputs!$B$43)^INT((52-1)/12) -> 6583.9922
A62: 5. Senior Engineer Gehalt | B62: =B24*Inputs!$B$35/12*(1+Inputs!$B$43)^INT((1-1)/12) -> 0 | C62: =C24*Inputs!$B$35/12*(1+Inputs!$B$43)^INT((2-1)/12) -> 0 | D62: =D24*Inputs!$B$35/12*(1+Inputs!$B$43)^INT((3-1)/12) -> 0 | E62: =E24*Inputs!$B$35/12*(1+Inputs!$B$43)^INT((4-1)/12) -> 0 | F62: =F24*Inputs!$B$35/12*(1+Inputs!$B$43)^INT((5-1)/12) -> 0 | G62: =G24*Inputs!$B$35/12*(1+Inputs!$B$43)^INT((6-1)/12) -> 0 | H62: =H24*Inputs!$B$35/12*(1+Inputs!$B$43)^INT((7-1)/12) -> 0 | I62: =I24*Inputs!$B$35/12*(1+Inputs!$B$43)^INT((8-1)/12) -> 0 | J62: =J24*Inputs!$B$35/12*(1+Inputs!$B$43)^INT((9-1)/12) -> 0 | K62: =K24*Inputs!$B$35/12*(1+Inputs!$B$43)^INT((10-1)/12) -> 0 | L62: =L24*Inputs!$B$35/12*(1+Inputs!$B$43)^INT((11-1)/12) -> 0 | M62: =M24*Inputs!$B$35/12*(1+Inputs!$B$43)^INT((12-1)/12) -> 0 | N62: =N24*Inputs!$B$35/12*(1+Inputs!$B$43)^INT((13-1)/12) -> 0 | O62: =O24*Inputs!$B$35/12*(1+Inputs!$B$43)^INT((14-1)/12) -> 0 | P62: =P24*Inputs!$B$35/12*(1+Inputs!$B$43)^INT((15-1)/12) -> 0 | Q62: =Q24*Inputs!$B$35/12*(1+Inputs!$B$43)^INT((16-1)/12) -> 0 | R62: =R24*Inputs!$B$35/12*(1+Inputs!$B$43)^INT((17-1)/12) -> 0 | S62: =S24*Inputs!$B$35/12*(1+Inputs!$B$43)^INT((18-1)/12) -> 0 | T62: =T24*Inputs!$B$35/12*(1+Inputs!$B$43)^INT((19-1)/12) -> 0 | U62: =U24*Inputs!$B$35/12*(1+Inputs!$B$43)^INT((20-1)/12) -> 0 | V62: =V24*Inputs!$B$35/12*(1+Inputs!$B$43)^INT((21-1)/12) -> 0 | W62: =W24*Inputs!$B$35/12*(1+Inputs!$B$43)^INT((22-1)/12) -> 0 | X62: =X24*Inputs!$B$35/12*(1+Inputs!$B$43)^INT((23-1)/12) -> 0 | Y62: =Y24*Inputs!$B$35/12*(1+Inputs!$B$43)^INT((24-1)/12) -> 0 | Z62: =Z24*Inputs!$B$35/12*(1+Inputs!$B$43)^INT((25-1)/12) -> 0 | AA62: =AA24*Inputs!$B$35/12*(1+Inputs!$B$43)^INT((26-1)/12) -> 0 | AB62: =AB24*Inputs!$B$35/12*(1+Inputs!$B$43)^INT((27-1)/12) -> 0 | AC62: =AC24*Inputs!$B$35/12*(1+Inputs!$B$43)^INT((28-1)/12) -> 0 | AD62: =AD24*Inputs!$B$35/12*(1+Inputs!$B$43)^INT((29-1)/12) -> 0 | AE62: =AE24*Inputs!$B$35/12*(1+Inputs!$B$43)^INT((30-1)/12) -> 8268.75 | AF62: =AF24*Inputs!$B$35/12*(1+Inputs!$B$43)^INT((31-1)/12) -> 8268.75 | AG62: =AG24*Inputs!$B$35/12*(1+Inputs!$B$43)^INT((32-1)/12) -> 8268.75 | AH62: =AH24*Inputs!$B$35/12*(1+Inputs!$B$43)^INT((33-1)/12) -> 8268.75 | AI62: =AI24*Inputs!$B$35/12*(1+Inputs!$B$43)^INT((34-1)/12) -> 8268.75 | AJ62: =AJ24*Inputs!$B$35/12*(1+Inputs!$B$43)^INT((35-1)/12) -> 8268.75 | AK62: =AK24*Inputs!$B$35/12*(1+Inputs!$B$43)^INT((36-1)/12) -> 8268.75 | AL62: =AL24*Inputs!$B$35/12*(1+Inputs!$B$43)^INT((37-1)/12) -> 8682.1875 | AM62: =AM24*Inputs!$B$35/12*(1+Inputs!$B$43)^INT((38-1)/12) -> 8682.1875 | AN62: =AN24*Inputs!$B$35/12*(1+Inputs!$B$43)^INT((39-1)/12) -> 8682.1875 | AO62: =AO24*Inputs!$B$35/12*(1+Inputs!$B$43)^INT((40-1)/12) -> 8682.1875 | AP62: =AP24*Inputs!$B$35/12*(1+Inputs!$B$43)^INT((41-1)/12) -> 8682.1875 | AQ62: =AQ24*Inputs!$B$35/12*(1+Inputs!$B$43)^INT((42-1)/12) -> 8682.1875 | AR62: =AR24*Inputs!$B$35/12*(1+Inputs!$B$43)^INT((43-1)/12) -> 8682.1875 | AS62: =AS24*Inputs!$B$35/12*(1+Inputs!$B$43)^INT((44-1)/12) -> 8682.1875 | AT62: =AT24*Inputs!$B$35/12*(1+Inputs!$B$43)^INT((45-1)/12) -> 8682.1875 | AU62: =AU24*Inputs!$B$35/12*(1+Inputs!$B$43)^INT((46-1)/12) -> 8682.1875 | AV62: =AV24*Inputs!$B$35/12*(1+Inputs!$B$43)^INT((47-1)/12) -> 8682.1875 | AW62: =AW24*Inputs!$B$35/12*(1+Inputs!$B$43)^INT((48-1)/12) -> 8682.1875 | AX62: =AX24*Inputs!$B$35/12*(1+Inputs!$B$43)^INT((49-1)/12) -> 9116.2969 | AY62: =AY24*Inputs!$B$35/12*(1+Inputs!$B$43)^INT((50-1)/12) -> 9116.2969 | AZ62: =AZ24*Inputs!$B$35/12*(1+Inputs!$B$43)^INT((51-1)/12) -> 9116.2969 | BA62: =BA24*Inputs!$B$35/12*(1+Inputs!$B$43)^INT((52-1)/12) -> 9116.2969
A63: 3. Junior Engineer Gehalt | B63: =B25*Inputs!$B$36/12*(1+Inputs!$B$43)^INT((1-1)/12) -> 0 | C63: =C25*Inputs!$B$36/12*(1+Inputs!$B$43)^INT((2-1)/12) -> 0 | D63: =D25*Inputs!$B$36/12*(1+Inputs!$B$43)^INT((3-1)/12) -> 0 | E63: =E25*Inputs!$B$36/12*(1+Inputs!$B$43)^INT((4-1)/12) -> 0 | F63: =F25*Inputs!$B$36/12*(1+Inputs!$B$43)^INT((5-1)/12) -> 0 | G63: =G25*Inputs!$B$36/12*(1+Inputs!$B$43)^INT((6-1)/12) -> 0 | H63: =H25*Inputs!$B$36/12*(1+Inputs!$B$43)^INT((7-1)/12) -> 0 | I63: =I25*Inputs!$B$36/12*(1+Inputs!$B$43)^INT((8-1)/12) -> 0 | J63: =J25*Inputs!$B$36/12*(1+Inputs!$B$43)^INT((9-1)/12) -> 0 | K63: =K25*Inputs!$B$36/12*(1+Inputs!$B$43)^INT((10-1)/12) -> 0 | L63: =L25*Inputs!$B$36/12*(1+Inputs!$B$43)^INT((11-1)/12) -> 0 | M63: =M25*Inputs!$B$36/12*(1+Inputs!$B$43)^INT((12-1)/12) -> 0 | N63: =N25*Inputs!$B$36/12*(1+Inputs!$B$43)^INT((13-1)/12) -> 0 | O63: =O25*Inputs!$B$36/12*(1+Inputs!$B$43)^INT((14-1)/12) -> 0 | P63: =P25*Inputs!$B$36/12*(1+Inputs!$B$43)^INT((15-1)/12) -> 0 | Q63: =Q25*Inputs!$B$36/12*(1+Inputs!$B$43)^INT((16-1)/12) -> 0 | R63: =R25*Inputs!$B$36/12*(1+Inputs!$B$43)^INT((17-1)/12) -> 0 | S63: =S25*Inputs!$B$36/12*(1+Inputs!$B$43)^INT((18-1)/12) -> 0 | T63: =T25*Inputs!$B$36/12*(1+Inputs!$B$43)^INT((19-1)/12) -> 0 | U63: =U25*Inputs!$B$36/12*(1+Inputs!$B$43)^INT((20-1)/12) -> 0 | V63: =V25*Inputs!$B$36/12*(1+Inputs!$B$43)^INT((21-1)/12) -> 0 | W63: =W25*Inputs!$B$36/12*(1+Inputs!$B$43)^INT((22-1)/12) -> 0 | X63: =X25*Inputs!$B$36/12*(1+Inputs!$B$43)^INT((23-1)/12) -> 0 | Y63: =Y25*Inputs!$B$36/12*(1+Inputs!$B$43)^INT((24-1)/12) -> 0 | Z63: =Z25*Inputs!$B$36/12*(1+Inputs!$B$43)^INT((25-1)/12) -> 0 | AA63: =AA25*Inputs!$B$36/12*(1+Inputs!$B$43)^INT((26-1)/12) -> 0 | AB63: =AB25*Inputs!$B$36/12*(1+Inputs!$B$43)^INT((27-1)/12) -> 0 | AC63: =AC25*Inputs!$B$36/12*(1+Inputs!$B$43)^INT((28-1)/12) -> 0 | AD63: =AD25*Inputs!$B$36/12*(1+Inputs!$B$43)^INT((29-1)/12) -> 0 | AE63: =AE25*Inputs!$B$36/12*(1+Inputs!$B$43)^INT((30-1)/12) -> 0 | AF63: =AF25*Inputs!$B$36/12*(1+Inputs!$B$43)^INT((31-1)/12) -> 0 | AG63: =AG25*Inputs!$B$36/12*(1+Inputs!$B$43)^INT((32-1)/12) -> 5512.5 | AH63: =AH25*Inputs!$B$36/12*(1+Inputs!$B$43)^INT((33-1)/12) -> 5512.5 | AI63: =AI25*Inputs!$B$36/12*(1+Inputs!$B$43)^INT((34-1)/12) -> 5512.5 | AJ63: =AJ25*Inputs!$B$36/12*(1+Inputs!$B$43)^INT((35-1)/12) -> 5512.5 | AK63: =AK25*Inputs!$B$36/12*(1+Inputs!$B$43)^INT((36-1)/12) -> 5512.5 | AL63: =AL25*Inputs!$B$36/12*(1+Inputs!$B$43)^INT((37-1)/12) -> 5788.125 | AM63: =AM25*Inputs!$B$36/12*(1+Inputs!$B$43)^INT((38-1)/12) -> 5788.125 | AN63: =AN25*Inputs!$B$36/12*(1+Inputs!$B$43)^INT((39-1)/12) -> 5788.125 | AO63: =AO25*Inputs!$B$36/12*(1+Inputs!$B$43)^INT((40-1)/12) -> 5788.125 | AP63: =AP25*Inputs!$B$36/12*(1+Inputs!$B$43)^INT((41-1)/12) -> 5788.125 | AQ63: =AQ25*Inputs!$B$36/12*(1+Inputs!$B$43)^INT((42-1)/12) -> 5788.125 | AR63: =AR25*Inputs!$B$36/12*(1+Inputs!$B$43)^INT((43-1)/12) -> 5788.125 | AS63: =AS25*Inputs!$B$36/12*(1+Inputs!$B$43)^INT((44-1)/12) -> 5788.125 | AT63: =AT25*Inputs!$B$36/12*(1+Inputs!$B$43)^INT((45-1)/12) -> 5788.125 | AU63: =AU25*Inputs!$B$36/12*(1+Inputs!$B$43)^INT((46-1)/12) -> 5788.125 | AV63: =AV25*Inputs!$B$36/12*(1+Inputs!$B$43)^INT((47-1)/12) -> 5788.125 | AW63: =AW25*Inputs!$B$36/12*(1+Inputs!$B$43)^INT((48-1)/12) -> 5788.125 | AX63: =AX25*Inputs!$B$36/12*(1+Inputs!$B$43)^INT((49-1)/12) -> 6077.5312 | AY63: =AY25*Inputs!$B$36/12*(1+Inputs!$B$43)^INT((50-1)/12) -> 6077.5312 | AZ63: =AZ25*Inputs!$B$36/12*(1+Inputs!$B$43)^INT((51-1)/12) -> 6077.5312 | BA63: =BA25*Inputs!$B$36/12*(1+Inputs!$B$43)^INT((52-1)/12) -> 6077.5312
