Workbook

Sheet Anleitung
A1: LoopforgeLab GmbH – Financial Projection Model
A3: Projektionszeitraum: 52 Monate (ca. 4,3 Jahre)
A5: INHALTSVERZEICHNIS
A6: Sheet 1: Anleitung – Diese Seite mit Übersicht und Legende
A7: Sheet 2: Inputs – Zentrale Eingabewerte (HIER STARTEN)
A8: Sheet 3: P&L – Gewinn- und Verlustrechnung (monatlich + jährlich)
A9: Sheet 4: Revenue – Detaillierte Umsatzmodellierung
A10: Sheet 5: Costs – Detaillierte Kostenaufschlüsselung
A11: Sheet 6: Balance Sheet – Vereinfachte Bilanz
A12: Sheet 7: Cash Flow – Kapitalflussrechnung mit Runway
A14: FARBCODIERUNG
A15: Blau | B15: Editierbare Eingabefelder
A16: Schwarz | B16: Formeln – nicht manuell ändern
A17: Grün | B17: Verweise auf andere Sheets
A18: Gelb hinterlegt | B18: Kritische Annahmen
A20: KURZANLEITUNG
A21: 1. Gehen Sie zum Sheet 'Inputs' und passen Sie alle blau markierten Werte an.
A22: 2. Alle anderen Sheets berechnen sich automatisch aus den Inputs.
A23: 3. Prüfen Sie die P&L, Revenue und Cash Flow Sheets auf Plausibilität.
A24: 4. Achten Sie auf rot markierte Warnungen (z.B. Runway < 6 Monate).
A25: 5. Exportieren Sie relevante Sheets als PDF für Investoren-Präsentationen.
A27: DISCLAIMER: Diese Projektion dient ausschließlich der Planung.
A28: Tatsächliche Ergebnisse können erheblich abweichen. Keine Garantie.

Sheet Treiber_Matrix
A1: LoopForgeLab – Treiber- & Annahmen-Matrix (importiert aus 260305_LFL_Treiber_Matrix_v1.xlsx)
A2: Alle Umsatz- und Kostentreiber | Szenarien: Gering · Normal · Stark | Spalten L & M: Eigene Bewertungen und Alternativwerte | NEU-markierte Zeilen: noch nicht im Modell — Entwicklungspotenzial
A3: Kategorie | B3: Unterkategorie | C3: Parameter / Treiber | D3: Aktueller Wert | E3: Einheit | F3: Szenario-Abhängigkeit | G3: Gering | H3: Normal | I3: Stark | J3: Einflussfaktor & Wirkungslogik | K3: Annahmen & Begründung | L3: ► Ihre Bewertung | M3: ► Neue Annahme
A5: Revenue 1: SaaS / Lizenzen
A6: UMSATZ | B6: SaaS / Lizenzen | C6: Startpreis pro Seat/Jahr | D6: 9.600 – 12.000 € | E6: €/Jahr | F6: Szenario | G6: 9600 | H6: 12000 | I6: 6000 | J6: Bestimmt den initialen Lizenzpreis je Nutzer-Seat. Direkter Multiplikator auf alle Lizenzerlöse. | K6: Automotive: höherer Preis durch Compliance-Wert (TISAX). Packaging: niedrigerer Einstiegspreis, Wachstum über Volumen & NRR. Value-based Pricing orientiert sich am TCO-Einsparpotenzial.
A7: UMSATZ | B7: SaaS / Lizenzen | C7: Jährliche Preiserhöhung | D7: 0.1 | E7: % p.a. | F7: Fest | G7: 0.1 | H7: 0.1 | I7: 0.1 | J7: Erhöht den Seat-Preis jährlich. Kompensiert Inflations- und Innovationskosten (Inferenz, neue Features). | K7: Standard für AI-SaaS 2026. Typisch: 3–10% p.a. Höherer Wert möglich bei starker Produktdifferenzierung.
A8: UMSATZ | B8: SaaS / Lizenzen | C8: Erster Umsatzmonat (Kunden) | D8: Monat 8–14 | E8: Monat | F8: Szenario | G8: Monat 14 | H8: Monat 8 | I8: Monat 9 | J8: Verschiebt den gesamten SaaS-Umsatz-Stream. Jeder Monat Verzögerung = direkte Liquiditätslücke. | K8: Automotive (Gering): lange Sales-Zyklen (9–12 Mon.) + TISAX-Prüfung. Packaging (Stark): kürzere IT-Entscheidungswege, frühere Piloten möglich.
A9: UMSATZ | B9: SaaS / Lizenzen | C9: Initiale Seats (1. Kunde) | D9: 5 | E9: Seats | F9: Fest | G9: 5 | H9: 5 | I9: 5 | J9: Anzahl der Seats beim ersten Kunden. Beeinflusst den initialen ARR-Wert und das Wachstums-Baseline. | K9: Konservative Annahme: 1–2 Pilotprojekte pro Werk. Land & Expand-Strategie: erst 1 Werk, dann Roll-out.
A10: UMSATZ | B10: SaaS / Lizenzen | C10: Monatliche Seat-Wachstumsrate | D10: 0.08 | E10: % / Monat | F10: Fest | G10: 0.08 | H10: 0.08 | I10: 0.08 | J10: Bestimmt, wie schnell neue Seats hinzukommen. Treiber für den kumulativen ARR-Aufbau. | K10: Alternative: Account-basierte Planung mit Stufenfunktion (Roll-out pro Werk statt linearer Rate). Realistischer Wert abhängig von Vertriebskapazität.
A11: UMSATZ | B11: SaaS / Lizenzen | C11: Enterprise-Deals ab Monat | D11: Monat 18 | E11: Monat | F11: Fest | G11: Monat 18 | H11: Monat 18 | I11: Monat 18 | J11: Ab diesem Monat werden größere Enterprise-Verträge abgeschlossen. Erhöht den durchschnittlichen ARR pro Kunde sprunghaft. | K11: Automotive: Verschiebung durch Technical Validation + Compliance. Typisch: 50.000–200.000 €/Jahr pro Enterprise-Kunde.
A12: UMSATZ | B12: SaaS / Lizenzen | C12: Durchschnittlicher Enterprise ARR | D12: 50000 | E12: €/Jahr | F12: Fest | G12: 50000 | H12: 50000 | I12: 50000 | J12: Erlös pro Enterprise-Vertrag. Beeinflusst den ARR-Sprung ab Monat 18 erheblich. | K12: Höheres Volumen durch tiefe Integration (DPP, Sustainability). Realistisch: 50.000–200.000 € je nach Kundentyp.
A13: UMSATZ | B13: SaaS / Lizenzen | C13: Enterprise Deals pro Quartal | D13: 2 | E13: Deals/Quartal | F13: Fest | G13: 2 | H13: 2 | I13: 2 | J13: Anzahl neuer Enterprise-Verträge pro Quartal. Direkter Treiber für den ARR-Aufbau nach Monat 18. | K13: Abhängig von Vertriebskapazität und Sales-Zyklus-Länge. Sollte mit Einstellungsplan abgestimmt sein.
A14: UMSATZ | B14: SaaS / Lizenzen | C14: Jährliche Churn Rate | D14: 0.06 | E14: % p.a. | F14: Fest | G14: 0.06 | H14: 0.06 | I14: 0.06 | J14: Anteil der Kunden, die jährlich abwandern. Reduziert den kumulativen ARR direkt. | K14: Konservative Planung für komplexe industrielle Buying Center. Typisch SaaS: 5–10%. Im Pilot-Jahr höher, ab Jahr 3 niedriger.
A15: UMSATZ | B15: SaaS / Lizenzen | C15: Net Revenue Retention (NRR) | D15: 1.25 | E15: % | F15: Fest | G15: 1.25 | H15: 1.25 | I15: 1.25 | J15: Expansion-Umsatz minus Churn. NRR > 100% bedeutet: Bestandskunden wachsen schneller als sie abwandern. | K15: Realisierbar durch DPP-Zusatzmodule und Material-Analytics-Upgrades. Typisch: 100–120%. 125% ist ambitioniert, aber bei starkem Upselling möglich.
A16: Revenue 2: Implementation-Support
A17: UMSATZ | B17: Implementation-Support | C17: Implementation-Support-Tagessatz | D17: 1.000 – 1.500 € | E17: €/Tag | F17: Szenario | G17: 1000 | H17: 1200 | I17: 1500 | J17: Verrechnungssatz für Beratungsleistungen. Multipliziert mit Tagen/Kunde ergibt den Erlös je Projekt. | K17: Automotive: niedrigerer Satz durch Preisdruck im Mittelstand. Packaging: höherer Satz durch Expertenstatus und Integrationskomplexität. Quelle: Marktanalyse Lothar.bm / Candemir.
A18: UMSATZ | B18: Implementation-Support | C18: Implementation-Support-Tage/Kunde | D18: 4 – 20 Tage | E18: Tage/Kunde | F18: Szenario | G18: 4 Tage | H18: 10 Tage | I18: 20 Tage | J18: Abrechnungsfähige Beratungstage je Kundenprojekt. Bestimmt zusammen mit dem Tagessatz den Erlös pro Implementation-Support-Kunde. | K18: Gering: standardisierter Onboarding-Prozess (4 Tage). Stark: tiefe Prozessintegration im Packaging (20 Tage). Formel: Implementation-Support-Umsatz/Kunde = Tagessatz × Tage/Kunde.
A19: UMSATZ | B19: Implementation-Support | C19: Implementation-Support-Umsatz/Kunde | D19: 4.000 – 30.000 € | E19: €/Kunde | F19: Berechnet | G19: 4000 | H19: 12000 | I19: 30000 | J19: Erlös pro beauftragendem Kunden. Berechnung: Tagessatz × Tage/Kunde. Beeinflusst den gesamten Implementation-Support-Umsatz-Stream. | K19: Gering: 1.000€ × 4 Tage = 4.000€/Kunde. Normal: 1.200€ × 10 Tage = 12.000€/Kunde. Stark: 1.500€ × 20 Tage = 30.000€/Kunde.
A20: UMSATZ | B20: Implementation-Support | C20: Implementation-Support-Quote (% Kunden) | D20: 20 – 100 % | E20: % Kunden | F20: Unabhängig | G20: 20 % (Niedrig) | H20: 50 % (Mittel) | I20: 100 % (Hoch) | J20: Anteil der Neukunden, die Implementation-Support beauftragen. UNABHÄNGIG vom strategischen Szenario einstellbar. Kombinierbar mit jedem der drei Szenarien (3×3-Matrix). | K20: Niedrig (20%): Self-Service-Kunden, minimaler Beratungsbedarf. Mittel (50%): Standardannahme, jeder zweite Kunde bucht Implementation-Support. Hoch (100%): Alle Kunden benötigen Onboarding-Unterstützung.
A21: UMSATZ | B21: Implementation-Support | C21: Implementation-Support-Startmonat | D21: Monat 3–6 | E21: Monat | F21: Szenario | G21: Monat 3 | H21: Monat 4 | I21: Monat 6 | J21: Monat des ersten Implementation-Support-Umsatzes. Implementation-Support startet als Enabler vor dem SaaS-Produkt. | K21: Gering: früher Start (Monat 3), da Automotive-Kunden sofort IT-Begleitung benötigen. Stark: späterer Start (Monat 6), da Packaging-Kunden länger Self-Service nutzen können.
A22: KOSTEN (OpEx)
A23: Personal & Gehälter
A24: KOSTEN | B24: Personal | C24: CEO Gehalt (Brutto/Jahr) | D24: 100000 | E24: €/Jahr | F24: Fest | G24: 100000 | H24: 100000 | I24: 100000 | J24: Gründer-Gehalt in der Pre-Seed-Phase. Beeinflusst die monatliche Burn Rate direkt. | K24: Gründer-Satz Pre-Seed. Anpassung ab Seed-Runde auf Marktgehalt. Typisch Startup: 60.000–90.000 €/Jahr.
A25: KOSTEN | B25: Personal | C25: CTO Gehalt (Brutto/Jahr) | D25: 100000 | E25: €/Jahr | F25: Fest | G25: 100000 | H25: 100000 | I25: 100000 | J25: Gründer-Gehalt in der Pre-Seed-Phase. Beeinflusst die monatliche Burn Rate direkt. | K25: Gründer-Satz Pre-Seed. Anpassung ab Seed-Runde auf Marktgehalt. Typisch Startup: 60.000–90.000 €/Jahr.
A26: KOSTEN | B26: Personal | C26: CCO Gehalt (Brutto/Jahr) | D26: 100000 | E26: €/Jahr | F26: Fest | G26: 100000 | H26: 100000 | I26: 100000 | J26: Gründer-Gehalt in der Pre-Seed-Phase. Beeinflusst die monatliche Burn Rate direkt. | K26: Gründer-Satz Pre-Seed. Anpassung ab Seed-Runde auf Marktgehalt. Typisch Startup: 60.000–90.000 €/Jahr.
A27: KOSTEN | B27: Personal | C27: Software Developer Gehalt | D27: 75000 | E27: €/Jahr | F27: Fest | G27: 75000 | H27: 75000 | I27: 75000 | J27: Erste strategische Einstellung. Fix-Position, nicht durch AI-Personal-Hebel verzögerbar.
A28: KOSTEN | B28: Personal | C28: Arbeitgeber-Nebenkosten | D28: 0.2 | E28: % auf Bruttogehalt | F28: Fest | G28: 0.2 | H28: 0.2 | I28: 0.2 | J28: Sozialversicherungsbeiträge des Arbeitgebers. Erhöht die effektiven Personalkosten um 20%. | K28: Standardsatz Deutschland 2026. Gesamtkosten pro MA = Bruttogehalt × 1,20.
A29: KOSTEN | B29: Personal | C29: Onboarding-Aufwand | D29: 30–120 Stunden | E29: Stunden/Kunde | F29: Szenario | G29: 120 Stunden | H29: 60 Stunden | I29: 30 Stunden | J29: Interner Aufwand für das Kunden-Onboarding. Bindet Entwickler- und Support-Kapazität. | K29: Gering: hoher Aufwand bei alten IT-Systemen (Automotive). Stark: standardisierter Self-Service-Prozess (Packaging). Quelle: Lothar.bm-Transkripte.
A30: Technologie & Cloud
A31: KOSTEN | B31: Technologie | C31: Cloud/Hosting Basis | D31: 2000 | E31: €/Monat | F31: Fest | G31: 2000 | H31: 2000 | I31: 2000 | J31: Fixe monatliche Grundkosten für Cloud-Infrastruktur. Unabhängig von der Kundenzahl. | K31: AWS/Azure/GCP Grundkonfiguration. Steigt mit Kundenzahl über den Skalierungsfaktor.
A32: KOSTEN | B32: Technologie | C32: Cloud-Skalierung pro Seat | D32: 80 | E32: €/Seat/Monat | F32: Skalierend | G32: 80 | H32: 80 | I32: 80 | J32: Variable Cloud-Kosten pro aktivem Seat. Wächst proportional zur Kundenbasis (szenarioabhängig). | K32: Gesamte Cloud-Kosten = Basis + (Seats × 80€). Im Stark-Szenario entstehen durch mehr Seats höhere Gesamtkosten.
A33: KOSTEN | B33: Technologie | C33: AI/ML APIs Basis | D33: 2000 | E33: €/Monat | F33: Fest | G33: 2000 | H33: 2000 | I33: 2000 | J33: Monatliche Grundkosten für KI-API-Nutzung (OpenAI/Anthropic/Frontier Models). | K33: Nutzung von GPT-5/Claude für Design-Logic. Wächst mit 8%/Monat proportional zur Nutzungsintensität.
A34: KOSTEN | B34: Technologie | C34: AI-Kosten Wachstum/Monat | D34: 0.08 | E34: % / Monat | F34: Fest | G34: 0.08 | H34: 0.08 | I34: 0.08 | J34: Monatliche Steigerungsrate der AI/ML-API-Kosten. Skaliert proportional zur Nutzung und Datentiefe. | K34: Skalierung proportional zur Nutzung und Datentiefe. Kann durch Open-Source-Modelle reduziert werden.
A35: KOSTEN | B35: Technologie | C35: SaaS Tools intern (Basis) | D35: 400 | E35: €/Monat | F35: Fest | G35: 400 | H35: 400 | I35: 400 | J35: Fixe monatliche Kosten für interne Tools (Slack, Notion, GitHub etc.). | K35: Standardpaket für Tech-Startups. Wächst mit Mitarbeiterzahl über den Pro-MA-Satz.
A36: KOSTEN | B36: Technologie | C36: SaaS Tools pro Mitarbeiter | D36: 100 | E36: €/MA/Monat | F36: Skalierend | G36: 100 | H36: 100 | I36: 100 | J36: Variable Tool-Kosten pro Mitarbeiter. Inkl. KI-Coding-Tools (Copilot/Cursor). | K36: Gesamte Tool-Kosten = Basis + (MAs × 100€). Im Gering-Szenario (mehr MAs) entstehen höhere Gesamtkosten.
A37: KOSTEN | B37: Technologie | C37: Sicherheit & Compliance | D37: 3500 | E37: €/Monat | F37: Fest | G37: 3500 | H37: 3500 | I37: 3500 | J37: Monatliche Kosten für Security-Tools und Compliance-Monitoring. Kritisch für TISAX-Zertifizierung im Automotive-Bereich. | K37: Puffer für TISAX-Audits und laufendes Compliance-Monitoring. Besonders relevant im Gering-Szenario (Automotive-Fokus).
A38: Marketing & Vertrieb
A39: KOSTEN | B39: Marketing & Vertrieb | C39: Paid Ads Budget (Initial) | D39: 1000 | E39: €/Monat | F39: Fest | G39: 1000 | H39: 1000 | I39: 1000 | J39: Monatliches Startbudget für bezahlte Werbung (Google, LinkedIn). Wächst mit 8%/Monat. | K39: Fokus eher auf Content/SEO im Industrie-Vertrieb. Skalierung mit Marktbekanntheit.
A40: KOSTEN | B40: Marketing & Vertrieb | C40: Content & SEO | D40: 2500 | E40: €/Monat | F40: Fest | G40: 2500 | H40: 2500 | I40: 2500 | J40: Monatliche Kosten für Content-Marketing und SEO. Fokus auf Whitepaper zu ROI, TCO und DPP-Compliance. | K40: Wichtiger Kanal für B2B-SaaS im Industriebereich. Langfristiger Aufbau von organischem Traffic.
A41: KOSTEN | B41: Marketing & Vertrieb | C41: Events & Messen/Ideation | D41: 3000 | E41: €/Jahr | F41: Fest | G41: 3000 | H41: 3000 | I41: 3000 | J41: Jährliche Kosten für Messeauftritte und Events. Wichtiger Kanal für Enterprise-Kundenkontakte. | K41: Erste Messeteilnahme/ Fachmessen
A42: KOSTEN | B42: Marketing & Vertrieb | C42: Events & Messen/Pre-Seed | D42: 10000 | E42: €/Jahr | F42: Fest | G42: 10000 | H42: 10000 | I42: 10000 | J42: Jährliche Kosten für Messeauftritte und Events. Wichtiger Kanal für Enterprise-Kundenkontakte. | K42: Messeteilnahme/ Fachmessen (nur die Gründer)
A43: KOSTEN | B43: Marketing & Vertrieb | C43: Events & Messen/Seed | D43: 15000 | E43: €/Jahr | F43: Fest | G43: 15000 | H43: 15000 | I43: 15000 | J43: Jährliche Kosten für Messeauftritte und Events. Wichtiger Kanal für Enterprise-Kundenkontakte. | K43: Präsenz auf Leitmessen (Hannover Messe, SPS). Hoher Posten – Überprüfung der Priorität empfohlen. Zusätzlich Sales-/Marketing MA auch auf Messebesuche
A44: KOSTEN | B44: Marketing & Vertrieb | C44: Events & Messen/Series A | D44: 25000 | E44: €/Jahr | F44: Fest | G44: 25000 | H44: 25000 | I44: 40000 | J44: Jährliche Kosten für Messeauftritte und Events. Wichtiger Kanal für Enterprise-Kundenkontakte. | K44: Präsenz auf Leitmessen (Hannover Messe, SPS). Hoher Posten – Überprüfung der Priorität empfohlen.
A45: KOSTEN | B45: Marketing & Vertrieb | C45: Events & Messen/Series B | D45: 25000 | E45: €/Jahr | F45: Fest | G45: 25000 | H45: 25000 | I45: 60000 | J45: Jährliche Kosten für Messeauftritte und Events. Wichtiger Kanal für Enterprise-Kundenkontakte. | K45: Zusätzlich Sales-/Marketing MA auch auf Messebesuche
A46: KOSTEN | B46: Marketing & Vertrieb | C46: Sales Provision | D46: 12 % | E46: % vom neuen ARR | F46: Skalierend | G46: 0.12 | H46: 0.12 | I46: 0.12 | J46: Vertriebsprovision als Anteil am neu gewonnenen ARR. Skaliert direkt mit dem Umsatzwachstum. | K46: Anreiz für Verkäufer. Im Stark-Szenario (höherer ARR) entstehen höhere absolute Provisionskosten.
A47: KOSTEN | B47: Marketing & Vertrieb | C47: Reisekosten Sales/MA/Monat | D47: 700 | E47: €/MA/Monat | F47: Skalierend | G47: 700 | H47: 700 | I47: 700 | J47: Monatliche Reisekosten pro Sales-Mitarbeiter. Notwendig für Werksbegehungen und Kundenbesuche. | K47: Besonders relevant im Automotive-Szenario (Gering) mit physischen Vor-Ort-Terminen bei Tier-1-Zulieferern.
A48: Professional Services & Sonstiges
A49: KOSTEN | B49: Professional Services | C49: Rechtsanwalt (Basis/Jahr) | D49: 8000 | E49: €/Jahr | F49: Fest | G49: 8000 | H49: 8000 | I49: 8000 | J49: Laufende Rechtsberatung (Verträge, IP, Arbeitsrecht). Basiskosten unabhängig von Finanzierungsrunden. | K49: Standard für Tech-Startups in Deutschland. Zusätzlich: 15.000€ pro Finanzierungsrunde.
A50: Kosten | B50: Professional Services | C50: Rechtsanwalt (pro Finanzierung) | D50: 15000 | E50: €/Jahr | F50: Fest | G50: 12000 | H50: 15000 | I50: 20000 | J50: Für jede Finanzierungsrunde ab Pre-Seed Anwalt erforderlich für Shareholder-Angelegenheiten | K50: Honoarhöhe abhängig von Geschwindigkeit und Anfall an Komplexität
A51: KOSTEN | B51: Professional Services | C51: Steuerberater | D51: 800 | E51: €/Monat | F51: Fest | G51: 800 | H51: 800 | I51: 800 | J51: Monatliche Kosten für laufende Buchhaltung und Steuerberatung. | K51: Standard für GmbH in Deutschland. Steigt mit Komplexität der Finanzstruktur.
A52: KOSTEN | B52: Professional Services | C52: Wirtschaftsprüfer (ab Monat 17) | D52: 12000 | E52: €/Jahr | F52: Fest | G52: – | H52: 12000 | I52: 12000 | J52: Jährliche Kosten für Wirtschaftsprüfung. Pflicht ab Series A für institutionelle Investoren. | K52: Start mit tatsächlicher Seed-Phase (Mitte 2027). Erst ab Monat 17 relevant.
A53: KOSTEN | B53: Sonstiges | C53: Weiterbildung/MA/Jahr | D53: 1000 | E53: €/MA/Jahr | F53: Skalierend | G53: 1000 | H53: 1000 | I53: 1000 | J53: Jährliche Weiterbildungskosten pro Mitarbeiter. Besonders wichtig im ML/KI-Bereich. | K53: Konferenzen, Online-Kurse, Zertifizierungen. Gesamtkosten skalieren mit Mitarbeiterzahl.
A54: KOSTEN | B54: Sonstiges | C54: Sonstiges / Puffer | D54: 5 % | E54: % der OpEx | F54: Fest | G54: 0.05 | H54: 0.05 | I54: 0.05 | J54: Puffer für ungeplante Ausgaben. Vorsichtsprinzip für unvorhergesehene Kosten. | K54: Standard-Puffer für Startup-Finanzplanung. Empfehlung: mindestens 5% der gesamten OpEx.
A55: INVESTITIONEN (CapEx)
A56: Hardware & Ausstattung
A57: OPEX | B57: Hardware | C57: Laptop pro Mitarbeiter | D57: 80 | E57: €/Monat/MA | F57: Skalierend | G57: 80 | H57: 80 | I57: 100 | J57: MA bekommen keine eigenen Geräte sondern Leihgeräte von Grover | K57: Grundsätzlich Reduzierung von CAPEX durch Mietmodell. Kann im Einzelfall verändert werden, wenn es besondere Bedarfe gibt
A58: OPEX | B58: Hardware | C58: Monitor & Peripherie pro MA | D58: 40 | E58: €/Monat/MA | F58: Skalierend | G58: 40 | H58: 40 | I58: 60 | J58: MA bekommen keine eigenen Geräte sondern Leihgeräte von Grover | K58: Grundsätzlich Reduzierung von CAPEX durch Mietmodell. Kann im Einzelfall verändert werden, wenn es besondere Bedarfe gibt
A59: Büro & Facilities
A60: Kosten | B60: Büro | C60: Coworking/Shared Desk | D60: 400 | E60: €/Monat/MA | F60: Skalierend | G60: 350 | H60: 400 | I60: 400 | J60: Zu Beginn nur Shared Desks im Coworking Space | K60: In der Ideation Phase geringer Bedarf, In der Pre-Seed Phase erste MA eingestellt. Bedarf an festen Desks im Coworking Space
A61: CAPEX | B61: Büro | C61: Büromiete (Initial): keine, da zunächst Coworking Space/ Shared Desks | D61: 0 | E61: €/Monat | F61: Fest | G61: 0 | H61: 0 | I61: 0 | J61: Monatliche Miete für Coworking-Space in der Anfangsphase. Wechselt ab Monat 18 auf größeres Büro. | K61: Coworking-Fokus in der ersten Phase (Berlin Mitte/Kreuzberg). Shift analog zur Einstellung von Solution Architects.
A62: CAPEX | B62: Büro | C62: Büromiete (ab Seed/M18) | D62: 4500 | E62: €/Monat | F62: Fest | G62: 3500 | H62: 4000 | I62: 4500 | J62: Monatliche Miete nach dem Seedfinanzierung ab Monat 18. Für ca. 10–20 Personen ausgelegt. | K62: Berliner Marktpreise für Bürofläche. Upgrade-Zeitpunkt kann szenariospezifisch angepasst werden.
A63: CAPEX | B63: Büro | C63: Büroausstattung (Initial) | D63: 5000 | E63: € (einmalig) | F63: Fest | G63: 5000 | H63: 5000 | I63: 5000 | J63: Einmalige Investition für Möbel und IT-Grundausstattung. Fällt beim Start an. | K63: Standard-Erstausstattung für kleines Tech-Team. Kein szenarioabhängiger Einfluss.
A64: NEUE / POTENZIELLE SZENARIEN
A65: Umsatz – Neue Treiber
A66: NEU | B66: SaaS-Pricing | C66: Produkt-Tiers (Basic/Pro/Enterprise) | D66: Noch nicht modelliert | E66: – | F66: Zu definieren | G66: Basic: ~5.000 €/J | H66: Pro: ~12.000 €/J | I66: Enterprise: ~25.000 €/J | J66: Gestaffelte Pakete mit unterschiedlichen Features und Preisen. Erhöht die Preisflexibilität und Marktabdeckung. | K66: Noch nicht im Modell. Würde den Startpreis-Parameter durch eine Tier-Verteilung ersetzen.
A67: NEU | B67: SaaS-Umsatz | C67: Upselling-Effizienz (NRR-Varianten) | D67: NRR: 125 % (fest) | E67: % | F67: Zu definieren | G67: NRR: 105 % | H67: NRR: 115 % | I67: NRR: 130 % | J67: Unterschiedliche NRR-Szenarien je nach Upselling-Erfolg. Direkter Einfluss auf den langfristigen ARR. | K67: Aktuell als fester Wert (125%) modelliert. Szenariofähig machen würde die Sensitivitätsanalyse verbessern.
A68: NEU | B68: SaaS-Umsatz | C68: Churn-Varianten | D68: Churn: 6 % (fest) | E68: % p.a. | F68: Zu definieren | G68: Hoher Churn: 10 % | H68: Normal: 6 % | I68: Niedriger Churn: 3 % | J68: Unterschiedliche Churn-Szenarien je nach Kundenbindung. Direkter Einfluss auf den kumulativen ARR. | K68: Aktuell als fester Wert (6%) modelliert. Besonders relevant für Langfristprojektionen (Jahr 3–5).
A69: NEU | B69: Marktexpansion | C69: Internationalisierung | D69: Noch nicht modelliert | E69: – | F69: Zu definieren | G69: Keine Expansion | H69: EU-Expansion (Y2) | I69: US-Expansion (Y3) | J69: Multiplikator auf das Kundenwachstum ab einem definierten Monat. Erheblicher Einfluss auf ARR und Personalplanung. | K69: Noch nicht im Modell. Würde zusätzliche Kosten (Lokalisierung, Compliance, Personal) erfordern.
A70: Kosten – Neue Treiber
A71: NEU | B71: Personal | C71: Gehaltsniveau-Faktor | D71: Noch nicht modelliert | E71: Faktor | F71: Zu definieren | G71: 85 % des Markts | H71: 100 % des Markts | I71: 115 % des Markts | J71: Prozentualer Faktor auf alle Gehälter im Einstellungsplan. Direkter Einfluss auf die gesamte Personalkostenbasis. | K71: Noch nicht im Modell. Besonders relevant für Talent-Wettbewerb im Berliner KI-Markt.
A73: LEGENDE – Szenario-Abhängigkeit
A74: Szenario | B74: Wert ändert sich je nach aktivem Szenario (Gering/Normal/Stark) in der 00_Input_Sandbox
A75: Unabhängig | B75: Eigenständiger Schalter – unabhängig vom Szenario einstellbar (z.B. Implementation-Support-Quote: 20%/50%/100%)
A76: Berechnet | B76: Abgeleiteter Wert – wird automatisch aus anderen Parametern berechnet (kein direkter Eingabewert)
A77: Skalierend | B77: Fester Satz, aber Gesamtbetrag skaliert mit Mitarbeiterzahl oder Kundenzahl
A78: Fest | B78: Fester Wert – unabhängig von Szenario und Unternehmensgröße
A79: Zu definieren | B79: Noch nicht im Modell – neuer Einflussfaktor, der entwickelt werden kann
A81: LEGENDE: Szenario=szenarioabhängig (Sandbox) | Unabhängig=eigenständiger Schalter (z.B. Implementation-Support-Quote) | Berechnet=abgeleiteter Wert | Skalierend=fixer Satz, skaliert mit MA/Kunden | NEU (lila)=noch nicht im Modell

Sheet Szenarien_Analyse
A1: Faktor | B1: Referenz (Basis) | C1: Szenario: Gering | D1: Szenario: Normal | E1: Szenario: Stark | F1: DELTA: (Stark vs Normal) | G1: Argumentation (Interviews & Transkripte) | I1: ⚑ HINWEIS: Werte in den Spalten C/D/E (Gering/Normal/Stark) sind direkt bearbeitbar. Änderungen in DIESEM Blatt fließen automatisch über Sandbox → Inputs → Revenue/P&L.
A2: Fokus: Packaging | B2: 0.3 | C2: 0.1 | D2: 0.6 | E2: 0.8 | F2: =E2-D2 | G2: Höhere Margen, schnellere Zyklen als Auto.
A3: Fokus: Automotive | B3: 0.7 | C3: 0.9 | D3: 0.4 | E3: 0.2 | F3: =E3-D3 | G3: Hohe IT-Hürden und Margendruck (Lothar).
A4: Erste zahlende Kunden Monat | B4: 6 | C4: 14 | D4: 8 | E4: 4 | F4: =E4-D4 | G4: IT-Integration ist der Flaschenhals.
A5: Buchungs-Wahrscheinlichkeit Implementation-Support je Kunde | B5: 0.5 | C5: 0.2 | D5: 0.5 | E5: 1 | F5: =E5-D5 | G5: Wahrscheinlichkeit, dass ein gewonnener Kunde Implementation-Support bucht: a) 20 % (gering) = jeder 5. Kunde – Automotive, wenig Beratungsbedarf b) 50 % (normal) = jeder 2. Kunde – Hybrid-Markt c) 100 % (stark) = jeder Kunde – Packaging, hohe Implementierungstiefe → Fließt über Sandbox Z.12 → Inputs Z.139 → Revenue Z.28 | H5: → Sandbox → Inputs
A6: Startpreis pro Seat/Jahr | B6: 1 | C6: 0.8 | D6: 1 | E6: 1.2 | F6: =E6-D6 | G6: Value-Pricing eher in Packaging möglich.
A7: Personal (Experten) in FTE | B7: 5 | C7: 3 | D7: 7 | E7: 12 | F7: =E7-D7 | G7: Bedarf an "Übersetzern" für IT-Landschaft.
A8: Implementation-Support-Tage/Einsatz | B8: 10 | C8: 5 | D8: 10 | E8: 20 | F8: =E8-D8 | G8: Implementation-Support-Tage pro Kunde je Einsatz: gering=5 (Basisschulung + Systemcheck) normal=10 (Implementierungsbegleitung + Anwenderschulung) stark=20 (Spez. Anforderungen, Datenbereinigung, Stammdaten-Harmonisierung) → Fließt über Sandbox Z.11 → Inputs Z.140 → Revenue Z.28 | H8: → Sandbox → Inputs
A9: Net Revenue Retention (NRR) Umsatz von bestehenden Kunden im Vergleich zum Vorjahr – inklusive Upgrades, Downgrades und Kündigungen. Ein NRR von 110% bedeutet z.B., dass Bestandskunden dieses Jahr 10% mehr zahlen als letztes Jahr, selbst ohne einen einzigen Neukunden. Für SaaS-Startups gilt ein NRR über 100% als starkes Signal für Product-Market-Fit, weil es zeigt, dass Kunden bleiben und mehr ausgeben. Benchmark im B2B-SaaS: >120% ist exzellent, >100% ist solide. | B9: 1.15 | C9: 1.8 | D9: 1.15 | E9: 1.3 | F9: =E9-D9 | G9: Treiber-Matrix: NRR szenarioabhängig machen (bisher fest 125%). Gering=105%: Automotive, wenig Upselling-Potenzial. Normal=115%: Hybrid, DPP-Module. Stark=130%: Packaging, Analytics-Premium + Multi-Werk-Rollouts. | H9: → Sandbox → Inputs
A10: Jährliche Churn Rate | B10: 0.06 | C10: 0.1 | D10: 0.06 | E10: 0.03 | F10: =E10-D10 | G10: Treiber-Matrix: Churn szenarioabhängig (bisher fest 6%). Gering=10%: Automotive-Budgetzyklen, höheres Abwanderungsrisiko. Normal=6%: Standardwert (SaaS-Industrie). Stark=3%: Packaging, tiefe API-Integration → hoher Switching-Cost. | H10: → Sandbox → Inputs
A11: Implementation-Support-Startmonat | B11: 4 | C11: 3 | D11: 4 | E11: 6 | F11: =E11-D11 | G11: Treiber-Matrix Z.21: Implementation-Support startet als Enabler vor dem SaaS-Produkt. Gering=Monat 3: Automotive benötigt sofort IT-Begleitung. Stark=Monat 6: Packaging-Kunden länger Self-Service-fähig. | H11: → Sandbox → Inputs

Sheet 00_Input_Sandbox
A1: Aktives Szenario | B1: gering | C1: Einheit | D1: Gering (Auto-Fokus) | E1: Normal (Hybrid) | F1: Stark (Pack-Fokus) | G1: Argumentation / Quelle
A2: Kategorie | B2: Variable | C2: Einheit | D2: Gering | E2: Normal | F2: Stark | G2: Quelle
A3: Markt-Mix | B3: Anteil Packaging | C3: % | D3: 0.1 | E3: 0.6 | F3: 0.8 | G3: Lothar: Packaging hat schnellere Zyklen.
A4: Vertrieb | B4: Startmonat Kunden | C4: Monate | D4: 17 | E4: 8 | F4: 4 | G4: Lothar: IT-Hürden bei Automotive Tier-1.
A5: Revenue 1 | B5: Startpreis Seat/Monat | C5: €/Monat | D5: 200 | E5: 350 | F5: 450 | G5: Value-based Pricing in Packaging (White Paper).
A6: Revenue 2 | B6: Implementation-Support-Tagessatz | C6: €/Tag | D6: 1000 | E6: 1200 | F6: 1500 | G6: Implementation-Support-Tagessatz: gering=1.000 €/Tag | normal=1.200 €/Tag | stark=1.500 €/Tag. Basiert auf Expertenstatus (Haag/Candemir) und Marktniveau B2B Industrie.
A7: Effizienz | B7: Iterations-Reduktion | C7: Faktor | D7: 1,2x | E7: 2,0x | F7: 3,0x | G7: White Paper: Redesign Trap vermeiden.
A8: Kosten | B8: Onboarding-Aufwand | C8: Stunden | D8: 120 | E8: 60 | F8: 30 | G8: Lothar: Hoher Aufwand bei alten IT-Systemen.
A9: Detailbeschreibung
A10: Revenue 2: Implementation-Support Einsatztage je Kunde initial | B10: Implementation-Support-Tage/Einsatz | C10: Tage/Einsatz | D10: =Szenarien_Analyse!C8 | E10: =Szenarien_Analyse!D8 | F10: =Szenarien_Analyse!E8 | G10: Referenziert Szenarien_Analyse Z.8 (dort bearbeitbar). gering=5 Tage | normal=10 Tage | stark=20 Tage. Direkte Eingabe hier überschreibt die Szenarien-Referenz.
A11: Revenue 2: Buchungs-Wahrscheinlichkeit Implementation-Support je Kunde | B11: Buchungs-Wahrscheinlichkeit Implementation-Support | C11: % | D11: =Szenarien_Analyse!C5 | E11: =Szenarien_Analyse!D5 | F11: =Szenarien_Analyse!E5 | G11: Referenziert Szenarien_Analyse Z.5 (dort bearbeitbar). a) gering=20% – jeder 5. Kunde kauft Implementation-Support, b) normal=50% – jeder 2. Kunde, c) stark=100% – jeder Kunde kauft Implementation-Support-Tage.
A12: Retention: Net Revenue Retention (NRR) | B12: Net Revenue Retention (NRR) | C12: % | D12: 1.05 | E12: =Szenarien_Analyse!D9 | F12: =Szenarien_Analyse!E9 | G12: Szenarioabhängig (Szenarien_Analyse Z.9). Gering=105% | Normal=115% | Stark=130%.
A13: Retention: Jährliche Churn Rate | B13: Churn Rate | C13: %/Jahr | D13: =Szenarien_Analyse!C10 | E13: =Szenarien_Analyse!D10 | F13: =Szenarien_Analyse!E10 | G13: Szenarioabhängig (Szenarien_Analyse Z.10). Gering=10% | Normal=6% | Stark=3%.
A14: Implementation-Support: Startmonat erster Implementation-Support-Umsatz | B14: Implementation-Support-Startmonat | C14: Monat | D14: =Szenarien_Analyse!C11 | E14: =Szenarien_Analyse!D11 | F14: =Szenarien_Analyse!E11 | G14: Szenarioabhängig (Szenarien_Analyse Z.11). Gering=3 | Normal=4 | Stark=6.

Sheet Inputs
A1: ZENTRALE EINGABEWERTE | B1: Wert | C1: Erklärung / Hinweis | D1: Bemerkungen | E1: Szenarioauswahl: gering, normal, stark
A2: To Do 10.3.26: * Den Begriff Consulting verändern in Implementierungs Support. * Checken ob die wesentlichen Parameter in Bezug auf Kostenhöhe et cetera abgeglichen worden sind mit den Informationen aus der Tabelle für den initialen Startpunkt Funding ideation Phase. * Einen anderen Kostensatz annehmen in Bezug auf Anwaltskosten. * Checken ob die absoluten Kostenhöhen so passen. * Checken welche Annahmen hinter den Produkt Feature Entwicklungen stecken können. * Wie es mit der entsprechenden Mannschaft eine Produktentwicklung und ein Rollout stattfinden kann wie er geplant ist. * Berücksichtigen dass einerseits Produkte gebaut andererseits aber auch Implementierung Projekte geleitet und umgesetzt werden müssen. * Diese Fragen auch auf das Thema Customer Success und Sales beziehungsweise Investor Relations ausrollen. * Prüfen ob Olaf René für diese Aufgaben ausreichend Zeit und Kapazität haben. * Mouaz in der Lage ist in dem verfügbaren Zeitrahmen diese Aufgaben umzusetzen, was realistischerweise berücksichtigt werden muss um diese Aufgaben tatsächlich auch umzusetzen. * Ziel sollte eine Szenario beschreibungs sein der besprochenen Vorgehensweise. * Ziel sollte auch sein hier die entsprechenden Bezüge zu den einzelnen Phasen herzustellen und genau zu beschreiben was in jeder Phase gemacht wird, was in jeder Phase kundenseitig und Revenue-seitig erreicht werden muss, welche Anforderungen damit verbunden sind und wie die Kunden gefunden werden sollen. * Also sprich wie viele Letters of Intent, wie viele Pilot-Kunden brauchen wir, in welchen Branchen und was bedeutet das Final für das Produkt. | E2: ='00_Input_Sandbox'!$B$1
A3: ALLGEMEINE EINSTELLUNGEN
A4: Firmenname | B4: LoopforgeLab GmbH | C4: Name des Unternehmens
A5: Startdatum | B5: 46113 | C5: Beginn der Projektionen
A6: Währung | B6: EUR | C6: EUR für DACH-Startups
A7: Steuersatz | B7: 0.3 | C7: KSt + GewSt (~30% in DE) | D7: Übernahme des Standardsatzes (KSt + GewSt in Deutschland).
A9: FINANZIERUNGSRUNDEN
A10: Ideation Phase | B10: 90000 | C10: Typisch: 100.000-500.000€ | D10: Phase: 1.4.26 bis 15.7.2026 MVP-Anschubfinanzierung; stellt keine Unternehmensbewertung dar.
A11: Ideation Phase | B11: 1 | C11: Monat der Einzahlung | D11: MVP-Entwicklung und IP-Aufbau starten unmittelbar.
A12: Pre-Seed Betrag | B12: 1500000 | C12: Typisch: 500.000-2.000.000€ | D12: Pre-Seed Phase ab VC Pitch im Juli '26 (1.5M-3M Bewertung).
A13: Pre-Seed Monat | B13: 5 | C13: Typisch: Monat 5 | D13: Juli 2026 entspricht Monat 5 Fokus auf Pilot-Traction.
A14: Seed Betrag | B14: 4000000 | C14: Typisch: 3.000.000-10.000.000€ | D14: Abhängig von Pilotprojekten und Reife des Produktes
A15: Seed Monat | B15: 17 | C15: Typisch: Monat 17 | D15: Geplant für Mitte 2027.
A16: Series A Betrag | B16: 10000000 | C16: Typisch: 10.000.000-25.000.000€ | D16: Vorerst unverändert als langfristige Wachstumsambition.
A17: Series A Monat | B17: 36 | C17: Typisch: Monat 35 | D17: Geplant für Herbst 2028.
A19: REVENUE-ANNAHMEN (SaaS/ARR)
A20: Startpreis pro Seat/Jahr | B20: =VLOOKUP("Startpreis Seat/Monat",'00_Input_Sandbox'!$B$2:$F$19,IF('00_Input_Sandbox'!$B$1="gering",3,IF('00_Input_Sandbox'!$B$1="normal",4,5)),FALSE)*12 | C20: Jährliche Lizenzgebühr pro Nutzer | D20: 1. Realistisch? Hängt auch ab vom Business Modell..Pricing basierend auf Wettbewerb oder auf voraussichtlichem Einsparpotential? 2. weitere Erlösquellen? Beratung? Implementierungsaufwand? Hybrid-Modell: Deckt Fixkosten und partizipiert am TCO-Einsparwert. [1] | F20: 2. Regulatory Moat (DPP): JE nach Branche (hier: Annahme von neuen Zielbranche in Bezuf auf DPP Verpflichtung) Die Zielbranchen Batterien und Elektronik unterliegen ab 2027 der DPP-Pflicht. Dies rechtfertigt höhere Preise und eine stärkere NRR, da LFL hiermit zur "Compliance Engine" des Kunden wird. -->"Compliance" könnte aber auch durch andere Benefits ersetzt werden
A21: Preiserhöhung/Jahr | B21: 0.05 | C21: Typisch: 3-5% p.a. | D21: Standard für AI-SaaS 2026 (Kompensation Inferenz/Innovation). [4]
A22: Erste zahlende Kunden Monat | B22: =VLOOKUP("Startmonat Kunden",'00_Input_Sandbox'!$B$2:$F$19,IF('00_Input_Sandbox'!$B$1="gering",3,IF('00_Input_Sandbox'!$B$1="normal",4,5)),FALSE) | C22: Wann erster Umsatz? | D22: Erster Umsatz in Monat 8 (Start: 04/26)…Realistisch? Wie lange Lead-Time? Zielkunden? Beachhead-Market? Weitere Begründung: wenn im Automotivebereich: Puffer für Sales-Zyklen (9-12 Mon.) und TISAX im Mittelstand. [1
A23: Initiale Seats | B23: 3 | C23: Anzahl Seats beim Kunden | D23: Realistisch? Hängt von Kundengrösse ab. Implementierungsaufwand je Kunde mit einkalkulieren weitere Aspekte: Kalkulieren mit 1-2 Projekten/ Start mit Pilotprojekten (Werke) zur ROI-Validierung ("Land&Expand")
A24: Monatliche Seat-Wachstumsrate | B24: 0.03 | C24: Wachstum neue Seats/Monat | D24: -->hier eine Annahme bzgll Vertriebsplanung treffen. Wie hoch ist die Zahl der Verkauften Sitze nach 1, 2, 3 Jahren? Gibt es noch andere Erlösströme? ALTERNATIVE: Account-basierte Planng: Wechsel auf "Stufenfunktion" beim Aufbau des Geschäfts (Roll-out pro Werk statt linearer Rate)
A25: Enterprise-Deals ab Monat | B25: 20 | C25: Fokus auf Packaging Industrie Wenn Automotive: Verschiebung durch längere Technical Validation und Compliance-Hürden. | D25: Start ab Fertigstellung MVP in der Seed Phase | F25: 3. Vertriebsrealismus: Der Start des Umsatzes wurde nach hinten geschoben da der industrielle Mittelstand ("Hidden Champions") langsame Entscheidungsprozesse und hohe Sicherheitsanforderungen (TISAX) hat. Die Zeit bis zum Juli 2026 wird für die Validierung der TCO-Einsparungen (Ausschuss-Reduktion) bei Pilotkunden genutzt.
A26: Durchschnitt Enterprise ARR | B26: 25000 | C26: Typisch: 50.000-200.000€/Jahr | D26: Höheres Volumen durch Tiefe der Integration: hier Annahme von weiteren Benefits wie Einbeziehung von DPP & Sustainability
A27: Enterprise Deals pro Quartal | B27: 1 | C27: Neue Enterprise-Deals pro Quartal
A28: Jährliche Churn Rate | B28: =VLOOKUP("Churn Rate",'00_Input_Sandbox'!$B$2:$F$19,IF('00_Input_Sandbox'!$B$1="gering",3,IF('00_Input_Sandbox'!$B$1="normal",4,5)),FALSE) | C28: Jährliche Churn Rate (szenarioabhängig): Gering=10% | Normal=6% | Stark=3% | D28: Treiber-Matrix: Churn jetzt szenarioabhängig (vorher fest 15%). Automotive: 10% (Budgetzyklen). Packaging: 3% (hoher Switching-Cost).
A29: Net Revenue Retention | B29: =VLOOKUP("Net Revenue Retention (NRR)",'00_Input_Sandbox'!$B$2:$F$19,IF('00_Input_Sandbox'!$B$1="gering",3,IF('00_Input_Sandbox'!$B$1="normal",4,5)),FALSE) | C29: Net Revenue Retention (szenarioabhängig): Gering=105% | Normal=115% | Stark=130% | D29: Treiber-Matrix: NRR jetzt szenarioabhängig (vorher fest 125%). Expansion-Umsatz minus Churn. NRR>100%=Bestandskunden wachsen.
A31: GEHÄLTER (Brutto/Jahr)
A32: CEO Gehalt | B32: 100000 | C32: Bestätigtes Gründergehalt: CEO/CTO/CCO je €100.000/Jahr (Brutto) | D32: Rene: negotiatable for Ideation Phase
A33: CTO Gehalt | B33: 100000 | C33: Bestätigtes Gründergehalt: CEO/CTO/CCO je €100.000/Jahr (Brutto)
A34: CCO Gehalt | B34: 100000 | C34: Bestätigtes Gründergehalt: CEO/CTO/CCO je €100.000/Jahr (Brutto)
A35: Software Developer | B35: 75000 | C35: Typisch: 55.000-90.000€ | D35: Source: various Sources (https://claude.ai/chat/0f63ea1a-6930-460c-954d-87864e88929e)
A36: Junior Software Developer | B36: 52000 | C36: Typisch: 42.000-58.000€ | D36: Source: various Sources (https://claude.ai/chat/0f63ea1a-6930-460c-954d-87864e88929e)
A37: ML/AI Engineer Gehalt | B37: 70000 | C37: Typisch: 50.000-125.000€ | D37: Source: various Sources (https://claude.ai/chat/0f63ea1a-6930-460c-954d-87864e88929e)
A38: Site Reliability Engineer | B38: 70000 | C38: Typisch: 50.000-110.000€ | D38: Source: various Sources (https://claude.ai/chat/0f63ea1a-6930-460c-954d-87864e88929e)
A39: UX/UI Designer | B39: 50000 | C39: Typisch: 42.000-80.000€ | D39: Source: various Sources (https://claude.ai/chat/0f63ea1a-6930-460c-954d-87864e88929e)
A40: Mechanical Engineer (incl. SoftwareDev) | B40: 70000 | C40: Typisch: 45.000-85.000€ | D40: Source: various Sources (https://claude.ai/chat/0f63ea1a-6930-460c-954d-87864e88929e)
A41: Customer Key Account Gehalt | B41: 100000 | C41: Typisch: 50.000-70.000€ + Provision | D41: Split 50/50 (65k fix + 65k var); zwingend für Enterprise-Vertrieb. [12
A42: Marketing Manager Gehalt | B42: 65000 | C42: Typisch: 55.000-75.000€ | D42: Anpassung an Marktniveau für B2B-Industrie-Spezialisten.
A43: Marketing Assistant Gehalt | B43: 45000
A44: Customer Success Gehalt | B44: 52000 | C44: Typisch: 45.000-60.000€
A45: Office Manager Gehalt | B45: 45000 | C45: Typisch: 40.000-50.000€
A46: Finance Manager | B46: 80000
A47: Jährliche Gehaltserhöhung | B47: 0.03 | C47: Typisch: 3-5% | D47: Berücksichtigt Inflations- und Kompetenzentwicklung im Tech-Sektor.
A48: Lohnnebenkosten | B48: 0.21 | C48: AG-Anteil Sozialversicherung ~20-21% | D48: Übernahme des gesetzlichen AG-Anteils.
A50: EINSTELLUNGSPLAN (Eintrittsmonat) | B50: geplanter Bedarf/ Zeitpunkt des geplanten Eintritts | C50: WICHTIG: KEINE Zeilen löschen. Wenn nicht benötigt, einfach SPALTE B nicht befüllen | E50: Tatsächlicher Eintritt ins Unternehmen
A51: 1. Software Developer | B51: 5 | C51: Software Developer | E51: =B51
A52: 2. Software Developer | B52: 17 | C52: Software Developer | E52: =B52
A53: 1. Junior Software Developer | B53: 9 | C53: Junior Developer | E53: =B53
A54: 1. ML/AI Engineer | B54: 8 | C54: ML/AI Spezialist | E54: =B54
A55: 1. Mechanical Engineer | B55: 11 | C55: Mec Engineer/Developer | D55: combining mechanical engineering with CAD automation, robotics software, or embedded systems | E55: =B55
A56: 1. UX/UI Designer | B56: 12 | C56: UX/UI Designer | E56: =B56
A57: 1. Customer Key Account | B57: 17 | C57: Sales & Key Account DACH | E57: =B57
A58: 2. Customer Key Account | B58: 20 | C58: Sales & Key Account DACH | E58: =B58
A59: 3. Customer Key Account | B59: 29 | C59: Sales & Key Account PL/CZ/Benelux | E59: =B59
A60: 1. Marketing Assistant | B60: 20 | C60: Marketing Support | E60: =B60
A61: 2. Marketing Assistant | B61: 29 | C61: Marketing Support | E61: =B61
A62: 1. Marketing Manager | B62: 18 | C62: Marketing | E62: =B62
A63: 1. Office Manager | B63: 14 | C63: Admin/Office | E63: =B63
A64: 1. Customer Success | B64: 24 | C64: CS Mgr | D64: taking care of Customer Projects and Support | E64: =B64
A65: 1. Finance Manager | B65: 19 | C65: Finance/Controlling | D65: Notwendig für professionelles Reporting ab Seed-Phase. | E65: =B65
A67: TECHNOLOGIE & CLOUD KOSTEN
A68: Cloud/Hosting Basis | B68: 2000 | C68: AWS/Azure/GCP Grundkosten €/Monat | D68: Höhere Last durch GPU-Inferenz und Vektordatenbanken. 800→2.000 €/Monat (Treiber-Matrix)
A69: Cloud Skalierung pro Seat | B69: 80 | C69: Variable Kosten €/Seat/Monat | D69: Wechsel von Seat- auf Projekt-Basis (AI-intensive Rechenlast). 50→80 €/Seat/Monat (Treiber-Matrix)
A70: AI/ML APIs Basis | B70: 2000 | C70: OpenAI/Anthropic etc. €/Monat | D70: Nutzung von Frontier Models (GPT-5/Claude) für Design-Logic. 600→2.000 €/Monat (Treiber-Matrix)
A71: AI Kosten Wachstum/Monat | B71: 0.08 | C71: Steigerung mit Nutzung | D71: Skalierung proportional zur Nutzung und Datentiefe. 3%→8%/Monat (Treiber-Matrix)
A72: SaaS Tools intern Basis | B72: 400 | C72: Slack, Notion, GitHub etc. €/Monat | D72: Slack; Notion; GitHub etc. (unverändert).
A73: SaaS Tools pro MA | B73: 100 | C73: Zusätzliche Lizenzen €/MA/Monat | D73: Inklusive KI-Coding-Tools (Copilot/Cursor) für Dev-Effizienz.
A74: Software-Lizenzen Dev | B74: 5000 | C74: IDE, Frameworks €/Jahr | D74: Spezialisierte Engineering-Tools und Frameworks (IDE).
A75: Sicherheit & Compliance | B75: 3500 | C75: Security Tools €/Monat | D75: Puffer für TISAX-Audits und laufendes Compliance-Monitoring. [17
A77: HARDWARE & EQUIPMENT
A78: Laptop pro MA | B78: 2500 | C78: Typisch: 1.500-3.000€ | D78: High-End Hardware zwingend für KI-Entwicklung (lokale Inferenz). -->CHANGE to smaller numbers, at least Think of renting IT (GROVER)
A79: Monitor & Peripherie | B79: 800 | C79: Typisch: 500-1.000€ | D79: Standard-Setup für Tech-Mitarbeiter.
A80: Ersatz-Zyklus Monate | B80: 36 | C80: Typisch: 36-48 Monate | D80: Branchenüblicher Turnus.
A81: Sonstige IT-Ausstattung/Jahr | B81: 2000 | C81: Server, Netzwerk etc. | D81: Puffer für Serverkomponenten/Netzwerk.
A83: BÜRO & FACILITIES
A84: Büromiete | B84: 1500 | C84: Coworking anfangs €/Monat | D84: Coworking-Fokus in der ersten Phase (Berlin Mitte/Kreuzberg).
A85: Büro-Upgrade ab Monat | B85: 18 | C85: Wann größeres Büro? | D85: Shift analog zur Einstellung von Solution Architects (Teamgröße).
A86: Neue Büromiete | B86: 4500 | C86: Kosten nach Upgrade €/Monat | D86: Anpassung an Berliner Marktpreise für ca. 15-20 Personen.
A87: Nebenkosten | B87: 300 | C87: Strom, Wasser, Heizung €/Monat | D87: Übernahme.
A88: Internet & Telefon | B88: 150 | C88: €/Monat | D88: Übernahme.
A89: Büroausstattung Initial | B89: 5000 | C89: Möbel, Einrichtung € | D89: Möbel und IT-Grundausstattung für Erst-Team.
A90: Bürobedarf pro MA | B90: 30 | C90: Verbrauchsmaterial €/MA/Monat | D90: Verbrauchsmaterial (unverändert).
A92: PROFESSIONAL SERVICES
A93: Rechtsanwalt Basis/Jahr | B93: 8000 | C93: Laufende Beratung €/Jahr
A94: RA pro Finanzierung | B94: 15000 | C94: Zusätzlich bei Funding € | D94: Ändern, 15k€ sind vermutlich zu hoch Für C13 Founding Phase: less effort
A95: Steuerberater | B95: 800 | C95: Laufende Buchhaltung €/Monat
A96: Wirtschaftsprüfer/Jahr | B96: 12000 | C96: Ab Series A €/Jahr
A97: WP ab Monat | B97: 17 | C97: Ab wann Wirtschaftsprüfer? Start mit tatsächlicher Seed-Phase Mitte 2027.
A98: Unternehmensberater/Jahr | B98: 5000 | C98: Optional €/Jahr Optionaler Puffer für Spezialberatung (DPP/MDR).
A100: VERSICHERUNGEN & BANK
A101: D&O Versicherung/Jahr | B101: 3000 | C101: Directors & Officers €/Jahr Schutz für Management (Standard-Satz).
A102: Betriebshaftpflicht/Jahr | B102: 1500 | C102: €/Jahr Deckung für industrielle Software-Einsätze.
A103: Cyber-Versicherung/Jahr | B103: 2000 | C103: €/Jahr Kritisch bei Verarbeitung von Kundendaten (IP-Schutz).
A104: Bankgebühren | B104: 50 | C104: Kontoführung €/Monat
A105: Payment Processing | B105: 0.025 | C105: Stripe/PayPal ~2-3% vom Umsatz Anteil am Umsatz für SaaS-Billing-Systeme (Stripe etc.).
A107: MARKETING & SALES
A108: Paid Ads Budget Initial | B108: 1000 | C108: Google, LinkedIn etc. €/Monat Fokus eher auf Content/SEO (Industrie-Vertrieb). | D108: 300→1.000 €/Monat (Treiber-Matrix)
A109: Ads Budget Wachstum/Monat | B109: 0.03 | C109: Monatliche Steigerung Skalierung mit Marktbekanntheit.
A110: Content & SEO | B110: 2500 | C110: €/Monat Fokus auf Whitepaper zu ROI; TCO und DPP-Compliance. | D110: 1.000→2.500 €/Monat (Treiber-Matrix)
...

Sheet P&L
A1: GEWINN- UND VERLUSTRECHNUNG (P&L)
A3: Position | B3: M1 | C3: M2 | D3: M3 | E3: M4 | F3: M5 | G3: M6 | H3: M7 | I3: M8 | J3: M9 | K3: M10 | L3: M11 | M3: M12 | N3: M13 | O3: M14 | P3: M15 | Q3: M16 | R3: M17 | S3: M18 | T3: M19 | U3: M20 | V3: M21 | W3: M22 | X3: M23 | Y3: M24 | Z3: M25 | AA3: M26 | AB3: M27 | AC3: M28 | AD3: M29 | AE3: M30 | AF3: M31 | AG3: M32 | AH3: M33 | AI3: M34 | AJ3: M35 | AK3: M36 | AL3: M37 | AM3: M38 | AN3: M39 | AO3: M40 | AP3: M41 | AQ3: M42 | AR3: M43 | AS3: M44 | AT3: M45 | AU3: M46 | AV3: M47 | AW3: M48 | AX3: M49 | AY3: M50 | AZ3: M51 | BA3: M52
A4: REVENUE
A5: Subscription Revenue | B5: =Revenue!B10 | C5: =Revenue!C10 | D5: =Revenue!D10 | E5: =Revenue!E10 | F5: =Revenue!F10 | G5: =Revenue!G10 | H5: =Revenue!H10 | I5: =Revenue!I10 | ... BA5: =Revenue!BA10
A6: Enterprise Revenue | B6: =Revenue!B17 | C6: =Revenue!C17 | D6: =Revenue!D17 | E6: =Revenue!E17 | F6: =Revenue!F17 | G6: =Revenue!G17 | H6: =Revenue!H17 | I6: =Revenue!I17 | ... BA6: =Revenue!BA17
A7: Implementation Support Revenue | B7: =Revenue!B30 | C7: =Revenue!C30 | D7: =Revenue!D30 | E7: =Revenue!E30 | F7: =Revenue!F30 | G7: =Revenue!G30 | H7: =Revenue!H30 | I7: =Revenue!I30 | ... BA7: =Revenue!BA30
A8: TOTAL REVENUE | B8: =B5+B6+B7 | C8: =C5+C6+C7 | D8: =D5+D6+D7 | E8: =E5+E6+E7 | F8: =F5+F6+F7 | G8: =G5+G6+G7 | H8: =H5+H6+H7 | I8: =I5+I6+I7 | ... BA8: =BA5+BA6+BA7
A9: COST OF GOODS SOLD (COGS)
A10: Cloud Hosting (variable) | B10: =Costs!B49 | C10: =Costs!C49 | D10: =Costs!D49 | E10: =Costs!E49 | F10: =Costs!F49 | G10: =Costs!G49 | H10: =Costs!H49 | I10: =Costs!I49 | ... BA10: =Costs!BA49
A11: AI/ML API Kosten | B11: =Costs!B50 | C11: =Costs!C50 | D11: =Costs!D50 | E11: =Costs!E50 | F11: =Costs!F50 | G11: =Costs!G50 | H11: =Costs!H50 | I11: =Costs!I50 | ... BA11: =Costs!BA50
A12: Payment Processing | B12: =Costs!B95 | C12: =Costs!C95 | D12: =Costs!D95 | E12: =Costs!E95 | F12: =Costs!F95 | G12: =Costs!G95 | H12: =Costs!H95 | I12: =Costs!I95 | ... BA12: =Costs!BA95
A13: TOTAL COGS | B13: =SUM(B10:B12) | C13: =SUM(C10:C12) | D13: =SUM(D10:D12) | E13: =SUM(E10:E12) | F13: =SUM(F10:F12) | G13: =SUM(G10:G12) | H13: =SUM(H10:H12) | I13: =SUM(I10:I12) | ... BA13: =SUM(BA10:BA12)
A15: GROSS PROFIT | B15: =B8-B13 | C15: =C8-C13 | D15: =D8-D13 | E15: =E8-E13 | F15: =F8-F13 | G15: =G8-G13 | H15: =H8-H13 | I15: =I8-I13 | ... BA15: =BA8-BA13
A16: Gross Margin % | B16: =IFERROR(B15/B8,0) | C16: =IFERROR(C15/C8,0) | D16: =IFERROR(D15/D8,0) | E16: =IFERROR(E15/E8,0) | F16: =IFERROR(F15/F8,0) | G16: =IFERROR(G15/G8,0) | H16: =IFERROR(H15/H8,0) | I16: =IFERROR(I15/I8,0) | ... BA16: =IFERROR(BA15/BA8,0)
A18: OPERATING EXPENSES
A19: Total Personnel | B19: =Costs!B45 | C19: =Costs!C45 | D19: =Costs!D45 | E19: =Costs!E45 | F19: =Costs!F45 | G19: =Costs!G45 | H19: =Costs!H45 | I19: =Costs!I45 | ... BA19: =Costs!BA45
A20: Total Technology | B20: =Costs!B54 | C20: =Costs!C54 | D20: =Costs!D54 | E20: =Costs!E54 | F20: =Costs!F54 | G20: =Costs!G54 | H20: =Costs!H54 | I20: =Costs!I54 | ... BA20: =Costs!BA54
A21: Total Office/Facilities | B21: =Costs!B61 | C21: =Costs!C61 | D21: =Costs!D61 | E21: =Costs!E61 | F21: =Costs!F61 | G21: =Costs!G61 | H21: =Costs!H61 | I21: =Costs!I61 | ... BA21: =Costs!BA61
A22: Total Professional Services | B22: =Costs!B68 | C22: =Costs!C68 | D22: =Costs!D68 | E22: =Costs!E68 | F22: =Costs!F68 | G22: =Costs!G68 | H22: =Costs!H68 | I22: =Costs!I68 | ... BA22: =Costs!BA68
A23: Total Insurance & Bank | B23: =Costs!B75 | C23: =Costs!C75 | D23: =Costs!D75 | E23: =Costs!E75 | F23: =Costs!F75 | G23: =Costs!G75 | H23: =Costs!H75 | I23: =Costs!I75 | ... BA23: =Costs!BA75
A24: Total Marketing & Sales | B24: =Costs!B84 | C24: =Costs!C84 | D24: =Costs!D84 | E24: =Costs!E84 | F24: =Costs!F84 | G24: =Costs!G84 | H24: =Costs!H84 | I24: =Costs!I84 | ... BA24: =Costs!BA84
A25: Total Other OpEx | B25: =Costs!B92 | C25: =Costs!C92 | D25: =Costs!D92 | E25: =Costs!E92 | F25: =Costs!F92 | G25: =Costs!G92 | H25: =Costs!H92 | I25: =Costs!I92 | ... BA25: =Costs!BA92
A26: Contingency/Buffer | B26: =Costs!B97 | C26: =Costs!C97 | D26: =Costs!D97 | E26: =Costs!E97 | F26: =Costs!F97 | G26: =Costs!G97 | H26: =Costs!H97 | I26: =Costs!I97 | ... BA26: =Costs!BA97
A27: TOTAL OPERATING EXPENSES | B27: =SUM(B19:B26) | C27: =SUM(C19:C26) | D27: =SUM(D19:D26) | E27: =SUM(E19:E26) | F27: =SUM(F19:F26) | G27: =SUM(G19:G26) | H27: =SUM(H19:H26) | I27: =SUM(I19:I26) | ... BA27: =SUM(BA19:BA26)
A29: EBITDA | B29: =B15-B27 | C29: =C15-C27 | D29: =D15-D27 | E29: =E15-E27 | F29: =F15-F27 | G29: =G15-G27 | H29: =H15-H27 | I29: =I15-I27 | ... BA29: =BA15-BA27
A30: EBITDA Margin % | B30: =IFERROR(B29/B8,0) | C30: =IFERROR(C29/C8,0) | D30: =IFERROR(D29/D8,0) | E30: =IFERROR(E29/E8,0) | F30: =IFERROR(F29/F8,0) | G30: =IFERROR(G29/G8,0) | H30: =IFERROR(H29/H8,0) | I30: =IFERROR(I29/I8,0) | ... BA30: =IFERROR(BA29/BA8,0)
A32: Depreciation & Amortization | B32: =Costs!B90/Inputs!$B$125/12 | C32: =Costs!C90/Inputs!$B$125/12 | D32: =Costs!D90/Inputs!$B$125/12 | E32: =Costs!E90/Inputs!$B$125/12 | F32: =Costs!F90/Inputs!$B$125/12 | G32: =Costs!G90/Inputs!$B$125/12 | H32: =Costs!H90/Inputs!$B$125/12 | I32: =Costs!I90/Inputs!$B$125/12 | ... BA32: =Costs!BA90/Inputs!$B$125/12
A34: EBIT (Operating Income) | B34: =B29-B32 | C34: =C29-C32 | D34: =D29-D32 | E34: =E29-E32 | F34: =F29-F32 | G34: =G29-G32 | H34: =H29-H32 | I34: =I29-I32 | ... BA34: =BA29-BA32
A36: EBT (Earnings Before Tax) | B36: =B34 | C36: =C34 | D36: =D34 | E36: =E34 | F36: =F34 | G36: =G34 | H36: =H34 | I36: =I34 | ... BA36: =BA34
A37: Income Tax | B37: =IF(B36>0,B36*Inputs!$B$7,0) | C37: =IF(C36>0,C36*Inputs!$B$7,0) | D37: =IF(D36>0,D36*Inputs!$B$7,0) | E37: =IF(E36>0,E36*Inputs!$B$7,0) | F37: =IF(F36>0,F36*Inputs!$B$7,0) | G37: =IF(G36>0,G36*Inputs!$B$7,0) | H37: =IF(H36>0,H36*Inputs!$B$7,0) | I37: =IF(I36>0,I36*Inputs!$B$7,0) | ... BA37: =IF(BA36>0,BA36*Inputs!$B$7,0)
A39: NET INCOME | B39: =B36-B37 | C39: =C36-C37 | D39: =D36-D37 | E39: =E36-E37 | F39: =F36-F37 | G39: =G36-G37 | H39: =H36-H37 | I39: =I36-I37 | ... BA39: =BA36-BA37
A40: Net Margin % | B40: =IFERROR(B39/B8,0) | C40: =IFERROR(C39/C8,0) | D40: =IFERROR(D39/D8,0) | E40: =IFERROR(E39/E8,0) | F40: =IFERROR(F39/F8,0) | G40: =IFERROR(G39/G8,0) | H40: =IFERROR(H39/H8,0) | I40: =IFERROR(I39/I8,0) | ... BA40: =IFERROR(BA39/BA8,0)

Sheet Tabelle1
A1: IT/Product Development/Framework | B1: Phase | C1: Content | D1: Phase | E1: Content | F1: Phase | G1: Content | H1: Phase | I1: Content | J1: Phase | K1: Content
A2: Month (starting Apr 26) | B2: M1-M4 | D2: M5-M16 | F2: M17-M28 | H2: M29-M40 | J2: M41-M52
B3: April to Jul 2026 | D3: Aug 2026 to Jul 2027 | F3: Aug 2027 to Jul 2028 | H3: Aug 2028 to Jul 2029 | J3: Aug 2029 to Jul 2030
B4: IDEATION Phase | D4: PRE-SEED | F4: SEED | H4: SERIES A | J4: Series B?? NOT PART OF OUR C13 Forecast
A5: Companies to be served | D5: 3 (SME) | E5: "Bottleneck" is Sales (Rene/Olaf) -->Existence of "MVP" is essential!! | G5: 2 Enterprises, 15 Mid-Size and 10 SMEs (27 cumulative) | I5: 6 Enterprises, 44 Mid-Size Companies, 30 SMEs (80 cumulative) (ARR: 5.6M by mid July 2029)
A6: Large OEM (Enterprise Deals) | B6: 0 | D6: 0 | F6: 2 | H6: 3 | J6: 6
A7: Mid-size OEM | B7: 0 | D7: 0 | F7: 15 | H7: 30 | J7: 50
A8: SME | B8: 0 | D8: 3 | F8: 10 | H8: 20 | J8: 60
A9: Cumulative | D9: 3 | F9: =D9+F6+F7+F8 | H9: =F9+H6+H7+H8 | J9: =H9+J6+J7+J8
A11: Co Founder Salary | C11: see: INPUT: Agreement: 100k€ per Cofounder as "AG-Brutto", ie. Approx. 52.000€/yr Netto
A12: Product features Product Development per Phase | C12: `-MVP "light" Getting LOIs | E12: -Plugins into one incumbent solution -Calculate manufacturing costs (BOM requirements) FEATURES of the MVP: -Core Engine -API for data ingestion & Normalisation -Data Integration (CAD, BOM, Processes costs, Supply data, EU regulations) -Manufacturing Cost engine -Operator Cost (TOC) engine -User Interface -(think about creating RfQ documents..is necessary for the mvp?) | G12: `-Integration into more incumbent solutions -Similarity and tribal knowledge engine -Compliance engine -Trade off and scnario analysis -Functional model and failure mode integration -… | I12: -Product Scaling -TCO Engine -Lifecycle Cost Engine -Propriatory Scoring Model for Products (depending on requirements) -Recommending alternative features of products/ decisions to take("Recommending System")
A13: People (IT) | E13: -Number of SW Engineers needed for MVP: -2 Developers -1 ML/AI Engineer (optional) -1 Site Reliability Engineer -1 UX/UI (optional) -1 Mechanical Engineer/Developer (who would love to work as a developer) -->people estimation are "conservative" -->ramp up of personnel over 12 month | G13: 1 Developer
A14: People (Marketing) | E14: `-1 Customer Key Account | G14: `-2 to 3 Sales/Marketing People -big budget for Sales/Marketing | I14: `-2 to 3 Sales/Marketing People -big budget for Sales/Marketing
A15: IT Licenses | E15: -Licenses for incumbent solutions (Autodesk, Siemens NX, Catia, PTC??
A16: IT Equipment | C16: -Budget for IT Licenses: 200€/month -no new equipment needed for the founders
A18: Office (permanent) | C18: no office in the first month | G18: Office Space
A19: Office (Coworking Space) | C19: `-400€/Desk/month | E19: 3 Desks/month? -->Meeting Place and conference room optional
A23: Fees (Lawyers, Notary,..) | C23: less spent in the ideation phase | E23: regular sum from here onwards | H23: higher? Sum according to more Stakeholders and bigger financing round

Sheet Revenue
A1: UMSATZMODELL - Detaillierte Aufschlüsselung
B2: 46113 | C2: 46143 | D2: 46174 | E2: 46204 | F2: 46235 | G2: 46266 | H2: 46296 | I2: 46327 | J2: 46357 | K2: 46388 | L2: 46419 | M2: 46447 | N2: 46478 | O2: 46508 | P2: 46539 | Q2: 46569 | R2: 46600 | S2: 46631 | T2: 46661 | U2: 46692 | V2: 46722 | W2: 46753 | X2: 46784 | Y2: 46813 | Z2: 46844 | AA2: 46874 | AB2: 46905 | AC2: 46935 | AD2: 46966 | AE2: 46997 | AF2: 47027 | AG2: 47058 | AH2: 47088 | AI2: 47119 | AJ2: 47150 | AK2: 47178 | AL2: 47209 | AM2: 47239 | AN2: 47270 | AO2: 47300 | AP2: 47331 | AQ2: 47362 | AR2: 47392 | AS2: 47423 | AT2: 47453 | AU2: 47484 | AV2: 47515 | AW2: 47543 | AX2: 47574 | AY2: 47604 | AZ2: 47635 | BA2: 47665
A3: Startup-Phasen | B3: Ideation | C3: Ideation | D3: Ideation | E3: Ideation | F3: Pre-Seed | G3: Pre-Seed | H3: Pre-Seed | I3: Pre-Seed | J3: Pre-Seed | K3: Pre-Seed | L3: Pre-Seed | M3: Pre-Seed | N3: Pre-Seed | O3: Pre-Seed | P3: Pre-Seed | Q3: Pre-Seed | R3: Seed | S3: Seed | T3: Seed | U3: Seed | V3: Seed | W3: Seed | X3: Seed | Y3: Seed | Z3: Seed | AA3: Seed | AB3: Seed | AC3: Seed | AD3: Series A | AE3: Series A | AF3: Series A | AG3: Series A | AH3: Series A | AI3: Series A | AJ3: Series A | AK3: Series A | AL3: Series A | AM3: Series A | AN3: Series A | AO3: Series A | AP3: Series B | AQ3: Series B | AR3: Series B | AS3: Series B | AT3: Series B | AU3: Series B | AV3: Series B | AW3: Series B | AX3: Series B | AY3: Series B | AZ3: Series B | BA3: Series B
A4: Kennzahl | B4: M1 | C4: M2 | D4: M3 | E4: M4 | F4: M5 | G4: M6 | H4: M7 | I4: M8 | J4: M9 | K4: M10 | L4: M11 | M4: M12 | N4: M13 | O4: M14 | P4: M15 | Q4: M16 | R4: M17 | S4: M18 | T4: M19 | U4: M20 | V4: M21 | W4: M22 | X4: M23 | Y4: M24 | Z4: M25 | AA4: M26 | AB4: M27 | AC4: M28 | AD4: M29 | AE4: M30 | AF4: M31 | AG4: M32 | AH4: M33 | AI4: M34 | AJ4: M35 | AK4: M36 | AL4: M37 | AM4: M38 | AN4: M39 | AO4: M40 | AP4: M41 | AQ4: M42 | AR4: M43 | AS4: M44 | AT4: M45 | AU4: M46 | AV4: M47 | AW4: M48 | AX4: M49 | AY4: M50 | AZ4: M51 | BA4: M52
A5: Preis pro Seat/Monat (€) (gilt für SME und Mid-Comps) | B5: =IFERROR(Inputs!$B$20/12*(1+Inputs!$B$21)^(INT((1-1)/12)),0) | C5: =Inputs!$B$20/12*(1+Inputs!$B$21)^INT((2-1)/12) | D5: =Inputs!$B$20/12*(1+Inputs!$B$21)^INT((3-1)/12) | E5: =Inputs!$B$20/12*(1+Inputs!$B$21)^INT((4-1)/12) | F5: =Inputs!$B$20/12*(1+Inputs!$B$21)^INT((5-1)/12) | G5: =Inputs!$B$20/12*(1+Inputs!$B$21)^INT((6-1)/12) | H5: =Inputs!$B$20/12*(1+Inputs!$B$21)^INT((7-1)/12) | I5: =Inputs!$B$20/12*(1+Inputs!$B$21)^INT((8-1)/12) | J5: =Inputs!$B$20/12*(1+Inputs!$B$21)^INT((9-1)/12) | K5: =Inputs!$B$20/12*(1+Inputs!$B$21)^INT((10-1)/12) | L5: =Inputs!$B$20/12*(1+Inputs!$B$21)^INT((11-1)/12) | M5: =Inputs!$B$20/12*(1+Inputs!$B$21)^INT((12-1)/12) | N5: =Inputs!$B$20/12*(1+Inputs!$B$21)^INT((13-1)/12) | O5: =Inputs!$B$20/12*(1+Inputs!$B$21)^INT((14-1)/12) | P5: =Inputs!$B$20/12*(1+Inputs!$B$21)^INT((15-1)/12) | Q5: =Inputs!$B$20/12*(1+Inputs!$B$21)^INT((16-1)/12) | R5: =Inputs!$B$20/12*(1+Inputs!$B$21)^INT((17-1)/12) | S5: =Inputs!$B$20/12*(1+Inputs!$B$21)^INT((18-1)/12) | T5: =Inputs!$B$20/12*(1+Inputs!$B$21)^INT((19-1)/12) | U5: =Inputs!$B$20/12*(1+Inputs!$B$21)^INT((20-1)/12) | V5: =Inputs!$B$20/12*(1+Inputs!$B$21)^INT((21-1)/12) | W5: =Inputs!$B$20/12*(1+Inputs!$B$21)^INT((22-1)/12) | X5: =Inputs!$B$20/12*(1+Inputs!$B$21)^INT((23-1)/12) | Y5: =Inputs!$B$20/12*(1+Inputs!$B$21)^INT((24-1)/12) | Z5: =Inputs!$B$20/12*(1+Inputs!$B$21)^INT((25-1)/12) | AA5: =Inputs!$B$20/12*(1+Inputs!$B$21)^INT((26-1)/12) | AB5: =Inputs!$B$20/12*(1+Inputs!$B$21)^INT((27-1)/12) | AC5: =Inputs!$B$20/12*(1+Inputs!$B$21)^INT((28-1)/12) | AD5: =Inputs!$B$20/12*(1+Inputs!$B$21)^INT((29-1)/12) | AE5: =Inputs!$B$20/12*(1+Inputs!$B$21)^INT((30-1)/12) | AF5: =Inputs!$B$20/12*(1+Inputs!$B$21)^INT((31-1)/12) | AG5: =Inputs!$B$20/12*(1+Inputs!$B$21)^INT((32-1)/12) | AH5: =Inputs!$B$20/12*(1+Inputs!$B$21)^INT((33-1)/12) | AI5: =Inputs!$B$20/12*(1+Inputs!$B$21)^INT((34-1)/12) | AJ5: =Inputs!$B$20/12*(1+Inputs!$B$21)^INT((35-1)/12) | AK5: =Inputs!$B$20/12*(1+Inputs!$B$21)^INT((36-1)/12) | AL5: =Inputs!$B$20/12*(1+Inputs!$B$21)^INT((37-1)/12) | AM5: =Inputs!$B$20/12*(1+Inputs!$B$21)^INT((38-1)/12) | AN5: =Inputs!$B$20/12*(1+Inputs!$B$21)^INT((39-1)/12) | AO5: =Inputs!$B$20/12*(1+Inputs!$B$21)^INT((40-1)/12) | AP5: =Inputs!$B$20/12*(1+Inputs!$B$21)^INT((41-1)/12) | AQ5: =Inputs!$B$20/12*(1+Inputs!$B$21)^INT((42-1)/12) | AR5: =Inputs!$B$20/12*(1+Inputs!$B$21)^INT((43-1)/12) | AS5: =Inputs!$B$20/12*(1+Inputs!$B$21)^INT((44-1)/12) | AT5: =Inputs!$B$20/12*(1+Inputs!$B$21)^INT((45-1)/12) | AU5: =Inputs!$B$20/12*(1+Inputs!$B$21)^INT((46-1)/12) | AV5: =Inputs!$B$20/12*(1+Inputs!$B$21)^INT((47-1)/12) | AW5: =Inputs!$B$20/12*(1+Inputs!$B$21)^INT((48-1)/12) | AX5: =Inputs!$B$20/12*(1+Inputs!$B$21)^INT((49-1)/12) | AY5: =Inputs!$B$20/12*(1+Inputs!$B$21)^INT((50-1)/12) | AZ5: =Inputs!$B$20/12*(1+Inputs!$B$21)^INT((51-1)/12) | BA5: =Inputs!$B$20/12*(1+Inputs!$B$21)^INT((52-1)/12)
A6: Neue Seats | B6: =IF(1>=Inputs!$B$22,Inputs!$B$23,0) | C6: =IF(2>=Inputs!$B$22,IF(2=Inputs!$B$22,Inputs!$B$23,ROUND(B9*Inputs!$B$24,0)),0) | D6: =IF(3>=Inputs!$B$22,IF(3=Inputs!$B$22,Inputs!$B$23,ROUND(C9*Inputs!$B$24,0)),0) | E6: =IF(4>=Inputs!$B$22,IF(4=Inputs!$B$22,Inputs!$B$23,ROUND(D9*Inputs!$B$24,0)),0) | F6: =IF(5>=Inputs!$B$22,IF(5=Inputs!$B$22,Inputs!$B$23,ROUND(E9*Inputs!$B$24,0)),0) | G6: =IF(6>=Inputs!$B$22,IF(6=Inputs!$B$22,Inputs!$B$23,ROUND(F9*Inputs!$B$24,0)),0) | H6: =IF(7>=Inputs!$B$22,IF(7=Inputs!$B$22,Inputs!$B$23,ROUND(G9*Inputs!$B$24,0)),0) | I6: =IF(8>=Inputs!$B$22,IF(8=Inputs!$B$22,Inputs!$B$23,ROUND(H9*Inputs!$B$24,0)),0) | J6: =IF(9>=Inputs!$B$22,IF(9=Inputs!$B$22,Inputs!$B$23,ROUND(I9*Inputs!$B$24,0)),0) | K6: =IF(10>=Inputs!$B$22,IF(10=Inputs!$B$22,Inputs!$B$23,ROUND(J9*Inputs!$B$24,0)),0) | L6: =IF(11>=Inputs!$B$22,IF(11=Inputs!$B$22,Inputs!$B$23,ROUND(K9*Inputs!$B$24,0)),0) | M6: =IF(12>=Inputs!$B$22,IF(12=Inputs!$B$22,Inputs!$B$23,ROUND(L9*Inputs!$B$24,0)),0) | N6: =IF(13>=Inputs!$B$22,IF(13=Inputs!$B$22,Inputs!$B$23,ROUND(M9*Inputs!$B$24,0)),0) | O6: =IF(14>=Inputs!$B$22,IF(14=Inputs!$B$22,Inputs!$B$23,ROUND(N9*Inputs!$B$24,0)),0) | P6: =IF(15>=Inputs!$B$22,IF(15=Inputs!$B$22,Inputs!$B$23,ROUND(O9*Inputs!$B$24,0)),0) | Q6: =IF(16>=Inputs!$B$22,IF(16=Inputs!$B$22,Inputs!$B$23,ROUND(P9*Inputs!$B$24,0)),0) | R6: =IF(17>=Inputs!$B$22,IF(17=Inputs!$B$22,Inputs!$B$23,ROUND(Q9*Inputs!$B$24,0)),0) | S6: =IF(18>=Inputs!$B$22,IF(18=Inputs!$B$22,Inputs!$B$23,ROUND(R9*Inputs!$B$24,0)),0) | T6: =IF(19>=Inputs!$B$22,IF(19=Inputs!$B$22,Inputs!$B$23,ROUND(S9*Inputs!$B$24,0)),0) | U6: =IF(20>=Inputs!$B$22,IF(20=Inputs!$B$22,Inputs!$B$23,ROUND(T9*Inputs!$B$24,0)),0) | V6: =IF(21>=Inputs!$B$22,IF(21=Inputs!$B$22,Inputs!$B$23,ROUND(U9*Inputs!$B$24,0)),0) | W6: =IF(22>=Inputs!$B$22,IF(22=Inputs!$B$22,Inputs!$B$23,ROUND(V9*Inputs!$B$24,0)),0) | X6: =IF(23>=Inputs!$B$22,IF(23=Inputs!$B$22,Inputs!$B$23,ROUND(W9*Inputs!$B$24,0)),0) | Y6: =IF(24>=Inputs!$B$22,IF(24=Inputs!$B$22,Inputs!$B$23,ROUND(X9*Inputs!$B$24,0)),0) | Z6: =IF(25>=Inputs!$B$22,IF(25=Inputs!$B$22,Inputs!$B$23,ROUND(Y9*Inputs!$B$24,0)),0) | AA6: =IF(26>=Inputs!$B$22,IF(26=Inputs!$B$22,Inputs!$B$23,ROUND(Z9*Inputs!$B$24,0)),0) | AB6: =IF(27>=Inputs!$B$22,IF(27=Inputs!$B$22,Inputs!$B$23,ROUND(AA9*Inputs!$B$24,0)),0) | AC6: =IF(28>=Inputs!$B$22,IF(28=Inputs!$B$22,Inputs!$B$23,ROUND(AB9*Inputs!$B$24,0)),0) | AD6: =IF(29>=Inputs!$B$22,IF(29=Inputs!$B$22,Inputs!$B$23,ROUND(AC9*Inputs!$B$24,0)),0) | AE6: =IF(30>=Inputs!$B$22,IF(30=Inputs!$B$22,Inputs!$B$23,ROUND(AD9*Inputs!$B$24,0)),0) | AF6: =IF(31>=Inputs!$B$22,IF(31=Inputs!$B$22,Inputs!$B$23,ROUND(AE9*Inputs!$B$24,0)),0) | AG6: =IF(32>=Inputs!$B$22,IF(32=Inputs!$B$22,Inputs!$B$23,ROUND(AF9*Inputs!$B$24,0)),0) | AH6: =IF(33>=Inputs!$B$22,IF(33=Inputs!$B$22,Inputs!$B$23,ROUND(AG9*Inputs!$B$24,0)),0) | AI6: =IF(34>=Inputs!$B$22,IF(34=Inputs!$B$22,Inputs!$B$23,ROUND(AH9*Inputs!$B$24,0)),0) | AJ6: =IF(35>=Inputs!$B$22,IF(35=Inputs!$B$22,Inputs!$B$23,ROUND(AI9*Inputs!$B$24,0)),0) | AK6: =IF(36>=Inputs!$B$22,IF(36=Inputs!$B$22,Inputs!$B$23,ROUND(AJ9*Inputs!$B$24,0)),0) | AL6: =IF(37>=Inputs!$B$22,IF(37=Inputs!$B$22,Inputs!$B$23,ROUND(AK9*Inputs!$B$24,0)),0) | AM6: =IF(38>=Inputs!$B$22,IF(38=Inputs!$B$22,Inputs!$B$23,ROUND(AL9*Inputs!$B$24,0)),0) | AN6: =IF(39>=Inputs!$B$22,IF(39=Inputs!$B$22,Inputs!$B$23,ROUND(AM9*Inputs!$B$24,0)),0) | AO6: =IF(40>=Inputs!$B$22,IF(40=Inputs!$B$22,Inputs!$B$23,ROUND(AN9*Inputs!$B$24,0)),0) | AP6: =IF(41>=Inputs!$B$22,IF(41=Inputs!$B$22,Inputs!$B$23,ROUND(AO9*Inputs!$B$24,0)),0) | AQ6: =IF(42>=Inputs!$B$22,IF(42=Inputs!$B$22,Inputs!$B$23,ROUND(AP9*Inputs!$B$24,0)),0) | AR6: =IF(43>=Inputs!$B$22,IF(43=Inputs!$B$22,Inputs!$B$23,ROUND(AQ9*Inputs!$B$24,0)),0) | AS6: =IF(44>=Inputs!$B$22,IF(44=Inputs!$B$22,Inputs!$B$23,ROUND(AR9*Inputs!$B$24,0)),0) | AT6: =IF(45>=Inputs!$B$22,IF(45=Inputs!$B$22,Inputs!$B$23,ROUND(AS9*Inputs!$B$24,0)),0) | AU6: =IF(46>=Inputs!$B$22,IF(46=Inputs!$B$22,Inputs!$B$23,ROUND(AT9*Inputs!$B$24,0)),0) | AV6: =IF(47>=Inputs!$B$22,IF(47=Inputs!$B$22,Inputs!$B$23,ROUND(AU9*Inputs!$B$24,0)),0) | AW6: =IF(48>=Inputs!$B$22,IF(48=Inputs!$B$22,Inputs!$B$23,ROUND(AV9*Inputs!$B$24,0)),0) | AX6: =IF(49>=Inputs!$B$22,IF(49=Inputs!$B$22,Inputs!$B$23,ROUND(AW9*Inputs!$B$24,0)),0) | AY6: =IF(50>=Inputs!$B$22,IF(50=Inputs!$B$22,Inputs!$B$23,ROUND(AX9*Inputs!$B$24,0)),0) | AZ6: =IF(51>=Inputs!$B$22,IF(51=Inputs!$B$22,Inputs!$B$23,ROUND(AY9*Inputs!$B$24,0)),0) | BA6: =IF(52>=Inputs!$B$22,IF(52=Inputs!$B$22,Inputs!$B$23,ROUND(AZ9*Inputs!$B$24,0)),0)
A7: Churned Seats | B7: =0 | C7: =IF(B9>0,ROUND(B9*Inputs!$B$28/12,0),0) | D7: =IF(C9>0,ROUND(C9*Inputs!$B$28/12,0),0) | E7: =IF(D9>0,ROUND(D9*Inputs!$B$28/12,0),0) | F7: =IF(E9>0,ROUND(E9*Inputs!$B$28/12,0),0) | G7: =IF(F9>0,ROUND(F9*Inputs!$B$28/12,0),0) | H7: =IF(G9>0,ROUND(G9*Inputs!$B$28/12,0),0) | I7: =IF(H9>0,ROUND(H9*Inputs!$B$28/12,0),0) | J7: =IF(I9>0,ROUND(I9*Inputs!$B$28/12,0),0) | ... BA7: =IF(AZ9>0,ROUND(AZ9*Inputs!$B$28/12,0),0)
A8: Net New Seats | B8: =B6-B7 | C8: =C6-C7 | D8: =D6-D7 | E8: =E6-E7 | F8: =F6-F7 | G8: =G6-G7 | H8: =H6-H7 | I8: =I6-I7 | ... BA8: =BA6-BA7
A9: Total Active Seats | B9: =B8 | C9: =B9+C8 | D9: =C9+D8 | E9: =D9+E8 | F9: =E9+F8 | G9: =F9+G8 | H9: =G9+H8 | I9: =H9+I8 | J9: =I9+J8 | ... BA9: =AZ9+BA8
A10: Monthly Subscription Revenue (€) | B10: =B9*B5 | C10: =C9*C5 | D10: =D9*D5 | E10: =E9*E5 | F10: =F9*F5 | G10: =G9*G5 | H10: =H9*H5 | I10: =I9*I5 | ... BA10: =BA9*BA5
A11: Subscription ARR (€) | B11: =B10*12 | C11: =C10*12 | D11: =D10*12 | E11: =E10*12 | F11: =F10*12 | G11: =G10*12 | H11: =H10*12 | I11: =I10*12 | ... BA11: =BA10*12
A13: Neue Enterprise-Deals (Quartal) | B13: =IF(AND(1>=Inputs!$B$25,MOD(1-Inputs!$B$25,3)=0),Inputs!$B$27,0) | C13: =IF(AND(2>=Inputs!$B$25,MOD(2-Inputs!$B$25,3)=0),Inputs!$B$27,0) | D13: =IF(AND(3>=Inputs!$B$25,MOD(3-Inputs!$B$25,3)=0),Inputs!$B$27,0) | E13: =IF(AND(4>=Inputs!$B$25,MOD(4-Inputs!$B$25,3)=0),Inputs!$B$27,0) | F13: =IF(AND(5>=Inputs!$B$25,MOD(5-Inputs!$B$25,3)=0),Inputs!$B$27,0) | G13: =IF(AND(6>=Inputs!$B$25,MOD(6-Inputs!$B$25,3)=0),Inputs!$B$27,0) | H13: =IF(AND(7>=Inputs!$B$25,MOD(7-Inputs!$B$25,3)=0),Inputs!$B$27,0) | I13: =IF(AND(8>=Inputs!$B$25,MOD(8-Inputs!$B$25,3)=0),Inputs!$B$27,0) | J13: =IF(AND(9>=Inputs!$B$25,MOD(9-Inputs!$B$25,3)=0),Inputs!$B$27,0) | K13: =IF(AND(10>=Inputs!$B$25,MOD(10-Inputs!$B$25,3)=0),Inputs!$B$27,0) | L13: =IF(AND(11>=Inputs!$B$25,MOD(11-Inputs!$B$25,3)=0),Inputs!$B$27,0) | M13: =IF(AND(12>=Inputs!$B$25,MOD(12-Inputs!$B$25,3)=0),Inputs!$B$27,0) | N13: =IF(AND(13>=Inputs!$B$25,MOD(13-Inputs!$B$25,3)=0),Inputs!$B$27,0) | O13: =IF(AND(14>=Inputs!$B$25,MOD(14-Inputs!$B$25,3)=0),Inputs!$B$27,0) | P13: =IF(AND(15>=Inputs!$B$25,MOD(15-Inputs!$B$25,3)=0),Inputs!$B$27,0) | Q13: =IF(AND(16>=Inputs!$B$25,MOD(16-Inputs!$B$25,3)=0),Inputs!$B$27,0) | R13: =IF(AND(17>=Inputs!$B$25,MOD(17-Inputs!$B$25,3)=0),Inputs!$B$27,0) | S13: =IF(AND(18>=Inputs!$B$25,MOD(18-Inputs!$B$25,3)=0),Inputs!$B$27,0) | T13: =IF(AND(19>=Inputs!$B$25,MOD(19-Inputs!$B$25,3)=0),Inputs!$B$27,0) | U13: =IF(AND(20>=Inputs!$B$25,MOD(20-Inputs!$B$25,3)=0),Inputs!$B$27,0) | V13: =IF(AND(21>=Inputs!$B$25,MOD(21-Inputs!$B$25,3)=0),Inputs!$B$27,0) | W13: =IF(AND(22>=Inputs!$B$25,MOD(22-Inputs!$B$25,3)=0),Inputs!$B$27,0) | X13: =IF(AND(23>=Inputs!$B$25,MOD(23-Inputs!$B$25,3)=0),Inputs!$B$27,0) | Y13: =IF(AND(24>=Inputs!$B$25,MOD(24-Inputs!$B$25,3)=0),Inputs!$B$27,0) | Z13: =IF(AND(25>=Inputs!$B$25,MOD(25-Inputs!$B$25,3)=0),Inputs!$B$27,0) | AA13: =IF(AND(26>=Inputs!$B$25,MOD(26-Inputs!$B$25,3)=0),Inputs!$B$27,0) | AB13: =IF(AND(27>=Inputs!$B$25,MOD(27-Inputs!$B$25,3)=0),Inputs!$B$27,0) | AC13: =IF(AND(28>=Inputs!$B$25,MOD(28-Inputs!$B$25,3)=0),Inputs!$B$27,0) | AD13: =IF(AND(29>=Inputs!$B$25,MOD(29-Inputs!$B$25,3)=0),Inputs!$B$27,0) | AE13: =IF(AND(30>=Inputs!$B$25,MOD(30-Inputs!$B$25,3)=0),Inputs!$B$27,0) | AF13: =IF(AND(31>=Inputs!$B$25,MOD(31-Inputs!$B$25,3)=0),Inputs!$B$27,0) | AG13: =IF(AND(32>=Inputs!$B$25,MOD(32-Inputs!$B$25,3)=0),Inputs!$B$27,0) | AH13: =IF(AND(33>=Inputs!$B$25,MOD(33-Inputs!$B$25,3)=0),Inputs!$B$27,0) | AI13: =IF(AND(34>=Inputs!$B$25,MOD(34-Inputs!$B$25,3)=0),Inputs!$B$27,0) | AJ13: =IF(AND(35>=Inputs!$B$25,MOD(35-Inputs!$B$25,3)=0),Inputs!$B$27,0) | AK13: =IF(AND(36>=Inputs!$B$25,MOD(36-Inputs!$B$25,3)=0),Inputs!$B$27,0) | AL13: =IF(AND(37>=Inputs!$B$25,MOD(37-Inputs!$B$25,3)=0),Inputs!$B$27,0) | AM13: =IF(AND(38>=Inputs!$B$25,MOD(38-Inputs!$B$25,3)=0),Inputs!$B$27,0) | AN13: =IF(AND(39>=Inputs!$B$25,MOD(39-Inputs!$B$25,3)=0),Inputs!$B$27,0) | AO13: =IF(AND(40>=Inputs!$B$25,MOD(40-Inputs!$B$25,3)=0),Inputs!$B$27,0) | AP13: =IF(AND(41>=Inputs!$B$25,MOD(41-Inputs!$B$25,3)=0),Inputs!$B$27,0) | AQ13: =IF(AND(42>=Inputs!$B$25,MOD(42-Inputs!$B$25,3)=0),Inputs!$B$27,0) | AR13: =IF(AND(43>=Inputs!$B$25,MOD(43-Inputs!$B$25,3)=0),Inputs!$B$27,0) | AS13: =IF(AND(44>=Inputs!$B$25,MOD(44-Inputs!$B$25,3)=0),Inputs!$B$27,0) | AT13: =IF(AND(45>=Inputs!$B$25,MOD(45-Inputs!$B$25,3)=0),Inputs!$B$27,0) | AU13: =IF(AND(46>=Inputs!$B$25,MOD(46-Inputs!$B$25,3)=0),Inputs!$B$27,0) | AV13: =IF(AND(47>=Inputs!$B$25,MOD(47-Inputs!$B$25,3)=0),Inputs!$B$27,0) | AW13: =IF(AND(48>=Inputs!$B$25,MOD(48-Inputs!$B$25,3)=0),Inputs!$B$27,0) | AX13: =IF(AND(49>=Inputs!$B$25,MOD(49-Inputs!$B$25,3)=0),Inputs!$B$27,0) | AY13: =IF(AND(50>=Inputs!$B$25,MOD(50-Inputs!$B$25,3)=0),Inputs!$B$27,0) | AZ13: =IF(AND(51>=Inputs!$B$25,MOD(51-Inputs!$B$25,3)=0),Inputs!$B$27,0) | BA13: =IF(AND(52>=Inputs!$B$25,MOD(52-Inputs!$B$25,3)=0),Inputs!$B$27,0)
A14: Churned Enterprise | B14: =0 | C14: =IF(B15>0,IF(MOD(2,12)=0,ROUND(B15*Inputs!$B$28,0),0),0) | D14: =IF(C15>0,IF(MOD(3,12)=0,ROUND(C15*Inputs!$B$28,0),0),0) | E14: =IF(D15>0,IF(MOD(4,12)=0,ROUND(D15*Inputs!$B$28,0),0),0) | F14: =IF(E15>0,IF(MOD(5,12)=0,ROUND(E15*Inputs!$B$28,0),0),0) | G14: =IF(F15>0,IF(MOD(6,12)=0,ROUND(F15*Inputs!$B$28,0),0),0) | H14: =IF(G15>0,IF(MOD(7,12)=0,ROUND(G15*Inputs!$B$28,0),0),0) | I14: =IF(H15>0,IF(MOD(8,12)=0,ROUND(H15*Inputs!$B$28,0),0),0) | J14: =IF(I15>0,IF(MOD(9,12)=0,ROUND(I15*Inputs!$B$28,0),0),0) | K14: =IF(J15>0,IF(MOD(10,12)=0,ROUND(J15*Inputs!$B$28,0),0),0) | L14: =IF(K15>0,IF(MOD(11,12)=0,ROUND(K15*Inputs!$B$28,0),0),0) | M14: =IF(L15>0,IF(MOD(12,12)=0,ROUND(L15*Inputs!$B$28,0),0),0) | N14: =IF(M15>0,IF(MOD(13,12)=0,ROUND(M15*Inputs!$B$28,0),0),0) | O14: =IF(N15>0,IF(MOD(14,12)=0,ROUND(N15*Inputs!$B$28,0),0),0) | P14: =IF(O15>0,IF(MOD(15,12)=0,ROUND(O15*Inputs!$B$28,0),0),0) | Q14: =IF(P15>0,IF(MOD(16,12)=0,ROUND(P15*Inputs!$B$28,0),0),0) | R14: =IF(Q15>0,IF(MOD(17,12)=0,ROUND(Q15*Inputs!$B$28,0),0),0) | S14: =IF(R15>0,IF(MOD(18,12)=0,ROUND(R15*Inputs!$B$28,0),0),0) | T14: =IF(S15>0,IF(MOD(19,12)=0,ROUND(S15*Inputs!$B$28,0),0),0) | U14: =IF(T15>0,IF(MOD(20,12)=0,ROUND(T15*Inputs!$B$28,0),0),0) | V14: =IF(U15>0,IF(MOD(21,12)=0,ROUND(U15*Inputs!$B$28,0),0),0) | W14: =IF(V15>0,IF(MOD(22,12)=0,ROUND(V15*Inputs!$B$28,0),0),0) | X14: =IF(W15>0,IF(MOD(23,12)=0,ROUND(W15*Inputs!$B$28,0),0),0) | Y14: =IF(X15>0,IF(MOD(24,12)=0,ROUND(X15*Inputs!$B$28,0),0),0) | Z14: =IF(Y15>0,IF(MOD(25,12)=0,ROUND(Y15*Inputs!$B$28,0),0),0) | AA14: =IF(Z15>0,IF(MOD(26,12)=0,ROUND(Z15*Inputs!$B$28,0),0),0) | AB14: =IF(AA15>0,IF(MOD(27,12)=0,ROUND(AA15*Inputs!$B$28,0),0),0) | AC14: =IF(AB15>0,IF(MOD(28,12)=0,ROUND(AB15*Inputs!$B$28,0),0),0) | AD14: =IF(AC15>0,IF(MOD(29,12)=0,ROUND(AC15*Inputs!$B$28,0),0),0) | AE14: =IF(AD15>0,IF(MOD(30,12)=0,ROUND(AD15*Inputs!$B$28,0),0),0) | AF14: =IF(AE15>0,IF(MOD(31,12)=0,ROUND(AE15*Inputs!$B$28,0),0),0) | AG14: =IF(AF15>0,IF(MOD(32,12)=0,ROUND(AF15*Inputs!$B$28,0),0),0) | AH14: =IF(AG15>0,IF(MOD(33,12)=0,ROUND(AG15*Inputs!$B$28,0),0),0) | AI14: =IF(AH15>0,IF(MOD(34,12)=0,ROUND(AH15*Inputs!$B$28,0),0),0) | AJ14: =IF(AI15>0,IF(MOD(35,12)=0,ROUND(AI15*Inputs!$B$28,0),0),0) | AK14: =IF(AJ15>0,IF(MOD(36,12)=0,ROUND(AJ15*Inputs!$B$28,0),0),0) | AL14: =IF(AK15>0,IF(MOD(37,12)=0,ROUND(AK15*Inputs!$B$28,0),0),0) | AM14: =IF(AL15>0,IF(MOD(38,12)=0,ROUND(AL15*Inputs!$B$28,0),0),0) | AN14: =IF(AM15>0,IF(MOD(39,12)=0,ROUND(AM15*Inputs!$B$28,0),0),0) | AO14: =IF(AN15>0,IF(MOD(40,12)=0,ROUND(AN15*Inputs!$B$28,0),0),0) | AP14: =IF(AO15>0,IF(MOD(41,12)=0,ROUND(AO15*Inputs!$B$28,0),0),0) | AQ14: =IF(AP15>0,IF(MOD(42,12)=0,ROUND(AP15*Inputs!$B$28,0),0),0) | AR14: =IF(AQ15>0,IF(MOD(43,12)=0,ROUND(AQ15*Inputs!$B$28,0),0),0) | AS14: =IF(AR15>0,IF(MOD(44,12)=0,ROUND(AR15*Inputs!$B$28,0),0),0) | AT14: =IF(AS15>0,IF(MOD(45,12)=0,ROUND(AS15*Inputs!$B$28,0),0),0) | AU14: =IF(AT15>0,IF(MOD(46,12)=0,ROUND(AT15*Inputs!$B$28,0),0),0) | AV14: =IF(AU15>0,IF(MOD(47,12)=0,ROUND(AU15*Inputs!$B$28,0),0),0) | AW14: =IF(AV15>0,IF(MOD(48,12)=0,ROUND(AV15*Inputs!$B$28,0),0),0) | AX14: =IF(AW15>0,IF(MOD(49,12)=0,ROUND(AW15*Inputs!$B$28,0),0),0) | AY14: =IF(AX15>0,IF(MOD(50,12)=0,ROUND(AX15*Inputs!$B$28,0),0),0) | AZ14: =IF(AY15>0,IF(MOD(51,12)=0,ROUND(AY15*Inputs!$B$28,0),0),0) | BA14: =IF(AZ15>0,IF(MOD(52,12)=0,ROUND(AZ15*Inputs!$B$28,0),0),0)
A15: Active Enterprise Contracts | B15: =B13-B14 | C15: =B15+C13-C14 | D15: =C15+D13-D14 | E15: =D15+E13-E14 | F15: =E15+F13-F14 | G15: =F15+G13-G14 | H15: =G15+H13-H14 | I15: =H15+I13-I14 | J15: =I15+J13-J14 | ... BA15: =AZ15+BA13-BA14
A16: Avg Enterprise ACV (€) | B16: =Inputs!$B$26*(1+Inputs!$B$21)^INT((1-1)/12) | C16: =Inputs!$B$26*(1+Inputs!$B$21)^INT((2-1)/12) | D16: =Inputs!$B$26*(1+Inputs!$B$21)^INT((3-1)/12) | E16: =Inputs!$B$26*(1+Inputs!$B$21)^INT((4-1)/12) | F16: =Inputs!$B$26*(1+Inputs!$B$21)^INT((5-1)/12) | G16: =Inputs!$B$26*(1+Inputs!$B$21)^INT((6-1)/12) | H16: =Inputs!$B$26*(1+Inputs!$B$21)^INT((7-1)/12) | I16: =Inputs!$B$26*(1+Inputs!$B$21)^INT((8-1)/12) | J16: =Inputs!$B$26*(1+Inputs!$B$21)^INT((9-1)/12) | K16: =Inputs!$B$26*(1+Inputs!$B$21)^INT((10-1)/12) | L16: =Inputs!$B$26*(1+Inputs!$B$21)^INT((11-1)/12) | M16: =Inputs!$B$26*(1+Inputs!$B$21)^INT((12-1)/12) | N16: =Inputs!$B$26*(1+Inputs!$B$21)^INT((13-1)/12) | O16: =Inputs!$B$26*(1+Inputs!$B$21)^INT((14-1)/12) | P16: =Inputs!$B$26*(1+Inputs!$B$21)^INT((15-1)/12) | Q16: =Inputs!$B$26*(1+Inputs!$B$21)^INT((16-1)/12) | R16: =Inputs!$B$26*(1+Inputs!$B$21)^INT((17-1)/12) | S16: =Inputs!$B$26*(1+Inputs!$B$21)^INT((18-1)/12) | T16: =Inputs!$B$26*(1+Inputs!$B$21)^INT((19-1)/12) | U16: =Inputs!$B$26*(1+Inputs!$B$21)^INT((20-1)/12) | V16: =Inputs!$B$26*(1+Inputs!$B$21)^INT((21-1)/12) | W16: =Inputs!$B$26*(1+Inputs!$B$21)^INT((22-1)/12) | X16: =Inputs!$B$26*(1+Inputs!$B$21)^INT((23-1)/12) | Y16: =Inputs!$B$26*(1+Inputs!$B$21)^INT((24-1)/12) | Z16: =Inputs!$B$26*(1+Inputs!$B$21)^INT((25-1)/12) | AA16: =Inputs!$B$26*(1+Inputs!$B$21)^INT((26-1)/12) | AB16: =Inputs!$B$26*(1+Inputs!$B$21)^INT((27-1)/12) | AC16: =Inputs!$B$26*(1+Inputs!$B$21)^INT((28-1)/12) | AD16: =Inputs!$B$26*(1+Inputs!$B$21)^INT((29-1)/12) | AE16: =Inputs!$B$26*(1+Inputs!$B$21)^INT((30-1)/12) | AF16: =Inputs!$B$26*(1+Inputs!$B$21)^INT((31-1)/12) | AG16: =Inputs!$B$26*(1+Inputs!$B$21)^INT((32-1)/12) | AH16: =Inputs!$B$26*(1+Inputs!$B$21)^INT((33-1)/12) | AI16: =Inputs!$B$26*(1+Inputs!$B$21)^INT((34-1)/12) | AJ16: =Inputs!$B$26*(1+Inputs!$B$21)^INT((35-1)/12) | AK16: =Inputs!$B$26*(1+Inputs!$B$21)^INT((36-1)/12) | AL16: =Inputs!$B$26*(1+Inputs!$B$21)^INT((37-1)/12) | AM16: =Inputs!$B$26*(1+Inputs!$B$21)^INT((38-1)/12) | AN16: =Inputs!$B$26*(1+Inputs!$B$21)^INT((39-1)/12) | AO16: =Inputs!$B$26*(1+Inputs!$B$21)^INT((40-1)/12) | AP16: =Inputs!$B$26*(1+Inputs!$B$21)^INT((41-1)/12) | AQ16: =Inputs!$B$26*(1+Inputs!$B$21)^INT((42-1)/12) | AR16: =Inputs!$B$26*(1+Inputs!$B$21)^INT((43-1)/12) | AS16: =Inputs!$B$26*(1+Inputs!$B$21)^INT((44-1)/12) | AT16: =Inputs!$B$26*(1+Inputs!$B$21)^INT((45-1)/12) | AU16: =Inputs!$B$26*(1+Inputs!$B$21)^INT((46-1)/12) | AV16: =Inputs!$B$26*(1+Inputs!$B$21)^INT((47-1)/12) | AW16: =Inputs!$B$26*(1+Inputs!$B$21)^INT((48-1)/12) | AX16: =Inputs!$B$26*(1+Inputs!$B$21)^INT((49-1)/12) | AY16: =Inputs!$B$26*(1+Inputs!$B$21)^INT((50-1)/12) | AZ16: =Inputs!$B$26*(1+Inputs!$B$21)^INT((51-1)/12) | BA16: =Inputs!$B$26*(1+Inputs!$B$21)^INT((52-1)/12)
A17: Enterprise Monthly Revenue (€) | B17: =B15*B16/12 | C17: =C15*C16/12 | D17: =D15*D16/12 | E17: =E15*E16/12 | F17: =F15*F16/12 | G17: =G15*G16/12 | H17: =H15*H16/12 | I17: =I15*I16/12 | ... BA17: =BA15*BA16/12
A18: ── RECURRING REVENUE (SaaS-Metriken, ohne Implementation-Support) ──
A19: MRR – Monthly Recurring Revenue (Lizenzen) | B19: =B10+B17 | C19: =C10+C17 | D19: =D10+D17 | E19: =E10+E17 | F19: =F10+F17 | G19: =G10+G17 | H19: =H10+H17 | I19: =I10+I17 | ... BA19: =BA10+BA17
A20: ARR – Annual Recurring Revenue (Lizenzen = MRR × 12) | B20: =B19*12 | C20: =C19*12 | D20: =D19*12 | E20: =E19*12 | F20: =F19*12 | G20: =G19*12 | H20: =H19*12 | I20: =I19*12 | ... BA20: =BA19*12
A21: Total Monthly Revenue (Lizenzen + Implementation-Support) | B21: =B19+B30 | C21: =C19+C30 | D21: =D19+D30 | E21: =E19+E30 | F21: =F19+F30 | G21: =G19+G30 | H21: =H19+H30 | I21: =I19+I30 | ... BA21: =BA19+BA30
A22: ARR Growth % (MoM) | B22: ="" | C22: =IFERROR(C20/B20-1,"") | D22: =IFERROR(D20/C20-1,"") | E22: =IFERROR(E20/D20-1,"") | F22: =IFERROR(F20/E20-1,"") | G22: =IFERROR(G20/F20-1,"") | H22: =IFERROR(H20/G20-1,"") | I22: =IFERROR(I20/H20-1,"") | J22: =IFERROR(J20/I20-1,"") | ... BA22: =IFERROR(BA20/AZ20-1,"")
A23: Net Revenue Retention % | B23: =Inputs!$B$29 | C23: =Inputs!$B$29 | D23: =Inputs!$B$29 | E23: =Inputs!$B$29 | F23: =Inputs!$B$29 | G23: =Inputs!$B$29 | H23: =Inputs!$B$29 | I23: =Inputs!$B$29 | ... BA23: =Inputs!$B$29
A24: Gross New ARR (€) | B24: =B6*B5*12+B13*B16 | C24: =C6*C5*12+C13*C16 | D24: =D6*D5*12+D13*D16 | E24: =E6*E5*12+E13*E16 | F24: =F6*F5*12+F13*F16 | G24: =G6*G5*12+G13*G16 | H24: =H6*H5*12+H13*H16 | I24: =I6*I5*12+I13*I16 | ... BA24: =BA6*BA5*12+BA13*BA16
A26: ── Implementation-Support REVENUE ──
A27: Active Subscription Customers | B27: =IF(B9>0, MAX(1, ROUND(B9/Inputs!$B$23, 0)), 0) | C27: =IF(C9>0, MAX(1, ROUND(C9/Inputs!$B$23, 0)), 0) | D27: =IF(D9>0, MAX(1, ROUND(D9/Inputs!$B$23, 0)), 0) | E27: =IF(E9>0, MAX(1, ROUND(E9/Inputs!$B$23, 0)), 0) | F27: =IF(F9>0, MAX(1, ROUND(F9/Inputs!$B$23, 0)), 0) | G27: =IF(G9>0, MAX(1, ROUND(G9/Inputs!$B$23, 0)), 0) | H27: =IF(H9>0, MAX(1, ROUND(H9/Inputs!$B$23, 0)), 0) | I27: =IF(I9>0, MAX(1, ROUND(I9/Inputs!$B$23, 0)), 0) | ... BA27: =IF(BA9>0, MAX(1, ROUND(BA9/Inputs!$B$23, 0)), 0)
A28: Total Active Customers (inkl. Enterprise) | B28: =B27+B15 | C28: =C27+C15 | D28: =D27+D15 | E28: =E27+E15 | F28: =F27+F15 | G28: =G27+G15 | H28: =H27+H15 | I28: =I27+I15 | ... BA28: =BA27+BA15
A29: Implementation-Support-Tage/Monat [ab Startmonat; Kunden × Wskt. × Tage/Einsatz] | B29: =IF(1>=Inputs!$B$131,B28*Inputs!$B$129*Inputs!$B$130,0) | C29: =IF(2>=Inputs!$B$131,C28*Inputs!$B$129*Inputs!$B$130,0) | D29: =IF(3>=Inputs!$B$131,D28*Inputs!$B$129*Inputs!$B$130,0) | E29: =IF(4>=Inputs!$B$131,E28*Inputs!$B$129*Inputs!$B$130,0) | F29: =IF(5>=Inputs!$B$131,F28*Inputs!$B$129*Inputs!$B$130,0) | G29: =IF(6>=Inputs!$B$131,G28*Inputs!$B$129*Inputs!$B$130,0) | H29: =IF(7>=Inputs!$B$131,H28*Inputs!$B$129*Inputs!$B$130,0) | I29: =IF(8>=Inputs!$B$131,I28*Inputs!$B$129*Inputs!$B$130,0) | J29: =IF(9>=Inputs!$B$131,J28*Inputs!$B$129*Inputs!$B$130,0) | K29: =IF(10>=Inputs!$B$131,K28*Inputs!$B$129*Inputs!$B$130,0) | L29: =IF(11>=Inputs!$B$131,L28*Inputs!$B$129*Inputs!$B$130,0) | M29: =IF(12>=Inputs!$B$131,M28*Inputs!$B$129*Inputs!$B$130,0) | N29: =IF(13>=Inputs!$B$131,N28*Inputs!$B$129*Inputs!$B$130,0) | O29: =IF(14>=Inputs!$B$131,O28*Inputs!$B$129*Inputs!$B$130,0) | P29: =IF(15>=Inputs!$B$131,P28*Inputs!$B$129*Inputs!$B$130,0) | Q29: =IF(16>=Inputs!$B$131,Q28*Inputs!$B$129*Inputs!$B$130,0) | R29: =IF(17>=Inputs!$B$131,R28*Inputs!$B$129*Inputs!$B$130,0) | S29: =IF(18>=Inputs!$B$131,S28*Inputs!$B$129*Inputs!$B$130,0) | T29: =IF(19>=Inputs!$B$131,T28*Inputs!$B$129*Inputs!$B$130,0) | U29: =IF(20>=Inputs!$B$131,U28*Inputs!$B$129*Inputs!$B$130,0) | V29: =IF(21>=Inputs!$B$131,V28*Inputs!$B$129*Inputs!$B$130,0) | W29: =IF(22>=Inputs!$B$131,W28*Inputs!$B$129*Inputs!$B$130,0) | X29: =IF(23>=Inputs!$B$131,X28*Inputs!$B$129*Inputs!$B$130,0) | Y29: =IF(24>=Inputs!$B$131,Y28*Inputs!$B$129*Inputs!$B$130,0) | Z29: =IF(25>=Inputs!$B$131,Z28*Inputs!$B$129*Inputs!$B$130,0) | AA29: =IF(26>=Inputs!$B$131,AA28*Inputs!$B$129*Inputs!$B$130,0) | AB29: =IF(27>=Inputs!$B$131,AB28*Inputs!$B$129*Inputs!$B$130,0) | AC29: =IF(28>=Inputs!$B$131,AC28*Inputs!$B$129*Inputs!$B$130,0) | AD29: =IF(29>=Inputs!$B$131,AD28*Inputs!$B$129*Inputs!$B$130,0) | AE29: =IF(30>=Inputs!$B$131,AE28*Inputs!$B$129*Inputs!$B$130,0) | AF29: =IF(31>=Inputs!$B$131,AF28*Inputs!$B$129*Inputs!$B$130,0) | AG29: =IF(32>=Inputs!$B$131,AG28*Inputs!$B$129*Inputs!$B$130,0) | AH29: =IF(33>=Inputs!$B$131,AH28*Inputs!$B$129*Inputs!$B$130,0) | AI29: =IF(34>=Inputs!$B$131,AI28*Inputs!$B$129*Inputs!$B$130,0) | AJ29: =IF(35>=Inputs!$B$131,AJ28*Inputs!$B$129*Inputs!$B$130,0) | AK29: =IF(36>=Inputs!$B$131,AK28*Inputs!$B$129*Inputs!$B$130,0) | AL29: =IF(37>=Inputs!$B$131,AL28*Inputs!$B$129*Inputs!$B$130,0) | AM29: =IF(38>=Inputs!$B$131,AM28*Inputs!$B$129*Inputs!$B$130,0) | AN29: =IF(39>=Inputs!$B$131,AN28*Inputs!$B$129*Inputs!$B$130,0) | AO29: =IF(40>=Inputs!$B$131,AO28*Inputs!$B$129*Inputs!$B$130,0) | AP29: =IF(41>=Inputs!$B$131,AP28*Inputs!$B$129*Inputs!$B$130,0) | AQ29: =IF(42>=Inputs!$B$131,AQ28*Inputs!$B$129*Inputs!$B$130,0) | AR29: =IF(43>=Inputs!$B$131,AR28*Inputs!$B$129*Inputs!$B$130,0) | AS29: =IF(44>=Inputs!$B$131,AS28*Inputs!$B$129*Inputs!$B$130,0) | AT29: =IF(45>=Inputs!$B$131,AT28*Inputs!$B$129*Inputs!$B$130,0) | AU29: =IF(46>=Inputs!$B$131,AU28*Inputs!$B$129*Inputs!$B$130,0) | AV29: =IF(47>=Inputs!$B$131,AV28*Inputs!$B$129*Inputs!$B$130,0) | AW29: =IF(48>=Inputs!$B$131,AW28*Inputs!$B$129*Inputs!$B$130,0) | AX29: =IF(49>=Inputs!$B$131,AX28*Inputs!$B$129*Inputs!$B$130,0) | AY29: =IF(50>=Inputs!$B$131,AY28*Inputs!$B$129*Inputs!$B$130,0) | AZ29: =IF(51>=Inputs!$B$131,AZ28*Inputs!$B$129*Inputs!$B$130,0) | BA29: =IF(52>=Inputs!$B$131,BA28*Inputs!$B$129*Inputs!$B$130,0)
A30: Implementation-Support Revenue (€/Monat) [= Tage/Mo × Tagessatz] | B30: =B29*Inputs!$B$128 | C30: =C29*Inputs!$B$128 | D30: =D29*Inputs!$B$128 | E30: =E29*Inputs!$B$128 | F30: =F29*Inputs!$B$128 | G30: =G29*Inputs!$B$128 | H30: =H29*Inputs!$B$128 | I30: =I29*Inputs!$B$128 | ... BA30: =BA29*Inputs!$B$128
A32: ℹ Hinweis MRR/ARR vs. Total Revenue: MRR/ARR (Z19/20) = ausschließlich wiederkehrende Lizenzumsätze (Subscription Seats + Enterprise-Verträge). Implementation-Support ist projektbezogen, nicht-wiederkehrend → kein Bestandteil von MRR/ARR (SaaS-Standard: SaaStr/OpenView/a16z). Total Monthly Revenue (Z21) = MRR + Implementation-Support → fließt in P&L TOTAL REVENUE.

Sheet Costs
A1: KOSTENDETAILS | B1: To do 10.3.2026 - Phasen einfügen anhand der Tabelle, die mit Rene und Mouaz abgesprochen worden ist. - Meilensteine in den Spalten markieren, das heißt wann werden entsprechende Funding-Zahlungen hier fällig? - Außerdem klar schauen ob der Aufwuchs an Personal modelliert werden kann oder ob er hier hart eingegeben werden muss. - Auf jeden Fall deutlich machen wo hier Kostensteigerungen durch den Einsatz von Personal stattfinden.
B2: 46113 | C2: 46143 | D2: 46174 | E2: 46204 | F2: 46235 | G2: 46266 | H2: 46296 | I2: 46327 | J2: 46357 | K2: 46388 | L2: 46419 | M2: 46447 | N2: 46478 | O2: 46508 | P2: 46539 | Q2: 46569 | R2: 46600 | S2: 46631 | T2: 46661 | U2: 46692 | V2: 46722 | W2: 46753 | X2: 46784 | Y2: 46813 | Z2: 46844 | AA2: 46874 | AB2: 46905 | AC2: 46935 | AD2: 46966 | AE2: 46997 | AF2: 47027 | AG2: 47058 | AH2: 47088 | AI2: 47119 | AJ2: 47150 | AK2: 47178 | AL2: 47209 | AM2: 47239 | AN2: 47270 | AO2: 47300 | AP2: 47331 | AQ2: 47362 | AR2: 47392 | AS2: 47423 | AT2: 47453 | AU2: 47484 | AV2: 47515 | AW2: 47543 | AX2: 47574 | AY2: 47604 | AZ2: 47635 | BA2: 47665
A3: Startup-Phasen | B3: Ideation | C3: Ideation | D3: Ideation | E3: Ideation | F3: Pre-Seed | G3: Pre-Seed | H3: Pre-Seed | I3: Pre-Seed | J3: Pre-Seed | K3: Pre-Seed | L3: Pre-Seed | M3: Pre-Seed | N3: Pre-Seed | O3: Pre-Seed | P3: Pre-Seed | Q3: Pre-Seed | R3: Seed | S3: Seed | T3: Seed | U3: Seed | V3: Seed | W3: Seed | X3: Seed | Y3: Seed | Z3: Seed | AA3: Seed | AB3: Seed | AC3: Seed | AD3: Series A | AE3: Series A | AF3: Series A | AG3: Series A | AH3: Series A | AI3: Series A | AJ3: Series A | AK3: Series A | AL3: Series A | AM3: Series A | AN3: Series A | AO3: Series A | AP3: Series B | AQ3: Series B | AR3: Series B | AS3: Series B | AT3: Series B | AU3: Series B | AV3: Series B | AW3: Series B | AX3: Series B | AY3: Series B | AZ3: Series B | BA3: Series B
A4: Kostenposition | B4: M1 | C4: M2 | D4: M3 | E4: M4 | F4: M5 | G4: M6 | H4: M7 | I4: M8 | J4: M9 | K4: M10 | L4: M11 | M4: M12 | N4: M13 | O4: M14 | P4: M15 | Q4: M16 | R4: M17 | S4: M18 | T4: M19 | U4: M20 | V4: M21 | W4: M22 | X4: M23 | Y4: M24 | Z4: M25 | AA4: M26 | AB4: M27 | AC4: M28 | AD4: M29 | AE4: M30 | AF4: M31 | AG4: M32 | AH4: M33 | AI4: M34 | AJ4: M35 | AK4: M36 | AL4: M37 | AM4: M38 | AN4: M39 | AO4: M40 | AP4: M41 | AQ4: M42 | AR4: M43 | AS4: M44 | AT4: M45 | AU4: M46 | AV4: M47 | AW4: M48 | AX4: M49 | AY4: M50 | AZ4: M51 | BA4: M52
A5: HEADCOUNT PLAN
A6: Executives (CEO, CTO, CCO) | B6: 3 | C6: 3 | D6: 3 | E6: 3 | F6: 3 | G6: 3 | H6: 3 | I6: 3 | J6: 3 | K6: 3 | L6: 3 | M6: 3 | N6: 3 | O6: 3 | P6: 3 | Q6: 3 | R6: 3 | S6: 3 | T6: 3 | U6: 3 | V6: 3 | W6: 3 | X6: 3 | Y6: 3 | Z6: 3 | AA6: 3 | AB6: 3 | AC6: 3 | AD6: 3 | AE6: 3 | AF6: 3 | AG6: 3 | AH6: 3 | AI6: 3 | AJ6: 3 | AK6: 3 | AL6: 3 | AM6: 3 | AN6: 3 | AO6: 3 | AP6: 3 | AQ6: 3 | AR6: 3 | AS6: 3 | AT6: 3 | AU6: 3 | AV6: 3 | AW6: 3 | AX6: 3 | AY6: 3 | AZ6: 3 | BA6: 3
A7: 1. Software Developer | B7: =IF(COLUMNS($B$7:B7) >= Inputs!$E$51, 1, 0) | C7: =IF(COLUMNS($B$7:C7) >= Inputs!$E$51, 1, 0) | D7: =IF(COLUMNS($B$7:D7) >= Inputs!$E$51, 1, 0) | E7: =IF(COLUMNS($B$7:E7) >= Inputs!$E$51, 1, 0) | F7: =IF(COLUMNS($B$7:F7) >= Inputs!$E$51, 1, 0) | G7: =IF(COLUMNS($B$7:G7) >= Inputs!$E$51, 1, 0) | H7: =IF(COLUMNS($B$7:H7) >= Inputs!$E$51, 1, 0) | I7: =IF(COLUMNS($B$7:I7) >= Inputs!$E$51, 1, 0) | ... BA7: =IF(COLUMNS($B$7:BA7) >= Inputs!$E$51, 1, 0)
A8: 2. Software Developer | B8: =IF(COLUMNS($B$8:B8)>=Inputs!$E$52,1,0) | C8: =IF(COLUMNS($B$8:C8)>=Inputs!$E$52,1,0) | D8: =IF(COLUMNS($B$8:D8)>=Inputs!$E$52,1,0) | E8: =IF(COLUMNS($B$8:E8)>=Inputs!$E$52,1,0) | F8: =IF(COLUMNS($B$8:F8)>=Inputs!$E$52,1,0) | G8: =IF(COLUMNS($B$8:G8)>=Inputs!$E$52,1,0) | H8: =IF(COLUMNS($B$8:H8)>=Inputs!$E$52,1,0) | I8: =IF(COLUMNS($B$8:I8)>=Inputs!$E$52,1,0) | ... BA8: =IF(COLUMNS($B$8:BA8)>=Inputs!$E$52,1,0)
A9: 1. Junior Software Developer | B9: =IF(COLUMNS($B$9:B9) >= Inputs!$E$53, 1, 0) | C9: =IF(COLUMNS($B$9:C9) >= Inputs!$E$53, 1, 0) | D9: =IF(COLUMNS($B$9:D9) >= Inputs!$E$53, 1, 0) | E9: =IF(COLUMNS($B$9:E9) >= Inputs!$E$53, 1, 0) | F9: =IF(COLUMNS($B$9:F9) >= Inputs!$E$53, 1, 0) | G9: =IF(COLUMNS($B$9:G9) >= Inputs!$E$53, 1, 0) | H9: =IF(COLUMNS($B$9:H9) >= Inputs!$E$53, 1, 0) | I9: =IF(COLUMNS($B$9:I9) >= Inputs!$E$53, 1, 0) | ... BA9: =IF(COLUMNS($B$9:BA9) >= Inputs!$E$53, 1, 0)
A10: 1. ML/AI Engineer | B10: =IF(COLUMNS($B$10:B10) >= Inputs!$E$54, 1, 0) | C10: =IF(COLUMNS($B$10:C10) >= Inputs!$E$54, 1, 0) | D10: =IF(COLUMNS($B$10:D10) >= Inputs!$E$54, 1, 0) | E10: =IF(COLUMNS($B$10:E10) >= Inputs!$E$54, 1, 0) | F10: =IF(COLUMNS($B$10:F10) >= Inputs!$E$54, 1, 0) | G10: =IF(COLUMNS($B$10:G10) >= Inputs!$E$54, 1, 0) | H10: =IF(COLUMNS($B$10:H10) >= Inputs!$E$54, 1, 0) | I10: =IF(COLUMNS($B$10:I10) >= Inputs!$E$54, 1, 0) | ... BA10: =IF(COLUMNS($B$10:BA10) >= Inputs!$E$54, 1, 0)
A11: 1. Mechanical Engineer | B11: =IF(COLUMNS($B$11:B11)>=Inputs!$E$55,1,0) | C11: =IF(COLUMNS($B$11:C11)>=Inputs!$E$55,1,0) | D11: =IF(COLUMNS($B$11:D11)>=Inputs!$E$55,1,0) | E11: =IF(COLUMNS($B$11:E11)>=Inputs!$E$55,1,0) | F11: =IF(COLUMNS($B$11:F11)>=Inputs!$E$55,1,0) | G11: =IF(COLUMNS($B$11:G11)>=Inputs!$E$55,1,0) | H11: =IF(COLUMNS($B$11:H11)>=Inputs!$E$55,1,0) | I11: =IF(COLUMNS($B$11:I11)>=Inputs!$E$55,1,0) | ... BA11: =IF(COLUMNS($B$11:BA11)>=Inputs!$E$55,1,0)
A12: 1. UX/UI Designer | B12: =IF(COLUMNS($B$12:B12)>=Inputs!$E$56,1,0) | C12: =IF(COLUMNS($B$12:C12)>=Inputs!$E$56,1,0) | D12: =IF(COLUMNS($B$12:D12)>=Inputs!$E$56,1,0) | E12: =IF(COLUMNS($B$12:E12)>=Inputs!$E$56,1,0) | F12: =IF(COLUMNS($B$12:F12)>=Inputs!$E$56,1,0) | G12: =IF(COLUMNS($B$12:G12)>=Inputs!$E$56,1,0) | H12: =IF(COLUMNS($B$12:H12)>=Inputs!$E$56,1,0) | I12: =IF(COLUMNS($B$12:I12)>=Inputs!$E$56,1,0) | ... BA12: =IF(COLUMNS($B$12:BA12)>=Inputs!$E$56,1,0)
A13: 1. Customer Key Account | B13: =IF(COLUMNS($B$13:B13)>=Inputs!$E$57,1,0) | C13: =IF(COLUMNS($B$13:C13)>=Inputs!$E$57,1,0) | D13: =IF(COLUMNS($B$13:D13)>=Inputs!$E$57,1,0) | E13: =IF(COLUMNS($B$13:E13)>=Inputs!$E$57,1,0) | F13: =IF(COLUMNS($B$13:F13)>=Inputs!$E$57,1,0) | G13: =IF(COLUMNS($B$13:G13)>=Inputs!$E$57,1,0) | H13: =IF(COLUMNS($B$13:H13)>=Inputs!$E$57,1,0) | I13: =IF(COLUMNS($B$13:I13)>=Inputs!$E$57,1,0) | ... BA13: =IF(COLUMNS($B$13:BA13)>=Inputs!$E$57,1,0)
A14: 2. Customer Key Account | B14: =IF(COLUMNS($B$14:B14)>=Inputs!$E$58,1,0) | C14: =IF(COLUMNS($B$14:C14)>=Inputs!$E$58,1,0) | D14: =IF(COLUMNS($B$14:D14)>=Inputs!$E$58,1,0) | E14: =IF(COLUMNS($B$14:E14)>=Inputs!$E$58,1,0) | F14: =IF(COLUMNS($B$14:F14)>=Inputs!$E$58,1,0) | G14: =IF(COLUMNS($B$14:G14)>=Inputs!$E$58,1,0) | H14: =IF(COLUMNS($B$14:H14)>=Inputs!$E$58,1,0) | I14: =IF(COLUMNS($B$14:I14)>=Inputs!$E$58,1,0) | ... BA14: =IF(COLUMNS($B$14:BA14)>=Inputs!$E$58,1,0)
A15: 3. Customer Key Account | B15: =IF(COLUMNS($B$15:B15)>=Inputs!$E$59,1,0) | C15: =IF(COLUMNS($B$15:C15)>=Inputs!$E$59,1,0) | D15: =IF(COLUMNS($B$15:D15)>=Inputs!$E$59,1,0) | E15: =IF(COLUMNS($B$15:E15)>=Inputs!$E$59,1,0) | F15: =IF(COLUMNS($B$15:F15)>=Inputs!$E$59,1,0) | G15: =IF(COLUMNS($B$15:G15)>=Inputs!$E$59,1,0) | H15: =IF(COLUMNS($B$15:H15)>=Inputs!$E$59,1,0) | I15: =IF(COLUMNS($B$15:I15)>=Inputs!$E$59,1,0) | ... BA15: =IF(COLUMNS($B$15:BA15)>=Inputs!$E$59,1,0)
A16: 1. Marketing Assistant | B16: =IF(COLUMNS($B$16:B16)>=Inputs!$E$60,1,0) | C16: =IF(COLUMNS($B$16:C16)>=Inputs!$E$60,1,0) | D16: =IF(COLUMNS($B$16:D16)>=Inputs!$E$60,1,0) | E16: =IF(COLUMNS($B$16:E16)>=Inputs!$E$60,1,0) | F16: =IF(COLUMNS($B$16:F16)>=Inputs!$E$60,1,0) | G16: =IF(COLUMNS($B$16:G16)>=Inputs!$E$60,1,0) | H16: =IF(COLUMNS($B$16:H16)>=Inputs!$E$60,1,0) | I16: =IF(COLUMNS($B$16:I16)>=Inputs!$E$60,1,0) | ... BA16: =IF(COLUMNS($B$16:BA16)>=Inputs!$E$60,1,0)
A17: 2. Marketing Assistant | B17: =IF(COLUMNS($B$17:B17)>=Inputs!$E$61,1,0) | C17: =IF(COLUMNS($B$17:C17)>=Inputs!$E$61,1,0) | D17: =IF(COLUMNS($B$17:D17)>=Inputs!$E$61,1,0) | E17: =IF(COLUMNS($B$17:E17)>=Inputs!$E$61,1,0) | F17: =IF(COLUMNS($B$17:F17)>=Inputs!$E$61,1,0) | G17: =IF(COLUMNS($B$17:G17)>=Inputs!$E$61,1,0) | H17: =IF(COLUMNS($B$17:H17)>=Inputs!$E$61,1,0) | I17: =IF(COLUMNS($B$17:I17)>=Inputs!$E$61,1,0) | ... BA17: =IF(COLUMNS($B$17:BA17)>=Inputs!$E$61,1,0)
A18: 1. Marketing Manager | B18: =IF(COLUMNS($B$18:B18)>=Inputs!$E$62,1,0) | C18: =IF(COLUMNS($B$18:C18)>=Inputs!$E$62,1,0) | D18: =IF(COLUMNS($B$18:D18)>=Inputs!$E$62,1,0) | E18: =IF(COLUMNS($B$18:E18)>=Inputs!$E$62,1,0) | F18: =IF(COLUMNS($B$18:F18)>=Inputs!$E$62,1,0) | G18: =IF(COLUMNS($B$18:G18)>=Inputs!$E$62,1,0) | H18: =IF(COLUMNS($B$18:H18)>=Inputs!$E$62,1,0) | I18: =IF(COLUMNS($B$18:I18)>=Inputs!$E$62,1,0) | ... BA18: =IF(COLUMNS($B$18:BA18)>=Inputs!$E$62,1,0)
A19: 1. Office Manager | B19: =IF(COLUMNS($B$19:B19)>=Inputs!$E$63,1,0) | C19: =IF(COLUMNS($B$19:C19)>=Inputs!$E$63,1,0) | D19: =IF(COLUMNS($B$19:D19)>=Inputs!$E$63,1,0) | E19: =IF(COLUMNS($B$19:E19)>=Inputs!$E$63,1,0) | F19: =IF(COLUMNS($B$19:F19)>=Inputs!$E$63,1,0) | G19: =IF(COLUMNS($B$19:G19)>=Inputs!$E$63,1,0) | H19: =IF(COLUMNS($B$19:H19)>=Inputs!$E$63,1,0) | I19: =IF(COLUMNS($B$19:I19)>=Inputs!$E$63,1,0) | ... BA19: =IF(COLUMNS($B$19:BA19)>=Inputs!$E$63,1,0)
A20: 1. Customer Success | B20: =IF(COLUMNS($B$20:B20)>=Inputs!$E$64,1,0) | C20: =IF(COLUMNS($B$20:C20)>=Inputs!$E$64,1,0) | D20: =IF(COLUMNS($B$20:D20)>=Inputs!$E$64,1,0) | E20: =IF(COLUMNS($B$20:E20)>=Inputs!$E$64,1,0) | F20: =IF(COLUMNS($B$20:F20)>=Inputs!$E$64,1,0) | G20: =IF(COLUMNS($B$20:G20)>=Inputs!$E$64,1,0) | H20: =IF(COLUMNS($B$20:H20)>=Inputs!$E$64,1,0) | I20: =IF(COLUMNS($B$20:I20)>=Inputs!$E$64,1,0) | ... BA20: =IF(COLUMNS($B$20:BA20)>=Inputs!$E$64,1,0)
A21: 1. Finance Manager | B21: =IF(COLUMNS($B$21:B21)>=Inputs!$E$65,1,0) | C21: =IF(COLUMNS($B$21:C21)>=Inputs!$E$65,1,0) | D21: =IF(COLUMNS($B$21:D21)>=Inputs!$E$65,1,0) | E21: =IF(COLUMNS($B$21:E21)>=Inputs!$E$65,1,0) | F21: =IF(COLUMNS($B$21:F21)>=Inputs!$E$65,1,0) | G21: =IF(COLUMNS($B$21:G21)>=Inputs!$E$65,1,0) | H21: =IF(COLUMNS($B$21:H21)>=Inputs!$E$65,1,0) | I21: =IF(COLUMNS($B$21:I21)>=Inputs!$E$65,1,0) | ... BA21: =IF(COLUMNS($B$21:BA21)>=Inputs!$E$65,1,0)
A22: TOTAL HEADCOUNT | B22: =SUM(B6:B21) | C22: =SUM(C6:C21) | D22: =SUM(D6:D21) | E22: =SUM(E6:E21) | F22: =SUM(F6:F21) | G22: =SUM(G6:G21) | H22: =SUM(H6:H21) | I22: =SUM(I6:I21) | ... BA22: =SUM(BA6:BA21)
A24: GEHÄLTER & PERSONALKOSTEN
A25: CEO Gehalt | B25: =B6/3 * (Inputs!$B$32 / 12) * (1 + Inputs!$B$47)^INT((COLUMNS($B$25:B25)-1) / 12) | C25: =C6/3 * (Inputs!$B$32 / 12) * (1 + Inputs!$B$47)^INT((COLUMNS($B$25:C25)-1) / 12) | D25: =D6/3 * (Inputs!$B$32 / 12) * (1 + Inputs!$B$47)^INT((COLUMNS($B$25:D25)-1) / 12) | E25: =E6/3 * (Inputs!$B$32 / 12) * (1 + Inputs!$B$47)^INT((COLUMNS($B$25:E25)-1) / 12) | F25: =F6/3 * (Inputs!$B$32 / 12) * (1 + Inputs!$B$47)^INT((COLUMNS($B$25:F25)-1) / 12) | G25: =G6/3 * (Inputs!$B$32 / 12) * (1 + Inputs!$B$47)^INT((COLUMNS($B$25:G25)-1) / 12) | H25: =H6/3 * (Inputs!$B$32 / 12) * (1 + Inputs!$B$47)^INT((COLUMNS($B$25:H25)-1) / 12) | I25: =I6/3 * (Inputs!$B$32 / 12) * (1 + Inputs!$B$47)^INT((COLUMNS($B$25:I25)-1) / 12) | ... BA25: =BA6/3 * (Inputs!$B$32 / 12) * (1 + Inputs!$B$47)^INT((COLUMNS($B$25:BA25)-1) / 12)
A26: CTO Gehalt | B26: =B6/3 * (Inputs!$B$33 / 12) * (1 + Inputs!$B$47)^INT((COLUMNS($B$26:B26)-1) / 12) | C26: =C6/3 * (Inputs!$B$33 / 12) * (1 + Inputs!$B$47)^INT((COLUMNS($B$26:C26)-1) / 12) | D26: =D6/3 * (Inputs!$B$33 / 12) * (1 + Inputs!$B$47)^INT((COLUMNS($B$26:D26)-1) / 12) | E26: =E6/3 * (Inputs!$B$33 / 12) * (1 + Inputs!$B$47)^INT((COLUMNS($B$26:E26)-1) / 12) | F26: =F6/3 * (Inputs!$B$33 / 12) * (1 + Inputs!$B$47)^INT((COLUMNS($B$26:F26)-1) / 12) | G26: =G6/3 * (Inputs!$B$33 / 12) * (1 + Inputs!$B$47)^INT((COLUMNS($B$26:G26)-1) / 12) | H26: =H6/3 * (Inputs!$B$33 / 12) * (1 + Inputs!$B$47)^INT((COLUMNS($B$26:H26)-1) / 12) | I26: =I6/3 * (Inputs!$B$33 / 12) * (1 + Inputs!$B$47)^INT((COLUMNS($B$26:I26)-1) / 12) | ... BA26: =BA6/3 * (Inputs!$B$33 / 12) * (1 + Inputs!$B$47)^INT((COLUMNS($B$26:BA26)-1) / 12)
A27: CCO Gehalt | B27: =B6/3 * (Inputs!$B$34 / 12) * (1 + Inputs!$B$47)^INT((COLUMNS($B$27:B27)-1) / 12) | C27: =C6/3 * (Inputs!$B$34 / 12) * (1 + Inputs!$B$47)^INT((COLUMNS($B$27:C27)-1) / 12) | D27: =D6/3 * (Inputs!$B$34 / 12) * (1 + Inputs!$B$47)^INT((COLUMNS($B$27:D27)-1) / 12) | E27: =E6/3 * (Inputs!$B$34 / 12) * (1 + Inputs!$B$47)^INT((COLUMNS($B$27:E27)-1) / 12) | F27: =F6/3 * (Inputs!$B$34 / 12) * (1 + Inputs!$B$47)^INT((COLUMNS($B$27:F27)-1) / 12) | G27: =G6/3 * (Inputs!$B$34 / 12) * (1 + Inputs!$B$47)^INT((COLUMNS($B$27:G27)-1) / 12) | H27: =H6/3 * (Inputs!$B$34 / 12) * (1 + Inputs!$B$47)^INT((COLUMNS($B$27:H27)-1) / 12) | I27: =I6/3 * (Inputs!$B$34 / 12) * (1 + Inputs!$B$47)^INT((COLUMNS($B$27:I27)-1) / 12) | ... BA27: =BA6/3 * (Inputs!$B$34 / 12) * (1 + Inputs!$B$47)^INT((COLUMNS($B$27:BA27)-1) / 12)
A28: 1. Software Developer Gehalt | B28: =B7 * (Inputs!$B$35 / 12) * (1 + Inputs!$B$47)^INT((COLUMNS($B$28:B28)-1) / 12) | C28: =C7 * (Inputs!$B$35 / 12) * (1 + Inputs!$B$47)^INT((COLUMNS($B$28:C28)-1) / 12) | D28: =D7 * (Inputs!$B$35 / 12) * (1 + Inputs!$B$47)^INT((COLUMNS($B$28:D28)-1) / 12) | E28: =E7 * (Inputs!$B$35 / 12) * (1 + Inputs!$B$47)^INT((COLUMNS($B$28:E28)-1) / 12) | F28: =F7 * (Inputs!$B$35 / 12) * (1 + Inputs!$B$47)^INT((COLUMNS($B$28:F28)-1) / 12) | G28: =G7 * (Inputs!$B$35 / 12) * (1 + Inputs!$B$47)^INT((COLUMNS($B$28:G28)-1) / 12) | H28: =H7 * (Inputs!$B$35 / 12) * (1 + Inputs!$B$47)^INT((COLUMNS($B$28:H28)-1) / 12) | I28: =I7 * (Inputs!$B$35 / 12) * (1 + Inputs!$B$47)^INT((COLUMNS($B$28:I28)-1) / 12) | ... BA28: =BA7 * (Inputs!$B$35 / 12) * (1 + Inputs!$B$47)^INT((COLUMNS($B$28:BA28)-1) / 12)
A29: 2. Software Developer Gehalt | B29: =B8 * (Inputs!$B$35 / 12) * (1 + Inputs!$B$47)^INT((COLUMNS($B$29:B29)-1) / 12) | C29: =C8 * (Inputs!$B$35 / 12) * (1 + Inputs!$B$47)^INT((COLUMNS($B$29:C29)-1) / 12) | D29: =D8 * (Inputs!$B$35 / 12) * (1 + Inputs!$B$47)^INT((COLUMNS($B$29:D29)-1) / 12) | E29: =E8 * (Inputs!$B$35 / 12) * (1 + Inputs!$B$47)^INT((COLUMNS($B$29:E29)-1) / 12) | F29: =F8 * (Inputs!$B$35 / 12) * (1 + Inputs!$B$47)^INT((COLUMNS($B$29:F29)-1) / 12) | G29: =G8 * (Inputs!$B$35 / 12) * (1 + Inputs!$B$47)^INT((COLUMNS($B$29:G29)-1) / 12) | H29: =H8 * (Inputs!$B$35 / 12) * (1 + Inputs!$B$47)^INT((COLUMNS($B$29:H29)-1) / 12) | I29: =I8 * (Inputs!$B$35 / 12) * (1 + Inputs!$B$47)^INT((COLUMNS($B$29:I29)-1) / 12) | ... BA29: =BA8 * (Inputs!$B$35 / 12) * (1 + Inputs!$B$47)^INT((COLUMNS($B$29:BA29)-1) / 12)
A30: 1. Junior Software Developer Gehalt | B30: =B9 * (Inputs!$B$36 / 12) * (1 + Inputs!$B$47)^INT((COLUMNS($B$30:B30)-1) / 12) | C30: =C9 * (Inputs!$B$36 / 12) * (1 + Inputs!$B$47)^INT((COLUMNS($B$30:C30)-1) / 12) | D30: =D9 * (Inputs!$B$36 / 12) * (1 + Inputs!$B$47)^INT((COLUMNS($B$30:D30)-1) / 12) | E30: =E9 * (Inputs!$B$36 / 12) * (1 + Inputs!$B$47)^INT((COLUMNS($B$30:E30)-1) / 12) | F30: =F9 * (Inputs!$B$36 / 12) * (1 + Inputs!$B$47)^INT((COLUMNS($B$30:F30)-1) / 12) | G30: =G9 * (Inputs!$B$36 / 12) * (1 + Inputs!$B$47)^INT((COLUMNS($B$30:G30)-1) / 12) | H30: =H9 * (Inputs!$B$36 / 12) * (1 + Inputs!$B$47)^INT((COLUMNS($B$30:H30)-1) / 12) | I30: =I9 * (Inputs!$B$36 / 12) * (1 + Inputs!$B$47)^INT((COLUMNS($B$30:I30)-1) / 12) | ... BA30: =BA9 * (Inputs!$B$36 / 12) * (1 + Inputs!$B$47)^INT((COLUMNS($B$30:BA30)-1) / 12)
A31: 1. ML/AI Engineer Gehalt | B31: =B10 * (Inputs!$B$37 / 12) * (1 + Inputs!$B$47)^INT((COLUMNS($B$31:B31)-1) / 12) | C31: =C10 * (Inputs!$B$37 / 12) * (1 + Inputs!$B$47)^INT((COLUMNS($B$31:C31)-1) / 12) | D31: =D10 * (Inputs!$B$37 / 12) * (1 + Inputs!$B$47)^INT((COLUMNS($B$31:D31)-1) / 12) | E31: =E10 * (Inputs!$B$37 / 12) * (1 + Inputs!$B$47)^INT((COLUMNS($B$31:E31)-1) / 12) | F31: =F10 * (Inputs!$B$37 / 12) * (1 + Inputs!$B$47)^INT((COLUMNS($B$31:F31)-1) / 12) | G31: =G10 * (Inputs!$B$37 / 12) * (1 + Inputs!$B$47)^INT((COLUMNS($B$31:G31)-1) / 12) | H31: =H10 * (Inputs!$B$37 / 12) * (1 + Inputs!$B$47)^INT((COLUMNS($B$31:H31)-1) / 12) | I31: =I10 * (Inputs!$B$37 / 12) * (1 + Inputs!$B$47)^INT((COLUMNS($B$31:I31)-1) / 12) | ... BA31: =BA10 * (Inputs!$B$37 / 12) * (1 + Inputs!$B$47)^INT((COLUMNS($B$31:BA31)-1) / 12)
A32: 1. Mechanical Engineer Gehalt | B32: =B11*(Inputs!$B$40/12)*(1+Inputs!$B$47)^INT((COLUMNS($B$32:B32)-1)/12) | C32: =C11*(Inputs!$B$40/12)*(1+Inputs!$B$47)^INT((COLUMNS($B$32:C32)-1)/12) | D32: =D11*(Inputs!$B$40/12)*(1+Inputs!$B$47)^INT((COLUMNS($B$32:D32)-1)/12) | E32: =E11*(Inputs!$B$40/12)*(1+Inputs!$B$47)^INT((COLUMNS($B$32:E32)-1)/12) | F32: =F11*(Inputs!$B$40/12)*(1+Inputs!$B$47)^INT((COLUMNS($B$32:F32)-1)/12) | G32: =G11*(Inputs!$B$40/12)*(1+Inputs!$B$47)^INT((COLUMNS($B$32:G32)-1)/12) | H32: =H11*(Inputs!$B$40/12)*(1+Inputs!$B$47)^INT((COLUMNS($B$32:H32)-1)/12) | I32: =I11*(Inputs!$B$40/12)*(1+Inputs!$B$47)^INT((COLUMNS($B$32:I32)-1)/12) | ... BA32: =BA11*(Inputs!$B$40/12)*(1+Inputs!$B$47)^INT((COLUMNS($B$32:BA32)-1)/12)
A33: 1. UX/UI Designer Gehalt | B33: =B12*(Inputs!$B$39/12)*(1+Inputs!$B$47)^INT((COLUMNS($B$33:B33)-1)/12) | C33: =C12*(Inputs!$B$39/12)*(1+Inputs!$B$47)^INT((COLUMNS($B$33:C33)-1)/12) | D33: =D12*(Inputs!$B$39/12)*(1+Inputs!$B$47)^INT((COLUMNS($B$33:D33)-1)/12) | E33: =E12*(Inputs!$B$39/12)*(1+Inputs!$B$47)^INT((COLUMNS($B$33:E33)-1)/12) | F33: =F12*(Inputs!$B$39/12)*(1+Inputs!$B$47)^INT((COLUMNS($B$33:F33)-1)/12) | G33: =G12*(Inputs!$B$39/12)*(1+Inputs!$B$47)^INT((COLUMNS($B$33:G33)-1)/12) | H33: =H12*(Inputs!$B$39/12)*(1+Inputs!$B$47)^INT((COLUMNS($B$33:H33)-1)/12) | I33: =I12*(Inputs!$B$39/12)*(1+Inputs!$B$47)^INT((COLUMNS($B$33:I33)-1)/12) | ... BA33: =BA12*(Inputs!$B$39/12)*(1+Inputs!$B$47)^INT((COLUMNS($B$33:BA33)-1)/12)
A34: 1. Customer Key Account Gehalt | B34: =B13 * (Inputs!$B$41 / 12) * (1 + Inputs!$B$47)^INT((COLUMNS($B$34:B34)-1) / 12) | C34: =C13 * (Inputs!$B$41 / 12) * (1 + Inputs!$B$47)^INT((COLUMNS($B$34:C34)-1) / 12) | D34: =D13 * (Inputs!$B$41 / 12) * (1 + Inputs!$B$47)^INT((COLUMNS($B$34:D34)-1) / 12) | E34: =E13 * (Inputs!$B$41 / 12) * (1 + Inputs!$B$47)^INT((COLUMNS($B$34:E34)-1) / 12) | F34: =F13 * (Inputs!$B$41 / 12) * (1 + Inputs!$B$47)^INT((COLUMNS($B$34:F34)-1) / 12) | G34: =G13 * (Inputs!$B$41 / 12) * (1 + Inputs!$B$47)^INT((COLUMNS($B$34:G34)-1) / 12) | H34: =H13 * (Inputs!$B$41 / 12) * (1 + Inputs!$B$47)^INT((COLUMNS($B$34:H34)-1) / 12) | I34: =I13 * (Inputs!$B$41 / 12) * (1 + Inputs!$B$47)^INT((COLUMNS($B$34:I34)-1) / 12) | ... BA34: =BA13 * (Inputs!$B$41 / 12) * (1 + Inputs!$B$47)^INT((COLUMNS($B$34:BA34)-1) / 12)
A35: 2. Customer Key Account Gehalt | B35: =B14*(Inputs!$B$41/12)*(1+Inputs!$B$47)^INT((COLUMNS($B$35:B35)-1)/12) | C35: =C14*(Inputs!$B$41/12)*(1+Inputs!$B$47)^INT((COLUMNS($B$35:C35)-1)/12) | D35: =D14*(Inputs!$B$41/12)*(1+Inputs!$B$47)^INT((COLUMNS($B$35:D35)-1)/12) | E35: =E14*(Inputs!$B$41/12)*(1+Inputs!$B$47)^INT((COLUMNS($B$35:E35)-1)/12) | F35: =F14*(Inputs!$B$41/12)*(1+Inputs!$B$47)^INT((COLUMNS($B$35:F35)-1)/12) | G35: =G14*(Inputs!$B$41/12)*(1+Inputs!$B$47)^INT((COLUMNS($B$35:G35)-1)/12) | H35: =H14*(Inputs!$B$41/12)*(1+Inputs!$B$47)^INT((COLUMNS($B$35:H35)-1)/12) | I35: =I14*(Inputs!$B$41/12)*(1+Inputs!$B$47)^INT((COLUMNS($B$35:I35)-1)/12) | ... BA35: =BA14*(Inputs!$B$41/12)*(1+Inputs!$B$47)^INT((COLUMNS($B$35:BA35)-1)/12)
A36: 3. Customer Key Account Gehalt | B36: =B15*(Inputs!$B$41/12)*(1+Inputs!$B$47)^INT((COLUMNS($B$36:B36)-1)/12) | C36: =C15*(Inputs!$B$41/12)*(1+Inputs!$B$47)^INT((COLUMNS($B$36:C36)-1)/12) | D36: =D15*(Inputs!$B$41/12)*(1+Inputs!$B$47)^INT((COLUMNS($B$36:D36)-1)/12) | E36: =E15*(Inputs!$B$41/12)*(1+Inputs!$B$47)^INT((COLUMNS($B$36:E36)-1)/12) | F36: =F15*(Inputs!$B$41/12)*(1+Inputs!$B$47)^INT((COLUMNS($B$36:F36)-1)/12) | G36: =G15*(Inputs!$B$41/12)*(1+Inputs!$B$47)^INT((COLUMNS($B$36:G36)-1)/12) | H36: =H15*(Inputs!$B$41/12)*(1+Inputs!$B$47)^INT((COLUMNS($B$36:H36)-1)/12) | I36: =I15*(Inputs!$B$41/12)*(1+Inputs!$B$47)^INT((COLUMNS($B$36:I36)-1)/12) | ... BA36: =BA15*(Inputs!$B$41/12)*(1+Inputs!$B$47)^INT((COLUMNS($B$36:BA36)-1)/12)
A37: 1. Marketing Assistant Gehalt | B37: =B16*(Inputs!$B$43/12)*(1+Inputs!$B$47)^INT((COLUMNS($B$37:B37)-1)/12) | C37: =C16*(Inputs!$B$43/12)*(1+Inputs!$B$47)^INT((COLUMNS($B$37:C37)-1)/12) | D37: =D16*(Inputs!$B$43/12)*(1+Inputs!$B$47)^INT((COLUMNS($B$37:D37)-1)/12) | E37: =E16*(Inputs!$B$43/12)*(1+Inputs!$B$47)^INT((COLUMNS($B$37:E37)-1)/12) | F37: =F16*(Inputs!$B$43/12)*(1+Inputs!$B$47)^INT((COLUMNS($B$37:F37)-1)/12) | G37: =G16*(Inputs!$B$43/12)*(1+Inputs!$B$47)^INT((COLUMNS($B$37:G37)-1)/12) | H37: =H16*(Inputs!$B$43/12)*(1+Inputs!$B$47)^INT((COLUMNS($B$37:H37)-1)/12) | I37: =I16*(Inputs!$B$43/12)*(1+Inputs!$B$47)^INT((COLUMNS($B$37:I37)-1)/12) | ... BA37: =BA16*(Inputs!$B$43/12)*(1+Inputs!$B$47)^INT((COLUMNS($B$37:BA37)-1)/12)
A38: 2. Marketing Assistant Gehalt | B38: =B17*(Inputs!$B$43/12)*(1+Inputs!$B$47)^INT((COLUMNS($B$38:B38)-1)/12) | C38: =C17*(Inputs!$B$43/12)*(1+Inputs!$B$47)^INT((COLUMNS($B$38:C38)-1)/12) | D38: =D17*(Inputs!$B$43/12)*(1+Inputs!$B$47)^INT((COLUMNS($B$38:D38)-1)/12) | E38: =E17*(Inputs!$B$43/12)*(1+Inputs!$B$47)^INT((COLUMNS($B$38:E38)-1)/12) | F38: =F17*(Inputs!$B$43/12)*(1+Inputs!$B$47)^INT((COLUMNS($B$38:F38)-1)/12) | G38: =G17*(Inputs!$B$43/12)*(1+Inputs!$B$47)^INT((COLUMNS($B$38:G38)-1)/12) | H38: =H17*(Inputs!$B$43/12)*(1+Inputs!$B$47)^INT((COLUMNS($B$38:H38)-1)/12) | I38: =I17*(Inputs!$B$43/12)*(1+Inputs!$B$47)^INT((COLUMNS($B$38:I38)-1)/12) | ... BA38: =BA17*(Inputs!$B$43/12)*(1+Inputs!$B$47)^INT((COLUMNS($B$38:BA38)-1)/12)
A39: 1. Marketing Manager Gehalt | B39: =B18*(Inputs!$B$42/12)*(1+Inputs!$B$47)^INT((COLUMNS($B$39:B39)-1)/12) | C39: =C18*(Inputs!$B$42/12)*(1+Inputs!$B$47)^INT((COLUMNS($B$39:C39)-1)/12) | D39: =D18*(Inputs!$B$42/12)*(1+Inputs!$B$47)^INT((COLUMNS($B$39:D39)-1)/12) | E39: =E18*(Inputs!$B$42/12)*(1+Inputs!$B$47)^INT((COLUMNS($B$39:E39)-1)/12) | F39: =F18*(Inputs!$B$42/12)*(1+Inputs!$B$47)^INT((COLUMNS($B$39:F39)-1)/12) | G39: =G18*(Inputs!$B$42/12)*(1+Inputs!$B$47)^INT((COLUMNS($B$39:G39)-1)/12) | H39: =H18*(Inputs!$B$42/12)*(1+Inputs!$B$47)^INT((COLUMNS($B$39:H39)-1)/12) | I39: =I18*(Inputs!$B$42/12)*(1+Inputs!$B$47)^INT((COLUMNS($B$39:I39)-1)/12) | ... BA39: =BA18*(Inputs!$B$42/12)*(1+Inputs!$B$47)^INT((COLUMNS($B$39:BA39)-1)/12)
A40: 1. Office Manager Gehalt | B40: =B19*(Inputs!$B$45/12)*(1+Inputs!$B$47)^INT((COLUMNS($B$40:B40)-1)/12) | C40: =C19*(Inputs!$B$45/12)*(1+Inputs!$B$47)^INT((COLUMNS($B$40:C40)-1)/12) | D40: =D19*(Inputs!$B$45/12)*(1+Inputs!$B$47)^INT((COLUMNS($B$40:D40)-1)/12) | E40: =E19*(Inputs!$B$45/12)*(1+Inputs!$B$47)^INT((COLUMNS($B$40:E40)-1)/12) | F40: =F19*(Inputs!$B$45/12)*(1+Inputs!$B$47)^INT((COLUMNS($B$40:F40)-1)/12) | G40: =G19*(Inputs!$B$45/12)*(1+Inputs!$B$47)^INT((COLUMNS($B$40:G40)-1)/12) | H40: =H19*(Inputs!$B$45/12)*(1+Inputs!$B$47)^INT((COLUMNS($B$40:H40)-1)/12) | I40: =I19*(Inputs!$B$45/12)*(1+Inputs!$B$47)^INT((COLUMNS($B$40:I40)-1)/12) | ... BA40: =BA19*(Inputs!$B$45/12)*(1+Inputs!$B$47)^INT((COLUMNS($B$40:BA40)-1)/12)
A41: 1. Customer Success Gehalt | B41: =B20*(Inputs!$B$44/12)*(1+Inputs!$B$47)^INT((COLUMNS($B$41:B41)-1)/12) | C41: =C20*(Inputs!$B$44/12)*(1+Inputs!$B$47)^INT((COLUMNS($B$41:C41)-1)/12) | D41: =D20*(Inputs!$B$44/12)*(1+Inputs!$B$47)^INT((COLUMNS($B$41:D41)-1)/12) | E41: =E20*(Inputs!$B$44/12)*(1+Inputs!$B$47)^INT((COLUMNS($B$41:E41)-1)/12) | F41: =F20*(Inputs!$B$44/12)*(1+Inputs!$B$47)^INT((COLUMNS($B$41:F41)-1)/12) | G41: =G20*(Inputs!$B$44/12)*(1+Inputs!$B$47)^INT((COLUMNS($B$41:G41)-1)/12) | H41: =H20*(Inputs!$B$44/12)*(1+Inputs!$B$47)^INT((COLUMNS($B$41:H41)-1)/12) | I41: =I20*(Inputs!$B$44/12)*(1+Inputs!$B$47)^INT((COLUMNS($B$41:I41)-1)/12) | ... BA41: =BA20*(Inputs!$B$44/12)*(1+Inputs!$B$47)^INT((COLUMNS($B$41:BA41)-1)/12)
A42: 1. Finance Manager Gehalt | B42: =B21*(Inputs!$B$46/12)*(1+Inputs!$B$47)^INT((COLUMNS($B$42:B42)-1)/12) | C42: =C21*(Inputs!$B$46/12)*(1+Inputs!$B$47)^INT((COLUMNS($B$42:C42)-1)/12) | D42: =D21*(Inputs!$B$46/12)*(1+Inputs!$B$47)^INT((COLUMNS($B$42:D42)-1)/12) | E42: =E21*(Inputs!$B$46/12)*(1+Inputs!$B$47)^INT((COLUMNS($B$42:E42)-1)/12) | F42: =F21*(Inputs!$B$46/12)*(1+Inputs!$B$47)^INT((COLUMNS($B$42:F42)-1)/12) | G42: =G21*(Inputs!$B$46/12)*(1+Inputs!$B$47)^INT((COLUMNS($B$42:G42)-1)/12) | H42: =H21*(Inputs!$B$46/12)*(1+Inputs!$B$47)^INT((COLUMNS($B$42:H42)-1)/12) | I42: =I21*(Inputs!$B$46/12)*(1+Inputs!$B$47)^INT((COLUMNS($B$42:I42)-1)/12) | ... BA42: =BA21*(Inputs!$B$46/12)*(1+Inputs!$B$47)^INT((COLUMNS($B$42:BA42)-1)/12)
A43: Subtotal Brutto-Gehälter | B43: =SUM(B25:B42) | C43: =SUM(C25:C42) | D43: =SUM(D25:D42) | E43: =SUM(E25:E42) | F43: =SUM(F25:F42) | G43: =SUM(G25:G42) | H43: =SUM(H25:H42) | I43: =SUM(I25:I42) | ... BA43: =SUM(BA25:BA42)
A44: Lohnnebenkosten (AG-Anteil) | B44: =B43*Inputs!$B$48 | C44: =C43*Inputs!$B$48 | D44: =D43*Inputs!$B$48 | E44: =E43*Inputs!$B$48 | F44: =F43*Inputs!$B$48 | G44: =G43*Inputs!$B$48 | H44: =H43*Inputs!$B$48 | I44: =I43*Inputs!$B$48 | ... BA44: =BA43*Inputs!$B$48
A45: TOTAL PERSONALKOSTEN | B45: =B43+B44 | C45: =C43+C44 | D45: =D43+D44 | E45: =E43+E44 | F45: =F43+F44 | G45: =G43+G44 | H45: =H43+H44 | I45: =I43+I44 | ... BA45: =BA43+BA44
A47: TECHNOLOGIEKOSTEN
A48: Cloud Infrastructure (Basis) | B48: =Inputs!$B$68 | C48: =Inputs!$B$68 | D48: =Inputs!$B$68 | E48: =Inputs!$B$68 | F48: =Inputs!$B$68 | G48: =Inputs!$B$68 | H48: =Inputs!$B$68 | I48: =Inputs!$B$68 | ... BA48: =Inputs!$B$68
A49: Cloud Infrastructure (Variable) | B49: =Revenue!B9*Inputs!$B$69 | C49: =Revenue!C9*Inputs!$B$69 | D49: =Revenue!D9*Inputs!$B$69 | E49: =Revenue!E9*Inputs!$B$69 | F49: =Revenue!F9*Inputs!$B$69 | G49: =Revenue!G9*Inputs!$B$69 | H49: =Revenue!H9*Inputs!$B$69 | I49: =Revenue!I9*Inputs!$B$69 | ... BA49: =Revenue!BA9*Inputs!$B$69
A50: AI/ML API Kosten | B50: =Inputs!$B$70*(1+Inputs!$B$71)^(1-1) | C50: =Inputs!$B$70*(1+Inputs!$B$71)^(2-1) | D50: =Inputs!$B$70*(1+Inputs!$B$71)^(3-1) | E50: =Inputs!$B$70*(1+Inputs!$B$71)^(4-1) | F50: =Inputs!$B$70*(1+Inputs!$B$71)^(5-1) | G50: =Inputs!$B$70*(1+Inputs!$B$71)^(6-1) | H50: =Inputs!$B$70*(1+Inputs!$B$71)^(7-1) | I50: =Inputs!$B$70*(1+Inputs!$B$71)^(8-1) | J50: =Inputs!$B$70*(1+Inputs!$B$71)^(9-1) | K50: =Inputs!$B$70*(1+Inputs!$B$71)^(10-1) | L50: =Inputs!$B$70*(1+Inputs!$B$71)^(11-1) | M50: =Inputs!$B$70*(1+Inputs!$B$71)^(12-1) | N50: =Inputs!$B$70*(1+Inputs!$B$71)^(13-1) | O50: =Inputs!$B$70*(1+Inputs!$B$71)^(14-1) | P50: =Inputs!$B$70*(1+Inputs!$B$71)^(15-1) | Q50: =Inputs!$B$70*(1+Inputs!$B$71)^(16-1) | R50: =Inputs!$B$70*(1+Inputs!$B$71)^(17-1) | S50: =Inputs!$B$70*(1+Inputs!$B$71)^(18-1) | T50: =Inputs!$B$70*(1+Inputs!$B$71)^(19-1) | U50: =Inputs!$B$70*(1+Inputs!$B$71)^(20-1) | V50: =Inputs!$B$70*(1+Inputs!$B$71)^(21-1) | W50: =Inputs!$B$70*(1+Inputs!$B$71)^(22-1) | X50: =Inputs!$B$70*(1+Inputs!$B$71)^(23-1) | Y50: =Inputs!$B$70*(1+Inputs!$B$71)^(24-1) | Z50: =Inputs!$B$70*(1+Inputs!$B$71)^(25-1) | AA50: =Inputs!$B$70*(1+Inputs!$B$71)^(26-1) | AB50: =Inputs!$B$70*(1+Inputs!$B$71)^(27-1) | AC50: =Inputs!$B$70*(1+Inputs!$B$71)^(28-1) | AD50: =Inputs!$B$70*(1+Inputs!$B$71)^(29-1) | AE50: =Inputs!$B$70*(1+Inputs!$B$71)^(30-1) | AF50: =Inputs!$B$70*(1+Inputs!$B$71)^(31-1) | AG50: =Inputs!$B$70*(1+Inputs!$B$71)^(32-1) | AH50: =Inputs!$B$70*(1+Inputs!$B$71)^(33-1) | AI50: =Inputs!$B$70*(1+Inputs!$B$71)^(34-1) | AJ50: =Inputs!$B$70*(1+Inputs!$B$71)^(35-1) | AK50: =Inputs!$B$70*(1+Inputs!$B$71)^(36-1) | AL50: =Inputs!$B$70*(1+Inputs!$B$71)^(37-1) | AM50: =Inputs!$B$70*(1+Inputs!$B$71)^(38-1) | AN50: =Inputs!$B$70*(1+Inputs!$B$71)^(39-1) | AO50: =Inputs!$B$70*(1+Inputs!$B$71)^(40-1) | AP50: =Inputs!$B$70*(1+Inputs!$B$71)^(41-1) | AQ50: =Inputs!$B$70*(1+Inputs!$B$71)^(42-1) | AR50: =Inputs!$B$70*(1+Inputs!$B$71)^(43-1) | AS50: =Inputs!$B$70*(1+Inputs!$B$71)^(44-1) | AT50: =Inputs!$B$70*(1+Inputs!$B$71)^(45-1) | AU50: =Inputs!$B$70*(1+Inputs!$B$71)^(46-1) | AV50: =Inputs!$B$70*(1+Inputs!$B$71)^(47-1) | AW50: =Inputs!$B$70*(1+Inputs!$B$71)^(48-1) | AX50: =Inputs!$B$70*(1+Inputs!$B$71)^(49-1) | AY50: =Inputs!$B$70*(1+Inputs!$B$71)^(50-1) | AZ50: =Inputs!$B$70*(1+Inputs!$B$71)^(51-1) | BA50: =Inputs!$B$70*(1+Inputs!$B$71)^(52-1)
A51: SaaS Tools intern | B51: =Inputs!$B$72+B22*Inputs!$B$73 | C51: =Inputs!$B$72+C22*Inputs!$B$73 | D51: =Inputs!$B$72+D22*Inputs!$B$73 | E51: =Inputs!$B$72+E22*Inputs!$B$73 | F51: =Inputs!$B$72+F22*Inputs!$B$73 | G51: =Inputs!$B$72+G22*Inputs!$B$73 | H51: =Inputs!$B$72+H22*Inputs!$B$73 | I51: =Inputs!$B$72+I22*Inputs!$B$73 | ... BA51: =Inputs!$B$72+BA22*Inputs!$B$73
A52: Software-Lizenzen Dev | B52: =Inputs!$B$74/12 | C52: =Inputs!$B$74/12 | D52: =Inputs!$B$74/12 | E52: =Inputs!$B$74/12 | F52: =Inputs!$B$74/12 | G52: =Inputs!$B$74/12 | H52: =Inputs!$B$74/12 | I52: =Inputs!$B$74/12 | ... BA52: =Inputs!$B$74/12
A53: Sicherheit & Compliance | B53: =Inputs!$B$75 | C53: =Inputs!$B$75 | D53: =Inputs!$B$75 | E53: =Inputs!$B$75 | F53: =Inputs!$B$75 | G53: =Inputs!$B$75 | H53: =Inputs!$B$75 | I53: =Inputs!$B$75 | ... BA53: =Inputs!$B$75
A54: TOTAL TECHNOLOGIE | B54: =SUM(B48:B53) | C54: =SUM(C48:C53) | D54: =SUM(D48:D53) | E54: =SUM(E48:E53) | F54: =SUM(F48:F53) | G54: =SUM(G48:G53) | H54: =SUM(H48:H53) | I54: =SUM(I48:I53) | ... BA54: =SUM(BA48:BA53)
A56: BÜROKOSTEN
A57: Büromiete | B57: =IF(1>=Inputs!$B$85,Inputs!$B$86,Inputs!$B$84) | C57: =IF(2>=Inputs!$B$85,Inputs!$B$86,Inputs!$B$84) | D57: =IF(3>=Inputs!$B$85,Inputs!$B$86,Inputs!$B$84) | E57: =IF(4>=Inputs!$B$85,Inputs!$B$86,Inputs!$B$84) | F57: =IF(5>=Inputs!$B$85,Inputs!$B$86,Inputs!$B$84) | G57: =IF(6>=Inputs!$B$85,Inputs!$B$86,Inputs!$B$84) | H57: =IF(7>=Inputs!$B$85,Inputs!$B$86,Inputs!$B$84) | I57: =IF(8>=Inputs!$B$85,Inputs!$B$86,Inputs!$B$84) | J57: =IF(9>=Inputs!$B$85,Inputs!$B$86,Inputs!$B$84) | K57: =IF(10>=Inputs!$B$85,Inputs!$B$86,Inputs!$B$84) | L57: =IF(11>=Inputs!$B$85,Inputs!$B$86,Inputs!$B$84) | M57: =IF(12>=Inputs!$B$85,Inputs!$B$86,Inputs!$B$84) | N57: =IF(13>=Inputs!$B$85,Inputs!$B$86,Inputs!$B$84) | O57: =IF(14>=Inputs!$B$85,Inputs!$B$86,Inputs!$B$84) | P57: =IF(15>=Inputs!$B$85,Inputs!$B$86,Inputs!$B$84) | Q57: =IF(16>=Inputs!$B$85,Inputs!$B$86,Inputs!$B$84) | R57: =IF(17>=Inputs!$B$85,Inputs!$B$86,Inputs!$B$84) | S57: =IF(18>=Inputs!$B$85,Inputs!$B$86,Inputs!$B$84) | T57: =IF(19>=Inputs!$B$85,Inputs!$B$86,Inputs!$B$84) | U57: =IF(20>=Inputs!$B$85,Inputs!$B$86,Inputs!$B$84) | V57: =IF(21>=Inputs!$B$85,Inputs!$B$86,Inputs!$B$84) | W57: =IF(22>=Inputs!$B$85,Inputs!$B$86,Inputs!$B$84) | X57: =IF(23>=Inputs!$B$85,Inputs!$B$86,Inputs!$B$84) | Y57: =IF(24>=Inputs!$B$85,Inputs!$B$86,Inputs!$B$84) | Z57: =IF(25>=Inputs!$B$85,Inputs!$B$86,Inputs!$B$84) | AA57: =IF(26>=Inputs!$B$85,Inputs!$B$86,Inputs!$B$84) | AB57: =IF(27>=Inputs!$B$85,Inputs!$B$86,Inputs!$B$84) | AC57: =IF(28>=Inputs!$B$85,Inputs!$B$86,Inputs!$B$84) | AD57: =IF(29>=Inputs!$B$85,Inputs!$B$86,Inputs!$B$84) | AE57: =IF(30>=Inputs!$B$85,Inputs!$B$86,Inputs!$B$84) | AF57: =IF(31>=Inputs!$B$85,Inputs!$B$86,Inputs!$B$84) | AG57: =IF(32>=Inputs!$B$85,Inputs!$B$86,Inputs!$B$84) | AH57: =IF(33>=Inputs!$B$85,Inputs!$B$86,Inputs!$B$84) | AI57: =IF(34>=Inputs!$B$85,Inputs!$B$86,Inputs!$B$84) | AJ57: =IF(35>=Inputs!$B$85,Inputs!$B$86,Inputs!$B$84) | AK57: =IF(36>=Inputs!$B$85,Inputs!$B$86,Inputs!$B$84) | AL57: =IF(37>=Inputs!$B$85,Inputs!$B$86,Inputs!$B$84) | AM57: =IF(38>=Inputs!$B$85,Inputs!$B$86,Inputs!$B$84) | AN57: =IF(39>=Inputs!$B$85,Inputs!$B$86,Inputs!$B$84) | AO57: =IF(40>=Inputs!$B$85,Inputs!$B$86,Inputs!$B$84) | AP57: =IF(41>=Inputs!$B$85,Inputs!$B$86,Inputs!$B$84) | AQ57: =IF(42>=Inputs!$B$85,Inputs!$B$86,Inputs!$B$84) | AR57: =IF(43>=Inputs!$B$85,Inputs!$B$86,Inputs!$B$84) | AS57: =IF(44>=Inputs!$B$85,Inputs!$B$86,Inputs!$B$84) | AT57: =IF(45>=Inputs!$B$85,Inputs!$B$86,Inputs!$B$84) | AU57: =IF(46>=Inputs!$B$85,Inputs!$B$86,Inputs!$B$84) | AV57: =IF(47>=Inputs!$B$85,Inputs!$B$86,Inputs!$B$84) | AW57: =IF(48>=Inputs!$B$85,Inputs!$B$86,Inputs!$B$84) | AX57: =IF(49>=Inputs!$B$85,Inputs!$B$86,Inputs!$B$84) | AY57: =IF(50>=Inputs!$B$85,Inputs!$B$86,Inputs!$B$84) | AZ57: =IF(51>=Inputs!$B$85,Inputs!$B$86,Inputs!$B$84) | BA57: =IF(52>=Inputs!$B$85,Inputs!$B$86,Inputs!$B$84)
A58: Nebenkosten | B58: =Inputs!$B$87 | C58: =Inputs!$B$87 | D58: =Inputs!$B$87 | E58: =Inputs!$B$87 | F58: =Inputs!$B$87 | G58: =Inputs!$B$87 | H58: =Inputs!$B$87 | I58: =Inputs!$B$87 | ... BA58: =Inputs!$B$87
A59: Internet & Telefon | B59: =Inputs!$B$88 | C59: =Inputs!$B$88 | D59: =Inputs!$B$88 | E59: =Inputs!$B$88 | F59: =Inputs!$B$88 | G59: =Inputs!$B$88 | H59: =Inputs!$B$88 | I59: =Inputs!$B$88 | ... BA59: =Inputs!$B$88
A60: Bürobedarf | B60: =B22*Inputs!$B$90 | C60: =C22*Inputs!$B$90 | D60: =D22*Inputs!$B$90 | E60: =E22*Inputs!$B$90 | F60: =F22*Inputs!$B$90 | G60: =G22*Inputs!$B$90 | H60: =H22*Inputs!$B$90 | I60: =I22*Inputs!$B$90 | ... BA60: =BA22*Inputs!$B$90
A61: TOTAL BÜRO | B61: =SUM(B57:B60) | C61: =SUM(C57:C60) | D61: =SUM(D57:D60) | E61: =SUM(E57:E60) | F61: =SUM(F57:F60) | G61: =SUM(G57:G60) | H61: =SUM(H57:H60) | I61: =SUM(I57:I60) | ... BA61: =SUM(BA57:BA60)
A63: PROFESSIONAL SERVICES
A64: Rechtsanwalt (laufend) | B64: =Inputs!$B$93/12+IF(OR(1=Inputs!$B$11,1=Inputs!$B$13,1=Inputs!$B$15,1=Inputs!$B$17),Inputs!$B$94,0) | C64: =Inputs!$B$93/12+IF(OR(2=Inputs!$B$11,2=Inputs!$B$13,2=Inputs!$B$15,2=Inputs!$B$17),Inputs!$B$94,0) | D64: =Inputs!$B$93/12+IF(OR(3=Inputs!$B$11,3=Inputs!$B$13,3=Inputs!$B$15,3=Inputs!$B$17),Inputs!$B$94,0) | E64: =Inputs!$B$93/12+IF(OR(4=Inputs!$B$11,4=Inputs!$B$13,4=Inputs!$B$15,4=Inputs!$B$17),Inputs!$B$94,0) | F64: =Inputs!$B$93/12+IF(OR(5=Inputs!$B$11,5=Inputs!$B$13,5=Inputs!$B$15,5=Inputs!$B$17),Inputs!$B$94,0) | G64: =Inputs!$B$93/12+IF(OR(6=Inputs!$B$11,6=Inputs!$B$13,6=Inputs!$B$15,6=Inputs!$B$17),Inputs!$B$94,0) | H64: =Inputs!$B$93/12+IF(OR(7=Inputs!$B$11,7=Inputs!$B$13,7=Inputs!$B$15,7=Inputs!$B$17),Inputs!$B$94,0) | I64: =Inputs!$B$93/12+IF(OR(8=Inputs!$B$11,8=Inputs!$B$13,8=Inputs!$B$15,8=Inputs!$B$17),Inputs!$B$94,0) | J64: =Inputs!$B$93/12+IF(OR(9=Inputs!$B$11,9=Inputs!$B$13,9=Inputs!$B$15,9=Inputs!$B$17),Inputs!$B$94,0) | K64: =Inputs!$B$93/12+IF(OR(10=Inputs!$B$11,10=Inputs!$B$13,10=Inputs!$B$15,10=Inputs!$B$17),Inputs!$B$94,0) | L64: =Inputs!$B$93/12+IF(OR(11=Inputs!$B$11,11=Inputs!$B$13,11=Inputs!$B$15,11=Inputs!$B$17),Inputs!$B$94,0) | M64: =Inputs!$B$93/12+IF(OR(12=Inputs!$B$11,12=Inputs!$B$13,12=Inputs!$B$15,12=Inputs!$B$17),Inputs!$B$94,0) | N64: =Inputs!$B$93/12+IF(OR(13=Inputs!$B$11,13=Inputs!$B$13,13=Inputs!$B$15,13=Inputs!$B$17),Inputs!$B$94,0) | O64: =Inputs!$B$93/12+IF(OR(14=Inputs!$B$11,14=Inputs!$B$13,14=Inputs!$B$15,14=Inputs!$B$17),Inputs!$B$94,0) | P64: =Inputs!$B$93/12+IF(OR(15=Inputs!$B$11,15=Inputs!$B$13,15=Inputs!$B$15,15=Inputs!$B$17),Inputs!$B$94,0) | Q64: =Inputs!$B$93/12+IF(OR(16=Inputs!$B$11,16=Inputs!$B$13,16=Inputs!$B$15,16=Inputs!$B$17),Inputs!$B$94,0) | R64: =Inputs!$B$93/12+IF(OR(17=Inputs!$B$11,17=Inputs!$B$13,17=Inputs!$B$15,17=Inputs!$B$17),Inputs!$B$94,0) | S64: =Inputs!$B$93/12+IF(OR(18=Inputs!$B$11,18=Inputs!$B$13,18=Inputs!$B$15,18=Inputs!$B$17),Inputs!$B$94,0) | T64: =Inputs!$B$93/12+IF(OR(19=Inputs!$B$11,19=Inputs!$B$13,19=Inputs!$B$15,19=Inputs!$B$17),Inputs!$B$94,0) | U64: =Inputs!$B$93/12+IF(OR(20=Inputs!$B$11,20=Inputs!$B$13,20=Inputs!$B$15,20=Inputs!$B$17),Inputs!$B$94,0) | V64: =Inputs!$B$93/12+IF(OR(21=Inputs!$B$11,21=Inputs!$B$13,21=Inputs!$B$15,21=Inputs!$B$17),Inputs!$B$94,0) | W64: =Inputs!$B$93/12+IF(OR(22=Inputs!$B$11,22=Inputs!$B$13,22=Inputs!$B$15,22=Inputs!$B$17),Inputs!$B$94,0) | X64: =Inputs!$B$93/12+IF(OR(23=Inputs!$B$11,23=Inputs!$B$13,23=Inputs!$B$15,23=Inputs!$B$17),Inputs!$B$94,0) | Y64: =Inputs!$B$93/12+IF(OR(24=Inputs!$B$11,24=Inputs!$B$13,24=Inputs!$B$15,24=Inputs!$B$17),Inputs!$B$94,0) | Z64: =Inputs!$B$93/12+IF(OR(25=Inputs!$B$11,25=Inputs!$B$13,25=Inputs!$B$15,25=Inputs!$B$17),Inputs!$B$94,0) | AA64: =Inputs!$B$93/12+IF(OR(26=Inputs!$B$11,26=Inputs!$B$13,26=Inputs!$B$15,26=Inputs!$B$17),Inputs!$B$94,0) | AB64: =Inputs!$B$93/12+IF(OR(27=Inputs!$B$11,27=Inputs!$B$13,27=Inputs!$B$15,27=Inputs!$B$17),Inputs!$B$94,0) | AC64: =Inputs!$B$93/12+IF(OR(28=Inputs!$B$11,28=Inputs!$B$13,28=Inputs!$B$15,28=Inputs!$B$17),Inputs!$B$94,0) | AD64: =Inputs!$B$93/12+IF(OR(29=Inputs!$B$11,29=Inputs!$B$13,29=Inputs!$B$15,29=Inputs!$B$17),Inputs!$B$94,0) | AE64: =Inputs!$B$93/12+IF(OR(30=Inputs!$B$11,30=Inputs!$B$13,30=Inputs!$B$15,30=Inputs!$B$17),Inputs!$B$94,0) | AF64: =Inputs!$B$93/12+IF(OR(31=Inputs!$B$11,31=Inputs!$B$13,31=Inputs!$B$15,31=Inputs!$B$17),Inputs!$B$94,0) | AG64: =Inputs!$B$93/12+IF(OR(32=Inputs!$B$11,32=Inputs!$B$13,32=Inputs!$B$15,32=Inputs!$B$17),Inputs!$B$94,0) | AH64: =Inputs!$B$93/12+IF(OR(33=Inputs!$B$11,33=Inputs!$B$13,33=Inputs!$B$15,33=Inputs!$B$17),Inputs!$B$94,0) | AI64: =Inputs!$B$93/12+IF(OR(34=Inputs!$B$11,34=Inputs!$B$13,34=Inputs!$B$15,34=Inputs!$B$17),Inputs!$B$94,0) | AJ64: =Inputs!$B$93/12+IF(OR(35=Inputs!$B$11,35=Inputs!$B$13,35=Inputs!$B$15,35=Inputs!$B$17),Inputs!$B$94,0) | AK64: =Inputs!$B$93/12+IF(OR(36=Inputs!$B$11,36=Inputs!$B$13,36=Inputs!$B$15,36=Inputs!$B$17),Inputs!$B$94,0) | AL64: =Inputs!$B$93/12+IF(OR(37=Inputs!$B$11,37=Inputs!$B$13,37=Inputs!$B$15,37=Inputs!$B$17),Inputs!$B$94,0) | AM64: =Inputs!$B$93/12+IF(OR(38=Inputs!$B$11,38=Inputs!$B$13,38=Inputs!$B$15,38=Inputs!$B$17),Inputs!$B$94,0) | AN64: =Inputs!$B$93/12+IF(OR(39=Inputs!$B$11,39=Inputs!$B$13,39=Inputs!$B$15,39=Inputs!$B$17),Inputs!$B$94,0) | AO64: =Inputs!$B$93/12+IF(OR(40=Inputs!$B$11,40=Inputs!$B$13,40=Inputs!$B$15,40=Inputs!$B$17),Inputs!$B$94,0) | AP64: =Inputs!$B$93/12+IF(OR(41=Inputs!$B$11,41=Inputs!$B$13,41=Inputs!$B$15,41=Inputs!$B$17),Inputs!$B$94,0) | AQ64: =Inputs!$B$93/12+IF(OR(42=Inputs!$B$11,42=Inputs!$B$13,42=Inputs!$B$15,42=Inputs!$B$17),Inputs!$B$94,0) | AR64: =Inputs!$B$93/12+IF(OR(43=Inputs!$B$11,43=Inputs!$B$13,43=Inputs!$B$15,43=Inputs!$B$17),Inputs!$B$94,0) | AS64: =Inputs!$B$93/12+IF(OR(44=Inputs!$B$11,44=Inputs!$B$13,44=Inputs!$B$15,44=Inputs!$B$17),Inputs!$B$94,0) | AT64: =Inputs!$B$93/12+IF(OR(45=Inputs!$B$11,45=Inputs!$B$13,45=Inputs!$B$15,45=Inputs!$B$17),Inputs!$B$94,0) | AU64: =Inputs!$B$93/12+IF(OR(46=Inputs!$B$11,46=Inputs!$B$13,46=Inputs!$B$15,46=Inputs!$B$17),Inputs!$B$94,0) | AV64: =Inputs!$B$93/12+IF(OR(47=Inputs!$B$11,47=Inputs!$B$13,47=Inputs!$B$15,47=Inputs!$B$17),Inputs!$B$94,0) | AW64: =Inputs!$B$93/12+IF(OR(48=Inputs!$B$11,48=Inputs!$B$13,48=Inputs!$B$15,48=Inputs!$B$17),Inputs!$B$94,0) | AX64: =Inputs!$B$93/12+IF(OR(49=Inputs!$B$11,49=Inputs!$B$13,49=Inputs!$B$15,49=Inputs!$B$17),Inputs!$B$94,0) | AY64: =Inputs!$B$93/12+IF(OR(50=Inputs!$B$11,50=Inputs!$B$13,50=Inputs!$B$15,50=Inputs!$B$17),Inputs!$B$94,0) | AZ64: =Inputs!$B$93/12+IF(OR(51=Inputs!$B$11,51=Inputs!$B$13,51=Inputs!$B$15,51=Inputs!$B$17),Inputs!$B$94,0) | BA64: =Inputs!$B$93/12+IF(OR(52=Inputs!$B$11,52=Inputs!$B$13,52=Inputs!$B$15,52=Inputs!$B$17),Inputs!$B$94,0)
A65: Steuerberater | B65: =Inputs!$B$95 | C65: =Inputs!$B$95 | D65: =Inputs!$B$95 | E65: =Inputs!$B$95 | F65: =Inputs!$B$95 | G65: =Inputs!$B$95 | H65: =Inputs!$B$95 | I65: =Inputs!$B$95 | ... BA65: =Inputs!$B$95
A66: Wirtschaftsprüfer | B66: =IF(1>=Inputs!$B$97,Inputs!$B$96/12,0) | C66: =IF(2>=Inputs!$B$97,Inputs!$B$96/12,0) | D66: =IF(3>=Inputs!$B$97,Inputs!$B$96/12,0) | E66: =IF(4>=Inputs!$B$97,Inputs!$B$96/12,0) | F66: =IF(5>=Inputs!$B$97,Inputs!$B$96/12,0) | G66: =IF(6>=Inputs!$B$97,Inputs!$B$96/12,0) | H66: =IF(7>=Inputs!$B$97,Inputs!$B$96/12,0) | I66: =IF(8>=Inputs!$B$97,Inputs!$B$96/12,0) | J66: =IF(9>=Inputs!$B$97,Inputs!$B$96/12,0) | K66: =IF(10>=Inputs!$B$97,Inputs!$B$96/12,0) | L66: =IF(11>=Inputs!$B$97,Inputs!$B$96/12,0) | M66: =IF(12>=Inputs!$B$97,Inputs!$B$96/12,0) | N66: =IF(13>=Inputs!$B$97,Inputs!$B$96/12,0) | O66: =IF(14>=Inputs!$B$97,Inputs!$B$96/12,0) | P66: =IF(15>=Inputs!$B$97,Inputs!$B$96/12,0) | Q66: =IF(16>=Inputs!$B$97,Inputs!$B$96/12,0) | R66: =IF(17>=Inputs!$B$97,Inputs!$B$96/12,0) | S66: =IF(18>=Inputs!$B$97,Inputs!$B$96/12,0) | T66: =IF(19>=Inputs!$B$97,Inputs!$B$96/12,0) | U66: =IF(20>=Inputs!$B$97,Inputs!$B$96/12,0) | V66: =IF(21>=Inputs!$B$97,Inputs!$B$96/12,0) | W66: =IF(22>=Inputs!$B$97,Inputs!$B$96/12,0) | X66: =IF(23>=Inputs!$B$97,Inputs!$B$96/12,0) | Y66: =IF(24>=Inputs!$B$97,Inputs!$B$96/12,0) | Z66: =IF(25>=Inputs!$B$97,Inputs!$B$96/12,0) | AA66: =IF(26>=Inputs!$B$97,Inputs!$B$96/12,0) | AB66: =IF(27>=Inputs!$B$97,Inputs!$B$96/12,0) | AC66: =IF(28>=Inputs!$B$97,Inputs!$B$96/12,0) | AD66: =IF(29>=Inputs!$B$97,Inputs!$B$96/12,0) | AE66: =IF(30>=Inputs!$B$97,Inputs!$B$96/12,0) | AF66: =IF(31>=Inputs!$B$97,Inputs!$B$96/12,0) | AG66: =IF(32>=Inputs!$B$97,Inputs!$B$96/12,0) | AH66: =IF(33>=Inputs!$B$97,Inputs!$B$96/12,0) | AI66: =IF(34>=Inputs!$B$97,Inputs!$B$96/12,0) | AJ66: =IF(35>=Inputs!$B$97,Inputs!$B$96/12,0) | AK66: =IF(36>=Inputs!$B$97,Inputs!$B$96/12,0) | AL66: =IF(37>=Inputs!$B$97,Inputs!$B$96/12,0) | AM66: =IF(38>=Inputs!$B$97,Inputs!$B$96/12,0) | AN66: =IF(39>=Inputs!$B$97,Inputs!$B$96/12,0) | AO66: =IF(40>=Inputs!$B$97,Inputs!$B$96/12,0) | AP66: =IF(41>=Inputs!$B$97,Inputs!$B$96/12,0) | AQ66: =IF(42>=Inputs!$B$97,Inputs!$B$96/12,0) | AR66: =IF(43>=Inputs!$B$97,Inputs!$B$96/12,0) | AS66: =IF(44>=Inputs!$B$97,Inputs!$B$96/12,0) | AT66: =IF(45>=Inputs!$B$97,Inputs!$B$96/12,0) | AU66: =IF(46>=Inputs!$B$97,Inputs!$B$96/12,0) | AV66: =IF(47>=Inputs!$B$97,Inputs!$B$96/12,0) | AW66: =IF(48>=Inputs!$B$97,Inputs!$B$96/12,0) | AX66: =IF(49>=Inputs!$B$97,Inputs!$B$96/12,0) | AY66: =IF(50>=Inputs!$B$97,Inputs!$B$96/12,0) | AZ66: =IF(51>=Inputs!$B$97,Inputs!$B$96/12,0) | BA66: =IF(52>=Inputs!$B$97,Inputs!$B$96/12,0)
A67: Unternehmensberater | B67: =Inputs!$B$98/12 | C67: =Inputs!$B$98/12 | D67: =Inputs!$B$98/12 | E67: =Inputs!$B$98/12 | F67: =Inputs!$B$98/12 | G67: =Inputs!$B$98/12 | H67: =Inputs!$B$98/12 | I67: =Inputs!$B$98/12 | ... BA67: =Inputs!$B$98/12
A68: TOTAL PROFESSIONAL | B68: =SUM(B64:B67) | C68: =SUM(C64:C67) | D68: =SUM(D64:D67) | E68: =SUM(E64:E67) | F68: =SUM(F64:F67) | G68: =SUM(G64:G67) | H68: =SUM(H64:H67) | I68: =SUM(I64:I67) | ... BA68: =SUM(BA64:BA67)
A70: VERSICHERUNGEN & BANK
A71: D&O Versicherung | B71: =Inputs!$B$101/12 | C71: =Inputs!$B$101/12 | D71: =Inputs!$B$101/12 | E71: =Inputs!$B$101/12 | F71: =Inputs!$B$101/12 | G71: =Inputs!$B$101/12 | H71: =Inputs!$B$101/12 | I71: =Inputs!$B$101/12 | ... BA71: =Inputs!$B$101/12
A72: Betriebshaftpflicht | B72: =Inputs!$B$102/12 | C72: =Inputs!$B$102/12 | D72: =Inputs!$B$102/12 | E72: =Inputs!$B$102/12 | F72: =Inputs!$B$102/12 | G72: =Inputs!$B$102/12 | H72: =Inputs!$B$102/12 | I72: =Inputs!$B$102/12 | ... BA72: =Inputs!$B$102/12
A73: Cyber-Versicherung | B73: =Inputs!$B$103/12 | C73: =Inputs!$B$103/12 | D73: =Inputs!$B$103/12 | E73: =Inputs!$B$103/12 | F73: =Inputs!$B$103/12 | G73: =Inputs!$B$103/12 | H73: =Inputs!$B$103/12 | I73: =Inputs!$B$103/12 | ... BA73: =Inputs!$B$103/12
A74: Bankgebühren | B74: =Inputs!$B$104 | C74: =Inputs!$B$104 | D74: =Inputs!$B$104 | E74: =Inputs!$B$104 | F74: =Inputs!$B$104 | G74: =Inputs!$B$104 | H74: =Inputs!$B$104 | I74: =Inputs!$B$104 | ... BA74: =Inputs!$B$104
A75: TOTAL VERSICHERUNG & BANK | B75: =SUM(B71:B74) | C75: =SUM(C71:C74) | D75: =SUM(D71:D74) | E75: =SUM(E71:E74) | F75: =SUM(F71:F74) | G75: =SUM(G71:G74) | H75: =SUM(H71:H74) | I75: =SUM(I71:I74) | ... BA75: =SUM(BA71:BA74)
A77: MARKETING & SALES KOSTEN
A78: Paid Advertising | B78: =Inputs!$B$108*(1+Inputs!$B$109)^(1-1) | C78: =Inputs!$B$108*(1+Inputs!$B$109)^(2-1) | D78: =Inputs!$B$108*(1+Inputs!$B$109)^(3-1) | E78: =Inputs!$B$108*(1+Inputs!$B$109)^(4-1) | F78: =Inputs!$B$108*(1+Inputs!$B$109)^(5-1) | G78: =Inputs!$B$108*(1+Inputs!$B$109)^(6-1) | H78: =Inputs!$B$108*(1+Inputs!$B$109)^(7-1) | I78: =Inputs!$B$108*(1+Inputs!$B$109)^(8-1) | J78: =Inputs!$B$108*(1+Inputs!$B$109)^(9-1) | K78: =Inputs!$B$108*(1+Inputs!$B$109)^(10-1) | L78: =Inputs!$B$108*(1+Inputs!$B$109)^(11-1) | M78: =Inputs!$B$108*(1+Inputs!$B$109)^(12-1) | N78: =Inputs!$B$108*(1+Inputs!$B$109)^(13-1) | O78: =Inputs!$B$108*(1+Inputs!$B$109)^(14-1) | P78: =Inputs!$B$108*(1+Inputs!$B$109)^(15-1) | Q78: =Inputs!$B$108*(1+Inputs!$B$109)^(16-1) | R78: =Inputs!$B$108*(1+Inputs!$B$109)^(17-1) | S78: =Inputs!$B$108*(1+Inputs!$B$109)^(18-1) | T78: =Inputs!$B$108*(1+Inputs!$B$109)^(19-1) | U78: =Inputs!$B$108*(1+Inputs!$B$109)^(20-1) | V78: =Inputs!$B$108*(1+Inputs!$B$109)^(21-1) | W78: =Inputs!$B$108*(1+Inputs!$B$109)^(22-1) | X78: =Inputs!$B$108*(1+Inputs!$B$109)^(23-1) | Y78: =Inputs!$B$108*(1+Inputs!$B$109)^(24-1) | Z78: =Inputs!$B$108*(1+Inputs!$B$109)^(25-1) | AA78: =Inputs!$B$108*(1+Inputs!$B$109)^(26-1) | AB78: =Inputs!$B$108*(1+Inputs!$B$109)^(27-1) | AC78: =Inputs!$B$108*(1+Inputs!$B$109)^(28-1) | AD78: =Inputs!$B$108*(1+Inputs!$B$109)^(29-1) | AE78: =Inputs!$B$108*(1+Inputs!$B$109)^(30-1) | AF78: =Inputs!$B$108*(1+Inputs!$B$109)^(31-1) | AG78: =Inputs!$B$108*(1+Inputs!$B$109)^(32-1) | AH78: =Inputs!$B$108*(1+Inputs!$B$109)^(33-1) | AI78: =Inputs!$B$108*(1+Inputs!$B$109)^(34-1) | AJ78: =Inputs!$B$108*(1+Inputs!$B$109)^(35-1) | AK78: =Inputs!$B$108*(1+Inputs!$B$109)^(36-1) | AL78: =Inputs!$B$108*(1+Inputs!$B$109)^(37-1) | AM78: =Inputs!$B$108*(1+Inputs!$B$109)^(38-1) | AN78: =Inputs!$B$108*(1+Inputs!$B$109)^(39-1) | AO78: =Inputs!$B$108*(1+Inputs!$B$109)^(40-1) | AP78: =Inputs!$B$108*(1+Inputs!$B$109)^(41-1) | AQ78: =Inputs!$B$108*(1+Inputs!$B$109)^(42-1) | AR78: =Inputs!$B$108*(1+Inputs!$B$109)^(43-1) | AS78: =Inputs!$B$108*(1+Inputs!$B$109)^(44-1) | AT78: =Inputs!$B$108*(1+Inputs!$B$109)^(45-1) | AU78: =Inputs!$B$108*(1+Inputs!$B$109)^(46-1) | AV78: =Inputs!$B$108*(1+Inputs!$B$109)^(47-1) | AW78: =Inputs!$B$108*(1+Inputs!$B$109)^(48-1) | AX78: =Inputs!$B$108*(1+Inputs!$B$109)^(49-1) | AY78: =Inputs!$B$108*(1+Inputs!$B$109)^(50-1) | AZ78: =Inputs!$B$108*(1+Inputs!$B$109)^(51-1) | BA78: =Inputs!$B$108*(1+Inputs!$B$109)^(52-1)
A79: Content & SEO | B79: =Inputs!$B$110 | C79: =Inputs!$B$110 | D79: =Inputs!$B$110 | E79: =Inputs!$B$110 | F79: =Inputs!$B$110 | G79: =Inputs!$B$110 | H79: =Inputs!$B$110 | I79: =Inputs!$B$110 | ... BA79: =Inputs!$B$110
A80: Events & Messen | B80: =Inputs!$B$115/12 | C80: =Inputs!$B$115/12 | D80: =Inputs!$B$115/12 | E80: =Inputs!$B$115/12 | F80: =Inputs!$B$115/12 | G80: =Inputs!$B$115/12 | H80: =Inputs!$B$115/12 | I80: =Inputs!$B$115/12 | ... BA80: =Inputs!$B$115/12
A81: Sales Tools | B81: =Inputs!$B$116 | C81: =Inputs!$B$116 | D81: =Inputs!$B$116 | E81: =Inputs!$B$116 | F81: =Inputs!$B$116 | G81: =Inputs!$B$116 | H81: =Inputs!$B$116 | I81: =Inputs!$B$116 | ... BA81: =Inputs!$B$116
A82: Sales Provisionen | B82: =Revenue!B24/12*Inputs!$B$117 | C82: =Revenue!C24/12*Inputs!$B$117 | D82: =Revenue!D24/12*Inputs!$B$117 | E82: =Revenue!E24/12*Inputs!$B$117 | F82: =Revenue!F24/12*Inputs!$B$117 | G82: =Revenue!G24/12*Inputs!$B$117 | H82: =Revenue!H24/12*Inputs!$B$117 | I82: =Revenue!I24/12*Inputs!$B$117 | ... BA82: =Revenue!BA24/12*Inputs!$B$117
A83: Reisekosten Sales | B83: =(B13+B14+B15)*Inputs!$B$118 | C83: =(C13+C14+C15)*Inputs!$B$118 | D83: =(D13+D14+D15)*Inputs!$B$118 | E83: =(E13+E14+E15)*Inputs!$B$118 | F83: =(F13+F14+F15)*Inputs!$B$118 | G83: =(G13+G14+G15)*Inputs!$B$118 | H83: =(H13+H14+H15)*Inputs!$B$118 | I83: =(I13+I14+I15)*Inputs!$B$118 | ... BA83: =(BA13+BA14+BA15)*Inputs!$B$118
A84: TOTAL MARKETING & SALES | B84: =SUM(B78:B83) | C84: =SUM(C78:C83) | D84: =SUM(D78:D83) | E84: =SUM(E78:E83) | F84: =SUM(F78:F83) | G84: =SUM(G78:G83) | H84: =SUM(H78:H83) | I84: =SUM(I78:I83) | ... BA84: =SUM(BA78:BA83)
A86: SONSTIGE KOSTEN
A87: Reisekosten allgemein | B87: =B22*Inputs!$B$121/12 | C87: =C22*Inputs!$B$121/12 | D87: =D22*Inputs!$B$121/12 | E87: =E22*Inputs!$B$121/12 | F87: =F22*Inputs!$B$121/12 | G87: =G22*Inputs!$B$121/12 | H87: =H22*Inputs!$B$121/12 | I87: =I22*Inputs!$B$121/12 | ... BA87: =BA22*Inputs!$B$121/12
A88: Weiterbildung | B88: =B22*Inputs!$B$122/12 | C88: =C22*Inputs!$B$122/12 | D88: =D22*Inputs!$B$122/12 | E88: =E22*Inputs!$B$122/12 | F88: =F22*Inputs!$B$122/12 | G88: =G22*Inputs!$B$122/12 | H88: =H22*Inputs!$B$122/12 | I88: =I22*Inputs!$B$122/12 | ... BA88: =BA22*Inputs!$B$122/12
A89: Team Events | B89: =B22*Inputs!$B$123/12 | C89: =C22*Inputs!$B$123/12 | D89: =D22*Inputs!$B$123/12 | E89: =E22*Inputs!$B$123/12 | F89: =F22*Inputs!$B$123/12 | G89: =G22*Inputs!$B$123/12 | H89: =H22*Inputs!$B$123/12 | I89: =I22*Inputs!$B$123/12 | ... BA89: =BA22*Inputs!$B$123/12
A90: Hardware (neue MA) | B90: =B22*(Inputs!$B$78+Inputs!$B$79) | C90: =MAX(0,C22-B22)*(Inputs!$B$78+Inputs!$B$79) | D90: =MAX(0,D22-C22)*(Inputs!$B$78+Inputs!$B$79) | E90: =MAX(0,E22-D22)*(Inputs!$B$78+Inputs!$B$79) | F90: =MAX(0,F22-E22)*(Inputs!$B$78+Inputs!$B$79) | G90: =MAX(0,G22-F22)*(Inputs!$B$78+Inputs!$B$79) | H90: =MAX(0,H22-G22)*(Inputs!$B$78+Inputs!$B$79) | I90: =MAX(0,I22-H22)*(Inputs!$B$78+Inputs!$B$79) | J90: =MAX(0,J22-I22)*(Inputs!$B$78+Inputs!$B$79) | ... BA90: =MAX(0,BA22-AZ22)*(Inputs!$B$78+Inputs!$B$79)
A91: Sonstige IT-Ausstattung | B91: =Inputs!$B$81/12 | C91: =Inputs!$B$81/12 | D91: =Inputs!$B$81/12 | E91: =Inputs!$B$81/12 | F91: =Inputs!$B$81/12 | G91: =Inputs!$B$81/12 | H91: =Inputs!$B$81/12 | I91: =Inputs!$B$81/12 | ... BA91: =Inputs!$B$81/12
A92: TOTAL SONSTIGE | B92: =SUM(B87:B91) | C92: =SUM(C87:C91) | D92: =SUM(D87:D91) | E92: =SUM(E87:E91) | F92: =SUM(F87:F91) | G92: =SUM(G87:G91) | H92: =SUM(H87:H91) | I92: =SUM(I87:I91) | ... BA92: =SUM(BA87:BA91)
A94: PAYMENT PROCESSING
A95: Payment Processing Fees | B95: =Revenue!B21*Inputs!$B$105 | C95: =Revenue!C21*Inputs!$B$105 | D95: =Revenue!D21*Inputs!$B$105 | E95: =Revenue!E21*Inputs!$B$105 | F95: =Revenue!F21*Inputs!$B$105 | G95: =Revenue!G21*Inputs!$B$105 | H95: =Revenue!H21*Inputs!$B$105 | I95: =Revenue!I21*Inputs!$B$105 | ... BA95: =Revenue!BA21*Inputs!$B$105
A97: Puffer/Unvorhergesehenes | B97: =(B45+B54+B61+B68+B75+B84+B92)*Inputs!$B$124 | C97: =(C45+C54+C61+C68+C75+C84+C92)*Inputs!$B$124 | D97: =(D45+D54+D61+D68+D75+D84+D92)*Inputs!$B$124 | E97: =(E45+E54+E61+E68+E75+E84+E92)*Inputs!$B$124 | F97: =(F45+F54+F61+F68+F75+F84+F92)*Inputs!$B$124 | G97: =(G45+G54+G61+G68+G75+G84+G92)*Inputs!$B$124 | H97: =(H45+H54+H61+H68+H75+H84+H92)*Inputs!$B$124 | I97: =(I45+I54+I61+I68+I75+I84+I92)*Inputs!$B$124 | ... BA97: =(BA45+BA54+BA61+BA68+BA75+BA84+BA92)*Inputs!$B$124
A99: TOTAL KOSTEN (exkl. COGS) | B99: =B45+B54+B61+B68+B75+B84+B92+B97 | C99: =C45+C54+C61+C68+C75+C84+C92+C97 | D99: =D45+D54+D61+D68+D75+D84+D92+D97 | E99: =E45+E54+E61+E68+E75+E84+E92+E97 | F99: =F45+F54+F61+F68+F75+F84+F92+F97 | G99: =G45+G54+G61+G68+G75+G84+G92+G97 | H99: =H45+H54+H61+H68+H75+H84+H92+H97 | I99: =I45+I54+I61+I68+I75+I84+I92+I97 | ... BA99: =BA45+BA54+BA61+BA68+BA75+BA84+BA92+BA97

Sheet Balance Sheet
A1: BILANZ (Vereinfacht)
B2: 46113 | C2: 46143 | D2: 46174 | E2: 46204 | F2: 46235 | G2: 46266 | H2: 46296 | I2: 46327 | J2: 46357 | K2: 46388 | L2: 46419 | M2: 46447 | N2: 46478 | O2: 46508 | P2: 46539 | Q2: 46569 | R2: 46600 | S2: 46631 | T2: 46661 | U2: 46692 | V2: 46722 | W2: 46753 | X2: 46784 | Y2: 46813 | Z2: 46844 | AA2: 46874 | AB2: 46905 | AC2: 46935 | AD2: 46966 | AE2: 46997 | AF2: 47027 | AG2: 47058 | AH2: 47088 | AI2: 47119 | AJ2: 47150 | AK2: 47178 | AL2: 47209 | AM2: 47239 | AN2: 47270 | AO2: 47300 | AP2: 47331 | AQ2: 47362 | AR2: 47392 | AS2: 47423 | AT2: 47453 | AU2: 47484 | AV2: 47515 | AW2: 47543 | AX2: 47574 | AY2: 47604 | AZ2: 47635 | BA2: 47665
A3: Startup-Phase | B3: Ideation | C3: Ideation | D3: Ideation | E3: Ideation | F3: Pre-Seed | G3: Pre-Seed | H3: Pre-Seed | I3: Pre-Seed | J3: Pre-Seed | K3: Pre-Seed | L3: Pre-Seed | M3: Pre-Seed | N3: Pre-Seed | O3: Pre-Seed | P3: Pre-Seed | Q3: Pre-Seed | R3: Seed | S3: Seed | T3: Seed | U3: Seed | V3: Seed | W3: Seed | X3: Seed | Y3: Seed | Z3: Seed | AA3: Seed | AB3: Seed | AC3: Seed | AD3: Series A | AE3: Series A | AF3: Series A | AG3: Series A | AH3: Series A | AI3: Series A | AJ3: Series A | AK3: Series A | AL3: Series A | AM3: Series A | AN3: Series A | AO3: Series A | AP3: Series B | AQ3: Series B | AR3: Series B | AS3: Series B | AT3: Series B | AU3: Series B | AV3: Series B | AW3: Series B | AX3: Series B | AY3: Series B | AZ3: Series B | BA3: Series B
A4: Position | B4: M1 | C4: M2 | D4: M3 | E4: M4 | F4: M5 | G4: M6 | H4: M7 | I4: M8 | J4: M9 | K4: M10 | L4: M11 | M4: M12 | N4: M13 | O4: M14 | P4: M15 | Q4: M16 | R4: M17 | S4: M18 | T4: M19 | U4: M20 | V4: M21 | W4: M22 | X4: M23 | Y4: M24 | Z4: M25 | AA4: M26 | AB4: M27 | AC4: M28 | AD4: M29 | AE4: M30 | AF4: M31 | AG4: M32 | AH4: M33 | AI4: M34 | AJ4: M35 | AK4: M36 | AL4: M37 | AM4: M38 | AN4: M39 | AO4: M40 | AP4: M41 | AQ4: M42 | AR4: M43 | AS4: M44 | AT4: M45 | AU4: M46 | AV4: M47 | AW4: M48 | AX4: M49 | AY4: M50 | AZ4: M51 | BA4: M52
A5: AKTIVA (ASSETS)
A6: Cash & Cash Equivalents | B6: ='Cash Flow'!B23 | C6: ='Cash Flow'!C23 | D6: ='Cash Flow'!D23 | E6: ='Cash Flow'!E23 | F6: ='Cash Flow'!F23 | G6: ='Cash Flow'!G23 | H6: ='Cash Flow'!H23 | I6: ='Cash Flow'!I23 | ... BA6: ='Cash Flow'!BA23
A7: Accounts Receivable | B7: ='P&L'!B8 | C7: ='P&L'!C8 | D7: ='P&L'!D8 | E7: ='P&L'!E8 | F7: ='P&L'!F8 | G7: ='P&L'!G8 | H7: ='P&L'!H8 | I7: ='P&L'!I8 | ... BA7: ='P&L'!BA8
A8: Prepaid Expenses | B8: 0 | C8: 0 | D8: 0 | E8: 0 | F8: 0 | G8: 0 | H8: 0 | I8: 0 | J8: 0 | K8: 0 | L8: 0 | M8: 0 | N8: 0 | O8: 0 | P8: 0 | Q8: 0 | R8: 0 | S8: 0 | T8: 0 | U8: 0 | V8: 0 | W8: 0 | X8: 0 | Y8: 0 | Z8: 0 | AA8: 0 | AB8: 0 | AC8: 0 | AD8: 0 | AE8: 0 | AF8: 0 | AG8: 0 | AH8: 0 | AI8: 0 | AJ8: 0 | AK8: 0 | AL8: 0 | AM8: 0 | AN8: 0 | AO8: 0 | AP8: 0 | AQ8: 0 | AR8: 0 | AS8: 0 | AT8: 0 | AU8: 0 | AV8: 0 | AW8: 0 | AX8: 0 | AY8: 0 | AZ8: 0 | BA8: 0
A9: Property & Equipment (net) | B9: =Costs!B90+Inputs!$B$89 | C9: =B9+Costs!C90-'P&L'!C32 | D9: =C9+Costs!D90-'P&L'!D32 | E9: =D9+Costs!E90-'P&L'!E32 | F9: =E9+Costs!F90-'P&L'!F32 | G9: =F9+Costs!G90-'P&L'!G32 | H9: =G9+Costs!H90-'P&L'!H32 | I9: =H9+Costs!I90-'P&L'!I32 | J9: =I9+Costs!J90-'P&L'!J32 | ... BA9: =AZ9+Costs!BA90-'P&L'!BA32
A10: TOTAL ASSETS | B10: =SUM(B6:B9) | C10: =SUM(C6:C9) | D10: =SUM(D6:D9) | E10: =SUM(E6:E9) | F10: =SUM(F6:F9) | G10: =SUM(G6:G9) | H10: =SUM(H6:H9) | I10: =SUM(I6:I9) | ... BA10: =SUM(BA6:BA9)
A12: PASSIVA (LIABILITIES)
A13: Accounts Payable | B13: =Costs!B99*0.1 | C13: =Costs!C99*0.1 | D13: =Costs!D99*0.1 | E13: =Costs!E99*0.1 | F13: =Costs!F99*0.1 | G13: =Costs!G99*0.1 | H13: =Costs!H99*0.1 | I13: =Costs!I99*0.1 | ... BA13: =Costs!BA99*0.1
A14: Accrued Expenses | B14: =Costs!B45*0.08 | C14: =Costs!C45*0.08 | D14: =Costs!D45*0.08 | E14: =Costs!E45*0.08 | F14: =Costs!F45*0.08 | G14: =Costs!G45*0.08 | H14: =Costs!H45*0.08 | I14: =Costs!I45*0.08 | ... BA14: =Costs!BA45*0.08
A15: Deferred Revenue | B15: ='P&L'!B5 | C15: ='P&L'!C5 | D15: ='P&L'!D5 | E15: ='P&L'!E5 | F15: ='P&L'!F5 | G15: ='P&L'!G5 | H15: ='P&L'!H5 | I15: ='P&L'!I5 | ... BA15: ='P&L'!BA5
A16: TOTAL LIABILITIES | B16: =SUM(B13:B15) | C16: =SUM(C13:C15) | D16: =SUM(D13:D15) | E16: =SUM(E13:E15) | F16: =SUM(F13:F15) | G16: =SUM(G13:G15) | H16: =SUM(H13:H15) | I16: =SUM(I13:I15) | ... BA16: =SUM(BA13:BA15)
A18: EIGENKAPITAL (EQUITY)
A19: Share Capital | B19: 25000 | C19: 25000 | D19: 25000 | E19: 25000 | F19: 25000 | G19: 25000 | H19: 25000 | I19: 25000 | J19: 25000 | K19: 25000 | L19: 25000 | M19: 25000 | N19: 25000 | O19: 25000 | P19: 25000 | Q19: 25000 | R19: 25000 | S19: 25000 | T19: 25000 | U19: 25000 | V19: 25000 | W19: 25000 | X19: 25000 | Y19: 25000 | Z19: 25000 | AA19: 25000 | AB19: 25000 | AC19: 25000 | AD19: 25000 | AE19: 25000 | AF19: 25000 | AG19: 25000 | AH19: 25000 | AI19: 25000 | AJ19: 25000 | AK19: 25000 | AL19: 25000 | AM19: 25000 | AN19: 25000 | AO19: 25000 | AP19: 25000 | AQ19: 25000 | AR19: 25000 | AS19: 25000 | AT19: 25000 | AU19: 25000 | AV19: 25000 | AW19: 25000 | AX19: 25000 | AY19: 25000 | AZ19: 25000 | BA19: 25000
A20: Additional Paid-in Capital | B20: =IF(1=Inputs!$B$11,Inputs!$B$10,0)+IF(1=Inputs!$B$13,Inputs!$B$12,0)+IF(1=Inputs!$B$15,Inputs!$B$14,0)+IF(1=Inputs!$B$17,Inputs!$B$16,0) | C20: =B20+IF(2=Inputs!$B$11,Inputs!$B$10,0)+IF(2=Inputs!$B$13,Inputs!$B$12,0)+IF(2=Inputs!$B$15,Inputs!$B$14,0)+IF(2=Inputs!$B$17,Inputs!$B$16,0) | D20: =C20+IF(3=Inputs!$B$11,Inputs!$B$10,0)+IF(3=Inputs!$B$13,Inputs!$B$12,0)+IF(3=Inputs!$B$15,Inputs!$B$14,0)+IF(3=Inputs!$B$17,Inputs!$B$16,0) | E20: =D20+IF(4=Inputs!$B$11,Inputs!$B$10,0)+IF(4=Inputs!$B$13,Inputs!$B$12,0)+IF(4=Inputs!$B$15,Inputs!$B$14,0)+IF(4=Inputs!$B$17,Inputs!$B$16,0) | F20: =E20+IF(5=Inputs!$B$11,Inputs!$B$10,0)+IF(5=Inputs!$B$13,Inputs!$B$12,0)+IF(5=Inputs!$B$15,Inputs!$B$14,0)+IF(5=Inputs!$B$17,Inputs!$B$16,0) | G20: =F20+IF(6=Inputs!$B$11,Inputs!$B$10,0)+IF(6=Inputs!$B$13,Inputs!$B$12,0)+IF(6=Inputs!$B$15,Inputs!$B$14,0)+IF(6=Inputs!$B$17,Inputs!$B$16,0) | H20: =G20+IF(7=Inputs!$B$11,Inputs!$B$10,0)+IF(7=Inputs!$B$13,Inputs!$B$12,0)+IF(7=Inputs!$B$15,Inputs!$B$14,0)+IF(7=Inputs!$B$17,Inputs!$B$16,0) | I20: =H20+IF(8=Inputs!$B$11,Inputs!$B$10,0)+IF(8=Inputs!$B$13,Inputs!$B$12,0)+IF(8=Inputs!$B$15,Inputs!$B$14,0)+IF(8=Inputs!$B$17,Inputs!$B$16,0) | J20: =I20+IF(9=Inputs!$B$11,Inputs!$B$10,0)+IF(9=Inputs!$B$13,Inputs!$B$12,0)+IF(9=Inputs!$B$15,Inputs!$B$14,0)+IF(9=Inputs!$B$17,Inputs!$B$16,0) | K20: =J20+IF(10=Inputs!$B$11,Inputs!$B$10,0)+IF(10=Inputs!$B$13,Inputs!$B$12,0)+IF(10=Inputs!$B$15,Inputs!$B$14,0)+IF(10=Inputs!$B$17,Inputs!$B$16,0) | L20: =K20+IF(11=Inputs!$B$11,Inputs!$B$10,0)+IF(11=Inputs!$B$13,Inputs!$B$12,0)+IF(11=Inputs!$B$15,Inputs!$B$14,0)+IF(11=Inputs!$B$17,Inputs!$B$16,0) | M20: =L20+IF(12=Inputs!$B$11,Inputs!$B$10,0)+IF(12=Inputs!$B$13,Inputs!$B$12,0)+IF(12=Inputs!$B$15,Inputs!$B$14,0)+IF(12=Inputs!$B$17,Inputs!$B$16,0) | N20: =M20+IF(13=Inputs!$B$11,Inputs!$B$10,0)+IF(13=Inputs!$B$13,Inputs!$B$12,0)+IF(13=Inputs!$B$15,Inputs!$B$14,0)+IF(13=Inputs!$B$17,Inputs!$B$16,0) | O20: =N20+IF(14=Inputs!$B$11,Inputs!$B$10,0)+IF(14=Inputs!$B$13,Inputs!$B$12,0)+IF(14=Inputs!$B$15,Inputs!$B$14,0)+IF(14=Inputs!$B$17,Inputs!$B$16,0) | P20: =O20+IF(15=Inputs!$B$11,Inputs!$B$10,0)+IF(15=Inputs!$B$13,Inputs!$B$12,0)+IF(15=Inputs!$B$15,Inputs!$B$14,0)+IF(15=Inputs!$B$17,Inputs!$B$16,0) | Q20: =P20+IF(16=Inputs!$B$11,Inputs!$B$10,0)+IF(16=Inputs!$B$13,Inputs!$B$12,0)+IF(16=Inputs!$B$15,Inputs!$B$14,0)+IF(16=Inputs!$B$17,Inputs!$B$16,0) | R20: =Q20+IF(17=Inputs!$B$11,Inputs!$B$10,0)+IF(17=Inputs!$B$13,Inputs!$B$12,0)+IF(17=Inputs!$B$15,Inputs!$B$14,0)+IF(17=Inputs!$B$17,Inputs!$B$16,0) | S20: =R20+IF(18=Inputs!$B$11,Inputs!$B$10,0)+IF(18=Inputs!$B$13,Inputs!$B$12,0)+IF(18=Inputs!$B$15,Inputs!$B$14,0)+IF(18=Inputs!$B$17,Inputs!$B$16,0) | T20: =S20+IF(19=Inputs!$B$11,Inputs!$B$10,0)+IF(19=Inputs!$B$13,Inputs!$B$12,0)+IF(19=Inputs!$B$15,Inputs!$B$14,0)+IF(19=Inputs!$B$17,Inputs!$B$16,0) | U20: =T20+IF(20=Inputs!$B$11,Inputs!$B$10,0)+IF(20=Inputs!$B$13,Inputs!$B$12,0)+IF(20=Inputs!$B$15,Inputs!$B$14,0)+IF(20=Inputs!$B$17,Inputs!$B$16,0) | V20: =U20+IF(21=Inputs!$B$11,Inputs!$B$10,0)+IF(21=Inputs!$B$13,Inputs!$B$12,0)+IF(21=Inputs!$B$15,Inputs!$B$14,0)+IF(21=Inputs!$B$17,Inputs!$B$16,0) | W20: =V20+IF(22=Inputs!$B$11,Inputs!$B$10,0)+IF(22=Inputs!$B$13,Inputs!$B$12,0)+IF(22=Inputs!$B$15,Inputs!$B$14,0)+IF(22=Inputs!$B$17,Inputs!$B$16,0) | X20: =W20+IF(23=Inputs!$B$11,Inputs!$B$10,0)+IF(23=Inputs!$B$13,Inputs!$B$12,0)+IF(23=Inputs!$B$15,Inputs!$B$14,0)+IF(23=Inputs!$B$17,Inputs!$B$16,0) | Y20: =X20+IF(24=Inputs!$B$11,Inputs!$B$10,0)+IF(24=Inputs!$B$13,Inputs!$B$12,0)+IF(24=Inputs!$B$15,Inputs!$B$14,0)+IF(24=Inputs!$B$17,Inputs!$B$16,0) | Z20: =Y20+IF(25=Inputs!$B$11,Inputs!$B$10,0)+IF(25=Inputs!$B$13,Inputs!$B$12,0)+IF(25=Inputs!$B$15,Inputs!$B$14,0)+IF(25=Inputs!$B$17,Inputs!$B$16,0) | AA20: =Z20+IF(26=Inputs!$B$11,Inputs!$B$10,0)+IF(26=Inputs!$B$13,Inputs!$B$12,0)+IF(26=Inputs!$B$15,Inputs!$B$14,0)+IF(26=Inputs!$B$17,Inputs!$B$16,0) | AB20: =AA20+IF(27=Inputs!$B$11,Inputs!$B$10,0)+IF(27=Inputs!$B$13,Inputs!$B$12,0)+IF(27=Inputs!$B$15,Inputs!$B$14,0)+IF(27=Inputs!$B$17,Inputs!$B$16,0) | AC20: =AB20+IF(28=Inputs!$B$11,Inputs!$B$10,0)+IF(28=Inputs!$B$13,Inputs!$B$12,0)+IF(28=Inputs!$B$15,Inputs!$B$14,0)+IF(28=Inputs!$B$17,Inputs!$B$16,0) | AD20: =AC20+IF(29=Inputs!$B$11,Inputs!$B$10,0)+IF(29=Inputs!$B$13,Inputs!$B$12,0)+IF(29=Inputs!$B$15,Inputs!$B$14,0)+IF(29=Inputs!$B$17,Inputs!$B$16,0) | AE20: =AD20+IF(30=Inputs!$B$11,Inputs!$B$10,0)+IF(30=Inputs!$B$13,Inputs!$B$12,0)+IF(30=Inputs!$B$15,Inputs!$B$14,0)+IF(30=Inputs!$B$17,Inputs!$B$16,0) | AF20: =AE20+IF(31=Inputs!$B$11,Inputs!$B$10,0)+IF(31=Inputs!$B$13,Inputs!$B$12,0)+IF(31=Inputs!$B$15,Inputs!$B$14,0)+IF(31=Inputs!$B$17,Inputs!$B$16,0) | AG20: =AF20+IF(32=Inputs!$B$11,Inputs!$B$10,0)+IF(32=Inputs!$B$13,Inputs!$B$12,0)+IF(32=Inputs!$B$15,Inputs!$B$14,0)+IF(32=Inputs!$B$17,Inputs!$B$16,0) | AH20: =AG20+IF(33=Inputs!$B$11,Inputs!$B$10,0)+IF(33=Inputs!$B$13,Inputs!$B$12,0)+IF(33=Inputs!$B$15,Inputs!$B$14,0)+IF(33=Inputs!$B$17,Inputs!$B$16,0) | AI20: =AH20+IF(34=Inputs!$B$11,Inputs!$B$10,0)+IF(34=Inputs!$B$13,Inputs!$B$12,0)+IF(34=Inputs!$B$15,Inputs!$B$14,0)+IF(34=Inputs!$B$17,Inputs!$B$16,0) | AJ20: =AI20+IF(35=Inputs!$B$11,Inputs!$B$10,0)+IF(35=Inputs!$B$13,Inputs!$B$12,0)+IF(35=Inputs!$B$15,Inputs!$B$14,0)+IF(35=Inputs!$B$17,Inputs!$B$16,0) | AK20: =AJ20+IF(36=Inputs!$B$11,Inputs!$B$10,0)+IF(36=Inputs!$B$13,Inputs!$B$12,0)+IF(36=Inputs!$B$15,Inputs!$B$14,0)+IF(36=Inputs!$B$17,Inputs!$B$16,0) | AL20: =AK20+IF(37=Inputs!$B$11,Inputs!$B$10,0)+IF(37=Inputs!$B$13,Inputs!$B$12,0)+IF(37=Inputs!$B$15,Inputs!$B$14,0)+IF(37=Inputs!$B$17,Inputs!$B$16,0) | AM20: =AL20+IF(38=Inputs!$B$11,Inputs!$B$10,0)+IF(38=Inputs!$B$13,Inputs!$B$12,0)+IF(38=Inputs!$B$15,Inputs!$B$14,0)+IF(38=Inputs!$B$17,Inputs!$B$16,0) | AN20: =AM20+IF(39=Inputs!$B$11,Inputs!$B$10,0)+IF(39=Inputs!$B$13,Inputs!$B$12,0)+IF(39=Inputs!$B$15,Inputs!$B$14,0)+IF(39=Inputs!$B$17,Inputs!$B$16,0) | AO20: =AN20+IF(40=Inputs!$B$11,Inputs!$B$10,0)+IF(40=Inputs!$B$13,Inputs!$B$12,0)+IF(40=Inputs!$B$15,Inputs!$B$14,0)+IF(40=Inputs!$B$17,Inputs!$B$16,0) | AP20: =AO20+IF(41=Inputs!$B$11,Inputs!$B$10,0)+IF(41=Inputs!$B$13,Inputs!$B$12,0)+IF(41=Inputs!$B$15,Inputs!$B$14,0)+IF(41=Inputs!$B$17,Inputs!$B$16,0) | AQ20: =AP20+IF(42=Inputs!$B$11,Inputs!$B$10,0)+IF(42=Inputs!$B$13,Inputs!$B$12,0)+IF(42=Inputs!$B$15,Inputs!$B$14,0)+IF(42=Inputs!$B$17,Inputs!$B$16,0) | AR20: =AQ20+IF(43=Inputs!$B$11,Inputs!$B$10,0)+IF(43=Inputs!$B$13,Inputs!$B$12,0)+IF(43=Inputs!$B$15,Inputs!$B$14,0)+IF(43=Inputs!$B$17,Inputs!$B$16,0) | AS20: =AR20+IF(44=Inputs!$B$11,Inputs!$B$10,0)+IF(44=Inputs!$B$13,Inputs!$B$12,0)+IF(44=Inputs!$B$15,Inputs!$B$14,0)+IF(44=Inputs!$B$17,Inputs!$B$16,0) | AT20: =AS20+IF(45=Inputs!$B$11,Inputs!$B$10,0)+IF(45=Inputs!$B$13,Inputs!$B$12,0)+IF(45=Inputs!$B$15,Inputs!$B$14,0)+IF(45=Inputs!$B$17,Inputs!$B$16,0) | AU20: =AT20+IF(46=Inputs!$B$11,Inputs!$B$10,0)+IF(46=Inputs!$B$13,Inputs!$B$12,0)+IF(46=Inputs!$B$15,Inputs!$B$14,0)+IF(46=Inputs!$B$17,Inputs!$B$16,0) | AV20: =AU20+IF(47=Inputs!$B$11,Inputs!$B$10,0)+IF(47=Inputs!$B$13,Inputs!$B$12,0)+IF(47=Inputs!$B$15,Inputs!$B$14,0)+IF(47=Inputs!$B$17,Inputs!$B$16,0) | AW20: =AV20+IF(48=Inputs!$B$11,Inputs!$B$10,0)+IF(48=Inputs!$B$13,Inputs!$B$12,0)+IF(48=Inputs!$B$15,Inputs!$B$14,0)+IF(48=Inputs!$B$17,Inputs!$B$16,0) | AX20: =AW20+IF(49=Inputs!$B$11,Inputs!$B$10,0)+IF(49=Inputs!$B$13,Inputs!$B$12,0)+IF(49=Inputs!$B$15,Inputs!$B$14,0)+IF(49=Inputs!$B$17,Inputs!$B$16,0) | AY20: =AX20+IF(50=Inputs!$B$11,Inputs!$B$10,0)+IF(50=Inputs!$B$13,Inputs!$B$12,0)+IF(50=Inputs!$B$15,Inputs!$B$14,0)+IF(50=Inputs!$B$17,Inputs!$B$16,0) | AZ20: =AY20+IF(51=Inputs!$B$11,Inputs!$B$10,0)+IF(51=Inputs!$B$13,Inputs!$B$12,0)+IF(51=Inputs!$B$15,Inputs!$B$14,0)+IF(51=Inputs!$B$17,Inputs!$B$16,0) | BA20: =AZ20+IF(52=Inputs!$B$11,Inputs!$B$10,0)+IF(52=Inputs!$B$13,Inputs!$B$12,0)+IF(52=Inputs!$B$15,Inputs!$B$14,0)+IF(52=Inputs!$B$17,Inputs!$B$16,0)
A21: Retained Earnings | B21: ='P&L'!B39 | C21: =B21+'P&L'!C39 | D21: =C21+'P&L'!D39 | E21: =D21+'P&L'!E39 | F21: =E21+'P&L'!F39 | G21: =F21+'P&L'!G39 | H21: =G21+'P&L'!H39 | I21: =H21+'P&L'!I39 | J21: =I21+'P&L'!J39 | ... BA21: =AZ21+'P&L'!BA39
A22: TOTAL EQUITY | B22: =B19+B20+B21 | C22: =C19+C20+C21 | D22: =D19+D20+D21 | E22: =E19+E20+E21 | F22: =F19+F20+F21 | G22: =G19+G20+G21 | H22: =H19+H20+H21 | I22: =I19+I20+I21 | ... BA22: =BA19+BA20+BA21
A24: TOTAL LIABILITIES + EQUITY | B24: =B16+B22 | C24: =C16+C22 | D24: =D16+D22 | E24: =E16+E22 | F24: =F16+F22 | G24: =G16+G22 | H24: =H16+H22 | I24: =I16+I22 | ... BA24: =BA16+BA22
A25: Check (Assets - L&E = 0) | B25: =B10-B24 | C25: =C10-C24 | D25: =D10-D24 | E25: =E10-E24 | F25: =F10-F24 | G25: =G10-G24 | H25: =H10-H24 | I25: =I10-I24 | ... BA25: =BA10-BA24

Sheet Cash Flow
A1: KAPITALFLUSSRECHNUNG (CASH FLOW)
B2: 46113 | C2: 46143 | D2: 46174 | E2: 46204 | F2: 46235 | G2: 46266 | H2: 46296 | I2: 46327 | J2: 46357 | K2: 46388 | L2: 46419 | M2: 46447 | N2: 46478 | O2: 46508 | P2: 46539 | Q2: 46569 | R2: 46600 | S2: 46631 | T2: 46661 | U2: 46692 | V2: 46722 | W2: 46753 | X2: 46784 | Y2: 46813 | Z2: 46844 | AA2: 46874 | AB2: 46905 | AC2: 46935 | AD2: 46966 | AE2: 46997 | AF2: 47027 | AG2: 47058 | AH2: 47088 | AI2: 47119 | AJ2: 47150 | AK2: 47178 | AL2: 47209 | AM2: 47239 | AN2: 47270 | AO2: 47300 | AP2: 47331 | AQ2: 47362 | AR2: 47392 | AS2: 47423 | AT2: 47453 | AU2: 47484 | AV2: 47515 | AW2: 47543 | AX2: 47574 | AY2: 47604 | AZ2: 47635 | BA2: 47665
A3: Startup-Phase | B3: Ideation | C3: Ideation | D3: Ideation | E3: Ideation | F3: Pre-Seed | G3: Pre-Seed | H3: Pre-Seed | I3: Pre-Seed | J3: Pre-Seed | K3: Pre-Seed | L3: Pre-Seed | M3: Pre-Seed | N3: Pre-Seed | O3: Pre-Seed | P3: Pre-Seed | Q3: Pre-Seed | R3: Seed | S3: Seed | T3: Seed | U3: Seed | V3: Seed | W3: Seed | X3: Seed | Y3: Seed | Z3: Seed | AA3: Seed | AB3: Seed | AC3: Seed | AD3: Series A | AE3: Series A | AF3: Series A | AG3: Series A | AH3: Series A | AI3: Series A | AJ3: Series A | AK3: Series A | AL3: Series A | AM3: Series A | AN3: Series A | AO3: Series A | AP3: Series B | AQ3: Series B | AR3: Series B | AS3: Series B | AT3: Series B | AU3: Series B | AV3: Series B | AW3: Series B | AX3: Series B | AY3: Series B | AZ3: Series B | BA3: Series B
A4: Position | B4: M1 | C4: M2 | D4: M3 | E4: M4 | F4: M5 | G4: M6 | H4: M7 | I4: M8 | J4: M9 | K4: M10 | L4: M11 | M4: M12 | N4: M13 | O4: M14 | P4: M15 | Q4: M16 | R4: M17 | S4: M18 | T4: M19 | U4: M20 | V4: M21 | W4: M22 | X4: M23 | Y4: M24 | Z4: M25 | AA4: M26 | AB4: M27 | AC4: M28 | AD4: M29 | AE4: M30 | AF4: M31 | AG4: M32 | AH4: M33 | AI4: M34 | AJ4: M35 | AK4: M36 | AL4: M37 | AM4: M38 | AN4: M39 | AO4: M40 | AP4: M41 | AQ4: M42 | AR4: M43 | AS4: M44 | AT4: M45 | AU4: M46 | AV4: M47 | AW4: M48 | AX4: M49 | AY4: M50 | AZ4: M51 | BA4: M52
A5: OPERATING ACTIVITIES
A6: Net Income | B6: ='P&L'!B39 | C6: ='P&L'!C39 | D6: ='P&L'!D39 | E6: ='P&L'!E39 | F6: ='P&L'!F39 | G6: ='P&L'!G39 | H6: ='P&L'!H39 | I6: ='P&L'!I39 | ... BA6: ='P&L'!BA39
A7: + Depreciation & Amortization | B7: ='P&L'!B32 | C7: ='P&L'!C32 | D7: ='P&L'!D32 | E7: ='P&L'!E32 | F7: ='P&L'!F32 | G7: ='P&L'!G32 | H7: ='P&L'!H32 | I7: ='P&L'!I32 | ... BA7: ='P&L'!BA32
A8: Changes in Working Capital | B8: =-'Balance Sheet'!B7-'Balance Sheet'!B8+'Balance Sheet'!B13+'Balance Sheet'!B14+'Balance Sheet'!B15 | C8: =-('Balance Sheet'!C7-'Balance Sheet'!B7)-('Balance Sheet'!C8-'Balance Sheet'!B8)+('Balance Sheet'!C13-'Balance Sheet'!B13)+('Balance Sheet'!C14-'Balance Sheet'!B14)+('Balance Sheet'!C15-'Balance Sheet'!B15) | D8: =-('Balance Sheet'!D7-'Balance Sheet'!C7)-('Balance Sheet'!D8-'Balance Sheet'!C8)+('Balance Sheet'!D13-'Balance Sheet'!C13)+('Balance Sheet'!D14-'Balance Sheet'!C14)+('Balance Sheet'!D15-'Balance Sheet'!C15) | E8: =-('Balance Sheet'!E7-'Balance Sheet'!D7)-('Balance Sheet'!E8-'Balance Sheet'!D8)+('Balance Sheet'!E13-'Balance Sheet'!D13)+('Balance Sheet'!E14-'Balance Sheet'!D14)+('Balance Sheet'!E15-'Balance Sheet'!D15) | F8: =-('Balance Sheet'!F7-'Balance Sheet'!E7)-('Balance Sheet'!F8-'Balance Sheet'!E8)+('Balance Sheet'!F13-'Balance Sheet'!E13)+('Balance Sheet'!F14-'Balance Sheet'!E14)+('Balance Sheet'!F15-'Balance Sheet'!E15) | G8: =-('Balance Sheet'!G7-'Balance Sheet'!F7)-('Balance Sheet'!G8-'Balance Sheet'!F8)+('Balance Sheet'!G13-'Balance Sheet'!F13)+('Balance Sheet'!G14-'Balance Sheet'!F14)+('Balance Sheet'!G15-'Balance Sheet'!F15) | H8: =-('Balance Sheet'!H7-'Balance Sheet'!G7)-('Balance Sheet'!H8-'Balance Sheet'!G8)+('Balance Sheet'!H13-'Balance Sheet'!G13)+('Balance Sheet'!H14-'Balance Sheet'!G14)+('Balance Sheet'!H15-'Balance Sheet'!G15) | I8: =-('Balance Sheet'!I7-'Balance Sheet'!H7)-('Balance Sheet'!I8-'Balance Sheet'!H8)+('Balance Sheet'!I13-'Balance Sheet'!H13)+('Balance Sheet'!I14-'Balance Sheet'!H14)+('Balance Sheet'!I15-'Balance Sheet'!H15) | J8: =-('Balance Sheet'!J7-'Balance Sheet'!I7)-('Balance Sheet'!J8-'Balance Sheet'!I8)+('Balance Sheet'!J13-'Balance Sheet'!I13)+('Balance Sheet'!J14-'Balance Sheet'!I14)+('Balance Sheet'!J15-'Balance Sheet'!I15) | ... BA8: =-('Balance Sheet'!BA7-'Balance Sheet'!AZ7)-('Balance Sheet'!BA8-'Balance Sheet'!AZ8)+('Balance Sheet'!BA13-'Balance Sheet'!AZ13)+('Balance Sheet'!BA14-'Balance Sheet'!AZ14)+('Balance Sheet'!BA15-'Balance Sheet'!AZ15)
A9: Net Cash from Operations | B9: =B6+B7+B8 | C9: =C6+C7+C8 | D9: =D6+D7+D8 | E9: =E6+E7+E8 | F9: =F6+F7+F8 | G9: =G6+G7+G8 | H9: =H6+H7+H8 | I9: =I6+I7+I8 | ... BA9: =BA6+BA7+BA8
A11: INVESTING ACTIVITIES
A12: Purchase of Equipment | B12: =-(Costs!B90+Inputs!$B$89) | C12: =-Costs!C90 | D12: =-Costs!D90 | E12: =-Costs!E90 | F12: =-Costs!F90 | G12: =-Costs!G90 | H12: =-Costs!H90 | I12: =-Costs!I90 | J12: =-Costs!J90 | ... BA12: =-Costs!BA90
A13: Net Cash from Investing | B13: =B12 | C13: =C12 | D13: =D12 | E13: =E12 | F13: =F12 | G13: =G12 | H13: =H12 | I13: =I12 | ... BA13: =BA12
A15: FINANCING ACTIVITIES
A16: Equity Funding Received | B16: =IF(1=Inputs!$B$11,Inputs!$B$10,0)+IF(1=Inputs!$B$13,Inputs!$B$12,0)+IF(1=Inputs!$B$15,Inputs!$B$14,0)+IF(1=Inputs!$B$17,Inputs!$B$16,0) | C16: =IF(2=Inputs!$B$11,Inputs!$B$10,0)+IF(2=Inputs!$B$13,Inputs!$B$12,0)+IF(2=Inputs!$B$15,Inputs!$B$14,0)+IF(2=Inputs!$B$17,Inputs!$B$16,0) | D16: =IF(3=Inputs!$B$11,Inputs!$B$10,0)+IF(3=Inputs!$B$13,Inputs!$B$12,0)+IF(3=Inputs!$B$15,Inputs!$B$14,0)+IF(3=Inputs!$B$17,Inputs!$B$16,0) | E16: =IF(4=Inputs!$B$11,Inputs!$B$10,0)+IF(4=Inputs!$B$13,Inputs!$B$12,0)+IF(4=Inputs!$B$15,Inputs!$B$14,0)+IF(4=Inputs!$B$17,Inputs!$B$16,0) | F16: =IF(5=Inputs!$B$11,Inputs!$B$10,0)+IF(5=Inputs!$B$13,Inputs!$B$12,0)+IF(5=Inputs!$B$15,Inputs!$B$14,0)+IF(5=Inputs!$B$17,Inputs!$B$16,0) | G16: =IF(6=Inputs!$B$11,Inputs!$B$10,0)+IF(6=Inputs!$B$13,Inputs!$B$12,0)+IF(6=Inputs!$B$15,Inputs!$B$14,0)+IF(6=Inputs!$B$17,Inputs!$B$16,0) | H16: =IF(7=Inputs!$B$11,Inputs!$B$10,0)+IF(7=Inputs!$B$13,Inputs!$B$12,0)+IF(7=Inputs!$B$15,Inputs!$B$14,0)+IF(7=Inputs!$B$17,Inputs!$B$16,0) | I16: =IF(8=Inputs!$B$11,Inputs!$B$10,0)+IF(8=Inputs!$B$13,Inputs!$B$12,0)+IF(8=Inputs!$B$15,Inputs!$B$14,0)+IF(8=Inputs!$B$17,Inputs!$B$16,0) | J16: =IF(9=Inputs!$B$11,Inputs!$B$10,0)+IF(9=Inputs!$B$13,Inputs!$B$12,0)+IF(9=Inputs!$B$15,Inputs!$B$14,0)+IF(9=Inputs!$B$17,Inputs!$B$16,0) | K16: =IF(10=Inputs!$B$11,Inputs!$B$10,0)+IF(10=Inputs!$B$13,Inputs!$B$12,0)+IF(10=Inputs!$B$15,Inputs!$B$14,0)+IF(10=Inputs!$B$17,Inputs!$B$16,0) | L16: =IF(11=Inputs!$B$11,Inputs!$B$10,0)+IF(11=Inputs!$B$13,Inputs!$B$12,0)+IF(11=Inputs!$B$15,Inputs!$B$14,0)+IF(11=Inputs!$B$17,Inputs!$B$16,0) | M16: =IF(12=Inputs!$B$11,Inputs!$B$10,0)+IF(12=Inputs!$B$13,Inputs!$B$12,0)+IF(12=Inputs!$B$15,Inputs!$B$14,0)+IF(12=Inputs!$B$17,Inputs!$B$16,0) | N16: =IF(13=Inputs!$B$11,Inputs!$B$10,0)+IF(13=Inputs!$B$13,Inputs!$B$12,0)+IF(13=Inputs!$B$15,Inputs!$B$14,0)+IF(13=Inputs!$B$17,Inputs!$B$16,0) | O16: =IF(14=Inputs!$B$11,Inputs!$B$10,0)+IF(14=Inputs!$B$13,Inputs!$B$12,0)+IF(14=Inputs!$B$15,Inputs!$B$14,0)+IF(14=Inputs!$B$17,Inputs!$B$16,0) | P16: =IF(15=Inputs!$B$11,Inputs!$B$10,0)+IF(15=Inputs!$B$13,Inputs!$B$12,0)+IF(15=Inputs!$B$15,Inputs!$B$14,0)+IF(15=Inputs!$B$17,Inputs!$B$16,0) | Q16: =IF(16=Inputs!$B$11,Inputs!$B$10,0)+IF(16=Inputs!$B$13,Inputs!$B$12,0)+IF(16=Inputs!$B$15,Inputs!$B$14,0)+IF(16=Inputs!$B$17,Inputs!$B$16,0) | R16: =IF(17=Inputs!$B$11,Inputs!$B$10,0)+IF(17=Inputs!$B$13,Inputs!$B$12,0)+IF(17=Inputs!$B$15,Inputs!$B$14,0)+IF(17=Inputs!$B$17,Inputs!$B$16,0) | S16: =IF(18=Inputs!$B$11,Inputs!$B$10,0)+IF(18=Inputs!$B$13,Inputs!$B$12,0)+IF(18=Inputs!$B$15,Inputs!$B$14,0)+IF(18=Inputs!$B$17,Inputs!$B$16,0) | T16: =IF(19=Inputs!$B$11,Inputs!$B$10,0)+IF(19=Inputs!$B$13,Inputs!$B$12,0)+IF(19=Inputs!$B$15,Inputs!$B$14,0)+IF(19=Inputs!$B$17,Inputs!$B$16,0) | U16: =IF(20=Inputs!$B$11,Inputs!$B$10,0)+IF(20=Inputs!$B$13,Inputs!$B$12,0)+IF(20=Inputs!$B$15,Inputs!$B$14,0)+IF(20=Inputs!$B$17,Inputs!$B$16,0) | V16: =IF(21=Inputs!$B$11,Inputs!$B$10,0)+IF(21=Inputs!$B$13,Inputs!$B$12,0)+IF(21=Inputs!$B$15,Inputs!$B$14,0)+IF(21=Inputs!$B$17,Inputs!$B$16,0) | W16: =IF(22=Inputs!$B$11,Inputs!$B$10,0)+IF(22=Inputs!$B$13,Inputs!$B$12,0)+IF(22=Inputs!$B$15,Inputs!$B$14,0)+IF(22=Inputs!$B$17,Inputs!$B$16,0) | X16: =IF(23=Inputs!$B$11,Inputs!$B$10,0)+IF(23=Inputs!$B$13,Inputs!$B$12,0)+IF(23=Inputs!$B$15,Inputs!$B$14,0)+IF(23=Inputs!$B$17,Inputs!$B$16,0) | Y16: =IF(24=Inputs!$B$11,Inputs!$B$10,0)+IF(24=Inputs!$B$13,Inputs!$B$12,0)+IF(24=Inputs!$B$15,Inputs!$B$14,0)+IF(24=Inputs!$B$17,Inputs!$B$16,0) | Z16: =IF(25=Inputs!$B$11,Inputs!$B$10,0)+IF(25=Inputs!$B$13,Inputs!$B$12,0)+IF(25=Inputs!$B$15,Inputs!$B$14,0)+IF(25=Inputs!$B$17,Inputs!$B$16,0) | AA16: =IF(26=Inputs!$B$11,Inputs!$B$10,0)+IF(26=Inputs!$B$13,Inputs!$B$12,0)+IF(26=Inputs!$B$15,Inputs!$B$14,0)+IF(26=Inputs!$B$17,Inputs!$B$16,0) | AB16: =IF(27=Inputs!$B$11,Inputs!$B$10,0)+IF(27=Inputs!$B$13,Inputs!$B$12,0)+IF(27=Inputs!$B$15,Inputs!$B$14,0)+IF(27=Inputs!$B$17,Inputs!$B$16,0) | AC16: =IF(28=Inputs!$B$11,Inputs!$B$10,0)+IF(28=Inputs!$B$13,Inputs!$B$12,0)+IF(28=Inputs!$B$15,Inputs!$B$14,0)+IF(28=Inputs!$B$17,Inputs!$B$16,0) | AD16: =IF(29=Inputs!$B$11,Inputs!$B$10,0)+IF(29=Inputs!$B$13,Inputs!$B$12,0)+IF(29=Inputs!$B$15,Inputs!$B$14,0)+IF(29=Inputs!$B$17,Inputs!$B$16,0) | AE16: =IF(30=Inputs!$B$11,Inputs!$B$10,0)+IF(30=Inputs!$B$13,Inputs!$B$12,0)+IF(30=Inputs!$B$15,Inputs!$B$14,0)+IF(30=Inputs!$B$17,Inputs!$B$16,0) | AF16: =IF(31=Inputs!$B$11,Inputs!$B$10,0)+IF(31=Inputs!$B$13,Inputs!$B$12,0)+IF(31=Inputs!$B$15,Inputs!$B$14,0)+IF(31=Inputs!$B$17,Inputs!$B$16,0) | AG16: =IF(32=Inputs!$B$11,Inputs!$B$10,0)+IF(32=Inputs!$B$13,Inputs!$B$12,0)+IF(32=Inputs!$B$15,Inputs!$B$14,0)+IF(32=Inputs!$B$17,Inputs!$B$16,0) | AH16: =IF(33=Inputs!$B$11,Inputs!$B$10,0)+IF(33=Inputs!$B$13,Inputs!$B$12,0)+IF(33=Inputs!$B$15,Inputs!$B$14,0)+IF(33=Inputs!$B$17,Inputs!$B$16,0) | AI16: =IF(34=Inputs!$B$11,Inputs!$B$10,0)+IF(34=Inputs!$B$13,Inputs!$B$12,0)+IF(34=Inputs!$B$15,Inputs!$B$14,0)+IF(34=Inputs!$B$17,Inputs!$B$16,0) | AJ16: =IF(35=Inputs!$B$11,Inputs!$B$10,0)+IF(35=Inputs!$B$13,Inputs!$B$12,0)+IF(35=Inputs!$B$15,Inputs!$B$14,0)+IF(35=Inputs!$B$17,Inputs!$B$16,0) | AK16: =IF(36=Inputs!$B$11,Inputs!$B$10,0)+IF(36=Inputs!$B$13,Inputs!$B$12,0)+IF(36=Inputs!$B$15,Inputs!$B$14,0)+IF(36=Inputs!$B$17,Inputs!$B$16,0) | AL16: =IF(37=Inputs!$B$11,Inputs!$B$10,0)+IF(37=Inputs!$B$13,Inputs!$B$12,0)+IF(37=Inputs!$B$15,Inputs!$B$14,0)+IF(37=Inputs!$B$17,Inputs!$B$16,0) | AM16: =IF(38=Inputs!$B$11,Inputs!$B$10,0)+IF(38=Inputs!$B$13,Inputs!$B$12,0)+IF(38=Inputs!$B$15,Inputs!$B$14,0)+IF(38=Inputs!$B$17,Inputs!$B$16,0) | AN16: =IF(39=Inputs!$B$11,Inputs!$B$10,0)+IF(39=Inputs!$B$13,Inputs!$B$12,0)+IF(39=Inputs!$B$15,Inputs!$B$14,0)+IF(39=Inputs!$B$17,Inputs!$B$16,0) | AO16: =IF(40=Inputs!$B$11,Inputs!$B$10,0)+IF(40=Inputs!$B$13,Inputs!$B$12,0)+IF(40=Inputs!$B$15,Inputs!$B$14,0)+IF(40=Inputs!$B$17,Inputs!$B$16,0) | AP16: =IF(41=Inputs!$B$11,Inputs!$B$10,0)+IF(41=Inputs!$B$13,Inputs!$B$12,0)+IF(41=Inputs!$B$15,Inputs!$B$14,0)+IF(41=Inputs!$B$17,Inputs!$B$16,0) | AQ16: =IF(42=Inputs!$B$11,Inputs!$B$10,0)+IF(42=Inputs!$B$13,Inputs!$B$12,0)+IF(42=Inputs!$B$15,Inputs!$B$14,0)+IF(42=Inputs!$B$17,Inputs!$B$16,0) | AR16: =IF(43=Inputs!$B$11,Inputs!$B$10,0)+IF(43=Inputs!$B$13,Inputs!$B$12,0)+IF(43=Inputs!$B$15,Inputs!$B$14,0)+IF(43=Inputs!$B$17,Inputs!$B$16,0) | AS16: =IF(44=Inputs!$B$11,Inputs!$B$10,0)+IF(44=Inputs!$B$13,Inputs!$B$12,0)+IF(44=Inputs!$B$15,Inputs!$B$14,0)+IF(44=Inputs!$B$17,Inputs!$B$16,0) | AT16: =IF(45=Inputs!$B$11,Inputs!$B$10,0)+IF(45=Inputs!$B$13,Inputs!$B$12,0)+IF(45=Inputs!$B$15,Inputs!$B$14,0)+IF(45=Inputs!$B$17,Inputs!$B$16,0) | AU16: =IF(46=Inputs!$B$11,Inputs!$B$10,0)+IF(46=Inputs!$B$13,Inputs!$B$12,0)+IF(46=Inputs!$B$15,Inputs!$B$14,0)+IF(46=Inputs!$B$17,Inputs!$B$16,0) | AV16: =IF(47=Inputs!$B$11,Inputs!$B$10,0)+IF(47=Inputs!$B$13,Inputs!$B$12,0)+IF(47=Inputs!$B$15,Inputs!$B$14,0)+IF(47=Inputs!$B$17,Inputs!$B$16,0) | AW16: =IF(48=Inputs!$B$11,Inputs!$B$10,0)+IF(48=Inputs!$B$13,Inputs!$B$12,0)+IF(48=Inputs!$B$15,Inputs!$B$14,0)+IF(48=Inputs!$B$17,Inputs!$B$16,0) | AX16: =IF(49=Inputs!$B$11,Inputs!$B$10,0)+IF(49=Inputs!$B$13,Inputs!$B$12,0)+IF(49=Inputs!$B$15,Inputs!$B$14,0)+IF(49=Inputs!$B$17,Inputs!$B$16,0) | AY16: =IF(50=Inputs!$B$11,Inputs!$B$10,0)+IF(50=Inputs!$B$13,Inputs!$B$12,0)+IF(50=Inputs!$B$15,Inputs!$B$14,0)+IF(50=Inputs!$B$17,Inputs!$B$16,0) | AZ16: =IF(51=Inputs!$B$11,Inputs!$B$10,0)+IF(51=Inputs!$B$13,Inputs!$B$12,0)+IF(51=Inputs!$B$15,Inputs!$B$14,0)+IF(51=Inputs!$B$17,Inputs!$B$16,0) | BA16: =IF(52=Inputs!$B$11,Inputs!$B$10,0)+IF(52=Inputs!$B$13,Inputs!$B$12,0)+IF(52=Inputs!$B$15,Inputs!$B$14,0)+IF(52=Inputs!$B$17,Inputs!$B$16,0)
A17: Net Cash from Financing | B17: =B16 | C17: =C16 | D17: =D16 | E17: =E16 | F17: =F16 | G17: =G16 | H17: =H16 | I17: =I16 | ... BA17: =BA16
A19: NET CHANGE IN CASH | B19: =B9+B13+B17 | C19: =C9+C13+C17 | D19: =D9+D13+D17 | E19: =E9+E13+E17 | F19: =F9+F13+F17 | G19: =G9+G13+G17 | H19: =H9+H13+H17 | I19: =I9+I13+I17 | ... BA19: =BA9+BA13+BA17
A21: Beginning Cash Balance | B21: 0 | C21: =B23 | D21: =C23 | E21: =D23 | F21: =E23 | G21: =F23 | H21: =G23 | I21: =H23 | J21: =I23 | ... BA21: =AZ23
A22: Net Change | B22: =B19 | C22: =C19 | D22: =D19 | E22: =E19 | F22: =F19 | G22: =G19 | H22: =H19 | I22: =I19 | ... BA22: =BA19
A23: ENDING CASH BALANCE | B23: =B21+B22 | C23: =C21+C22 | D23: =D21+D22 | E23: =E21+E22 | F23: =F21+F22 | G23: =G21+G22 | H23: =H21+H22 | I23: =I21+I22 | ... BA23: =BA21+BA22
A25: KEY METRICS
A26: Monthly Burn Rate | B26: =IF(B19<0,-B19,0) | C26: =IF(C19<0,-C19,0) | D26: =IF(D19<0,-D19,0) | E26: =IF(E19<0,-E19,0) | F26: =IF(F19<0,-F19,0) | G26: =IF(G19<0,-G19,0) | H26: =IF(H19<0,-H19,0) | I26: =IF(I19<0,-I19,0) | ... BA26: =IF(BA19<0,-BA19,0)
A27: Runway (Months) | B27: =IFERROR(IF(B26>0,B23/B26,"∞"),"∞") | C27: =IFERROR(IF(C26>0,C23/C26,"∞"),"∞") | D27: =IFERROR(IF(D26>0,D23/D26,"∞"),"∞") | E27: =IFERROR(IF(E26>0,E23/E26,"∞"),"∞") | F27: =IFERROR(IF(F26>0,F23/F26,"∞"),"∞") | G27: =IFERROR(IF(G26>0,G23/G26,"∞"),"∞") | H27: =IFERROR(IF(H26>0,H23/H26,"∞"),"∞") | I27: =IFERROR(IF(I26>0,I23/I26,"∞"),"∞") | ... BA27: =IFERROR(IF(BA26>0,BA23/BA26,"∞"),"∞")
A28: Cumulative Cash Position | B28: =B23 | C28: =C23 | D28: =D23 | E28: =E23 | F28: =F23 | G28: =G23 | H28: =H23 | I28: =I23 | ... BA28: =BA23
A29: Cash Runway Alert | B29: =IF(ISNUMBER(B27),IF(B27<6,"WARNUNG: <6 Monate!","OK"),"OK") | C29: =IF(ISNUMBER(C27),IF(C27<6,"WARNUNG: <6 Monate!","OK"),"OK") | D29: =IF(ISNUMBER(D27),IF(D27<6,"WARNUNG: <6 Monate!","OK"),"OK") | E29: =IF(ISNUMBER(E27),IF(E27<6,"WARNUNG: <6 Monate!","OK"),"OK") | F29: =IF(ISNUMBER(F27),IF(F27<6,"WARNUNG: <6 Monate!","OK"),"OK") | G29: =IF(ISNUMBER(G27),IF(G27<6,"WARNUNG: <6 Monate!","OK"),"OK") | H29: =IF(ISNUMBER(H27),IF(H27<6,"WARNUNG: <6 Monate!","OK"),"OK") | I29: =IF(ISNUMBER(I27),IF(I27<6,"WARNUNG: <6 Monate!","OK"),"OK") | ... BA29: =IF(ISNUMBER(BA27),IF(BA27<6,"WARNUNG: <6 Monate!","OK"),"OK")

Sheet LFL_Szenario_Erklaerung
A1: LFL FINANCIAL PROJECTIONS — SZENARIO KONSERVATIV
A2: Basis: 260304_LFL-Financial-Planning-and-Carbon-Case.pdf | Erstellt: 04.03.2026 23:13
A4: HINTERGRUND
A5: Dieses Szenario basiert auf dem LFL Financial Planning & Carbon Case Dossier (260304_LFL-Financial-Planning-and-Carbon-Case.pdf, Stand 4. März 2026). Alle Parameter wurden aus den strategischen Meeting-Transkripten von Rene und dem Finanzmodellierer abgeleitet. Externe Annahmen wurden nicht hinzugefügt. Offene Punkte (TBD/OPEN) aus dem Dossier sind im Report-Sheet markiert.
A7: Parameter | B7: Bezeichnung | C7: Baseline | D7: NEU (KONSERVATIV) | E7: Begründung / Zusammenhang
A8: 1. PREISGESTALTUNG — Konservative Positionierung
A9: Sandbox D6 | B9: Preis/Seat/Monat | C9: 800 EUR (gering-Standard) | D9: 200 EUR | E9: Das PDF nennt 350 EUR/Monat als Referenzpreis (→ 4.200 EUR/Seat/Jahr) und 200 EUR als benchmark_low. Im konservativen Szenario wählen wir den Benchmark-Tiefpunkt, um das Preisrisiko in der Marktvalidierung abzubilden. Ein zu hoher Einstiegspreis ohne bewiesenen ROI verlängert den Sales-Zyklus erheblich.
A10: Inputs B21 | B10: Preiserhöhung/Jahr | C10: 8% | D10: 5% | E10: Geringere jährliche Preissteigerung reflektiert schwächere Marktposition und Kundenwiderstand in der Frühphase. Packaging-Kunden (primärer Markt: 2.255 Unternehmen laut Rene) sind preissensitiv.
A11: → Auswirkung | B11: ARR pro Standardkunde (5 Seats): 200 EUR × 5 × 12 = 12.000 EUR/Jahr (vs. 21.000 EUR im PDF-Referenzpreis). Runway und Break-Even verschlechtern sich deutlich. Höheres Funding-Risiko.
A13: 2. KUNDEN-TIMING & WACHSTUM — Langsame Marktdurchdringung
A14: Sandbox D5 | B14: Startmonat erste Kunden | C14: 14 | D14: 17 | E14: Das PDF nennt explizit '~17 months to first revenue'. Im konservativen Szenario halten wir an diesem Planwert fest. Die Pre-Seed-Phase (3-5 Kunden, Sept 2026-Sept 2027) dient reiner Validierung ohne Revenue-Fokus. First paying customer frühestens Monat 17 (September 2027, mit Seed-Close).
A15: Inputs B23 | B15: Initiale Seats | C15: 5 | D15: 3 | E15: PDF nennt 3-5 als Pre-Seed-Kundenzahl. Konservativ: 3 Piloten. Jeder Pilot mit 5 Seats = 15 Seats total.
A16: Inputs B24 | B16: Monatl. Seat-Wachstum | C16: 5% | D16: 3% | E16: Verlangsamtes Wachstum durch längere Sales-Zyklen (packaging/automotive lt. PDF: 'longer lead cycle in automotive'). 3% entspricht ca. 43% Jahreswachstum – konservativ aber realistisch für B2B-Manufacturing.
A17: Inputs B25 | B17: Enterprise-Deals ab Monat | C17: 24 | D17: 30 | E17: Enterprise-Deals starten erst nach Monat 30 – nach erstem erfolgreichen Track Record. PDF: deal_complexity höher als Standard, lead_cycle länger.
A18: → Auswirkung | B18: Seed-Ziel: 50-60 Kunden (PDF) → im Konservativ-Szenario realistisch 25-35 Kunden bis Monat 17-24. Gesamt-ARR M24: deutlich unter 500K EUR. Enterprise-Revenue startet erst ab M30.
A20: 3. CHURN & KUNDENBINDUNG — Höheres Abwanderungsrisiko
A21: Inputs B28 | B21: Jährliche Churn Rate | C21: 8% | D21: 15% | E21: PDF: adoption_probability_low = 10%. Geringe Adoption bedeutet hohes Abwanderungsrisiko sobald Verträge auslaufen. 15% Churn entspricht einem 'gefährdeten' SaaS-Modell in der Early-Stage, typisch für Produkte ohne tiefen Workflow-Lock-in. Causal: Fehlende Onboarding-Qualität + unklarer ROI-Nachweis (wie Olaf betont) führen zu Abwanderung.
A22: Inputs B29 | B22: Net Revenue Retention | C22: 118% | D22: 105% | E22: Ohne starke Expansion durch Upsell oder neue Seats bleibt NRR knapp über 100%. PDF: Keine quantifizierten Upsell-Mechanismen – konservativ daher 105%.
A23: → Auswirkung | B23: ARR-Erosion durch Churn: Bei 100K ARR und 15% Churn verliert das Unternehmen 15K/Jahr. Ohne starkes Neuwachstum schrumpft der Revenue-Pool. NRR von 105% rettet knapp die Nettowachstum-Rate.
A25: 4. FUNDING — Konservative Kapitalstrategie
A26: Inputs B12 | B26: Pre-Seed Betrag | C26: 1.500.000 EUR | D26: 1.500.000 EUR | E26: PDF Lower End: 1,5M EUR. Im Konservativ-Szenario bleibt Pre-Seed beim Minimum. Runway: 12 Monate (Sept 2026 – Sept 2027). Reicht für MVP + 3-5 Pilotkunden.
A27: Inputs B14 | B27: Seed Betrag | C27: 6.000.000 EUR | D27: 4.000.000 EUR | E27: PDF Seed Lower End: 4M EUR. Konservativ, da langsameres Wachstum weniger Kapital verbraucht. Seed-Runway: 12 Monate (Sept 2027 – Sept 2028), für 50-60 Kunden.
A28: Inputs B16 | B28: Series A Betrag | C28: 15.000.000 EUR | D28: 10.000.000 EUR | E28: Reduzierte Series A durch geringeres Wachstumstempo. Schont Verwässerung.
A29: Inputs B17 | B29: Series A Monat | C29: 35 | D29: 36 | E29: Leicht später, da Meilensteine langsamer erreicht werden.
A30: → Auswirkung | B30: Gesamtfinanzierung: 15,5M EUR (vs. 23,5M im Aggressiv). Niedrigerer Cash-Verbrauch durch geringere Headcount- und Marketing-Ausgaben.
A32: 5. HEADCOUNT & KI-HEBEL — Vollständige Personalplanung
A33: Sandbox D10 | B33: AI-Personal-Hebel | C33: 0 Monate (Gering-Standard) | D33: 0 Monate | E33: Konservativ: Kein KI-Delay beim Hiring. Alle Rollen werden zum ursprünglich geplanten Monat eingestellt. Begründung: KI-Werkzeuge sind in der Praxis in Monat 1-24 noch nicht produktionsreif genug, um Hiring zu verzögern. Das Unternehmen baut Standard-Kapazitäten auf.
A34: Inputs B44 | B34: Jährl. Gehaltserhöhung | C34: 5% | D34: 3% | E34: Geringere Lohnsteigerung reflektiert konservatives Budget und weniger Wettbewerb um Talent im konservativen Szenario (kleineres Unternehmen, Berlin-Markt).
A35: → Auswirkung | B35: Konservativ hat MEHR Mitarbeiter als Aggressiv (kein KI-Delay). Personalkosten sind der größte Kostenblock. Typische Entwicklung: M1-5: CEO + CTO (Founder, Eigenfinanzierung) M5-17: +2 Senior Engineers nach Pre-Seed M17-24: +CCO, +1 Sales, +1 Customer Success nach Seed M24-36: +Marketing, +Finance, +2 weitere Engineers M36-52: +2-3 Sales Reps, +2 CS, +1 weitere GESAMT M52: ~18-22 Mitarbeiter
A37: 6. MARKETING & SALES — Budgetdisziplin
A38: Inputs B125 | B38: Events & Messen/Jahr | C38: 25.000 EUR | D38: 25.000 EUR | E38: PDF-Placeholder-Wert beibehalten. Rene betont: Industrie-Konferenzen > Software-Konferenzen. 25K EUR als Baseline für 2-3 Packaging/Machinery-Konferenzen. Im Konservativ-Szenario kein Aufschlag.
A39: Inputs B122 | B39: Paid Ads Initial | C39: 500 EUR/Monat | D39: 300 EUR/Monat | E39: Geringeres Ads-Budget in der Validierungsphase. B2B-Manufacturing kauft nicht über Ads.
A40: Inputs B127 | B40: Sales-Provision | C40: 10% | D40: 8% | E40: Etwas geringere Provision, da weniger aggressives Sales-Ziel.
A41: → Auswirkung | B41: Total Marketing-Spend M1-M52: ~30-40% geringer als Aggressiv. GTM über Konferenzen (primary), Content (sekundär), POCs (Conversion).
A43: VERGLEICH: KONSERVATIV vs. AGGRESSIV
A44: ╔══════════════════════════════════════════════════════════════════════╗ ║ HAUPTUNTERSCHIEDE: KONSERVATIV vs. AGGRESSIV ║ ╠══════════════════════════════════════════════════════════════════════╣ ║ Parameter │ Konservativ │ Aggressiv │ Quelle ║ ╠══════════════════════════════════════════════════════════════════════╣ ║ Preis/Seat/Monat │ 200 EUR │ 500 EUR │ PDF benchmark ║ ║ Preis/Seat/Jahr │ 2.400 EUR │ 6.000 EUR │ ×12 ║ ║ First Revenue Mon. │ 17 │ 9 │ PDF + Anpassung ║ ║ Initiale Seats │ 3 │ 5 │ PDF avg ║ ║ Seat-Wachstum/Mo. │ 3% │ 8% │ Scenario ║ ║ Enterprise ab Mon. │ 30 │ 18 │ Scenario ║ ║ Enterprise ARR │ 25.000 EUR │ 50.000 EUR │ Scenario ║ ║ Deals/Quartal │ 1 │ 2 │ Scenario ║ ║ Churn Rate/Jahr │ 15% │ 6% │ PDF adoption ║ ║ NRR │ 105% │ 125% │ Scenario ║ ║ Pre-Seed │ 1,5M EUR │ 2,0M EUR │ PDF range ║ ║ Seed │ 4,0M EUR │ 6,0M EUR │ PDF range ║ ║ Series A │ 10M EUR │ 20M EUR │ Scenario ║ ║ Headcount M52 │ ~18-22 │ ~10-14 │ KI-Hebel-Effekt ║ ║ Events/Jahr │ 25.000 EUR │ 50.000 EUR │ PDF + ×2 ║ ║ KI-Personal-Hebel │ 0 Monate │ 99 Monate │ Maximaler Effekt║ ║ ARR-Schätzung M24 │ 200-400K │ 600K-1,2M │ Modellschätzung ║ ║ ARR-Schätzung M52 │ 500K-1M │ 5-10M │ Modellschätzung ║ ╚══════════════════════════════════════════════════════════════════════╝
A46: OFFENE PUNKTE (aus PDF Decision Register Part G)
A47: OFFENE PUNKTE AUS DEM PDF (Decision Register Part G): ───────────────────────────────────────────────────── G1.1 HIGH: Timeline-Varianten konsolidieren (Sept 2026 vs. April-Start) G1.3 HIGH: First-Paying-Customer-Timing final festlegen (kritischste Variable) G1.4 MED: Deployment-Standard (Cloud/On-Prem/Hybrid) → beeinflusst Kostenstruktur G1.7 MED: KI-Rollensubstitution quantifizieren (direkt auf Personalkosten) G2.2 HIGH: Conversion-Rate-Annahmen per Kanal definieren G2.3 HIGH: Customer-Success-Skalierungsmodell planen (identifizierter Engpass) G3.1 HIGH: Kausale CO₂-Wirkungskette präzise definieren G3.3 HIGH: Baseline für CO₂-Berechnungen festlegen

Sheet Entwicklungs_Roadmap
A1: LFL – Entwicklungs-Roadmap: Neue Treiber aus Treiber-Matrix (noch nicht modelliert)
A2: Kategorie | B2: Parameter / Treiber | C2: Mögliche Werte (G/N/S) | D2: Auswirkung | E2: Priorität | F2: Nächster Schritt
A3: SaaS-Pricing | B3: Produkt-Tiers (Basic/Pro/Enterprise) | C3: Basic ~5K€/J | Pro ~12K€/J | Ent ~25K€/J | D3: Höhere Preisflexibilität, bessere Marktabdeckung → ARR ↑ | E3: P1 HOCH | F3: Seat-Preis in Sandbox durch Tier-Verteilung ersetzen
A4: SaaS-Umsatz | B4: NRR-Varianten (bereits integriert!) | C4: Gering=105% | Normal=115% | Stark=130% | D4: ✓ In v6 implementiert — Sandbox Z.13 / Szenarien Z.9 | E4: ✓ ERLEDIGT | F4: —
A5: SaaS-Umsatz | B5: Churn-Varianten (bereits integriert!) | C5: Gering=10% | Normal=6% | Stark=3% | D5: ✓ In v6 implementiert — Sandbox Z.14 / Szenarien Z.10 | E5: ✓ ERLEDIGT | F5: —
A6: Marktexpansion | B6: Internationalisierung | C6: Keine | EU Y2 | US Y3 | D6: Multiplikator auf Kundenwachstum ab definiertem Monat → ARR ↑↑ | E6: P2 MITTEL | F6: Revenue: Multiplikator-Zeile ab Monat X; Inputs: Expansion-Startmonat
A7: Personal | B7: Gehaltsniveau-Faktor | C7: 85% | 100% | 115% des Markts | D7: Direkter Hebel auf gesamte Personalkostenbasis → EBITDA ± | E7: P2 MITTEL | F7: Inputs: Faktor auf alle Gehälter in Einstellungsplan
A8: Büro/Facilities | B8: Remote-Work-Strategie | C8: Office-First | Hybrid | Full-Remote | D8: Büromiete 0–4.500€/Monat → Burn Rate ↓ bei Remote | E8: P3 NIEDRIG | F8: Inputs: Büromiete durch Strategie-Faktor (0/0.5/1.0) steuern
A9: Technologie | B9: Technologie-Stack-Strategie | C9: Open-Source -40% | Proprietär | Multi-Provider +15% | D9: AI/ML-API-Kosten direkt → COGS Margin ± | E9: P2 MITTEL | F9: Sandbox: Stack-Faktor auf AI/ML APIs Basis
