Workbook

Sheet 0_Anleitung
A1: LoopForgeLab_Financial Projection Model: ANLEITUNG ZUM AUSFUELLEN DES BUSINESS MODELS
A2: Bearbeitungstand: | B2: =TODAY() -> 46096
A3: 1. SHEET-UEBERSICHT
A4: Sheet | B4: Funktion | C4: Editierbar? | D4: Abhaengigkeit
A5: 0_Anleitung | B5: Diese Anleitung | C5: Nein | D5: -
A6: 1_Szenario | B6: Dropdown: gering/normal/stark | C6: JA: nur C1 | D6: Keine (Quelle)
A7: Szenario_Beschreibung | B7: Szenario-Auswirkungen, dynamisch | C7: Nein | D7: 1_Szenario
A8: 2_Inputs | B8: Gehaelter, Kosten, Finanzierung, Hiring, Neukunden | C8: JA: blaue Zellen | D8: 1_Szenario
A9: 3_Roadmap | B9: Dashboard je Startup-Phase | C9: Nein | D9: 4_Rev, 5_Costs
A10: 4_Revenue | B10: 52-Mo Umsatz SME/Mid/Enterprise | C10: Nein | D10: 2_Inputs
A11: 5_Costs | B11: 52-Mo Kosten, 8 Kategorien, phasenabh. | C11: Nein | D11: 2_Inputs
A12: 6_P&L | B12: Gewinn- & Verlustrechnung | C12: Nein | D12: 4_Rev, 5_Costs
A13: 7_BS_CF | B13: Cashflow, Burn Rate, Runway | C13: Nein | D13: 6_P&L, 2_Inputs
A15: 2. SZENARIO EINSTELLEN (1_Szenario)
A16: Zelle C1 | B16: Dropdown: gering / normal / stark | C16: Aendert ALLE szenarioabh. Parameter
A17: Zeilen 3-22 | B17: Spalte C = aktiver Wert, E/F/G = alle 3 Szenarien
A18: Steuerbare Parameter:
A19: Seats/Kunde SME & Mid | B19: gering=3/8, normal=5/15, stark=10/25
A20: Seat-Preis SME & Mid | B20: 250 / 350 / 450 EUR pro Monat
A21: Enterprise Fee | B21: 18k / 25k / 40k EUR pro Jahr
A22: Impl.-Support | B22: Tagessatz, Tage/Kunde, Buchungsquote
A23: Retention/Preise | B23: NRR, Churn, Preiserhoehung/Jahr
A25: 3. MANUELLE EINGABEN IN 2_INPUTS
A26: Farbcode: | B26: BLAU = manuell aenderbar | C26: BLAU-BG = aus Szenario (NICHT aendern) | D26: GELB = Achtung
A27: Bereich | B27: Zeilen | C27: Inhalt | D27: Hinweis
A28: Allgemein | B28: Zeilen 2-7 | C28: Firma, Startdatum, Waehrung, Steuersatz | D28: Steuersatz = gelb
A29: Finanzierungsrunden | B29: Zeilen 8-16 | C29: Betraege & Monate: Ideation bis Series A | D29: -> Cash Flow (7_BS_CF)
A30: Business Angels | B30: 17-23 | C30: 3 Platzhalter (A/B/C): Betrag + Monat | D30: Monat=0 -> nicht aktiv
A31: Grants / Foerdermittel | B31: 24-30 | C31: 3 Platzhalter (A/B/C): Betrag + Monat | D31: Monat=0 -> nicht aktiv
A32: Revenue-Annahmen | B32: 32-40 | C32: Seats, Preise, Churn, Startmonat | D32: Blau-BG = Auto aus Szenario!
A33: Impl.-Support | B33: 42-46 | C33: Tagessatz, Tage, Quote, Startmonat | D33: Blau-BG = Auto aus Szenario!
A34: Gehaelter Gruender (Phasen) | B34: 47-69 | C34: CEO/CTO/CCO: AG-Brutto je Phase (5 Stufen) | D34: Ideation kann 0 EUR sein
A35: Gehaelter Mitarbeiter | B35: 71-84 | C35: AN-Brutto je Rolle + AG-Aufschlag (22%) | D35: Spalte C = AG-Brutto (autom.)
A36: Technologie | B36: 86-91 | C36: Cloud Hosting, AI/ML APIs, SaaS pro MA | D36: Blau = manuell
A37: SaaS Tools (Phasen) | B37: 92-97 | C37: SaaS-Lizenzen je Startup-Phase | D37: 5 Phasen-Werte
... A47: NEUKUNDEN-PLAN (!) | B47: 185-190 | C47: MANUELL: Neukunden je Monat & Groesse | D47: -> Direkt in 4_Revenue
A49: 4. WICHTIGE HINWEISE
A50: Alle Kosten in 5_Costs sind phasenabhaengig (Ideation/Pre-Seed/Seed/Series A/Series B) und werden ausschliesslich ueber 2_Inputs gesteuert. Im Costs-Blatt keine direkten Eingaben vornehmen!

Sheet 1_Szenario
B1: Aktives Szenario: hier einstellen → | C1: normal | E1: Gering | F1: Normal | G1: Stark
A2: Kategorie | B2: Parameter | C2: Aktiver Wert | D2: Einheit | E2: Gering | F2: Normal | G2: Stark
A3: Markt | B3: Anteil Packaging | C3: =IF($C$1="gering",E3,IF($C$1="normal",F3,G3)) -> 0.7 | D3: % | E3: 0.5 | F3: 0.7 | G3: 0.8
A4: Vertrieb | B4: Startmonat Kunden | C4: =IF($C$1="gering",E4,IF($C$1="normal",F4,G4)) -> 8 | D4: Monat | E4: 17 | F4: 8 | G4: 6
A5: Revenue | B5: Impl.-Support Tagessatz (€) | C5: =IF($C$1="gering",E5,IF($C$1="normal",F5,G5)) -> 1500 | D5: €/Tag | E5: 1500 | F5: 1500 | G5: 2500
A6: Revenue | B6: Impl.-Support Tage/Kunde | C6: =IF($C$1="gering",E6,IF($C$1="normal",F6,G6)) -> 20 | D6: Tage | E6: 10 | F6: 20 | G6: 30
A7: Revenue | B7: Impl.-Support Buchungsquote | C7: =IF($C$1="gering",E7,IF($C$1="normal",F7,G7)) -> 1 | D7: % | E7: 0.8 | F7: 1 | G7: 1
A8: Revenue | B8: Impl.-Support Startmonat | C8: =IF($C$1="gering",E8,IF($C$1="normal",F8,G8)) -> 6 | D8: Monat | E8: 10 | F8: 6 | G8: 5
A9: Retention | B9: Net Revenue Retention (NRR) | C9: =IF($C$1="gering",E9,IF($C$1="normal",F9,G9)) -> 1.15 | D9: % | E9: 1.15 | F9: 1.15 | G9: 1.3
A10: Retention | B10: Jährliche Churn Rate | C10: =IF($C$1="gering",E10,IF($C$1="normal",F10,G10)) -> 0.05 | D10: % | E10: 0.05 | F10: 0.05 | G10: 0.03
A11: Effizienz | B11: Iterations-Reduktion | C11: =IF($C$1="gering",E11,IF($C$1="normal",F11,G11)) -> 2,0x | D11: Faktor | E11: 1,2x | F11: 2,0x | G11: 3,0x
A12: Kosten | B12: Onboarding-Aufwand (Std.) | C12: =IF($C$1="gering",E12,IF($C$1="normal",F12,G12)) -> 60 | D12: Stunden | E12: 120 | F12: 60 | G12: 30
A13: Personal | B13: externe Experten als Untersützung (FTE-Plan) -->Puffer wenn benötigt | C13: =IF($C$1="gering",E13,IF($C$1="normal",F13,G13)) -> 0 | D13: FTE | E13: 0 | F13: 0 | G13: 0
A14: Revenue | B14: Impl.-Support Umsatz/Kunde | C14: =C5*C6 -> 30000 | D14: €/Kunde | E14: =E5*E6 -> 15000 | F14: =F5*F6 -> 30000 | G14: =G5*G6 -> 75000
A15: Revenue | B15: Seats/Kunde SME | C15: =IF($C$1="gering",E15,IF($C$1="normal",F15,G15)) -> 6 | D15: Seats | E15: 4 | F15: 6 | G15: 10
A16: Revenue | B16: Seats/Kunde Mid-Company | C16: =IF($C$1="gering",E16,IF($C$1="normal",F16,G16)) -> 12 | D16: Seats | E16: 8 | F16: 12 | G16: 15
A17: Revenue | B17: Seat-Preis SME (€/Monat) | C17: =IF($C$1="gering",E17,IF($C$1="normal",F17,G17)) -> 460 | D17: €/Monat | E17: 350 | F17: 460 | G17: 500
A18: Revenue | B18: Seat-Preis Mid-Company (€/Monat) | C18: =IF($C$1="gering",E18,IF($C$1="normal",F18,G18)) -> 530 | D18: €/Monat | E18: 450 | F18: 530 | G18: 550
A19: Revenue | B19: Enterprise Jahres-Fee (€/Jahr) | C19: =IF($C$1="gering",E19,IF($C$1="normal",F19,G19)) -> 50000 | D19: €/Jahr | E19: 30000 | F19: 50000 | G19: 45000
A20: Revenue | B20: Preiserhöhung/Jahr | C20: =IF($C$1="gering",E20,IF($C$1="normal",F20,G20)) -> 0.04 | D20: % | E20: 0.03 | F20: 0.04 | G20: 0.06

Sheet Szenario_Beschreibung
A1: SZENARIO-BESCHREIBUNG & AUSWIRKUNGSANALYSE
A3: 1. SZENARIO-VERGLEICH: PARAMETER & AUSWIRKUNGEN
A4: Parameter | B4: Gering | C4: Normal | D4: Stark | E4: Einfluss auf | F4: Beschreibung
A5: Seats/Kunde SME | B5: ='1_Szenario'!E15 -> 4 | C5: ='1_Szenario'!F15 -> 6 | D5: ='1_Szenario'!G15 -> 10 | E5: Revenue | F5: Weniger Seats = weniger MRR je Kunde. Typisch: 3-10 User für SME.
A6: Seats/Kunde Mid | B6: ='1_Szenario'!E16 -> 8 | C6: ='1_Szenario'!F16 -> 12 | D6: ='1_Szenario'!G16 -> 15 | E6: Revenue | F6: Mid-Market hat 3-5x mehr Seats als SME.
A7: Seat-Preis SME (€/Mo) | B7: ='1_Szenario'!E17 -> 350 | C7: ='1_Szenario'!F17 -> 460 | D7: ='1_Szenario'!G17 -> 500 | E7: Revenue, Margin | F7: Höherer Preis = mehr Umsatz, aber auch höhere Churn-Gefahr.
A8: Seat-Preis Mid (€/Mo) | B8: ='1_Szenario'!E18 -> 450 | C8: ='1_Szenario'!F18 -> 530 | D8: ='1_Szenario'!G18 -> 550 | E8: Revenue, Margin | F8: Mid-Companies zahlen höhere Preise für mehr Features.
A9: Enterprise Fee (€/Jahr) | B9: ='1_Szenario'!E19 -> 30000 | C9: ='1_Szenario'!F19 -> 50000 | D9: ='1_Szenario'!G19 -> 45000 | E9: Revenue, ARR | F9: Jahresverträge mit Custom-Pricing. Enterprise-ACV kann 47k€+ erreichen.
A10: Startmonat Kunden | B10: ='1_Szenario'!E4 -> 17 | C10: ='1_Szenario'!F4 -> 8 | D10: ='1_Szenario'!G4 -> 6 | E10: Revenue, Break-Even | F10: Späterer Start = länger kein Revenue = höherer Burn.
A11: Impl.-Support Tage/Kunde | B11: ='1_Szenario'!E6 -> 10 | C11: ='1_Szenario'!F6 -> 20 | D11: ='1_Szenario'!G6 -> 30 | E11: Revenue, Personal | F11: Mehr Tage = mehr Einmal-Revenue, aber auch mehr Personalaufwand.
A12: Buchungsquote | B12: ='1_Szenario'!E7 -> 0.8 | C12: ='1_Szenario'!F7 -> 1 | D12: ='1_Szenario'!G7 -> 1 | E12: Revenue | F12: Anteil Neukunden die Impl.-Support buchen.
A13: Churn Rate | B13: ='1_Szenario'!E10 -> 0.05 | C13: ='1_Szenario'!F10 -> 0.05 | D13: ='1_Szenario'!G10 -> 0.03 | E13: Revenue, LTV | F13: SME-Churn kann 15-30% p.a. erreichen, Enterprise liegt bei 5-8%.
A14: Preiserhöhung/Jahr | B14: ='1_Szenario'!E20 -> 0.03 | C14: ='1_Szenario'!F20 -> 0.04 | D14: ='1_Szenario'!G20 -> 0.06 | E14: Revenue, ARR | F14: SaaS-Preise steigen durchschnittlich 8-12% pro Jahr (2025).
A15: NRR | B15: ='1_Szenario'!E9 -> 1.15 | C15: ='1_Szenario'!F9 -> 1.15 | D15: ='1_Szenario'!G9 -> 1.3 | E15: Revenue, ARR | F15: Best-in-class NRR: SME 110-120%, Mid 120-130%, Enterprise 130-140%.
A17: 2. REVENUE-AUSWIRKUNG JE KUNDENSEGMENT (pro Kunde/Monat)
A18: KPI | B18: Gering | C18: Normal | D18: Stark | E18: Einheit | F18: Berechnung
A19: MRR je SME-Kunde | B19: ='1_Szenario'!E15*'1_Szenario'!E17 -> 1400 | C19: ='1_Szenario'!F15*'1_Szenario'!F17 -> 2760 | D19: ='1_Szenario'!G15*'1_Szenario'!G17 -> 5000 | E19: €/Monat | F19: Seats/Kunde × Seat-Preis
A20: ARR je SME-Kunde | B20: =B19*12 -> 16800 | C20: =C19*12 -> 33120 | D20: =D19*12 -> 60000 | E20: €/Jahr | F20: MRR × 12
A21: MRR je Mid-Kunde | B21: ='1_Szenario'!E16*'1_Szenario'!E18 -> 3600 | C21: ='1_Szenario'!F16*'1_Szenario'!F18 -> 6360 | D21: ='1_Szenario'!G16*'1_Szenario'!G18 -> 8250 | E21: €/Monat | F21: Seats/Kunde × Seat-Preis
A22: ARR je Mid-Kunde | B22: =B21*12 -> 43200 | C22: =C21*12 -> 76320 | D22: =D21*12 -> 99000 | E22: €/Jahr | F22: MRR × 12
A23: Revenue je Enterprise/Monat | B23: ='1_Szenario'!E19/12 -> 2500 | C23: ='1_Szenario'!F19/12 -> 4166.6667 | D23: ='1_Szenario'!G19/12 -> 3750 | E23: €/Monat | F23: Jahres-Fee / 12
A24: Impl.-Support je Neukunde | B24: ='1_Szenario'!E14 -> 15000 | C24: ='1_Szenario'!F14 -> 30000 | D24: ='1_Szenario'!G14 -> 75000 | E24: € (einmalig) | F24: Tagessatz × Tage (wenn gebucht)
A26: 3. SALES CYCLE & PIPELINE BENCHMARKS (Branchendaten)
A27: Segment | B27: Sales Cycle | C27: Close Rate | D27: Typischer ACV | E27: Churn Rate | F27: Quelle
A28: SME | B28: 14-30 Tage | C28: 15-25% | D28: <15k€/Jahr | E28: 15-30% p.a. | F28: Optifai 2025, Marketing LTB
A29: Mid-Market | B29: 30-90 Tage | C29: 15-25% | D29: 15-100k€/Jahr | E29: 5-15% p.a. | F29: Optifai 2025, DollarPocket
A30: Enterprise | B30: 90-180+ Tage | C30: 15-25% | D30: >100k€/Jahr | E30: 5-8% p.a. | F30: Optifai 2025, Marketing LTB
A32: 4. PIPELINE & ADDRESSABLE COMPANIES
A33: Um die Sales-Targets zu erreichen, müssen deutlich MEHR Unternehmen angesprochen werden als Neukunden geplant sind:
A34: Berechnung | B34: SME (Close Rate 20%) | C34: Mid (Close Rate 15%) | D34: Enterprise (Close Rate 10%) | E34: Formel | F34: Hinweis
A35: Für 1 Neukunde müssen angesprochen werden: | B35: 5 Unternehmen | C35: 7 Unternehmen | D35: 10 Unternehmen | E35: 1 / Close Rate | F35: Ohne Berücksichtigung Awareness-Phase
A37: 5. POTENZIELLE ENGPÄSSE & RISIKEN (Shortfalls)
A38: Risiko | B38: Gering (Worst Case) | C38: Normal (Base Case) | D38: Stark (Best Case) | E38: Mitigierung | F38: Quelle / Benchmark
A39: Personal für Entwicklung | B39: ='1_Szenario'!E13&" FTE" -> 0 FTE | C39: ='1_Szenario'!F13&" FTE" -> 0 FTE | D39: ='1_Szenario'!G13&" FTE" -> 0 FTE | E39: Frühzeitig Key Hires planen | F39: Median ARR/FTE: 125k€ (Vena 2024)
A40: Personal für Testing/QA | B40: Keine dediz. QA | C40: Dev + QA kombiniert | D40: Dedizierte QA-Rolle | E40: Testautomatisierung investieren | F40: SaaS-Standard ab Series A
A41: Implementation & Training | B41: ='1_Szenario'!E6&" Tage/Kunde, low-touch" -> 10 Tage/Kunde, low-touch | C41: ='1_Szenario'!F6&" Tage/Kunde, medium" -> 20 Tage/Kunde, medium | D41: ='1_Szenario'!G6&" Tage/Kunde, high-touch" -> 30 Tage/Kunde, high-touch | E41: Skalierbare Onboarding-Plattform | F41: Onboarding beeinflusst 75% der Churn
A42: Customer Success | B42: Kein CS-Team, Founder | C42: 1 CS ab M24 | D42: 2 CS-Manager | E42: CS reduziert Churn um 10-35% | F42: Marketing LTB 2025
A43: Sales Cycle Überlappung | B43: Ent. Deals: 6-18 Mo Vorlauf | C43: Mid: 1-3 Mo Vorlauf | D43: SME: 2-4 Wochen | E43: Pipeline 3x Target aufbauen | F43: Optifai 2025 (N=687)
A44: Lead-to-Close Verzögerung | B44: =_xludf.CONCAT("M",'1_Szenario'!E4," Start → Revenue erst M",'1_Szenario'!E4+2,"+") -> #NAME? | C44: =_xludf.CONCAT("M",'1_Szenario'!F4," Start → Revenue M",'1_Szenario'!F4+1,"+") -> #NAME? | D44: =_xludf.CONCAT("M",'1_Szenario'!G4," Start → Revenue M",'1_Szenario'!G4+1,"+") -> #NAME? | E44: Früh Marketing starten | F44: Sales Cycles +22% seit 2022
A45: Runway-Risiko | B45: Burn >50k€/Mo, Cash <12Mo | C45: Burn ∼100k€/Mo, Cash 18Mo | D45: Burn ∼150k€/Mo, Cash 24Mo+ | E45: Bridge-Finanzierung planen | F45: Break-Even abhängig von Wachstum
A46: Pipeline-Volumen SME | B46: Gering: wenig Leads nötig | C46: Für 5 Kunden/Mo: 25 Leads | D46: Für 10 Kunden/Mo: 50 Leads | E46: Content Marketing + SEO | F46: SEO = 30-60% SaaS Pipeline
A47: Pipeline-Volumen Enterprise | B47: Lange Zyklen, wenig Deals | C47: Für 1/Quartal: 10 Prospects | D47: Für 2/Quartal: 20 Prospects | E47: Events + Account-Based Marketing | F47: Median B2B Cycle: 84 Tage
A49: 6. BENCHMARKS & QUELLEN
A50: Metrik | B50: Benchmark | C50: Quelle | D50: URL
A51: Sales Cycle SME | B51: 14-30 Tage | C51: Optifai Benchmark 2025 | D51: https://optif.ai/learn/questions/sales-cycle-length-benchmark/
A52: Sales Cycle Mid-Market | B52: 30-90 Tage | C52: Optifai Benchmark 2025 | D52: https://optif.ai/learn/questions/sales-cycle-length-benchmark/
A53: Sales Cycle Enterprise | B53: 90-180+ Tage | C53: Optifai Benchmark 2025 | D53: https://optif.ai/learn/questions/sales-cycle-length-benchmark/
A54: Close Rate B2B SaaS | B54: 15-25% | C54: Marketing LTB 2025 | D54: https://marketingltb.com/blog/statistics/saas-statistics/
A55: SME SaaS Churn p.a. | B55: 15-30% | C55: Marketing LTB 2025 | D55: https://marketingltb.com/blog/statistics/saas-statistics/
A56: Enterprise SaaS Churn p.a. | B56: 5-8% | C56: Marketing LTB 2025 | D56: https://marketingltb.com/blog/statistics/saas-statistics/
A57: SaaS Median Seat-Preis | B57: 45€/User/Monat | C57: Monetizely SaaS Pricing 2025 | D57: https://www.getmonetizely.com/articles/saas-pricing-benchmark-study-2025-key-insights-from-100-companies-analyzed
A58: Enterprise ACV (<100 Seats) | B58: ∼47.000€ | C58: Monetizely SaaS Pricing 2025 | D58: https://www.getmonetizely.com/articles/saas-pricing-benchmark-study-2025-key-insights-from-100-companies-analyzed
A59: NRR Best-in-Class (Enterprise) | B59: 130-140%+ | C59: Marketing LTB 2025 | D59: https://marketingltb.com/blog/statistics/saas-statistics/
A60: SaaS Preiserhöhung/Jahr | B60: 8-12% | C60: Monetizely SaaS Pricing 2025 | D60: https://www.getmonetizely.com/articles/saas-pricing-benchmark-study-2025-key-insights-from-100-companies-analyzed

Sheet 2_Inputs
A1: ZENTRALE EINGABEWERTE | B1: Wert | C1: Einheit / Hinweis | D1: Quelle
A2: ALLGEMEIN
A3: Firmenname | B3: LoopforgeLab GmbH | C3: Name des Unternehmens
A4: Startdatum | B4: 46113 | C4: Beginn Projektionen
A5: Währung | B5: EUR
A6: Steuersatz | B6: 0.3 | C6: KSt + GewSt (~30%)
A8: FINANZIERUNGSRUNDEN
A9: Ideation Betrag | B9: 120000 | C9: € | D9: C13 funding + GmbH Stammeinlage
A10: Ideation Monat | B10: 4
A11: Pre-Seed Betrag | B11: 0 | C11: € | D11: no funding round but Angels
A12: Pre-Seed Monat | B12: 0
A13: Seed Betrag | B13: 2000000 | C13: €
A14: Seed Monat | B14: 17
A15: Series A Betrag | B15: 10000000 | C15: €
A16: Series A Monat | B16: 29
A17: BUSINESS ANGELS
A18: Business Angel A Betrag | B18: 200000 | C18: €
A19: Business Angel A Monat | B19: 4 | C19: 0 = nicht aktiv
A20: Business Angel B Betrag | B20: 200000 | C20: €
A21: Business Angel B Monat | B21: 5 | C21: 0 = nicht aktiv
A22: Business Angel C Betrag | B22: 200000 | C22: € | D22: probably 4 small Angels here
A23: Business Angel C Monat | B23: 8 | C23: 0 = nicht aktiv
A24: GRANTS / FÖRDERMITTEL
A25: Grant A Betrag | B25: 0 | C25: €
A26: Grant A Monat | B26: 0 | C26: 0 = nicht aktiv
A27: Grant B Betrag | B27: 0 | C27: €
A28: Grant B Monat | B28: 0 | C28: 0 = nicht aktiv
A29: Grant C Betrag | B29: 0 | C29: €
A30: Grant C Monat | B30: 0 | C30: 0 = nicht aktiv
A32: REVENUE-ANNAHMEN
A33: Seats/Kunde SME | B33: ='1_Szenario'!C15 -> 6 | C33: → Szenario
A34: Seats/Kunde Mid-Company | B34: ='1_Szenario'!C16 -> 12 | C34: → Szenario
A35: Seat-Preis SME (€/Monat) | B35: ='1_Szenario'!C17 -> 460 | C35: → Szenario
A36: Seat-Preis Mid-Company (€/Monat) | B36: ='1_Szenario'!C18 -> 530 | C36: → Szenario
A37: Enterprise Jahres-Fee (€/Jahr) | B37: ='1_Szenario'!C19 -> 50000 | C37: → Szenario
A38: Preiserhöhung/Jahr | B38: ='1_Szenario'!C20 -> 0.04 | C38: → Szenario
A39: Erste zahlende Kunden Monat | B39: ='1_Szenario'!C4 -> 8 | C39: → Szenario
A40: Churn Rate / Net Revenue Retention | B40: ='1_Szenario'!C10 -> 0.05 | C40: → Szenario
A42: IMPL.-SUPPORT
A43: Tagessatz (€/Tag) | B43: ='1_Szenario'!C5 -> 1500 | C43: → Szenario
A44: Tage/Kunde | B44: ='1_Szenario'!C6 -> 20 | C44: → Szenario
A45: Buchungsquote | B45: ='1_Szenario'!C7 -> 1 | C45: → Szenario
A46: Startmonat | B46: ='1_Szenario'!C8 -> 6 | C46: → Szenario
A47: GEHÄLTER & PERSONAL | B47: Arbeitsvertrag-Gehalt | C47: relevant for Business Case inkl. AG-SV, Umlagen, BG | D47: Schätzung (StKl 4, GKV)
A48: Rolle | B48: AN-Brutto (€/J) | C48: AG-Brutto (€/J) | D48: AN-Netto (€/J)
A49: CEO (Referenz Vollgehalt) | B49: 81967 | C49: 100000 | D49: 45082
A50: CTO (Referenz Vollgehalt) | B50: 81967 | C50: 100000 | D50: 45082
A51: CCO (Referenz Vollgehalt) | B51: 81967 | C51: 100000 | D51: 45082
A52: CEO – AG-Brutto je Phase (€/Jahr) | B52: AG-Brutto | C52: Monate
A53: Ideation (M1-4) | B53: 0 | C53: M1-M4
A54: Pre-Seed (M5-16) | B54: 100000 | C54: M5-M16
A55: Seed (M17-28) | B55: 100000 | C55: M17-M28
A56: Series A (M29-40) | B56: 100000 | C56: M29-M40
A57: Series B (M41-52) | B57: 120000 | C57: M41-M52
A58: CTO – AG-Brutto je Phase (€/Jahr) | B58: AG-Brutto | C58: Monate
A59: Ideation (M1-4) | B59: 0 | C59: M1-M4
A60: Pre-Seed (M5-16) | B60: 100000 | C60: M5-M16
A61: Seed (M17-28) | B61: 100000 | C61: M17-M28
A62: Series A (M29-40) | B62: 100000 | C62: M29-M40
A63: Series B (M41-52) | B63: 120000 | C63: M41-M52
A64: CCO – AG-Brutto je Phase (€/Jahr) | B64: AG-Brutto | C64: Monate
A65: Ideation (M1-4) | B65: 0 | C65: M1-M4
A66: Pre-Seed (M5-16) | B66: 100000 | C66: M5-M16
A67: Seed (M17-28) | B67: 100000 | C67: M17-M28
A68: Series A (M29-40) | B68: 100000 | C68: M29-M40
A69: Series B (M41-52) | B69: 120000 | C69: M41-M52
A71: Software Developer | B71: 75000 | C71: 91500 | D71: 41250
A72: Junior Developer | B72: 50000 | C72: 61000 | D72: 27500
A73: ML/AI Engineer | B73: 90000 | C73: 109800 | D73: 49500
A74: Mechanical Engineer | B74: 68000 | C74: 82960 | D74: 37400
A75: UX/UI Designer | B75: 50000 | C75: 61000 | D75: 27500
A76: Customer Key Account (incl fix/var) | B76: 78000 | C76: 95160 | D76: 42900
A77: Marketing Manager | B77: 52000 | C77: 63440 | D77: 28600
A78: Marketing Assistant | B78: 42000 | C78: 51240 | D78: 23100
A79: Office Manager | B79: 40000 | C79: 48800 | D79: 22000
A80: Customer Success | B80: 52000 | C80: 63440 | D80: 28600
A81: Finance Manager | B81: 80000 | C81: 97600 | D81: 44000
A82: Site Reliability Engineer (SRE) | B82: 90000 | C82: 109800 | D82: 49500
A83: Site Reliability Engineer (SRE) | B83: 90000 | C83: =ROUND(B83*(1+$B$85),0) -> 109800 | D83: =ROUND(B83*0.55,0) -> 49500
A84: Gehaltserhöhung p.a. | B84: 0.03
A85: AG-Aufschlag (SV+Umlagen+BG) | B85: 0.22 | C85: ~22% auf AN-Brutto
A87: TECHNOLOGIE & KOSTEN | D87: Bemerkungen | E87: Bemerkungen
A88: Cloud Hosting Basis SME (pro Seat) | B88: 90 | C88: €/Mo/Seat | D88: Cloudkosten je MA/Seat beim Kunden | E88: Siehe auch Dokument "LFL_Pricing.." Die Cloudkosten werden gegenüber dem Kunden nicht separat ausgewiesen sondern sind Teil der Kosten je Seat für den Kunden
A89: Cloud Hosting Basis Mid-Company (pro Seat) | B89: 90 | C89: €/Mo/Seat | D89: Cloudkosten je MA/Seat beim Kunden
A90: Cloud Hosting Basis Enterprise (pro Kunde) | B90: 450 | C90: €/Mo/Enterprise Kunde | D90: Cloudkosten für 5 Seats bei Enterprisekunden
A91: AI/ML APIs Basis (für LFL MA) Ideation (M1-4) | B91: 0 | C91: €/MA/Mo | D91: LLM-API-Kosten (Anthropic, OpenAI etc.) für Text-/Code-Generierung und Analyse, spezialisierte ML-Services wie Computer Vision, Speech-to-Text oder Embedding-Modelle für Vektorsuche, Infrastrukturkosten für Fine-Tuning oder RAG-Pipelines (Vektor-Datenbanken, Hosting), und Tooling-Lizenzen wie Claude Pro/Team-Subscriptions, GitHub Copilot oder ähnliches.
A92: AI/ML APIs Basis (für LFL MA) Pre-Seed (M5-16) | B92: 100 | C92: €/MA/Mo | D92: siehe Kostenaufstellung/ Dokument Claude
A93: AI/ML APIs Basis (für LFL MA) Seed (M17-28) | B93: 200 | C93: €/MA/Mo
A94: AI/ML APIs Basis (für LFL MA) Series A (M29-40) | B94: 250 | C94: €/MA/Mo
A95: AI/ML APIs Basis Series B (für LFL MA) (M41-52) | B95: 300 | C95: €/MA/Mo
A97: SaaS Tools & Lizenzen (€/Mo je Phase) | B97: €/Mo | C97: Monate
A98: Ideation (M1-4) | B98: 0 | C98: M1-M4
A99: Pre-Seed (M5-16) | B99: 400 | C99: M5-M16
A100: Seed (M17-28) | B100: 800 | C100: M17-M28
A101: Series A (M29-40) | B101: 1500 | C101: M29-M40
A102: Series B (M41-52) | B102: 2500 | C102: M41-M52
A104: Rechtsanwalt allgemein (€/Mo je Phase) | B104: €/Mo | C104: Monate
A105: Ideation (M1-4) | B105: 0 | C105: M1-M4
A106: Pre-Seed (M5-16) | B106: 500 | C106: M5-M16
A107: Seed (M17-28) | B107: 1000 | C107: M17-M28
...

Sheet 3_Roadmap
A1: BUSINESS ROADMAP & ÜBERSICHT
A3: 1. PRODUKTENTWICKLUNGSPHASEN
A4: Phase | B4: Zeitraum | C4: Monate | D4: Kernfeatures / Inhalte | E4: Meilensteine | G4: Bemerkungen Rene | H4: Bemerkungen Mouaz | I4: Bemerkungen Olaf
A5: Ideation | B5: M1–M4 | C5: 4 | D5: MVP-Konzept, Technologie-Stack, Marktvalidierung, IP-Aufbau | E5: MVP-Design abgeschlossen
A6: Pre-Seed | B6: M5–M16 | C6: 12 | D6: MVP-Entwicklung, Beta-Tests, erste Pilotkunden, DPP-Modul v1 | E6: Erster zahlender Kunde | G6: DPP Modul?
A7: Seed | B7: M17–M28 | C7: 12 | D7: Product-Market-Fit, Skalierung Vertrieb, Material-Analytics, Multi-Werk | E7: PMF validiert, >50 Kunden
A8: Series A | B8: M29–M40 | C8: 12 | D8: Internationale Expansion Central Europe, Enterprise-Features, API-Plattform | E8: ARR >1M€, Profitabilitätspfad
A9: Series B | B9: M41–M52 | C9: 12 | D9: Marktführerschaft, Konsolidierung, Premium-Analytics, AI-Plattform | E9: Marktführerschaft Nische
A11: 2. INVESTITIONSZEITPUNKTE & -HÖHEN
A12: Runde | B12: Monat | C12: Betrag (€) | D12: Kumuliert (€)
A13: Ideation | B13: ='2_Inputs'!B10 -> 4 | C13: ='2_Inputs'!B9 -> 120000 | D13: =C13 -> 120000
A14: Pre-Seed | B14: ='2_Inputs'!B12 -> 0 | C14: ='2_Inputs'!B11 -> 0 | D14: =D13+C14 -> 120000
A15: Seed | B15: ='2_Inputs'!B14 -> 17 | C15: ='2_Inputs'!B13 -> 2000000 | D15: =D14+C15 -> 2120000
A16: Series A | B16: ='2_Inputs'!B16 -> 29 | C16: ='2_Inputs'!B15 -> 10000000 | D16: =D15+C16 -> 12120000
A18: 3. UMSATZENTWICKLUNG & KUNDENGEWINNUNG (je Phase, kumuliert zum Phasenende)
A19: Kennzahl | B19: Ideation (M4) | C19: Pre-Seed (M16) | D19: Seed (M28) | E19: Series A (M40) | F19: Series B (M52)
A20: Neue SME-Kunden (kum.) | B20: =SUMPRODUCT('4_Revenue'!B5:E5) -> 0 | C20: =SUMPRODUCT('4_Revenue'!B5:Q5) -> 3 | D20: =SUMPRODUCT('4_Revenue'!B5:AC5) -> 13 | E20: =SUMPRODUCT('4_Revenue'!B5:AO5) -> 33 | F20: =SUMPRODUCT('4_Revenue'!B5:BA5) -> 93
A21: Neue Mid-Company-Kunden (kum.) | B21: =SUMPRODUCT('4_Revenue'!B12:E12) -> 0 | C21: =SUMPRODUCT('4_Revenue'!B12:Q12) -> 0 | D21: =SUMPRODUCT('4_Revenue'!B12:AC12) -> 15 | E21: =SUMPRODUCT('4_Revenue'!B12:AO12) -> 45 | F21: =SUMPRODUCT('4_Revenue'!B12:BA12) -> 95
A22: Neue Enterprise-Kunden (kum.) | B22: =SUMPRODUCT('4_Revenue'!B19:E19) -> 0 | C22: =SUMPRODUCT('4_Revenue'!B19:Q19) -> 0 | D22: =SUMPRODUCT('4_Revenue'!B19:AC19) -> 2 | E22: =SUMPRODUCT('4_Revenue'!B19:AO19) -> 5 | F22: =SUMPRODUCT('4_Revenue'!B19:BA19) -> 11
A23: Total Active Seats (SME+Mid) | B23: ='4_Revenue'!E8+'4_Revenue'!E15 -> 0 | C23: ='4_Revenue'!Q8+'4_Revenue'!Q15 -> 18 | D23: ='4_Revenue'!AC8+'4_Revenue'!AC15 -> 254 | E23: ='4_Revenue'!AO8+'4_Revenue'!AO15 -> 710 | F23: ='4_Revenue'!BA8+'4_Revenue'!BA15 -> 1614
A24: MRR zum Phasenende (€) | B24: ='4_Revenue'!E25 -> 0 | C24: ='4_Revenue'!Q25 -> 8611.2 | D24: ='4_Revenue'!AC25 -> 148712.79 | E24: ='4_Revenue'!AO25 -> 431681.56 | F24: ='4_Revenue'!BA25 -> 1010609.6
A26: 4. KOSTENPOSITIONEN NACH OBERTHEMEN (monatl. Durchschnitt je Phase)
A27: Kostenposition | B27: Ideation | C27: Pre-Seed | D27: Seed | E27: Series A | F27: Series B
A28: Personal | B28: =AVERAGE('5_Costs'!B13:E13) -> 0 | C28: =AVERAGE('5_Costs'!F13:Q13) -> 42980.108 | D28: =AVERAGE('5_Costs'!R13:AC13) -> 86826.037 | E28: =AVERAGE('5_Costs'!AD13:AO13) -> 106374.32 | F28: =AVERAGE('5_Costs'!AP13:BA13) -> 113786.18
A29: Technologie (IT) | B29: =AVERAGE('5_Costs'!B18:E18) -> 0 | C29: =AVERAGE('5_Costs'!F18:Q18) -> 1850 | D29: =AVERAGE('5_Costs'!R18:AC18) -> 16948.333 | E29: =AVERAGE('5_Costs'!AD18:AO18) -> 49542.5 | F29: =AVERAGE('5_Costs'!AP18:BA18) -> 117542.5
A30: Bürokosten | B30: =AVERAGE('5_Costs'!B24:E24) -> 0 | C30: =AVERAGE('5_Costs'!F24:Q24) -> 1133.3333 | D30: =AVERAGE('5_Costs'!R24:AC24) -> 4040 | E30: =AVERAGE('5_Costs'!AD24:AO24) -> 5040 | F30: =AVERAGE('5_Costs'!AP24:BA24) -> 5040
A31: Professional Services | B31: =AVERAGE('5_Costs'!B30:E30) -> 0 | C31: =AVERAGE('5_Costs'!F30:Q30) -> 1100 | D31: =AVERAGE('5_Costs'!R30:AC30) -> 6766.6667 | E31: =AVERAGE('5_Costs'!AD30:AO30) -> 14033.333 | F31: =AVERAGE('5_Costs'!AP30:BA30) -> 15333.333
A32: Versicherung & Bank | B32: =AVERAGE('5_Costs'!B35:E35) -> 92 | C32: =AVERAGE('5_Costs'!F35:Q35) -> 750 | D32: =AVERAGE('5_Costs'!R35:AC35) -> 1150 | E32: =AVERAGE('5_Costs'!AD35:AO35) -> 1500 | F32: =AVERAGE('5_Costs'!AP35:BA35) -> 1850
A33: Marketing & Sales | B33: =AVERAGE('5_Costs'!B40:E40) -> 1633.3333 | C33: =AVERAGE('5_Costs'!F40:Q40) -> 3227.5413 | D33: =AVERAGE('5_Costs'!R40:AC40) -> 7723.8174 | E33: =AVERAGE('5_Costs'!AD40:AO40) -> 18084.773 | F33: =AVERAGE('5_Costs'!AP40:BA40) -> 32006.948
A34: Sonstige Kosten | B34: =AVERAGE('5_Costs'!B45:E45) -> 350 | C34: =AVERAGE('5_Costs'!F45:Q45) -> 1733.3333 | D34: =AVERAGE('5_Costs'!R45:AC45) -> 3791.6667 | E34: =AVERAGE('5_Costs'!AD45:AO45) -> 6150 | F34: =AVERAGE('5_Costs'!AP45:BA45) -> 8400
A35: Payment Processing | B35: =AVERAGE('5_Costs'!B48:E48) -> 0 | C35: =AVERAGE('5_Costs'!F48:Q48) -> 117.76 | D35: =AVERAGE('5_Costs'!R48:AC48) -> 2092.2717 | E35: =AVERAGE('5_Costs'!AD48:AO48) -> 7126.7997 | F35: =AVERAGE('5_Costs'!AP48:BA48) -> 18279.518
A36: TOTAL (Ø/Monat) | B36: =SUM(B28:B35) -> 2075.3333 | C36: =SUM(C28:C35) -> 52892.076 | D36: =SUM(D28:D35) -> 129338.79 | E36: =SUM(E28:E35) -> 207851.73 | F36: =SUM(F28:F35) -> 312238.48

Sheet 4_Revenue
A1: UMSATZMODELL | AP1: Series B not modelled yet | AR1: `-->
A2: Monat | B2: M1 | C2: M2 | D2: M3 | E2: M4 | F2: M5 | G2: M6 | H2: M7 | I2: M8 | J2: M9 | K2: M10 | L2: M11 | M2: M12 | N2: M13 | O2: M14 | P2: M15 | Q2: M16 | R2: M17 | S2: M18 | T2: M19 | U2: M20 | V2: M21 | W2: M22 | X2: M23 | Y2: M24 | Z2: M25 | AA2: M26 | AB2: M27 | AC2: M28 | AD2: M29 | AE2: M30 | AF2: M31 | AG2: M32 | AH2: M33 | AI2: M34 | AJ2: M35 | AK2: M36 | AL2: M37 | AM2: M38 | AN2: M39 | AO2: M40 | AP2: M41 | AQ2: M42 | AR2: M43 | AS2: M44 | AT2: M45 | AU2: M46 | AV2: M47 | AW2: M48 | AX2: M49 | AY2: M50 | AZ2: M51 | BA2: M52
A3: Startup-Phasen | B3: Ideation | C3: Ideation | D3: Ideation | E3: Ideation | F3: Pre-Seed | G3: Pre-Seed | H3: Pre-Seed | I3: Pre-Seed | J3: Pre-Seed | K3: Pre-Seed | L3: Pre-Seed | M3: Pre-Seed | N3: Pre-Seed | O3: Pre-Seed | P3: Pre-Seed | Q3: Pre-Seed | R3: Seed | S3: Seed | T3: Seed | U3: Seed | V3: Seed | W3: Seed | X3: Seed | Y3: Seed | Z3: Seed | AA3: Seed | AB3: Seed | AC3: Seed | AD3: Series A | AE3: Series A | AF3: Series A | AG3: Series A | AH3: Series A | AI3: Series A | AJ3: Series A | AK3: Series A | AL3: Series A | AM3: Series A | AN3: Series A | AO3: Series A | AP3: Series B | AQ3: Series B | AR3: Series B | AS3: Series B | AT3: Series B | AU3: Series B | AV3: Series B | AW3: Series B | AX3: Series B | AY3: Series B | AZ3: Series B | BA3: Series B
A4: ── SME KUNDEN (Seat-Modell) ──
A5: Neue SME-Kunden | B5: ='2_Inputs'!B217 -> 0 | C5: ='2_Inputs'!C217 -> 0 | D5: ='2_Inputs'!D217 -> 0 | E5: ='2_Inputs'!E217 -> 0 | F5: ='2_Inputs'!F217 -> 0 | G5: ='2_Inputs'!G217 -> 0 | H5: ='2_Inputs'!H217 -> 1 | I5: ='2_Inputs'!I217 -> 0 | ... BA5: ='2_Inputs'!BA217 -> 5
A6: Neue SME-Seats | B6: =B5*'2_Inputs'!$B$33 -> 0 | C6: =C5*'2_Inputs'!$B$33 -> 0 | D6: =D5*'2_Inputs'!$B$33 -> 0 | E6: =E5*'2_Inputs'!$B$33 -> 0 | F6: =F5*'2_Inputs'!$B$33 -> 0 | G6: =G5*'2_Inputs'!$B$33 -> 0 | H6: =H5*'2_Inputs'!$B$33 -> 6 | I6: =I5*'2_Inputs'!$B$33 -> 0 | ... BA6: =BA5*'2_Inputs'!$B$33 -> 30
A7: Churned SME-Seats | B7: =0 -> 0 | C7: =-ROUND(B8*'2_Inputs'!$B$40/12,0) -> 0 | D7: =-ROUND(C8*'2_Inputs'!$B$40/12,0) -> 0 | E7: =-ROUND(D8*'2_Inputs'!$B$40/12,0) -> 0 | F7: =-ROUND(E8*'2_Inputs'!$B$40/12,0) -> 0 | G7: =-ROUND(F8*'2_Inputs'!$B$40/12,0) -> 0 | H7: =-ROUND(G8*'2_Inputs'!$B$40/12,0) -> 0 | I7: =-ROUND(H8*'2_Inputs'!$B$40/12,0) -> 0 | J7: =-ROUND(I8*'2_Inputs'!$B$40/12,0) -> 0 | ... BA7: =-ROUND(AZ8*'2_Inputs'!$B$40/12,0) -> -2
A8: Active SME-Seats (kum.) | B8: =B6 -> 0 | C8: =B8+C6+C7 -> 0 | D8: =C8+D6+D7 -> 0 | E8: =D8+E6+E7 -> 0 | F8: =E8+F6+F7 -> 0 | G8: =F8+G6+G7 -> 0 | H8: =G8+H6+H7 -> 6 | I8: =H8+I6+I7 -> 6 | J8: =I8+J6+J7 -> 6 | ... BA8: =AZ8+BA6+BA7 -> 534
A9: SME Seat-Preis (€/Monat) | B9: ='2_Inputs'!$B$35*(1+'2_Inputs'!$B$38)^INT((COLUMN()-2)/12) -> 460 | C9: ='2_Inputs'!$B$35*(1+'2_Inputs'!$B$38)^INT((COLUMN()-2)/12) -> 460 | D9: ='2_Inputs'!$B$35*(1+'2_Inputs'!$B$38)^INT((COLUMN()-2)/12) -> 460 | E9: ='2_Inputs'!$B$35*(1+'2_Inputs'!$B$38)^INT((COLUMN()-2)/12) -> 460 | F9: ='2_Inputs'!$B$35*(1+'2_Inputs'!$B$38)^INT((COLUMN()-2)/12) -> 460 | G9: ='2_Inputs'!$B$35*(1+'2_Inputs'!$B$38)^INT((COLUMN()-2)/12) -> 460 | H9: ='2_Inputs'!$B$35*(1+'2_Inputs'!$B$38)^INT((COLUMN()-2)/12) -> 460 | I9: ='2_Inputs'!$B$35*(1+'2_Inputs'!$B$38)^INT((COLUMN()-2)/12) -> 460 | ... BA9: ='2_Inputs'!$B$35*(1+'2_Inputs'!$B$38)^INT((COLUMN()-2)/12) -> 538.13494
A10: SME Monthly Revenue (€) | B10: =B8*B9 -> 0 | C10: =C8*C9 -> 0 | D10: =D8*D9 -> 0 | E10: =E8*E9 -> 0 | F10: =F8*F9 -> 0 | G10: =G8*G9 -> 0 | H10: =H8*H9 -> 2760 | I10: =I8*I9 -> 2760 | ... BA10: =BA8*BA9 -> 287364.06
A11: ── MID-COMPANY KUNDEN (Seat-Modell) ──
A12: Neue Mid-Company-Kunden | B12: ='2_Inputs'!B218 -> 0 | C12: ='2_Inputs'!C218 -> 0 | D12: ='2_Inputs'!D218 -> 0 | E12: ='2_Inputs'!E218 -> 0 | F12: ='2_Inputs'!F218 -> 0 | G12: ='2_Inputs'!G218 -> 0 | H12: ='2_Inputs'!H218 -> 0 | I12: ='2_Inputs'!I218 -> 0 | ... BA12: ='2_Inputs'!BA218 -> 5
A13: Neue Mid-Seats | B13: =B12*'2_Inputs'!$B$34 -> 0 | C13: =C12*'2_Inputs'!$B$34 -> 0 | D13: =D12*'2_Inputs'!$B$34 -> 0 | E13: =E12*'2_Inputs'!$B$34 -> 0 | F13: =F12*'2_Inputs'!$B$34 -> 0 | G13: =G12*'2_Inputs'!$B$34 -> 0 | H13: =H12*'2_Inputs'!$B$34 -> 0 | I13: =I12*'2_Inputs'!$B$34 -> 0 | ... BA13: =BA12*'2_Inputs'!$B$34 -> 60
A14: Churned Mid-Seats | B14: =0 -> 0 | C14: =-ROUND(B15*'2_Inputs'!$B$40/12,0) -> 0 | D14: =-ROUND(C15*'2_Inputs'!$B$40/12,0) -> 0 | E14: =-ROUND(D15*'2_Inputs'!$B$40/12,0) -> 0 | F14: =-ROUND(E15*'2_Inputs'!$B$40/12,0) -> 0 | G14: =-ROUND(F15*'2_Inputs'!$B$40/12,0) -> 0 | H14: =-ROUND(G15*'2_Inputs'!$B$40/12,0) -> 0 | I14: =-ROUND(H15*'2_Inputs'!$B$40/12,0) -> 0 | J14: =-ROUND(I15*'2_Inputs'!$B$40/12,0) -> 0 | ... BA14: =-ROUND(AZ15*'2_Inputs'!$B$40/12,0) -> -4
A15: Active Mid-Seats (kum.) | B15: =B13 -> 0 | C15: =B15+C13+C14 -> 0 | D15: =C15+D13+D14 -> 0 | E15: =D15+E13+E14 -> 0 | F15: =E15+F13+F14 -> 0 | G15: =F15+G13+G14 -> 0 | H15: =G15+H13+H14 -> 0 | I15: =H15+I13+I14 -> 0 | J15: =I15+J13+J14 -> 0 | ... BA15: =AZ15+BA13+BA14 -> 1080
A16: Mid Seat-Preis (€/Monat) | B16: ='2_Inputs'!$B$36*(1+'2_Inputs'!$B$38)^INT((COLUMN()-2)/12) -> 530 | C16: ='2_Inputs'!$B$36*(1+'2_Inputs'!$B$38)^INT((COLUMN()-2)/12) -> 530 | D16: ='2_Inputs'!$B$36*(1+'2_Inputs'!$B$38)^INT((COLUMN()-2)/12) -> 530 | E16: ='2_Inputs'!$B$36*(1+'2_Inputs'!$B$38)^INT((COLUMN()-2)/12) -> 530 | F16: ='2_Inputs'!$B$36*(1+'2_Inputs'!$B$38)^INT((COLUMN()-2)/12) -> 530 | G16: ='2_Inputs'!$B$36*(1+'2_Inputs'!$B$38)^INT((COLUMN()-2)/12) -> 530 | H16: ='2_Inputs'!$B$36*(1+'2_Inputs'!$B$38)^INT((COLUMN()-2)/12) -> 530 | I16: ='2_Inputs'!$B$36*(1+'2_Inputs'!$B$38)^INT((COLUMN()-2)/12) -> 530 | ... BA16: ='2_Inputs'!$B$36*(1+'2_Inputs'!$B$38)^INT((COLUMN()-2)/12) -> 620.02504
A17: Mid Monthly Revenue (€) | B17: =B15*B16 -> 0 | C17: =C15*C16 -> 0 | D17: =D15*D16 -> 0 | E17: =E15*E16 -> 0 | F17: =F15*F16 -> 0 | G17: =G15*G16 -> 0 | H17: =H15*H16 -> 0 | I17: =I15*I16 -> 0 | ... BA17: =BA15*BA16 -> 669627.04
A18: ── ENTERPRISE (Jahres-Fee) ──
A19: Neue Enterprise-Kunden | B19: ='2_Inputs'!B219 -> 0 | C19: ='2_Inputs'!C219 -> 0 | D19: ='2_Inputs'!D219 -> 0 | E19: ='2_Inputs'!E219 -> 0 | F19: ='2_Inputs'!F219 -> 0 | G19: ='2_Inputs'!G219 -> 0 | H19: ='2_Inputs'!H219 -> 0 | I19: ='2_Inputs'!I219 -> 0 | ... BA19: ='2_Inputs'!BA219 -> 0
A20: Churned Enterprise | B20: =0 -> 0 | C20: =-ROUND(B21*'2_Inputs'!$B$40/12,0) -> 0 | D20: =-ROUND(C21*'2_Inputs'!$B$40/12,0) -> 0 | E20: =-ROUND(D21*'2_Inputs'!$B$40/12,0) -> 0 | F20: =-ROUND(E21*'2_Inputs'!$B$40/12,0) -> 0 | G20: =-ROUND(F21*'2_Inputs'!$B$40/12,0) -> 0 | H20: =-ROUND(G21*'2_Inputs'!$B$40/12,0) -> 0 | I20: =-ROUND(H21*'2_Inputs'!$B$40/12,0) -> 0 | J20: =-ROUND(I21*'2_Inputs'!$B$40/12,0) -> 0 | ... BA20: =-ROUND(AZ21*'2_Inputs'!$B$40/12,0) -> 0
A21: Active Enterprise (kum.) | B21: =B19 -> 0 | C21: =B21+C19+C20 -> 0 | D21: =C21+D19+D20 -> 0 | E21: =D21+E19+E20 -> 0 | F21: =E21+F19+F20 -> 0 | G21: =F21+G19+G20 -> 0 | H21: =G21+H19+H20 -> 0 | I21: =H21+I19+I20 -> 0 | J21: =I21+J19+J20 -> 0 | ... BA21: =AZ21+BA19+BA20 -> 11
A22: Enterprise Fee/Monat (€) | B22: ='2_Inputs'!$B$37*(1+'2_Inputs'!$B$38)^INT((COLUMN()-2)/12)/12 -> 4166.6667 | C22: ='2_Inputs'!$B$37*(1+'2_Inputs'!$B$38)^INT((COLUMN()-2)/12)/12 -> 4166.6667 | D22: ='2_Inputs'!$B$37*(1+'2_Inputs'!$B$38)^INT((COLUMN()-2)/12)/12 -> 4166.6667 | E22: ='2_Inputs'!$B$37*(1+'2_Inputs'!$B$38)^INT((COLUMN()-2)/12)/12 -> 4166.6667 | F22: ='2_Inputs'!$B$37*(1+'2_Inputs'!$B$38)^INT((COLUMN()-2)/12)/12 -> 4166.6667 | G22: ='2_Inputs'!$B$37*(1+'2_Inputs'!$B$38)^INT((COLUMN()-2)/12)/12 -> 4166.6667 | H22: ='2_Inputs'!$B$37*(1+'2_Inputs'!$B$38)^INT((COLUMN()-2)/12)/12 -> 4166.6667 | I22: ='2_Inputs'!$B$37*(1+'2_Inputs'!$B$38)^INT((COLUMN()-2)/12)/12 -> 4166.6667 | ... BA22: ='2_Inputs'!$B$37*(1+'2_Inputs'!$B$38)^INT((COLUMN()-2)/12)/12 -> 4874.4107
A23: Enterprise Monthly Revenue (€) | B23: =B21*B22 -> 0 | C23: =C21*C22 -> 0 | D23: =D21*D22 -> 0 | E23: =E21*E22 -> 0 | F23: =F21*F22 -> 0 | G23: =G21*G22 -> 0 | H23: =H21*H22 -> 0 | I23: =I21*I22 -> 0 | ... BA23: =BA21*BA22 -> 53618.517
A24: ── TOTAL RECURRING REVENUE ──
A25: MRR – Monthly Recurring Revenue | B25: =B10+B17+B23 -> 0 | C25: =C10+C17+C23 -> 0 | D25: =D10+D17+D23 -> 0 | E25: =E10+E17+E23 -> 0 | F25: =F10+F17+F23 -> 0 | G25: =G10+G17+G23 -> 0 | H25: =H10+H17+H23 -> 2760 | I25: =I10+I17+I23 -> 2760 | ... BA25: =BA10+BA17+BA23 -> 1010609.6
A26: ARR – Annual Recurring Revenue | B26: =B25*12 -> 0 | C26: =C25*12 -> 0 | D26: =D25*12 -> 0 | E26: =E25*12 -> 0 | F26: =F25*12 -> 0 | G26: =G25*12 -> 0 | H26: =H25*12 -> 33120 | I26: =I25*12 -> 33120 | ... BA26: =BA25*12 -> 12127315
A27: ── IMPLEMENTATION-SUPPORT ──
A28: Neue Kunden im Monat (gesamt) | B28: =B5+B12+B19 -> 0 | C28: =C5+C12+C19 -> 0 | D28: =D5+D12+D19 -> 0 | E28: =E5+E12+E19 -> 0 | F28: =F5+F12+F19 -> 0 | G28: =G5+G12+G19 -> 0 | H28: =H5+H12+H19 -> 1 | I28: =I5+I12+I19 -> 0 | ... BA28: =BA5+BA12+BA19 -> 10
A29: Impl.-Support Tage/Monat | B29: =IF(COLUMN()-1>='2_Inputs'!$B$46,B28*'2_Inputs'!$B$45*'2_Inputs'!$B$44,0) -> 0 | C29: =IF(COLUMN()-1>='2_Inputs'!$B$46,C28*'2_Inputs'!$B$45*'2_Inputs'!$B$44,0) -> 0 | D29: =IF(COLUMN()-1>='2_Inputs'!$B$46,D28*'2_Inputs'!$B$45*'2_Inputs'!$B$44,0) -> 0 | E29: =IF(COLUMN()-1>='2_Inputs'!$B$46,E28*'2_Inputs'!$B$45*'2_Inputs'!$B$44,0) -> 0 | F29: =IF(COLUMN()-1>='2_Inputs'!$B$46,F28*'2_Inputs'!$B$45*'2_Inputs'!$B$44,0) -> 0 | G29: =IF(COLUMN()-1>='2_Inputs'!$B$46,G28*'2_Inputs'!$B$45*'2_Inputs'!$B$44,0) -> 0 | H29: =IF(COLUMN()-1>='2_Inputs'!$B$46,H28*'2_Inputs'!$B$45*'2_Inputs'!$B$44,0) -> 20 | I29: =IF(COLUMN()-1>='2_Inputs'!$B$46,I28*'2_Inputs'!$B$45*'2_Inputs'!$B$44,0) -> 0 | ... BA29: =IF(COLUMN()-1>='2_Inputs'!$B$46,BA28*'2_Inputs'!$B$45*'2_Inputs'!$B$44,0) -> 200
A30: Impl.-Support Revenue (€/Monat) | B30: =B29*'2_Inputs'!$B$43 -> 0 | C30: =C29*'2_Inputs'!$B$43 -> 0 | D30: =D29*'2_Inputs'!$B$43 -> 0 | E30: =E29*'2_Inputs'!$B$43 -> 0 | F30: =F29*'2_Inputs'!$B$43 -> 0 | G30: =G29*'2_Inputs'!$B$43 -> 0 | H30: =H29*'2_Inputs'!$B$43 -> 30000 | I30: =I29*'2_Inputs'!$B$43 -> 0 | ... BA30: =BA29*'2_Inputs'!$B$43 -> 300000
A31: ── TOTAL MONTHLY REVENUE ──
A32: Total Revenue (€/Monat) | B32: =B25+B30 -> 0 | C32: =C25+C30 -> 0 | D32: =D25+D30 -> 0 | E32: =E25+E30 -> 0 | F32: =F25+F30 -> 0 | G32: =G25+G30 -> 0 | H32: =H25+H30 -> 32760 | I32: =I25+I30 -> 2760 | ... BA32: =BA25+BA30 -> 1310609.6
A33: ARR Growth % (MoM) | B33: =IFERROR((B25-0)/1,0) -> 0 | C33: =IFERROR((C25-B25)/B25,0) -> 0 | D33: =IFERROR((D25-C25)/C25,0) -> 0 | E33: =IFERROR((E25-D25)/D25,0) -> 0 | F33: =IFERROR((F25-E25)/E25,0) -> 0 | G33: =IFERROR((G25-F25)/F25,0) -> 0 | H33: =IFERROR((H25-G25)/G25,0) -> 0 | I33: =IFERROR((I25-H25)/H25,0) -> 0 | J33: =IFERROR((J25-I25)/I25,0) -> 0 | ... BA33: =IFERROR((BA25-AZ25)/AZ25,0) -> 0.051819444
A34: ARR Total (inkl. Impl.-Support) | B34: =B32*12 -> 0 | C34: =C32*12 -> 0 | D34: =D32*12 -> 0 | E34: =E32*12 -> 0 | F34: =F32*12 -> 0 | G34: =G32*12 -> 0 | H34: =H32*12 -> 393120 | I34: =I32*12 -> 33120 | ... BA34: =BA32*12 -> 15727315

Sheet 5_Costs
A1: KOSTENDETAILS | AP1: Series B not modelled yet | AR1: `-->
A2: Monat | B2: M1 | C2: M2 | D2: M3 | E2: M4 | F2: M5 | G2: M6 | H2: M7 | I2: M8 | J2: M9 | K2: M10 | L2: M11 | M2: M12 | N2: M13 | O2: M14 | P2: M15 | Q2: M16 | R2: M17 | S2: M18 | T2: M19 | U2: M20 | V2: M21 | W2: M22 | X2: M23 | Y2: M24 | Z2: M25 | AA2: M26 | AB2: M27 | AC2: M28 | AD2: M29 | AE2: M30 | AF2: M31 | AG2: M32 | AH2: M33 | AI2: M34 | AJ2: M35 | AK2: M36 | AL2: M37 | AM2: M38 | AN2: M39 | AO2: M40 | AP2: M41 | AQ2: M42 | AR2: M43 | AS2: M44 | AT2: M45 | AU2: M46 | AV2: M47 | AW2: M48 | AX2: M49 | AY2: M50 | AZ2: M51 | BA2: M52
A3: Startup-Phasen | B3: Ideation | C3: Ideation | D3: Ideation | E3: Ideation | F3: Pre-Seed | G3: Pre-Seed | H3: Pre-Seed | I3: Pre-Seed | J3: Pre-Seed | K3: Pre-Seed | L3: Pre-Seed | M3: Pre-Seed | N3: Pre-Seed | O3: Pre-Seed | P3: Pre-Seed | Q3: Pre-Seed | R3: Seed | S3: Seed | T3: Seed | U3: Seed | V3: Seed | W3: Seed | X3: Seed | Y3: Seed | Z3: Seed | AA3: Seed | AB3: Seed | AC3: Seed | AD3: Series A | AE3: Series A | AF3: Series A | AG3: Series A | AH3: Series A | AI3: Series A | AJ3: Series A | AK3: Series A | AL3: Series A | AM3: Series A | AN3: Series A | AO3: Series A | AP3: Series B | AQ3: Series B | AR3: Series B | AS3: Series B | AT3: Series B | AU3: Series B | AV3: Series B | AW3: Series B | AX3: Series B | AY3: Series B | AZ3: Series B | BA3: Series B
A4: Kostenposition | B4: M1 | C4: M2 | D4: M3 | E4: M4 | F4: M5 | G4: M6 | H4: M7 | I4: M8 | J4: M9 | K4: M10 | L4: M11 | M4: M12 | N4: M13 | O4: M14 | P4: M15 | Q4: M16 | R4: M17 | S4: M18 | T4: M19 | U4: M20 | V4: M21 | W4: M22 | X4: M23 | Y4: M24 | Z4: M25 | AA4: M26 | AB4: M27 | AC4: M28 | AD4: M29 | AE4: M30 | AF4: M31 | AG4: M32 | AH4: M33 | AI4: M34 | AJ4: M35 | AK4: M36 | AL4: M37 | AM4: M38 | AN4: M39 | AO4: M40 | AP4: M41 | AQ4: M42 | AR4: M43 | AS4: M44 | AT4: M45 | AU4: M46 | AV4: M47 | AW4: M48 | AX4: M49 | AY4: M50 | AZ4: M51 | BA4: M52
A5: ── PERSONAL ──
A6: CEO | B6: =IF(COLUMN()-1<=4,'2_Inputs'!$B$53,IF(COLUMN()-1<=16,'2_Inputs'!$B$54,IF(COLUMN()-1<=28,'2_Inputs'!$B$55,IF(COLUMN()-1<=40,'2_Inputs'!$B$56,'2_Inputs'!$B$57))))/12 -> 0 | C6: =IF(COLUMN()-1<=4,'2_Inputs'!$B$53,IF(COLUMN()-1<=16,'2_Inputs'!$B$54,IF(COLUMN()-1<=28,'2_Inputs'!$B$55,IF(COLUMN()-1<=40,'2_Inputs'!$B$56,'2_Inputs'!$B$57))))/12 -> 0 | D6: =IF(COLUMN()-1<=4,'2_Inputs'!$B$53,IF(COLUMN()-1<=16,'2_Inputs'!$B$54,IF(COLUMN()-1<=28,'2_Inputs'!$B$55,IF(COLUMN()-1<=40,'2_Inputs'!$B$56,'2_Inputs'!$B$57))))/12 -> 0 | E6: =IF(COLUMN()-1<=4,'2_Inputs'!$B$53,IF(COLUMN()-1<=16,'2_Inputs'!$B$54,IF(COLUMN()-1<=28,'2_Inputs'!$B$55,IF(COLUMN()-1<=40,'2_Inputs'!$B$56,'2_Inputs'!$B$57))))/12 -> 0 | F6: =IF(COLUMN()-1<=4,'2_Inputs'!$B$53,IF(COLUMN()-1<=16,'2_Inputs'!$B$54,IF(COLUMN()-1<=28,'2_Inputs'!$B$55,IF(COLUMN()-1<=40,'2_Inputs'!$B$56,'2_Inputs'!$B$57))))/12 -> 8333.3333 | G6: =IF(COLUMN()-1<=4,'2_Inputs'!$B$53,IF(COLUMN()-1<=16,'2_Inputs'!$B$54,IF(COLUMN()-1<=28,'2_Inputs'!$B$55,IF(COLUMN()-1<=40,'2_Inputs'!$B$56,'2_Inputs'!$B$57))))/12 -> 8333.3333 | H6: =IF(COLUMN()-1<=4,'2_Inputs'!$B$53,IF(COLUMN()-1<=16,'2_Inputs'!$B$54,IF(COLUMN()-1<=28,'2_Inputs'!$B$55,IF(COLUMN()-1<=40,'2_Inputs'!$B$56,'2_Inputs'!$B$57))))/12 -> 8333.3333 | I6: =IF(COLUMN()-1<=4,'2_Inputs'!$B$53,IF(COLUMN()-1<=16,'2_Inputs'!$B$54,IF(COLUMN()-1<=28,'2_Inputs'!$B$55,IF(COLUMN()-1<=40,'2_Inputs'!$B$56,'2_Inputs'!$B$57))))/12 -> 8333.3333 | ... BA6: =IF(COLUMN()-1<=4,'2_Inputs'!$B$53,IF(COLUMN()-1<=16,'2_Inputs'!$B$54,IF(COLUMN()-1<=28,'2_Inputs'!$B$55,IF(COLUMN()-1<=40,'2_Inputs'!$B$56,'2_Inputs'!$B$57))))/12 -> 10000
A7: CTO | B7: =IF(COLUMN()-1<=4,'2_Inputs'!$B$59,IF(COLUMN()-1<=16,'2_Inputs'!$B$60,IF(COLUMN()-1<=28,'2_Inputs'!$B$61,IF(COLUMN()-1<=40,'2_Inputs'!$B$62,'2_Inputs'!$B$63))))/12 -> 0 | C7: =IF(COLUMN()-1<=4,'2_Inputs'!$B$59,IF(COLUMN()-1<=16,'2_Inputs'!$B$60,IF(COLUMN()-1<=28,'2_Inputs'!$B$61,IF(COLUMN()-1<=40,'2_Inputs'!$B$62,'2_Inputs'!$B$63))))/12 -> 0 | D7: =IF(COLUMN()-1<=4,'2_Inputs'!$B$59,IF(COLUMN()-1<=16,'2_Inputs'!$B$60,IF(COLUMN()-1<=28,'2_Inputs'!$B$61,IF(COLUMN()-1<=40,'2_Inputs'!$B$62,'2_Inputs'!$B$63))))/12 -> 0 | E7: =IF(COLUMN()-1<=4,'2_Inputs'!$B$59,IF(COLUMN()-1<=16,'2_Inputs'!$B$60,IF(COLUMN()-1<=28,'2_Inputs'!$B$61,IF(COLUMN()-1<=40,'2_Inputs'!$B$62,'2_Inputs'!$B$63))))/12 -> 0 | F7: =IF(COLUMN()-1<=4,'2_Inputs'!$B$59,IF(COLUMN()-1<=16,'2_Inputs'!$B$60,IF(COLUMN()-1<=28,'2_Inputs'!$B$61,IF(COLUMN()-1<=40,'2_Inputs'!$B$62,'2_Inputs'!$B$63))))/12 -> 8333.3333 | G7: =IF(COLUMN()-1<=4,'2_Inputs'!$B$59,IF(COLUMN()-1<=16,'2_Inputs'!$B$60,IF(COLUMN()-1<=28,'2_Inputs'!$B$61,IF(COLUMN()-1<=40,'2_Inputs'!$B$62,'2_Inputs'!$B$63))))/12 -> 8333.3333 | H7: =IF(COLUMN()-1<=4,'2_Inputs'!$B$59,IF(COLUMN()-1<=16,'2_Inputs'!$B$60,IF(COLUMN()-1<=28,'2_Inputs'!$B$61,IF(COLUMN()-1<=40,'2_Inputs'!$B$62,'2_Inputs'!$B$63))))/12 -> 8333.3333 | I7: =IF(COLUMN()-1<=4,'2_Inputs'!$B$59,IF(COLUMN()-1<=16,'2_Inputs'!$B$60,IF(COLUMN()-1<=28,'2_Inputs'!$B$61,IF(COLUMN()-1<=40,'2_Inputs'!$B$62,'2_Inputs'!$B$63))))/12 -> 8333.3333 | ... BA7: =IF(COLUMN()-1<=4,'2_Inputs'!$B$59,IF(COLUMN()-1<=16,'2_Inputs'!$B$60,IF(COLUMN()-1<=28,'2_Inputs'!$B$61,IF(COLUMN()-1<=40,'2_Inputs'!$B$62,'2_Inputs'!$B$63))))/12 -> 10000
A8: CCO | B8: =IF(COLUMN()-1<=4,'2_Inputs'!$B$65,IF(COLUMN()-1<=16,'2_Inputs'!$B$66,IF(COLUMN()-1<=28,'2_Inputs'!$B$67,IF(COLUMN()-1<=40,'2_Inputs'!$B$68,'2_Inputs'!$B$69))))/12 -> 0 | C8: =IF(COLUMN()-1<=4,'2_Inputs'!$B$65,IF(COLUMN()-1<=16,'2_Inputs'!$B$66,IF(COLUMN()-1<=28,'2_Inputs'!$B$67,IF(COLUMN()-1<=40,'2_Inputs'!$B$68,'2_Inputs'!$B$69))))/12 -> 0 | D8: =IF(COLUMN()-1<=4,'2_Inputs'!$B$65,IF(COLUMN()-1<=16,'2_Inputs'!$B$66,IF(COLUMN()-1<=28,'2_Inputs'!$B$67,IF(COLUMN()-1<=40,'2_Inputs'!$B$68,'2_Inputs'!$B$69))))/12 -> 0 | E8: =IF(COLUMN()-1<=4,'2_Inputs'!$B$65,IF(COLUMN()-1<=16,'2_Inputs'!$B$66,IF(COLUMN()-1<=28,'2_Inputs'!$B$67,IF(COLUMN()-1<=40,'2_Inputs'!$B$68,'2_Inputs'!$B$69))))/12 -> 0 | F8: =IF(COLUMN()-1<=4,'2_Inputs'!$B$65,IF(COLUMN()-1<=16,'2_Inputs'!$B$66,IF(COLUMN()-1<=28,'2_Inputs'!$B$67,IF(COLUMN()-1<=40,'2_Inputs'!$B$68,'2_Inputs'!$B$69))))/12 -> 8333.3333 | G8: =IF(COLUMN()-1<=4,'2_Inputs'!$B$65,IF(COLUMN()-1<=16,'2_Inputs'!$B$66,IF(COLUMN()-1<=28,'2_Inputs'!$B$67,IF(COLUMN()-1<=40,'2_Inputs'!$B$68,'2_Inputs'!$B$69))))/12 -> 8333.3333 | H8: =IF(COLUMN()-1<=4,'2_Inputs'!$B$65,IF(COLUMN()-1<=16,'2_Inputs'!$B$66,IF(COLUMN()-1<=28,'2_Inputs'!$B$67,IF(COLUMN()-1<=40,'2_Inputs'!$B$68,'2_Inputs'!$B$69))))/12 -> 8333.3333 | I8: =IF(COLUMN()-1<=4,'2_Inputs'!$B$65,IF(COLUMN()-1<=16,'2_Inputs'!$B$66,IF(COLUMN()-1<=28,'2_Inputs'!$B$67,IF(COLUMN()-1<=40,'2_Inputs'!$B$68,'2_Inputs'!$B$69))))/12 -> 8333.3333 | ... BA8: =IF(COLUMN()-1<=4,'2_Inputs'!$B$65,IF(COLUMN()-1<=16,'2_Inputs'!$B$66,IF(COLUMN()-1<=28,'2_Inputs'!$B$67,IF(COLUMN()-1<=40,'2_Inputs'!$B$68,'2_Inputs'!$B$69))))/12 -> 10000
A9: Executives (3 Gründer) | B9: =SUM(B6:B8) -> 0 | C9: =SUM(C6:C8) -> 0 | D9: =SUM(D6:D8) -> 0 | E9: =SUM(E6:E8) -> 0 | F9: =SUM(F6:F8) -> 25000 | G9: =SUM(G6:G8) -> 25000 | H9: =SUM(H6:H8) -> 25000 | I9: =SUM(I6:I8) -> 25000 | ... BA9: =SUM(BA6:BA8) -> 30000
A10: Mitarbeiter (Gehälter) | B10: =IF(AND(COLUMN()-1>='2_Inputs'!$B$177,'2_Inputs'!$C$177="JA"),'2_Inputs'!$C$71/12*(1+'2_Inputs'!$B$84)^INT((COLUMN()-2)/12),0)+IF(AND(COLUMN()-1>='2_Inputs'!$B$178,'2_Inputs'!$C$178="JA"),'2_Inputs'!$C$71/12*(1+'2_Inputs'!$B$84)^INT((COLUMN()-2)/12),0)+IF(AND(COLUMN()-1>='2_Inputs'!$B$179,'2_Inputs'!$C$179="JA"),'2_Inputs'!$C$72/12*(1+'2_Inputs'!$B$84)^INT((COLUMN()-2)/12),0)+IF(AND(COLUMN()-1>='2_Inputs'!$B$180,'2_Inputs'!$C$180="JA"),'2_Inputs'!$C$73/12*(1+'2_Inputs'!$B$84)^INT((COLUMN()-2)/12),0)+IF(AND(COLUMN()-1>='2_Inputs'!$B$181,'2_Inputs'!$C$181="JA"),'2_Inputs'!$C$74/12*(1+'2_Inputs'!$B$84)^INT((COLUMN()-2)/12),0)+IF(AND(COLUMN()-1>='2_Inputs'!$B$182,'2_Inputs'!$C$182="JA"),'2_Inputs'!$C$82/12*(1+'2_Inputs'!$B$84)^INT((COLUMN()-2)/12),0)+IF(AND(COLUMN()-1>='2_Inputs'!$B$183,'2_Inputs'!$C$183="JA"),'2_Inputs'!$C$75/12*(1+'2_Inputs'!$B$84)^INT((COLUMN()-2)/12),0)+IF(AND(COLUMN()-1>='2_Inputs'!$B$184,'2_Inputs'!$C$184="JA"),'2_Inputs'!$C$76/12*(1+'2_Inputs'!$B$84)^INT((COLUMN()-2)/12),0)+IF(AND(COLUMN()-1>='2_Inputs'!$B$185,'2_Inputs'!$C$185="JA"),'2_Inputs'!$C$76/12*(1+'2_Inputs'!$B$84)^INT((COLUMN()-2)/12),0)+IF(AND(COLUMN()-1>='2_Inputs'!$B$186,'2_Inputs'!$C$186="JA"),'2_Inputs'!$C$76/12*(1+'2_Inputs'!$B$84)^INT((COLUMN()-2)/12),0)+IF(AND(COLUMN()-1>='2_Inputs'!$B$187,'2_Inputs'!$C$187="JA"),'2_Inputs'!$C$78/12*(1+'2_Inputs'!$B$84)^INT((COLUMN()-2)/12),0)+IF(AND(COLUMN()-1>='2_Inputs'!$B$188,'2_Inputs'!$C$188="JA"),'2_Inputs'!$C$78/12*(1+'2_Inputs'!$B$84)^INT((COLUMN()-2)/12),0)+IF(AND(COLUMN()-1>='2_Inputs'!$B$189,'2_Inputs'!$C$189="JA"),'2_Inputs'!$C$77/12*(1+'2_Inputs'!$B$84)^INT((COLUMN()-2)/12),0)+IF(AND(COLUMN()-1>='2_Inputs'!$B$190,'2_Inputs'!$C$190="JA"),'2_Inputs'!$C$79/12*(1+'2_Inputs'!$B$84)^INT((COLUMN()-2)/12),0)+IF(AND(COLUMN()-1>='2_Inputs'!$B$191,'2_Inputs'!$C$191="JA"),'2_Inputs'!$C$80/12*(1+'2_Inputs'!$B$84)^INT((COLUMN()-2)/12),0)+IF(AND(COLUMN()-1>='2_Inputs'!$B$192,'2_Inputs'!$C$192="JA"),'2_Inputs'!$C$81/12*(1+'2_Inputs'!$B$84)^INT((COLUMN()-2)/12),0) -> 0 | C10: =IF(AND(COLUMN()-1>='2_Inputs'!$B$177,'2_Inputs'!$C$177="JA"),'2_Inputs'!$C$71/12*(1+'2_Inputs'!$B$84)^INT((COLUMN()-2)/12),0)+IF(AND(COLUMN()-1>='2_Inputs'!$B$178,'2_Inputs'!$C$178="JA"),'2_Inputs'!$C$71/12*(1+'2_Inputs'!$B$84)^INT((COLUMN()-2)/12),0)+IF(AND(COLUMN()-1>='2_Inputs'!$B$179,'2_Inputs'!$C$179="JA"),'2_Inputs'!$C$72/12*(1+'2_Inputs'!$B$84)^INT((COLUMN()-2)/12),0)+IF(AND(COLUMN()-1>='2_Inputs'!$B$180,'2_Inputs'!$C$180="JA"),'2_Inputs'!$C$73/12*(1+'2_Inputs'!$B$84)^INT((COLUMN()-2)/12),0)+IF(AND(COLUMN()-1>='2_Inputs'!$B$181,'2_Inputs'!$C$181="JA"),'2_Inputs'!$C$74/12*(1+'2_Inputs'!$B$84)^INT((COLUMN()-2)/12),0)+IF(AND(COLUMN()-1>='2_Inputs'!$B$182,'2_Inputs'!$C$182="JA"),'2_Inputs'!$C$82/12*(1+'2_Inputs'!$B$84)^INT((COLUMN()-2)/12),0)+IF(AND(COLUMN()-1>='2_Inputs'!$B$183,'2_Inputs'!$C$183="JA"),'2_Inputs'!$C$75/12*(1+'2_Inputs'!$B$84)^INT((COLUMN()-2)/12),0)+IF(AND(COLUMN()-1>='2_Inputs'!$B$184,'2_Inputs'!$C$184="JA"),'2_Inputs'!$C$76/12*(1+'2_Inputs'!$B$84)^INT((COLUMN()-2)/12),0)+IF(AND(COLUMN()-1>='2_Inputs'!$B$185,'2_Inputs'!$C$185="JA"),'2_Inputs'!$C$76/12*(1+'2_Inputs'!$B$84)^INT((COLUMN()-2)/12),0)+IF(AND(COLUMN()-1>='2_Inputs'!$B$186,'2_Inputs'!$C$186="JA"),'2_Inputs'!$C$76/12*(1+'2_Inputs'!$B$84)^INT((COLUMN()-2)/12),0)+IF(AND(COLUMN()-1>='2_Inputs'!$B$187,'2_Inputs'!$C$187="JA"),'2_Inputs'!$C$78/12*(1+'2_Inputs'!$B$84)^INT((COLUMN()-2)/12),0)+IF(AND(COLUMN()-1>='2_Inputs'!$B$188,'2_Inputs'!$C$188="JA"),'2_Inputs'!$C$78/12*(1+'2_Inputs'!$B$84)^INT((COLUMN()-2)/12),0)+IF(AND(COLUMN()-1>='2_Inputs'!$B$189,'2_Inputs'!$C$189="JA"),'2_Inputs'!$C$77/12*(1+'2_Inputs'!$B$84)^INT((COLUMN()-2)/12),0)+IF(AND(COLUMN()-1>='2_Inputs'!$B$190,'2_Inputs'!$C$190="JA"),'2_Inputs'!$C$79/12*(1+'2_Inputs'!$B$84)^INT((COLUMN()-2)/12),0)+IF(AND(COLUMN()-1>='2_Inputs'!$B$191,'2_Inputs'!$C$191="JA"),'2_Inputs'!$C$80/12*(1+'2_Inputs'!$B$84)^INT((COLUMN()-2)/12),0)+IF(AND(COLUMN()-1>='2_Inputs'!$B$192,'2_Inputs'!$C$192="JA"),'2_Inputs'!$C$81/12*(1+'2_Inputs'!$B$84)^INT((COLUMN()-2)/12),0) -> 0 | D10: =IF(AND(COLUMN()-1>='2_Inputs'!$B$177,'2_Inputs'!$C$177="JA"),'2_Inputs'!$C$71/12*(1+'2_Inputs'!$B$84)^INT((COLUMN()-2)/12),0)+IF(AND(COLUMN()-1>='2_Inputs'!$B$178,'2_Inputs'!$C$178="JA"),'2_Inputs'!$C$71/12*(1+'2_Inputs'!$B$84)^INT((COLUMN()-2)/12),0)+IF(AND(COLUMN()-1>='2_Inputs'!$B$179,'2_Inputs'!$C$179="JA"),'2_Inputs'!$C$72/12*(1+'2_Inputs'!$B$84)^INT((COLUMN()-2)/12),0)+IF(AND(COLUMN()-1>='2_Inputs'!$B$180,'2_Inputs'!$C$180="JA"),'2_Inputs'!$C$73/12*(1+'2_Inputs'!$B$84)^INT((COLUMN()-2)/12),0)+IF(AND(COLUMN()-1>='2_Inputs'!$B$181,'2_Inputs'!$C$181="JA"),'2_Inputs'!$C$74/12*(1+'2_Inputs'!$B$84)^INT((COLUMN()-2)/12),0)+IF(AND(COLUMN()-1>='2_Inputs'!$B$182,'2_Inputs'!$C$182="JA"),'2_Inputs'!$C$82/12*(1+'2_Inputs'!$B$84)^INT((COLUMN()-2)/12),0)+IF(AND(COLUMN()-1>='2_Inputs'!$B$183,'2_Inputs'!$C$183="JA"),'2_Inputs'!$C$75/12*(1+'2_Inputs'!$B$84)^INT((COLUMN()-2)/12),0)+IF(AND(COLUMN()-1>='2_Inputs'!$B$184,'2_Inputs'!$C$184="JA"),'2_Inputs'!$C$76/12*(1+'2_Inputs'!$B$84)^INT((COLUMN()-2)/12),0)+IF(AND(COLUMN()-1>='2_Inputs'!$B$185,'2_Inputs'!$C$185="JA"),'2_Inputs'!$C$76/12*(1+'2_Inputs'!$B$84)^INT((COLUMN()-2)/12),0)+IF(AND(COLUMN()-1>='2_Inputs'!$B$186,'2_Inputs'!$C$186="JA"),'2_Inputs'!$C$76/12*(1+'2_Inputs'!$B$84)^INT((COLUMN()-2)/12),0)+IF(AND(COLUMN()-1>='2_Inputs'!$B$187,'2_Inputs'!$C$187="JA"),'2_Inputs'!$C$78/12*(1+'2_Inputs'!$B$84)^INT((COLUMN()-2)/12),0)+IF(AND(COLUMN()-1>='2_Inputs'!$B$188,'2_Inputs'!$C$188="JA"),'2_Inputs'!$C$78/12*(1+'2_Inputs'!$B$84)^INT((COLUMN()-2)/12),0)+IF(AND(COLUMN()-1>='2_Inputs'!$B$189,'2_Inputs'!$C$189="JA"),'2_Inputs'!$C$77/12*(1+'2_Inputs'!$B$84)^INT((COLUMN()-2)/12),0)+IF(AND(COLUMN()-1>='2_Inputs'!$B$190,'2_Inputs'!$C$190="JA"),'2_Inputs'!$C$79/12*(1+'2_Inputs'!$B$84)^INT((COLUMN()-2)/12),0)+IF(AND(COLUMN()-1>='2_Inputs'!$B$191,'2_Inputs'!$C$191="JA"),'2_Inputs'!$C$80/12*(1+'2_Inputs'!$B$84)^INT((COLUMN()-2)/12),0)+IF(AND(COLUMN()-1>='2_Inputs'!$B$192,'2_Inputs'!$C$192="JA"),'2_Inputs'!$C$81/12*(1+'2_Inputs'!$B$84)^INT((COLUMN()-2)/12),0) -> 0 | E10: =IF(AND(COLUMN()-1>='2_Inputs'!$B$177,'2_Inputs'!$C$177="JA"),'2_Inputs'!$C$71/12*(1+'2_Inputs'!$B$84)^INT((COLUMN()-2)/12),0)+IF(AND(COLUMN()-1>='2_Inputs'!$B$178,'2_Inputs'!$C$178="JA"),'2_Inputs'!$C$71/12*(1+'2_Inputs'!$B$84)^INT((COLUMN()-2)/12),0)+IF(AND(COLUMN()-1>='2_Inputs'!$B$179,'2_Inputs'!$C$179="JA"),'2_Inputs'!$C$72/12*(1+'2_Inputs'!$B$84)^INT((COLUMN()-2)/12),0)+IF(AND(COLUMN()-1>='2_Inputs'!$B$180,'2_Inputs'!$C$180="JA"),'2_Inputs'!$C$73/12*(1+'2_Inputs'!$B$84)^INT((COLUMN()-2)/12),0)+IF(AND(COLUMN()-1>='2_Inputs'!$B$181,'2_Inputs'!$C$181="JA"),'2_Inputs'!$C$74/12*(1+'2_Inputs'!$B$84)^INT((COLUMN()-2)/12),0)+IF(AND(COLUMN()-1>='2_Inputs'!$B$182,'2_Inputs'!$C$182="JA"),'2_Inputs'!$C$82/12*(1+'2_Inputs'!$B$84)^INT((COLUMN()-2)/12),0)+IF(AND(COLUMN()-1>='2_Inputs'!$B$183,'2_Inputs'!$C$183="JA"),'2_Inputs'!$C$75/12*(1+'2_Inputs'!$B$84)^INT((COLUMN()-2)/12),0)+IF(AND(COLUMN()-1>='2_Inputs'!$B$184,'2_Inputs'!$C$184="JA"),'2_Inputs'!$C$76/12*(1+'2_Inputs'!$B$84)^INT((COLUMN()-2)/12),0)+IF(AND(COLUMN()-1>='2_Inputs'!$B$185,'2_Inputs'!$C$185="JA"),'2_Inputs'!$C$76/12*(1+'2_Inputs'!$B$84)^INT((COLUMN()-2)/12),0)+IF(AND(COLUMN()-1>='2_Inputs'!$B$186,'2_Inputs'!$C$186="JA"),'2_Inputs'!$C$76/12*(1+'2_Inputs'!$B$84)^INT((COLUMN()-2)/12),0)+IF(AND(COLUMN()-1>='2_Inputs'!$B$187,'2_Inputs'!$C$187="JA"),'2_Inputs'!$C$78/12*(1+'2_Inputs'!$B$84)^INT((COLUMN()-2)/12),0)+IF(AND(COLUMN()-1>='2_Inputs'!$B$188,'2_Inputs'!$C$188="JA"),'2_Inputs'!$C$78/12*(1+'2_Inputs'!$B$84)^INT((COLUMN()-2)/12),0)+IF(AND(COLUMN()-1>='2_Inputs'!$B$189,'2_Inputs'!$C$189="JA"),'2_Inputs'!$C$77/12*(1+'2_Inputs'!$B$84)^INT((COLUMN()-2)/12),0)+IF(AND(COLUMN()-1>='2_Inputs'!$B$190,'2_Inputs'!$C$190="JA"),'2_Inputs'!$C$79/12*(1+'2_Inputs'!$B$84)^INT((COLUMN()-2)/12),0)+IF(AND(COLUMN()-1>='2_Inputs'!$B$191,'2_Inputs'!$C$191="JA"),'2_Inputs'!$C$80/12*(1+'2_Inputs'!$B$84)^INT((COLUMN()-2)/12),0)+IF(AND(COLUMN()-1>='2_Inputs'!$B$192,'2_Inputs'!$C$192="JA"),'2_Inputs'!$C$81/12*(1+'2_Inputs'!$B$84)^INT((COLUMN()-2)/12),0) -> 0 | F10: =IF(AND(COLUMN()-1>='2_Inputs'!$B$177,'2_Inputs'!$C$177="JA"),'2_Inputs'!$C$71/12*(1+'2_Inputs'!$B$84)^INT((COLUMN()-2)/12),0)+IF(AND(COLUMN()-1>='2_Inputs'!$B$178,'2_Inputs'!$C$178="JA"),'2_Inputs'!$C$71/12*(1+'2_Inputs'!$B$84)^INT((COLUMN()-2)/12),0)+IF(AND(COLUMN()-1>='2_Inputs'!$B$179,'2_Inputs'!$C$179="JA"),'2_Inputs'!$C$72/12*(1+'2_Inputs'!$B$84)^INT((COLUMN()-2)/12),0)+IF(AND(COLUMN()-1>='2_Inputs'!$B$180,'2_Inputs'!$C$180="JA"),'2_Inputs'!$C$73/12*(1+'2_Inputs'!$B$84)^INT((COLUMN()-2)/12),0)+IF(AND(COLUMN()-1>='2_Inputs'!$B$181,'2_Inputs'!$C$181="JA"),'2_Inputs'!$C$74/12*(1+'2_Inputs'!$B$84)^INT((COLUMN()-2)/12),0)+IF(AND(COLUMN()-1>='2_Inputs'!$B$182,'2_Inputs'!$C$182="JA"),'2_Inputs'!$C$82/12*(1+'2_Inputs'!$B$84)^INT((COLUMN()-2)/12),0)+IF(AND(COLUMN()-1>='2_Inputs'!$B$183,'2_Inputs'!$C$183="JA"),'2_Inputs'!$C$75/12*(1+'2_Inputs'!$B$84)^INT((COLUMN()-2)/12),0)+IF(AND(COLUMN()-1>='2_Inputs'!$B$184,'2_Inputs'!$C$184="JA"),'2_Inputs'!$C$76/12*(1+'2_Inputs'!$B$84)^INT((COLUMN()-2)/12),0)+IF(AND(COLUMN()-1>='2_Inputs'!$B$185,'2_Inputs'!$C$185="JA"),'2_Inputs'!$C$76/12*(1+'2_Inputs'!$B$84)^INT((COLUMN()-2)/12),0)+IF(AND(COLUMN()-1>='2_Inputs'!$B$186,'2_Inputs'!$C$186="JA"),'2_Inputs'!$C$76/12*(1+'2_Inputs'!$B$84)^INT((COLUMN()-2)/12),0)+IF(AND(COLUMN()-1>='2_Inputs'!$B$187,'2_Inputs'!$C$187="JA"),'2_Inputs'!$C$78/12*(1+'2_Inputs'!$B$84)^INT((COLUMN()-2)/12),0)+IF(AND(COLUMN()-1>='2_Inputs'!$B$188,'2_Inputs'!$C$188="JA"),'2_Inputs'!$C$78/12*(1+'2_Inputs'!$B$84)^INT((COLUMN()-2)/12),0)+IF(AND(COLUMN()-1>='2_Inputs'!$B$189,'2_Inputs'!$C$189="JA"),'2_Inputs'!$C$77/12*(1+'2_Inputs'!$B$84)^INT((COLUMN()-2)/12),0)+IF(AND(COLUMN()-1>='2_Inputs'!$B$190,'2_Inputs'!$C$190="JA"),'2_Inputs'!$C$79/12*(1+'2_Inputs'!$B$84)^INT((COLUMN()-2)/12),0)+IF(AND(COLUMN()-1>='2_Inputs'!$B$191,'2_Inputs'!$C$191="JA"),'2_Inputs'!$C$80/12*(1+'2_Inputs'!$B$84)^INT((COLUMN()-2)/12),0)+IF(AND(COLUMN()-1>='2_Inputs'!$B$192,'2_Inputs'!$C$192="JA"),'2_Inputs'!$C$81/12*(1+'2_Inputs'!$B$84)^INT((COLUMN()-2)/12),0) -> 0 | G10: =IF(AND(COLUMN()-1>='2_Inputs'!$B$177,'2_Inputs'!$C$177="JA"),'2_Inputs'!$C$71/12*(1+'2_Inputs'!$B$84)^INT((COLUMN()-2)/12),0)+IF(AND(COLUMN()-1>='2_Inputs'!$B$178,'2_Inputs'!$C$178="JA"),'2_Inputs'!$C$71/12*(1+'2_Inputs'!$B$84)^INT((COLUMN()-2)/12),0)+IF(AND(COLUMN()-1>='2_Inputs'!$B$179,'2_Inputs'!$C$179="JA"),'2_Inputs'!$C$72/12*(1+'2_Inputs'!$B$84)^INT((COLUMN()-2)/12),0)+IF(AND(COLUMN()-1>='2_Inputs'!$B$180,'2_Inputs'!$C$180="JA"),'2_Inputs'!$C$73/12*(1+'2_Inputs'!$B$84)^INT((COLUMN()-2)/12),0)+IF(AND(COLUMN()-1>='2_Inputs'!$B$181,'2_Inputs'!$C$181="JA"),'2_Inputs'!$C$74/12*(1+'2_Inputs'!$B$84)^INT((COLUMN()-2)/12),0)+IF(AND(COLUMN()-1>='2_Inputs'!$B$182,'2_Inputs'!$C$182="JA"),'2_Inputs'!$C$82/12*(1+'2_Inputs'!$B$84)^INT((COLUMN()-2)/12),0)+IF(AND(COLUMN()-1>='2_Inputs'!$B$183,'2_Inputs'!$C$183="JA"),'2_Inputs'!$C$75/12*(1+'2_Inputs'!$B$84)^INT((COLUMN()-2)/12),0)+IF(AND(COLUMN()-1>='2_Inputs'!$B$184,'2_Inputs'!$C$184="JA"),'2_Inputs'!$C$76/12*(1+'2_Inputs'!$B$84)^INT((COLUMN()-2)/12),0)+IF(AND(COLUMN()-1>='2_Inputs'!$B$185,'2_Inputs'!$C$185="JA"),'2_Inputs'!$C$76/12*(1+'2_Inputs'!$B$84)^INT((COLUMN()-2)/12),0)+IF(AND(COLUMN()-1>='2_Inputs'!$B$186,'2_Inputs'!$C$186="JA"),'2_Inputs'!$C$76/12*(1+'2_Inputs'!$B$84)^INT((COLUMN()-2)/12),0)+IF(AND(COLUMN()-1>='2_Inputs'!$B$187,'2_Inputs'!$C$187="JA"),'2_Inputs'!$C$78/12*(1+'2_Inputs'!$B$84)^INT((COLUMN()-2)/12),0)+IF(AND(COLUMN()-1>='2_Inputs'!$B$188,'2_Inputs'!$C$188="JA"),'2_Inputs'!$C$78/12*(1+'2_Inputs'!$B$84)^INT((COLUMN()-2)/12),0)+IF(AND(COLUMN()-1>='2_Inputs'!$B$189,'2_Inputs'!$C$189="JA"),'2_Inputs'!$C$77/12*(1+'2_Inputs'!$B$84)^INT((COLUMN()-2)/12),0)+IF(AND(COLUMN()-1>='2_Inputs'!$B$190,'2_Inputs'!$C$190="JA"),'2_Inputs'!$C$79/12*(1+'2_Inputs'!$B$84)^INT((COLUMN()-2)/12),0)+IF(AND(COLUMN()-1>='2_Inputs'!$B$191,'2_Inputs'!$C$191="JA"),'2_Inputs'!$C$80/12*(1+'2_Inputs'!$B$84)^INT((COLUMN()-2)/12),0)+IF(AND(COLUMN()-1>='2_Inputs'!$B$192,'2_Inputs'!$C$192="JA"),'2_Inputs'!$C$81/12*(1+'2_Inputs'!$B$84)^INT((COLUMN()-2)/12),0) -> 7625 | H10: =IF(AND(COLUMN()-1>='2_Inputs'!$B$177,'2_Inputs'!$C$177="JA"),'2_Inputs'!$C$71/12*(1+'2_Inputs'!$B$84)^INT((COLUMN()-2)/12),0)+IF(AND(COLUMN()-1>='2_Inputs'!$B$178,'2_Inputs'!$C$178="JA"),'2_Inputs'!$C$71/12*(1+'2_Inputs'!$B$84)^INT((COLUMN()-2)/12),0)+IF(AND(COLUMN()-1>='2_Inputs'!$B$179,'2_Inputs'!$C$179="JA"),'2_Inputs'!$C$72/12*(1+'2_Inputs'!$B$84)^INT((COLUMN()-2)/12),0)+IF(AND(COLUMN()-1>='2_Inputs'!$B$180,'2_Inputs'!$C$180="JA"),'2_Inputs'!$C$73/12*(1+'2_Inputs'!$B$84)^INT((COLUMN()-2)/12),0)+IF(AND(COLUMN()-1>='2_Inputs'!$B$181,'2_Inputs'!$C$181="JA"),'2_Inputs'!$C$74/12*(1+'2_Inputs'!$B$84)^INT((COLUMN()-2)/12),0)+IF(AND(COLUMN()-1>='2_Inputs'!$B$182,'2_Inputs'!$C$182="JA"),'2_Inputs'!$C$82/12*(1+'2_Inputs'!$B$84)^INT((COLUMN()-2)/12),0)+IF(AND(COLUMN()-1>='2_Inputs'!$B$183,'2_Inputs'!$C$183="JA"),'2_Inputs'!$C$75/12*(1+'2_Inputs'!$B$84)^INT((COLUMN()-2)/12),0)+IF(AND(COLUMN()-1>='2_Inputs'!$B$184,'2_Inputs'!$C$184="JA"),'2_Inputs'!$C$76/12*(1+'2_Inputs'!$B$84)^INT((COLUMN()-2)/12),0)+IF(AND(COLUMN()-1>='2_Inputs'!$B$185,'2_Inputs'!$C$185="JA"),'2_Inputs'!$C$76/12*(1+'2_Inputs'!$B$84)^INT((COLUMN()-2)/12),0)+IF(AND(COLUMN()-1>='2_Inputs'!$B$186,'2_Inputs'!$C$186="JA"),'2_Inputs'!$C$76/12*(1+'2_Inputs'!$B$84)^INT((COLUMN()-2)/12),0)+IF(AND(COLUMN()-1>='2_Inputs'!$B$187,'2_Inputs'!$C$187="JA"),'2_Inputs'!$C$78/12*(1+'2_Inputs'!$B$84)^INT((COLUMN()-2)/12),0)+IF(AND(COLUMN()-1>='2_Inputs'!$B$188,'2_Inputs'!$C$188="JA"),'2_Inputs'!$C$78/12*(1+'2_Inputs'!$B$84)^INT((COLUMN()-2)/12),0)+IF(AND(COLUMN()-1>='2_Inputs'!$B$189,'2_Inputs'!$C$189="JA"),'2_Inputs'!$C$77/12*(1+'2_Inputs'!$B$84)^INT((COLUMN()-2)/12),0)+IF(AND(COLUMN()-1>='2_Inputs'!$B$190,'2_Inputs'!$C$190="JA"),'2_Inputs'!$C$79/12*(1+'2_Inputs'!$B$84)^INT((COLUMN()-2)/12),0)+IF(AND(COLUMN()-1>='2_Inputs'!$B$191,'2_Inputs'!$C$191="JA"),'2_Inputs'!$C$80/12*(1+'2_Inputs'!$B$84)^INT((COLUMN()-2)/12),0)+IF(AND(COLUMN()-1>='2_Inputs'!$B$192,'2_Inputs'!$C$192="JA"),'2_Inputs'!$C$81/12*(1+'2_Inputs'!$B$84)^INT((COLUMN()-2)/12),0) -> 7625 | I10: =IF(AND(COLUMN()-1>='2_Inputs'!$B$177,'2_Inputs'!$C$177="JA"),'2_Inputs'!$C$71/12*(1+'2_Inputs'!$B$84)^INT((COLUMN()-2)/12),0)+IF(AND(COLUMN()-1>='2_Inputs'!$B$178,'2_Inputs'!$C$178="JA"),'2_Inputs'!$C$71/12*(1+'2_Inputs'!$B$84)^INT((COLUMN()-2)/12),0)+IF(AND(COLUMN()-1>='2_Inputs'!$B$179,'2_Inputs'!$C$179="JA"),'2_Inputs'!$C$72/12*(1+'2_Inputs'!$B$84)^INT((COLUMN()-2)/12),0)+IF(AND(COLUMN()-1>='2_Inputs'!$B$180,'2_Inputs'!$C$180="JA"),'2_Inputs'!$C$73/12*(1+'2_Inputs'!$B$84)^INT((COLUMN()-2)/12),0)+IF(AND(COLUMN()-1>='2_Inputs'!$B$181,'2_Inputs'!$C$181="JA"),'2_Inputs'!$C$74/12*(1+'2_Inputs'!$B$84)^INT((COLUMN()-2)/12),0)+IF(AND(COLUMN()-1>='2_Inputs'!$B$182,'2_Inputs'!$C$182="JA"),'2_Inputs'!$C$82/12*(1+'2_Inputs'!$B$84)^INT((COLUMN()-2)/12),0)+IF(AND(COLUMN()-1>='2_Inputs'!$B$183,'2_Inputs'!$C$183="JA"),'2_Inputs'!$C$75/12*(1+'2_Inputs'!$B$84)^INT((COLUMN()-2)/12),0)+IF(AND(COLUMN()-1>='2_Inputs'!$B$184,'2_Inputs'!$C$184="JA"),'2_Inputs'!$C$76/12*(1+'2_Inputs'!$B$84)^INT((COLUMN()-2)/12),0)+IF(AND(COLUMN()-1>='2_Inputs'!$B$185,'2_Inputs'!$C$185="JA"),'2_Inputs'!$C$76/12*(1+'2_Inputs'!$B$84)^INT((COLUMN()-2)/12),0)+IF(AND(COLUMN()-1>='2_Inputs'!$B$186,'2_Inputs'!$C$186="JA"),'2_Inputs'!$C$76/12*(1+'2_Inputs'!$B$84)^INT((COLUMN()-2)/12),0)+IF(AND(COLUMN()-1>='2_Inputs'!$B$187,'2_Inputs'!$C$187="JA"),'2_Inputs'!$C$78/12*(1+'2_Inputs'!$B$84)^INT((COLUMN()-2)/12),0)+IF(AND(COLUMN()-1>='2_Inputs'!$B$188,'2_Inputs'!$C$188="JA"),'2_Inputs'!$C$78/12*(1+'2_Inputs'!$B$84)^INT((COLUMN()-2)/12),0)+IF(AND(COLUMN()-1>='2_Inputs'!$B$189,'2_Inputs'!$C$189="JA"),'2_Inputs'!$C$77/12*(1+'2_Inputs'!$B$84)^INT((COLUMN()-2)/12),0)+IF(AND(COLUMN()-1>='2_Inputs'!$B$190,'2_Inputs'!$C$190="JA"),'2_Inputs'!$C$79/12*(1+'2_Inputs'!$B$84)^INT((COLUMN()-2)/12),0)+IF(AND(COLUMN()-1>='2_Inputs'!$B$191,'2_Inputs'!$C$191="JA"),'2_Inputs'!$C$80/12*(1+'2_Inputs'!$B$84)^INT((COLUMN()-2)/12),0)+IF(AND(COLUMN()-1>='2_Inputs'!$B$192,'2_Inputs'!$C$192="JA"),'2_Inputs'!$C$81/12*(1+'2_Inputs'!$B$84)^INT((COLUMN()-2)/12),0) -> 7625 | ... BA10: =IF(AND(COLUMN()-1>='2_Inputs'!$B$177,'2_Inputs'!$C$177="JA"),'2_Inputs'!$C$71/12*(1+'2_Inputs'!$B$84)^INT((COLUMN()-2)/12),0)+IF(AND(COLUMN()-1>='2_Inputs'!$B$178,'2_Inputs'!$C$178="JA"),'2_Inputs'!$C$71/12*(1+'2_Inputs'!$B$84)^INT((COLUMN()-2)/12),0)+IF(AND(COLUMN()-1>='2_Inputs'!$B$179,'2_Inputs'!$C$179="JA"),'2_Inputs'!$C$72/12*(1+'2_Inputs'!$B$84)^INT((COLUMN()-2)/12),0)+IF(AND(COLUMN()-1>='2_Inputs'!$B$180,'2_Inputs'!$C$180="JA"),'2_Inputs'!$C$73/12*(1+'2_Inputs'!$B$84)^INT((COLUMN()-2)/12),0)+IF(AND(COLUMN()-1>='2_Inputs'!$B$181,'2_Inputs'!$C$181="JA"),'2_Inputs'!$C$74/12*(1+'2_Inputs'!$B$84)^INT((COLUMN()-2)/12),0)+IF(AND(COLUMN()-1>='2_Inputs'!$B$182,'2_Inputs'!$C$182="JA"),'2_Inputs'!$C$82/12*(1+'2_Inputs'!$B$84)^INT((COLUMN()-2)/12),0)+IF(AND(COLUMN()-1>='2_Inputs'!$B$183,'2_Inputs'!$C$183="JA"),'2_Inputs'!$C$75/12*(1+'2_Inputs'!$B$84)^INT((COLUMN()-2)/12),0)+IF(AND(COLUMN()-1>='2_Inputs'!$B$184,'2_Inputs'!$C$184="JA"),'2_Inputs'!$C$76/12*(1+'2_Inputs'!$B$84)^INT((COLUMN()-2)/12),0)+IF(AND(COLUMN()-1>='2_Inputs'!$B$185,'2_Inputs'!$C$185="JA"),'2_Inputs'!$C$76/12*(1+'2_Inputs'!$B$84)^INT((COLUMN()-2)/12),0)+IF(AND(COLUMN()-1>='2_Inputs'!$B$186,'2_Inputs'!$C$186="JA"),'2_Inputs'!$C$76/12*(1+'2_Inputs'!$B$84)^INT((COLUMN()-2)/12),0)+IF(AND(COLUMN()-1>='2_Inputs'!$B$187,'2_Inputs'!$C$187="JA"),'2_Inputs'!$C$78/12*(1+'2_Inputs'!$B$84)^INT((COLUMN()-2)/12),0)+IF(AND(COLUMN()-1>='2_Inputs'!$B$188,'2_Inputs'!$C$188="JA"),'2_Inputs'!$C$78/12*(1+'2_Inputs'!$B$84)^INT((COLUMN()-2)/12),0)+IF(AND(COLUMN()-1>='2_Inputs'!$B$189,'2_Inputs'!$C$189="JA"),'2_Inputs'!$C$77/12*(1+'2_Inputs'!$B$84)^INT((COLUMN()-2)/12),0)+IF(AND(COLUMN()-1>='2_Inputs'!$B$190,'2_Inputs'!$C$190="JA"),'2_Inputs'!$C$79/12*(1+'2_Inputs'!$B$84)^INT((COLUMN()-2)/12),0)+IF(AND(COLUMN()-1>='2_Inputs'!$B$191,'2_Inputs'!$C$191="JA"),'2_Inputs'!$C$80/12*(1+'2_Inputs'!$B$84)^INT((COLUMN()-2)/12),0)+IF(AND(COLUMN()-1>='2_Inputs'!$B$192,'2_Inputs'!$C$192="JA"),'2_Inputs'!$C$81/12*(1+'2_Inputs'!$B$84)^INT((COLUMN()-2)/12),0) -> 84446.926
A11: Lohnnebenkosten (in AG-Brutto enthalten) | B11: 0 | C11: 0 | D11: 0 | E11: 0 | F11: 0 | G11: 0 | H11: 0 | I11: 0 | J11: 0 | K11: 0 | L11: 0 | M11: 0 | N11: 0 | O11: 0 | P11: 0 | Q11: 0 | R11: 0 | S11: 0 | T11: 0 | U11: 0 | V11: 0 | W11: 0 | X11: 0 | Y11: 0 | Z11: 0 | AA11: 0 | AB11: 0 | AC11: 0 | AD11: 0 | AE11: 0 | AF11: 0 | AG11: 0 | AH11: 0 | AI11: 0 | AJ11: 0 | AK11: 0 | AL11: 0 | AM11: 0 | AN11: 0 | AO11: 0 | AP11: 0 | AQ11: 0 | AR11: 0 | AS11: 0 | AT11: 0 | AU11: 0 | AV11: 0 | AW11: 0 | AX11: 0 | AY11: 0 | AZ11: 0 | BA11: 0
A12: Hardware-Renting (neue MA) | B12: =IF(AND(COLUMN()-1>='2_Inputs'!$B$177,'2_Inputs'!$C$177="JA"),'2_Inputs'!$B$197,0)+IF(AND(COLUMN()-1>='2_Inputs'!$B$178,'2_Inputs'!$C$178="JA"),'2_Inputs'!$B$197,0)+IF(AND(COLUMN()-1>='2_Inputs'!$B$179,'2_Inputs'!$C$179="JA"),'2_Inputs'!$B$197,0)+IF(AND(COLUMN()-1>='2_Inputs'!$B$180,'2_Inputs'!$C$180="JA"),'2_Inputs'!$B$197,0)+IF(AND(COLUMN()-1>='2_Inputs'!$B$181,'2_Inputs'!$C$181="JA"),'2_Inputs'!$B$197,0)+IF(AND(COLUMN()-1>='2_Inputs'!$B$182,'2_Inputs'!$C$182="JA"),'2_Inputs'!$B$197,0)+IF(AND(COLUMN()-1>='2_Inputs'!$B$183,'2_Inputs'!$C$183="JA"),'2_Inputs'!$B$197,0)+IF(AND(COLUMN()-1>='2_Inputs'!$B$184,'2_Inputs'!$C$184="JA"),'2_Inputs'!$B$197,0)+IF(AND(COLUMN()-1>='2_Inputs'!$B$185,'2_Inputs'!$C$185="JA"),'2_Inputs'!$B$197,0)+IF(AND(COLUMN()-1>='2_Inputs'!$B$186,'2_Inputs'!$C$186="JA"),'2_Inputs'!$B$197,0)+IF(AND(COLUMN()-1>='2_Inputs'!$B$187,'2_Inputs'!$C$187="JA"),'2_Inputs'!$B$197,0)+IF(AND(COLUMN()-1>='2_Inputs'!$B$188,'2_Inputs'!$C$188="JA"),'2_Inputs'!$B$197,0)+IF(AND(COLUMN()-1>='2_Inputs'!$B$189,'2_Inputs'!$C$189="JA"),'2_Inputs'!$B$197,0)+IF(AND(COLUMN()-1>='2_Inputs'!$B$190,'2_Inputs'!$C$190="JA"),'2_Inputs'!$B$197,0)+IF(AND(COLUMN()-1>='2_Inputs'!$B$191,'2_Inputs'!$C$191="JA"),'2_Inputs'!$B$197,0)+IF(AND(COLUMN()-1>='2_Inputs'!$B$192,'2_Inputs'!$C$192="JA"),'2_Inputs'!$B$197,0) -> 0 | C12: =IF(AND(COLUMN()-1>='2_Inputs'!$B$177,'2_Inputs'!$C$177="JA"),'2_Inputs'!$B$197,0)+IF(AND(COLUMN()-1>='2_Inputs'!$B$178,'2_Inputs'!$C$178="JA"),'2_Inputs'!$B$197,0)+IF(AND(COLUMN()-1>='2_Inputs'!$B$179,'2_Inputs'!$C$179="JA"),'2_Inputs'!$B$197,0)+IF(AND(COLUMN()-1>='2_Inputs'!$B$180,'2_Inputs'!$C$180="JA"),'2_Inputs'!$B$197,0)+IF(AND(COLUMN()-1>='2_Inputs'!$B$181,'2_Inputs'!$C$181="JA"),'2_Inputs'!$B$197,0)+IF(AND(COLUMN()-1>='2_Inputs'!$B$182,'2_Inputs'!$C$182="JA"),'2_Inputs'!$B$197,0)+IF(AND(COLUMN()-1>='2_Inputs'!$B$183,'2_Inputs'!$C$183="JA"),'2_Inputs'!$B$197,0)+IF(AND(COLUMN()-1>='2_Inputs'!$B$184,'2_Inputs'!$C$184="JA"),'2_Inputs'!$B$197,0)+IF(AND(COLUMN()-1>='2_Inputs'!$B$185,'2_Inputs'!$C$185="JA"),'2_Inputs'!$B$197,0)+IF(AND(COLUMN()-1>='2_Inputs'!$B$186,'2_Inputs'!$C$186="JA"),'2_Inputs'!$B$197,0)+IF(AND(COLUMN()-1>='2_Inputs'!$B$187,'2_Inputs'!$C$187="JA"),'2_Inputs'!$B$197,0)+IF(AND(COLUMN()-1>='2_Inputs'!$B$188,'2_Inputs'!$C$188="JA"),'2_Inputs'!$B$197,0)+IF(AND(COLUMN()-1>='2_Inputs'!$B$189,'2_Inputs'!$C$189="JA"),'2_Inputs'!$B$197,0)+IF(AND(COLUMN()-1>='2_Inputs'!$B$190,'2_Inputs'!$C$190="JA"),'2_Inputs'!$B$197,0)+IF(AND(COLUMN()-1>='2_Inputs'!$B$191,'2_Inputs'!$C$191="JA"),'2_Inputs'!$B$197,0)+IF(AND(COLUMN()-1>='2_Inputs'!$B$192,'2_Inputs'!$C$192="JA"),'2_Inputs'!$B$197,0) -> 0 | D12: =IF(AND(COLUMN()-1>='2_Inputs'!$B$177,'2_Inputs'!$C$177="JA"),'2_Inputs'!$B$197,0)+IF(AND(COLUMN()-1>='2_Inputs'!$B$178,'2_Inputs'!$C$178="JA"),'2_Inputs'!$B$197,0)+IF(AND(COLUMN()-1>='2_Inputs'!$B$179,'2_Inputs'!$C$179="JA"),'2_Inputs'!$B$197,0)+IF(AND(COLUMN()-1>='2_Inputs'!$B$180,'2_Inputs'!$C$180="JA"),'2_Inputs'!$B$197,0)+IF(AND(COLUMN()-1>='2_Inputs'!$B$181,'2_Inputs'!$C$181="JA"),'2_Inputs'!$B$197,0)+IF(AND(COLUMN()-1>='2_Inputs'!$B$182,'2_Inputs'!$C$182="JA"),'2_Inputs'!$B$197,0)+IF(AND(COLUMN()-1>='2_Inputs'!$B$183,'2_Inputs'!$C$183="JA"),'2_Inputs'!$B$197,0)+IF(AND(COLUMN()-1>='2_Inputs'!$B$184,'2_Inputs'!$C$184="JA"),'2_Inputs'!$B$197,0)+IF(AND(COLUMN()-1>='2_Inputs'!$B$185,'2_Inputs'!$C$185="JA"),'2_Inputs'!$B$197,0)+IF(AND(COLUMN()-1>='2_Inputs'!$B$186,'2_Inputs'!$C$186="JA"),'2_Inputs'!$B$197,0)+IF(AND(COLUMN()-1>='2_Inputs'!$B$187,'2_Inputs'!$C$187="JA"),'2_Inputs'!$B$197,0)+IF(AND(COLUMN()-1>='2_Inputs'!$B$188,'2_Inputs'!$C$188="JA"),'2_Inputs'!$B$197,0)+IF(AND(COLUMN()-1>='2_Inputs'!$B$189,'2_Inputs'!$C$189="JA"),'2_Inputs'!$B$197,0)+IF(AND(COLUMN()-1>='2_Inputs'!$B$190,'2_Inputs'!$C$190="JA"),'2_Inputs'!$B$197,0)+IF(AND(COLUMN()-1>='2_Inputs'!$B$191,'2_Inputs'!$C$191="JA"),'2_Inputs'!$B$197,0)+IF(AND(COLUMN()-1>='2_Inputs'!$B$192,'2_Inputs'!$C$192="JA"),'2_Inputs'!$B$197,0) -> 0 | E12: =IF(AND(COLUMN()-1>='2_Inputs'!$B$177,'2_Inputs'!$C$177="JA"),'2_Inputs'!$B$197,0)+IF(AND(COLUMN()-1>='2_Inputs'!$B$178,'2_Inputs'!$C$178="JA"),'2_Inputs'!$B$197,0)+IF(AND(COLUMN()-1>='2_Inputs'!$B$179,'2_Inputs'!$C$179="JA"),'2_Inputs'!$B$197,0)+IF(AND(COLUMN()-1>='2_Inputs'!$B$180,'2_Inputs'!$C$180="JA"),'2_Inputs'!$B$197,0)+IF(AND(COLUMN()-1>='2_Inputs'!$B$181,'2_Inputs'!$C$181="JA"),'2_Inputs'!$B$197,0)+IF(AND(COLUMN()-1>='2_Inputs'!$B$182,'2_Inputs'!$C$182="JA"),'2_Inputs'!$B$197,0)+IF(AND(COLUMN()-1>='2_Inputs'!$B$183,'2_Inputs'!$C$183="JA"),'2_Inputs'!$B$197,0)+IF(AND(COLUMN()-1>='2_Inputs'!$B$184,'2_Inputs'!$C$184="JA"),'2_Inputs'!$B$197,0)+IF(AND(COLUMN()-1>='2_Inputs'!$B$185,'2_Inputs'!$C$185="JA"),'2_Inputs'!$B$197,0)+IF(AND(COLUMN()-1>='2_Inputs'!$B$186,'2_Inputs'!$C$186="JA"),'2_Inputs'!$B$197,0)+IF(AND(COLUMN()-1>='2_Inputs'!$B$187,'2_Inputs'!$C$187="JA"),'2_Inputs'!$B$197,0)+IF(AND(COLUMN()-1>='2_Inputs'!$B$188,'2_Inputs'!$C$188="JA"),'2_Inputs'!$B$197,0)+IF(AND(COLUMN()-1>='2_Inputs'!$B$189,'2_Inputs'!$C$189="JA"),'2_Inputs'!$B$197,0)+IF(AND(COLUMN()-1>='2_Inputs'!$B$190,'2_Inputs'!$C$190="JA"),'2_Inputs'!$B$197,0)+IF(AND(COLUMN()-1>='2_Inputs'!$B$191,'2_Inputs'!$C$191="JA"),'2_Inputs'!$B$197,0)+IF(AND(COLUMN()-1>='2_Inputs'!$B$192,'2_Inputs'!$C$192="JA"),'2_Inputs'!$B$197,0) -> 0 | F12: =IF(AND(COLUMN()-1>='2_Inputs'!$B$177,'2_Inputs'!$C$177="JA"),'2_Inputs'!$B$197,0)+IF(AND(COLUMN()-1>='2_Inputs'!$B$178,'2_Inputs'!$C$178="JA"),'2_Inputs'!$B$197,0)+IF(AND(COLUMN()-1>='2_Inputs'!$B$179,'2_Inputs'!$C$179="JA"),'2_Inputs'!$B$197,0)+IF(AND(COLUMN()-1>='2_Inputs'!$B$180,'2_Inputs'!$C$180="JA"),'2_Inputs'!$B$197,0)+IF(AND(COLUMN()-1>='2_Inputs'!$B$181,'2_Inputs'!$C$181="JA"),'2_Inputs'!$B$197,0)+IF(AND(COLUMN()-1>='2_Inputs'!$B$182,'2_Inputs'!$C$182="JA"),'2_Inputs'!$B$197,0)+IF(AND(COLUMN()-1>='2_Inputs'!$B$183,'2_Inputs'!$C$183="JA"),'2_Inputs'!$B$197,0)+IF(AND(COLUMN()-1>='2_Inputs'!$B$184,'2_Inputs'!$C$184="JA"),'2_Inputs'!$B$197,0)+IF(AND(COLUMN()-1>='2_Inputs'!$B$185,'2_Inputs'!$C$185="JA"),'2_Inputs'!$B$197,0)+IF(AND(COLUMN()-1>='2_Inputs'!$B$186,'2_Inputs'!$C$186="JA"),'2_Inputs'!$B$197,0)+IF(AND(COLUMN()-1>='2_Inputs'!$B$187,'2_Inputs'!$C$187="JA"),'2_Inputs'!$B$197,0)+IF(AND(COLUMN()-1>='2_Inputs'!$B$188,'2_Inputs'!$C$188="JA"),'2_Inputs'!$B$197,0)+IF(AND(COLUMN()-1>='2_Inputs'!$B$189,'2_Inputs'!$C$189="JA"),'2_Inputs'!$B$197,0)+IF(AND(COLUMN()-1>='2_Inputs'!$B$190,'2_Inputs'!$C$190="JA"),'2_Inputs'!$B$197,0)+IF(AND(COLUMN()-1>='2_Inputs'!$B$191,'2_Inputs'!$C$191="JA"),'2_Inputs'!$B$197,0)+IF(AND(COLUMN()-1>='2_Inputs'!$B$192,'2_Inputs'!$C$192="JA"),'2_Inputs'!$B$197,0) -> 0 | G12: =IF(AND(COLUMN()-1>='2_Inputs'!$B$177,'2_Inputs'!$C$177="JA"),'2_Inputs'!$B$197,0)+IF(AND(COLUMN()-1>='2_Inputs'!$B$178,'2_Inputs'!$C$178="JA"),'2_Inputs'!$B$197,0)+IF(AND(COLUMN()-1>='2_Inputs'!$B$179,'2_Inputs'!$C$179="JA"),'2_Inputs'!$B$197,0)+IF(AND(COLUMN()-1>='2_Inputs'!$B$180,'2_Inputs'!$C$180="JA"),'2_Inputs'!$B$197,0)+IF(AND(COLUMN()-1>='2_Inputs'!$B$181,'2_Inputs'!$C$181="JA"),'2_Inputs'!$B$197,0)+IF(AND(COLUMN()-1>='2_Inputs'!$B$182,'2_Inputs'!$C$182="JA"),'2_Inputs'!$B$197,0)+IF(AND(COLUMN()-1>='2_Inputs'!$B$183,'2_Inputs'!$C$183="JA"),'2_Inputs'!$B$197,0)+IF(AND(COLUMN()-1>='2_Inputs'!$B$184,'2_Inputs'!$C$184="JA"),'2_Inputs'!$B$197,0)+IF(AND(COLUMN()-1>='2_Inputs'!$B$185,'2_Inputs'!$C$185="JA"),'2_Inputs'!$B$197,0)+IF(AND(COLUMN()-1>='2_Inputs'!$B$186,'2_Inputs'!$C$186="JA"),'2_Inputs'!$B$197,0)+IF(AND(COLUMN()-1>='2_Inputs'!$B$187,'2_Inputs'!$C$187="JA"),'2_Inputs'!$B$197,0)+IF(AND(COLUMN()-1>='2_Inputs'!$B$188,'2_Inputs'!$C$188="JA"),'2_Inputs'!$B$197,0)+IF(AND(COLUMN()-1>='2_Inputs'!$B$189,'2_Inputs'!$C$189="JA"),'2_Inputs'!$B$197,0)+IF(AND(COLUMN()-1>='2_Inputs'!$B$190,'2_Inputs'!$C$190="JA"),'2_Inputs'!$B$197,0)+IF(AND(COLUMN()-1>='2_Inputs'!$B$191,'2_Inputs'!$C$191="JA"),'2_Inputs'!$B$197,0)+IF(AND(COLUMN()-1>='2_Inputs'!$B$192,'2_Inputs'!$C$192="JA"),'2_Inputs'!$B$197,0) -> 89 | H12: =IF(AND(COLUMN()-1>='2_Inputs'!$B$177,'2_Inputs'!$C$177="JA"),'2_Inputs'!$B$197,0)+IF(AND(COLUMN()-1>='2_Inputs'!$B$178,'2_Inputs'!$C$178="JA"),'2_Inputs'!$B$197,0)+IF(AND(COLUMN()-1>='2_Inputs'!$B$179,'2_Inputs'!$C$179="JA"),'2_Inputs'!$B$197,0)+IF(AND(COLUMN()-1>='2_Inputs'!$B$180,'2_Inputs'!$C$180="JA"),'2_Inputs'!$B$197,0)+IF(AND(COLUMN()-1>='2_Inputs'!$B$181,'2_Inputs'!$C$181="JA"),'2_Inputs'!$B$197,0)+IF(AND(COLUMN()-1>='2_Inputs'!$B$182,'2_Inputs'!$C$182="JA"),'2_Inputs'!$B$197,0)+IF(AND(COLUMN()-1>='2_Inputs'!$B$183,'2_Inputs'!$C$183="JA"),'2_Inputs'!$B$197,0)+IF(AND(COLUMN()-1>='2_Inputs'!$B$184,'2_Inputs'!$C$184="JA"),'2_Inputs'!$B$197,0)+IF(AND(COLUMN()-1>='2_Inputs'!$B$185,'2_Inputs'!$C$185="JA"),'2_Inputs'!$B$197,0)+IF(AND(COLUMN()-1>='2_Inputs'!$B$186,'2_Inputs'!$C$186="JA"),'2_Inputs'!$B$197,0)+IF(AND(COLUMN()-1>='2_Inputs'!$B$187,'2_Inputs'!$C$187="JA"),'2_Inputs'!$B$197,0)+IF(AND(COLUMN()-1>='2_Inputs'!$B$188,'2_Inputs'!$C$188="JA"),'2_Inputs'!$B$197,0)+IF(AND(COLUMN()-1>='2_Inputs'!$B$189,'2_Inputs'!$C$189="JA"),'2_Inputs'!$B$197,0)+IF(AND(COLUMN()-1>='2_Inputs'!$B$190,'2_Inputs'!$C$190="JA"),'2_Inputs'!$B$197,0)+IF(AND(COLUMN()-1>='2_Inputs'!$B$191,'2_Inputs'!$C$191="JA"),'2_Inputs'!$B$197,0)+IF(AND(COLUMN()-1>='2_Inputs'!$B$192,'2_Inputs'!$C$192="JA"),'2_Inputs'!$B$197,0) -> 89 | I12: =IF(AND(COLUMN()-1>='2_Inputs'!$B$177,'2_Inputs'!$C$177="JA"),'2_Inputs'!$B$197,0)+IF(AND(COLUMN()-1>='2_Inputs'!$B$178,'2_Inputs'!$C$178="JA"),'2_Inputs'!$B$197,0)+IF(AND(COLUMN()-1>='2_Inputs'!$B$179,'2_Inputs'!$C$179="JA"),'2_Inputs'!$B$197,0)+IF(AND(COLUMN()-1>='2_Inputs'!$B$180,'2_Inputs'!$C$180="JA"),'2_Inputs'!$B$197,0)+IF(AND(COLUMN()-1>='2_Inputs'!$B$181,'2_Inputs'!$C$181="JA"),'2_Inputs'!$B$197,0)+IF(AND(COLUMN()-1>='2_Inputs'!$B$182,'2_Inputs'!$C$182="JA"),'2_Inputs'!$B$197,0)+IF(AND(COLUMN()-1>='2_Inputs'!$B$183,'2_Inputs'!$C$183="JA"),'2_Inputs'!$B$197,0)+IF(AND(COLUMN()-1>='2_Inputs'!$B$184,'2_Inputs'!$C$184="JA"),'2_Inputs'!$B$197,0)+IF(AND(COLUMN()-1>='2_Inputs'!$B$185,'2_Inputs'!$C$185="JA"),'2_Inputs'!$B$197,0)+IF(AND(COLUMN()-1>='2_Inputs'!$B$186,'2_Inputs'!$C$186="JA"),'2_Inputs'!$B$197,0)+IF(AND(COLUMN()-1>='2_Inputs'!$B$187,'2_Inputs'!$C$187="JA"),'2_Inputs'!$B$197,0)+IF(AND(COLUMN()-1>='2_Inputs'!$B$188,'2_Inputs'!$C$188="JA"),'2_Inputs'!$B$197,0)+IF(AND(COLUMN()-1>='2_Inputs'!$B$189,'2_Inputs'!$C$189="JA"),'2_Inputs'!$B$197,0)+IF(AND(COLUMN()-1>='2_Inputs'!$B$190,'2_Inputs'!$C$190="JA"),'2_Inputs'!$B$197,0)+IF(AND(COLUMN()-1>='2_Inputs'!$B$191,'2_Inputs'!$C$191="JA"),'2_Inputs'!$B$197,0)+IF(AND(COLUMN()-1>='2_Inputs'!$B$192,'2_Inputs'!$C$192="JA"),'2_Inputs'!$B$197,0) -> 89 | ... BA12: =IF(AND(COLUMN()-1>='2_Inputs'!$B$177,'2_Inputs'!$C$177="JA"),'2_Inputs'!$B$197,0)+IF(AND(COLUMN()-1>='2_Inputs'!$B$178,'2_Inputs'!$C$178="JA"),'2_Inputs'!$B$197,0)+IF(AND(COLUMN()-1>='2_Inputs'!$B$179,'2_Inputs'!$C$179="JA"),'2_Inputs'!$B$197,0)+IF(AND(COLUMN()-1>='2_Inputs'!$B$180,'2_Inputs'!$C$180="JA"),'2_Inputs'!$B$197,0)+IF(AND(COLUMN()-1>='2_Inputs'!$B$181,'2_Inputs'!$C$181="JA"),'2_Inputs'!$B$197,0)+IF(AND(COLUMN()-1>='2_Inputs'!$B$182,'2_Inputs'!$C$182="JA"),'2_Inputs'!$B$197,0)+IF(AND(COLUMN()-1>='2_Inputs'!$B$183,'2_Inputs'!$C$183="JA"),'2_Inputs'!$B$197,0)+IF(AND(COLUMN()-1>='2_Inputs'!$B$184,'2_Inputs'!$C$184="JA"),'2_Inputs'!$B$197,0)+IF(AND(COLUMN()-1>='2_Inputs'!$B$185,'2_Inputs'!$C$185="JA"),'2_Inputs'!$B$197,0)+IF(AND(COLUMN()-1>='2_Inputs'!$B$186,'2_Inputs'!$C$186="JA"),'2_Inputs'!$B$197,0)+IF(AND(COLUMN()-1>='2_Inputs'!$B$187,'2_Inputs'!$C$187="JA"),'2_Inputs'!$B$197,0)+IF(AND(COLUMN()-1>='2_Inputs'!$B$188,'2_Inputs'!$C$188="JA"),'2_Inputs'!$B$197,0)+IF(AND(COLUMN()-1>='2_Inputs'!$B$189,'2_Inputs'!$C$189="JA"),'2_Inputs'!$B$197,0)+IF(AND(COLUMN()-1>='2_Inputs'!$B$190,'2_Inputs'!$C$190="JA"),'2_Inputs'!$B$197,0)+IF(AND(COLUMN()-1>='2_Inputs'!$B$191,'2_Inputs'!$C$191="JA"),'2_Inputs'!$B$197,0)+IF(AND(COLUMN()-1>='2_Inputs'!$B$192,'2_Inputs'!$C$192="JA"),'2_Inputs'!$B$197,0) -> 979
A13: TOTAL PERSONAL | B13: =SUM(B9:B12) -> 0 | C13: =SUM(C9:C12) -> 0 | D13: =SUM(D9:D12) -> 0 | E13: =SUM(E9:E12) -> 0 | F13: =SUM(F9:F12) -> 25000 | G13: =SUM(G9:G12) -> 32714 | H13: =SUM(H9:H12) -> 32714 | I13: =SUM(I9:I12) -> 32714 | ... BA13: =SUM(BA9:BA12) -> 115425.93
A14: ── TECHNOLOGIE (IT) ──
A15: Cloud Hosting (Basis) | B15: ='2_Inputs'!$B$88*'4_Revenue'!B8+'2_Inputs'!$B$89*'4_Revenue'!B15+'2_Inputs'!$B$90*'4_Revenue'!B21 -> 0 | C15: ='2_Inputs'!$B$88*'4_Revenue'!C8+'2_Inputs'!$B$89*'4_Revenue'!C15+'2_Inputs'!$B$90*'4_Revenue'!C21 -> 0 | D15: ='2_Inputs'!$B$88*'4_Revenue'!D8+'2_Inputs'!$B$89*'4_Revenue'!D15+'2_Inputs'!$B$90*'4_Revenue'!D21 -> 0 | E15: ='2_Inputs'!$B$88*'4_Revenue'!E8+'2_Inputs'!$B$89*'4_Revenue'!E15+'2_Inputs'!$B$90*'4_Revenue'!E21 -> 0 | F15: ='2_Inputs'!$B$88*'4_Revenue'!F8+'2_Inputs'!$B$89*'4_Revenue'!F15+'2_Inputs'!$B$90*'4_Revenue'!F21 -> 0 | G15: ='2_Inputs'!$B$88*'4_Revenue'!G8+'2_Inputs'!$B$89*'4_Revenue'!G15+'2_Inputs'!$B$90*'4_Revenue'!G21 -> 0 | H15: ='2_Inputs'!$B$88*'4_Revenue'!H8+'2_Inputs'!$B$89*'4_Revenue'!H15+'2_Inputs'!$B$90*'4_Revenue'!H21 -> 540 | I15: ='2_Inputs'!$B$88*'4_Revenue'!I8+'2_Inputs'!$B$89*'4_Revenue'!I15+'2_Inputs'!$B$90*'4_Revenue'!I21 -> 540 | ... BA15: ='2_Inputs'!$B$88*'4_Revenue'!BA8+'2_Inputs'!$B$89*'4_Revenue'!BA15+'2_Inputs'!$B$90*'4_Revenue'!BA21 -> 150210
A16: AI/ML APIs | B16: =(IF(COLUMN()-1<=4,'2_Inputs'!$B$91,IF(COLUMN()-1<=16,'2_Inputs'!$B$92,IF(COLUMN()-1<=28,'2_Inputs'!$B$93,IF(COLUMN()-1<=40,'2_Inputs'!$B$94,'2_Inputs'!$B$95)))))*(3+IF(AND(COLUMN()-1>='2_Inputs'!$B$177,'2_Inputs'!$C$177="JA"),1,0)+IF(AND(COLUMN()-1>='2_Inputs'!$B$178,'2_Inputs'!$C$178="JA"),1,0)+IF(AND(COLUMN()-1>='2_Inputs'!$B$179,'2_Inputs'!$C$179="JA"),1,0)+IF(AND(COLUMN()-1>='2_Inputs'!$B$180,'2_Inputs'!$C$180="JA"),1,0)+IF(AND(COLUMN()-1>='2_Inputs'!$B$181,'2_Inputs'!$C$181="JA"),1,0)+IF(AND(COLUMN()-1>='2_Inputs'!$B$182,'2_Inputs'!$C$182="JA"),1,0)+IF(AND(COLUMN()-1>='2_Inputs'!$B$183,'2_Inputs'!$C$183="JA"),1,0)+IF(AND(COLUMN()-1>='2_Inputs'!$B$184,'2_Inputs'!$C$184="JA"),1,0)+IF(AND(COLUMN()-1>='2_Inputs'!$B$185,'2_Inputs'!$C$185="JA"),1,0)+IF(AND(COLUMN()-1>='2_Inputs'!$B$186,'2_Inputs'!$C$186="JA"),1,0)+IF(AND(COLUMN()-1>='2_Inputs'!$B$187,'2_Inputs'!$C$187="JA"),1,0)+IF(AND(COLUMN()-1>='2_Inputs'!$B$188,'2_Inputs'!$C$188="JA"),1,0)+IF(AND(COLUMN()-1>='2_Inputs'!$B$189,'2_Inputs'!$C$189="JA"),1,0)+IF(AND(COLUMN()-1>='2_Inputs'!$B$190,'2_Inputs'!$C$190="JA"),1,0)+IF(AND(COLUMN()-1>='2_Inputs'!$B$191,'2_Inputs'!$C$191="JA"),1,0)+IF(AND(COLUMN()-1>='2_Inputs'!$B$192,'2_Inputs'!$C$192="JA"),1,0)) -> 0 | C16: =(IF(COLUMN()-1<=4,'2_Inputs'!$B$91,IF(COLUMN()-1<=16,'2_Inputs'!$B$92,IF(COLUMN()-1<=28,'2_Inputs'!$B$93,IF(COLUMN()-1<=40,'2_Inputs'!$B$94,'2_Inputs'!$B$95)))))*(3+IF(AND(COLUMN()-1>='2_Inputs'!$B$177,'2_Inputs'!$C$177="JA"),1,0)+IF(AND(COLUMN()-1>='2_Inputs'!$B$178,'2_Inputs'!$C$178="JA"),1,0)+IF(AND(COLUMN()-1>='2_Inputs'!$B$179,'2_Inputs'!$C$179="JA"),1,0)+IF(AND(COLUMN()-1>='2_Inputs'!$B$180,'2_Inputs'!$C$180="JA"),1,0)+IF(AND(COLUMN()-1>='2_Inputs'!$B$181,'2_Inputs'!$C$181="JA"),1,0)+IF(AND(COLUMN()-1>='2_Inputs'!$B$182,'2_Inputs'!$C$182="JA"),1,0)+IF(AND(COLUMN()-1>='2_Inputs'!$B$183,'2_Inputs'!$C$183="JA"),1,0)+IF(AND(COLUMN()-1>='2_Inputs'!$B$184,'2_Inputs'!$C$184="JA"),1,0)+IF(AND(COLUMN()-1>='2_Inputs'!$B$185,'2_Inputs'!$C$185="JA"),1,0)+IF(AND(COLUMN()-1>='2_Inputs'!$B$186,'2_Inputs'!$C$186="JA"),1,0)+IF(AND(COLUMN()-1>='2_Inputs'!$B$187,'2_Inputs'!$C$187="JA"),1,0)+IF(AND(COLUMN()-1>='2_Inputs'!$B$188,'2_Inputs'!$C$188="JA"),1,0)+IF(AND(COLUMN()-1>='2_Inputs'!$B$189,'2_Inputs'!$C$189="JA"),1,0)+IF(AND(COLUMN()-1>='2_Inputs'!$B$190,'2_Inputs'!$C$190="JA"),1,0)+IF(AND(COLUMN()-1>='2_Inputs'!$B$191,'2_Inputs'!$C$191="JA"),1,0)+IF(AND(COLUMN()-1>='2_Inputs'!$B$192,'2_Inputs'!$C$192="JA"),1,0)) -> 0 | D16: =(IF(COLUMN()-1<=4,'2_Inputs'!$B$91,IF(COLUMN()-1<=16,'2_Inputs'!$B$92,IF(COLUMN()-1<=28,'2_Inputs'!$B$93,IF(COLUMN()-1<=40,'2_Inputs'!$B$94,'2_Inputs'!$B$95)))))*(3+IF(AND(COLUMN()-1>='2_Inputs'!$B$177,'2_Inputs'!$C$177="JA"),1,0)+IF(AND(COLUMN()-1>='2_Inputs'!$B$178,'2_Inputs'!$C$178="JA"),1,0)+IF(AND(COLUMN()-1>='2_Inputs'!$B$179,'2_Inputs'!$C$179="JA"),1,0)+IF(AND(COLUMN()-1>='2_Inputs'!$B$180,'2_Inputs'!$C$180="JA"),1,0)+IF(AND(COLUMN()-1>='2_Inputs'!$B$181,'2_Inputs'!$C$181="JA"),1,0)+IF(AND(COLUMN()-1>='2_Inputs'!$B$182,'2_Inputs'!$C$182="JA"),1,0)+IF(AND(COLUMN()-1>='2_Inputs'!$B$183,'2_Inputs'!$C$183="JA"),1,0)+IF(AND(COLUMN()-1>='2_Inputs'!$B$184,'2_Inputs'!$C$184="JA"),1,0)+IF(AND(COLUMN()-1>='2_Inputs'!$B$185,'2_Inputs'!$C$185="JA"),1,0)+IF(AND(COLUMN()-1>='2_Inputs'!$B$186,'2_Inputs'!$C$186="JA"),1,0)+IF(AND(COLUMN()-1>='2_Inputs'!$B$187,'2_Inputs'!$C$187="JA"),1,0)+IF(AND(COLUMN()-1>='2_Inputs'!$B$188,'2_Inputs'!$C$188="JA"),1,0)+IF(AND(COLUMN()-1>='2_Inputs'!$B$189,'2_Inputs'!$C$189="JA"),1,0)+IF(AND(COLUMN()-1>='2_Inputs'!$B$190,'2_Inputs'!$C$190="JA"),1,0)+IF(AND(COLUMN()-1>='2_Inputs'!$B$191,'2_Inputs'!$C$191="JA"),1,0)+IF(AND(COLUMN()-1>='2_Inputs'!$B$192,'2_Inputs'!$C$192="JA"),1,0)) -> 0 | E16: =(IF(COLUMN()-1<=4,'2_Inputs'!$B$91,IF(COLUMN()-1<=16,'2_Inputs'!$B$92,IF(COLUMN()-1<=28,'2_Inputs'!$B$93,IF(COLUMN()-1<=40,'2_Inputs'!$B$94,'2_Inputs'!$B$95)))))*(3+IF(AND(COLUMN()-1>='2_Inputs'!$B$177,'2_Inputs'!$C$177="JA"),1,0)+IF(AND(COLUMN()-1>='2_Inputs'!$B$178,'2_Inputs'!$C$178="JA"),1,0)+IF(AND(COLUMN()-1>='2_Inputs'!$B$179,'2_Inputs'!$C$179="JA"),1,0)+IF(AND(COLUMN()-1>='2_Inputs'!$B$180,'2_Inputs'!$C$180="JA"),1,0)+IF(AND(COLUMN()-1>='2_Inputs'!$B$181,'2_Inputs'!$C$181="JA"),1,0)+IF(AND(COLUMN()-1>='2_Inputs'!$B$182,'2_Inputs'!$C$182="JA"),1,0)+IF(AND(COLUMN()-1>='2_Inputs'!$B$183,'2_Inputs'!$C$183="JA"),1,0)+IF(AND(COLUMN()-1>='2_Inputs'!$B$184,'2_Inputs'!$C$184="JA"),1,0)+IF(AND(COLUMN()-1>='2_Inputs'!$B$185,'2_Inputs'!$C$185="JA"),1,0)+IF(AND(COLUMN()-1>='2_Inputs'!$B$186,'2_Inputs'!$C$186="JA"),1,0)+IF(AND(COLUMN()-1>='2_Inputs'!$B$187,'2_Inputs'!$C$187="JA"),1,0)+IF(AND(COLUMN()-1>='2_Inputs'!$B$188,'2_Inputs'!$C$188="JA"),1,0)+IF(AND(COLUMN()-1>='2_Inputs'!$B$189,'2_Inputs'!$C$189="JA"),1,0)+IF(AND(COLUMN()-1>='2_Inputs'!$B$190,'2_Inputs'!$C$190="JA"),1,0)+IF(AND(COLUMN()-1>='2_Inputs'!$B$191,'2_Inputs'!$C$191="JA"),1,0)+IF(AND(COLUMN()-1>='2_Inputs'!$B$192,'2_Inputs'!$C$192="JA"),1,0)) -> 0 | F16: =(IF(COLUMN()-1<=4,'2_Inputs'!$B$91,IF(COLUMN()-1<=16,'2_Inputs'!$B$92,IF(COLUMN()-1<=28,'2_Inputs'!$B$93,IF(COLUMN()-1<=40,'2_Inputs'!$B$94,'2_Inputs'!$B$95)))))*(3+IF(AND(COLUMN()-1>='2_Inputs'!$B$177,'2_Inputs'!$C$177="JA"),1,0)+IF(AND(COLUMN()-1>='2_Inputs'!$B$178,'2_Inputs'!$C$178="JA"),1,0)+IF(AND(COLUMN()-1>='2_Inputs'!$B$179,'2_Inputs'!$C$179="JA"),1,0)+IF(AND(COLUMN()-1>='2_Inputs'!$B$180,'2_Inputs'!$C$180="JA"),1,0)+IF(AND(COLUMN()-1>='2_Inputs'!$B$181,'2_Inputs'!$C$181="JA"),1,0)+IF(AND(COLUMN()-1>='2_Inputs'!$B$182,'2_Inputs'!$C$182="JA"),1,0)+IF(AND(COLUMN()-1>='2_Inputs'!$B$183,'2_Inputs'!$C$183="JA"),1,0)+IF(AND(COLUMN()-1>='2_Inputs'!$B$184,'2_Inputs'!$C$184="JA"),1,0)+IF(AND(COLUMN()-1>='2_Inputs'!$B$185,'2_Inputs'!$C$185="JA"),1,0)+IF(AND(COLUMN()-1>='2_Inputs'!$B$186,'2_Inputs'!$C$186="JA"),1,0)+IF(AND(COLUMN()-1>='2_Inputs'!$B$187,'2_Inputs'!$C$187="JA"),1,0)+IF(AND(COLUMN()-1>='2_Inputs'!$B$188,'2_Inputs'!$C$188="JA"),1,0)+IF(AND(COLUMN()-1>='2_Inputs'!$B$189,'2_Inputs'!$C$189="JA"),1,0)+IF(AND(COLUMN()-1>='2_Inputs'!$B$190,'2_Inputs'!$C$190="JA"),1,0)+IF(AND(COLUMN()-1>='2_Inputs'!$B$191,'2_Inputs'!$C$191="JA"),1,0)+IF(AND(COLUMN()-1>='2_Inputs'!$B$192,'2_Inputs'!$C$192="JA"),1,0)) -> 300 | G16: =(IF(COLUMN()-1<=4,'2_Inputs'!$B$91,IF(COLUMN()-1<=16,'2_Inputs'!$B$92,IF(COLUMN()-1<=28,'2_Inputs'!$B$93,IF(COLUMN()-1<=40,'2_Inputs'!$B$94,'2_Inputs'!$B$95)))))*(3+IF(AND(COLUMN()-1>='2_Inputs'!$B$177,'2_Inputs'!$C$177="JA"),1,0)+IF(AND(COLUMN()-1>='2_Inputs'!$B$178,'2_Inputs'!$C$178="JA"),1,0)+IF(AND(COLUMN()-1>='2_Inputs'!$B$179,'2_Inputs'!$C$179="JA"),1,0)+IF(AND(COLUMN()-1>='2_Inputs'!$B$180,'2_Inputs'!$C$180="JA"),1,0)+IF(AND(COLUMN()-1>='2_Inputs'!$B$181,'2_Inputs'!$C$181="JA"),1,0)+IF(AND(COLUMN()-1>='2_Inputs'!$B$182,'2_Inputs'!$C$182="JA"),1,0)+IF(AND(COLUMN()-1>='2_Inputs'!$B$183,'2_Inputs'!$C$183="JA"),1,0)+IF(AND(COLUMN()-1>='2_Inputs'!$B$184,'2_Inputs'!$C$184="JA"),1,0)+IF(AND(COLUMN()-1>='2_Inputs'!$B$185,'2_Inputs'!$C$185="JA"),1,0)+IF(AND(COLUMN()-1>='2_Inputs'!$B$186,'2_Inputs'!$C$186="JA"),1,0)+IF(AND(COLUMN()-1>='2_Inputs'!$B$187,'2_Inputs'!$C$187="JA"),1,0)+IF(AND(COLUMN()-1>='2_Inputs'!$B$188,'2_Inputs'!$C$188="JA"),1,0)+IF(AND(COLUMN()-1>='2_Inputs'!$B$189,'2_Inputs'!$C$189="JA"),1,0)+IF(AND(COLUMN()-1>='2_Inputs'!$B$190,'2_Inputs'!$C$190="JA"),1,0)+IF(AND(COLUMN()-1>='2_Inputs'!$B$191,'2_Inputs'!$C$191="JA"),1,0)+IF(AND(COLUMN()-1>='2_Inputs'!$B$192,'2_Inputs'!$C$192="JA"),1,0)) -> 400 | H16: =(IF(COLUMN()-1<=4,'2_Inputs'!$B$91,IF(COLUMN()-1<=16,'2_Inputs'!$B$92,IF(COLUMN()-1<=28,'2_Inputs'!$B$93,IF(COLUMN()-1<=40,'2_Inputs'!$B$94,'2_Inputs'!$B$95)))))*(3+IF(AND(COLUMN()-1>='2_Inputs'!$B$177,'2_Inputs'!$C$177="JA"),1,0)+IF(AND(COLUMN()-1>='2_Inputs'!$B$178,'2_Inputs'!$C$178="JA"),1,0)+IF(AND(COLUMN()-1>='2_Inputs'!$B$179,'2_Inputs'!$C$179="JA"),1,0)+IF(AND(COLUMN()-1>='2_Inputs'!$B$180,'2_Inputs'!$C$180="JA"),1,0)+IF(AND(COLUMN()-1>='2_Inputs'!$B$181,'2_Inputs'!$C$181="JA"),1,0)+IF(AND(COLUMN()-1>='2_Inputs'!$B$182,'2_Inputs'!$C$182="JA"),1,0)+IF(AND(COLUMN()-1>='2_Inputs'!$B$183,'2_Inputs'!$C$183="JA"),1,0)+IF(AND(COLUMN()-1>='2_Inputs'!$B$184,'2_Inputs'!$C$184="JA"),1,0)+IF(AND(COLUMN()-1>='2_Inputs'!$B$185,'2_Inputs'!$C$185="JA"),1,0)+IF(AND(COLUMN()-1>='2_Inputs'!$B$186,'2_Inputs'!$C$186="JA"),1,0)+IF(AND(COLUMN()-1>='2_Inputs'!$B$187,'2_Inputs'!$C$187="JA"),1,0)+IF(AND(COLUMN()-1>='2_Inputs'!$B$188,'2_Inputs'!$C$188="JA"),1,0)+IF(AND(COLUMN()-1>='2_Inputs'!$B$189,'2_Inputs'!$C$189="JA"),1,0)+IF(AND(COLUMN()-1>='2_Inputs'!$B$190,'2_Inputs'!$C$190="JA"),1,0)+IF(AND(COLUMN()-1>='2_Inputs'!$B$191,'2_Inputs'!$C$191="JA"),1,0)+IF(AND(COLUMN()-1>='2_Inputs'!$B$192,'2_Inputs'!$C$192="JA"),1,0)) -> 400 | I16: =(IF(COLUMN()-1<=4,'2_Inputs'!$B$91,IF(COLUMN()-1<=16,'2_Inputs'!$B$92,IF(COLUMN()-1<=28,'2_Inputs'!$B$93,IF(COLUMN()-1<=40,'2_Inputs'!$B$94,'2_Inputs'!$B$95)))))*(3+IF(AND(COLUMN()-1>='2_Inputs'!$B$177,'2_Inputs'!$C$177="JA"),1,0)+IF(AND(COLUMN()-1>='2_Inputs'!$B$178,'2_Inputs'!$C$178="JA"),1,0)+IF(AND(COLUMN()-1>='2_Inputs'!$B$179,'2_Inputs'!$C$179="JA"),1,0)+IF(AND(COLUMN()-1>='2_Inputs'!$B$180,'2_Inputs'!$C$180="JA"),1,0)+IF(AND(COLUMN()-1>='2_Inputs'!$B$181,'2_Inputs'!$C$181="JA"),1,0)+IF(AND(COLUMN()-1>='2_Inputs'!$B$182,'2_Inputs'!$C$182="JA"),1,0)+IF(AND(COLUMN()-1>='2_Inputs'!$B$183,'2_Inputs'!$C$183="JA"),1,0)+IF(AND(COLUMN()-1>='2_Inputs'!$B$184,'2_Inputs'!$C$184="JA"),1,0)+IF(AND(COLUMN()-1>='2_Inputs'!$B$185,'2_Inputs'!$C$185="JA"),1,0)+IF(AND(COLUMN()-1>='2_Inputs'!$B$186,'2_Inputs'!$C$186="JA"),1,0)+IF(AND(COLUMN()-1>='2_Inputs'!$B$187,'2_Inputs'!$C$187="JA"),1,0)+IF(AND(COLUMN()-1>='2_Inputs'!$B$188,'2_Inputs'!$C$188="JA"),1,0)+IF(AND(COLUMN()-1>='2_Inputs'!$B$189,'2_Inputs'!$C$189="JA"),1,0)+IF(AND(COLUMN()-1>='2_Inputs'!$B$190,'2_Inputs'!$C$190="JA"),1,0)+IF(AND(COLUMN()-1>='2_Inputs'!$B$191,'2_Inputs'!$C$191="JA"),1,0)+IF(AND(COLUMN()-1>='2_Inputs'!$B$192,'2_Inputs'!$C$192="JA"),1,0)) -> 400 | ... BA16: =(IF(COLUMN()-1<=4,'2_Inputs'!$B$91,IF(COLUMN()-1<=16,'2_Inputs'!$B$92,IF(COLUMN()-1<=28,'2_Inputs'!$B$93,IF(COLUMN()-1<=40,'2_Inputs'!$B$94,'2_Inputs'!$B$95)))))*(3+IF(AND(COLUMN()-1>='2_Inputs'!$B$177,'2_Inputs'!$C$177="JA"),1,0)+IF(AND(COLUMN()-1>='2_Inputs'!$B$178,'2_Inputs'!$C$178="JA"),1,0)+IF(AND(COLUMN()-1>='2_Inputs'!$B$179,'2_Inputs'!$C$179="JA"),1,0)+IF(AND(COLUMN()-1>='2_Inputs'!$B$180,'2_Inputs'!$C$180="JA"),1,0)+IF(AND(COLUMN()-1>='2_Inputs'!$B$181,'2_Inputs'!$C$181="JA"),1,0)+IF(AND(COLUMN()-1>='2_Inputs'!$B$182,'2_Inputs'!$C$182="JA"),1,0)+IF(AND(COLUMN()-1>='2_Inputs'!$B$183,'2_Inputs'!$C$183="JA"),1,0)+IF(AND(COLUMN()-1>='2_Inputs'!$B$184,'2_Inputs'!$C$184="JA"),1,0)+IF(AND(COLUMN()-1>='2_Inputs'!$B$185,'2_Inputs'!$C$185="JA"),1,0)+IF(AND(COLUMN()-1>='2_Inputs'!$B$186,'2_Inputs'!$C$186="JA"),1,0)+IF(AND(COLUMN()-1>='2_Inputs'!$B$187,'2_Inputs'!$C$187="JA"),1,0)+IF(AND(COLUMN()-1>='2_Inputs'!$B$188,'2_Inputs'!$C$188="JA"),1,0)+IF(AND(COLUMN()-1>='2_Inputs'!$B$189,'2_Inputs'!$C$189="JA"),1,0)+IF(AND(COLUMN()-1>='2_Inputs'!$B$190,'2_Inputs'!$C$190="JA"),1,0)+IF(AND(COLUMN()-1>='2_Inputs'!$B$191,'2_Inputs'!$C$191="JA"),1,0)+IF(AND(COLUMN()-1>='2_Inputs'!$B$192,'2_Inputs'!$C$192="JA"),1,0)) -> 4200
A17: SaaS Tools & Lizenzen | B17: =IF(COLUMN()-1<=4,'2_Inputs'!$B$98,IF(COLUMN()-1<=16,'2_Inputs'!$B$99,IF(COLUMN()-1<=28,'2_Inputs'!$B$100,IF(COLUMN()-1<=40,'2_Inputs'!$B$101,'2_Inputs'!$B$102)))) -> 0 | C17: =IF(COLUMN()-1<=4,'2_Inputs'!$B$98,IF(COLUMN()-1<=16,'2_Inputs'!$B$99,IF(COLUMN()-1<=28,'2_Inputs'!$B$100,IF(COLUMN()-1<=40,'2_Inputs'!$B$101,'2_Inputs'!$B$102)))) -> 0 | D17: =IF(COLUMN()-1<=4,'2_Inputs'!$B$98,IF(COLUMN()-1<=16,'2_Inputs'!$B$99,IF(COLUMN()-1<=28,'2_Inputs'!$B$100,IF(COLUMN()-1<=40,'2_Inputs'!$B$101,'2_Inputs'!$B$102)))) -> 0 | E17: =IF(COLUMN()-1<=4,'2_Inputs'!$B$98,IF(COLUMN()-1<=16,'2_Inputs'!$B$99,IF(COLUMN()-1<=28,'2_Inputs'!$B$100,IF(COLUMN()-1<=40,'2_Inputs'!$B$101,'2_Inputs'!$B$102)))) -> 0 | F17: =IF(COLUMN()-1<=4,'2_Inputs'!$B$98,IF(COLUMN()-1<=16,'2_Inputs'!$B$99,IF(COLUMN()-1<=28,'2_Inputs'!$B$100,IF(COLUMN()-1<=40,'2_Inputs'!$B$101,'2_Inputs'!$B$102)))) -> 400 | G17: =IF(COLUMN()-1<=4,'2_Inputs'!$B$98,IF(COLUMN()-1<=16,'2_Inputs'!$B$99,IF(COLUMN()-1<=28,'2_Inputs'!$B$100,IF(COLUMN()-1<=40,'2_Inputs'!$B$101,'2_Inputs'!$B$102)))) -> 400 | H17: =IF(COLUMN()-1<=4,'2_Inputs'!$B$98,IF(COLUMN()-1<=16,'2_Inputs'!$B$99,IF(COLUMN()-1<=28,'2_Inputs'!$B$100,IF(COLUMN()-1<=40,'2_Inputs'!$B$101,'2_Inputs'!$B$102)))) -> 400 | I17: =IF(COLUMN()-1<=4,'2_Inputs'!$B$98,IF(COLUMN()-1<=16,'2_Inputs'!$B$99,IF(COLUMN()-1<=28,'2_Inputs'!$B$100,IF(COLUMN()-1<=40,'2_Inputs'!$B$101,'2_Inputs'!$B$102)))) -> 400 | ... BA17: =IF(COLUMN()-1<=4,'2_Inputs'!$B$98,IF(COLUMN()-1<=16,'2_Inputs'!$B$99,IF(COLUMN()-1<=28,'2_Inputs'!$B$100,IF(COLUMN()-1<=40,'2_Inputs'!$B$101,'2_Inputs'!$B$102)))) -> 2500
A18: TOTAL TECHNOLOGIE | B18: =SUM(B15:B17) -> 0 | C18: =SUM(C15:C17) -> 0 | D18: =SUM(D15:D17) -> 0 | E18: =SUM(E15:E17) -> 0 | F18: =SUM(F15:F17) -> 700 | G18: =SUM(G15:G17) -> 800 | H18: =SUM(H15:H17) -> 1340 | I18: =SUM(I15:I17) -> 1340 | ... BA18: =SUM(BA15:BA17) -> 156910
A19: ── BÜROKOSTEN ──
A20: Kosten Coworking Space | B20: =IF(AND(COLUMN()-1>=5,COLUMN()-1<=16),'2_Inputs'!$B$199*CEILING((3+IF(AND(COLUMN()-1>='2_Inputs'!$B$177,'2_Inputs'!$C$177="JA"),1,0)+IF(AND(COLUMN()-1>='2_Inputs'!$B$178,'2_Inputs'!$C$178="JA"),1,0)+IF(AND(COLUMN()-1>='2_Inputs'!$B$179,'2_Inputs'!$C$179="JA"),1,0)+IF(AND(COLUMN()-1>='2_Inputs'!$B$180,'2_Inputs'!$C$180="JA"),1,0)+IF(AND(COLUMN()-1>='2_Inputs'!$B$181,'2_Inputs'!$C$181="JA"),1,0)+IF(AND(COLUMN()-1>='2_Inputs'!$B$182,'2_Inputs'!$C$182="JA"),1,0)+IF(AND(COLUMN()-1>='2_Inputs'!$B$183,'2_Inputs'!$C$183="JA"),1,0)+IF(AND(COLUMN()-1>='2_Inputs'!$B$184,'2_Inputs'!$C$184="JA"),1,0)+IF(AND(COLUMN()-1>='2_Inputs'!$B$185,'2_Inputs'!$C$185="JA"),1,0)+IF(AND(COLUMN()-1>='2_Inputs'!$B$186,'2_Inputs'!$C$186="JA"),1,0)+IF(AND(COLUMN()-1>='2_Inputs'!$B$187,'2_Inputs'!$C$187="JA"),1,0)+IF(AND(COLUMN()-1>='2_Inputs'!$B$188,'2_Inputs'!$C$188="JA"),1,0)+IF(AND(COLUMN()-1>='2_Inputs'!$B$189,'2_Inputs'!$C$189="JA"),1,0)+IF(AND(COLUMN()-1>='2_Inputs'!$B$190,'2_Inputs'!$C$190="JA"),1,0)+IF(AND(COLUMN()-1>='2_Inputs'!$B$191,'2_Inputs'!$C$191="JA"),1,0)+IF(AND(COLUMN()-1>='2_Inputs'!$B$192,'2_Inputs'!$C$192="JA"),1,0))/'2_Inputs'!$B$200,1),0) -> 0 | C20: =IF(AND(COLUMN()-1>=5,COLUMN()-1<=16),'2_Inputs'!$B$199*CEILING((3+IF(AND(COLUMN()-1>='2_Inputs'!$B$177,'2_Inputs'!$C$177="JA"),1,0)+IF(AND(COLUMN()-1>='2_Inputs'!$B$178,'2_Inputs'!$C$178="JA"),1,0)+IF(AND(COLUMN()-1>='2_Inputs'!$B$179,'2_Inputs'!$C$179="JA"),1,0)+IF(AND(COLUMN()-1>='2_Inputs'!$B$180,'2_Inputs'!$C$180="JA"),1,0)+IF(AND(COLUMN()-1>='2_Inputs'!$B$181,'2_Inputs'!$C$181="JA"),1,0)+IF(AND(COLUMN()-1>='2_Inputs'!$B$182,'2_Inputs'!$C$182="JA"),1,0)+IF(AND(COLUMN()-1>='2_Inputs'!$B$183,'2_Inputs'!$C$183="JA"),1,0)+IF(AND(COLUMN()-1>='2_Inputs'!$B$184,'2_Inputs'!$C$184="JA"),1,0)+IF(AND(COLUMN()-1>='2_Inputs'!$B$185,'2_Inputs'!$C$185="JA"),1,0)+IF(AND(COLUMN()-1>='2_Inputs'!$B$186,'2_Inputs'!$C$186="JA"),1,0)+IF(AND(COLUMN()-1>='2_Inputs'!$B$187,'2_Inputs'!$C$187="JA"),1,0)+IF(AND(COLUMN()-1>='2_Inputs'!$B$188,'2_Inputs'!$C$188="JA"),1,0)+IF(AND(COLUMN()-1>='2_Inputs'!$B$189,'2_Inputs'!$C$189="JA"),1,0)+IF(AND(COLUMN()-1>='2_Inputs'!$B$190,'2_Inputs'!$C$190="JA"),1,0)+IF(AND(COLUMN()-1>='2_Inputs'!$B$191,'2_Inputs'!$C$191="JA"),1,0)+IF(AND(COLUMN()-1>='2_Inputs'!$B$192,'2_Inputs'!$C$192="JA"),1,0))/'2_Inputs'!$B$200,1),0) -> 0 | D20: =IF(AND(COLUMN()-1>=5,COLUMN()-1<=16),'2_Inputs'!$B$199*CEILING((3+IF(AND(COLUMN()-1>='2_Inputs'!$B$177,'2_Inputs'!$C$177="JA"),1,0)+IF(AND(COLUMN()-1>='2_Inputs'!$B$178,'2_Inputs'!$C$178="JA"),1,0)+IF(AND(COLUMN()-1>='2_Inputs'!$B$179,'2_Inputs'!$C$179="JA"),1,0)+IF(AND(COLUMN()-1>='2_Inputs'!$B$180,'2_Inputs'!$C$180="JA"),1,0)+IF(AND(COLUMN()-1>='2_Inputs'!$B$181,'2_Inputs'!$C$181="JA"),1,0)+IF(AND(COLUMN()-1>='2_Inputs'!$B$182,'2_Inputs'!$C$182="JA"),1,0)+IF(AND(COLUMN()-1>='2_Inputs'!$B$183,'2_Inputs'!$C$183="JA"),1,0)+IF(AND(COLUMN()-1>='2_Inputs'!$B$184,'2_Inputs'!$C$184="JA"),1,0)+IF(AND(COLUMN()-1>='2_Inputs'!$B$185,'2_Inputs'!$C$185="JA"),1,0)+IF(AND(COLUMN()-1>='2_Inputs'!$B$186,'2_Inputs'!$C$186="JA"),1,0)+IF(AND(COLUMN()-1>='2_Inputs'!$B$187,'2_Inputs'!$C$187="JA"),1,0)+IF(AND(COLUMN()-1>='2_Inputs'!$B$188,'2_Inputs'!$C$188="JA"),1,0)+IF(AND(COLUMN()-1>='2_Inputs'!$B$189,'2_Inputs'!$C$189="JA"),1,0)+IF(AND(COLUMN()-1>='2_Inputs'!$B$190,'2_Inputs'!$C$190="JA"),1,0)+IF(AND(COLUMN()-1>='2_Inputs'!$B$191,'2_Inputs'!$C$191="JA"),1,0)+IF(AND(COLUMN()-1>='2_Inputs'!$B$192,'2_Inputs'!$C$192="JA"),1,0))/'2_Inputs'!$B$200,1),0) -> 0 | E20: =IF(AND(COLUMN()-1>=5,COLUMN()-1<=16),'2_Inputs'!$B$199*CEILING((3+IF(AND(COLUMN()-1>='2_Inputs'!$B$177,'2_Inputs'!$C$177="JA"),1,0)+IF(AND(COLUMN()-1>='2_Inputs'!$B$178,'2_Inputs'!$C$178="JA"),1,0)+IF(AND(COLUMN()-1>='2_Inputs'!$B$179,'2_Inputs'!$C$179="JA"),1,0)+IF(AND(COLUMN()-1>='2_Inputs'!$B$180,'2_Inputs'!$C$180="JA"),1,0)+IF(AND(COLUMN()-1>='2_Inputs'!$B$181,'2_Inputs'!$C$181="JA"),1,0)+IF(AND(COLUMN()-1>='2_Inputs'!$B$182,'2_Inputs'!$C$182="JA"),1,0)+IF(AND(COLUMN()-1>='2_Inputs'!$B$183,'2_Inputs'!$C$183="JA"),1,0)+IF(AND(COLUMN()-1>='2_Inputs'!$B$184,'2_Inputs'!$C$184="JA"),1,0)+IF(AND(COLUMN()-1>='2_Inputs'!$B$185,'2_Inputs'!$C$185="JA"),1,0)+IF(AND(COLUMN()-1>='2_Inputs'!$B$186,'2_Inputs'!$C$186="JA"),1,0)+IF(AND(COLUMN()-1>='2_Inputs'!$B$187,'2_Inputs'!$C$187="JA"),1,0)+IF(AND(COLUMN()-1>='2_Inputs'!$B$188,'2_Inputs'!$C$188="JA"),1,0)+IF(AND(COLUMN()-1>='2_Inputs'!$B$189,'2_Inputs'!$C$189="JA"),1,0)+IF(AND(COLUMN()-1>='2_Inputs'!$B$190,'2_Inputs'!$C$190="JA"),1,0)+IF(AND(COLUMN()-1>='2_Inputs'!$B$191,'2_Inputs'!$C$191="JA"),1,0)+IF(AND(COLUMN()-1>='2_Inputs'!$B$192,'2_Inputs'!$C$192="JA"),1,0))/'2_Inputs'!$B$200,1),0) -> 0 | F20: =IF(AND(COLUMN()-1>=5,COLUMN()-1<=16),'2_Inputs'!$B$199*CEILING((3+IF(AND(COLUMN()-1>='2_Inputs'!$B$177,'2_Inputs'!$C$177="JA"),1,0)+IF(AND(COLUMN()-1>='2_Inputs'!$B$178,'2_Inputs'!$C$178="JA"),1,0)+IF(AND(COLUMN()-1>='2_Inputs'!$B$179,'2_Inputs'!$C$179="JA"),1,0)+IF(AND(COLUMN()-1>='2_Inputs'!$B$180,'2_Inputs'!$C$180="JA"),1,0)+IF(AND(COLUMN()-1>='2_Inputs'!$B$181,'2_Inputs'!$C$181="JA"),1,0)+IF(AND(COLUMN()-1>='2_Inputs'!$B$182,'2_Inputs'!$C$182="JA"),1,0)+IF(AND(COLUMN()-1>='2_Inputs'!$B$183,'2_Inputs'!$C$183="JA"),1,0)+IF(AND(COLUMN()-1>='2_Inputs'!$B$184,'2_Inputs'!$C$184="JA"),1,0)+IF(AND(COLUMN()-1>='2_Inputs'!$B$185,'2_Inputs'!$C$185="JA"),1,0)+IF(AND(COLUMN()-1>='2_Inputs'!$B$186,'2_Inputs'!$C$186="JA"),1,0)+IF(AND(COLUMN()-1>='2_Inputs'!$B$187,'2_Inputs'!$C$187="JA"),1,0)+IF(AND(COLUMN()-1>='2_Inputs'!$B$188,'2_Inputs'!$C$188="JA"),1,0)+IF(AND(COLUMN()-1>='2_Inputs'!$B$189,'2_Inputs'!$C$189="JA"),1,0)+IF(AND(COLUMN()-1>='2_Inputs'!$B$190,'2_Inputs'!$C$190="JA"),1,0)+IF(AND(COLUMN()-1>='2_Inputs'!$B$191,'2_Inputs'!$C$191="JA"),1,0)+IF(AND(COLUMN()-1>='2_Inputs'!$B$192,'2_Inputs'!$C$192="JA"),1,0))/'2_Inputs'!$B$200,1),0) -> 800 | G20: =IF(AND(COLUMN()-1>=5,COLUMN()-1<=16),'2_Inputs'!$B$199*CEILING((3+IF(AND(COLUMN()-1>='2_Inputs'!$B$177,'2_Inputs'!$C$177="JA"),1,0)+IF(AND(COLUMN()-1>='2_Inputs'!$B$178,'2_Inputs'!$C$178="JA"),1,0)+IF(AND(COLUMN()-1>='2_Inputs'!$B$179,'2_Inputs'!$C$179="JA"),1,0)+IF(AND(COLUMN()-1>='2_Inputs'!$B$180,'2_Inputs'!$C$180="JA"),1,0)+IF(AND(COLUMN()-1>='2_Inputs'!$B$181,'2_Inputs'!$C$181="JA"),1,0)+IF(AND(COLUMN()-1>='2_Inputs'!$B$182,'2_Inputs'!$C$182="JA"),1,0)+IF(AND(COLUMN()-1>='2_Inputs'!$B$183,'2_Inputs'!$C$183="JA"),1,0)+IF(AND(COLUMN()-1>='2_Inputs'!$B$184,'2_Inputs'!$C$184="JA"),1,0)+IF(AND(COLUMN()-1>='2_Inputs'!$B$185,'2_Inputs'!$C$185="JA"),1,0)+IF(AND(COLUMN()-1>='2_Inputs'!$B$186,'2_Inputs'!$C$186="JA"),1,0)+IF(AND(COLUMN()-1>='2_Inputs'!$B$187,'2_Inputs'!$C$187="JA"),1,0)+IF(AND(COLUMN()-1>='2_Inputs'!$B$188,'2_Inputs'!$C$188="JA"),1,0)+IF(AND(COLUMN()-1>='2_Inputs'!$B$189,'2_Inputs'!$C$189="JA"),1,0)+IF(AND(COLUMN()-1>='2_Inputs'!$B$190,'2_Inputs'!$C$190="JA"),1,0)+IF(AND(COLUMN()-1>='2_Inputs'!$B$191,'2_Inputs'!$C$191="JA"),1,0)+IF(AND(COLUMN()-1>='2_Inputs'!$B$192,'2_Inputs'!$C$192="JA"),1,0))/'2_Inputs'!$B$200,1),0) -> 800 | H20: =IF(AND(COLUMN()-1>=5,COLUMN()-1<=16),'2_Inputs'!$B$199*CEILING((3+IF(AND(COLUMN()-1>='2_Inputs'!$B$177,'2_Inputs'!$C$177="JA"),1,0)+IF(AND(COLUMN()-1>='2_Inputs'!$B$178,'2_Inputs'!$C$178="JA"),1,0)+IF(AND(COLUMN()-1>='2_Inputs'!$B$179,'2_Inputs'!$C$179="JA"),1,0)+IF(AND(COLUMN()-1>='2_Inputs'!$B$180,'2_Inputs'!$C$180="JA"),1,0)+IF(AND(COLUMN()-1>='2_Inputs'!$B$181,'2_Inputs'!$C$181="JA"),1,0)+IF(AND(COLUMN()-1>='2_Inputs'!$B$182,'2_Inputs'!$C$182="JA"),1,0)+IF(AND(COLUMN()-1>='2_Inputs'!$B$183,'2_Inputs'!$C$183="JA"),1,0)+IF(AND(COLUMN()-1>='2_Inputs'!$B$184,'2_Inputs'!$C$184="JA"),1,0)+IF(AND(COLUMN()-1>='2_Inputs'!$B$185,'2_Inputs'!$C$185="JA"),1,0)+IF(AND(COLUMN()-1>='2_Inputs'!$B$186,'2_Inputs'!$C$186="JA"),1,0)+IF(AND(COLUMN()-1>='2_Inputs'!$B$187,'2_Inputs'!$C$187="JA"),1,0)+IF(AND(COLUMN()-1>='2_Inputs'!$B$188,'2_Inputs'!$C$188="JA"),1,0)+IF(AND(COLUMN()-1>='2_Inputs'!$B$189,'2_Inputs'!$C$189="JA"),1,0)+IF(AND(COLUMN()-1>='2_Inputs'!$B$190,'2_Inputs'!$C$190="JA"),1,0)+IF(AND(COLUMN()-1>='2_Inputs'!$B$191,'2_Inputs'!$C$191="JA"),1,0)+IF(AND(COLUMN()-1>='2_Inputs'!$B$192,'2_Inputs'!$C$192="JA"),1,0))/'2_Inputs'!$B$200,1),0) -> 800 | I20: =IF(AND(COLUMN()-1>=5,COLUMN()-1<=16),'2_Inputs'!$B$199*CEILING((3+IF(AND(COLUMN()-1>='2_Inputs'!$B$177,'2_Inputs'!$C$177="JA"),1,0)+IF(AND(COLUMN()-1>='2_Inputs'!$B$178,'2_Inputs'!$C$178="JA"),1,0)+IF(AND(COLUMN()-1>='2_Inputs'!$B$179,'2_Inputs'!$C$179="JA"),1,0)+IF(AND(COLUMN()-1>='2_Inputs'!$B$180,'2_Inputs'!$C$180="JA"),1,0)+IF(AND(COLUMN()-1>='2_Inputs'!$B$181,'2_Inputs'!$C$181="JA"),1,0)+IF(AND(COLUMN()-1>='2_Inputs'!$B$182,'2_Inputs'!$C$182="JA"),1,0)+IF(AND(COLUMN()-1>='2_Inputs'!$B$183,'2_Inputs'!$C$183="JA"),1,0)+IF(AND(COLUMN()-1>='2_Inputs'!$B$184,'2_Inputs'!$C$184="JA"),1,0)+IF(AND(COLUMN()-1>='2_Inputs'!$B$185,'2_Inputs'!$C$185="JA"),1,0)+IF(AND(COLUMN()-1>='2_Inputs'!$B$186,'2_Inputs'!$C$186="JA"),1,0)+IF(AND(COLUMN()-1>='2_Inputs'!$B$187,'2_Inputs'!$C$187="JA"),1,0)+IF(AND(COLUMN()-1>='2_Inputs'!$B$188,'2_Inputs'!$C$188="JA"),1,0)+IF(AND(COLUMN()-1>='2_Inputs'!$B$189,'2_Inputs'!$C$189="JA"),1,0)+IF(AND(COLUMN()-1>='2_Inputs'!$B$190,'2_Inputs'!$C$190="JA"),1,0)+IF(AND(COLUMN()-1>='2_Inputs'!$B$191,'2_Inputs'!$C$191="JA"),1,0)+IF(AND(COLUMN()-1>='2_Inputs'!$B$192,'2_Inputs'!$C$192="JA"),1,0))/'2_Inputs'!$B$200,1),0) -> 800 | ... BA20: =IF(AND(COLUMN()-1>=5,COLUMN()-1<=16),'2_Inputs'!$B$199*CEILING((3+IF(AND(COLUMN()-1>='2_Inputs'!$B$177,'2_Inputs'!$C$177="JA"),1,0)+IF(AND(COLUMN()-1>='2_Inputs'!$B$178,'2_Inputs'!$C$178="JA"),1,0)+IF(AND(COLUMN()-1>='2_Inputs'!$B$179,'2_Inputs'!$C$179="JA"),1,0)+IF(AND(COLUMN()-1>='2_Inputs'!$B$180,'2_Inputs'!$C$180="JA"),1,0)+IF(AND(COLUMN()-1>='2_Inputs'!$B$181,'2_Inputs'!$C$181="JA"),1,0)+IF(AND(COLUMN()-1>='2_Inputs'!$B$182,'2_Inputs'!$C$182="JA"),1,0)+IF(AND(COLUMN()-1>='2_Inputs'!$B$183,'2_Inputs'!$C$183="JA"),1,0)+IF(AND(COLUMN()-1>='2_Inputs'!$B$184,'2_Inputs'!$C$184="JA"),1,0)+IF(AND(COLUMN()-1>='2_Inputs'!$B$185,'2_Inputs'!$C$185="JA"),1,0)+IF(AND(COLUMN()-1>='2_Inputs'!$B$186,'2_Inputs'!$C$186="JA"),1,0)+IF(AND(COLUMN()-1>='2_Inputs'!$B$187,'2_Inputs'!$C$187="JA"),1,0)+IF(AND(COLUMN()-1>='2_Inputs'!$B$188,'2_Inputs'!$C$188="JA"),1,0)+IF(AND(COLUMN()-1>='2_Inputs'!$B$189,'2_Inputs'!$C$189="JA"),1,0)+IF(AND(COLUMN()-1>='2_Inputs'!$B$190,'2_Inputs'!$C$190="JA"),1,0)+IF(AND(COLUMN()-1>='2_Inputs'!$B$191,'2_Inputs'!$C$191="JA"),1,0)+IF(AND(COLUMN()-1>='2_Inputs'!$B$192,'2_Inputs'!$C$192="JA"),1,0))/'2_Inputs'!$B$200,1),0) -> 0
A21: Büromiete | B21: =IF(COLUMN()-1<=16,0,IF(COLUMN()-1<=28,'2_Inputs'!$B$201,'2_Inputs'!$B$202)) -> 0 | C21: =IF(COLUMN()-1<=16,0,IF(COLUMN()-1<=28,'2_Inputs'!$B$201,'2_Inputs'!$B$202)) -> 0 | D21: =IF(COLUMN()-1<=16,0,IF(COLUMN()-1<=28,'2_Inputs'!$B$201,'2_Inputs'!$B$202)) -> 0 | E21: =IF(COLUMN()-1<=16,0,IF(COLUMN()-1<=28,'2_Inputs'!$B$201,'2_Inputs'!$B$202)) -> 0 | F21: =IF(COLUMN()-1<=16,0,IF(COLUMN()-1<=28,'2_Inputs'!$B$201,'2_Inputs'!$B$202)) -> 0 | G21: =IF(COLUMN()-1<=16,0,IF(COLUMN()-1<=28,'2_Inputs'!$B$201,'2_Inputs'!$B$202)) -> 0 | H21: =IF(COLUMN()-1<=16,0,IF(COLUMN()-1<=28,'2_Inputs'!$B$201,'2_Inputs'!$B$202)) -> 0 | I21: =IF(COLUMN()-1<=16,0,IF(COLUMN()-1<=28,'2_Inputs'!$B$201,'2_Inputs'!$B$202)) -> 0 | ... BA21: =IF(COLUMN()-1<=16,0,IF(COLUMN()-1<=28,'2_Inputs'!$B$201,'2_Inputs'!$B$202)) -> 4500
A22: Nebenkosten & Internet | B22: =IF(COLUMN()-1>=17,450,0) -> 0 | C22: =IF(COLUMN()-1>=17,450,0) -> 0 | D22: =IF(COLUMN()-1>=17,450,0) -> 0 | E22: =IF(COLUMN()-1>=17,450,0) -> 0 | F22: =IF(COLUMN()-1>=17,450,0) -> 0 | G22: =IF(COLUMN()-1>=17,450,0) -> 0 | H22: =IF(COLUMN()-1>=17,450,0) -> 0 | I22: =IF(COLUMN()-1>=17,450,0) -> 0 | ... BA22: =IF(COLUMN()-1>=17,450,0) -> 450
A23: Bürobedarf | B23: =IF(COLUMN()-1>=17,30*3,0) -> 0 | C23: =IF(COLUMN()-1>=17,30*3,0) -> 0 | D23: =IF(COLUMN()-1>=17,30*3,0) -> 0 | E23: =IF(COLUMN()-1>=17,30*3,0) -> 0 | F23: =IF(COLUMN()-1>=17,30*3,0) -> 0 | G23: =IF(COLUMN()-1>=17,30*3,0) -> 0 | H23: =IF(COLUMN()-1>=17,30*3,0) -> 0 | I23: =IF(COLUMN()-1>=17,30*3,0) -> 0 | ... BA23: =IF(COLUMN()-1>=17,30*3,0) -> 90
A24: TOTAL BÜRO | B24: =SUM(B20:B23) -> 0 | C24: =SUM(C20:C23) -> 0 | D24: =SUM(D20:D23) -> 0 | E24: =SUM(E20:E23) -> 0 | F24: =SUM(F20:F23) -> 800 | G24: =SUM(G20:G23) -> 800 | H24: =SUM(H20:H23) -> 800 | I24: =SUM(I20:I23) -> 800 | ... BA24: =SUM(BA20:BA23) -> 5040
A25: ── PROFESSIONAL SERVICES ──
A26: Rechtsanwalt | B26: =IF(COLUMN()-1<=4,'2_Inputs'!$B$105,IF(COLUMN()-1<=16,'2_Inputs'!$B$106,IF(COLUMN()-1<=28,'2_Inputs'!$B$107,IF(COLUMN()-1<=40,'2_Inputs'!$B$108,'2_Inputs'!$B$109))))+IF(OR(COLUMN()-1='2_Inputs'!$B$10,COLUMN()-1='2_Inputs'!$B$12,COLUMN()-1='2_Inputs'!$B$14,COLUMN()-1='2_Inputs'!$B$16,COLUMN()-1=41),IF(COLUMN()-1='2_Inputs'!$B$10,'2_Inputs'!$B$112,IF(COLUMN()-1='2_Inputs'!$B$12,'2_Inputs'!$B$113,IF(COLUMN()-1='2_Inputs'!$B$14,'2_Inputs'!$B$114,IF(COLUMN()-1='2_Inputs'!$B$16,'2_Inputs'!$B$115,IF(COLUMN()-1=41,'2_Inputs'!$B$116,0))))),0) -> 0 | C26: =IF(COLUMN()-1<=4,'2_Inputs'!$B$105,IF(COLUMN()-1<=16,'2_Inputs'!$B$106,IF(COLUMN()-1<=28,'2_Inputs'!$B$107,IF(COLUMN()-1<=40,'2_Inputs'!$B$108,'2_Inputs'!$B$109))))+IF(OR(COLUMN()-1='2_Inputs'!$B$10,COLUMN()-1='2_Inputs'!$B$12,COLUMN()-1='2_Inputs'!$B$14,COLUMN()-1='2_Inputs'!$B$16,COLUMN()-1=41),IF(COLUMN()-1='2_Inputs'!$B$10,'2_Inputs'!$B$112,IF(COLUMN()-1='2_Inputs'!$B$12,'2_Inputs'!$B$113,IF(COLUMN()-1='2_Inputs'!$B$14,'2_Inputs'!$B$114,IF(COLUMN()-1='2_Inputs'!$B$16,'2_Inputs'!$B$115,IF(COLUMN()-1=41,'2_Inputs'!$B$116,0))))),0) -> 0 | D26: =IF(COLUMN()-1<=4,'2_Inputs'!$B$105,IF(COLUMN()-1<=16,'2_Inputs'!$B$106,IF(COLUMN()-1<=28,'2_Inputs'!$B$107,IF(COLUMN()-1<=40,'2_Inputs'!$B$108,'2_Inputs'!$B$109))))+IF(OR(COLUMN()-1='2_Inputs'!$B$10,COLUMN()-1='2_Inputs'!$B$12,COLUMN()-1='2_Inputs'!$B$14,COLUMN()-1='2_Inputs'!$B$16,COLUMN()-1=41),IF(COLUMN()-1='2_Inputs'!$B$10,'2_Inputs'!$B$112,IF(COLUMN()-1='2_Inputs'!$B$12,'2_Inputs'!$B$113,IF(COLUMN()-1='2_Inputs'!$B$14,'2_Inputs'!$B$114,IF(COLUMN()-1='2_Inputs'!$B$16,'2_Inputs'!$B$115,IF(COLUMN()-1=41,'2_Inputs'!$B$116,0))))),0) -> 0 | E26: =IF(COLUMN()-1<=4,'2_Inputs'!$B$105,IF(COLUMN()-1<=16,'2_Inputs'!$B$106,IF(COLUMN()-1<=28,'2_Inputs'!$B$107,IF(COLUMN()-1<=40,'2_Inputs'!$B$108,'2_Inputs'!$B$109))))+IF(OR(COLUMN()-1='2_Inputs'!$B$10,COLUMN()-1='2_Inputs'!$B$12,COLUMN()-1='2_Inputs'!$B$14,COLUMN()-1='2_Inputs'!$B$16,COLUMN()-1=41),IF(COLUMN()-1='2_Inputs'!$B$10,'2_Inputs'!$B$112,IF(COLUMN()-1='2_Inputs'!$B$12,'2_Inputs'!$B$113,IF(COLUMN()-1='2_Inputs'!$B$14,'2_Inputs'!$B$114,IF(COLUMN()-1='2_Inputs'!$B$16,'2_Inputs'!$B$115,IF(COLUMN()-1=41,'2_Inputs'!$B$116,0))))),0) -> 0 | F26: =IF(COLUMN()-1<=4,'2_Inputs'!$B$105,IF(COLUMN()-1<=16,'2_Inputs'!$B$106,IF(COLUMN()-1<=28,'2_Inputs'!$B$107,IF(COLUMN()-1<=40,'2_Inputs'!$B$108,'2_Inputs'!$B$109))))+IF(OR(COLUMN()-1='2_Inputs'!$B$10,COLUMN()-1='2_Inputs'!$B$12,COLUMN()-1='2_Inputs'!$B$14,COLUMN()-1='2_Inputs'!$B$16,COLUMN()-1=41),IF(COLUMN()-1='2_Inputs'!$B$10,'2_Inputs'!$B$112,IF(COLUMN()-1='2_Inputs'!$B$12,'2_Inputs'!$B$113,IF(COLUMN()-1='2_Inputs'!$B$14,'2_Inputs'!$B$114,IF(COLUMN()-1='2_Inputs'!$B$16,'2_Inputs'!$B$115,IF(COLUMN()-1=41,'2_Inputs'!$B$116,0))))),0) -> 500 | G26: =IF(COLUMN()-1<=4,'2_Inputs'!$B$105,IF(COLUMN()-1<=16,'2_Inputs'!$B$106,IF(COLUMN()-1<=28,'2_Inputs'!$B$107,IF(COLUMN()-1<=40,'2_Inputs'!$B$108,'2_Inputs'!$B$109))))+IF(OR(COLUMN()-1='2_Inputs'!$B$10,COLUMN()-1='2_Inputs'!$B$12,COLUMN()-1='2_Inputs'!$B$14,COLUMN()-1='2_Inputs'!$B$16,COLUMN()-1=41),IF(COLUMN()-1='2_Inputs'!$B$10,'2_Inputs'!$B$112,IF(COLUMN()-1='2_Inputs'!$B$12,'2_Inputs'!$B$113,IF(COLUMN()-1='2_Inputs'!$B$14,'2_Inputs'!$B$114,IF(COLUMN()-1='2_Inputs'!$B$16,'2_Inputs'!$B$115,IF(COLUMN()-1=41,'2_Inputs'!$B$116,0))))),0) -> 500 | H26: =IF(COLUMN()-1<=4,'2_Inputs'!$B$105,IF(COLUMN()-1<=16,'2_Inputs'!$B$106,IF(COLUMN()-1<=28,'2_Inputs'!$B$107,IF(COLUMN()-1<=40,'2_Inputs'!$B$108,'2_Inputs'!$B$109))))+IF(OR(COLUMN()-1='2_Inputs'!$B$10,COLUMN()-1='2_Inputs'!$B$12,COLUMN()-1='2_Inputs'!$B$14,COLUMN()-1='2_Inputs'!$B$16,COLUMN()-1=41),IF(COLUMN()-1='2_Inputs'!$B$10,'2_Inputs'!$B$112,IF(COLUMN()-1='2_Inputs'!$B$12,'2_Inputs'!$B$113,IF(COLUMN()-1='2_Inputs'!$B$14,'2_Inputs'!$B$114,IF(COLUMN()-1='2_Inputs'!$B$16,'2_Inputs'!$B$115,IF(COLUMN()-1=41,'2_Inputs'!$B$116,0))))),0) -> 500 | I26: =IF(COLUMN()-1<=4,'2_Inputs'!$B$105,IF(COLUMN()-1<=16,'2_Inputs'!$B$106,IF(COLUMN()-1<=28,'2_Inputs'!$B$107,IF(COLUMN()-1<=40,'2_Inputs'!$B$108,'2_Inputs'!$B$109))))+IF(OR(COLUMN()-1='2_Inputs'!$B$10,COLUMN()-1='2_Inputs'!$B$12,COLUMN()-1='2_Inputs'!$B$14,COLUMN()-1='2_Inputs'!$B$16,COLUMN()-1=41),IF(COLUMN()-1='2_Inputs'!$B$10,'2_Inputs'!$B$112,IF(COLUMN()-1='2_Inputs'!$B$12,'2_Inputs'!$B$113,IF(COLUMN()-1='2_Inputs'!$B$14,'2_Inputs'!$B$114,IF(COLUMN()-1='2_Inputs'!$B$16,'2_Inputs'!$B$115,IF(COLUMN()-1=41,'2_Inputs'!$B$116,0))))),0) -> 500 | ... BA26: =IF(COLUMN()-1<=4,'2_Inputs'!$B$105,IF(COLUMN()-1<=16,'2_Inputs'!$B$106,IF(COLUMN()-1<=28,'2_Inputs'!$B$107,IF(COLUMN()-1<=40,'2_Inputs'!$B$108,'2_Inputs'!$B$109))))+IF(OR(COLUMN()-1='2_Inputs'!$B$10,COLUMN()-1='2_Inputs'!$B$12,COLUMN()-1='2_Inputs'!$B$14,COLUMN()-1='2_Inputs'!$B$16,COLUMN()-1=41),IF(COLUMN()-1='2_Inputs'!$B$10,'2_Inputs'!$B$112,IF(COLUMN()-1='2_Inputs'!$B$12,'2_Inputs'!$B$113,IF(COLUMN()-1='2_Inputs'!$B$14,'2_Inputs'!$B$114,IF(COLUMN()-1='2_Inputs'!$B$16,'2_Inputs'!$B$115,IF(COLUMN()-1=41,'2_Inputs'!$B$116,0))))),0) -> 1500
A27: Steuerberater | B27: =IF(COLUMN()-1<=4,'2_Inputs'!$B$119,IF(COLUMN()-1<=16,'2_Inputs'!$B$120,IF(COLUMN()-1<=28,'2_Inputs'!$B$121,IF(COLUMN()-1<=40,'2_Inputs'!$B$122,'2_Inputs'!$B$123)))) -> 0 | C27: =IF(COLUMN()-1<=4,'2_Inputs'!$B$119,IF(COLUMN()-1<=16,'2_Inputs'!$B$120,IF(COLUMN()-1<=28,'2_Inputs'!$B$121,IF(COLUMN()-1<=40,'2_Inputs'!$B$122,'2_Inputs'!$B$123)))) -> 0 | D27: =IF(COLUMN()-1<=4,'2_Inputs'!$B$119,IF(COLUMN()-1<=16,'2_Inputs'!$B$120,IF(COLUMN()-1<=28,'2_Inputs'!$B$121,IF(COLUMN()-1<=40,'2_Inputs'!$B$122,'2_Inputs'!$B$123)))) -> 0 | E27: =IF(COLUMN()-1<=4,'2_Inputs'!$B$119,IF(COLUMN()-1<=16,'2_Inputs'!$B$120,IF(COLUMN()-1<=28,'2_Inputs'!$B$121,IF(COLUMN()-1<=40,'2_Inputs'!$B$122,'2_Inputs'!$B$123)))) -> 0 | F27: =IF(COLUMN()-1<=4,'2_Inputs'!$B$119,IF(COLUMN()-1<=16,'2_Inputs'!$B$120,IF(COLUMN()-1<=28,'2_Inputs'!$B$121,IF(COLUMN()-1<=40,'2_Inputs'!$B$122,'2_Inputs'!$B$123)))) -> 600 | G27: =IF(COLUMN()-1<=4,'2_Inputs'!$B$119,IF(COLUMN()-1<=16,'2_Inputs'!$B$120,IF(COLUMN()-1<=28,'2_Inputs'!$B$121,IF(COLUMN()-1<=40,'2_Inputs'!$B$122,'2_Inputs'!$B$123)))) -> 600 | H27: =IF(COLUMN()-1<=4,'2_Inputs'!$B$119,IF(COLUMN()-1<=16,'2_Inputs'!$B$120,IF(COLUMN()-1<=28,'2_Inputs'!$B$121,IF(COLUMN()-1<=40,'2_Inputs'!$B$122,'2_Inputs'!$B$123)))) -> 600 | I27: =IF(COLUMN()-1<=4,'2_Inputs'!$B$119,IF(COLUMN()-1<=16,'2_Inputs'!$B$120,IF(COLUMN()-1<=28,'2_Inputs'!$B$121,IF(COLUMN()-1<=40,'2_Inputs'!$B$122,'2_Inputs'!$B$123)))) -> 600 | ... BA27: =IF(COLUMN()-1<=4,'2_Inputs'!$B$119,IF(COLUMN()-1<=16,'2_Inputs'!$B$120,IF(COLUMN()-1<=28,'2_Inputs'!$B$121,IF(COLUMN()-1<=40,'2_Inputs'!$B$122,'2_Inputs'!$B$123)))) -> 1500
A28: Wirtschaftsprüfer | B28: =IF(COLUMN()-1<=4,'2_Inputs'!$B$126,IF(COLUMN()-1<=16,'2_Inputs'!$B$127,IF(COLUMN()-1<=28,'2_Inputs'!$B$128,IF(COLUMN()-1<=40,'2_Inputs'!$B$129,'2_Inputs'!$B$130)))) -> 0 | C28: =IF(COLUMN()-1<=4,'2_Inputs'!$B$126,IF(COLUMN()-1<=16,'2_Inputs'!$B$127,IF(COLUMN()-1<=28,'2_Inputs'!$B$128,IF(COLUMN()-1<=40,'2_Inputs'!$B$129,'2_Inputs'!$B$130)))) -> 0 | D28: =IF(COLUMN()-1<=4,'2_Inputs'!$B$126,IF(COLUMN()-1<=16,'2_Inputs'!$B$127,IF(COLUMN()-1<=28,'2_Inputs'!$B$128,IF(COLUMN()-1<=40,'2_Inputs'!$B$129,'2_Inputs'!$B$130)))) -> 0 | E28: =IF(COLUMN()-1<=4,'2_Inputs'!$B$126,IF(COLUMN()-1<=16,'2_Inputs'!$B$127,IF(COLUMN()-1<=28,'2_Inputs'!$B$128,IF(COLUMN()-1<=40,'2_Inputs'!$B$129,'2_Inputs'!$B$130)))) -> 0 | F28: =IF(COLUMN()-1<=4,'2_Inputs'!$B$126,IF(COLUMN()-1<=16,'2_Inputs'!$B$127,IF(COLUMN()-1<=28,'2_Inputs'!$B$128,IF(COLUMN()-1<=40,'2_Inputs'!$B$129,'2_Inputs'!$B$130)))) -> 0 | G28: =IF(COLUMN()-1<=4,'2_Inputs'!$B$126,IF(COLUMN()-1<=16,'2_Inputs'!$B$127,IF(COLUMN()-1<=28,'2_Inputs'!$B$128,IF(COLUMN()-1<=40,'2_Inputs'!$B$129,'2_Inputs'!$B$130)))) -> 0 | H28: =IF(COLUMN()-1<=4,'2_Inputs'!$B$126,IF(COLUMN()-1<=16,'2_Inputs'!$B$127,IF(COLUMN()-1<=28,'2_Inputs'!$B$128,IF(COLUMN()-1<=40,'2_Inputs'!$B$129,'2_Inputs'!$B$130)))) -> 0 | I28: =IF(COLUMN()-1<=4,'2_Inputs'!$B$126,IF(COLUMN()-1<=16,'2_Inputs'!$B$127,IF(COLUMN()-1<=28,'2_Inputs'!$B$128,IF(COLUMN()-1<=40,'2_Inputs'!$B$129,'2_Inputs'!$B$130)))) -> 0 | ... BA28: =IF(COLUMN()-1<=4,'2_Inputs'!$B$126,IF(COLUMN()-1<=16,'2_Inputs'!$B$127,IF(COLUMN()-1<=28,'2_Inputs'!$B$128,IF(COLUMN()-1<=40,'2_Inputs'!$B$129,'2_Inputs'!$B$130)))) -> 2000
A29: Berater | B29: =IF(COLUMN()-1<=4,'2_Inputs'!$B$133,IF(COLUMN()-1<=16,'2_Inputs'!$B$134,IF(COLUMN()-1<=28,'2_Inputs'!$B$135,IF(COLUMN()-1<=40,'2_Inputs'!$B$136,'2_Inputs'!$B$137)))) -> 0 | C29: =IF(COLUMN()-1<=4,'2_Inputs'!$B$133,IF(COLUMN()-1<=16,'2_Inputs'!$B$134,IF(COLUMN()-1<=28,'2_Inputs'!$B$135,IF(COLUMN()-1<=40,'2_Inputs'!$B$136,'2_Inputs'!$B$137)))) -> 0 | D29: =IF(COLUMN()-1<=4,'2_Inputs'!$B$133,IF(COLUMN()-1<=16,'2_Inputs'!$B$134,IF(COLUMN()-1<=28,'2_Inputs'!$B$135,IF(COLUMN()-1<=40,'2_Inputs'!$B$136,'2_Inputs'!$B$137)))) -> 0 | E29: =IF(COLUMN()-1<=4,'2_Inputs'!$B$133,IF(COLUMN()-1<=16,'2_Inputs'!$B$134,IF(COLUMN()-1<=28,'2_Inputs'!$B$135,IF(COLUMN()-1<=40,'2_Inputs'!$B$136,'2_Inputs'!$B$137)))) -> 0 | F29: =IF(COLUMN()-1<=4,'2_Inputs'!$B$133,IF(COLUMN()-1<=16,'2_Inputs'!$B$134,IF(COLUMN()-1<=28,'2_Inputs'!$B$135,IF(COLUMN()-1<=40,'2_Inputs'!$B$136,'2_Inputs'!$B$137)))) -> 0 | G29: =IF(COLUMN()-1<=4,'2_Inputs'!$B$133,IF(COLUMN()-1<=16,'2_Inputs'!$B$134,IF(COLUMN()-1<=28,'2_Inputs'!$B$135,IF(COLUMN()-1<=40,'2_Inputs'!$B$136,'2_Inputs'!$B$137)))) -> 0 | H29: =IF(COLUMN()-1<=4,'2_Inputs'!$B$133,IF(COLUMN()-1<=16,'2_Inputs'!$B$134,IF(COLUMN()-1<=28,'2_Inputs'!$B$135,IF(COLUMN()-1<=40,'2_Inputs'!$B$136,'2_Inputs'!$B$137)))) -> 0 | I29: =IF(COLUMN()-1<=4,'2_Inputs'!$B$133,IF(COLUMN()-1<=16,'2_Inputs'!$B$134,IF(COLUMN()-1<=28,'2_Inputs'!$B$135,IF(COLUMN()-1<=40,'2_Inputs'!$B$136,'2_Inputs'!$B$137)))) -> 0 | ... BA29: =IF(COLUMN()-1<=4,'2_Inputs'!$B$133,IF(COLUMN()-1<=16,'2_Inputs'!$B$134,IF(COLUMN()-1<=28,'2_Inputs'!$B$135,IF(COLUMN()-1<=40,'2_Inputs'!$B$136,'2_Inputs'!$B$137)))) -> 2000
A30: TOTAL PROFESSIONAL | B30: =SUM(B26:B29) -> 0 | C30: =SUM(C26:C29) -> 0 | D30: =SUM(D26:D29) -> 0 | E30: =SUM(E26:E29) -> 0 | F30: =SUM(F26:F29) -> 1100 | G30: =SUM(G26:G29) -> 1100 | H30: =SUM(H26:H29) -> 1100 | I30: =SUM(I26:I29) -> 1100 | ... BA30: =SUM(BA26:BA29) -> 7000
A31: ── VERSICHERUNG & BANK ──
A32: Versicherungen (D&O, Haftpfl., Cyber) | B32: =IF(COLUMN()-1<=4,'2_Inputs'!$B$147,IF(COLUMN()-1<=16,'2_Inputs'!$B$148,IF(COLUMN()-1<=28,'2_Inputs'!$B$149,IF(COLUMN()-1<=40,'2_Inputs'!$B$150,'2_Inputs'!$B$151)))) -> 42 | C32: =IF(COLUMN()-1<=4,'2_Inputs'!$B$147,IF(COLUMN()-1<=16,'2_Inputs'!$B$148,IF(COLUMN()-1<=28,'2_Inputs'!$B$149,IF(COLUMN()-1<=40,'2_Inputs'!$B$150,'2_Inputs'!$B$151)))) -> 42 | D32: =IF(COLUMN()-1<=4,'2_Inputs'!$B$147,IF(COLUMN()-1<=16,'2_Inputs'!$B$148,IF(COLUMN()-1<=28,'2_Inputs'!$B$149,IF(COLUMN()-1<=40,'2_Inputs'!$B$150,'2_Inputs'!$B$151)))) -> 42 | E32: =IF(COLUMN()-1<=4,'2_Inputs'!$B$147,IF(COLUMN()-1<=16,'2_Inputs'!$B$148,IF(COLUMN()-1<=28,'2_Inputs'!$B$149,IF(COLUMN()-1<=40,'2_Inputs'!$B$150,'2_Inputs'!$B$151)))) -> 42 | F32: =IF(COLUMN()-1<=4,'2_Inputs'!$B$147,IF(COLUMN()-1<=16,'2_Inputs'!$B$148,IF(COLUMN()-1<=28,'2_Inputs'!$B$149,IF(COLUMN()-1<=40,'2_Inputs'!$B$150,'2_Inputs'!$B$151)))) -> 300 | G32: =IF(COLUMN()-1<=4,'2_Inputs'!$B$147,IF(COLUMN()-1<=16,'2_Inputs'!$B$148,IF(COLUMN()-1<=28,'2_Inputs'!$B$149,IF(COLUMN()-1<=40,'2_Inputs'!$B$150,'2_Inputs'!$B$151)))) -> 300 | H32: =IF(COLUMN()-1<=4,'2_Inputs'!$B$147,IF(COLUMN()-1<=16,'2_Inputs'!$B$148,IF(COLUMN()-1<=28,'2_Inputs'!$B$149,IF(COLUMN()-1<=40,'2_Inputs'!$B$150,'2_Inputs'!$B$151)))) -> 300 | I32: =IF(COLUMN()-1<=4,'2_Inputs'!$B$147,IF(COLUMN()-1<=16,'2_Inputs'!$B$148,IF(COLUMN()-1<=28,'2_Inputs'!$B$149,IF(COLUMN()-1<=40,'2_Inputs'!$B$150,'2_Inputs'!$B$151)))) -> 300 | ... BA32: =IF(COLUMN()-1<=4,'2_Inputs'!$B$147,IF(COLUMN()-1<=16,'2_Inputs'!$B$148,IF(COLUMN()-1<=28,'2_Inputs'!$B$149,IF(COLUMN()-1<=40,'2_Inputs'!$B$150,'2_Inputs'!$B$151)))) -> 1200
A33: Bankgebühren | B33: =IF(COLUMN()-1<=4,'2_Inputs'!$B$153,IF(COLUMN()-1<=16,'2_Inputs'!$B$154,IF(COLUMN()-1<=28,'2_Inputs'!$B$155,IF(COLUMN()-1<=40,'2_Inputs'!$B$156,'2_Inputs'!$B$157)))) -> 50 | C33: =IF(COLUMN()-1<=4,'2_Inputs'!$B$153,IF(COLUMN()-1<=16,'2_Inputs'!$B$154,IF(COLUMN()-1<=28,'2_Inputs'!$B$155,IF(COLUMN()-1<=40,'2_Inputs'!$B$156,'2_Inputs'!$B$157)))) -> 50 | D33: =IF(COLUMN()-1<=4,'2_Inputs'!$B$153,IF(COLUMN()-1<=16,'2_Inputs'!$B$154,IF(COLUMN()-1<=28,'2_Inputs'!$B$155,IF(COLUMN()-1<=40,'2_Inputs'!$B$156,'2_Inputs'!$B$157)))) -> 50 | E33: =IF(COLUMN()-1<=4,'2_Inputs'!$B$153,IF(COLUMN()-1<=16,'2_Inputs'!$B$154,IF(COLUMN()-1<=28,'2_Inputs'!$B$155,IF(COLUMN()-1<=40,'2_Inputs'!$B$156,'2_Inputs'!$B$157)))) -> 50 | F33: =IF(COLUMN()-1<=4,'2_Inputs'!$B$153,IF(COLUMN()-1<=16,'2_Inputs'!$B$154,IF(COLUMN()-1<=28,'2_Inputs'!$B$155,IF(COLUMN()-1<=40,'2_Inputs'!$B$156,'2_Inputs'!$B$157)))) -> 150 | G33: =IF(COLUMN()-1<=4,'2_Inputs'!$B$153,IF(COLUMN()-1<=16,'2_Inputs'!$B$154,IF(COLUMN()-1<=28,'2_Inputs'!$B$155,IF(COLUMN()-1<=40,'2_Inputs'!$B$156,'2_Inputs'!$B$157)))) -> 150 | H33: =IF(COLUMN()-1<=4,'2_Inputs'!$B$153,IF(COLUMN()-1<=16,'2_Inputs'!$B$154,IF(COLUMN()-1<=28,'2_Inputs'!$B$155,IF(COLUMN()-1<=40,'2_Inputs'!$B$156,'2_Inputs'!$B$157)))) -> 150 | I33: =IF(COLUMN()-1<=4,'2_Inputs'!$B$153,IF(COLUMN()-1<=16,'2_Inputs'!$B$154,IF(COLUMN()-1<=28,'2_Inputs'!$B$155,IF(COLUMN()-1<=40,'2_Inputs'!$B$156,'2_Inputs'!$B$157)))) -> 150 | ... BA33: =IF(COLUMN()-1<=4,'2_Inputs'!$B$153,IF(COLUMN()-1<=16,'2_Inputs'!$B$154,IF(COLUMN()-1<=28,'2_Inputs'!$B$155,IF(COLUMN()-1<=40,'2_Inputs'!$B$156,'2_Inputs'!$B$157)))) -> 350
A34: Sicherheit & Compliance | B34: =IF(COLUMN()-1<=4,'2_Inputs'!$B$140,IF(COLUMN()-1<=16,'2_Inputs'!$B$141,IF(COLUMN()-1<=28,'2_Inputs'!$B$142,IF(COLUMN()-1<=40,'2_Inputs'!$B$143,'2_Inputs'!$B$144)))) -> 0 | C34: =IF(COLUMN()-1<=4,'2_Inputs'!$B$140,IF(COLUMN()-1<=16,'2_Inputs'!$B$141,IF(COLUMN()-1<=28,'2_Inputs'!$B$142,IF(COLUMN()-1<=40,'2_Inputs'!$B$143,'2_Inputs'!$B$144)))) -> 0 | D34: =IF(COLUMN()-1<=4,'2_Inputs'!$B$140,IF(COLUMN()-1<=16,'2_Inputs'!$B$141,IF(COLUMN()-1<=28,'2_Inputs'!$B$142,IF(COLUMN()-1<=40,'2_Inputs'!$B$143,'2_Inputs'!$B$144)))) -> 0 | E34: =IF(COLUMN()-1<=4,'2_Inputs'!$B$140,IF(COLUMN()-1<=16,'2_Inputs'!$B$141,IF(COLUMN()-1<=28,'2_Inputs'!$B$142,IF(COLUMN()-1<=40,'2_Inputs'!$B$143,'2_Inputs'!$B$144)))) -> 0 | F34: =IF(COLUMN()-1<=4,'2_Inputs'!$B$140,IF(COLUMN()-1<=16,'2_Inputs'!$B$141,IF(COLUMN()-1<=28,'2_Inputs'!$B$142,IF(COLUMN()-1<=40,'2_Inputs'!$B$143,'2_Inputs'!$B$144)))) -> 300 | G34: =IF(COLUMN()-1<=4,'2_Inputs'!$B$140,IF(COLUMN()-1<=16,'2_Inputs'!$B$141,IF(COLUMN()-1<=28,'2_Inputs'!$B$142,IF(COLUMN()-1<=40,'2_Inputs'!$B$143,'2_Inputs'!$B$144)))) -> 300 | H34: =IF(COLUMN()-1<=4,'2_Inputs'!$B$140,IF(COLUMN()-1<=16,'2_Inputs'!$B$141,IF(COLUMN()-1<=28,'2_Inputs'!$B$142,IF(COLUMN()-1<=40,'2_Inputs'!$B$143,'2_Inputs'!$B$144)))) -> 300 | I34: =IF(COLUMN()-1<=4,'2_Inputs'!$B$140,IF(COLUMN()-1<=16,'2_Inputs'!$B$141,IF(COLUMN()-1<=28,'2_Inputs'!$B$142,IF(COLUMN()-1<=40,'2_Inputs'!$B$143,'2_Inputs'!$B$144)))) -> 300 | ... BA34: =IF(COLUMN()-1<=4,'2_Inputs'!$B$140,IF(COLUMN()-1<=16,'2_Inputs'!$B$141,IF(COLUMN()-1<=28,'2_Inputs'!$B$142,IF(COLUMN()-1<=40,'2_Inputs'!$B$143,'2_Inputs'!$B$144)))) -> 300
A35: TOTAL VERSICHERUNG & BANK | B35: =SUM(B32:B34) -> 92 | C35: =SUM(C32:C34) -> 92 | D35: =SUM(D32:D34) -> 92 | E35: =SUM(E32:E34) -> 92 | F35: =SUM(F32:F34) -> 750 | G35: =SUM(G32:G34) -> 750 | H35: =SUM(H32:H34) -> 750 | I35: =SUM(I32:I34) -> 750 | ... BA35: =SUM(BA32:BA34) -> 1850
A36: ── MARKETING & SALES ──
A37: Paid Ads & Content/SEO | B37: =IF(COLUMN()-1<=4,'2_Inputs'!$B$204+'2_Inputs'!$B$210,IF(COLUMN()-1<=16,'2_Inputs'!$B$205+'2_Inputs'!$B$211,IF(COLUMN()-1<=28,'2_Inputs'!$B$206+'2_Inputs'!$B$212,IF(COLUMN()-1<=40,'2_Inputs'!$B$207+'2_Inputs'!$B$213,'2_Inputs'!$B$208+'2_Inputs'!$B$214)))) -> 500 | C37: =IF(COLUMN()-1<=4,'2_Inputs'!$B$204+'2_Inputs'!$B$210,IF(COLUMN()-1<=16,'2_Inputs'!$B$205+'2_Inputs'!$B$211,IF(COLUMN()-1<=28,'2_Inputs'!$B$206+'2_Inputs'!$B$212,IF(COLUMN()-1<=40,'2_Inputs'!$B$207+'2_Inputs'!$B$213,'2_Inputs'!$B$208+'2_Inputs'!$B$214)))) -> 500 | D37: =IF(COLUMN()-1<=4,'2_Inputs'!$B$204+'2_Inputs'!$B$210,IF(COLUMN()-1<=16,'2_Inputs'!$B$205+'2_Inputs'!$B$211,IF(COLUMN()-1<=28,'2_Inputs'!$B$206+'2_Inputs'!$B$212,IF(COLUMN()-1<=40,'2_Inputs'!$B$207+'2_Inputs'!$B$213,'2_Inputs'!$B$208+'2_Inputs'!$B$214)))) -> 500 | E37: =IF(COLUMN()-1<=4,'2_Inputs'!$B$204+'2_Inputs'!$B$210,IF(COLUMN()-1<=16,'2_Inputs'!$B$205+'2_Inputs'!$B$211,IF(COLUMN()-1<=28,'2_Inputs'!$B$206+'2_Inputs'!$B$212,IF(COLUMN()-1<=40,'2_Inputs'!$B$207+'2_Inputs'!$B$213,'2_Inputs'!$B$208+'2_Inputs'!$B$214)))) -> 500 | F37: =IF(COLUMN()-1<=4,'2_Inputs'!$B$204+'2_Inputs'!$B$210,IF(COLUMN()-1<=16,'2_Inputs'!$B$205+'2_Inputs'!$B$211,IF(COLUMN()-1<=28,'2_Inputs'!$B$206+'2_Inputs'!$B$212,IF(COLUMN()-1<=40,'2_Inputs'!$B$207+'2_Inputs'!$B$213,'2_Inputs'!$B$208+'2_Inputs'!$B$214)))) -> 2000 | G37: =IF(COLUMN()-1<=4,'2_Inputs'!$B$204+'2_Inputs'!$B$210,IF(COLUMN()-1<=16,'2_Inputs'!$B$205+'2_Inputs'!$B$211,IF(COLUMN()-1<=28,'2_Inputs'!$B$206+'2_Inputs'!$B$212,IF(COLUMN()-1<=40,'2_Inputs'!$B$207+'2_Inputs'!$B$213,'2_Inputs'!$B$208+'2_Inputs'!$B$214)))) -> 2000 | H37: =IF(COLUMN()-1<=4,'2_Inputs'!$B$204+'2_Inputs'!$B$210,IF(COLUMN()-1<=16,'2_Inputs'!$B$205+'2_Inputs'!$B$211,IF(COLUMN()-1<=28,'2_Inputs'!$B$206+'2_Inputs'!$B$212,IF(COLUMN()-1<=40,'2_Inputs'!$B$207+'2_Inputs'!$B$213,'2_Inputs'!$B$208+'2_Inputs'!$B$214)))) -> 2000 | I37: =IF(COLUMN()-1<=4,'2_Inputs'!$B$204+'2_Inputs'!$B$210,IF(COLUMN()-1<=16,'2_Inputs'!$B$205+'2_Inputs'!$B$211,IF(COLUMN()-1<=28,'2_Inputs'!$B$206+'2_Inputs'!$B$212,IF(COLUMN()-1<=40,'2_Inputs'!$B$207+'2_Inputs'!$B$213,'2_Inputs'!$B$208+'2_Inputs'!$B$214)))) -> 2000 | ... BA37: =IF(COLUMN()-1<=4,'2_Inputs'!$B$204+'2_Inputs'!$B$210,IF(COLUMN()-1<=16,'2_Inputs'!$B$205+'2_Inputs'!$B$211,IF(COLUMN()-1<=28,'2_Inputs'!$B$206+'2_Inputs'!$B$212,IF(COLUMN()-1<=40,'2_Inputs'!$B$207+'2_Inputs'!$B$213,'2_Inputs'!$B$208+'2_Inputs'!$B$214)))) -> 15000
A38: Events & Messen | B38: =IF(COLUMN()-1>='2_Inputs'!$B$16,25000/12,IF(COLUMN()-1>='2_Inputs'!$B$14,15000/12,IF(COLUMN()-1>='2_Inputs'!$B$12,10000/12,3000/12))) -> 833.33333 | C38: =IF(COLUMN()-1>='2_Inputs'!$B$16,25000/12,IF(COLUMN()-1>='2_Inputs'!$B$14,15000/12,IF(COLUMN()-1>='2_Inputs'!$B$12,10000/12,3000/12))) -> 833.33333 | D38: =IF(COLUMN()-1>='2_Inputs'!$B$16,25000/12,IF(COLUMN()-1>='2_Inputs'!$B$14,15000/12,IF(COLUMN()-1>='2_Inputs'!$B$12,10000/12,3000/12))) -> 833.33333 | E38: =IF(COLUMN()-1>='2_Inputs'!$B$16,25000/12,IF(COLUMN()-1>='2_Inputs'!$B$14,15000/12,IF(COLUMN()-1>='2_Inputs'!$B$12,10000/12,3000/12))) -> 833.33333 | F38: =IF(COLUMN()-1>='2_Inputs'!$B$16,25000/12,IF(COLUMN()-1>='2_Inputs'!$B$14,15000/12,IF(COLUMN()-1>='2_Inputs'!$B$12,10000/12,3000/12))) -> 833.33333 | G38: =IF(COLUMN()-1>='2_Inputs'!$B$16,25000/12,IF(COLUMN()-1>='2_Inputs'!$B$14,15000/12,IF(COLUMN()-1>='2_Inputs'!$B$12,10000/12,3000/12))) -> 833.33333 | H38: =IF(COLUMN()-1>='2_Inputs'!$B$16,25000/12,IF(COLUMN()-1>='2_Inputs'!$B$14,15000/12,IF(COLUMN()-1>='2_Inputs'!$B$12,10000/12,3000/12))) -> 833.33333 | I38: =IF(COLUMN()-1>='2_Inputs'!$B$16,25000/12,IF(COLUMN()-1>='2_Inputs'!$B$14,15000/12,IF(COLUMN()-1>='2_Inputs'!$B$12,10000/12,3000/12))) -> 833.33333 | ... BA38: =IF(COLUMN()-1>='2_Inputs'!$B$16,25000/12,IF(COLUMN()-1>='2_Inputs'!$B$14,15000/12,IF(COLUMN()-1>='2_Inputs'!$B$12,10000/12,3000/12))) -> 2083.3333
A39: Sales Tools & Provisionen | B39: =300+'4_Revenue'!B26/12*0.02 -> 300 | C39: =300+'4_Revenue'!C26/12*0.02 -> 300 | D39: =300+'4_Revenue'!D26/12*0.02 -> 300 | E39: =300+'4_Revenue'!E26/12*0.02 -> 300 | F39: =300+'4_Revenue'!F26/12*0.02 -> 300 | G39: =300+'4_Revenue'!G26/12*0.02 -> 300 | H39: =300+'4_Revenue'!H26/12*0.02 -> 355.2 | I39: =300+'4_Revenue'!I26/12*0.02 -> 355.2 | ... BA39: =300+'4_Revenue'!BA26/12*0.02 -> 20512.192
A40: TOTAL MARKETING & SALES | B40: =SUM(B37:B39) -> 1633.3333 | C40: =SUM(C37:C39) -> 1633.3333 | D40: =SUM(D37:D39) -> 1633.3333 | E40: =SUM(E37:E39) -> 1633.3333 | F40: =SUM(F37:F39) -> 3133.3333 | G40: =SUM(G37:G39) -> 3133.3333 | H40: =SUM(H37:H39) -> 3188.5333 | I40: =SUM(I37:I39) -> 3188.5333 | ... BA40: =SUM(BA37:BA39) -> 37595.526
A41: ── SONSTIGE KOSTEN ──
A42: Reisekosten & Weiterbildung | B42: =IF(COLUMN()-1<=4,'2_Inputs'!$B$160,IF(COLUMN()-1<=16,'2_Inputs'!$B$161,IF(COLUMN()-1<=28,'2_Inputs'!$B$162,IF(COLUMN()-1<=40,'2_Inputs'!$B$163,'2_Inputs'!$B$164))))+'2_Inputs'!$B$165*(IF(AND(COLUMN()-1>='2_Inputs'!$B$184,'2_Inputs'!$C$184="JA"),1,0)+IF(AND(COLUMN()-1>='2_Inputs'!$B$185,'2_Inputs'!$C$185="JA"),1,0)+IF(AND(COLUMN()-1>='2_Inputs'!$B$186,'2_Inputs'!$C$186="JA"),1,0)+IF(AND(COLUMN()-1>='2_Inputs'!$B$191,'2_Inputs'!$C$191="JA"),1,0)) -> 300 | C42: =IF(COLUMN()-1<=4,'2_Inputs'!$B$160,IF(COLUMN()-1<=16,'2_Inputs'!$B$161,IF(COLUMN()-1<=28,'2_Inputs'!$B$162,IF(COLUMN()-1<=40,'2_Inputs'!$B$163,'2_Inputs'!$B$164))))+'2_Inputs'!$B$165*(IF(AND(COLUMN()-1>='2_Inputs'!$B$184,'2_Inputs'!$C$184="JA"),1,0)+IF(AND(COLUMN()-1>='2_Inputs'!$B$185,'2_Inputs'!$C$185="JA"),1,0)+IF(AND(COLUMN()-1>='2_Inputs'!$B$186,'2_Inputs'!$C$186="JA"),1,0)+IF(AND(COLUMN()-1>='2_Inputs'!$B$191,'2_Inputs'!$C$191="JA"),1,0)) -> 300 | D42: =IF(COLUMN()-1<=4,'2_Inputs'!$B$160,IF(COLUMN()-1<=16,'2_Inputs'!$B$161,IF(COLUMN()-1<=28,'2_Inputs'!$B$162,IF(COLUMN()-1<=40,'2_Inputs'!$B$163,'2_Inputs'!$B$164))))+'2_Inputs'!$B$165*(IF(AND(COLUMN()-1>='2_Inputs'!$B$184,'2_Inputs'!$C$184="JA"),1,0)+IF(AND(COLUMN()-1>='2_Inputs'!$B$185,'2_Inputs'!$C$185="JA"),1,0)+IF(AND(COLUMN()-1>='2_Inputs'!$B$186,'2_Inputs'!$C$186="JA"),1,0)+IF(AND(COLUMN()-1>='2_Inputs'!$B$191,'2_Inputs'!$C$191="JA"),1,0)) -> 300 | E42: =IF(COLUMN()-1<=4,'2_Inputs'!$B$160,IF(COLUMN()-1<=16,'2_Inputs'!$B$161,IF(COLUMN()-1<=28,'2_Inputs'!$B$162,IF(COLUMN()-1<=40,'2_Inputs'!$B$163,'2_Inputs'!$B$164))))+'2_Inputs'!$B$165*(IF(AND(COLUMN()-1>='2_Inputs'!$B$184,'2_Inputs'!$C$184="JA"),1,0)+IF(AND(COLUMN()-1>='2_Inputs'!$B$185,'2_Inputs'!$C$185="JA"),1,0)+IF(AND(COLUMN()-1>='2_Inputs'!$B$186,'2_Inputs'!$C$186="JA"),1,0)+IF(AND(COLUMN()-1>='2_Inputs'!$B$191,'2_Inputs'!$C$191="JA"),1,0)) -> 300 | F42: =IF(COLUMN()-1<=4,'2_Inputs'!$B$160,IF(COLUMN()-1<=16,'2_Inputs'!$B$161,IF(COLUMN()-1<=28,'2_Inputs'!$B$162,IF(COLUMN()-1<=40,'2_Inputs'!$B$163,'2_Inputs'!$B$164))))+'2_Inputs'!$B$165*(IF(AND(COLUMN()-1>='2_Inputs'!$B$184,'2_Inputs'!$C$184="JA"),1,0)+IF(AND(COLUMN()-1>='2_Inputs'!$B$185,'2_Inputs'!$C$185="JA"),1,0)+IF(AND(COLUMN()-1>='2_Inputs'!$B$186,'2_Inputs'!$C$186="JA"),1,0)+IF(AND(COLUMN()-1>='2_Inputs'!$B$191,'2_Inputs'!$C$191="JA"),1,0)) -> 1400 | G42: =IF(COLUMN()-1<=4,'2_Inputs'!$B$160,IF(COLUMN()-1<=16,'2_Inputs'!$B$161,IF(COLUMN()-1<=28,'2_Inputs'!$B$162,IF(COLUMN()-1<=40,'2_Inputs'!$B$163,'2_Inputs'!$B$164))))+'2_Inputs'!$B$165*(IF(AND(COLUMN()-1>='2_Inputs'!$B$184,'2_Inputs'!$C$184="JA"),1,0)+IF(AND(COLUMN()-1>='2_Inputs'!$B$185,'2_Inputs'!$C$185="JA"),1,0)+IF(AND(COLUMN()-1>='2_Inputs'!$B$186,'2_Inputs'!$C$186="JA"),1,0)+IF(AND(COLUMN()-1>='2_Inputs'!$B$191,'2_Inputs'!$C$191="JA"),1,0)) -> 1400 | H42: =IF(COLUMN()-1<=4,'2_Inputs'!$B$160,IF(COLUMN()-1<=16,'2_Inputs'!$B$161,IF(COLUMN()-1<=28,'2_Inputs'!$B$162,IF(COLUMN()-1<=40,'2_Inputs'!$B$163,'2_Inputs'!$B$164))))+'2_Inputs'!$B$165*(IF(AND(COLUMN()-1>='2_Inputs'!$B$184,'2_Inputs'!$C$184="JA"),1,0)+IF(AND(COLUMN()-1>='2_Inputs'!$B$185,'2_Inputs'!$C$185="JA"),1,0)+IF(AND(COLUMN()-1>='2_Inputs'!$B$186,'2_Inputs'!$C$186="JA"),1,0)+IF(AND(COLUMN()-1>='2_Inputs'!$B$191,'2_Inputs'!$C$191="JA"),1,0)) -> 1400 | I42: =IF(COLUMN()-1<=4,'2_Inputs'!$B$160,IF(COLUMN()-1<=16,'2_Inputs'!$B$161,IF(COLUMN()-1<=28,'2_Inputs'!$B$162,IF(COLUMN()-1<=40,'2_Inputs'!$B$163,'2_Inputs'!$B$164))))+'2_Inputs'!$B$165*(IF(AND(COLUMN()-1>='2_Inputs'!$B$184,'2_Inputs'!$C$184="JA"),1,0)+IF(AND(COLUMN()-1>='2_Inputs'!$B$185,'2_Inputs'!$C$185="JA"),1,0)+IF(AND(COLUMN()-1>='2_Inputs'!$B$186,'2_Inputs'!$C$186="JA"),1,0)+IF(AND(COLUMN()-1>='2_Inputs'!$B$191,'2_Inputs'!$C$191="JA"),1,0)) -> 1400 | ... BA42: =IF(COLUMN()-1<=4,'2_Inputs'!$B$160,IF(COLUMN()-1<=16,'2_Inputs'!$B$161,IF(COLUMN()-1<=28,'2_Inputs'!$B$162,IF(COLUMN()-1<=40,'2_Inputs'!$B$163,'2_Inputs'!$B$164))))+'2_Inputs'!$B$165*(IF(AND(COLUMN()-1>='2_Inputs'!$B$184,'2_Inputs'!$C$184="JA"),1,0)+IF(AND(COLUMN()-1>='2_Inputs'!$B$185,'2_Inputs'!$C$185="JA"),1,0)+IF(AND(COLUMN()-1>='2_Inputs'!$B$186,'2_Inputs'!$C$186="JA"),1,0)+IF(AND(COLUMN()-1>='2_Inputs'!$B$191,'2_Inputs'!$C$191="JA"),1,0)) -> 7400
A43: Team Events | B43: =IF(COLUMN()-1<=4,'2_Inputs'!$B$168,IF(COLUMN()-1<=16,'2_Inputs'!$B$169,IF(COLUMN()-1<=28,'2_Inputs'!$B$170,IF(COLUMN()-1<=40,'2_Inputs'!$B$171,'2_Inputs'!$B$172)))) -> 50 | C43: =IF(COLUMN()-1<=4,'2_Inputs'!$B$168,IF(COLUMN()-1<=16,'2_Inputs'!$B$169,IF(COLUMN()-1<=28,'2_Inputs'!$B$170,IF(COLUMN()-1<=40,'2_Inputs'!$B$171,'2_Inputs'!$B$172)))) -> 50 | D43: =IF(COLUMN()-1<=4,'2_Inputs'!$B$168,IF(COLUMN()-1<=16,'2_Inputs'!$B$169,IF(COLUMN()-1<=28,'2_Inputs'!$B$170,IF(COLUMN()-1<=40,'2_Inputs'!$B$171,'2_Inputs'!$B$172)))) -> 50 | E43: =IF(COLUMN()-1<=4,'2_Inputs'!$B$168,IF(COLUMN()-1<=16,'2_Inputs'!$B$169,IF(COLUMN()-1<=28,'2_Inputs'!$B$170,IF(COLUMN()-1<=40,'2_Inputs'!$B$171,'2_Inputs'!$B$172)))) -> 50 | F43: =IF(COLUMN()-1<=4,'2_Inputs'!$B$168,IF(COLUMN()-1<=16,'2_Inputs'!$B$169,IF(COLUMN()-1<=28,'2_Inputs'!$B$170,IF(COLUMN()-1<=40,'2_Inputs'!$B$171,'2_Inputs'!$B$172)))) -> 250 | G43: =IF(COLUMN()-1<=4,'2_Inputs'!$B$168,IF(COLUMN()-1<=16,'2_Inputs'!$B$169,IF(COLUMN()-1<=28,'2_Inputs'!$B$170,IF(COLUMN()-1<=40,'2_Inputs'!$B$171,'2_Inputs'!$B$172)))) -> 250 | H43: =IF(COLUMN()-1<=4,'2_Inputs'!$B$168,IF(COLUMN()-1<=16,'2_Inputs'!$B$169,IF(COLUMN()-1<=28,'2_Inputs'!$B$170,IF(COLUMN()-1<=40,'2_Inputs'!$B$171,'2_Inputs'!$B$172)))) -> 250 | I43: =IF(COLUMN()-1<=4,'2_Inputs'!$B$168,IF(COLUMN()-1<=16,'2_Inputs'!$B$169,IF(COLUMN()-1<=28,'2_Inputs'!$B$170,IF(COLUMN()-1<=40,'2_Inputs'!$B$171,'2_Inputs'!$B$172)))) -> 250 | ... BA43: =IF(COLUMN()-1<=4,'2_Inputs'!$B$168,IF(COLUMN()-1<=16,'2_Inputs'!$B$169,IF(COLUMN()-1<=28,'2_Inputs'!$B$170,IF(COLUMN()-1<=40,'2_Inputs'!$B$171,'2_Inputs'!$B$172)))) -> 1000
A44: Puffer/Unvorhergesehenes | B44: =0 -> 0 | C44: =0 -> 0 | D44: =0 -> 0 | E44: =0 -> 0 | F44: =0 -> 0 | G44: =0 -> 0 | H44: =0 -> 0 | I44: =0 -> 0 | ... BA44: =0 -> 0
A45: TOTAL SONSTIGE | B45: =SUM(B42:B44) -> 350 | C45: =SUM(C42:C44) -> 350 | D45: =SUM(D42:D44) -> 350 | E45: =SUM(E42:E44) -> 350 | F45: =SUM(F42:F44) -> 1650 | G45: =SUM(G42:G44) -> 1650 | H45: =SUM(H42:H44) -> 1650 | I45: =SUM(I42:I44) -> 1650 | ... BA45: =SUM(BA42:BA44) -> 8400
A46: ── PAYMENT PROCESSING ──
A47: Payment Processing Fees | B47: ='4_Revenue'!B25*'2_Inputs'!$B$173 -> 0 | C47: ='4_Revenue'!C25*'2_Inputs'!$B$173 -> 0 | D47: ='4_Revenue'!D25*'2_Inputs'!$B$173 -> 0 | E47: ='4_Revenue'!E25*'2_Inputs'!$B$173 -> 0 | F47: ='4_Revenue'!F25*'2_Inputs'!$B$173 -> 0 | G47: ='4_Revenue'!G25*'2_Inputs'!$B$173 -> 0 | H47: ='4_Revenue'!H25*'2_Inputs'!$B$173 -> 69 | I47: ='4_Revenue'!I25*'2_Inputs'!$B$173 -> 69 | ... BA47: ='4_Revenue'!BA25*'2_Inputs'!$B$173 -> 25265.24
A48: TOTAL PAYMENT | B48: =B47 -> 0 | C48: =C47 -> 0 | D48: =D47 -> 0 | E48: =E47 -> 0 | F48: =F47 -> 0 | G48: =G47 -> 0 | H48: =H47 -> 69 | I48: =I47 -> 69 | ... BA48: =BA47 -> 25265.24
A50: TOTAL KOSTEN (exkl. COGS) | B50: =B13+B18+B24+B30+B35+B40+B45+B48 -> 2075.3333 | C50: =C13+C18+C24+C30+C35+C40+C45+C48 -> 2075.3333 | D50: =D13+D18+D24+D30+D35+D40+D45+D48 -> 2075.3333 | E50: =E13+E18+E24+E30+E35+E40+E45+E48 -> 2075.3333 | F50: =F13+F18+F24+F30+F35+F40+F45+F48 -> 33133.333 | G50: =G13+G18+G24+G30+G35+G40+G45+G48 -> 40947.333 | H50: =H13+H18+H24+H30+H35+H40+H45+H48 -> 41611.533 | I50: =I13+I18+I24+I30+I35+I40+I45+I48 -> 41611.533 | ... BA50: =BA13+BA18+BA24+BA30+BA35+BA40+BA45+BA48 -> 357486.69
B90: Cloud Hosting Basis ist eine Fee, die jeden Monat anfällt. Cloud Pro Seat ist eine zusätzliche Fee, die abhängig ist von den verkauften Seats im jeweiligen Monat. Somit ist also die Cloud Fee

Sheet 6_P&L
A1: GEWINN- UND VERLUSTRECHNUNG (P&L) | AP1: Series B not modelled yet | AR1: `-->
A2: Startup-Phase | B2: Ideation | C2: Ideation | D2: Ideation | E2: Ideation | F2: Pre-Seed | G2: Pre-Seed | H2: Pre-Seed | I2: Pre-Seed | J2: Pre-Seed | K2: Pre-Seed | L2: Pre-Seed | M2: Pre-Seed | N2: Pre-Seed | O2: Pre-Seed | P2: Pre-Seed | Q2: Pre-Seed | R2: Seed | S2: Seed | T2: Seed | U2: Seed | V2: Seed | W2: Seed | X2: Seed | Y2: Seed | Z2: Seed | AA2: Seed | AB2: Seed | AC2: Seed | AD2: Series A | AE2: Series A | AF2: Series A | AG2: Series A | AH2: Series A | AI2: Series A | AJ2: Series A | AK2: Series A | AL2: Series A | AM2: Series A | AN2: Series A | AO2: Series A | AP2: Series B | AQ2: Series B | AR2: Series B | AS2: Series B | AT2: Series B | AU2: Series B | AV2: Series B | AW2: Series B | AX2: Series B | AY2: Series B | AZ2: Series B | BA2: Series B
A3: Position | B3: M1 | C3: M2 | D3: M3 | E3: M4 | F3: M5 | G3: M6 | H3: M7 | I3: M8 | J3: M9 | K3: M10 | L3: M11 | M3: M12 | N3: M13 | O3: M14 | P3: M15 | Q3: M16 | R3: M17 | S3: M18 | T3: M19 | U3: M20 | V3: M21 | W3: M22 | X3: M23 | Y3: M24 | Z3: M25 | AA3: M26 | AB3: M27 | AC3: M28 | AD3: M29 | AE3: M30 | AF3: M31 | AG3: M32 | AH3: M33 | AI3: M34 | AJ3: M35 | AK3: M36 | AL3: M37 | AM3: M38 | AN3: M39 | AO3: M40 | AP3: M41 | AQ3: M42 | AR3: M43 | AS3: M44 | AT3: M45 | AU3: M46 | AV3: M47 | AW3: M48 | AX3: M49 | AY3: M50 | AZ3: M51 | BA3: M52
A4: REVENUE
A5: Seat Revenue (SME + Mid) | B5: ='4_Revenue'!B10+'4_Revenue'!B17 -> 0 | C5: ='4_Revenue'!C10+'4_Revenue'!C17 -> 0 | D5: ='4_Revenue'!D10+'4_Revenue'!D17 -> 0 | E5: ='4_Revenue'!E10+'4_Revenue'!E17 -> 0 | F5: ='4_Revenue'!F10+'4_Revenue'!F17 -> 0 | G5: ='4_Revenue'!G10+'4_Revenue'!G17 -> 0 | H5: ='4_Revenue'!H10+'4_Revenue'!H17 -> 2760 | I5: ='4_Revenue'!I10+'4_Revenue'!I17 -> 2760 | ... BA5: ='4_Revenue'!BA10+'4_Revenue'!BA17 -> 956991.1
A6: Enterprise Revenue (Jahres-Fee) | B6: ='4_Revenue'!B23 -> 0 | C6: ='4_Revenue'!C23 -> 0 | D6: ='4_Revenue'!D23 -> 0 | E6: ='4_Revenue'!E23 -> 0 | F6: ='4_Revenue'!F23 -> 0 | G6: ='4_Revenue'!G23 -> 0 | H6: ='4_Revenue'!H23 -> 0 | I6: ='4_Revenue'!I23 -> 0 | ... BA6: ='4_Revenue'!BA23 -> 53618.517
A7: Implementation Support Revenue | B7: ='4_Revenue'!B30 -> 0 | C7: ='4_Revenue'!C30 -> 0 | D7: ='4_Revenue'!D30 -> 0 | E7: ='4_Revenue'!E30 -> 0 | F7: ='4_Revenue'!F30 -> 0 | G7: ='4_Revenue'!G30 -> 0 | H7: ='4_Revenue'!H30 -> 30000 | I7: ='4_Revenue'!I30 -> 0 | ... BA7: ='4_Revenue'!BA30 -> 300000
A8: TOTAL REVENUE | B8: =SUM(B5:B7) -> 0 | C8: =SUM(C5:C7) -> 0 | D8: =SUM(D5:D7) -> 0 | E8: =SUM(E5:E7) -> 0 | F8: =SUM(F5:F7) -> 0 | G8: =SUM(G5:G7) -> 0 | H8: =SUM(H5:H7) -> 32760 | I8: =SUM(I5:I7) -> 2760 | ... BA8: =SUM(BA5:BA7) -> 1310609.6
A10: COST OF GOODS SOLD (COGS)
A11: Cloud Hosting (variable) | B11: ='5_Costs'!B15 -> 0 | C11: ='5_Costs'!C15 -> 0 | D11: ='5_Costs'!D15 -> 0 | E11: ='5_Costs'!E15 -> 0 | F11: ='5_Costs'!F15 -> 0 | G11: ='5_Costs'!G15 -> 0 | H11: ='5_Costs'!H15 -> 540 | I11: ='5_Costs'!I15 -> 540 | ... BA11: ='5_Costs'!BA15 -> 150210
A12: AI/ML API Kosten | B12: ='5_Costs'!B16 -> 0 | C12: ='5_Costs'!C16 -> 0 | D12: ='5_Costs'!D16 -> 0 | E12: ='5_Costs'!E16 -> 0 | F12: ='5_Costs'!F16 -> 300 | G12: ='5_Costs'!G16 -> 400 | H12: ='5_Costs'!H16 -> 400 | I12: ='5_Costs'!I16 -> 400 | ... BA12: ='5_Costs'!BA16 -> 4200
A13: Payment Processing | B13: ='5_Costs'!B47 -> 0 | C13: ='5_Costs'!C47 -> 0 | D13: ='5_Costs'!D47 -> 0 | E13: ='5_Costs'!E47 -> 0 | F13: ='5_Costs'!F47 -> 0 | G13: ='5_Costs'!G47 -> 0 | H13: ='5_Costs'!H47 -> 69 | I13: ='5_Costs'!I47 -> 69 | ... BA13: ='5_Costs'!BA47 -> 25265.24
A14: TOTAL COGS | B14: =SUM(B11:B13) -> 0 | C14: =SUM(C11:C13) -> 0 | D14: =SUM(D11:D13) -> 0 | E14: =SUM(E11:E13) -> 0 | F14: =SUM(F11:F13) -> 300 | G14: =SUM(G11:G13) -> 400 | H14: =SUM(H11:H13) -> 1009 | I14: =SUM(I11:I13) -> 1009 | ... BA14: =SUM(BA11:BA13) -> 179675.24
A16: GROSS PROFIT | B16: =B8-B14 -> 0 | C16: =C8-C14 -> 0 | D16: =D8-D14 -> 0 | E16: =E8-E14 -> 0 | F16: =F8-F14 -> -300 | G16: =G8-G14 -> -400 | H16: =H8-H14 -> 31751 | I16: =I8-I14 -> 1751 | ... BA16: =BA8-BA14 -> 1130934.4
A17: Gross Margin % | B17: =IFERROR(B16/B8,0) -> 0 | C17: =IFERROR(C16/C8,0) -> 0 | D17: =IFERROR(D16/D8,0) -> 0 | E17: =IFERROR(E16/E8,0) -> 0 | F17: =IFERROR(F16/F8,0) -> 0 | G17: =IFERROR(G16/G8,0) -> 0 | H17: =IFERROR(H16/H8,0) -> 0.96920024 | I17: =IFERROR(I16/I8,0) -> 0.63442029 | ... BA17: =IFERROR(BA16/BA8,0) -> 0.86290712
A19: OPERATING EXPENSES
A20: Total Personnel | B20: ='5_Costs'!B13 -> 0 | C20: ='5_Costs'!C13 -> 0 | D20: ='5_Costs'!D13 -> 0 | E20: ='5_Costs'!E13 -> 0 | F20: ='5_Costs'!F13 -> 25000 | G20: ='5_Costs'!G13 -> 32714 | H20: ='5_Costs'!H13 -> 32714 | I20: ='5_Costs'!I13 -> 32714 | ... BA20: ='5_Costs'!BA13 -> 115425.93
A21: Total Technology | B21: ='5_Costs'!B18 -> 0 | C21: ='5_Costs'!C18 -> 0 | D21: ='5_Costs'!D18 -> 0 | E21: ='5_Costs'!E18 -> 0 | F21: ='5_Costs'!F18 -> 700 | G21: ='5_Costs'!G18 -> 800 | H21: ='5_Costs'!H18 -> 1340 | I21: ='5_Costs'!I18 -> 1340 | ... BA21: ='5_Costs'!BA18 -> 156910
A22: Total Office | B22: ='5_Costs'!B24 -> 0 | C22: ='5_Costs'!C24 -> 0 | D22: ='5_Costs'!D24 -> 0 | E22: ='5_Costs'!E24 -> 0 | F22: ='5_Costs'!F24 -> 800 | G22: ='5_Costs'!G24 -> 800 | H22: ='5_Costs'!H24 -> 800 | I22: ='5_Costs'!I24 -> 800 | ... BA22: ='5_Costs'!BA24 -> 5040
A23: Total Professional Services | B23: ='5_Costs'!B30 -> 0 | C23: ='5_Costs'!C30 -> 0 | D23: ='5_Costs'!D30 -> 0 | E23: ='5_Costs'!E30 -> 0 | F23: ='5_Costs'!F30 -> 1100 | G23: ='5_Costs'!G30 -> 1100 | H23: ='5_Costs'!H30 -> 1100 | I23: ='5_Costs'!I30 -> 1100 | ... BA23: ='5_Costs'!BA30 -> 7000
A24: Total Insurance & Bank | B24: ='5_Costs'!B35 -> 92 | C24: ='5_Costs'!C35 -> 92 | D24: ='5_Costs'!D35 -> 92 | E24: ='5_Costs'!E35 -> 92 | F24: ='5_Costs'!F35 -> 750 | G24: ='5_Costs'!G35 -> 750 | H24: ='5_Costs'!H35 -> 750 | I24: ='5_Costs'!I35 -> 750 | ... BA24: ='5_Costs'!BA35 -> 1850
A25: Total Marketing & Sales | B25: ='5_Costs'!B40 -> 1633.3333 | C25: ='5_Costs'!C40 -> 1633.3333 | D25: ='5_Costs'!D40 -> 1633.3333 | E25: ='5_Costs'!E40 -> 1633.3333 | F25: ='5_Costs'!F40 -> 3133.3333 | G25: ='5_Costs'!G40 -> 3133.3333 | H25: ='5_Costs'!H40 -> 3188.5333 | I25: ='5_Costs'!I40 -> 3188.5333 | ... BA25: ='5_Costs'!BA40 -> 37595.526
A26: Total Other OpEx | B26: ='5_Costs'!B45 -> 350 | C26: ='5_Costs'!C45 -> 350 | D26: ='5_Costs'!D45 -> 350 | E26: ='5_Costs'!E45 -> 350 | F26: ='5_Costs'!F45 -> 1650 | G26: ='5_Costs'!G45 -> 1650 | H26: ='5_Costs'!H45 -> 1650 | I26: ='5_Costs'!I45 -> 1650 | ... BA26: ='5_Costs'!BA45 -> 8400
A27: TOTAL OPERATING EXPENSES | B27: =SUM(B20:B26) -> 2075.3333 | C27: =SUM(C20:C26) -> 2075.3333 | D27: =SUM(D20:D26) -> 2075.3333 | E27: =SUM(E20:E26) -> 2075.3333 | F27: =SUM(F20:F26) -> 33133.333 | G27: =SUM(G20:G26) -> 40947.333 | H27: =SUM(H20:H26) -> 41542.533 | I27: =SUM(I20:I26) -> 41542.533 | ... BA27: =SUM(BA20:BA26) -> 332221.45
A29: EBITDA | B29: =B16-B27 -> -2075.3333 | C29: =C16-C27 -> -2075.3333 | D29: =D16-D27 -> -2075.3333 | E29: =E16-E27 -> -2075.3333 | F29: =F16-F27 -> -33433.333 | G29: =G16-G27 -> -41347.333 | H29: =H16-H27 -> -9791.5333 | I29: =I16-I27 -> -39791.533 | ... BA29: =BA16-BA27 -> 798712.92
A30: EBITDA Margin % | B30: =IFERROR(B29/B8,0) -> 0 | C30: =IFERROR(C29/C8,0) -> 0 | D30: =IFERROR(D29/D8,0) -> 0 | E30: =IFERROR(E29/E8,0) -> 0 | F30: =IFERROR(F29/F8,0) -> 0 | G30: =IFERROR(G29/G8,0) -> 0 | H30: =IFERROR(H29/H8,0) -> -0.29888685 | I30: =IFERROR(I29/I8,0) -> -14.417222 | ... BA30: =IFERROR(BA29/BA8,0) -> 0.60942092
A32: EBIT (Operating Income) | B32: =B29 -> -2075.3333 | C32: =C29 -> -2075.3333 | D32: =D29 -> -2075.3333 | E32: =E29 -> -2075.3333 | F32: =F29 -> -33433.333 | G32: =G29 -> -41347.333 | H32: =H29 -> -9791.5333 | I32: =I29 -> -39791.533 | ... BA32: =BA29 -> 798712.92
A34: EBT (Earnings Before Tax) | B34: =B32 -> -2075.3333 | C34: =C32 -> -2075.3333 | D34: =D32 -> -2075.3333 | E34: =E32 -> -2075.3333 | F34: =F32 -> -33433.333 | G34: =G32 -> -41347.333 | H34: =H32 -> -9791.5333 | I34: =I32 -> -39791.533 | ... BA34: =BA32 -> 798712.92
A35: Income Tax | B35: =IF(B34>0,B34*'2_Inputs'!$B$6,0) -> 0 | C35: =IF(C34>0,C34*'2_Inputs'!$B$6,0) -> 0 | D35: =IF(D34>0,D34*'2_Inputs'!$B$6,0) -> 0 | E35: =IF(E34>0,E34*'2_Inputs'!$B$6,0) -> 0 | F35: =IF(F34>0,F34*'2_Inputs'!$B$6,0) -> 0 | G35: =IF(G34>0,G34*'2_Inputs'!$B$6,0) -> 0 | H35: =IF(H34>0,H34*'2_Inputs'!$B$6,0) -> 0 | I35: =IF(I34>0,I34*'2_Inputs'!$B$6,0) -> 0 | ... BA35: =IF(BA34>0,BA34*'2_Inputs'!$B$6,0) -> 239613.88
A37: NET INCOME | B37: =B34-B35 -> -2075.3333 | C37: =C34-C35 -> -2075.3333 | D37: =D34-D35 -> -2075.3333 | E37: =E34-E35 -> -2075.3333 | F37: =F34-F35 -> -33433.333 | G37: =G34-G35 -> -41347.333 | H37: =H34-H35 -> -9791.5333 | I37: =I34-I35 -> -39791.533 | ... BA37: =BA34-BA35 -> 559099.05
A38: Net Margin % | B38: =IFERROR(B37/B8,0) -> 0 | C38: =IFERROR(C37/C8,0) -> 0 | D38: =IFERROR(D37/D8,0) -> 0 | E38: =IFERROR(E37/E8,0) -> 0 | F38: =IFERROR(F37/F8,0) -> 0 | G38: =IFERROR(G37/G8,0) -> 0 | H38: =IFERROR(H37/H8,0) -> -0.29888685 | I38: =IFERROR(I37/I8,0) -> -14.417222 | ... BA38: =IFERROR(BA37/BA8,0) -> 0.42659465
Q39: =SUM(F37:Q37) -> -505580.12

Sheet 7_BS_CF
A1: BILANZ & CASH FLOW | AP1: Series B not modelled yet | AR1: `-->
A2: Startup-Phase | B2: Ideation | C2: Ideation | D2: Ideation | E2: Ideation | F2: Pre-Seed | G2: Pre-Seed | H2: Pre-Seed | I2: Pre-Seed | J2: Pre-Seed | K2: Pre-Seed | L2: Pre-Seed | M2: Pre-Seed | N2: Pre-Seed | O2: Pre-Seed | P2: Pre-Seed | Q2: Pre-Seed | R2: Seed | S2: Seed | T2: Seed | U2: Seed | V2: Seed | W2: Seed | X2: Seed | Y2: Seed | Z2: Seed | AA2: Seed | AB2: Seed | AC2: Seed | AD2: Series A | AE2: Series A | AF2: Series A | AG2: Series A | AH2: Series A | AI2: Series A | AJ2: Series A | AK2: Series A | AL2: Series A | AM2: Series A | AN2: Series A | AO2: Series A | AP2: Series B | AQ2: Series B | AR2: Series B | AS2: Series B | AT2: Series B | AU2: Series B | AV2: Series B | AW2: Series B | AX2: Series B | AY2: Series B | AZ2: Series B | BA2: Series B
A3: Position | B3: M1 | C3: M2 | D3: M3 | E3: M4 | F3: M5 | G3: M6 | H3: M7 | I3: M8 | J3: M9 | K3: M10 | L3: M11 | M3: M12 | N3: M13 | O3: M14 | P3: M15 | Q3: M16 | R3: M17 | S3: M18 | T3: M19 | U3: M20 | V3: M21 | W3: M22 | X3: M23 | Y3: M24 | Z3: M25 | AA3: M26 | AB3: M27 | AC3: M28 | AD3: M29 | AE3: M30 | AF3: M31 | AG3: M32 | AH3: M33 | AI3: M34 | AJ3: M35 | AK3: M36 | AL3: M37 | AM3: M38 | AN3: M39 | AO3: M40 | AP3: M41 | AQ3: M42 | AR3: M43 | AS3: M44 | AT3: M45 | AU3: M46 | AV3: M47 | AW3: M48 | AX3: M49 | AY3: M50 | AZ3: M51 | BA3: M52
A4: ── CASH FLOW ──
A5: Net Income | B5: ='6_P&L'!B37 -> -2075.3333 | C5: ='6_P&L'!C37 -> -2075.3333 | D5: ='6_P&L'!D37 -> -2075.3333 | E5: ='6_P&L'!E37 -> -2075.3333 | F5: ='6_P&L'!F37 -> -33433.333 | G5: ='6_P&L'!G37 -> -41347.333 | H5: ='6_P&L'!H37 -> -9791.5333 | I5: ='6_P&L'!I37 -> -39791.533 | ... BA5: ='6_P&L'!BA37 -> 559099.05
A6: Changes in Working Capital | B6: =0 -> 0 | C6: =0 -> 0 | D6: =0 -> 0 | E6: =0 -> 0 | F6: =0 -> 0 | G6: =0 -> 0 | H6: =0 -> 0 | I6: =0 -> 0 | ... BA6: =0 -> 0
A7: Net Cash from Operations | B7: =B5+B6 -> -2075.3333 | C7: =C5+C6 -> -2075.3333 | D7: =D5+D6 -> -2075.3333 | E7: =E5+E6 -> -2075.3333 | F7: =F5+F6 -> -33433.333 | G7: =G5+G6 -> -41347.333 | H7: =H5+H6 -> -9791.5333 | I7: =I5+I6 -> -39791.533 | ... BA7: =BA5+BA6 -> 559099.05
A9: Equity Funding Received | B9: =IF(COLUMN()-1='2_Inputs'!$B$10,'2_Inputs'!$B$9,0)+IF(COLUMN()-1='2_Inputs'!$B$12,'2_Inputs'!$B$11,0)+IF(COLUMN()-1='2_Inputs'!$B$14,'2_Inputs'!$B$13,0)+IF(COLUMN()-1='2_Inputs'!$B$16,'2_Inputs'!$B$15,0)+IF(AND('2_Inputs'!$B$19>0,COLUMN()-1='2_Inputs'!$B$19),'2_Inputs'!$B$18,0)+IF(AND('2_Inputs'!$B$21>0,COLUMN()-1='2_Inputs'!$B$21),'2_Inputs'!$B$20,0)+IF(AND('2_Inputs'!$B$23>0,COLUMN()-1='2_Inputs'!$B$23),'2_Inputs'!$B$22,0)+IF(AND('2_Inputs'!$B$26>0,COLUMN()-1='2_Inputs'!$B$26),'2_Inputs'!$B$25,0)+IF(AND('2_Inputs'!$B$28>0,COLUMN()-1='2_Inputs'!$B$28),'2_Inputs'!$B$27,0)+IF(AND('2_Inputs'!$B$30>0,COLUMN()-1='2_Inputs'!$B$30),'2_Inputs'!$B$29,0) -> 0 | C9: =IF(COLUMN()-1='2_Inputs'!$B$10,'2_Inputs'!$B$9,0)+IF(COLUMN()-1='2_Inputs'!$B$12,'2_Inputs'!$B$11,0)+IF(COLUMN()-1='2_Inputs'!$B$14,'2_Inputs'!$B$13,0)+IF(COLUMN()-1='2_Inputs'!$B$16,'2_Inputs'!$B$15,0)+IF(AND('2_Inputs'!$B$19>0,COLUMN()-1='2_Inputs'!$B$19),'2_Inputs'!$B$18,0)+IF(AND('2_Inputs'!$B$21>0,COLUMN()-1='2_Inputs'!$B$21),'2_Inputs'!$B$20,0)+IF(AND('2_Inputs'!$B$23>0,COLUMN()-1='2_Inputs'!$B$23),'2_Inputs'!$B$22,0)+IF(AND('2_Inputs'!$B$26>0,COLUMN()-1='2_Inputs'!$B$26),'2_Inputs'!$B$25,0)+IF(AND('2_Inputs'!$B$28>0,COLUMN()-1='2_Inputs'!$B$28),'2_Inputs'!$B$27,0)+IF(AND('2_Inputs'!$B$30>0,COLUMN()-1='2_Inputs'!$B$30),'2_Inputs'!$B$29,0) -> 0 | D9: =IF(COLUMN()-1='2_Inputs'!$B$10,'2_Inputs'!$B$9,0)+IF(COLUMN()-1='2_Inputs'!$B$12,'2_Inputs'!$B$11,0)+IF(COLUMN()-1='2_Inputs'!$B$14,'2_Inputs'!$B$13,0)+IF(COLUMN()-1='2_Inputs'!$B$16,'2_Inputs'!$B$15,0)+IF(AND('2_Inputs'!$B$19>0,COLUMN()-1='2_Inputs'!$B$19),'2_Inputs'!$B$18,0)+IF(AND('2_Inputs'!$B$21>0,COLUMN()-1='2_Inputs'!$B$21),'2_Inputs'!$B$20,0)+IF(AND('2_Inputs'!$B$23>0,COLUMN()-1='2_Inputs'!$B$23),'2_Inputs'!$B$22,0)+IF(AND('2_Inputs'!$B$26>0,COLUMN()-1='2_Inputs'!$B$26),'2_Inputs'!$B$25,0)+IF(AND('2_Inputs'!$B$28>0,COLUMN()-1='2_Inputs'!$B$28),'2_Inputs'!$B$27,0)+IF(AND('2_Inputs'!$B$30>0,COLUMN()-1='2_Inputs'!$B$30),'2_Inputs'!$B$29,0) -> 0 | E9: =IF(COLUMN()-1='2_Inputs'!$B$10,'2_Inputs'!$B$9,0)+IF(COLUMN()-1='2_Inputs'!$B$12,'2_Inputs'!$B$11,0)+IF(COLUMN()-1='2_Inputs'!$B$14,'2_Inputs'!$B$13,0)+IF(COLUMN()-1='2_Inputs'!$B$16,'2_Inputs'!$B$15,0)+IF(AND('2_Inputs'!$B$19>0,COLUMN()-1='2_Inputs'!$B$19),'2_Inputs'!$B$18,0)+IF(AND('2_Inputs'!$B$21>0,COLUMN()-1='2_Inputs'!$B$21),'2_Inputs'!$B$20,0)+IF(AND('2_Inputs'!$B$23>0,COLUMN()-1='2_Inputs'!$B$23),'2_Inputs'!$B$22,0)+IF(AND('2_Inputs'!$B$26>0,COLUMN()-1='2_Inputs'!$B$26),'2_Inputs'!$B$25,0)+IF(AND('2_Inputs'!$B$28>0,COLUMN()-1='2_Inputs'!$B$28),'2_Inputs'!$B$27,0)+IF(AND('2_Inputs'!$B$30>0,COLUMN()-1='2_Inputs'!$B$30),'2_Inputs'!$B$29,0) -> 320000 | F9: =IF(COLUMN()-1='2_Inputs'!$B$10,'2_Inputs'!$B$9,0)+IF(COLUMN()-1='2_Inputs'!$B$12,'2_Inputs'!$B$11,0)+IF(COLUMN()-1='2_Inputs'!$B$14,'2_Inputs'!$B$13,0)+IF(COLUMN()-1='2_Inputs'!$B$16,'2_Inputs'!$B$15,0)+IF(AND('2_Inputs'!$B$19>0,COLUMN()-1='2_Inputs'!$B$19),'2_Inputs'!$B$18,0)+IF(AND('2_Inputs'!$B$21>0,COLUMN()-1='2_Inputs'!$B$21),'2_Inputs'!$B$20,0)+IF(AND('2_Inputs'!$B$23>0,COLUMN()-1='2_Inputs'!$B$23),'2_Inputs'!$B$22,0)+IF(AND('2_Inputs'!$B$26>0,COLUMN()-1='2_Inputs'!$B$26),'2_Inputs'!$B$25,0)+IF(AND('2_Inputs'!$B$28>0,COLUMN()-1='2_Inputs'!$B$28),'2_Inputs'!$B$27,0)+IF(AND('2_Inputs'!$B$30>0,COLUMN()-1='2_Inputs'!$B$30),'2_Inputs'!$B$29,0) -> 200000 | G9: =IF(COLUMN()-1='2_Inputs'!$B$10,'2_Inputs'!$B$9,0)+IF(COLUMN()-1='2_Inputs'!$B$12,'2_Inputs'!$B$11,0)+IF(COLUMN()-1='2_Inputs'!$B$14,'2_Inputs'!$B$13,0)+IF(COLUMN()-1='2_Inputs'!$B$16,'2_Inputs'!$B$15,0)+IF(AND('2_Inputs'!$B$19>0,COLUMN()-1='2_Inputs'!$B$19),'2_Inputs'!$B$18,0)+IF(AND('2_Inputs'!$B$21>0,COLUMN()-1='2_Inputs'!$B$21),'2_Inputs'!$B$20,0)+IF(AND('2_Inputs'!$B$23>0,COLUMN()-1='2_Inputs'!$B$23),'2_Inputs'!$B$22,0)+IF(AND('2_Inputs'!$B$26>0,COLUMN()-1='2_Inputs'!$B$26),'2_Inputs'!$B$25,0)+IF(AND('2_Inputs'!$B$28>0,COLUMN()-1='2_Inputs'!$B$28),'2_Inputs'!$B$27,0)+IF(AND('2_Inputs'!$B$30>0,COLUMN()-1='2_Inputs'!$B$30),'2_Inputs'!$B$29,0) -> 0 | H9: =IF(COLUMN()-1='2_Inputs'!$B$10,'2_Inputs'!$B$9,0)+IF(COLUMN()-1='2_Inputs'!$B$12,'2_Inputs'!$B$11,0)+IF(COLUMN()-1='2_Inputs'!$B$14,'2_Inputs'!$B$13,0)+IF(COLUMN()-1='2_Inputs'!$B$16,'2_Inputs'!$B$15,0)+IF(AND('2_Inputs'!$B$19>0,COLUMN()-1='2_Inputs'!$B$19),'2_Inputs'!$B$18,0)+IF(AND('2_Inputs'!$B$21>0,COLUMN()-1='2_Inputs'!$B$21),'2_Inputs'!$B$20,0)+IF(AND('2_Inputs'!$B$23>0,COLUMN()-1='2_Inputs'!$B$23),'2_Inputs'!$B$22,0)+IF(AND('2_Inputs'!$B$26>0,COLUMN()-1='2_Inputs'!$B$26),'2_Inputs'!$B$25,0)+IF(AND('2_Inputs'!$B$28>0,COLUMN()-1='2_Inputs'!$B$28),'2_Inputs'!$B$27,0)+IF(AND('2_Inputs'!$B$30>0,COLUMN()-1='2_Inputs'!$B$30),'2_Inputs'!$B$29,0) -> 0 | I9: =IF(COLUMN()-1='2_Inputs'!$B$10,'2_Inputs'!$B$9,0)+IF(COLUMN()-1='2_Inputs'!$B$12,'2_Inputs'!$B$11,0)+IF(COLUMN()-1='2_Inputs'!$B$14,'2_Inputs'!$B$13,0)+IF(COLUMN()-1='2_Inputs'!$B$16,'2_Inputs'!$B$15,0)+IF(AND('2_Inputs'!$B$19>0,COLUMN()-1='2_Inputs'!$B$19),'2_Inputs'!$B$18,0)+IF(AND('2_Inputs'!$B$21>0,COLUMN()-1='2_Inputs'!$B$21),'2_Inputs'!$B$20,0)+IF(AND('2_Inputs'!$B$23>0,COLUMN()-1='2_Inputs'!$B$23),'2_Inputs'!$B$22,0)+IF(AND('2_Inputs'!$B$26>0,COLUMN()-1='2_Inputs'!$B$26),'2_Inputs'!$B$25,0)+IF(AND('2_Inputs'!$B$28>0,COLUMN()-1='2_Inputs'!$B$28),'2_Inputs'!$B$27,0)+IF(AND('2_Inputs'!$B$30>0,COLUMN()-1='2_Inputs'!$B$30),'2_Inputs'!$B$29,0) -> 200000 | ... BA9: =IF(COLUMN()-1='2_Inputs'!$B$10,'2_Inputs'!$B$9,0)+IF(COLUMN()-1='2_Inputs'!$B$12,'2_Inputs'!$B$11,0)+IF(COLUMN()-1='2_Inputs'!$B$14,'2_Inputs'!$B$13,0)+IF(COLUMN()-1='2_Inputs'!$B$16,'2_Inputs'!$B$15,0)+IF(AND('2_Inputs'!$B$19>0,COLUMN()-1='2_Inputs'!$B$19),'2_Inputs'!$B$18,0)+IF(AND('2_Inputs'!$B$21>0,COLUMN()-1='2_Inputs'!$B$21),'2_Inputs'!$B$20,0)+IF(AND('2_Inputs'!$B$23>0,COLUMN()-1='2_Inputs'!$B$23),'2_Inputs'!$B$22,0)+IF(AND('2_Inputs'!$B$26>0,COLUMN()-1='2_Inputs'!$B$26),'2_Inputs'!$B$25,0)+IF(AND('2_Inputs'!$B$28>0,COLUMN()-1='2_Inputs'!$B$28),'2_Inputs'!$B$27,0)+IF(AND('2_Inputs'!$B$30>0,COLUMN()-1='2_Inputs'!$B$30),'2_Inputs'!$B$29,0) -> 0
A10: Net Cash from Financing | B10: =B9 -> 0 | C10: =C9 -> 0 | D10: =D9 -> 0 | E10: =E9 -> 320000 | F10: =F9 -> 200000 | G10: =G9 -> 0 | H10: =H9 -> 0 | I10: =I9 -> 200000 | ... BA10: =BA9 -> 0
A12: NET CHANGE IN CASH | B12: =B7+B10 -> -2075.3333 | C12: =C7+C10 -> -2075.3333 | D12: =D7+D10 -> -2075.3333 | E12: =E7+E10 -> 317924.67 | F12: =F7+F10 -> 166566.67 | G12: =G7+G10 -> -41347.333 | H12: =H7+H10 -> -9791.5333 | I12: =I7+I10 -> 160208.47 | ... BA12: =BA7+BA10 -> 559099.05
A14: Beginning Cash Balance | B14: 0 | C14: =B15 -> -2075.3333 | D14: =C15 -> -4150.6667 | E14: =D15 -> -6226 | F14: =E15 -> 311698.67 | G14: =F15 -> 478265.33 | H14: =G15 -> 436918 | I14: =H15 -> 427126.47 | J14: =I15 -> 587334.93 | ... BA14: =AZ15 -> 17909325
A15: ENDING CASH BALANCE | B15: =B14+B12 -> -2075.3333 | C15: =C14+C12 -> -4150.6667 | D15: =D14+D12 -> -6226 | E15: =E14+E12 -> 311698.67 | F15: =F14+F12 -> 478265.33 | G15: =G14+G12 -> 436918 | H15: =H14+H12 -> 427126.47 | I15: =I14+I12 -> 587334.93 | ... BA15: =BA14+BA12 -> 18468424
A17: ── KEY METRICS ──
A18: Monthly Burn Rate | B18: =IF(B12<0,-B12,0) -> 2075.3333 | C18: =IF(C12<0,-C12,0) -> 2075.3333 | D18: =IF(D12<0,-D12,0) -> 2075.3333 | E18: =IF(E12<0,-E12,0) -> 0 | F18: =IF(F12<0,-F12,0) -> 0 | G18: =IF(G12<0,-G12,0) -> 41347.333 | H18: =IF(H12<0,-H12,0) -> 9791.5333 | I18: =IF(I12<0,-I12,0) -> 0 | ... BA18: =IF(BA12<0,-BA12,0) -> 0
A19: Runway (Months) | B19: =IFERROR(IF(B18>0,B15/B18,"∞"),"∞") -> -1 | C19: =IFERROR(IF(C18>0,C15/C18,"∞"),"∞") -> -2 | D19: =IFERROR(IF(D18>0,D15/D18,"∞"),"∞") -> -3 | E19: =IFERROR(IF(E18>0,E15/E18,"∞"),"∞") -> ∞ | F19: =IFERROR(IF(F18>0,F15/F18,"∞"),"∞") -> ∞ | G19: =IFERROR(IF(G18>0,G15/G18,"∞"),"∞") -> 10.567018 | H19: =IFERROR(IF(H18>0,H15/H18,"∞"),"∞") -> 43.62202 | I19: =IFERROR(IF(I18>0,I15/I18,"∞"),"∞") -> ∞ | ... BA19: =IFERROR(IF(BA18>0,BA15/BA18,"∞"),"∞") -> ∞
A20: Cash Runway Alert | B20: =IF(ISNUMBER(B19),IF(B19<6,"WARNUNG","OK"),"OK") -> WARNUNG | C20: =IF(ISNUMBER(C19),IF(C19<6,"WARNUNG","OK"),"OK") -> WARNUNG | D20: =IF(ISNUMBER(D19),IF(D19<6,"WARNUNG","OK"),"OK") -> WARNUNG | E20: =IF(ISNUMBER(E19),IF(E19<6,"WARNUNG","OK"),"OK") -> OK | F20: =IF(ISNUMBER(F19),IF(F19<6,"WARNUNG","OK"),"OK") -> OK | G20: =IF(ISNUMBER(G19),IF(G19<6,"WARNUNG","OK"),"OK") -> OK | H20: =IF(ISNUMBER(H19),IF(H19<6,"WARNUNG","OK"),"OK") -> OK | I20: =IF(ISNUMBER(I19),IF(I19<6,"WARNUNG","OK"),"OK") -> OK | ... BA20: =IF(ISNUMBER(BA19),IF(BA19<6,"WARNUNG","OK"),"OK") -> OK
