Workbook

Sheet Anleitung
A1: LoopforgeLab GmbH – Financial Projection Model
A3: Projektionszeitraum: 52 Monate (ca. 4,3 Jahre)
A5: INHALTSVERZEICHNIS
A6: Sheet 1: Anleitung – Diese Seite mit Übersicht und Legende
A7: Sheet 2: Inputs – Zentrale Eingabewerte (HIER STARTEN)
A8: Sheet 3: P&L – Gewinn- und Verlustrechnung (monatlich + jährlich)
A9: Sheet 4: Revenue – Detaillierte Umsatzmodellierung
A10: Sheet 5: Costs – Detaillierte Kostenaufschlüsselung
A11: Sheet 6: Balance Sheet – Vereinfachte Bilanz
A12: Sheet 7: Cash Flow – Kapitalflussrechnung mit Runway
A14: FARBCODIERUNG
A15: Blau | B15: Editierbare Eingabefelder
A16: Schwarz | B16: Formeln – nicht manuell ändern
A17: Grün | B17: Verweise auf andere Sheets
A18: Gelb hinterlegt | B18: Kritische Annahmen
A20: KURZANLEITUNG
A21: 1. Gehen Sie zum Sheet 'Inputs' und passen Sie alle blau markierten Werte an.
A22: 2. Alle anderen Sheets berechnen sich automatisch aus den Inputs.
A23: 3. Prüfen Sie die P&L, Revenue und Cash Flow Sheets auf Plausibilität.
A24: 4. Achten Sie auf rot markierte Warnungen (z.B. Runway < 6 Monate).
A25: 5. Exportieren Sie relevante Sheets als PDF für Investoren-Präsentationen.
A27: DISCLAIMER: Diese Projektion dient ausschließlich der Planung.
A28: Tatsächliche Ergebnisse können erheblich abweichen. Keine Garantie.

Sheet Treiber_Matrix
A1: LoopForgeLab – Treiber- & Annahmen-Matrix (importiert aus 260305_LFL_Treiber_Matrix_v1.xlsx)
A2: Alle Umsatz- und Kostentreiber | Szenarien: Gering · Normal · Stark | Spalten L & M: Eigene Bewertungen und Alternativwerte | NEU-markierte Zeilen: noch nicht im Modell — Entwicklungspotenzial
A3: Kategorie | B3: Unterkategorie | C3: Parameter / Treiber | D3: Aktueller Wert | E3: Einheit | F3: Szenario-Abhängigkeit | G3: Gering | H3: Normal | I3: Stark | J3: Einflussfaktor & Wirkungslogik | K3: Annahmen & Begründung | L3: ► Ihre Bewertung | M3: ► Neue Annahme
A5: Revenue 1: SaaS / Lizenzen
A6: UMSATZ | B6: SaaS / Lizenzen | C6: Startpreis pro Seat/Jahr | D6: 9.600 – 12.000 € | E6: €/Jahr | F6: Szenario | G6: 2400 | H6: 4200 | I6: 5400 | J6: Bestimmt den initialen Lizenzpreis je Nutzer-Seat. Direkter Multiplikator auf alle Lizenzerlöse. | K6: Automotive: höherer Preis durch Compliance-Wert (TISAX). Packaging: niedrigerer Einstiegspreis, Wachstum über Volumen & NRR. Value-based Pricing orientiert sich am TCO-Einsparpotenzial.
A7: UMSATZ | B7: SaaS / Lizenzen | C7: Jährliche Preiserhöhung | D7: 0.1 | E7: % p.a. | F7: Fest | G7: 0.1 | H7: 0.1 | I7: 0.1 | J7: Erhöht den Seat-Preis jährlich. Kompensiert Inflations- und Innovationskosten (Inferenz, neue Features). | K7: Standard für AI-SaaS 2026. Typisch: 3–10% p.a. Höherer Wert möglich bei starker Produktdifferenzierung.
A8: UMSATZ | B8: SaaS / Lizenzen | C8: Erster Umsatzmonat (Kunden) | D8: Monat 8–14 | E8: Monat | F8: Szenario | G8: Monat 14 | H8: Monat 8 | I8: Monat 9 | J8: Verschiebt den gesamten SaaS-Umsatz-Stream. Jeder Monat Verzögerung = direkte Liquiditätslücke. | K8: Automotive (Gering): lange Sales-Zyklen (9–12 Mon.) + TISAX-Prüfung. Packaging (Stark): kürzere IT-Entscheidungswege, frühere Piloten möglich.
A9: UMSATZ | B9: SaaS / Lizenzen | C9: Initiale Seats (1. Kunde) | D9: 5 | E9: Seats | F9: Fest | G9: 5 | H9: 5 | I9: 5 | J9: Anzahl der Seats beim ersten Kunden. Beeinflusst den initialen ARR-Wert und das Wachstums-Baseline. | K9: Konservative Annahme: 1–2 Pilotprojekte pro Werk. Land & Expand-Strategie: erst 1 Werk, dann Roll-out.
A10: UMSATZ | B10: SaaS / Lizenzen | C10: Monatliche Seat-Wachstumsrate | D10: 0.08 | E10: % / Monat | F10: Fest | G10: 0.08 | H10: 0.08 | I10: 0.08 | J10: Bestimmt, wie schnell neue Seats hinzukommen. Treiber für den kumulativen ARR-Aufbau. | K10: Alternative: Account-basierte Planung mit Stufenfunktion (Roll-out pro Werk statt linearer Rate). Realistischer Wert abhängig von Vertriebskapazität.
A11: UMSATZ | B11: SaaS / Lizenzen | C11: Enterprise-Deals ab Monat | D11: Monat 18 | E11: Monat | F11: Fest | G11: Monat 18 | H11: Monat 18 | I11: Monat 18 | J11: Ab diesem Monat werden größere Enterprise-Verträge abgeschlossen. Erhöht den durchschnittlichen ARR pro Kunde sprunghaft. | K11: Automotive: Verschiebung durch Technical Validation + Compliance. Typisch: 50.000–200.000 €/Jahr pro Enterprise-Kunde.
A12: UMSATZ | B12: SaaS / Lizenzen | C12: Durchschnittlicher Enterprise ARR | D12: 50000 | E12: €/Jahr | F12: Fest | G12: 50000 | H12: 50000 | I12: 50000 | J12: Erlös pro Enterprise-Vertrag. Beeinflusst den ARR-Sprung ab Monat 18 erheblich. | K12: Höheres Volumen durch tiefe Integration (DPP, Sustainability). Realistisch: 50.000–200.000 € je nach Kundentyp.
A13: UMSATZ | B13: SaaS / Lizenzen | C13: Enterprise Deals pro Quartal | D13: 2 | E13: Deals/Quartal | F13: Fest | G13: 2 | H13: 2 | I13: 2 | J13: Anzahl neuer Enterprise-Verträge pro Quartal. Direkter Treiber für den ARR-Aufbau nach Monat 18. | K13: Abhängig von Vertriebskapazität und Sales-Zyklus-Länge. Sollte mit Einstellungsplan abgestimmt sein.
A14: UMSATZ | B14: SaaS / Lizenzen | C14: Jährliche Churn Rate | D14: 0.06 | E14: % p.a. | F14: Fest | G14: 0.06 | H14: 0.06 | I14: 0.06 | J14: Anteil der Kunden, die jährlich abwandern. Reduziert den kumulativen ARR direkt. | K14: Konservative Planung für komplexe industrielle Buying Center. Typisch SaaS: 5–10%. Im Pilot-Jahr höher, ab Jahr 3 niedriger.
A15: UMSATZ | B15: SaaS / Lizenzen | C15: Net Revenue Retention (NRR) | D15: 1.25 | E15: % | F15: Fest | G15: 1.25 | H15: 1.25 | I15: 1.25 | J15: Expansion-Umsatz minus Churn. NRR > 100% bedeutet: Bestandskunden wachsen schneller als sie abwandern. | K15: Realisierbar durch DPP-Zusatzmodule und Material-Analytics-Upgrades. Typisch: 100–120%. 125% ist ambitioniert, aber bei starkem Upselling möglich.
A16: Revenue 2: Implementation-Support
A17: UMSATZ | B17: Implementation-Support | C17: Implementation-Support-Tagessatz | D17: 1.000 – 1.500 € | E17: €/Tag | F17: Szenario | G17: 1000 | H17: 1200 | I17: 1500 | J17: Verrechnungssatz für Beratungsleistungen. Multipliziert mit Tagen/Kunde ergibt den Erlös je Projekt. | K17: Automotive: niedrigerer Satz durch Preisdruck im Mittelstand. Packaging: höherer Satz durch Expertenstatus und Integrationskomplexität. Quelle: Marktanalyse Lothar.bm / Candemir.
A18: UMSATZ | B18: Implementation-Support | C18: Implementation-Support-Tage/Kunde | D18: 4 – 20 Tage | E18: Tage/Kunde | F18: Szenario | G18: 4 Tage | H18: 10 Tage | I18: 20 Tage | J18: Abrechnungsfähige Beratungstage je Kundenprojekt. Bestimmt zusammen mit dem Tagessatz den Erlös pro Implementation-Support-Kunde. | K18: Gering: standardisierter Onboarding-Prozess (4 Tage). Stark: tiefe Prozessintegration im Packaging (20 Tage). Formel: Implementation-Support-Umsatz/Kunde = Tagessatz × Tage/Kunde.
A19: UMSATZ | B19: Implementation-Support | C19: Implementation-Support-Umsatz/Kunde | D19: 4.000 – 30.000 € | E19: €/Kunde | F19: Berechnet | G19: 4000 | H19: 12000 | I19: 30000 | J19: Erlös pro beauftragendem Kunden. Berechnung: Tagessatz × Tage/Kunde. Beeinflusst den gesamten Implementation-Support-Umsatz-Stream. | K19: Gering: 1.000€ × 4 Tage = 4.000€/Kunde. Normal: 1.200€ × 10 Tage = 12.000€/Kunde. Stark: 1.500€ × 20 Tage = 30.000€/Kunde.
A20: UMSATZ | B20: Implementation-Support | C20: Implementation-Support-Quote (% Kunden) | D20: 20 – 100 % | E20: % Kunden | F20: Unabhängig | G20: 20 % (Niedrig) | H20: 50 % (Mittel) | I20: 100 % (Hoch) | J20: Anteil der Neukunden, die Implementation-Support beauftragen. UNABHÄNGIG vom strategischen Szenario einstellbar. Kombinierbar mit jedem der drei Szenarien (3×3-Matrix). | K20: Niedrig (20%): Self-Service-Kunden, minimaler Beratungsbedarf. Mittel (50%): Standardannahme, jeder zweite Kunde bucht Implementation-Support. Hoch (100%): Alle Kunden benötigen Onboarding-Unterstützung.
A21: UMSATZ | B21: Implementation-Support | C21: Implementation-Support-Startmonat | D21: Monat 3–6 | E21: Monat | F21: Szenario | G21: Monat 3 | H21: Monat 4 | I21: Monat 6 | J21: Monat des ersten Implementation-Support-Umsatzes. Implementation-Support startet als Enabler vor dem SaaS-Produkt. | K21: Gering: früher Start (Monat 3), da Automotive-Kunden sofort IT-Begleitung benötigen. Stark: späterer Start (Monat 6), da Packaging-Kunden länger Self-Service nutzen können.
A22: KOSTEN (OpEx)
A23: Personal & Gehälter
A24: KOSTEN | B24: Personal | C24: CEO Gehalt (Brutto/Jahr) | D24: 100000 | E24: €/Jahr | F24: Fest | G24: 100000 | H24: 100000 | I24: 100000 | J24: Gründer-Gehalt in der Pre-Seed-Phase. Beeinflusst die monatliche Burn Rate direkt. | K24: Gründer-Satz Pre-Seed. Anpassung ab Seed-Runde auf Marktgehalt. Typisch Startup: 60.000–90.000 €/Jahr.
A25: KOSTEN | B25: Personal | C25: CTO Gehalt (Brutto/Jahr) | D25: 100000 | E25: €/Jahr | F25: Fest | G25: 100000 | H25: 100000 | I25: 100000 | J25: Gründer-Gehalt in der Pre-Seed-Phase. Beeinflusst die monatliche Burn Rate direkt. | K25: Gründer-Satz Pre-Seed. Anpassung ab Seed-Runde auf Marktgehalt. Typisch Startup: 60.000–90.000 €/Jahr.
A26: KOSTEN | B26: Personal | C26: CCO Gehalt (Brutto/Jahr) | D26: 100000 | E26: €/Jahr | F26: Fest | G26: 100000 | H26: 100000 | I26: 100000 | J26: Gründer-Gehalt in der Pre-Seed-Phase. Beeinflusst die monatliche Burn Rate direkt. | K26: Gründer-Satz Pre-Seed. Anpassung ab Seed-Runde auf Marktgehalt. Typisch Startup: 60.000–90.000 €/Jahr.
A27: KOSTEN | B27: Personal | C27: Software Developer Gehalt | D27: 75000 | E27: €/Jahr | F27: Fest | G27: 75000 | H27: 75000 | I27: 75000 | J27: Erste strategische Einstellung. Fix-Position, nicht durch AI-Personal-Hebel verzögerbar.
A28: KOSTEN | B28: Personal | C28: Arbeitgeber-Nebenkosten | D28: 0.2 | E28: % auf Bruttogehalt | F28: Fest | G28: 0.2 | H28: 0.2 | I28: 0.2 | J28: Sozialversicherungsbeiträge des Arbeitgebers. Erhöht die effektiven Personalkosten um 20%. | K28: Standardsatz Deutschland 2026. Gesamtkosten pro MA = Bruttogehalt × 1,20.
A29: KOSTEN | B29: Personal | C29: Onboarding-Aufwand | D29: 30–120 Stunden | E29: Stunden/Kunde | F29: Szenario | G29: 120 Stunden | H29: 60 Stunden | I29: 30 Stunden | J29: Interner Aufwand für das Kunden-Onboarding. Bindet Entwickler- und Support-Kapazität. | K29: Gering: hoher Aufwand bei alten IT-Systemen (Automotive). Stark: standardisierter Self-Service-Prozess (Packaging). Quelle: Lothar.bm-Transkripte.
A30: Technologie & Cloud
A31: KOSTEN | B31: Technologie | C31: Cloud/Hosting Basis | D31: 2000 | E31: €/Monat | F31: Fest | G31: 2000 | H31: 2000 | I31: 2000 | J31: Fixe monatliche Grundkosten für Cloud-Infrastruktur. Unabhängig von der Kundenzahl. | K31: AWS/Azure/GCP Grundkonfiguration. Steigt mit Kundenzahl über den Skalierungsfaktor.
A32: KOSTEN | B32: Technologie | C32: Cloud-Skalierung pro Seat | D32: 80 | E32: €/Seat/Monat | F32: Skalierend | G32: 80 | H32: 80 | I32: 80 | J32: Variable Cloud-Kosten pro aktivem Seat. Wächst proportional zur Kundenbasis (szenarioabhängig). | K32: Gesamte Cloud-Kosten = Basis + (Seats × 80€). Im Stark-Szenario entstehen durch mehr Seats höhere Gesamtkosten.
A33: KOSTEN | B33: Technologie | C33: AI/ML APIs Basis | D33: 2000 | E33: €/Monat | F33: Fest | G33: 2000 | H33: 2000 | I33: 2000 | J33: Monatliche Grundkosten für KI-API-Nutzung (OpenAI/Anthropic/Frontier Models). | K33: Nutzung von GPT-5/Claude für Design-Logic. Wächst mit 8%/Monat proportional zur Nutzungsintensität.
A34: KOSTEN | B34: Technologie | C34: AI-Kosten Wachstum/Monat | D34: 0.08 | E34: % / Monat | F34: Fest | G34: 0.08 | H34: 0.08 | I34: 0.08 | J34: Monatliche Steigerungsrate der AI/ML-API-Kosten. Skaliert proportional zur Nutzung und Datentiefe. | K34: Skalierung proportional zur Nutzung und Datentiefe. Kann durch Open-Source-Modelle reduziert werden.
A35: KOSTEN | B35: Technologie | C35: SaaS Tools intern (Basis) | D35: 400 | E35: €/Monat | F35: Fest | G35: 400 | H35: 400 | I35: 400 | J35: Fixe monatliche Kosten für interne Tools (Slack, Notion, GitHub etc.). | K35: Standardpaket für Tech-Startups. Wächst mit Mitarbeiterzahl über den Pro-MA-Satz.
A36: KOSTEN | B36: Technologie | C36: SaaS Tools pro Mitarbeiter | D36: 100 | E36: €/MA/Monat | F36: Skalierend | G36: 100 | H36: 100 | I36: 100 | J36: Variable Tool-Kosten pro Mitarbeiter. Inkl. KI-Coding-Tools (Copilot/Cursor). | K36: Gesamte Tool-Kosten = Basis + (MAs × 100€). Im Gering-Szenario (mehr MAs) entstehen höhere Gesamtkosten.
A37: KOSTEN | B37: Technologie | C37: Sicherheit & Compliance | D37: 3500 | E37: €/Monat | F37: Fest | G37: 3500 | H37: 3500 | I37: 3500 | J37: Monatliche Kosten für Security-Tools und Compliance-Monitoring. Kritisch für TISAX-Zertifizierung im Automotive-Bereich. | K37: Puffer für TISAX-Audits und laufendes Compliance-Monitoring. Besonders relevant im Gering-Szenario (Automotive-Fokus).
A38: Marketing & Vertrieb
A39: KOSTEN | B39: Marketing & Vertrieb | C39: Paid Ads Budget (Initial) | D39: 1000 | E39: €/Monat | F39: Fest | G39: 1000 | H39: 1000 | I39: 1000 | J39: Monatliches Startbudget für bezahlte Werbung (Google, LinkedIn). Wächst mit 8%/Monat. | K39: Fokus eher auf Content/SEO im Industrie-Vertrieb. Skalierung mit Marktbekanntheit.
A40: KOSTEN | B40: Marketing & Vertrieb | C40: Content & SEO | D40: 2500 | E40: €/Monat | F40: Fest | G40: 2500 | H40: 2500 | I40: 2500 | J40: Monatliche Kosten für Content-Marketing und SEO. Fokus auf Whitepaper zu ROI, TCO und DPP-Compliance. | K40: Wichtiger Kanal für B2B-SaaS im Industriebereich. Langfristiger Aufbau von organischem Traffic.
A41: KOSTEN | B41: Marketing & Vertrieb | C41: Events & Messen/Ideation | D41: 3000 | E41: €/Jahr | F41: Fest | G41: 3000 | H41: 3000 | I41: 3000 | J41: Jährliche Kosten für Messeauftritte und Events. Wichtiger Kanal für Enterprise-Kundenkontakte. | K41: Erste Messeteilnahme/ Fachmessen
A42: KOSTEN | B42: Marketing & Vertrieb | C42: Events & Messen/Pre-Seed | D42: 10000 | E42: €/Jahr | F42: Fest | G42: 10000 | H42: 10000 | I42: 10000 | J42: Jährliche Kosten für Messeauftritte und Events. Wichtiger Kanal für Enterprise-Kundenkontakte. | K42: Messeteilnahme/ Fachmessen (nur die Gründer)
A43: KOSTEN | B43: Marketing & Vertrieb | C43: Events & Messen/Seed | D43: 15000 | E43: €/Jahr | F43: Fest | G43: 15000 | H43: 15000 | I43: 15000 | J43: Jährliche Kosten für Messeauftritte und Events. Wichtiger Kanal für Enterprise-Kundenkontakte. | K43: Präsenz auf Leitmessen (Hannover Messe, SPS). Hoher Posten – Überprüfung der Priorität empfohlen. Zusätzlich Sales-/Marketing MA auch auf Messebesuche
A44: KOSTEN | B44: Marketing & Vertrieb | C44: Events & Messen/Series A | D44: 25000 | E44: €/Jahr | F44: Fest | G44: 25000 | H44: 25000 | I44: 40000 | J44: Jährliche Kosten für Messeauftritte und Events. Wichtiger Kanal für Enterprise-Kundenkontakte. | K44: Präsenz auf Leitmessen (Hannover Messe, SPS). Hoher Posten – Überprüfung der Priorität empfohlen.
A45: KOSTEN | B45: Marketing & Vertrieb | C45: Events & Messen/Series B | D45: 25000 | E45: €/Jahr | F45: Fest | G45: 25000 | H45: 25000 | I45: 60000 | J45: Jährliche Kosten für Messeauftritte und Events. Wichtiger Kanal für Enterprise-Kundenkontakte. | K45: Zusätzlich Sales-/Marketing MA auch auf Messebesuche
A46: KOSTEN | B46: Marketing & Vertrieb | C46: Sales Provision | D46: 12 % | E46: % vom neuen ARR | F46: Skalierend | G46: 0.12 | H46: 0.12 | I46: 0.12 | J46: Vertriebsprovision als Anteil am neu gewonnenen ARR. Skaliert direkt mit dem Umsatzwachstum. | K46: Anreiz für Verkäufer. Im Stark-Szenario (höherer ARR) entstehen höhere absolute Provisionskosten.
A47: KOSTEN | B47: Marketing & Vertrieb | C47: Reisekosten Sales/MA/Monat | D47: 700 | E47: €/MA/Monat | F47: Skalierend | G47: 700 | H47: 700 | I47: 700 | J47: Monatliche Reisekosten pro Sales-Mitarbeiter. Notwendig für Werksbegehungen und Kundenbesuche. | K47: Besonders relevant im Automotive-Szenario (Gering) mit physischen Vor-Ort-Terminen bei Tier-1-Zulieferern.
A48: Professional Services & Sonstiges
A49: KOSTEN | B49: Professional Services | C49: Rechtsanwalt (Basis/Jahr) | D49: 8000 | E49: €/Jahr | F49: Fest | G49: 8000 | H49: 8000 | I49: 8000 | J49: Laufende Rechtsberatung (Verträge, IP, Arbeitsrecht). Basiskosten unabhängig von Finanzierungsrunden. | K49: Standard für Tech-Startups in Deutschland. Zusätzlich: 15.000€ pro Finanzierungsrunde.
A50: Kosten | B50: Professional Services | C50: Rechtsanwalt (pro Finanzierung) | D50: 15000 | E50: €/Jahr | F50: Fest | G50: 12000 | H50: 15000 | I50: 20000 | J50: Für jede Finanzierungsrunde ab Pre-Seed Anwalt erforderlich für Shareholder-Angelegenheiten | K50: Honoarhöhe abhängig von Geschwindigkeit und Anfall an Komplexität
A51: KOSTEN | B51: Professional Services | C51: Steuerberater | D51: 800 | E51: €/Monat | F51: Fest | G51: 800 | H51: 800 | I51: 800 | J51: Monatliche Kosten für laufende Buchhaltung und Steuerberatung. | K51: Standard für GmbH in Deutschland. Steigt mit Komplexität der Finanzstruktur.
A52: KOSTEN | B52: Professional Services | C52: Wirtschaftsprüfer (ab Monat 17) | D52: 12000 | E52: €/Jahr | F52: Fest | G52: – | H52: 12000 | I52: 12000 | J52: Jährliche Kosten für Wirtschaftsprüfung. Pflicht ab Series A für institutionelle Investoren. | K52: Start mit tatsächlicher Seed-Phase (Mitte 2027). Erst ab Monat 17 relevant.
A53: KOSTEN | B53: Sonstiges | C53: Weiterbildung/MA/Jahr | D53: 1000 | E53: €/MA/Jahr | F53: Skalierend | G53: 1000 | H53: 1000 | I53: 1000 | J53: Jährliche Weiterbildungskosten pro Mitarbeiter. Besonders wichtig im ML/KI-Bereich. | K53: Konferenzen, Online-Kurse, Zertifizierungen. Gesamtkosten skalieren mit Mitarbeiterzahl.
A54: KOSTEN | B54: Sonstiges | C54: Sonstiges / Puffer | D54: 5 % | E54: % der OpEx | F54: Fest | G54: 0.05 | H54: 0.05 | I54: 0.05 | J54: Puffer für ungeplante Ausgaben. Vorsichtsprinzip für unvorhergesehene Kosten. | K54: Standard-Puffer für Startup-Finanzplanung. Empfehlung: mindestens 5% der gesamten OpEx.
A55: INVESTITIONEN (CapEx)
A56: Hardware & Ausstattung
A57: OPEX | B57: Hardware | C57: Laptop pro Mitarbeiter | D57: 80 | E57: €/Monat/MA | F57: Skalierend | G57: 80 | H57: 80 | I57: 100 | J57: MA bekommen keine eigenen Geräte sondern Leihgeräte von Grover | K57: Grundsätzlich Reduzierung von CAPEX durch Mietmodell. Kann im Einzelfall verändert werden, wenn es besondere Bedarfe gibt
A58: OPEX | B58: Hardware | C58: Monitor & Peripherie pro MA | D58: 40 | E58: €/Monat/MA | F58: Skalierend | G58: 40 | H58: 40 | I58: 60 | J58: MA bekommen keine eigenen Geräte sondern Leihgeräte von Grover | K58: Grundsätzlich Reduzierung von CAPEX durch Mietmodell. Kann im Einzelfall verändert werden, wenn es besondere Bedarfe gibt
A59: Büro & Facilities
A60: Kosten | B60: Büro | C60: Coworking/Shared Desk | D60: 400 | E60: €/Monat/MA | F60: Skalierend | G60: 350 | H60: 400 | I60: 400 | J60: Zu Beginn nur Shared Desks im Coworking Space | K60: In der Ideation Phase geringer Bedarf, In der Pre-Seed Phase erste MA eingestellt. Bedarf an festen Desks im Coworking Space
A61: CAPEX | B61: Büro | C61: Büromiete (Initial): keine, da zunächst Coworking Space/ Shared Desks | D61: 0 | E61: €/Monat | F61: Fest | G61: 0 | H61: 0 | I61: 0 | J61: Monatliche Miete für Coworking-Space in der Anfangsphase. Wechselt ab Monat 18 auf größeres Büro. | K61: Coworking-Fokus in der ersten Phase (Berlin Mitte/Kreuzberg). Shift analog zur Einstellung von Solution Architects.
A62: CAPEX | B62: Büro | C62: Büromiete (ab Seed/M18) | D62: 4500 | E62: €/Monat | F62: Fest | G62: 3500 | H62: 4000 | I62: 4500 | J62: Monatliche Miete nach dem Seedfinanzierung ab Monat 18. Für ca. 10–20 Personen ausgelegt. | K62: Berliner Marktpreise für Bürofläche. Upgrade-Zeitpunkt kann szenariospezifisch angepasst werden.
A63: CAPEX | B63: Büro | C63: Büroausstattung (Initial) | D63: 5000 | E63: € (einmalig) | F63: Fest | G63: 5000 | H63: 5000 | I63: 5000 | J63: Einmalige Investition für Möbel und IT-Grundausstattung. Fällt beim Start an. | K63: Standard-Erstausstattung für kleines Tech-Team. Kein szenarioabhängiger Einfluss.
A64: NEUE / POTENZIELLE SZENARIEN
A65: Umsatz – Neue Treiber
A66: NEU | B66: SaaS-Pricing | C66: Produkt-Tiers (Basic/Pro/Enterprise) | D66: Noch nicht modelliert | E66: – | F66: Zu definieren | G66: Basic: ~5.000 €/J | H66: Pro: ~12.000 €/J | I66: Enterprise: ~25.000 €/J | J66: Gestaffelte Pakete mit unterschiedlichen Features und Preisen. Erhöht die Preisflexibilität und Marktabdeckung. | K66: Noch nicht im Modell. Würde den Startpreis-Parameter durch eine Tier-Verteilung ersetzen.
A67: NEU | B67: SaaS-Umsatz | C67: Upselling-Effizienz (NRR-Varianten) | D67: NRR: 125 % (fest) | E67: % | F67: Zu definieren | G67: NRR: 105 % | H67: NRR: 115 % | I67: NRR: 130 % | J67: Unterschiedliche NRR-Szenarien je nach Upselling-Erfolg. Direkter Einfluss auf den langfristigen ARR. | K67: Aktuell als fester Wert (125%) modelliert. Szenariofähig machen würde die Sensitivitätsanalyse verbessern.
A68: NEU | B68: SaaS-Umsatz | C68: Churn-Varianten | D68: Churn: 6 % (fest) | E68: % p.a. | F68: Zu definieren | G68: Hoher Churn: 10 % | H68: Normal: 6 % | I68: Niedriger Churn: 3 % | J68: Unterschiedliche Churn-Szenarien je nach Kundenbindung. Direkter Einfluss auf den kumulativen ARR. | K68: Aktuell als fester Wert (6%) modelliert. Besonders relevant für Langfristprojektionen (Jahr 3–5).
A69: NEU | B69: Marktexpansion | C69: Internationalisierung | D69: Noch nicht modelliert | E69: – | F69: Zu definieren | G69: Keine Expansion | H69: EU-Expansion (Y2) | I69: US-Expansion (Y3) | J69: Multiplikator auf das Kundenwachstum ab einem definierten Monat. Erheblicher Einfluss auf ARR und Personalplanung. | K69: Noch nicht im Modell. Würde zusätzliche Kosten (Lokalisierung, Compliance, Personal) erfordern.
A70: Kosten – Neue Treiber
A71: NEU | B71: Personal | C71: Gehaltsniveau-Faktor | D71: Noch nicht modelliert | E71: Faktor | F71: Zu definieren | G71: 85 % des Markts | H71: 100 % des Markts | I71: 115 % des Markts | J71: Prozentualer Faktor auf alle Gehälter im Einstellungsplan. Direkter Einfluss auf die gesamte Personalkostenbasis. | K71: Noch nicht im Modell. Besonders relevant für Talent-Wettbewerb im Berliner KI-Markt.
A73: LEGENDE – Szenario-Abhängigkeit
A74: Szenario | B74: Wert ändert sich je nach aktivem Szenario (Gering/Normal/Stark) in der 00_Input_Sandbox
A75: Unabhängig | B75: Eigenständiger Schalter – unabhängig vom Szenario einstellbar (z.B. Implementation-Support-Quote: 20%/50%/100%)
A76: Berechnet | B76: Abgeleiteter Wert – wird automatisch aus anderen Parametern berechnet (kein direkter Eingabewert)
A77: Skalierend | B77: Fester Satz, aber Gesamtbetrag skaliert mit Mitarbeiterzahl oder Kundenzahl
A78: Fest | B78: Fester Wert – unabhängig von Szenario und Unternehmensgröße
A79: Zu definieren | B79: Noch nicht im Modell – neuer Einflussfaktor, der entwickelt werden kann
A81: LEGENDE: Szenario=szenarioabhängig (Sandbox) | Unabhängig=eigenständiger Schalter (z.B. Implementation-Support-Quote) | Berechnet=abgeleiteter Wert | Skalierend=fixer Satz, skaliert mit MA/Kunden | NEU (lila)=noch nicht im Modell

Sheet Szenarien_Analyse
A1: Faktor | B1: Referenz (Basis) | C1: Szenario: Gering | D1: Szenario: Normal | E1: Szenario: Stark | F1: DELTA: (Stark vs Normal) | G1: Argumentation (Interviews & Transkripte) | I1: ⚑ HINWEIS: Werte in den Spalten C/D/E (Gering/Normal/Stark) sind direkt bearbeitbar. Änderungen in DIESEM Blatt fließen automatisch über Sandbox → Inputs → Revenue/P&L.
A2: Fokus: Packaging | B2: 0.3 | C2: 0.1 | D2: 0.6 | E2: 0.8 | F2: =E2-D2 | G2: Höhere Margen, schnellere Zyklen als Auto.
A3: Fokus: Automotive | B3: 0.7 | C3: 0.9 | D3: 0.4 | E3: 0.2 | F3: =E3-D3 | G3: Hohe IT-Hürden und Margendruck (Lothar).
A4: Erste zahlende Kunden Monat | B4: 6 | C4: 14 | D4: 8 | E4: 4 | F4: =E4-D4 | G4: IT-Integration ist der Flaschenhals.
A5: Buchungs-Wahrscheinlichkeit Implementation-Support je Kunde | B5: 0.5 | C5: 0.2 | D5: 0.5 | E5: 1 | F5: =E5-D5 | G5: Wahrscheinlichkeit, dass ein gewonnener Kunde Implementation-Support bucht: a) 20 % (gering) = jeder 5. Kunde – Automotive, wenig Beratungsbedarf b) 50 % (normal) = jeder 2. Kunde – Hybrid-Markt c) 100 % (stark) = jeder Kunde – Packaging, hohe Implementierungstiefe → Fließt über Sandbox Z.12 → Inputs Z.139 → Revenue Z.28 | H5: → Sandbox → Inputs
A6: Startpreis pro Seat/Jahr | B6: 1 | C6: 0.8 | D6: 1 | E6: 1.2 | F6: =E6-D6 | G6: Value-Pricing eher in Packaging möglich.
A7: Personal (Experten) in FTE | B7: 5 | C7: 3 | D7: 7 | E7: 12 | F7: =E7-D7 | G7: Bedarf an "Übersetzern" für IT-Landschaft.
A8: Implementation-Support-Tage/Einsatz | B8: 10 | C8: 5 | D8: 10 | E8: 20 | F8: =E8-D8 | G8: Implementation-Support-Tage pro Kunde je Einsatz: gering=5 (Basisschulung + Systemcheck) normal=10 (Implementierungsbegleitung + Anwenderschulung) stark=20 (Spez. Anforderungen, Datenbereinigung, Stammdaten-Harmonisierung) → Fließt über Sandbox Z.11 → Inputs Z.140 → Revenue Z.28 | H8: → Sandbox → Inputs
A9: Net Revenue Retention (NRR) Umsatz von bestehenden Kunden im Vergleich zum Vorjahr – inklusive Upgrades, Downgrades und Kündigungen. Ein NRR von 110% bedeutet z.B., dass Bestandskunden dieses Jahr 10% mehr zahlen als letztes Jahr, selbst ohne einen einzigen Neukunden. Für SaaS-Startups gilt ein NRR über 100% als starkes Signal für Product-Market-Fit, weil es zeigt, dass Kunden bleiben und mehr ausgeben. Benchmark im B2B-SaaS: >120% ist exzellent, >100% ist solide. | B9: 1.15 | C9: 1.05 | D9: 1.15 | E9: 1.3 | F9: =E9-D9 | G9: Treiber-Matrix: NRR szenarioabhängig machen (bisher fest 125%). Gering=105%: Automotive, wenig Upselling-Potenzial. Normal=115%: Hybrid, DPP-Module. Stark=130%: Packaging, Analytics-Premium + Multi-Werk-Rollouts. | H9: → Sandbox → Inputs
A10: Jährliche Churn Rate | B10: 0.06 | C10: 0.1 | D10: 0.06 | E10: 0.03 | F10: =E10-D10 | G10: Treiber-Matrix: Churn szenarioabhängig (bisher fest 6%). Gering=10%: Automotive-Budgetzyklen, höheres Abwanderungsrisiko. Normal=6%: Standardwert (SaaS-Industrie). Stark=3%: Packaging, tiefe API-Integration → hoher Switching-Cost. | H10: → Sandbox → Inputs
A11: Implementation-Support-Startmonat | B11: 4 | C11: 3 | D11: 4 | E11: 6 | F11: =E11-D11 | G11: Treiber-Matrix Z.21: Implementation-Support startet als Enabler vor dem SaaS-Produkt. Gering=Monat 3: Automotive benötigt sofort IT-Begleitung. Stark=Monat 6: Packaging-Kunden länger Self-Service-fähig. | H11: → Sandbox → Inputs

Sheet 00_Input_Sandbox
A1: Wähle aktives Szenario aus --> | B1: gering | C1: Einheit | D1: Gering (Auto-Fokus) | E1: Normal (Hybrid) | F1: Stark (Pack-Fokus) | G1: Argumentation / Quelle
A2: Kategorie | B2: Variable | C2: Einheit | D2: Gering | E2: Normal | F2: Stark | G2: Quelle
A3: Markt-Mix | B3: Anteil Packaging | C3: % | D3: 0.1 | E3: 0.6 | F3: 0.8 | G3: Lothar: Packaging hat schnellere Zyklen.
A4: Vertrieb | B4: Startmonat Kunden | C4: Monate | D4: 17 | E4: 8 | F4: 4 | G4: Lothar: IT-Hürden bei Automotive Tier-1.
A5: Revenue 1 | B5: Startpreis Seat/Monat | C5: €/Monat | D5: 200 | E5: 350 | F5: 450 | G5: Value-based Pricing in Packaging (White Paper).
A6: Revenue 2 | B6: Implementation-Support-Tagessatz | C6: €/Tag | D6: 1000 | E6: 1200 | F6: 1500 | G6: Implementation-Support-Tagessatz: gering=1.000 €/Tag | normal=1.200 €/Tag | stark=1.500 €/Tag. Basiert auf Expertenstatus (Haag/Candemir) und Marktniveau B2B Industrie.
A7: Effizienz | B7: Iterations-Reduktion | C7: Faktor | D7: 1,2x | E7: 2,0x | F7: 3,0x | G7: White Paper: Redesign Trap vermeiden.
A8: Kosten | B8: Onboarding-Aufwand | C8: Stunden | D8: 120 | E8: 60 | F8: 30 | G8: Lothar: Hoher Aufwand bei alten IT-Systemen.
A9: Detailbeschreibung
A10: Revenue 2: Implementation-Support Einsatztage je Kunde initial | B10: Implementation-Support-Tage/Einsatz | C10: Tage/Einsatz | D10: =Szenarien_Analyse!C8 | E10: =Szenarien_Analyse!D8 | F10: =Szenarien_Analyse!E8 | G10: Referenziert Szenarien_Analyse Z.8 (dort bearbeitbar). gering=5 Tage | normal=10 Tage | stark=20 Tage. Direkte Eingabe hier überschreibt die Szenarien-Referenz.
A11: Revenue 2: Buchungs-Wahrscheinlichkeit Implementation-Support je Kunde | B11: Buchungs-Wahrscheinlichkeit Implementation-Support | C11: % | D11: =Szenarien_Analyse!C5 | E11: =Szenarien_Analyse!D5 | F11: =Szenarien_Analyse!E5 | G11: Referenziert Szenarien_Analyse Z.5 (dort bearbeitbar). a) gering=20% – jeder 5. Kunde kauft Implementation-Support, b) normal=50% – jeder 2. Kunde, c) stark=100% – jeder Kunde kauft Implementation-Support-Tage.
A12: Retention: Net Revenue Retention (NRR) | B12: Net Revenue Retention (NRR) | C12: % | D12: =Szenarien_Analyse!C9 | E12: =Szenarien_Analyse!D9 | F12: =Szenarien_Analyse!E9 | G12: Szenarioabhängig (Szenarien_Analyse Z.9). Gering=105% | Normal=115% | Stark=130%.
A13: Retention: Jährliche Churn Rate | B13: Churn Rate | C13: %/Jahr | D13: =Szenarien_Analyse!C10 | E13: =Szenarien_Analyse!D10 | F13: =Szenarien_Analyse!E10 | G13: Szenarioabhängig (Szenarien_Analyse Z.10). Gering=10% | Normal=6% | Stark=3%.
A14: Implementation-Support: Startmonat erster Implementation-Support-Umsatz | B14: Implementation-Support-Startmonat | C14: Monat | D14: =Szenarien_Analyse!C11 | E14: =Szenarien_Analyse!D11 | F14: =Szenarien_Analyse!E11 | G14: Szenarioabhängig (Szenarien_Analyse Z.11). Gering=3 | Normal=4 | Stark=6.

Sheet Inputs
A1: ZENTRALE EINGABEWERTE | B1: Wert | C1: Erklärung / Hinweis | D1: Bemerkungen | E1: Szenarioauswahl: gering, normal, stark
E2: ='00_Input_Sandbox'!$B$1
A3: ALLGEMEINE EINSTELLUNGEN
A4: Firmenname | B4: LoopforgeLab GmbH | C4: Name des Unternehmens
A5: Startdatum | B5: 46113 | C5: Beginn der Projektionen
A6: Währung | B6: EUR | C6: EUR für DACH-Startups
A7: Steuersatz | B7: 0.3 | C7: KSt + GewSt (~30% in DE) | D7: Übernahme des Standardsatzes (KSt + GewSt in Deutschland).
A9: FINANZIERUNGSRUNDEN
A10: Ideation Phase | B10: 90000 | C10: Typisch: 100.000-500.000€ | D10: Phase: 1.4.26 bis 15.7.2026 MVP-Anschubfinanzierung; stellt keine Unternehmensbewertung dar.
A11: Ideation Phase | B11: 1 | C11: Monat der Einzahlung | D11: MVP-Entwicklung und IP-Aufbau starten unmittelbar.
A12: Pre-Seed Betrag | B12: 1500000 | C12: Typisch: 500.000-2.000.000€ | D12: Pre-Seed Phase ab VC Pitch im Juli '26 (1.5M-3M Bewertung).
A13: Pre-Seed Monat | B13: 5 | C13: Typisch: Monat 5 | D13: Juli 2026 entspricht Monat 5 Fokus auf Pilot-Traction.
A14: Seed Betrag | B14: 4000000 | C14: Typisch: 3.000.000-10.000.000€ | D14: Abhängig von Pilotprojekten und Reife des Produktes
A15: Seed Monat | B15: 17 | C15: Typisch: Monat 17 | D15: Geplant für Mitte 2027.
A16: Series A Betrag | B16: 10000000 | C16: Typisch: 10.000.000-25.000.000€ | D16: Vorerst unverändert als langfristige Wachstumsambition.
A17: Series A Monat | B17: 36 | C17: Typisch: Monat 35 | D17: Geplant für Herbst 2028.
A19: REVENUE-ANNAHMEN (SaaS/ARR)
A20: Startpreis pro Seat/Jahr | B20: =VLOOKUP("Startpreis Seat/Monat",'00_Input_Sandbox'!$B$2:$F$19,IF('00_Input_Sandbox'!$B$1="gering",3,IF('00_Input_Sandbox'!$B$1="normal",4,5)),FALSE)*12 | C20: Jährliche Lizenzgebühr pro Nutzer | D20: 1. Realistisch? Hängt auch ab vom Business Modell..Pricing basierend auf Wettbewerb oder auf voraussichtlichem Einsparpotential? 2. weitere Erlösquellen? Beratung? Implementierungsaufwand? Hybrid-Modell: Deckt Fixkosten und partizipiert am TCO-Einsparwert. [1]
A21: Preiserhöhung/Jahr | B21: 0.05 | C21: Typisch: 3-5% p.a. | D21: Standard für AI-SaaS 2026 (Kompensation Inferenz/Innovation). [4]
A22: Erste zahlende Kunden Monat | B22: =VLOOKUP("Startmonat Kunden",'00_Input_Sandbox'!$B$2:$F$19,IF('00_Input_Sandbox'!$B$1="gering",3,IF('00_Input_Sandbox'!$B$1="normal",4,5)),FALSE) | C22: Wann erster Umsatz? | D22: Erster Umsatz in Monat 8 (Start: 04/26)…Realistisch? Wie lange Lead-Time? Zielkunden? Beachhead-Market? Weitere Begründung: wenn im Automotivebereich: Puffer für Sales-Zyklen (9-12 Mon.) und TISAX im Mittelstand. [1
A23: Initiale Seats SME | B23: 5 | C23: Anzahl Seats beim Kunden | D23: Realistisch? Hängt von Kundengrösse ab. Implementierungsaufwand je Kunde mit einkalkulieren weitere Aspekte: Kalkulieren mit 1-2 Projekten/ Start mit Pilotprojekten (Werke) zur ROI-Validierung ("Land&Expand")
A24: Initiale Seats Mid-Company | B24: 15
A25: Monatliche Seat-Wachstumsrate | B25: 0.03 | C25: Wachstum neue Seats/Monat | D25: -->hier eine Annahme bzgll Vertriebsplanung treffen. Wie hoch ist die Zahl der Verkauften Sitze nach 1, 2, 3 Jahren? Gibt es noch andere Erlösströme? ALTERNATIVE: Account-basierte Planng: Wechsel auf "Stufenfunktion" beim Aufbau des Geschäfts (Roll-out pro Werk statt linearer Rate)
C26: Fokus auf Packaging Industrie Wenn Automotive: Verschiebung durch längere Technical Validation und Compliance-Hürden. | D26: Start ab Fertigstellung MVP in der Seed Phase
A27: Durchschnittlicher Enterprise ARR pro Vertrag | B27: 25000 | C27: Typisch: 50.000-200.000€/Jahr | D27: Höheres Volumen durch Tiefe der Integration: hier Annahme von weiteren Benefits wie Einbeziehung von DPP & Sustainability
C28: Neue Enterprise-Deals pro Quartal
A29: Jährliche Churn Rate | B29: =VLOOKUP("Churn Rate",'00_Input_Sandbox'!$B$2:$F$19,IF('00_Input_Sandbox'!$B$1="gering",3,IF('00_Input_Sandbox'!$B$1="normal",4,5)),FALSE) | C29: Jährliche Churn Rate (szenarioabhängig): Gering=10% | Normal=6% | Stark=3% | D29: Treiber-Matrix: Churn jetzt szenarioabhängig (vorher fest 15%). Automotive: 10% (Budgetzyklen). Packaging: 3% (hoher Switching-Cost).
A30: Net Revenue Retention | B30: =VLOOKUP("Net Revenue Retention (NRR)",'00_Input_Sandbox'!$B$2:$F$19,IF('00_Input_Sandbox'!$B$1="gering",3,IF('00_Input_Sandbox'!$B$1="normal",4,5)),FALSE) | C30: Net Revenue Retention (szenarioabhängig): Gering=105% | Normal=115% | Stark=130% | D30: Treiber-Matrix: NRR jetzt szenarioabhängig (vorher fest 125%). Expansion-Umsatz minus Churn. NRR>100%=Bestandskunden wachsen.
A32: GEHÄLTER (Brutto/Jahr)
A33: CEO Gehalt | B33: 100000 | C33: Bestätigtes Gründergehalt: CEO/CTO/CCO je €100.000/Jahr (Brutto) | D33: Rene: negotiatable for Ideation Phase
A34: CTO Gehalt | B34: 100000 | C34: Bestätigtes Gründergehalt: CEO/CTO/CCO je €100.000/Jahr (Brutto)
A35: CCO Gehalt | B35: 100000 | C35: Bestätigtes Gründergehalt: CEO/CTO/CCO je €100.000/Jahr (Brutto)
A36: Software Developer | B36: 75000 | C36: Typisch: 55.000-90.000€ | D36: Source: various Sources (https://claude.ai/chat/0f63ea1a-6930-460c-954d-87864e88929e)
A37: Junior Software Developer | B37: 52000 | C37: Typisch: 42.000-58.000€ | D37: Source: various Sources (https://claude.ai/chat/0f63ea1a-6930-460c-954d-87864e88929e)
A38: ML/AI Engineer Gehalt | B38: 70000 | C38: Typisch: 50.000-125.000€ | D38: Source: various Sources (https://claude.ai/chat/0f63ea1a-6930-460c-954d-87864e88929e)
A39: Site Reliability Engineer | B39: 70000 | C39: Typisch: 50.000-110.000€ | D39: Source: various Sources (https://claude.ai/chat/0f63ea1a-6930-460c-954d-87864e88929e)
A40: UX/UI Designer | B40: 50000 | C40: Typisch: 42.000-80.000€ | D40: Source: various Sources (https://claude.ai/chat/0f63ea1a-6930-460c-954d-87864e88929e)
A41: Mechanical Engineer (incl. SoftwareDev) | B41: 70000 | C41: Typisch: 45.000-85.000€ | D41: Source: various Sources (https://claude.ai/chat/0f63ea1a-6930-460c-954d-87864e88929e)
A42: Customer Key Account Gehalt | B42: 100000 | C42: Typisch: 50.000-70.000€ + Provision | D42: Split 50/50 (65k fix + 65k var); zwingend für Enterprise-Vertrieb. [12
A43: Marketing Manager Gehalt | B43: 65000 | C43: Typisch: 55.000-75.000€ | D43: Anpassung an Marktniveau für B2B-Industrie-Spezialisten.
A44: Marketing Assistant Gehalt | B44: 45000
A45: Customer Success Gehalt | B45: 52000 | C45: Typisch: 45.000-60.000€
A46: Office Manager Gehalt | B46: 45000 | C46: Typisch: 40.000-50.000€
A47: Finance Manager | B47: 80000
A48: Jährliche Gehaltserhöhung | B48: 0.03 | C48: Typisch: 3-5% | D48: Berücksichtigt Inflations- und Kompetenzentwicklung im Tech-Sektor.
A49: Lohnnebenkosten | B49: 0.21 | C49: AG-Anteil Sozialversicherung ~20-21% | D49: Übernahme des gesetzlichen AG-Anteils.
A51: EINSTELLUNGSPLAN (Eintrittsmonat) | B51: geplanter Bedarf/ Zeitpunkt des geplanten Eintritts | C51: WICHTIG: KEINE Zeilen löschen. Wenn nicht benötigt, einfach SPALTE B nicht befüllen | E51: Tatsächlicher Eintritt ins Unternehmen
A52: 1. Software Developer | B52: 5 | C52: Software Developer | E52: =B51
A53: 2. Software Developer | B53: 17 | C53: Software Developer | E53: =B52
A54: 1. Junior Software Developer | B54: 9 | C54: Junior Developer | E54: =B53
A55: 1. ML/AI Engineer | B55: 8 | C55: ML/AI Spezialist | E55: =B54
A56: 1. Mechanical Engineer | B56: 11 | C56: Mec Engineer/Developer | D56: combining mechanical engineering with CAD automation, robotics software, or embedded systems | E56: =B55
A57: 1. Site Reliability Mgr | B57: 10 | E57: =B56
A58: 1. UX/UI Designer | B58: 12 | C58: UX/UI Designer | E58: =B57
A59: 1. Customer Key Account | B59: 17 | C59: Sales & Key Account DACH | E59: =B58
A60: 2. Customer Key Account | B60: 20 | C60: Sales & Key Account DACH | E60: =B59
A61: 3. Customer Key Account | B61: 29 | C61: Sales & Key Account PL/CZ/Benelux | E61: =B60
A62: 1. Marketing Assistant | B62: 20 | C62: Marketing Support | E62: =B61
A63: 2. Marketing Assistant | B63: 29 | C63: Marketing Support | E63: =B62
A64: 1. Marketing Manager | B64: 18 | C64: Marketing | E64: =B63
A65: 1. Office Manager | B65: 14 | C65: Admin/Office | E65: =B64
A66: 1. Customer Success | B66: 24 | C66: CS Mgr | D66: taking care of Customer Projects and Support | E66: =B65
A67: 1. Finance Manager | B67: 19 | C67: Finance/Controlling | D67: Notwendig für professionelles Reporting ab Seed-Phase. | E67: =B66
A69: TECHNOLOGIE & CLOUD KOSTEN
A70: Cloud/Hosting Basis | B70: 2000 | C70: AWS/Azure/GCP Grundkosten €/Monat | D70: Höhere Last durch GPU-Inferenz und Vektordatenbanken. 800→2.000 €/Monat (Treiber-Matrix)
A71: Cloud Skalierung pro Seat | B71: 80 | C71: Variable Kosten €/Seat/Monat | D71: Wechsel von Seat- auf Projekt-Basis (AI-intensive Rechenlast). 50→80 €/Seat/Monat (Treiber-Matrix)
A72: AI/ML APIs Basis | B72: 2000 | C72: OpenAI/Anthropic etc. €/Monat | D72: Nutzung von Frontier Models (GPT-5/Claude) für Design-Logic. 600→2.000 €/Monat (Treiber-Matrix)
A73: AI Kosten Wachstum/Monat | B73: 0.08 | C73: Steigerung mit Nutzung | D73: Skalierung proportional zur Nutzung und Datentiefe. 3%→8%/Monat (Treiber-Matrix)
A74: SaaS Tools intern Basis | B74: 400 | C74: Slack, Notion, GitHub etc. €/Monat | D74: Slack; Notion; GitHub etc. (unverändert).
A75: SaaS Tools pro MA | B75: 100 | C75: Zusätzliche Lizenzen €/MA/Monat | D75: Inklusive KI-Coding-Tools (Copilot/Cursor) für Dev-Effizienz.
A76: Software-Lizenzen Dev | B76: 5000 | C76: IDE, Frameworks €/Jahr | D76: Spezialisierte Engineering-Tools und Frameworks (IDE).
A77: Sicherheit & Compliance | B77: 3500 | C77: Security Tools €/Monat | D77: Puffer für TISAX-Audits und laufendes Compliance-Monitoring. [17
A79: HARDWARE & EQUIPMENT
A80: Laptop pro MA | B80: 2500 | C80: Typisch: 1.500-3.000€ | D80: High-End Hardware zwingend für KI-Entwicklung (lokale Inferenz). -->CHANGE to smaller numbers, at least Think of renting IT (GROVER)
A81: Monitor & Peripherie | B81: 800 | C81: Typisch: 500-1.000€ | D81: Standard-Setup für Tech-Mitarbeiter.
A82: Ersatz-Zyklus Monate | B82: 36 | C82: Typisch: 36-48 Monate | D82: Branchenüblicher Turnus.
A83: Sonstige IT-Ausstattung/Jahr | B83: 2000 | C83: Server, Netzwerk etc. | D83: Puffer für Serverkomponenten/Netzwerk.
A85: BÜRO & FACILITIES
A86: Büromiete | B86: 1500 | C86: Coworking anfangs €/Monat | D86: Coworking-Fokus in der ersten Phase (Berlin Mitte/Kreuzberg).
A87: Büro-Upgrade ab Monat | B87: 18 | C87: Wann größeres Büro? | D87: Shift analog zur Einstellung von Solution Architects (Teamgröße).
A88: Neue Büromiete | B88: 4500 | C88: Kosten nach Upgrade €/Monat | D88: Anpassung an Berliner Marktpreise für ca. 15-20 Personen.
A89: Nebenkosten | B89: 300 | C89: Strom, Wasser, Heizung €/Monat | D89: Übernahme.
A90: Internet & Telefon | B90: 150 | C90: €/Monat | D90: Übernahme.
A91: Büroausstattung Initial | B91: 5000 | C91: Möbel, Einrichtung € | D91: Möbel und IT-Grundausstattung für Erst-Team.
A92: Bürobedarf pro MA | B92: 30 | C92: Verbrauchsmaterial €/MA/Monat | D92: Verbrauchsmaterial (unverändert).
A94: PROFESSIONAL SERVICES
A95: Rechtsanwalt Basis/Jahr | B95: 8000 | C95: Laufende Beratung €/Jahr
A96: RA pro Finanzierung | B96: 15000 | C96: Zusätzlich bei Funding € | D96: Ändern, 15k€ sind vermutlich zu hoch Für C13 Founding Phase: less effort
A97: Steuerberater | B97: 800 | C97: Laufende Buchhaltung €/Monat
A98: Wirtschaftsprüfer/Jahr | B98: 12000 | C98: Ab Series A €/Jahr
A99: WP ab Monat | B99: 17 | C99: Ab wann Wirtschaftsprüfer? Start mit tatsächlicher Seed-Phase Mitte 2027.
A100: Unternehmensberater/Jahr | B100: 5000 | C100: Optional €/Jahr Optionaler Puffer für Spezialberatung (DPP/MDR).
A102: VERSICHERUNGEN & BANK
A103: D&O Versicherung/Jahr | B103: 3000 | C103: Directors & Officers €/Jahr Schutz für Management (Standard-Satz).
A104: Betriebshaftpflicht/Jahr | B104: 1500 | C104: €/Jahr Deckung für industrielle Software-Einsätze.
A105: Cyber-Versicherung/Jahr | B105: 2000 | C105: €/Jahr Kritisch bei Verarbeitung von Kundendaten (IP-Schutz).
A106: Bankgebühren | B106: 50 | C106: Kontoführung €/Monat
A107: Payment Processing | B107: 0.025 | C107: Stripe/PayPal ~2-3% vom Umsatz Anteil am Umsatz für SaaS-Billing-Systeme (Stripe etc.).
A109: MARKETING & SALES
A110: Paid Ads Budget Initial | B110: 1000 | C110: Google, LinkedIn etc. €/Monat Fokus eher auf Content/SEO (Industrie-Vertrieb). | D110: 300→1.000 €/Monat (Treiber-Matrix)
...

Sheet P&L
A1: GEWINN- UND VERLUSTRECHNUNG (P&L)
A3: Position | B3: M1 | C3: M2 | D3: M3 | E3: M4 | F3: M5 | G3: M6 | H3: M7 | I3: M8 | J3: M9 | K3: M10 | L3: M11 | M3: M12 | N3: M13 | O3: M14 | P3: M15 | Q3: M16 | R3: M17 | S3: M18 | T3: M19 | U3: M20 | V3: M21 | W3: M22 | X3: M23 | Y3: M24 | Z3: M25 | AA3: M26 | AB3: M27 | AC3: M28 | AD3: M29 | AE3: M30 | AF3: M31 | AG3: M32 | AH3: M33 | AI3: M34 | AJ3: M35 | AK3: M36 | AL3: M37 | AM3: M38 | AN3: M39 | AO3: M40 | AP3: M41 | AQ3: M42 | AR3: M43 | AS3: M44 | AT3: M45 | AU3: M46 | AV3: M47 | AW3: M48 | AX3: M49 | AY3: M50 | AZ3: M51 | BA3: M52
A4: REVENUE
A5: Subscription Revenue | B5: =Revenue!B12 | C5: =Revenue!C12 | D5: =Revenue!D12 | E5: =Revenue!E12 | F5: =Revenue!F12 | G5: =Revenue!G12 | H5: =Revenue!H12 | I5: =Revenue!I12 | ... BA5: =Revenue!BA12
A6: Enterprise Revenue | B6: =Revenue!B19 | C6: =Revenue!C19 | D6: =Revenue!D19 | E6: =Revenue!E19 | F6: =Revenue!F19 | G6: =Revenue!G19 | H6: =Revenue!H19 | I6: =Revenue!I19 | ... BA6: =Revenue!BA19
A7: Implementation Support Revenue | B7: =Revenue!B32 | C7: =Revenue!C32 | D7: =Revenue!D32 | E7: =Revenue!E32 | F7: =Revenue!F32 | G7: =Revenue!G32 | H7: =Revenue!H32 | I7: =Revenue!I32 | ... BA7: =Revenue!BA32
A8: TOTAL REVENUE | B8: =B5+B6+B7 | C8: =C5+C6+C7 | D8: =D5+D6+D7 | E8: =E5+E6+E7 | F8: =F5+F6+F7 | G8: =G5+G6+G7 | H8: =H5+H6+H7 | I8: =I5+I6+I7 | ... BA8: =BA5+BA6+BA7
A9: COST OF GOODS SOLD (COGS)
A10: Cloud Hosting (variable) | B10: =Costs!B50 | C10: =Costs!C50 | D10: =Costs!D50 | E10: =Costs!E50 | F10: =Costs!F50 | G10: =Costs!G50 | H10: =Costs!H50 | I10: =Costs!I50 | ... BA10: =Costs!BA50
A11: AI/ML API Kosten | B11: =Costs!B51 | C11: =Costs!C51 | D11: =Costs!D51 | E11: =Costs!E51 | F11: =Costs!F51 | G11: =Costs!G51 | H11: =Costs!H51 | I11: =Costs!I51 | ... BA11: =Costs!BA51
A12: Payment Processing | B12: =Costs!B96 | C12: =Costs!C96 | D12: =Costs!D96 | E12: =Costs!E96 | F12: =Costs!F96 | G12: =Costs!G96 | H12: =Costs!H96 | I12: =Costs!I96 | ... BA12: =Costs!BA96
A13: TOTAL COGS | B13: =SUM(B10:B12) | C13: =SUM(C10:C12) | D13: =SUM(D10:D12) | E13: =SUM(E10:E12) | F13: =SUM(F10:F12) | G13: =SUM(G10:G12) | H13: =SUM(H10:H12) | I13: =SUM(I10:I12) | ... BA13: =SUM(BA10:BA12)
A15: GROSS PROFIT | B15: =B8-B13 | C15: =C8-C13 | D15: =D8-D13 | E15: =E8-E13 | F15: =F8-F13 | G15: =G8-G13 | H15: =H8-H13 | I15: =I8-I13 | ... BA15: =BA8-BA13
A16: Gross Margin % | B16: =IFERROR(B15/B8,0) | C16: =IFERROR(C15/C8,0) | D16: =IFERROR(D15/D8,0) | E16: =IFERROR(E15/E8,0) | F16: =IFERROR(F15/F8,0) | G16: =IFERROR(G15/G8,0) | H16: =IFERROR(H15/H8,0) | I16: =IFERROR(I15/I8,0) | ... BA16: =IFERROR(BA15/BA8,0)
A18: OPERATING EXPENSES
A19: Total Personnel | B19: =Costs!B46 | C19: =Costs!C46 | D19: =Costs!D46 | E19: =Costs!E46 | F19: =Costs!F46 | G19: =Costs!G46 | H19: =Costs!H46 | I19: =Costs!I46 | ... BA19: =Costs!BA46
A20: Total Technology | B20: =Costs!B55 | C20: =Costs!C55 | D20: =Costs!D55 | E20: =Costs!E55 | F20: =Costs!F55 | G20: =Costs!G55 | H20: =Costs!H55 | I20: =Costs!I55 | ... BA20: =Costs!BA55
A21: Total Office/Facilities | B21: =Costs!B62 | C21: =Costs!C62 | D21: =Costs!D62 | E21: =Costs!E62 | F21: =Costs!F62 | G21: =Costs!G62 | H21: =Costs!H62 | I21: =Costs!I62 | ... BA21: =Costs!BA62
A22: Total Professional Services | B22: =Costs!B69 | C22: =Costs!C69 | D22: =Costs!D69 | E22: =Costs!E69 | F22: =Costs!F69 | G22: =Costs!G69 | H22: =Costs!H69 | I22: =Costs!I69 | ... BA22: =Costs!BA69
A23: Total Insurance & Bank | B23: =Costs!B76 | C23: =Costs!C76 | D23: =Costs!D76 | E23: =Costs!E76 | F23: =Costs!F76 | G23: =Costs!G76 | H23: =Costs!H76 | I23: =Costs!I76 | ... BA23: =Costs!BA76
A24: Total Marketing & Sales | B24: =Costs!B85 | C24: =Costs!C85 | D24: =Costs!D85 | E24: =Costs!E85 | F24: =Costs!F85 | G24: =Costs!G85 | H24: =Costs!H85 | I24: =Costs!I85 | ... BA24: =Costs!BA85
A25: Total Other OpEx | B25: =Costs!B93 | C25: =Costs!C93 | D25: =Costs!D93 | E25: =Costs!E93 | F25: =Costs!F93 | G25: =Costs!G93 | H25: =Costs!H93 | I25: =Costs!I93 | ... BA25: =Costs!BA93
A26: Contingency/Buffer | B26: =Costs!B98 | C26: =Costs!C98 | D26: =Costs!D98 | E26: =Costs!E98 | F26: =Costs!F98 | G26: =Costs!G98 | H26: =Costs!H98 | I26: =Costs!I98 | ... BA26: =Costs!BA98
A27: TOTAL OPERATING EXPENSES | B27: =SUM(B19:B26) | C27: =SUM(C19:C26) | D27: =SUM(D19:D26) | E27: =SUM(E19:E26) | F27: =SUM(F19:F26) | G27: =SUM(G19:G26) | H27: =SUM(H19:H26) | I27: =SUM(I19:I26) | ... BA27: =SUM(BA19:BA26)
A29: EBITDA | B29: =B15-B27 | C29: =C15-C27 | D29: =D15-D27 | E29: =E15-E27 | F29: =F15-F27 | G29: =G15-G27 | H29: =H15-H27 | I29: =I15-I27 | ... BA29: =BA15-BA27
A30: EBITDA Margin % | B30: =IFERROR(B29/B8,0) | C30: =IFERROR(C29/C8,0) | D30: =IFERROR(D29/D8,0) | E30: =IFERROR(E29/E8,0) | F30: =IFERROR(F29/F8,0) | G30: =IFERROR(G29/G8,0) | H30: =IFERROR(H29/H8,0) | I30: =IFERROR(I29/I8,0) | ... BA30: =IFERROR(BA29/BA8,0)
A32: Depreciation & Amortization | B32: =Costs!B91/Inputs!$B$127/12 | C32: =Costs!C91/Inputs!$B$127/12 | D32: =Costs!D91/Inputs!$B$127/12 | E32: =Costs!E91/Inputs!$B$127/12 | F32: =Costs!F91/Inputs!$B$127/12 | G32: =Costs!G91/Inputs!$B$127/12 | H32: =Costs!H91/Inputs!$B$127/12 | I32: =Costs!I91/Inputs!$B$127/12 | ... BA32: =Costs!BA91/Inputs!$B$127/12
A34: EBIT (Operating Income) | B34: =B29-B32 | C34: =C29-C32 | D34: =D29-D32 | E34: =E29-E32 | F34: =F29-F32 | G34: =G29-G32 | H34: =H29-H32 | I34: =I29-I32 | ... BA34: =BA29-BA32
A36: EBT (Earnings Before Tax) | B36: =B34 | C36: =C34 | D36: =D34 | E36: =E34 | F36: =F34 | G36: =G34 | H36: =H34 | I36: =I34 | ... BA36: =BA34
A37: Income Tax | B37: =IF(B36>0,B36*Inputs!$B$7,0) | C37: =IF(C36>0,C36*Inputs!$B$7,0) | D37: =IF(D36>0,D36*Inputs!$B$7,0) | E37: =IF(E36>0,E36*Inputs!$B$7,0) | F37: =IF(F36>0,F36*Inputs!$B$7,0) | G37: =IF(G36>0,G36*Inputs!$B$7,0) | H37: =IF(H36>0,H36*Inputs!$B$7,0) | I37: =IF(I36>0,I36*Inputs!$B$7,0) | ... BA37: =IF(BA36>0,BA36*Inputs!$B$7,0)
A39: NET INCOME | B39: =B36-B37 | C39: =C36-C37 | D39: =D36-D37 | E39: =E36-E37 | F39: =F36-F37 | G39: =G36-G37 | H39: =H36-H37 | I39: =I36-I37 | ... BA39: =BA36-BA37
A40: Net Margin % | B40: =IFERROR(B39/B8,0) | C40: =IFERROR(C39/C8,0) | D40: =IFERROR(D39/D8,0) | E40: =IFERROR(E39/E8,0) | F40: =IFERROR(F39/F8,0) | G40: =IFERROR(G39/G8,0) | H40: =IFERROR(H39/H8,0) | I40: =IFERROR(I39/I8,0) | ... BA40: =IFERROR(BA39/BA8,0)

Sheet Tabelle1
A1: IT/Product Development/Framework | B1: Phase | C1: Content | D1: Phase | E1: Content | F1: Phase | G1: Content | H1: Phase | I1: Content | J1: Phase | K1: Content
A2: Month (starting Apr 26) | B2: M1-M4 | D2: M5-M16 | F2: M17-M28 | H2: M29-M40 | J2: M41-M52
B3: April to Jul 2026 | D3: Aug 2026 to Jul 2027 | F3: Aug 2027 to Jul 2028 | H3: Aug 2028 to Jul 2029 | J3: Aug 2029 to Jul 2030
B4: IDEATION Phase | D4: PRE-SEED | F4: SEED | H4: SERIES A | J4: Series B?? NOT PART OF OUR C13 Forecast
A5: Companies to be served | D5: 3 (SME) | E5: "Bottleneck" is Sales (Rene/Olaf) -->Existence of "MVP" is essential!! | G5: 2 Enterprises, 15 Mid-Size and 10 SMEs (27 cumulative) | I5: 6 Enterprises, 44 Mid-Size Companies, 30 SMEs (80 cumulative) (ARR: 5.6M by mid July 2029)
A6: Large OEM (Enterprise Deals) | B6: 0 | D6: 0 | F6: 2 | H6: 3 | J6: 6
A7: Mid-size OEM | B7: 0 | D7: 0 | F7: 15 | H7: 30 | J7: 50
A8: SME | B8: 0 | D8: 3 | F8: 10 | H8: 20 | J8: 60
A9: Cumulative | D9: 3 | F9: =D9+F6+F7+F8 | H9: =F9+H6+H7+H8 | J9: =H9+J6+J7+J8
A11: Co Founder Salary | C11: see: INPUT: Agreement: 100k€ per Cofounder as "AG-Brutto", ie. Approx. 52.000€/yr Netto
A12: Product features Product Development per Phase | C12: `-MVP "light" Getting LOIs | E12: -Plugins into one incumbent solution -Calculate manufacturing costs (BOM requirements) FEATURES of the MVP: -Core Engine -API for data ingestion & Normalisation -Data Integration (CAD, BOM, Processes costs, Supply data, EU regulations) -Manufacturing Cost engine -Operator Cost (TOC) engine -User Interface -(think about creating RfQ documents..is necessary for the mvp?) | G12: `-Integration into more incumbent solutions -Similarity and tribal knowledge engine -Compliance engine -Trade off and scnario analysis -Functional model and failure mode integration -… | I12: -Product Scaling -TCO Engine -Lifecycle Cost Engine -Propriatory Scoring Model for Products (depending on requirements) -Recommending alternative features of products/ decisions to take("Recommending System")
A13: People (IT) | E13: -Number of SW Engineers needed for MVP: -2 Developers -1 ML/AI Engineer (optional) -1 Site Reliability Engineer -1 UX/UI (optional) -1 Mechanical Engineer/Developer (who would love to work as a developer) -->people estimation are "conservative" -->ramp up of personnel over 12 month | G13: 1 Developer
A14: People (Marketing) | E14: `-1 Customer Key Account | G14: `-2 to 3 Sales/Marketing People -big budget for Sales/Marketing | I14: `-2 to 3 Sales/Marketing People -big budget for Sales/Marketing
A15: IT Licenses | E15: -Licenses for incumbent solutions (Autodesk, Siemens NX, Catia, PTC??
A16: IT Equipment | C16: -Budget for IT Licenses: 200€/month -no new equipment needed for the founders
A18: Office (permanent) | C18: no office in the first month | G18: Office Space
A19: Office (Coworking Space) | C19: `-400€/Desk/month | E19: 3 Desks/month? -->Meeting Place and conference room optional
A23: Fees (Lawyers, Notary,..) | C23: less spent in the ideation phase | E23: regular sum from here onwards | H23: higher? Sum according to more Stakeholders and bigger financing round

Sheet Revenue
A1: UMSATZMODELL - Detaillierte Aufschlüsselung
B2: 46113 | C2: 46143 | D2: 46174 | E2: 46204 | F2: 46235 | G2: 46266 | H2: 46296 | I2: 46327 | J2: 46357 | K2: 46388 | L2: 46419 | M2: 46447 | N2: 46478 | O2: 46508 | P2: 46539 | Q2: 46569 | R2: 46600 | S2: 46631 | T2: 46661 | U2: 46692 | V2: 46722 | W2: 46753 | X2: 46784 | Y2: 46813 | Z2: 46844 | AA2: 46874 | AB2: 46905 | AC2: 46935 | AD2: 46966 | AE2: 46997 | AF2: 47027 | AG2: 47058 | AH2: 47088 | AI2: 47119 | AJ2: 47150 | AK2: 47178 | AL2: 47209 | AM2: 47239 | AN2: 47270 | AO2: 47300 | AP2: 47331 | AQ2: 47362 | AR2: 47392 | AS2: 47423 | AT2: 47453 | AU2: 47484 | AV2: 47515 | AW2: 47543 | AX2: 47574 | AY2: 47604 | AZ2: 47635 | BA2: 47665
A3: Startup-Phasen | B3: Ideation | C3: Ideation | D3: Ideation | E3: Ideation | F3: Pre-Seed | G3: Pre-Seed | H3: Pre-Seed | I3: Pre-Seed | J3: Pre-Seed | K3: Pre-Seed | L3: Pre-Seed | M3: Pre-Seed | N3: Pre-Seed | O3: Pre-Seed | P3: Pre-Seed | Q3: Pre-Seed | R3: Seed | S3: Seed | T3: Seed | U3: Seed | V3: Seed | W3: Seed | X3: Seed | Y3: Seed | Z3: Seed | AA3: Seed | AB3: Seed | AC3: Seed | AD3: Series A | AE3: Series A | AF3: Series A | AG3: Series A | AH3: Series A | AI3: Series A | AJ3: Series A | AK3: Series A | AL3: Series A | AM3: Series A | AN3: Series A | AO3: Series A | AP3: Series B | AQ3: Series B | AR3: Series B | AS3: Series B | AT3: Series B | AU3: Series B | AV3: Series B | AW3: Series B | AX3: Series B | AY3: Series B | AZ3: Series B | BA3: Series B
A4: Kennzahl | B4: M1 | C4: M2 | D4: M3 | E4: M4 | F4: M5 | G4: M6 | H4: M7 | I4: M8 | J4: M9 | K4: M10 | L4: M11 | M4: M12 | N4: M13 | O4: M14 | P4: M15 | Q4: M16 | R4: M17 | S4: M18 | T4: M19 | U4: M20 | V4: M21 | W4: M22 | X4: M23 | Y4: M24 | Z4: M25 | AA4: M26 | AB4: M27 | AC4: M28 | AD4: M29 | AE4: M30 | AF4: M31 | AG4: M32 | AH4: M33 | AI4: M34 | AJ4: M35 | AK4: M36 | AL4: M37 | AM4: M38 | AN4: M39 | AO4: M40 | AP4: M41 | AQ4: M42 | AR4: M43 | AS4: M44 | AT4: M45 | AU4: M46 | AV4: M47 | AW4: M48 | AX4: M49 | AY4: M50 | AZ4: M51 | BA4: M52
A5: Preis pro Seat/Monat (€) (gilt für SME und Mid-Comps) | B5: =IFERROR(Inputs!$B$20/12*(1+Inputs!$B$21)^(INT((1-1)/12)),0) | C5: =Inputs!$B$20/12*(1+Inputs!$B$21)^INT((2-1)/12) | D5: =Inputs!$B$20/12*(1+Inputs!$B$21)^INT((3-1)/12) | E5: =Inputs!$B$20/12*(1+Inputs!$B$21)^INT((4-1)/12) | F5: =Inputs!$B$20/12*(1+Inputs!$B$21)^INT((5-1)/12) | G5: =Inputs!$B$20/12*(1+Inputs!$B$21)^INT((6-1)/12) | H5: =Inputs!$B$20/12*(1+Inputs!$B$21)^INT((7-1)/12) | I5: =Inputs!$B$20/12*(1+Inputs!$B$21)^INT((8-1)/12) | J5: =Inputs!$B$20/12*(1+Inputs!$B$21)^INT((9-1)/12) | K5: =Inputs!$B$20/12*(1+Inputs!$B$21)^INT((10-1)/12) | L5: =Inputs!$B$20/12*(1+Inputs!$B$21)^INT((11-1)/12) | M5: =Inputs!$B$20/12*(1+Inputs!$B$21)^INT((12-1)/12) | N5: =Inputs!$B$20/12*(1+Inputs!$B$21)^INT((13-1)/12) | O5: =Inputs!$B$20/12*(1+Inputs!$B$21)^INT((14-1)/12) | P5: =Inputs!$B$20/12*(1+Inputs!$B$21)^INT((15-1)/12) | Q5: =Inputs!$B$20/12*(1+Inputs!$B$21)^INT((16-1)/12) | R5: =Inputs!$B$20/12*(1+Inputs!$B$21)^INT((17-1)/12) | S5: =Inputs!$B$20/12*(1+Inputs!$B$21)^INT((18-1)/12) | T5: =Inputs!$B$20/12*(1+Inputs!$B$21)^INT((19-1)/12) | U5: =Inputs!$B$20/12*(1+Inputs!$B$21)^INT((20-1)/12) | V5: =Inputs!$B$20/12*(1+Inputs!$B$21)^INT((21-1)/12) | W5: =Inputs!$B$20/12*(1+Inputs!$B$21)^INT((22-1)/12) | X5: =Inputs!$B$20/12*(1+Inputs!$B$21)^INT((23-1)/12) | Y5: =Inputs!$B$20/12*(1+Inputs!$B$21)^INT((24-1)/12) | Z5: =Inputs!$B$20/12*(1+Inputs!$B$21)^INT((25-1)/12) | AA5: =Inputs!$B$20/12*(1+Inputs!$B$21)^INT((26-1)/12) | AB5: =Inputs!$B$20/12*(1+Inputs!$B$21)^INT((27-1)/12) | AC5: =Inputs!$B$20/12*(1+Inputs!$B$21)^INT((28-1)/12) | AD5: =Inputs!$B$20/12*(1+Inputs!$B$21)^INT((29-1)/12) | AE5: =Inputs!$B$20/12*(1+Inputs!$B$21)^INT((30-1)/12) | AF5: =Inputs!$B$20/12*(1+Inputs!$B$21)^INT((31-1)/12) | AG5: =Inputs!$B$20/12*(1+Inputs!$B$21)^INT((32-1)/12) | AH5: =Inputs!$B$20/12*(1+Inputs!$B$21)^INT((33-1)/12) | AI5: =Inputs!$B$20/12*(1+Inputs!$B$21)^INT((34-1)/12) | AJ5: =Inputs!$B$20/12*(1+Inputs!$B$21)^INT((35-1)/12) | AK5: =Inputs!$B$20/12*(1+Inputs!$B$21)^INT((36-1)/12) | AL5: =Inputs!$B$20/12*(1+Inputs!$B$21)^INT((37-1)/12) | AM5: =Inputs!$B$20/12*(1+Inputs!$B$21)^INT((38-1)/12) | AN5: =Inputs!$B$20/12*(1+Inputs!$B$21)^INT((39-1)/12) | AO5: =Inputs!$B$20/12*(1+Inputs!$B$21)^INT((40-1)/12) | AP5: =Inputs!$B$20/12*(1+Inputs!$B$21)^INT((41-1)/12) | AQ5: =Inputs!$B$20/12*(1+Inputs!$B$21)^INT((42-1)/12) | AR5: =Inputs!$B$20/12*(1+Inputs!$B$21)^INT((43-1)/12) | AS5: =Inputs!$B$20/12*(1+Inputs!$B$21)^INT((44-1)/12) | AT5: =Inputs!$B$20/12*(1+Inputs!$B$21)^INT((45-1)/12) | AU5: =Inputs!$B$20/12*(1+Inputs!$B$21)^INT((46-1)/12) | AV5: =Inputs!$B$20/12*(1+Inputs!$B$21)^INT((47-1)/12) | AW5: =Inputs!$B$20/12*(1+Inputs!$B$21)^INT((48-1)/12) | AX5: =Inputs!$B$20/12*(1+Inputs!$B$21)^INT((49-1)/12) | AY5: =Inputs!$B$20/12*(1+Inputs!$B$21)^INT((50-1)/12) | AZ5: =Inputs!$B$20/12*(1+Inputs!$B$21)^INT((51-1)/12) | BA5: =Inputs!$B$20/12*(1+Inputs!$B$21)^INT((52-1)/12)
A6: New Customer: SME | B6: 0 | C6: 0 | D6: 0 | E6: 0 | F6: 0 | G6: 0 | H6: 1 | I6: 1 | J6: 1 | K6: 1 | L6: 1 | M6: 1 | N6: 2 | O6: 2 | P6: 2 | Q6: 2 | R6: 2 | S6: 2 | T6: 2 | U6: 2 | V6: 2 | W6: 2 | X6: 2 | Y6: 2 | Z6: 3 | AA6: 3 | AB6: 3 | AC6: 3 | AD6: 3 | AE6: 3 | AF6: 3 | AG6: 3 | AH6: 3 | AI6: 3 | AJ6: 3 | AK6: 3 | AL6: 4 | AM6: 4 | AN6: 4 | AO6: 4 | AP6: 4 | AQ6: 4 | AR6: 4 | AS6: 4 | AT6: 4 | AU6: 4 | AV6: 4 | AW6: 4 | AX6: 4 | AY6: 4 | AZ6: 4 | BA6: 4
A7: New Customer: Mid-Company | B7: 0 | C7: 0 | D7: 0 | E7: 0 | F7: 0 | G7: 0 | H7: 0 | I7: 0 | J7: 0 | K7: 0 | L7: 0 | M7: 0 | N7: 1 | O7: 1 | P7: 1 | Q7: 1 | R7: 1 | S7: 1 | T7: 1 | U7: 1 | V7: 1 | W7: 1 | X7: 1 | Y7: 1 | Z7: 1 | AA7: 1 | AB7: 1 | AC7: 1 | AD7: 1 | AE7: 1 | AF7: 1 | AG7: 1 | AH7: 1 | AI7: 1 | AJ7: 1 | AK7: 1 | AL7: 2 | AM7: 2 | AN7: 2 | AO7: 2 | AP7: 2 | AQ7: 2 | AR7: 2 | AS7: 2 | AT7: 2 | AU7: 2 | AV7: 2 | AW7: 2 | AX7: 2 | AY7: 2 | AZ7: 2 | BA7: 2
A8: New Seats total | B8: =B6*Inputs!$B$23+B7*Inputs!$B$24 | C8: =C6*Inputs!$B$23+C7*Inputs!$B$24 | D8: =D6*Inputs!$B$23+D7*Inputs!$B$24 | E8: =E6*Inputs!$B$23+E7*Inputs!$B$24 | F8: =F6*Inputs!$B$23+F7*Inputs!$B$24 | G8: =G6*Inputs!$B$23+G7*Inputs!$B$24 | H8: =H6*Inputs!$B$23+H7*Inputs!$B$24 | I8: =I6*Inputs!$B$23+I7*Inputs!$B$24 | ... BA8: =BA6*Inputs!$B$23+BA7*Inputs!$B$24
A9: Churned Seats | B9: =0 | C9: =IF(B11>0,ROUND(B11*Inputs!$B$30/12,0),0) | D9: =IF(C11>0,ROUND(C11*Inputs!$B$30/12,0),0) | E9: =IF(D11>0,ROUND(D11*Inputs!$B$30/12,0),0) | F9: =IF(E11>0,ROUND(E11*Inputs!$B$30/12,0),0) | G9: =IF(F11>0,ROUND(F11*Inputs!$B$30/12,0),0) | H9: =IF(G11>0,ROUND(G11*Inputs!$B$30/12,0),0) | I9: =IF(H11>0,ROUND(H11*Inputs!$B$30/12,0),0) | J9: =IF(I11>0,ROUND(I11*Inputs!$B$30/12,0),0) | ... BA9: =IF(AZ11>0,ROUND(AZ11*Inputs!$B$30/12,0),0)
A10: Net New Seats | B10: =B8-B9 | C10: =C8-C9 | D10: =D8-D9 | E10: =E8-E9 | F10: =F8-F9 | G10: =G8-G9 | H10: =H8-H9 | I10: =I8-I9 | ... BA10: =BA8-BA9
A11: Total Active Seats | B11: =B10 | C11: =B11+C10 | D11: =C11+D10 | E11: =D11+E10 | F11: =E11+F10 | G11: =F11+G10 | H11: =G11+H10 | I11: =H11+I10 | J11: =I11+J10 | ... BA11: =AZ11+BA10
A12: Monthly Subscription Revenue (€) | B12: =B11*B5 | C12: =C11*C5 | D12: =D11*D5 | E12: =E11*E5 | F12: =F11*F5 | G12: =G11*G5 | H12: =H11*H5 | I12: =I11*I5 | ... BA12: =BA11*BA5
A13: Subscription ARR (€) | B13: =B12*12 | C13: =C12*12 | D13: =D12*12 | E13: =E12*12 | F13: =F12*12 | G13: =G12*12 | H13: =H12*12 | I13: =I12*12 | ... BA13: =BA12*12
A15: Neue Enterprise-Deals (Quartal) | B15: 0 | C15: 0 | D15: 0 | E15: 0 | F15: 0 | G15: 0 | H15: 0 | I15: 0 | J15: 0 | K15: 0 | L15: 0 | M15: 0 | N15: 0 | O15: 0 | P15: 0 | Q15: 0 | R15: 0 | S15: 0 | T15: 0 | U15: 0 | V15: 0 | W15: 0 | X15: 0 | Y15: 1 | Z15: 0 | AA15: 0 | AB15: 0 | AC15: 0 | AD15: 0 | AE15: 1 | AF15: 0 | AG15: 0 | AH15: 0 | AI15: 0 | AJ15: 0 | AK15: 1 | AL15: 0 | AM15: 0 | AN15: 0 | AO15: 0 | AP15: 0 | AQ15: 1 | AR15: 0 | AS15: 0 | AT15: 0 | AU15: 0 | AV15: 0 | AW15: 1 | AX15: 0 | AY15: 0 | AZ15: 0 | BA15: 0
A16: Churned Enterprise | B16: =0 | C16: =IF(B17>0,IF(MOD(2,12)=0,ROUND(B17*Inputs!$B$30,0),0),0) | D16: =IF(C17>0,IF(MOD(3,12)=0,ROUND(C17*Inputs!$B$30,0),0),0) | E16: =IF(D17>0,IF(MOD(4,12)=0,ROUND(D17*Inputs!$B$30,0),0),0) | F16: =IF(E17>0,IF(MOD(5,12)=0,ROUND(E17*Inputs!$B$30,0),0),0) | G16: =IF(F17>0,IF(MOD(6,12)=0,ROUND(F17*Inputs!$B$30,0),0),0) | H16: =IF(G17>0,IF(MOD(7,12)=0,ROUND(G17*Inputs!$B$30,0),0),0) | I16: =IF(H17>0,IF(MOD(8,12)=0,ROUND(H17*Inputs!$B$30,0),0),0) | J16: =IF(I17>0,IF(MOD(9,12)=0,ROUND(I17*Inputs!$B$30,0),0),0) | K16: =IF(J17>0,IF(MOD(10,12)=0,ROUND(J17*Inputs!$B$30,0),0),0) | L16: =IF(K17>0,IF(MOD(11,12)=0,ROUND(K17*Inputs!$B$30,0),0),0) | M16: =IF(L17>0,IF(MOD(12,12)=0,ROUND(L17*Inputs!$B$30,0),0),0) | N16: =IF(M17>0,IF(MOD(13,12)=0,ROUND(M17*Inputs!$B$30,0),0),0) | O16: =IF(N17>0,IF(MOD(14,12)=0,ROUND(N17*Inputs!$B$30,0),0),0) | P16: =IF(O17>0,IF(MOD(15,12)=0,ROUND(O17*Inputs!$B$30,0),0),0) | Q16: =IF(P17>0,IF(MOD(16,12)=0,ROUND(P17*Inputs!$B$30,0),0),0) | R16: =IF(Q17>0,IF(MOD(17,12)=0,ROUND(Q17*Inputs!$B$30,0),0),0) | S16: =IF(R17>0,IF(MOD(18,12)=0,ROUND(R17*Inputs!$B$30,0),0),0) | T16: =IF(S17>0,IF(MOD(19,12)=0,ROUND(S17*Inputs!$B$30,0),0),0) | U16: =IF(T17>0,IF(MOD(20,12)=0,ROUND(T17*Inputs!$B$30,0),0),0) | V16: =IF(U17>0,IF(MOD(21,12)=0,ROUND(U17*Inputs!$B$30,0),0),0) | W16: =IF(V17>0,IF(MOD(22,12)=0,ROUND(V17*Inputs!$B$30,0),0),0) | X16: =IF(W17>0,IF(MOD(23,12)=0,ROUND(W17*Inputs!$B$30,0),0),0) | Y16: =IF(X17>0,IF(MOD(24,12)=0,ROUND(X17*Inputs!$B$30,0),0),0) | Z16: =IF(Y17>0,IF(MOD(25,12)=0,ROUND(Y17*Inputs!$B$30,0),0),0) | AA16: =IF(Z17>0,IF(MOD(26,12)=0,ROUND(Z17*Inputs!$B$30,0),0),0) | AB16: =IF(AA17>0,IF(MOD(27,12)=0,ROUND(AA17*Inputs!$B$30,0),0),0) | AC16: =IF(AB17>0,IF(MOD(28,12)=0,ROUND(AB17*Inputs!$B$30,0),0),0) | AD16: =IF(AC17>0,IF(MOD(29,12)=0,ROUND(AC17*Inputs!$B$30,0),0),0) | AE16: =IF(AD17>0,IF(MOD(30,12)=0,ROUND(AD17*Inputs!$B$30,0),0),0) | AF16: =IF(AE17>0,IF(MOD(31,12)=0,ROUND(AE17*Inputs!$B$30,0),0),0) | AG16: =IF(AF17>0,IF(MOD(32,12)=0,ROUND(AF17*Inputs!$B$30,0),0),0) | AH16: =IF(AG17>0,IF(MOD(33,12)=0,ROUND(AG17*Inputs!$B$30,0),0),0) | AI16: =IF(AH17>0,IF(MOD(34,12)=0,ROUND(AH17*Inputs!$B$30,0),0),0) | AJ16: =IF(AI17>0,IF(MOD(35,12)=0,ROUND(AI17*Inputs!$B$30,0),0),0) | AK16: =IF(AJ17>0,IF(MOD(36,12)=0,ROUND(AJ17*Inputs!$B$30,0),0),0) | AL16: =IF(AK17>0,IF(MOD(37,12)=0,ROUND(AK17*Inputs!$B$30,0),0),0) | AM16: =IF(AL17>0,IF(MOD(38,12)=0,ROUND(AL17*Inputs!$B$30,0),0),0) | AN16: =IF(AM17>0,IF(MOD(39,12)=0,ROUND(AM17*Inputs!$B$30,0),0),0) | AO16: =IF(AN17>0,IF(MOD(40,12)=0,ROUND(AN17*Inputs!$B$30,0),0),0) | AP16: =IF(AO17>0,IF(MOD(41,12)=0,ROUND(AO17*Inputs!$B$30,0),0),0) | AQ16: =IF(AP17>0,IF(MOD(42,12)=0,ROUND(AP17*Inputs!$B$30,0),0),0) | AR16: =IF(AQ17>0,IF(MOD(43,12)=0,ROUND(AQ17*Inputs!$B$30,0),0),0) | AS16: =IF(AR17>0,IF(MOD(44,12)=0,ROUND(AR17*Inputs!$B$30,0),0),0) | AT16: =IF(AS17>0,IF(MOD(45,12)=0,ROUND(AS17*Inputs!$B$30,0),0),0) | AU16: =IF(AT17>0,IF(MOD(46,12)=0,ROUND(AT17*Inputs!$B$30,0),0),0) | AV16: =IF(AU17>0,IF(MOD(47,12)=0,ROUND(AU17*Inputs!$B$30,0),0),0) | AW16: =IF(AV17>0,IF(MOD(48,12)=0,ROUND(AV17*Inputs!$B$30,0),0),0) | AX16: =IF(AW17>0,IF(MOD(49,12)=0,ROUND(AW17*Inputs!$B$30,0),0),0) | AY16: =IF(AX17>0,IF(MOD(50,12)=0,ROUND(AX17*Inputs!$B$30,0),0),0) | AZ16: =IF(AY17>0,IF(MOD(51,12)=0,ROUND(AY17*Inputs!$B$30,0),0),0) | BA16: =IF(AZ17>0,IF(MOD(52,12)=0,ROUND(AZ17*Inputs!$B$30,0),0),0)
A17: Active Enterprise Contracts | B17: =B15-B16 | C17: =B17+C15-C16 | D17: =C17+D15-D16 | E17: =D17+E15-E16 | F17: =E17+F15-F16 | G17: =F17+G15-G16 | H17: =G17+H15-H16 | I17: =H17+I15-I16 | J17: =I17+J15-J16 | ... BA17: =AZ17+BA15-BA16
A18: Avg Enterprise ACV (€) | B18: =Inputs!$B$27*(1+Inputs!$B$21)^INT((1-1)/12) | C18: =Inputs!$B$27*(1+Inputs!$B$21)^INT((2-1)/12) | D18: =Inputs!$B$27*(1+Inputs!$B$21)^INT((3-1)/12) | E18: =Inputs!$B$27*(1+Inputs!$B$21)^INT((4-1)/12) | F18: =Inputs!$B$27*(1+Inputs!$B$21)^INT((5-1)/12) | G18: =Inputs!$B$27*(1+Inputs!$B$21)^INT((6-1)/12) | H18: =Inputs!$B$27*(1+Inputs!$B$21)^INT((7-1)/12) | I18: =Inputs!$B$27*(1+Inputs!$B$21)^INT((8-1)/12) | J18: =Inputs!$B$27*(1+Inputs!$B$21)^INT((9-1)/12) | K18: =Inputs!$B$27*(1+Inputs!$B$21)^INT((10-1)/12) | L18: =Inputs!$B$27*(1+Inputs!$B$21)^INT((11-1)/12) | M18: =Inputs!$B$27*(1+Inputs!$B$21)^INT((12-1)/12) | N18: =Inputs!$B$27*(1+Inputs!$B$21)^INT((13-1)/12) | O18: =Inputs!$B$27*(1+Inputs!$B$21)^INT((14-1)/12) | P18: =Inputs!$B$27*(1+Inputs!$B$21)^INT((15-1)/12) | Q18: =Inputs!$B$27*(1+Inputs!$B$21)^INT((16-1)/12) | R18: =Inputs!$B$27*(1+Inputs!$B$21)^INT((17-1)/12) | S18: =Inputs!$B$27*(1+Inputs!$B$21)^INT((18-1)/12) | T18: =Inputs!$B$27*(1+Inputs!$B$21)^INT((19-1)/12) | U18: =Inputs!$B$27*(1+Inputs!$B$21)^INT((20-1)/12) | V18: =Inputs!$B$27*(1+Inputs!$B$21)^INT((21-1)/12) | W18: =Inputs!$B$27*(1+Inputs!$B$21)^INT((22-1)/12) | X18: =Inputs!$B$27*(1+Inputs!$B$21)^INT((23-1)/12) | Y18: =Inputs!$B$27*(1+Inputs!$B$21)^INT((24-1)/12) | Z18: =Inputs!$B$27*(1+Inputs!$B$21)^INT((25-1)/12) | AA18: =Inputs!$B$27*(1+Inputs!$B$21)^INT((26-1)/12) | AB18: =Inputs!$B$27*(1+Inputs!$B$21)^INT((27-1)/12) | AC18: =Inputs!$B$27*(1+Inputs!$B$21)^INT((28-1)/12) | AD18: =Inputs!$B$27*(1+Inputs!$B$21)^INT((29-1)/12) | AE18: =Inputs!$B$27*(1+Inputs!$B$21)^INT((30-1)/12) | AF18: =Inputs!$B$27*(1+Inputs!$B$21)^INT((31-1)/12) | AG18: =Inputs!$B$27*(1+Inputs!$B$21)^INT((32-1)/12) | AH18: =Inputs!$B$27*(1+Inputs!$B$21)^INT((33-1)/12) | AI18: =Inputs!$B$27*(1+Inputs!$B$21)^INT((34-1)/12) | AJ18: =Inputs!$B$27*(1+Inputs!$B$21)^INT((35-1)/12) | AK18: =Inputs!$B$27*(1+Inputs!$B$21)^INT((36-1)/12) | AL18: =Inputs!$B$27*(1+Inputs!$B$21)^INT((37-1)/12) | AM18: =Inputs!$B$27*(1+Inputs!$B$21)^INT((38-1)/12) | AN18: =Inputs!$B$27*(1+Inputs!$B$21)^INT((39-1)/12) | AO18: =Inputs!$B$27*(1+Inputs!$B$21)^INT((40-1)/12) | AP18: =Inputs!$B$27*(1+Inputs!$B$21)^INT((41-1)/12) | AQ18: =Inputs!$B$27*(1+Inputs!$B$21)^INT((42-1)/12) | AR18: =Inputs!$B$27*(1+Inputs!$B$21)^INT((43-1)/12) | AS18: =Inputs!$B$27*(1+Inputs!$B$21)^INT((44-1)/12) | AT18: =Inputs!$B$27*(1+Inputs!$B$21)^INT((45-1)/12) | AU18: =Inputs!$B$27*(1+Inputs!$B$21)^INT((46-1)/12) | AV18: =Inputs!$B$27*(1+Inputs!$B$21)^INT((47-1)/12) | AW18: =Inputs!$B$27*(1+Inputs!$B$21)^INT((48-1)/12) | AX18: =Inputs!$B$27*(1+Inputs!$B$21)^INT((49-1)/12) | AY18: =Inputs!$B$27*(1+Inputs!$B$21)^INT((50-1)/12) | AZ18: =Inputs!$B$27*(1+Inputs!$B$21)^INT((51-1)/12) | BA18: =Inputs!$B$27*(1+Inputs!$B$21)^INT((52-1)/12)
A19: Enterprise Monthly Revenue (€) | B19: =B17*B18/12 | C19: =C17*C18/12 | D19: =D17*D18/12 | E19: =E17*E18/12 | F19: =F17*F18/12 | G19: =G17*G18/12 | H19: =H17*H18/12 | I19: =I17*I18/12 | ... BA19: =BA17*BA18/12
A20: ── RECURRING REVENUE (SaaS-Metriken, ohne Implementation-Support) ──
A21: MRR – Monthly Recurring Revenue (Lizenzen) | B21: =B12+B19 | C21: =C12+C19 | D21: =D12+D19 | E21: =E12+E19 | F21: =F12+F19 | G21: =G12+G19 | H21: =H12+H19 | I21: =I12+I19 | ... BA21: =BA12+BA19
A22: ARR – Annual Recurring Revenue (Lizenzen = MRR × 12) | B22: =B21*12 | C22: =C21*12 | D22: =D21*12 | E22: =E21*12 | F22: =F21*12 | G22: =G21*12 | H22: =H21*12 | I22: =I21*12 | ... BA22: =BA21*12
A23: Total Monthly Revenue (Lizenzen + Implementation-Support) | B23: =B21+B32 | C23: =C21+C32 | D23: =D21+D32 | E23: =E21+E32 | F23: =F21+F32 | G23: =G21+G32 | H23: =H21+H32 | I23: =I21+I32 | ... BA23: =BA21+BA32
A24: ARR Growth % (MoM) | B24: ="" | C24: =IFERROR(C22/B22-1,"") | D24: =IFERROR(D22/C22-1,"") | E24: =IFERROR(E22/D22-1,"") | F24: =IFERROR(F22/E22-1,"") | G24: =IFERROR(G22/F22-1,"") | H24: =IFERROR(H22/G22-1,"") | I24: =IFERROR(I22/H22-1,"") | J24: =IFERROR(J22/I22-1,"") | ... BA24: =IFERROR(BA22/AZ22-1,"")
A25: Net Revenue Retention % | B25: =Inputs!$B$30 | C25: =Inputs!$B$30 | D25: =Inputs!$B$30 | E25: =Inputs!$B$30 | F25: =Inputs!$B$30 | G25: =Inputs!$B$30 | H25: =Inputs!$B$30 | I25: =Inputs!$B$30 | ... BA25: =Inputs!$B$30
A26: Gross New ARR (€) | B26: =B8*B5*12+B15*B18 | C26: =C8*C5*12+C15*C18 | D26: =D8*D5*12+D15*D18 | E26: =E8*E5*12+E15*E18 | F26: =F8*F5*12+F15*F18 | G26: =G8*G5*12+G15*G18 | H26: =H8*H5*12+H15*H18 | I26: =I8*I5*12+I15*I18 | ... BA26: =BA8*BA5*12+BA15*BA18
A28: ── Implementation-Support REVENUE ──
A29: Active Subscription Customers | B29: =IF(B11>0, MAX(1, ROUND(B11/Inputs!$B$23, 0)), 0) | C29: =IF(C11>0, MAX(1, ROUND(C11/Inputs!$B$23, 0)), 0) | D29: =IF(D11>0, MAX(1, ROUND(D11/Inputs!$B$23, 0)), 0) | E29: =IF(E11>0, MAX(1, ROUND(E11/Inputs!$B$23, 0)), 0) | F29: =IF(F11>0, MAX(1, ROUND(F11/Inputs!$B$23, 0)), 0) | G29: =IF(G11>0, MAX(1, ROUND(G11/Inputs!$B$23, 0)), 0) | H29: =IF(H11>0, MAX(1, ROUND(H11/Inputs!$B$23, 0)), 0) | I29: =IF(I11>0, MAX(1, ROUND(I11/Inputs!$B$23, 0)), 0) | ... BA29: =IF(BA11>0, MAX(1, ROUND(BA11/Inputs!$B$23, 0)), 0)
A30: Total Active Customers (inkl. Enterprise) | B30: =B29+B17 | C30: =C29+C17 | D30: =D29+D17 | E30: =E29+E17 | F30: =F29+F17 | G30: =G29+G17 | H30: =H29+H17 | I30: =I29+I17 | ... BA30: =BA29+BA17
A31: Implementation-Support-Tage/Monat [ab Startmonat; Kunden × Wskt. × Tage/Einsatz] | B31: =IF(1>=Inputs!$B$133,B30*Inputs!$B$131*Inputs!$B$132,0) | C31: =IF(2>=Inputs!$B$133,C30*Inputs!$B$131*Inputs!$B$132,0) | D31: =IF(3>=Inputs!$B$133,D30*Inputs!$B$131*Inputs!$B$132,0) | E31: =IF(4>=Inputs!$B$133,E30*Inputs!$B$131*Inputs!$B$132,0) | F31: =IF(5>=Inputs!$B$133,F30*Inputs!$B$131*Inputs!$B$132,0) | G31: =IF(6>=Inputs!$B$133,G30*Inputs!$B$131*Inputs!$B$132,0) | H31: =IF(7>=Inputs!$B$133,H30*Inputs!$B$131*Inputs!$B$132,0) | I31: =IF(8>=Inputs!$B$133,I30*Inputs!$B$131*Inputs!$B$132,0) | J31: =IF(9>=Inputs!$B$133,J30*Inputs!$B$131*Inputs!$B$132,0) | K31: =IF(10>=Inputs!$B$133,K30*Inputs!$B$131*Inputs!$B$132,0) | L31: =IF(11>=Inputs!$B$133,L30*Inputs!$B$131*Inputs!$B$132,0) | M31: =IF(12>=Inputs!$B$133,M30*Inputs!$B$131*Inputs!$B$132,0) | N31: =IF(13>=Inputs!$B$133,N30*Inputs!$B$131*Inputs!$B$132,0) | O31: =IF(14>=Inputs!$B$133,O30*Inputs!$B$131*Inputs!$B$132,0) | P31: =IF(15>=Inputs!$B$133,P30*Inputs!$B$131*Inputs!$B$132,0) | Q31: =IF(16>=Inputs!$B$133,Q30*Inputs!$B$131*Inputs!$B$132,0) | R31: =IF(17>=Inputs!$B$133,R30*Inputs!$B$131*Inputs!$B$132,0) | S31: =IF(18>=Inputs!$B$133,S30*Inputs!$B$131*Inputs!$B$132,0) | T31: =IF(19>=Inputs!$B$133,T30*Inputs!$B$131*Inputs!$B$132,0) | U31: =IF(20>=Inputs!$B$133,U30*Inputs!$B$131*Inputs!$B$132,0) | V31: =IF(21>=Inputs!$B$133,V30*Inputs!$B$131*Inputs!$B$132,0) | W31: =IF(22>=Inputs!$B$133,W30*Inputs!$B$131*Inputs!$B$132,0) | X31: =IF(23>=Inputs!$B$133,X30*Inputs!$B$131*Inputs!$B$132,0) | Y31: =IF(24>=Inputs!$B$133,Y30*Inputs!$B$131*Inputs!$B$132,0) | Z31: =IF(25>=Inputs!$B$133,Z30*Inputs!$B$131*Inputs!$B$132,0) | AA31: =IF(26>=Inputs!$B$133,AA30*Inputs!$B$131*Inputs!$B$132,0) | AB31: =IF(27>=Inputs!$B$133,AB30*Inputs!$B$131*Inputs!$B$132,0) | AC31: =IF(28>=Inputs!$B$133,AC30*Inputs!$B$131*Inputs!$B$132,0) | AD31: =IF(29>=Inputs!$B$133,AD30*Inputs!$B$131*Inputs!$B$132,0) | AE31: =IF(30>=Inputs!$B$133,AE30*Inputs!$B$131*Inputs!$B$132,0) | AF31: =IF(31>=Inputs!$B$133,AF30*Inputs!$B$131*Inputs!$B$132,0) | AG31: =IF(32>=Inputs!$B$133,AG30*Inputs!$B$131*Inputs!$B$132,0) | AH31: =IF(33>=Inputs!$B$133,AH30*Inputs!$B$131*Inputs!$B$132,0) | AI31: =IF(34>=Inputs!$B$133,AI30*Inputs!$B$131*Inputs!$B$132,0) | AJ31: =IF(35>=Inputs!$B$133,AJ30*Inputs!$B$131*Inputs!$B$132,0) | AK31: =IF(36>=Inputs!$B$133,AK30*Inputs!$B$131*Inputs!$B$132,0) | AL31: =IF(37>=Inputs!$B$133,AL30*Inputs!$B$131*Inputs!$B$132,0) | AM31: =IF(38>=Inputs!$B$133,AM30*Inputs!$B$131*Inputs!$B$132,0) | AN31: =IF(39>=Inputs!$B$133,AN30*Inputs!$B$131*Inputs!$B$132,0) | AO31: =IF(40>=Inputs!$B$133,AO30*Inputs!$B$131*Inputs!$B$132,0) | AP31: =IF(41>=Inputs!$B$133,AP30*Inputs!$B$131*Inputs!$B$132,0) | AQ31: =IF(42>=Inputs!$B$133,AQ30*Inputs!$B$131*Inputs!$B$132,0) | AR31: =IF(43>=Inputs!$B$133,AR30*Inputs!$B$131*Inputs!$B$132,0) | AS31: =IF(44>=Inputs!$B$133,AS30*Inputs!$B$131*Inputs!$B$132,0) | AT31: =IF(45>=Inputs!$B$133,AT30*Inputs!$B$131*Inputs!$B$132,0) | AU31: =IF(46>=Inputs!$B$133,AU30*Inputs!$B$131*Inputs!$B$132,0) | AV31: =IF(47>=Inputs!$B$133,AV30*Inputs!$B$131*Inputs!$B$132,0) | AW31: =IF(48>=Inputs!$B$133,AW30*Inputs!$B$131*Inputs!$B$132,0) | AX31: =IF(49>=Inputs!$B$133,AX30*Inputs!$B$131*Inputs!$B$132,0) | AY31: =IF(50>=Inputs!$B$133,AY30*Inputs!$B$131*Inputs!$B$132,0) | AZ31: =IF(51>=Inputs!$B$133,AZ30*Inputs!$B$131*Inputs!$B$132,0) | BA31: =IF(52>=Inputs!$B$133,BA30*Inputs!$B$131*Inputs!$B$132,0)
A32: Implementation-Support Revenue (€/Monat) [= Tage/Mo × Tagessatz] | B32: =B31*Inputs!$B$130 | C32: =C31*Inputs!$B$130 | D32: =D31*Inputs!$B$130 | E32: =E31*Inputs!$B$130 | F32: =F31*Inputs!$B$130 | G32: =G31*Inputs!$B$130 | H32: =H31*Inputs!$B$130 | I32: =I31*Inputs!$B$130 | ... BA32: =BA31*Inputs!$B$130
A34: ℹ Hinweis MRR/ARR vs. Total Revenue: MRR/ARR (Z19/20) = ausschließlich wiederkehrende Lizenzumsätze (Subscription Seats + Enterprise-Verträge). Implementation-Support ist projektbezogen, nicht-wiederkehrend → kein Bestandteil von MRR/ARR (SaaS-Standard: SaaStr/OpenView/a16z). Total Monthly Revenue (Z21) = MRR + Implementation-Support → fließt in P&L TOTAL REVENUE.

Sheet Costs
A1: KOSTENDETAILS
B2: 46113 | C2: 46143 | D2: 46174 | E2: 46204 | F2: 46235 | G2: 46266 | H2: 46296 | I2: 46327 | J2: 46357 | K2: 46388 | L2: 46419 | M2: 46447 | N2: 46478 | O2: 46508 | P2: 46539 | Q2: 46569 | R2: 46600 | S2: 46631 | T2: 46661 | U2: 46692 | V2: 46722 | W2: 46753 | X2: 46784 | Y2: 46813 | Z2: 46844 | AA2: 46874 | AB2: 46905 | AC2: 46935 | AD2: 46966 | AE2: 46997 | AF2: 47027 | AG2: 47058 | AH2: 47088 | AI2: 47119 | AJ2: 47150 | AK2: 47178 | AL2: 47209 | AM2: 47239 | AN2: 47270 | AO2: 47300 | AP2: 47331 | AQ2: 47362 | AR2: 47392 | AS2: 47423 | AT2: 47453 | AU2: 47484 | AV2: 47515 | AW2: 47543 | AX2: 47574 | AY2: 47604 | AZ2: 47635 | BA2: 47665
A3: Startup-Phasen | B3: Ideation | C3: Ideation | D3: Ideation | E3: Ideation | F3: Pre-Seed | G3: Pre-Seed | H3: Pre-Seed | I3: Pre-Seed | J3: Pre-Seed | K3: Pre-Seed | L3: Pre-Seed | M3: Pre-Seed | N3: Pre-Seed | O3: Pre-Seed | P3: Pre-Seed | Q3: Pre-Seed | R3: Seed | S3: Seed | T3: Seed | U3: Seed | V3: Seed | W3: Seed | X3: Seed | Y3: Seed | Z3: Seed | AA3: Seed | AB3: Seed | AC3: Seed | AD3: Series A | AE3: Series A | AF3: Series A | AG3: Series A | AH3: Series A | AI3: Series A | AJ3: Series A | AK3: Series A | AL3: Series A | AM3: Series A | AN3: Series A | AO3: Series A | AP3: Series B | AQ3: Series B | AR3: Series B | AS3: Series B | AT3: Series B | AU3: Series B | AV3: Series B | AW3: Series B | AX3: Series B | AY3: Series B | AZ3: Series B | BA3: Series B
A4: Kostenposition | B4: M1 | C4: M2 | D4: M3 | E4: M4 | F4: M5 | G4: M6 | H4: M7 | I4: M8 | J4: M9 | K4: M10 | L4: M11 | M4: M12 | N4: M13 | O4: M14 | P4: M15 | Q4: M16 | R4: M17 | S4: M18 | T4: M19 | U4: M20 | V4: M21 | W4: M22 | X4: M23 | Y4: M24 | Z4: M25 | AA4: M26 | AB4: M27 | AC4: M28 | AD4: M29 | AE4: M30 | AF4: M31 | AG4: M32 | AH4: M33 | AI4: M34 | AJ4: M35 | AK4: M36 | AL4: M37 | AM4: M38 | AN4: M39 | AO4: M40 | AP4: M41 | AQ4: M42 | AR4: M43 | AS4: M44 | AT4: M45 | AU4: M46 | AV4: M47 | AW4: M48 | AX4: M49 | AY4: M50 | AZ4: M51 | BA4: M52
A5: HEADCOUNT PLAN
A6: Executives (CEO, CTO, CCO) | B6: 3 | C6: 3 | D6: 3 | E6: 3 | F6: 3 | G6: 3 | H6: 3 | I6: 3 | J6: 3 | K6: 3 | L6: 3 | M6: 3 | N6: 3 | O6: 3 | P6: 3 | Q6: 3 | R6: 3 | S6: 3 | T6: 3 | U6: 3 | V6: 3 | W6: 3 | X6: 3 | Y6: 3 | Z6: 3 | AA6: 3 | AB6: 3 | AC6: 3 | AD6: 3 | AE6: 3 | AF6: 3 | AG6: 3 | AH6: 3 | AI6: 3 | AJ6: 3 | AK6: 3 | AL6: 3 | AM6: 3 | AN6: 3 | AO6: 3 | AP6: 3 | AQ6: 3 | AR6: 3 | AS6: 3 | AT6: 3 | AU6: 3 | AV6: 3 | AW6: 3 | AX6: 3 | AY6: 3 | AZ6: 3 | BA6: 3
A7: 1. Software Developer | B7: =IF(COLUMNS($B$7:B7) >= Inputs!$E$52, 1, 0) | C7: =IF(COLUMNS($B$7:C7) >= Inputs!$E$52, 1, 0) | D7: =IF(COLUMNS($B$7:D7) >= Inputs!$E$52, 1, 0) | E7: =IF(COLUMNS($B$7:E7) >= Inputs!$E$52, 1, 0) | F7: =IF(COLUMNS($B$7:F7) >= Inputs!$E$52, 1, 0) | G7: =IF(COLUMNS($B$7:G7) >= Inputs!$E$52, 1, 0) | H7: =IF(COLUMNS($B$7:H7) >= Inputs!$E$52, 1, 0) | I7: =IF(COLUMNS($B$7:I7) >= Inputs!$E$52, 1, 0) | ... BA7: =IF(COLUMNS($B$7:BA7) >= Inputs!$E$52, 1, 0)
A8: 2. Software Developer | B8: =IF(COLUMNS($B$8:B8)>=Inputs!$E$53,1,0) | C8: =IF(COLUMNS($B$8:C8)>=Inputs!$E$53,1,0) | D8: =IF(COLUMNS($B$8:D8)>=Inputs!$E$53,1,0) | E8: =IF(COLUMNS($B$8:E8)>=Inputs!$E$53,1,0) | F8: =IF(COLUMNS($B$8:F8)>=Inputs!$E$53,1,0) | G8: =IF(COLUMNS($B$8:G8)>=Inputs!$E$53,1,0) | H8: =IF(COLUMNS($B$8:H8)>=Inputs!$E$53,1,0) | I8: =IF(COLUMNS($B$8:I8)>=Inputs!$E$53,1,0) | ... BA8: =IF(COLUMNS($B$8:BA8)>=Inputs!$E$53,1,0)
A9: 1. Junior Software Developer | B9: =IF(COLUMNS($B$9:B9) >= Inputs!$E$54, 1, 0) | C9: =IF(COLUMNS($B$9:C9) >= Inputs!$E$54, 1, 0) | D9: =IF(COLUMNS($B$9:D9) >= Inputs!$E$54, 1, 0) | E9: =IF(COLUMNS($B$9:E9) >= Inputs!$E$54, 1, 0) | F9: =IF(COLUMNS($B$9:F9) >= Inputs!$E$54, 1, 0) | G9: =IF(COLUMNS($B$9:G9) >= Inputs!$E$54, 1, 0) | H9: =IF(COLUMNS($B$9:H9) >= Inputs!$E$54, 1, 0) | I9: =IF(COLUMNS($B$9:I9) >= Inputs!$E$54, 1, 0) | ... BA9: =IF(COLUMNS($B$9:BA9) >= Inputs!$E$54, 1, 0)
A10: 1. ML/AI Engineer | B10: =IF(COLUMNS($B$10:B10) >= Inputs!$E$55, 1, 0) | C10: =IF(COLUMNS($B$10:C10) >= Inputs!$E$55, 1, 0) | D10: =IF(COLUMNS($B$10:D10) >= Inputs!$E$55, 1, 0) | E10: =IF(COLUMNS($B$10:E10) >= Inputs!$E$55, 1, 0) | F10: =IF(COLUMNS($B$10:F10) >= Inputs!$E$55, 1, 0) | G10: =IF(COLUMNS($B$10:G10) >= Inputs!$E$55, 1, 0) | H10: =IF(COLUMNS($B$10:H10) >= Inputs!$E$55, 1, 0) | I10: =IF(COLUMNS($B$10:I10) >= Inputs!$E$55, 1, 0) | ... BA10: =IF(COLUMNS($B$10:BA10) >= Inputs!$E$55, 1, 0)
A11: 1. Mechanical Engineer | B11: =IF(COLUMNS($B$11:B11)>=Inputs!$E$56,1,0) | C11: =IF(COLUMNS($B$11:C11)>=Inputs!$E$56,1,0) | D11: =IF(COLUMNS($B$11:D11)>=Inputs!$E$56,1,0) | E11: =IF(COLUMNS($B$11:E11)>=Inputs!$E$56,1,0) | F11: =IF(COLUMNS($B$11:F11)>=Inputs!$E$56,1,0) | G11: =IF(COLUMNS($B$11:G11)>=Inputs!$E$56,1,0) | H11: =IF(COLUMNS($B$11:H11)>=Inputs!$E$56,1,0) | I11: =IF(COLUMNS($B$11:I11)>=Inputs!$E$56,1,0) | ... BA11: =IF(COLUMNS($B$11:BA11)>=Inputs!$E$56,1,0)
A12: 1. Site Reliability Mgr | B12: =IF(COLUMNS($B$11:B12)>=Inputs!$E$57,1,0) | C12: =IF(COLUMNS($B$11:C12)>=Inputs!$E$57,1,0) | D12: =IF(COLUMNS($B$11:D12)>=Inputs!$E$57,1,0) | E12: =IF(COLUMNS($B$11:E12)>=Inputs!$E$57,1,0) | F12: =IF(COLUMNS($B$11:F12)>=Inputs!$E$57,1,0) | G12: =IF(COLUMNS($B$11:G12)>=Inputs!$E$57,1,0) | H12: =IF(COLUMNS($B$11:H12)>=Inputs!$E$57,1,0) | I12: =IF(COLUMNS($B$11:I12)>=Inputs!$E$57,1,0) | ... BA12: =IF(COLUMNS($B$11:BA12)>=Inputs!$E$57,1,0)
A13: 1. UX/UI Designer | B13: =IF(COLUMNS($B$13:B13)>=Inputs!$E$58,1,0) | C13: =IF(COLUMNS($B$13:C13)>=Inputs!$E$58,1,0) | D13: =IF(COLUMNS($B$13:D13)>=Inputs!$E$58,1,0) | E13: =IF(COLUMNS($B$13:E13)>=Inputs!$E$58,1,0) | F13: =IF(COLUMNS($B$13:F13)>=Inputs!$E$58,1,0) | G13: =IF(COLUMNS($B$13:G13)>=Inputs!$E$58,1,0) | H13: =IF(COLUMNS($B$13:H13)>=Inputs!$E$58,1,0) | I13: =IF(COLUMNS($B$13:I13)>=Inputs!$E$58,1,0) | ... BA13: =IF(COLUMNS($B$13:BA13)>=Inputs!$E$58,1,0)
A14: 1. Customer Key Account | B14: =IF(COLUMNS($B$14:B14)>=Inputs!$E$59,1,0) | C14: =IF(COLUMNS($B$14:C14)>=Inputs!$E$59,1,0) | D14: =IF(COLUMNS($B$14:D14)>=Inputs!$E$59,1,0) | E14: =IF(COLUMNS($B$14:E14)>=Inputs!$E$59,1,0) | F14: =IF(COLUMNS($B$14:F14)>=Inputs!$E$59,1,0) | G14: =IF(COLUMNS($B$14:G14)>=Inputs!$E$59,1,0) | H14: =IF(COLUMNS($B$14:H14)>=Inputs!$E$59,1,0) | I14: =IF(COLUMNS($B$14:I14)>=Inputs!$E$59,1,0) | ... BA14: =IF(COLUMNS($B$14:BA14)>=Inputs!$E$59,1,0)
A15: 2. Customer Key Account | B15: =IF(COLUMNS($B$15:B15)>=Inputs!$E$60,1,0) | C15: =IF(COLUMNS($B$15:C15)>=Inputs!$E$60,1,0) | D15: =IF(COLUMNS($B$15:D15)>=Inputs!$E$60,1,0) | E15: =IF(COLUMNS($B$15:E15)>=Inputs!$E$60,1,0) | F15: =IF(COLUMNS($B$15:F15)>=Inputs!$E$60,1,0) | G15: =IF(COLUMNS($B$15:G15)>=Inputs!$E$60,1,0) | H15: =IF(COLUMNS($B$15:H15)>=Inputs!$E$60,1,0) | I15: =IF(COLUMNS($B$15:I15)>=Inputs!$E$60,1,0) | ... BA15: =IF(COLUMNS($B$15:BA15)>=Inputs!$E$60,1,0)
A16: 3. Customer Key Account | B16: =IF(COLUMNS($B$16:B16)>=Inputs!$E$61,1,0) | C16: =IF(COLUMNS($B$16:C16)>=Inputs!$E$61,1,0) | D16: =IF(COLUMNS($B$16:D16)>=Inputs!$E$61,1,0) | E16: =IF(COLUMNS($B$16:E16)>=Inputs!$E$61,1,0) | F16: =IF(COLUMNS($B$16:F16)>=Inputs!$E$61,1,0) | G16: =IF(COLUMNS($B$16:G16)>=Inputs!$E$61,1,0) | H16: =IF(COLUMNS($B$16:H16)>=Inputs!$E$61,1,0) | I16: =IF(COLUMNS($B$16:I16)>=Inputs!$E$61,1,0) | ... BA16: =IF(COLUMNS($B$16:BA16)>=Inputs!$E$61,1,0)
A17: 1. Marketing Assistant | B17: =IF(COLUMNS($B$17:B17)>=Inputs!$E$62,1,0) | C17: =IF(COLUMNS($B$17:C17)>=Inputs!$E$62,1,0) | D17: =IF(COLUMNS($B$17:D17)>=Inputs!$E$62,1,0) | E17: =IF(COLUMNS($B$17:E17)>=Inputs!$E$62,1,0) | F17: =IF(COLUMNS($B$17:F17)>=Inputs!$E$62,1,0) | G17: =IF(COLUMNS($B$17:G17)>=Inputs!$E$62,1,0) | H17: =IF(COLUMNS($B$17:H17)>=Inputs!$E$62,1,0) | I17: =IF(COLUMNS($B$17:I17)>=Inputs!$E$62,1,0) | ... BA17: =IF(COLUMNS($B$17:BA17)>=Inputs!$E$62,1,0)
A18: 2. Marketing Assistant | B18: =IF(COLUMNS($B$18:B18)>=Inputs!$E$63,1,0) | C18: =IF(COLUMNS($B$18:C18)>=Inputs!$E$63,1,0) | D18: =IF(COLUMNS($B$18:D18)>=Inputs!$E$63,1,0) | E18: =IF(COLUMNS($B$18:E18)>=Inputs!$E$63,1,0) | F18: =IF(COLUMNS($B$18:F18)>=Inputs!$E$63,1,0) | G18: =IF(COLUMNS($B$18:G18)>=Inputs!$E$63,1,0) | H18: =IF(COLUMNS($B$18:H18)>=Inputs!$E$63,1,0) | I18: =IF(COLUMNS($B$18:I18)>=Inputs!$E$63,1,0) | ... BA18: =IF(COLUMNS($B$18:BA18)>=Inputs!$E$63,1,0)
A19: 1. Marketing Manager | B19: =IF(COLUMNS($B$19:B19)>=Inputs!$E$64,1,0) | C19: =IF(COLUMNS($B$19:C19)>=Inputs!$E$64,1,0) | D19: =IF(COLUMNS($B$19:D19)>=Inputs!$E$64,1,0) | E19: =IF(COLUMNS($B$19:E19)>=Inputs!$E$64,1,0) | F19: =IF(COLUMNS($B$19:F19)>=Inputs!$E$64,1,0) | G19: =IF(COLUMNS($B$19:G19)>=Inputs!$E$64,1,0) | H19: =IF(COLUMNS($B$19:H19)>=Inputs!$E$64,1,0) | I19: =IF(COLUMNS($B$19:I19)>=Inputs!$E$64,1,0) | ... BA19: =IF(COLUMNS($B$19:BA19)>=Inputs!$E$64,1,0)
A20: 1. Office Manager | B20: =IF(COLUMNS($B$20:B20)>=Inputs!$E$65,1,0) | C20: =IF(COLUMNS($B$20:C20)>=Inputs!$E$65,1,0) | D20: =IF(COLUMNS($B$20:D20)>=Inputs!$E$65,1,0) | E20: =IF(COLUMNS($B$20:E20)>=Inputs!$E$65,1,0) | F20: =IF(COLUMNS($B$20:F20)>=Inputs!$E$65,1,0) | G20: =IF(COLUMNS($B$20:G20)>=Inputs!$E$65,1,0) | H20: =IF(COLUMNS($B$20:H20)>=Inputs!$E$65,1,0) | I20: =IF(COLUMNS($B$20:I20)>=Inputs!$E$65,1,0) | ... BA20: =IF(COLUMNS($B$20:BA20)>=Inputs!$E$65,1,0)
A21: 1. Customer Success | B21: =IF(COLUMNS($B$21:B21)>=Inputs!$E$66,1,0) | C21: =IF(COLUMNS($B$21:C21)>=Inputs!$E$66,1,0) | D21: =IF(COLUMNS($B$21:D21)>=Inputs!$E$66,1,0) | E21: =IF(COLUMNS($B$21:E21)>=Inputs!$E$66,1,0) | F21: =IF(COLUMNS($B$21:F21)>=Inputs!$E$66,1,0) | G21: =IF(COLUMNS($B$21:G21)>=Inputs!$E$66,1,0) | H21: =IF(COLUMNS($B$21:H21)>=Inputs!$E$66,1,0) | I21: =IF(COLUMNS($B$21:I21)>=Inputs!$E$66,1,0) | ... BA21: =IF(COLUMNS($B$21:BA21)>=Inputs!$E$66,1,0)
A22: 1. Finance Manager | B22: =IF(COLUMNS($B$22:B22)>=Inputs!$E$67,1,0) | C22: =IF(COLUMNS($B$22:C22)>=Inputs!$E$67,1,0) | D22: =IF(COLUMNS($B$22:D22)>=Inputs!$E$67,1,0) | E22: =IF(COLUMNS($B$22:E22)>=Inputs!$E$67,1,0) | F22: =IF(COLUMNS($B$22:F22)>=Inputs!$E$67,1,0) | G22: =IF(COLUMNS($B$22:G22)>=Inputs!$E$67,1,0) | H22: =IF(COLUMNS($B$22:H22)>=Inputs!$E$67,1,0) | I22: =IF(COLUMNS($B$22:I22)>=Inputs!$E$67,1,0) | ... BA22: =IF(COLUMNS($B$22:BA22)>=Inputs!$E$67,1,0)
A23: TOTAL HEADCOUNT | B23: =SUM(B6:B22) | C23: =SUM(C6:C22) | D23: =SUM(D6:D22) | E23: =SUM(E6:E22) | F23: =SUM(F6:F22) | G23: =SUM(G6:G22) | H23: =SUM(H6:H22) | I23: =SUM(I6:I22) | ... BA23: =SUM(BA6:BA22)
A25: GEHÄLTER & PERSONALKOSTEN
A26: CEO Gehalt | B26: =B6/3 * (Inputs!$B$33 / 12) * (1 + Inputs!$B$48)^INT((COLUMNS($B$26:B26)-1) / 12) | C26: =C6/3 * (Inputs!$B$33 / 12) * (1 + Inputs!$B$48)^INT((COLUMNS($B$26:C26)-1) / 12) | D26: =D6/3 * (Inputs!$B$33 / 12) * (1 + Inputs!$B$48)^INT((COLUMNS($B$26:D26)-1) / 12) | E26: =E6/3 * (Inputs!$B$33 / 12) * (1 + Inputs!$B$48)^INT((COLUMNS($B$26:E26)-1) / 12) | F26: =F6/3 * (Inputs!$B$33 / 12) * (1 + Inputs!$B$48)^INT((COLUMNS($B$26:F26)-1) / 12) | G26: =G6/3 * (Inputs!$B$33 / 12) * (1 + Inputs!$B$48)^INT((COLUMNS($B$26:G26)-1) / 12) | H26: =H6/3 * (Inputs!$B$33 / 12) * (1 + Inputs!$B$48)^INT((COLUMNS($B$26:H26)-1) / 12) | I26: =I6/3 * (Inputs!$B$33 / 12) * (1 + Inputs!$B$48)^INT((COLUMNS($B$26:I26)-1) / 12) | ... BA26: =BA6/3 * (Inputs!$B$33 / 12) * (1 + Inputs!$B$48)^INT((COLUMNS($B$26:BA26)-1) / 12)
A27: CTO Gehalt | B27: =B6/3 * (Inputs!$B$34 / 12) * (1 + Inputs!$B$48)^INT((COLUMNS($B$27:B27)-1) / 12) | C27: =C6/3 * (Inputs!$B$34 / 12) * (1 + Inputs!$B$48)^INT((COLUMNS($B$27:C27)-1) / 12) | D27: =D6/3 * (Inputs!$B$34 / 12) * (1 + Inputs!$B$48)^INT((COLUMNS($B$27:D27)-1) / 12) | E27: =E6/3 * (Inputs!$B$34 / 12) * (1 + Inputs!$B$48)^INT((COLUMNS($B$27:E27)-1) / 12) | F27: =F6/3 * (Inputs!$B$34 / 12) * (1 + Inputs!$B$48)^INT((COLUMNS($B$27:F27)-1) / 12) | G27: =G6/3 * (Inputs!$B$34 / 12) * (1 + Inputs!$B$48)^INT((COLUMNS($B$27:G27)-1) / 12) | H27: =H6/3 * (Inputs!$B$34 / 12) * (1 + Inputs!$B$48)^INT((COLUMNS($B$27:H27)-1) / 12) | I27: =I6/3 * (Inputs!$B$34 / 12) * (1 + Inputs!$B$48)^INT((COLUMNS($B$27:I27)-1) / 12) | ... BA27: =BA6/3 * (Inputs!$B$34 / 12) * (1 + Inputs!$B$48)^INT((COLUMNS($B$27:BA27)-1) / 12)
A28: CCO Gehalt | B28: =B6/3 * (Inputs!$B$35 / 12) * (1 + Inputs!$B$48)^INT((COLUMNS($B$28:B28)-1) / 12) | C28: =C6/3 * (Inputs!$B$35 / 12) * (1 + Inputs!$B$48)^INT((COLUMNS($B$28:C28)-1) / 12) | D28: =D6/3 * (Inputs!$B$35 / 12) * (1 + Inputs!$B$48)^INT((COLUMNS($B$28:D28)-1) / 12) | E28: =E6/3 * (Inputs!$B$35 / 12) * (1 + Inputs!$B$48)^INT((COLUMNS($B$28:E28)-1) / 12) | F28: =F6/3 * (Inputs!$B$35 / 12) * (1 + Inputs!$B$48)^INT((COLUMNS($B$28:F28)-1) / 12) | G28: =G6/3 * (Inputs!$B$35 / 12) * (1 + Inputs!$B$48)^INT((COLUMNS($B$28:G28)-1) / 12) | H28: =H6/3 * (Inputs!$B$35 / 12) * (1 + Inputs!$B$48)^INT((COLUMNS($B$28:H28)-1) / 12) | I28: =I6/3 * (Inputs!$B$35 / 12) * (1 + Inputs!$B$48)^INT((COLUMNS($B$28:I28)-1) / 12) | ... BA28: =BA6/3 * (Inputs!$B$35 / 12) * (1 + Inputs!$B$48)^INT((COLUMNS($B$28:BA28)-1) / 12)
A29: 1. Software Developer Gehalt | B29: =B7 * (Inputs!$B$36 / 12) * (1 + Inputs!$B$48)^INT((COLUMNS($B$29:B29)-1) / 12) | C29: =C7 * (Inputs!$B$36 / 12) * (1 + Inputs!$B$48)^INT((COLUMNS($B$29:C29)-1) / 12) | D29: =D7 * (Inputs!$B$36 / 12) * (1 + Inputs!$B$48)^INT((COLUMNS($B$29:D29)-1) / 12) | E29: =E7 * (Inputs!$B$36 / 12) * (1 + Inputs!$B$48)^INT((COLUMNS($B$29:E29)-1) / 12) | F29: =F7 * (Inputs!$B$36 / 12) * (1 + Inputs!$B$48)^INT((COLUMNS($B$29:F29)-1) / 12) | G29: =G7 * (Inputs!$B$36 / 12) * (1 + Inputs!$B$48)^INT((COLUMNS($B$29:G29)-1) / 12) | H29: =H7 * (Inputs!$B$36 / 12) * (1 + Inputs!$B$48)^INT((COLUMNS($B$29:H29)-1) / 12) | I29: =I7 * (Inputs!$B$36 / 12) * (1 + Inputs!$B$48)^INT((COLUMNS($B$29:I29)-1) / 12) | ... BA29: =BA7 * (Inputs!$B$36 / 12) * (1 + Inputs!$B$48)^INT((COLUMNS($B$29:BA29)-1) / 12)
A30: 2. Software Developer Gehalt | B30: =B8 * (Inputs!$B$36 / 12) * (1 + Inputs!$B$48)^INT((COLUMNS($B$30:B30)-1) / 12) | C30: =C8 * (Inputs!$B$36 / 12) * (1 + Inputs!$B$48)^INT((COLUMNS($B$30:C30)-1) / 12) | D30: =D8 * (Inputs!$B$36 / 12) * (1 + Inputs!$B$48)^INT((COLUMNS($B$30:D30)-1) / 12) | E30: =E8 * (Inputs!$B$36 / 12) * (1 + Inputs!$B$48)^INT((COLUMNS($B$30:E30)-1) / 12) | F30: =F8 * (Inputs!$B$36 / 12) * (1 + Inputs!$B$48)^INT((COLUMNS($B$30:F30)-1) / 12) | G30: =G8 * (Inputs!$B$36 / 12) * (1 + Inputs!$B$48)^INT((COLUMNS($B$30:G30)-1) / 12) | H30: =H8 * (Inputs!$B$36 / 12) * (1 + Inputs!$B$48)^INT((COLUMNS($B$30:H30)-1) / 12) | I30: =I8 * (Inputs!$B$36 / 12) * (1 + Inputs!$B$48)^INT((COLUMNS($B$30:I30)-1) / 12) | ... BA30: =BA8 * (Inputs!$B$36 / 12) * (1 + Inputs!$B$48)^INT((COLUMNS($B$30:BA30)-1) / 12)
A31: 1. Junior Software Developer Gehalt | B31: =B9 * (Inputs!$B$37 / 12) * (1 + Inputs!$B$48)^INT((COLUMNS($B$31:B31)-1) / 12) | C31: =C9 * (Inputs!$B$37 / 12) * (1 + Inputs!$B$48)^INT((COLUMNS($B$31:C31)-1) / 12) | D31: =D9 * (Inputs!$B$37 / 12) * (1 + Inputs!$B$48)^INT((COLUMNS($B$31:D31)-1) / 12) | E31: =E9 * (Inputs!$B$37 / 12) * (1 + Inputs!$B$48)^INT((COLUMNS($B$31:E31)-1) / 12) | F31: =F9 * (Inputs!$B$37 / 12) * (1 + Inputs!$B$48)^INT((COLUMNS($B$31:F31)-1) / 12) | G31: =G9 * (Inputs!$B$37 / 12) * (1 + Inputs!$B$48)^INT((COLUMNS($B$31:G31)-1) / 12) | H31: =H9 * (Inputs!$B$37 / 12) * (1 + Inputs!$B$48)^INT((COLUMNS($B$31:H31)-1) / 12) | I31: =I9 * (Inputs!$B$37 / 12) * (1 + Inputs!$B$48)^INT((COLUMNS($B$31:I31)-1) / 12) | ... BA31: =BA9 * (Inputs!$B$37 / 12) * (1 + Inputs!$B$48)^INT((COLUMNS($B$31:BA31)-1) / 12)
A32: 1. ML/AI Engineer Gehalt | B32: =B10 * (Inputs!$B$38 / 12) * (1 + Inputs!$B$48)^INT((COLUMNS($B$32:B32)-1) / 12) | C32: =C10 * (Inputs!$B$38 / 12) * (1 + Inputs!$B$48)^INT((COLUMNS($B$32:C32)-1) / 12) | D32: =D10 * (Inputs!$B$38 / 12) * (1 + Inputs!$B$48)^INT((COLUMNS($B$32:D32)-1) / 12) | E32: =E10 * (Inputs!$B$38 / 12) * (1 + Inputs!$B$48)^INT((COLUMNS($B$32:E32)-1) / 12) | F32: =F10 * (Inputs!$B$38 / 12) * (1 + Inputs!$B$48)^INT((COLUMNS($B$32:F32)-1) / 12) | G32: =G10 * (Inputs!$B$38 / 12) * (1 + Inputs!$B$48)^INT((COLUMNS($B$32:G32)-1) / 12) | H32: =H10 * (Inputs!$B$38 / 12) * (1 + Inputs!$B$48)^INT((COLUMNS($B$32:H32)-1) / 12) | I32: =I10 * (Inputs!$B$38 / 12) * (1 + Inputs!$B$48)^INT((COLUMNS($B$32:I32)-1) / 12) | ... BA32: =BA10 * (Inputs!$B$38 / 12) * (1 + Inputs!$B$48)^INT((COLUMNS($B$32:BA32)-1) / 12)
A33: 1. Mechanical Engineer Gehalt | B33: =B11*(Inputs!$B$41/12)*(1+Inputs!$B$48)^INT((COLUMNS($B$33:B33)-1)/12) | C33: =C11*(Inputs!$B$41/12)*(1+Inputs!$B$48)^INT((COLUMNS($B$33:C33)-1)/12) | D33: =D11*(Inputs!$B$41/12)*(1+Inputs!$B$48)^INT((COLUMNS($B$33:D33)-1)/12) | E33: =E11*(Inputs!$B$41/12)*(1+Inputs!$B$48)^INT((COLUMNS($B$33:E33)-1)/12) | F33: =F11*(Inputs!$B$41/12)*(1+Inputs!$B$48)^INT((COLUMNS($B$33:F33)-1)/12) | G33: =G11*(Inputs!$B$41/12)*(1+Inputs!$B$48)^INT((COLUMNS($B$33:G33)-1)/12) | H33: =H11*(Inputs!$B$41/12)*(1+Inputs!$B$48)^INT((COLUMNS($B$33:H33)-1)/12) | I33: =I11*(Inputs!$B$41/12)*(1+Inputs!$B$48)^INT((COLUMNS($B$33:I33)-1)/12) | ... BA33: =BA11*(Inputs!$B$41/12)*(1+Inputs!$B$48)^INT((COLUMNS($B$33:BA33)-1)/12)
A34: 1. UX/UI Designer Gehalt | B34: =B13*(Inputs!$B$40/12)*(1+Inputs!$B$48)^INT((COLUMNS($B$34:B34)-1)/12) | C34: =C13*(Inputs!$B$40/12)*(1+Inputs!$B$48)^INT((COLUMNS($B$34:C34)-1)/12) | D34: =D13*(Inputs!$B$40/12)*(1+Inputs!$B$48)^INT((COLUMNS($B$34:D34)-1)/12) | E34: =E13*(Inputs!$B$40/12)*(1+Inputs!$B$48)^INT((COLUMNS($B$34:E34)-1)/12) | F34: =F13*(Inputs!$B$40/12)*(1+Inputs!$B$48)^INT((COLUMNS($B$34:F34)-1)/12) | G34: =G13*(Inputs!$B$40/12)*(1+Inputs!$B$48)^INT((COLUMNS($B$34:G34)-1)/12) | H34: =H13*(Inputs!$B$40/12)*(1+Inputs!$B$48)^INT((COLUMNS($B$34:H34)-1)/12) | I34: =I13*(Inputs!$B$40/12)*(1+Inputs!$B$48)^INT((COLUMNS($B$34:I34)-1)/12) | ... BA34: =BA13*(Inputs!$B$40/12)*(1+Inputs!$B$48)^INT((COLUMNS($B$34:BA34)-1)/12)
A35: 1. Customer Key Account Gehalt | B35: =B14 * (Inputs!$B$42 / 12) * (1 + Inputs!$B$48)^INT((COLUMNS($B$35:B35)-1) / 12) | C35: =C14 * (Inputs!$B$42 / 12) * (1 + Inputs!$B$48)^INT((COLUMNS($B$35:C35)-1) / 12) | D35: =D14 * (Inputs!$B$42 / 12) * (1 + Inputs!$B$48)^INT((COLUMNS($B$35:D35)-1) / 12) | E35: =E14 * (Inputs!$B$42 / 12) * (1 + Inputs!$B$48)^INT((COLUMNS($B$35:E35)-1) / 12) | F35: =F14 * (Inputs!$B$42 / 12) * (1 + Inputs!$B$48)^INT((COLUMNS($B$35:F35)-1) / 12) | G35: =G14 * (Inputs!$B$42 / 12) * (1 + Inputs!$B$48)^INT((COLUMNS($B$35:G35)-1) / 12) | H35: =H14 * (Inputs!$B$42 / 12) * (1 + Inputs!$B$48)^INT((COLUMNS($B$35:H35)-1) / 12) | I35: =I14 * (Inputs!$B$42 / 12) * (1 + Inputs!$B$48)^INT((COLUMNS($B$35:I35)-1) / 12) | ... BA35: =BA14 * (Inputs!$B$42 / 12) * (1 + Inputs!$B$48)^INT((COLUMNS($B$35:BA35)-1) / 12)
A36: 2. Customer Key Account Gehalt | B36: =B15*(Inputs!$B$42/12)*(1+Inputs!$B$48)^INT((COLUMNS($B$36:B36)-1)/12) | C36: =C15*(Inputs!$B$42/12)*(1+Inputs!$B$48)^INT((COLUMNS($B$36:C36)-1)/12) | D36: =D15*(Inputs!$B$42/12)*(1+Inputs!$B$48)^INT((COLUMNS($B$36:D36)-1)/12) | E36: =E15*(Inputs!$B$42/12)*(1+Inputs!$B$48)^INT((COLUMNS($B$36:E36)-1)/12) | F36: =F15*(Inputs!$B$42/12)*(1+Inputs!$B$48)^INT((COLUMNS($B$36:F36)-1)/12) | G36: =G15*(Inputs!$B$42/12)*(1+Inputs!$B$48)^INT((COLUMNS($B$36:G36)-1)/12) | H36: =H15*(Inputs!$B$42/12)*(1+Inputs!$B$48)^INT((COLUMNS($B$36:H36)-1)/12) | I36: =I15*(Inputs!$B$42/12)*(1+Inputs!$B$48)^INT((COLUMNS($B$36:I36)-1)/12) | ... BA36: =BA15*(Inputs!$B$42/12)*(1+Inputs!$B$48)^INT((COLUMNS($B$36:BA36)-1)/12)
A37: 3. Customer Key Account Gehalt | B37: =B16*(Inputs!$B$42/12)*(1+Inputs!$B$48)^INT((COLUMNS($B$37:B37)-1)/12) | C37: =C16*(Inputs!$B$42/12)*(1+Inputs!$B$48)^INT((COLUMNS($B$37:C37)-1)/12) | D37: =D16*(Inputs!$B$42/12)*(1+Inputs!$B$48)^INT((COLUMNS($B$37:D37)-1)/12) | E37: =E16*(Inputs!$B$42/12)*(1+Inputs!$B$48)^INT((COLUMNS($B$37:E37)-1)/12) | F37: =F16*(Inputs!$B$42/12)*(1+Inputs!$B$48)^INT((COLUMNS($B$37:F37)-1)/12) | G37: =G16*(Inputs!$B$42/12)*(1+Inputs!$B$48)^INT((COLUMNS($B$37:G37)-1)/12) | H37: =H16*(Inputs!$B$42/12)*(1+Inputs!$B$48)^INT((COLUMNS($B$37:H37)-1)/12) | I37: =I16*(Inputs!$B$42/12)*(1+Inputs!$B$48)^INT((COLUMNS($B$37:I37)-1)/12) | ... BA37: =BA16*(Inputs!$B$42/12)*(1+Inputs!$B$48)^INT((COLUMNS($B$37:BA37)-1)/12)
A38: 1. Marketing Assistant Gehalt | B38: =B17*(Inputs!$B$44/12)*(1+Inputs!$B$48)^INT((COLUMNS($B$38:B38)-1)/12) | C38: =C17*(Inputs!$B$44/12)*(1+Inputs!$B$48)^INT((COLUMNS($B$38:C38)-1)/12) | D38: =D17*(Inputs!$B$44/12)*(1+Inputs!$B$48)^INT((COLUMNS($B$38:D38)-1)/12) | E38: =E17*(Inputs!$B$44/12)*(1+Inputs!$B$48)^INT((COLUMNS($B$38:E38)-1)/12) | F38: =F17*(Inputs!$B$44/12)*(1+Inputs!$B$48)^INT((COLUMNS($B$38:F38)-1)/12) | G38: =G17*(Inputs!$B$44/12)*(1+Inputs!$B$48)^INT((COLUMNS($B$38:G38)-1)/12) | H38: =H17*(Inputs!$B$44/12)*(1+Inputs!$B$48)^INT((COLUMNS($B$38:H38)-1)/12) | I38: =I17*(Inputs!$B$44/12)*(1+Inputs!$B$48)^INT((COLUMNS($B$38:I38)-1)/12) | ... BA38: =BA17*(Inputs!$B$44/12)*(1+Inputs!$B$48)^INT((COLUMNS($B$38:BA38)-1)/12)
A39: 2. Marketing Assistant Gehalt | B39: =B18*(Inputs!$B$44/12)*(1+Inputs!$B$48)^INT((COLUMNS($B$39:B39)-1)/12) | C39: =C18*(Inputs!$B$44/12)*(1+Inputs!$B$48)^INT((COLUMNS($B$39:C39)-1)/12) | D39: =D18*(Inputs!$B$44/12)*(1+Inputs!$B$48)^INT((COLUMNS($B$39:D39)-1)/12) | E39: =E18*(Inputs!$B$44/12)*(1+Inputs!$B$48)^INT((COLUMNS($B$39:E39)-1)/12) | F39: =F18*(Inputs!$B$44/12)*(1+Inputs!$B$48)^INT((COLUMNS($B$39:F39)-1)/12) | G39: =G18*(Inputs!$B$44/12)*(1+Inputs!$B$48)^INT((COLUMNS($B$39:G39)-1)/12) | H39: =H18*(Inputs!$B$44/12)*(1+Inputs!$B$48)^INT((COLUMNS($B$39:H39)-1)/12) | I39: =I18*(Inputs!$B$44/12)*(1+Inputs!$B$48)^INT((COLUMNS($B$39:I39)-1)/12) | ... BA39: =BA18*(Inputs!$B$44/12)*(1+Inputs!$B$48)^INT((COLUMNS($B$39:BA39)-1)/12)
A40: 1. Marketing Manager Gehalt | B40: =B19*(Inputs!$B$43/12)*(1+Inputs!$B$48)^INT((COLUMNS($B$40:B40)-1)/12) | C40: =C19*(Inputs!$B$43/12)*(1+Inputs!$B$48)^INT((COLUMNS($B$40:C40)-1)/12) | D40: =D19*(Inputs!$B$43/12)*(1+Inputs!$B$48)^INT((COLUMNS($B$40:D40)-1)/12) | E40: =E19*(Inputs!$B$43/12)*(1+Inputs!$B$48)^INT((COLUMNS($B$40:E40)-1)/12) | F40: =F19*(Inputs!$B$43/12)*(1+Inputs!$B$48)^INT((COLUMNS($B$40:F40)-1)/12) | G40: =G19*(Inputs!$B$43/12)*(1+Inputs!$B$48)^INT((COLUMNS($B$40:G40)-1)/12) | H40: =H19*(Inputs!$B$43/12)*(1+Inputs!$B$48)^INT((COLUMNS($B$40:H40)-1)/12) | I40: =I19*(Inputs!$B$43/12)*(1+Inputs!$B$48)^INT((COLUMNS($B$40:I40)-1)/12) | ... BA40: =BA19*(Inputs!$B$43/12)*(1+Inputs!$B$48)^INT((COLUMNS($B$40:BA40)-1)/12)
A41: 1. Office Manager Gehalt | B41: =B20*(Inputs!$B$46/12)*(1+Inputs!$B$48)^INT((COLUMNS($B$41:B41)-1)/12) | C41: =C20*(Inputs!$B$46/12)*(1+Inputs!$B$48)^INT((COLUMNS($B$41:C41)-1)/12) | D41: =D20*(Inputs!$B$46/12)*(1+Inputs!$B$48)^INT((COLUMNS($B$41:D41)-1)/12) | E41: =E20*(Inputs!$B$46/12)*(1+Inputs!$B$48)^INT((COLUMNS($B$41:E41)-1)/12) | F41: =F20*(Inputs!$B$46/12)*(1+Inputs!$B$48)^INT((COLUMNS($B$41:F41)-1)/12) | G41: =G20*(Inputs!$B$46/12)*(1+Inputs!$B$48)^INT((COLUMNS($B$41:G41)-1)/12) | H41: =H20*(Inputs!$B$46/12)*(1+Inputs!$B$48)^INT((COLUMNS($B$41:H41)-1)/12) | I41: =I20*(Inputs!$B$46/12)*(1+Inputs!$B$48)^INT((COLUMNS($B$41:I41)-1)/12) | ... BA41: =BA20*(Inputs!$B$46/12)*(1+Inputs!$B$48)^INT((COLUMNS($B$41:BA41)-1)/12)
A42: 1. Customer Success Gehalt | B42: =B21*(Inputs!$B$45/12)*(1+Inputs!$B$48)^INT((COLUMNS($B$42:B42)-1)/12) | C42: =C21*(Inputs!$B$45/12)*(1+Inputs!$B$48)^INT((COLUMNS($B$42:C42)-1)/12) | D42: =D21*(Inputs!$B$45/12)*(1+Inputs!$B$48)^INT((COLUMNS($B$42:D42)-1)/12) | E42: =E21*(Inputs!$B$45/12)*(1+Inputs!$B$48)^INT((COLUMNS($B$42:E42)-1)/12) | F42: =F21*(Inputs!$B$45/12)*(1+Inputs!$B$48)^INT((COLUMNS($B$42:F42)-1)/12) | G42: =G21*(Inputs!$B$45/12)*(1+Inputs!$B$48)^INT((COLUMNS($B$42:G42)-1)/12) | H42: =H21*(Inputs!$B$45/12)*(1+Inputs!$B$48)^INT((COLUMNS($B$42:H42)-1)/12) | I42: =I21*(Inputs!$B$45/12)*(1+Inputs!$B$48)^INT((COLUMNS($B$42:I42)-1)/12) | ... BA42: =BA21*(Inputs!$B$45/12)*(1+Inputs!$B$48)^INT((COLUMNS($B$42:BA42)-1)/12)
A43: 1. Finance Manager Gehalt | B43: =B22*(Inputs!$B$47/12)*(1+Inputs!$B$48)^INT((COLUMNS($B$43:B43)-1)/12) | C43: =C22*(Inputs!$B$47/12)*(1+Inputs!$B$48)^INT((COLUMNS($B$43:C43)-1)/12) | D43: =D22*(Inputs!$B$47/12)*(1+Inputs!$B$48)^INT((COLUMNS($B$43:D43)-1)/12) | E43: =E22*(Inputs!$B$47/12)*(1+Inputs!$B$48)^INT((COLUMNS($B$43:E43)-1)/12) | F43: =F22*(Inputs!$B$47/12)*(1+Inputs!$B$48)^INT((COLUMNS($B$43:F43)-1)/12) | G43: =G22*(Inputs!$B$47/12)*(1+Inputs!$B$48)^INT((COLUMNS($B$43:G43)-1)/12) | H43: =H22*(Inputs!$B$47/12)*(1+Inputs!$B$48)^INT((COLUMNS($B$43:H43)-1)/12) | I43: =I22*(Inputs!$B$47/12)*(1+Inputs!$B$48)^INT((COLUMNS($B$43:I43)-1)/12) | ... BA43: =BA22*(Inputs!$B$47/12)*(1+Inputs!$B$48)^INT((COLUMNS($B$43:BA43)-1)/12)
A44: Subtotal Brutto-Gehälter | B44: =SUM(B26:B43) | C44: =SUM(C26:C43) | D44: =SUM(D26:D43) | E44: =SUM(E26:E43) | F44: =SUM(F26:F43) | G44: =SUM(G26:G43) | H44: =SUM(H26:H43) | I44: =SUM(I26:I43) | ... BA44: =SUM(BA26:BA43)
A45: Lohnnebenkosten (AG-Anteil) | B45: =B44*Inputs!$B$49 | C45: =C44*Inputs!$B$49 | D45: =D44*Inputs!$B$49 | E45: =E44*Inputs!$B$49 | F45: =F44*Inputs!$B$49 | G45: =G44*Inputs!$B$49 | H45: =H44*Inputs!$B$49 | I45: =I44*Inputs!$B$49 | ... BA45: =BA44*Inputs!$B$49
A46: TOTAL PERSONALKOSTEN | B46: =B44+B45 | C46: =C44+C45 | D46: =D44+D45 | E46: =E44+E45 | F46: =F44+F45 | G46: =G44+G45 | H46: =H44+H45 | I46: =I44+I45 | ... BA46: =BA44+BA45
A48: TECHNOLOGIEKOSTEN
A49: Cloud Infrastructure (Basis) | B49: =Inputs!$B$70 | C49: =Inputs!$B$70 | D49: =Inputs!$B$70 | E49: =Inputs!$B$70 | F49: =Inputs!$B$70 | G49: =Inputs!$B$70 | H49: =Inputs!$B$70 | I49: =Inputs!$B$70 | ... BA49: =Inputs!$B$70
A50: Cloud Infrastructure (Variable) | B50: =Revenue!B11*Inputs!$B$71 | C50: =Revenue!C11*Inputs!$B$71 | D50: =Revenue!D11*Inputs!$B$71 | E50: =Revenue!E11*Inputs!$B$71 | F50: =Revenue!F11*Inputs!$B$71 | G50: =Revenue!G11*Inputs!$B$71 | H50: =Revenue!H11*Inputs!$B$71 | I50: =Revenue!I11*Inputs!$B$71 | ... BA50: =Revenue!BA11*Inputs!$B$71
A51: AI/ML API Kosten | B51: =Inputs!$B$72*(1+Inputs!$B$73)^(1-1) | C51: =Inputs!$B$72*(1+Inputs!$B$73)^(2-1) | D51: =Inputs!$B$72*(1+Inputs!$B$73)^(3-1) | E51: =Inputs!$B$72*(1+Inputs!$B$73)^(4-1) | F51: =Inputs!$B$72*(1+Inputs!$B$73)^(5-1) | G51: =Inputs!$B$72*(1+Inputs!$B$73)^(6-1) | H51: =Inputs!$B$72*(1+Inputs!$B$73)^(7-1) | I51: =Inputs!$B$72*(1+Inputs!$B$73)^(8-1) | J51: =Inputs!$B$72*(1+Inputs!$B$73)^(9-1) | K51: =Inputs!$B$72*(1+Inputs!$B$73)^(10-1) | L51: =Inputs!$B$72*(1+Inputs!$B$73)^(11-1) | M51: =Inputs!$B$72*(1+Inputs!$B$73)^(12-1) | N51: =Inputs!$B$72*(1+Inputs!$B$73)^(13-1) | O51: =Inputs!$B$72*(1+Inputs!$B$73)^(14-1) | P51: =Inputs!$B$72*(1+Inputs!$B$73)^(15-1) | Q51: =Inputs!$B$72*(1+Inputs!$B$73)^(16-1) | R51: =Inputs!$B$72*(1+Inputs!$B$73)^(17-1) | S51: =Inputs!$B$72*(1+Inputs!$B$73)^(18-1) | T51: =Inputs!$B$72*(1+Inputs!$B$73)^(19-1) | U51: =Inputs!$B$72*(1+Inputs!$B$73)^(20-1) | V51: =Inputs!$B$72*(1+Inputs!$B$73)^(21-1) | W51: =Inputs!$B$72*(1+Inputs!$B$73)^(22-1) | X51: =Inputs!$B$72*(1+Inputs!$B$73)^(23-1) | Y51: =Inputs!$B$72*(1+Inputs!$B$73)^(24-1) | Z51: =Inputs!$B$72*(1+Inputs!$B$73)^(25-1) | AA51: =Inputs!$B$72*(1+Inputs!$B$73)^(26-1) | AB51: =Inputs!$B$72*(1+Inputs!$B$73)^(27-1) | AC51: =Inputs!$B$72*(1+Inputs!$B$73)^(28-1) | AD51: =Inputs!$B$72*(1+Inputs!$B$73)^(29-1) | AE51: =Inputs!$B$72*(1+Inputs!$B$73)^(30-1) | AF51: =Inputs!$B$72*(1+Inputs!$B$73)^(31-1) | AG51: =Inputs!$B$72*(1+Inputs!$B$73)^(32-1) | AH51: =Inputs!$B$72*(1+Inputs!$B$73)^(33-1) | AI51: =Inputs!$B$72*(1+Inputs!$B$73)^(34-1) | AJ51: =Inputs!$B$72*(1+Inputs!$B$73)^(35-1) | AK51: =Inputs!$B$72*(1+Inputs!$B$73)^(36-1) | AL51: =Inputs!$B$72*(1+Inputs!$B$73)^(37-1) | AM51: =Inputs!$B$72*(1+Inputs!$B$73)^(38-1) | AN51: =Inputs!$B$72*(1+Inputs!$B$73)^(39-1) | AO51: =Inputs!$B$72*(1+Inputs!$B$73)^(40-1) | AP51: =Inputs!$B$72*(1+Inputs!$B$73)^(41-1) | AQ51: =Inputs!$B$72*(1+Inputs!$B$73)^(42-1) | AR51: =Inputs!$B$72*(1+Inputs!$B$73)^(43-1) | AS51: =Inputs!$B$72*(1+Inputs!$B$73)^(44-1) | AT51: =Inputs!$B$72*(1+Inputs!$B$73)^(45-1) | AU51: =Inputs!$B$72*(1+Inputs!$B$73)^(46-1) | AV51: =Inputs!$B$72*(1+Inputs!$B$73)^(47-1) | AW51: =Inputs!$B$72*(1+Inputs!$B$73)^(48-1) | AX51: =Inputs!$B$72*(1+Inputs!$B$73)^(49-1) | AY51: =Inputs!$B$72*(1+Inputs!$B$73)^(50-1) | AZ51: =Inputs!$B$72*(1+Inputs!$B$73)^(51-1) | BA51: =Inputs!$B$72*(1+Inputs!$B$73)^(52-1)
A52: SaaS Tools intern | B52: =Inputs!$B$74+B23*Inputs!$B$75 | C52: =Inputs!$B$74+C23*Inputs!$B$75 | D52: =Inputs!$B$74+D23*Inputs!$B$75 | E52: =Inputs!$B$74+E23*Inputs!$B$75 | F52: =Inputs!$B$74+F23*Inputs!$B$75 | G52: =Inputs!$B$74+G23*Inputs!$B$75 | H52: =Inputs!$B$74+H23*Inputs!$B$75 | I52: =Inputs!$B$74+I23*Inputs!$B$75 | ... BA52: =Inputs!$B$74+BA23*Inputs!$B$75
A53: Software-Lizenzen Dev | B53: =Inputs!$B$76/12 | C53: =Inputs!$B$76/12 | D53: =Inputs!$B$76/12 | E53: =Inputs!$B$76/12 | F53: =Inputs!$B$76/12 | G53: =Inputs!$B$76/12 | H53: =Inputs!$B$76/12 | I53: =Inputs!$B$76/12 | ... BA53: =Inputs!$B$76/12
A54: Sicherheit & Compliance | B54: =Inputs!$B$77 | C54: =Inputs!$B$77 | D54: =Inputs!$B$77 | E54: =Inputs!$B$77 | F54: =Inputs!$B$77 | G54: =Inputs!$B$77 | H54: =Inputs!$B$77 | I54: =Inputs!$B$77 | ... BA54: =Inputs!$B$77
A55: TOTAL TECHNOLOGIE | B55: =SUM(B49:B54) | C55: =SUM(C49:C54) | D55: =SUM(D49:D54) | E55: =SUM(E49:E54) | F55: =SUM(F49:F54) | G55: =SUM(G49:G54) | H55: =SUM(H49:H54) | I55: =SUM(I49:I54) | ... BA55: =SUM(BA49:BA54)
A57: BÜROKOSTEN
A58: Büromiete | B58: =IF(1>=Inputs!$B$87,Inputs!$B$88,Inputs!$B$86) | C58: =IF(2>=Inputs!$B$87,Inputs!$B$88,Inputs!$B$86) | D58: =IF(3>=Inputs!$B$87,Inputs!$B$88,Inputs!$B$86) | E58: =IF(4>=Inputs!$B$87,Inputs!$B$88,Inputs!$B$86) | F58: =IF(5>=Inputs!$B$87,Inputs!$B$88,Inputs!$B$86) | G58: =IF(6>=Inputs!$B$87,Inputs!$B$88,Inputs!$B$86) | H58: =IF(7>=Inputs!$B$87,Inputs!$B$88,Inputs!$B$86) | I58: =IF(8>=Inputs!$B$87,Inputs!$B$88,Inputs!$B$86) | J58: =IF(9>=Inputs!$B$87,Inputs!$B$88,Inputs!$B$86) | K58: =IF(10>=Inputs!$B$87,Inputs!$B$88,Inputs!$B$86) | L58: =IF(11>=Inputs!$B$87,Inputs!$B$88,Inputs!$B$86) | M58: =IF(12>=Inputs!$B$87,Inputs!$B$88,Inputs!$B$86) | N58: =IF(13>=Inputs!$B$87,Inputs!$B$88,Inputs!$B$86) | O58: =IF(14>=Inputs!$B$87,Inputs!$B$88,Inputs!$B$86) | P58: =IF(15>=Inputs!$B$87,Inputs!$B$88,Inputs!$B$86) | Q58: =IF(16>=Inputs!$B$87,Inputs!$B$88,Inputs!$B$86) | R58: =IF(17>=Inputs!$B$87,Inputs!$B$88,Inputs!$B$86) | S58: =IF(18>=Inputs!$B$87,Inputs!$B$88,Inputs!$B$86) | T58: =IF(19>=Inputs!$B$87,Inputs!$B$88,Inputs!$B$86) | U58: =IF(20>=Inputs!$B$87,Inputs!$B$88,Inputs!$B$86) | V58: =IF(21>=Inputs!$B$87,Inputs!$B$88,Inputs!$B$86) | W58: =IF(22>=Inputs!$B$87,Inputs!$B$88,Inputs!$B$86) | X58: =IF(23>=Inputs!$B$87,Inputs!$B$88,Inputs!$B$86) | Y58: =IF(24>=Inputs!$B$87,Inputs!$B$88,Inputs!$B$86) | Z58: =IF(25>=Inputs!$B$87,Inputs!$B$88,Inputs!$B$86) | AA58: =IF(26>=Inputs!$B$87,Inputs!$B$88,Inputs!$B$86) | AB58: =IF(27>=Inputs!$B$87,Inputs!$B$88,Inputs!$B$86) | AC58: =IF(28>=Inputs!$B$87,Inputs!$B$88,Inputs!$B$86) | AD58: =IF(29>=Inputs!$B$87,Inputs!$B$88,Inputs!$B$86) | AE58: =IF(30>=Inputs!$B$87,Inputs!$B$88,Inputs!$B$86) | AF58: =IF(31>=Inputs!$B$87,Inputs!$B$88,Inputs!$B$86) | AG58: =IF(32>=Inputs!$B$87,Inputs!$B$88,Inputs!$B$86) | AH58: =IF(33>=Inputs!$B$87,Inputs!$B$88,Inputs!$B$86) | AI58: =IF(34>=Inputs!$B$87,Inputs!$B$88,Inputs!$B$86) | AJ58: =IF(35>=Inputs!$B$87,Inputs!$B$88,Inputs!$B$86) | AK58: =IF(36>=Inputs!$B$87,Inputs!$B$88,Inputs!$B$86) | AL58: =IF(37>=Inputs!$B$87,Inputs!$B$88,Inputs!$B$86) | AM58: =IF(38>=Inputs!$B$87,Inputs!$B$88,Inputs!$B$86) | AN58: =IF(39>=Inputs!$B$87,Inputs!$B$88,Inputs!$B$86) | AO58: =IF(40>=Inputs!$B$87,Inputs!$B$88,Inputs!$B$86) | AP58: =IF(41>=Inputs!$B$87,Inputs!$B$88,Inputs!$B$86) | AQ58: =IF(42>=Inputs!$B$87,Inputs!$B$88,Inputs!$B$86) | AR58: =IF(43>=Inputs!$B$87,Inputs!$B$88,Inputs!$B$86) | AS58: =IF(44>=Inputs!$B$87,Inputs!$B$88,Inputs!$B$86) | AT58: =IF(45>=Inputs!$B$87,Inputs!$B$88,Inputs!$B$86) | AU58: =IF(46>=Inputs!$B$87,Inputs!$B$88,Inputs!$B$86) | AV58: =IF(47>=Inputs!$B$87,Inputs!$B$88,Inputs!$B$86) | AW58: =IF(48>=Inputs!$B$87,Inputs!$B$88,Inputs!$B$86) | AX58: =IF(49>=Inputs!$B$87,Inputs!$B$88,Inputs!$B$86) | AY58: =IF(50>=Inputs!$B$87,Inputs!$B$88,Inputs!$B$86) | AZ58: =IF(51>=Inputs!$B$87,Inputs!$B$88,Inputs!$B$86) | BA58: =IF(52>=Inputs!$B$87,Inputs!$B$88,Inputs!$B$86)
A59: Nebenkosten | B59: =Inputs!$B$89 | C59: =Inputs!$B$89 | D59: =Inputs!$B$89 | E59: =Inputs!$B$89 | F59: =Inputs!$B$89 | G59: =Inputs!$B$89 | H59: =Inputs!$B$89 | I59: =Inputs!$B$89 | ... BA59: =Inputs!$B$89
A60: Internet & Telefon | B60: =Inputs!$B$90 | C60: =Inputs!$B$90 | D60: =Inputs!$B$90 | E60: =Inputs!$B$90 | F60: =Inputs!$B$90 | G60: =Inputs!$B$90 | H60: =Inputs!$B$90 | I60: =Inputs!$B$90 | ... BA60: =Inputs!$B$90
A61: Bürobedarf | B61: =B23*Inputs!$B$92 | C61: =C23*Inputs!$B$92 | D61: =D23*Inputs!$B$92 | E61: =E23*Inputs!$B$92 | F61: =F23*Inputs!$B$92 | G61: =G23*Inputs!$B$92 | H61: =H23*Inputs!$B$92 | I61: =I23*Inputs!$B$92 | ... BA61: =BA23*Inputs!$B$92
A62: TOTAL BÜRO | B62: =SUM(B58:B61) | C62: =SUM(C58:C61) | D62: =SUM(D58:D61) | E62: =SUM(E58:E61) | F62: =SUM(F58:F61) | G62: =SUM(G58:G61) | H62: =SUM(H58:H61) | I62: =SUM(I58:I61) | ... BA62: =SUM(BA58:BA61)
A64: PROFESSIONAL SERVICES
A65: Rechtsanwalt (laufend) | B65: =Inputs!$B$95/12+IF(OR(1=Inputs!$B$11,1=Inputs!$B$13,1=Inputs!$B$15,1=Inputs!$B$17),Inputs!$B$96,0) | C65: =Inputs!$B$95/12+IF(OR(2=Inputs!$B$11,2=Inputs!$B$13,2=Inputs!$B$15,2=Inputs!$B$17),Inputs!$B$96,0) | D65: =Inputs!$B$95/12+IF(OR(3=Inputs!$B$11,3=Inputs!$B$13,3=Inputs!$B$15,3=Inputs!$B$17),Inputs!$B$96,0) | E65: =Inputs!$B$95/12+IF(OR(4=Inputs!$B$11,4=Inputs!$B$13,4=Inputs!$B$15,4=Inputs!$B$17),Inputs!$B$96,0) | F65: =Inputs!$B$95/12+IF(OR(5=Inputs!$B$11,5=Inputs!$B$13,5=Inputs!$B$15,5=Inputs!$B$17),Inputs!$B$96,0) | G65: =Inputs!$B$95/12+IF(OR(6=Inputs!$B$11,6=Inputs!$B$13,6=Inputs!$B$15,6=Inputs!$B$17),Inputs!$B$96,0) | H65: =Inputs!$B$95/12+IF(OR(7=Inputs!$B$11,7=Inputs!$B$13,7=Inputs!$B$15,7=Inputs!$B$17),Inputs!$B$96,0) | I65: =Inputs!$B$95/12+IF(OR(8=Inputs!$B$11,8=Inputs!$B$13,8=Inputs!$B$15,8=Inputs!$B$17),Inputs!$B$96,0) | J65: =Inputs!$B$95/12+IF(OR(9=Inputs!$B$11,9=Inputs!$B$13,9=Inputs!$B$15,9=Inputs!$B$17),Inputs!$B$96,0) | K65: =Inputs!$B$95/12+IF(OR(10=Inputs!$B$11,10=Inputs!$B$13,10=Inputs!$B$15,10=Inputs!$B$17),Inputs!$B$96,0) | L65: =Inputs!$B$95/12+IF(OR(11=Inputs!$B$11,11=Inputs!$B$13,11=Inputs!$B$15,11=Inputs!$B$17),Inputs!$B$96,0) | M65: =Inputs!$B$95/12+IF(OR(12=Inputs!$B$11,12=Inputs!$B$13,12=Inputs!$B$15,12=Inputs!$B$17),Inputs!$B$96,0) | N65: =Inputs!$B$95/12+IF(OR(13=Inputs!$B$11,13=Inputs!$B$13,13=Inputs!$B$15,13=Inputs!$B$17),Inputs!$B$96,0) | O65: =Inputs!$B$95/12+IF(OR(14=Inputs!$B$11,14=Inputs!$B$13,14=Inputs!$B$15,14=Inputs!$B$17),Inputs!$B$96,0) | P65: =Inputs!$B$95/12+IF(OR(15=Inputs!$B$11,15=Inputs!$B$13,15=Inputs!$B$15,15=Inputs!$B$17),Inputs!$B$96,0) | Q65: =Inputs!$B$95/12+IF(OR(16=Inputs!$B$11,16=Inputs!$B$13,16=Inputs!$B$15,16=Inputs!$B$17),Inputs!$B$96,0) | R65: =Inputs!$B$95/12+IF(OR(17=Inputs!$B$11,17=Inputs!$B$13,17=Inputs!$B$15,17=Inputs!$B$17),Inputs!$B$96,0) | S65: =Inputs!$B$95/12+IF(OR(18=Inputs!$B$11,18=Inputs!$B$13,18=Inputs!$B$15,18=Inputs!$B$17),Inputs!$B$96,0) | T65: =Inputs!$B$95/12+IF(OR(19=Inputs!$B$11,19=Inputs!$B$13,19=Inputs!$B$15,19=Inputs!$B$17),Inputs!$B$96,0) | U65: =Inputs!$B$95/12+IF(OR(20=Inputs!$B$11,20=Inputs!$B$13,20=Inputs!$B$15,20=Inputs!$B$17),Inputs!$B$96,0) | V65: =Inputs!$B$95/12+IF(OR(21=Inputs!$B$11,21=Inputs!$B$13,21=Inputs!$B$15,21=Inputs!$B$17),Inputs!$B$96,0) | W65: =Inputs!$B$95/12+IF(OR(22=Inputs!$B$11,22=Inputs!$B$13,22=Inputs!$B$15,22=Inputs!$B$17),Inputs!$B$96,0) | X65: =Inputs!$B$95/12+IF(OR(23=Inputs!$B$11,23=Inputs!$B$13,23=Inputs!$B$15,23=Inputs!$B$17),Inputs!$B$96,0) | Y65: =Inputs!$B$95/12+IF(OR(24=Inputs!$B$11,24=Inputs!$B$13,24=Inputs!$B$15,24=Inputs!$B$17),Inputs!$B$96,0) | Z65: =Inputs!$B$95/12+IF(OR(25=Inputs!$B$11,25=Inputs!$B$13,25=Inputs!$B$15,25=Inputs!$B$17),Inputs!$B$96,0) | AA65: =Inputs!$B$95/12+IF(OR(26=Inputs!$B$11,26=Inputs!$B$13,26=Inputs!$B$15,26=Inputs!$B$17),Inputs!$B$96,0) | AB65: =Inputs!$B$95/12+IF(OR(27=Inputs!$B$11,27=Inputs!$B$13,27=Inputs!$B$15,27=Inputs!$B$17),Inputs!$B$96,0) | AC65: =Inputs!$B$95/12+IF(OR(28=Inputs!$B$11,28=Inputs!$B$13,28=Inputs!$B$15,28=Inputs!$B$17),Inputs!$B$96,0) | AD65: =Inputs!$B$95/12+IF(OR(29=Inputs!$B$11,29=Inputs!$B$13,29=Inputs!$B$15,29=Inputs!$B$17),Inputs!$B$96,0) | AE65: =Inputs!$B$95/12+IF(OR(30=Inputs!$B$11,30=Inputs!$B$13,30=Inputs!$B$15,30=Inputs!$B$17),Inputs!$B$96,0) | AF65: =Inputs!$B$95/12+IF(OR(31=Inputs!$B$11,31=Inputs!$B$13,31=Inputs!$B$15,31=Inputs!$B$17),Inputs!$B$96,0) | AG65: =Inputs!$B$95/12+IF(OR(32=Inputs!$B$11,32=Inputs!$B$13,32=Inputs!$B$15,32=Inputs!$B$17),Inputs!$B$96,0) | AH65: =Inputs!$B$95/12+IF(OR(33=Inputs!$B$11,33=Inputs!$B$13,33=Inputs!$B$15,33=Inputs!$B$17),Inputs!$B$96,0) | AI65: =Inputs!$B$95/12+IF(OR(34=Inputs!$B$11,34=Inputs!$B$13,34=Inputs!$B$15,34=Inputs!$B$17),Inputs!$B$96,0) | AJ65: =Inputs!$B$95/12+IF(OR(35=Inputs!$B$11,35=Inputs!$B$13,35=Inputs!$B$15,35=Inputs!$B$17),Inputs!$B$96,0) | AK65: =Inputs!$B$95/12+IF(OR(36=Inputs!$B$11,36=Inputs!$B$13,36=Inputs!$B$15,36=Inputs!$B$17),Inputs!$B$96,0) | AL65: =Inputs!$B$95/12+IF(OR(37=Inputs!$B$11,37=Inputs!$B$13,37=Inputs!$B$15,37=Inputs!$B$17),Inputs!$B$96,0) | AM65: =Inputs!$B$95/12+IF(OR(38=Inputs!$B$11,38=Inputs!$B$13,38=Inputs!$B$15,38=Inputs!$B$17),Inputs!$B$96,0) | AN65: =Inputs!$B$95/12+IF(OR(39=Inputs!$B$11,39=Inputs!$B$13,39=Inputs!$B$15,39=Inputs!$B$17),Inputs!$B$96,0) | AO65: =Inputs!$B$95/12+IF(OR(40=Inputs!$B$11,40=Inputs!$B$13,40=Inputs!$B$15,40=Inputs!$B$17),Inputs!$B$96,0) | AP65: =Inputs!$B$95/12+IF(OR(41=Inputs!$B$11,41=Inputs!$B$13,41=Inputs!$B$15,41=Inputs!$B$17),Inputs!$B$96,0) | AQ65: =Inputs!$B$95/12+IF(OR(42=Inputs!$B$11,42=Inputs!$B$13,42=Inputs!$B$15,42=Inputs!$B$17),Inputs!$B$96,0) | AR65: =Inputs!$B$95/12+IF(OR(43=Inputs!$B$11,43=Inputs!$B$13,43=Inputs!$B$15,43=Inputs!$B$17),Inputs!$B$96,0) | AS65: =Inputs!$B$95/12+IF(OR(44=Inputs!$B$11,44=Inputs!$B$13,44=Inputs!$B$15,44=Inputs!$B$17),Inputs!$B$96,0) | AT65: =Inputs!$B$95/12+IF(OR(45=Inputs!$B$11,45=Inputs!$B$13,45=Inputs!$B$15,45=Inputs!$B$17),Inputs!$B$96,0) | AU65: =Inputs!$B$95/12+IF(OR(46=Inputs!$B$11,46=Inputs!$B$13,46=Inputs!$B$15,46=Inputs!$B$17),Inputs!$B$96,0) | AV65: =Inputs!$B$95/12+IF(OR(47=Inputs!$B$11,47=Inputs!$B$13,47=Inputs!$B$15,47=Inputs!$B$17),Inputs!$B$96,0) | AW65: =Inputs!$B$95/12+IF(OR(48=Inputs!$B$11,48=Inputs!$B$13,48=Inputs!$B$15,48=Inputs!$B$17),Inputs!$B$96,0) | AX65: =Inputs!$B$95/12+IF(OR(49=Inputs!$B$11,49=Inputs!$B$13,49=Inputs!$B$15,49=Inputs!$B$17),Inputs!$B$96,0) | AY65: =Inputs!$B$95/12+IF(OR(50=Inputs!$B$11,50=Inputs!$B$13,50=Inputs!$B$15,50=Inputs!$B$17),Inputs!$B$96,0) | AZ65: =Inputs!$B$95/12+IF(OR(51=Inputs!$B$11,51=Inputs!$B$13,51=Inputs!$B$15,51=Inputs!$B$17),Inputs!$B$96,0) | BA65: =Inputs!$B$95/12+IF(OR(52=Inputs!$B$11,52=Inputs!$B$13,52=Inputs!$B$15,52=Inputs!$B$17),Inputs!$B$96,0)
A66: Steuerberater | B66: =Inputs!$B$97 | C66: =Inputs!$B$97 | D66: =Inputs!$B$97 | E66: =Inputs!$B$97 | F66: =Inputs!$B$97 | G66: =Inputs!$B$97 | H66: =Inputs!$B$97 | I66: =Inputs!$B$97 | ... BA66: =Inputs!$B$97
A67: Wirtschaftsprüfer | B67: =IF(1>=Inputs!$B$99,Inputs!$B$98/12,0) | C67: =IF(2>=Inputs!$B$99,Inputs!$B$98/12,0) | D67: =IF(3>=Inputs!$B$99,Inputs!$B$98/12,0) | E67: =IF(4>=Inputs!$B$99,Inputs!$B$98/12,0) | F67: =IF(5>=Inputs!$B$99,Inputs!$B$98/12,0) | G67: =IF(6>=Inputs!$B$99,Inputs!$B$98/12,0) | H67: =IF(7>=Inputs!$B$99,Inputs!$B$98/12,0) | I67: =IF(8>=Inputs!$B$99,Inputs!$B$98/12,0) | J67: =IF(9>=Inputs!$B$99,Inputs!$B$98/12,0) | K67: =IF(10>=Inputs!$B$99,Inputs!$B$98/12,0) | L67: =IF(11>=Inputs!$B$99,Inputs!$B$98/12,0) | M67: =IF(12>=Inputs!$B$99,Inputs!$B$98/12,0) | N67: =IF(13>=Inputs!$B$99,Inputs!$B$98/12,0) | O67: =IF(14>=Inputs!$B$99,Inputs!$B$98/12,0) | P67: =IF(15>=Inputs!$B$99,Inputs!$B$98/12,0) | Q67: =IF(16>=Inputs!$B$99,Inputs!$B$98/12,0) | R67: =IF(17>=Inputs!$B$99,Inputs!$B$98/12,0) | S67: =IF(18>=Inputs!$B$99,Inputs!$B$98/12,0) | T67: =IF(19>=Inputs!$B$99,Inputs!$B$98/12,0) | U67: =IF(20>=Inputs!$B$99,Inputs!$B$98/12,0) | V67: =IF(21>=Inputs!$B$99,Inputs!$B$98/12,0) | W67: =IF(22>=Inputs!$B$99,Inputs!$B$98/12,0) | X67: =IF(23>=Inputs!$B$99,Inputs!$B$98/12,0) | Y67: =IF(24>=Inputs!$B$99,Inputs!$B$98/12,0) | Z67: =IF(25>=Inputs!$B$99,Inputs!$B$98/12,0) | AA67: =IF(26>=Inputs!$B$99,Inputs!$B$98/12,0) | AB67: =IF(27>=Inputs!$B$99,Inputs!$B$98/12,0) | AC67: =IF(28>=Inputs!$B$99,Inputs!$B$98/12,0) | AD67: =IF(29>=Inputs!$B$99,Inputs!$B$98/12,0) | AE67: =IF(30>=Inputs!$B$99,Inputs!$B$98/12,0) | AF67: =IF(31>=Inputs!$B$99,Inputs!$B$98/12,0) | AG67: =IF(32>=Inputs!$B$99,Inputs!$B$98/12,0) | AH67: =IF(33>=Inputs!$B$99,Inputs!$B$98/12,0) | AI67: =IF(34>=Inputs!$B$99,Inputs!$B$98/12,0) | AJ67: =IF(35>=Inputs!$B$99,Inputs!$B$98/12,0) | AK67: =IF(36>=Inputs!$B$99,Inputs!$B$98/12,0) | AL67: =IF(37>=Inputs!$B$99,Inputs!$B$98/12,0) | AM67: =IF(38>=Inputs!$B$99,Inputs!$B$98/12,0) | AN67: =IF(39>=Inputs!$B$99,Inputs!$B$98/12,0) | AO67: =IF(40>=Inputs!$B$99,Inputs!$B$98/12,0) | AP67: =IF(41>=Inputs!$B$99,Inputs!$B$98/12,0) | AQ67: =IF(42>=Inputs!$B$99,Inputs!$B$98/12,0) | AR67: =IF(43>=Inputs!$B$99,Inputs!$B$98/12,0) | AS67: =IF(44>=Inputs!$B$99,Inputs!$B$98/12,0) | AT67: =IF(45>=Inputs!$B$99,Inputs!$B$98/12,0) | AU67: =IF(46>=Inputs!$B$99,Inputs!$B$98/12,0) | AV67: =IF(47>=Inputs!$B$99,Inputs!$B$98/12,0) | AW67: =IF(48>=Inputs!$B$99,Inputs!$B$98/12,0) | AX67: =IF(49>=Inputs!$B$99,Inputs!$B$98/12,0) | AY67: =IF(50>=Inputs!$B$99,Inputs!$B$98/12,0) | AZ67: =IF(51>=Inputs!$B$99,Inputs!$B$98/12,0) | BA67: =IF(52>=Inputs!$B$99,Inputs!$B$98/12,0)
A68: Unternehmensberater | B68: =Inputs!$B$100/12 | C68: =Inputs!$B$100/12 | D68: =Inputs!$B$100/12 | E68: =Inputs!$B$100/12 | F68: =Inputs!$B$100/12 | G68: =Inputs!$B$100/12 | H68: =Inputs!$B$100/12 | I68: =Inputs!$B$100/12 | ... BA68: =Inputs!$B$100/12
A69: TOTAL PROFESSIONAL | B69: =SUM(B65:B68) | C69: =SUM(C65:C68) | D69: =SUM(D65:D68) | E69: =SUM(E65:E68) | F69: =SUM(F65:F68) | G69: =SUM(G65:G68) | H69: =SUM(H65:H68) | I69: =SUM(I65:I68) | ... BA69: =SUM(BA65:BA68)
A71: VERSICHERUNGEN & BANK
A72: D&O Versicherung | B72: =Inputs!$B$103/12 | C72: =Inputs!$B$103/12 | D72: =Inputs!$B$103/12 | E72: =Inputs!$B$103/12 | F72: =Inputs!$B$103/12 | G72: =Inputs!$B$103/12 | H72: =Inputs!$B$103/12 | I72: =Inputs!$B$103/12 | ... BA72: =Inputs!$B$103/12
A73: Betriebshaftpflicht | B73: =Inputs!$B$104/12 | C73: =Inputs!$B$104/12 | D73: =Inputs!$B$104/12 | E73: =Inputs!$B$104/12 | F73: =Inputs!$B$104/12 | G73: =Inputs!$B$104/12 | H73: =Inputs!$B$104/12 | I73: =Inputs!$B$104/12 | ... BA73: =Inputs!$B$104/12
A74: Cyber-Versicherung | B74: =Inputs!$B$105/12 | C74: =Inputs!$B$105/12 | D74: =Inputs!$B$105/12 | E74: =Inputs!$B$105/12 | F74: =Inputs!$B$105/12 | G74: =Inputs!$B$105/12 | H74: =Inputs!$B$105/12 | I74: =Inputs!$B$105/12 | ... BA74: =Inputs!$B$105/12
A75: Bankgebühren | B75: =Inputs!$B$106 | C75: =Inputs!$B$106 | D75: =Inputs!$B$106 | E75: =Inputs!$B$106 | F75: =Inputs!$B$106 | G75: =Inputs!$B$106 | H75: =Inputs!$B$106 | I75: =Inputs!$B$106 | ... BA75: =Inputs!$B$106
A76: TOTAL VERSICHERUNG & BANK | B76: =SUM(B72:B75) | C76: =SUM(C72:C75) | D76: =SUM(D72:D75) | E76: =SUM(E72:E75) | F76: =SUM(F72:F75) | G76: =SUM(G72:G75) | H76: =SUM(H72:H75) | I76: =SUM(I72:I75) | ... BA76: =SUM(BA72:BA75)
A78: MARKETING & SALES KOSTEN
A79: Paid Advertising | B79: =Inputs!$B$110*(1+Inputs!$B$111)^(1-1) | C79: =Inputs!$B$110*(1+Inputs!$B$111)^(2-1) | D79: =Inputs!$B$110*(1+Inputs!$B$111)^(3-1) | E79: =Inputs!$B$110*(1+Inputs!$B$111)^(4-1) | F79: =Inputs!$B$110*(1+Inputs!$B$111)^(5-1) | G79: =Inputs!$B$110*(1+Inputs!$B$111)^(6-1) | H79: =Inputs!$B$110*(1+Inputs!$B$111)^(7-1) | I79: =Inputs!$B$110*(1+Inputs!$B$111)^(8-1) | J79: =Inputs!$B$110*(1+Inputs!$B$111)^(9-1) | K79: =Inputs!$B$110*(1+Inputs!$B$111)^(10-1) | L79: =Inputs!$B$110*(1+Inputs!$B$111)^(11-1) | M79: =Inputs!$B$110*(1+Inputs!$B$111)^(12-1) | N79: =Inputs!$B$110*(1+Inputs!$B$111)^(13-1) | O79: =Inputs!$B$110*(1+Inputs!$B$111)^(14-1) | P79: =Inputs!$B$110*(1+Inputs!$B$111)^(15-1) | Q79: =Inputs!$B$110*(1+Inputs!$B$111)^(16-1) | R79: =Inputs!$B$110*(1+Inputs!$B$111)^(17-1) | S79: =Inputs!$B$110*(1+Inputs!$B$111)^(18-1) | T79: =Inputs!$B$110*(1+Inputs!$B$111)^(19-1) | U79: =Inputs!$B$110*(1+Inputs!$B$111)^(20-1) | V79: =Inputs!$B$110*(1+Inputs!$B$111)^(21-1) | W79: =Inputs!$B$110*(1+Inputs!$B$111)^(22-1) | X79: =Inputs!$B$110*(1+Inputs!$B$111)^(23-1) | Y79: =Inputs!$B$110*(1+Inputs!$B$111)^(24-1) | Z79: =Inputs!$B$110*(1+Inputs!$B$111)^(25-1) | AA79: =Inputs!$B$110*(1+Inputs!$B$111)^(26-1) | AB79: =Inputs!$B$110*(1+Inputs!$B$111)^(27-1) | AC79: =Inputs!$B$110*(1+Inputs!$B$111)^(28-1) | AD79: =Inputs!$B$110*(1+Inputs!$B$111)^(29-1) | AE79: =Inputs!$B$110*(1+Inputs!$B$111)^(30-1) | AF79: =Inputs!$B$110*(1+Inputs!$B$111)^(31-1) | AG79: =Inputs!$B$110*(1+Inputs!$B$111)^(32-1) | AH79: =Inputs!$B$110*(1+Inputs!$B$111)^(33-1) | AI79: =Inputs!$B$110*(1+Inputs!$B$111)^(34-1) | AJ79: =Inputs!$B$110*(1+Inputs!$B$111)^(35-1) | AK79: =Inputs!$B$110*(1+Inputs!$B$111)^(36-1) | AL79: =Inputs!$B$110*(1+Inputs!$B$111)^(37-1) | AM79: =Inputs!$B$110*(1+Inputs!$B$111)^(38-1) | AN79: =Inputs!$B$110*(1+Inputs!$B$111)^(39-1) | AO79: =Inputs!$B$110*(1+Inputs!$B$111)^(40-1) | AP79: =Inputs!$B$110*(1+Inputs!$B$111)^(41-1) | AQ79: =Inputs!$B$110*(1+Inputs!$B$111)^(42-1) | AR79: =Inputs!$B$110*(1+Inputs!$B$111)^(43-1) | AS79: =Inputs!$B$110*(1+Inputs!$B$111)^(44-1) | AT79: =Inputs!$B$110*(1+Inputs!$B$111)^(45-1) | AU79: =Inputs!$B$110*(1+Inputs!$B$111)^(46-1) | AV79: =Inputs!$B$110*(1+Inputs!$B$111)^(47-1) | AW79: =Inputs!$B$110*(1+Inputs!$B$111)^(48-1) | AX79: =Inputs!$B$110*(1+Inputs!$B$111)^(49-1) | AY79: =Inputs!$B$110*(1+Inputs!$B$111)^(50-1) | AZ79: =Inputs!$B$110*(1+Inputs!$B$111)^(51-1) | BA79: =Inputs!$B$110*(1+Inputs!$B$111)^(52-1)
A80: Content & SEO | B80: =Inputs!$B$112 | C80: =Inputs!$B$112 | D80: =Inputs!$B$112 | E80: =Inputs!$B$112 | F80: =Inputs!$B$112 | G80: =Inputs!$B$112 | H80: =Inputs!$B$112 | I80: =Inputs!$B$112 | ... BA80: =Inputs!$B$112
A81: Events & Messen | B81: =IF(COLUMNS($B$81:B81)>=Inputs!$B$17,Inputs!$B$116/12,IF(COLUMNS($B$81:B81)>=Inputs!$B$15,Inputs!$B$115/12,IF(COLUMNS($B$81:B81)>=Inputs!$B$13,Inputs!$B$114/12,Inputs!$B$113/12))) | C81: =IF(COLUMNS($B$81:C81)>=Inputs!$B$17,Inputs!$B$116/12,IF(COLUMNS($B$81:C81)>=Inputs!$B$15,Inputs!$B$115/12,IF(COLUMNS($B$81:C81)>=Inputs!$B$13,Inputs!$B$114/12,Inputs!$B$113/12))) | D81: =IF(COLUMNS($B$81:D81)>=Inputs!$B$17,Inputs!$B$116/12,IF(COLUMNS($B$81:D81)>=Inputs!$B$15,Inputs!$B$115/12,IF(COLUMNS($B$81:D81)>=Inputs!$B$13,Inputs!$B$114/12,Inputs!$B$113/12))) | E81: =IF(COLUMNS($B$81:E81)>=Inputs!$B$17,Inputs!$B$116/12,IF(COLUMNS($B$81:E81)>=Inputs!$B$15,Inputs!$B$115/12,IF(COLUMNS($B$81:E81)>=Inputs!$B$13,Inputs!$B$114/12,Inputs!$B$113/12))) | F81: =IF(COLUMNS($B$81:F81)>=Inputs!$B$17,Inputs!$B$116/12,IF(COLUMNS($B$81:F81)>=Inputs!$B$15,Inputs!$B$115/12,IF(COLUMNS($B$81:F81)>=Inputs!$B$13,Inputs!$B$114/12,Inputs!$B$113/12))) | G81: =IF(COLUMNS($B$81:G81)>=Inputs!$B$17,Inputs!$B$116/12,IF(COLUMNS($B$81:G81)>=Inputs!$B$15,Inputs!$B$115/12,IF(COLUMNS($B$81:G81)>=Inputs!$B$13,Inputs!$B$114/12,Inputs!$B$113/12))) | H81: =IF(COLUMNS($B$81:H81)>=Inputs!$B$17,Inputs!$B$116/12,IF(COLUMNS($B$81:H81)>=Inputs!$B$15,Inputs!$B$115/12,IF(COLUMNS($B$81:H81)>=Inputs!$B$13,Inputs!$B$114/12,Inputs!$B$113/12))) | I81: =IF(COLUMNS($B$81:I81)>=Inputs!$B$17,Inputs!$B$116/12,IF(COLUMNS($B$81:I81)>=Inputs!$B$15,Inputs!$B$115/12,IF(COLUMNS($B$81:I81)>=Inputs!$B$13,Inputs!$B$114/12,Inputs!$B$113/12))) | ... BA81: =IF(COLUMNS($B$81:BA81)>=Inputs!$B$17,Inputs!$B$116/12,IF(COLUMNS($B$81:BA81)>=Inputs!$B$15,Inputs!$B$115/12,IF(COLUMNS($B$81:BA81)>=Inputs!$B$13,Inputs!$B$114/12,Inputs!$B$113/12)))
A82: Sales Tools | B82: =Inputs!$B$118 | C82: =Inputs!$B$118 | D82: =Inputs!$B$118 | E82: =Inputs!$B$118 | F82: =Inputs!$B$118 | G82: =Inputs!$B$118 | H82: =Inputs!$B$118 | I82: =Inputs!$B$118 | ... BA82: =Inputs!$B$118
A83: Sales Provisionen | B83: =Revenue!B26/12*Inputs!$B$119 | C83: =Revenue!C26/12*Inputs!$B$119 | D83: =Revenue!D26/12*Inputs!$B$119 | E83: =Revenue!E26/12*Inputs!$B$119 | F83: =Revenue!F26/12*Inputs!$B$119 | G83: =Revenue!G26/12*Inputs!$B$119 | H83: =Revenue!H26/12*Inputs!$B$119 | I83: =Revenue!I26/12*Inputs!$B$119 | ... BA83: =Revenue!BA26/12*Inputs!$B$119
A84: Reisekosten Sales | B84: =(B14+B15+B16)*Inputs!$B$120 | C84: =(C14+C15+C16)*Inputs!$B$120 | D84: =(D14+D15+D16)*Inputs!$B$120 | E84: =(E14+E15+E16)*Inputs!$B$120 | F84: =(F14+F15+F16)*Inputs!$B$120 | G84: =(G14+G15+G16)*Inputs!$B$120 | H84: =(H14+H15+H16)*Inputs!$B$120 | I84: =(I14+I15+I16)*Inputs!$B$120 | ... BA84: =(BA14+BA15+BA16)*Inputs!$B$120
A85: TOTAL MARKETING & SALES | B85: =SUM(B79:B84) | C85: =SUM(C79:C84) | D85: =SUM(D79:D84) | E85: =SUM(E79:E84) | F85: =SUM(F79:F84) | G85: =SUM(G79:G84) | H85: =SUM(H79:H84) | I85: =SUM(I79:I84) | ... BA85: =SUM(BA79:BA84)
A87: SONSTIGE KOSTEN
A88: Reisekosten allgemein | B88: =B23*Inputs!$B$123/12 | C88: =C23*Inputs!$B$123/12 | D88: =D23*Inputs!$B$123/12 | E88: =E23*Inputs!$B$123/12 | F88: =F23*Inputs!$B$123/12 | G88: =G23*Inputs!$B$123/12 | H88: =H23*Inputs!$B$123/12 | I88: =I23*Inputs!$B$123/12 | ... BA88: =BA23*Inputs!$B$123/12
A89: Weiterbildung | B89: =B23*Inputs!$B$124/12 | C89: =C23*Inputs!$B$124/12 | D89: =D23*Inputs!$B$124/12 | E89: =E23*Inputs!$B$124/12 | F89: =F23*Inputs!$B$124/12 | G89: =G23*Inputs!$B$124/12 | H89: =H23*Inputs!$B$124/12 | I89: =I23*Inputs!$B$124/12 | ... BA89: =BA23*Inputs!$B$124/12
A90: Team Events | B90: =B23*Inputs!$B$125/12 | C90: =C23*Inputs!$B$125/12 | D90: =D23*Inputs!$B$125/12 | E90: =E23*Inputs!$B$125/12 | F90: =F23*Inputs!$B$125/12 | G90: =G23*Inputs!$B$125/12 | H90: =H23*Inputs!$B$125/12 | I90: =I23*Inputs!$B$125/12 | ... BA90: =BA23*Inputs!$B$125/12
A91: Hardware (neue MA) | B91: =B23*(Inputs!$B$80+Inputs!$B$81) | C91: =MAX(0,C23-B23)*(Inputs!$B$80+Inputs!$B$81) | D91: =MAX(0,D23-C23)*(Inputs!$B$80+Inputs!$B$81) | E91: =MAX(0,E23-D23)*(Inputs!$B$80+Inputs!$B$81) | F91: =MAX(0,F23-E23)*(Inputs!$B$80+Inputs!$B$81) | G91: =MAX(0,G23-F23)*(Inputs!$B$80+Inputs!$B$81) | H91: =MAX(0,H23-G23)*(Inputs!$B$80+Inputs!$B$81) | I91: =MAX(0,I23-H23)*(Inputs!$B$80+Inputs!$B$81) | J91: =MAX(0,J23-I23)*(Inputs!$B$80+Inputs!$B$81) | ... BA91: =MAX(0,BA23-AZ23)*(Inputs!$B$80+Inputs!$B$81)
A92: Sonstige IT-Ausstattung | B92: =Inputs!$B$83/12 | C92: =Inputs!$B$83/12 | D92: =Inputs!$B$83/12 | E92: =Inputs!$B$83/12 | F92: =Inputs!$B$83/12 | G92: =Inputs!$B$83/12 | H92: =Inputs!$B$83/12 | I92: =Inputs!$B$83/12 | ... BA92: =Inputs!$B$83/12
A93: TOTAL SONSTIGE | B93: =SUM(B88:B92) | C93: =SUM(C88:C92) | D93: =SUM(D88:D92) | E93: =SUM(E88:E92) | F93: =SUM(F88:F92) | G93: =SUM(G88:G92) | H93: =SUM(H88:H92) | I93: =SUM(I88:I92) | ... BA93: =SUM(BA88:BA92)
A95: PAYMENT PROCESSING
A96: Payment Processing Fees | B96: =Revenue!B23*Inputs!$B$107 | C96: =Revenue!C23*Inputs!$B$107 | D96: =Revenue!D23*Inputs!$B$107 | E96: =Revenue!E23*Inputs!$B$107 | F96: =Revenue!F23*Inputs!$B$107 | G96: =Revenue!G23*Inputs!$B$107 | H96: =Revenue!H23*Inputs!$B$107 | I96: =Revenue!I23*Inputs!$B$107 | ... BA96: =Revenue!BA23*Inputs!$B$107
A98: Puffer/Unvorhergesehenes | B98: =(B46+B55+B62+B69+B76+B85+B93)*Inputs!$B$126 | C98: =(C46+C55+C62+C69+C76+C85+C93)*Inputs!$B$126 | D98: =(D46+D55+D62+D69+D76+D85+D93)*Inputs!$B$126 | E98: =(E46+E55+E62+E69+E76+E85+E93)*Inputs!$B$126 | F98: =(F46+F55+F62+F69+F76+F85+F93)*Inputs!$B$126 | G98: =(G46+G55+G62+G69+G76+G85+G93)*Inputs!$B$126 | H98: =(H46+H55+H62+H69+H76+H85+H93)*Inputs!$B$126 | I98: =(I46+I55+I62+I69+I76+I85+I93)*Inputs!$B$126 | ... BA98: =(BA46+BA55+BA62+BA69+BA76+BA85+BA93)*Inputs!$B$126
A100: TOTAL KOSTEN (exkl. COGS) | B100: =B46+B55+B62+B69+B76+B85+B93+B98 | C100: =C46+C55+C62+C69+C76+C85+C93+C98 | D100: =D46+D55+D62+D69+D76+D85+D93+D98 | E100: =E46+E55+E62+E69+E76+E85+E93+E98 | F100: =F46+F55+F62+F69+F76+F85+F93+F98 | G100: =G46+G55+G62+G69+G76+G85+G93+G98 | H100: =H46+H55+H62+H69+H76+H85+H93+H98 | I100: =I46+I55+I62+I69+I76+I85+I93+I98 | ... BA100: =BA46+BA55+BA62+BA69+BA76+BA85+BA93+BA98

Sheet Balance Sheet
A1: BILANZ (Vereinfacht)
B2: 46113 | C2: 46143 | D2: 46174 | E2: 46204 | F2: 46235 | G2: 46266 | H2: 46296 | I2: 46327 | J2: 46357 | K2: 46388 | L2: 46419 | M2: 46447 | N2: 46478 | O2: 46508 | P2: 46539 | Q2: 46569 | R2: 46600 | S2: 46631 | T2: 46661 | U2: 46692 | V2: 46722 | W2: 46753 | X2: 46784 | Y2: 46813 | Z2: 46844 | AA2: 46874 | AB2: 46905 | AC2: 46935 | AD2: 46966 | AE2: 46997 | AF2: 47027 | AG2: 47058 | AH2: 47088 | AI2: 47119 | AJ2: 47150 | AK2: 47178 | AL2: 47209 | AM2: 47239 | AN2: 47270 | AO2: 47300 | AP2: 47331 | AQ2: 47362 | AR2: 47392 | AS2: 47423 | AT2: 47453 | AU2: 47484 | AV2: 47515 | AW2: 47543 | AX2: 47574 | AY2: 47604 | AZ2: 47635 | BA2: 47665
A3: Startup-Phase | B3: Ideation | C3: Ideation | D3: Ideation | E3: Ideation | F3: Pre-Seed | G3: Pre-Seed | H3: Pre-Seed | I3: Pre-Seed | J3: Pre-Seed | K3: Pre-Seed | L3: Pre-Seed | M3: Pre-Seed | N3: Pre-Seed | O3: Pre-Seed | P3: Pre-Seed | Q3: Pre-Seed | R3: Seed | S3: Seed | T3: Seed | U3: Seed | V3: Seed | W3: Seed | X3: Seed | Y3: Seed | Z3: Seed | AA3: Seed | AB3: Seed | AC3: Seed | AD3: Series A | AE3: Series A | AF3: Series A | AG3: Series A | AH3: Series A | AI3: Series A | AJ3: Series A | AK3: Series A | AL3: Series A | AM3: Series A | AN3: Series A | AO3: Series A | AP3: Series B | AQ3: Series B | AR3: Series B | AS3: Series B | AT3: Series B | AU3: Series B | AV3: Series B | AW3: Series B | AX3: Series B | AY3: Series B | AZ3: Series B | BA3: Series B
A4: Position | B4: M1 | C4: M2 | D4: M3 | E4: M4 | F4: M5 | G4: M6 | H4: M7 | I4: M8 | J4: M9 | K4: M10 | L4: M11 | M4: M12 | N4: M13 | O4: M14 | P4: M15 | Q4: M16 | R4: M17 | S4: M18 | T4: M19 | U4: M20 | V4: M21 | W4: M22 | X4: M23 | Y4: M24 | Z4: M25 | AA4: M26 | AB4: M27 | AC4: M28 | AD4: M29 | AE4: M30 | AF4: M31 | AG4: M32 | AH4: M33 | AI4: M34 | AJ4: M35 | AK4: M36 | AL4: M37 | AM4: M38 | AN4: M39 | AO4: M40 | AP4: M41 | AQ4: M42 | AR4: M43 | AS4: M44 | AT4: M45 | AU4: M46 | AV4: M47 | AW4: M48 | AX4: M49 | AY4: M50 | AZ4: M51 | BA4: M52
A5: AKTIVA (ASSETS)
A6: Cash & Cash Equivalents | B6: ='Cash Flow'!B23 | C6: ='Cash Flow'!C23 | D6: ='Cash Flow'!D23 | E6: ='Cash Flow'!E23 | F6: ='Cash Flow'!F23 | G6: ='Cash Flow'!G23 | H6: ='Cash Flow'!H23 | I6: ='Cash Flow'!I23 | ... BA6: ='Cash Flow'!BA23
A7: Accounts Receivable | B7: ='P&L'!B8 | C7: ='P&L'!C8 | D7: ='P&L'!D8 | E7: ='P&L'!E8 | F7: ='P&L'!F8 | G7: ='P&L'!G8 | H7: ='P&L'!H8 | I7: ='P&L'!I8 | ... BA7: ='P&L'!BA8
A8: Prepaid Expenses | B8: 0 | C8: 0 | D8: 0 | E8: 0 | F8: 0 | G8: 0 | H8: 0 | I8: 0 | J8: 0 | K8: 0 | L8: 0 | M8: 0 | N8: 0 | O8: 0 | P8: 0 | Q8: 0 | R8: 0 | S8: 0 | T8: 0 | U8: 0 | V8: 0 | W8: 0 | X8: 0 | Y8: 0 | Z8: 0 | AA8: 0 | AB8: 0 | AC8: 0 | AD8: 0 | AE8: 0 | AF8: 0 | AG8: 0 | AH8: 0 | AI8: 0 | AJ8: 0 | AK8: 0 | AL8: 0 | AM8: 0 | AN8: 0 | AO8: 0 | AP8: 0 | AQ8: 0 | AR8: 0 | AS8: 0 | AT8: 0 | AU8: 0 | AV8: 0 | AW8: 0 | AX8: 0 | AY8: 0 | AZ8: 0 | BA8: 0
A9: Property & Equipment (net) | B9: =Costs!B91+Inputs!$B$91 | C9: =B9+Costs!C91-'P&L'!C32 | D9: =C9+Costs!D91-'P&L'!D32 | E9: =D9+Costs!E91-'P&L'!E32 | F9: =E9+Costs!F91-'P&L'!F32 | G9: =F9+Costs!G91-'P&L'!G32 | H9: =G9+Costs!H91-'P&L'!H32 | I9: =H9+Costs!I91-'P&L'!I32 | J9: =I9+Costs!J91-'P&L'!J32 | ... BA9: =AZ9+Costs!BA91-'P&L'!BA32
A10: TOTAL ASSETS | B10: =SUM(B6:B9) | C10: =SUM(C6:C9) | D10: =SUM(D6:D9) | E10: =SUM(E6:E9) | F10: =SUM(F6:F9) | G10: =SUM(G6:G9) | H10: =SUM(H6:H9) | I10: =SUM(I6:I9) | ... BA10: =SUM(BA6:BA9)
A12: PASSIVA (LIABILITIES)
A13: Accounts Payable | B13: =Costs!B100*0.1 | C13: =Costs!C100*0.1 | D13: =Costs!D100*0.1 | E13: =Costs!E100*0.1 | F13: =Costs!F100*0.1 | G13: =Costs!G100*0.1 | H13: =Costs!H100*0.1 | I13: =Costs!I100*0.1 | ... BA13: =Costs!BA100*0.1
A14: Accrued Expenses | B14: =Costs!B46*0.08 | C14: =Costs!C46*0.08 | D14: =Costs!D46*0.08 | E14: =Costs!E46*0.08 | F14: =Costs!F46*0.08 | G14: =Costs!G46*0.08 | H14: =Costs!H46*0.08 | I14: =Costs!I46*0.08 | ... BA14: =Costs!BA46*0.08
A15: Deferred Revenue | B15: ='P&L'!B5 | C15: ='P&L'!C5 | D15: ='P&L'!D5 | E15: ='P&L'!E5 | F15: ='P&L'!F5 | G15: ='P&L'!G5 | H15: ='P&L'!H5 | I15: ='P&L'!I5 | ... BA15: ='P&L'!BA5
A16: TOTAL LIABILITIES | B16: =SUM(B13:B15) | C16: =SUM(C13:C15) | D16: =SUM(D13:D15) | E16: =SUM(E13:E15) | F16: =SUM(F13:F15) | G16: =SUM(G13:G15) | H16: =SUM(H13:H15) | I16: =SUM(I13:I15) | ... BA16: =SUM(BA13:BA15)
A18: EIGENKAPITAL (EQUITY)
A19: Share Capital | B19: 25000 | C19: 25000 | D19: 25000 | E19: 25000 | F19: 25000 | G19: 25000 | H19: 25000 | I19: 25000 | J19: 25000 | K19: 25000 | L19: 25000 | M19: 25000 | N19: 25000 | O19: 25000 | P19: 25000 | Q19: 25000 | R19: 25000 | S19: 25000 | T19: 25000 | U19: 25000 | V19: 25000 | W19: 25000 | X19: 25000 | Y19: 25000 | Z19: 25000 | AA19: 25000 | AB19: 25000 | AC19: 25000 | AD19: 25000 | AE19: 25000 | AF19: 25000 | AG19: 25000 | AH19: 25000 | AI19: 25000 | AJ19: 25000 | AK19: 25000 | AL19: 25000 | AM19: 25000 | AN19: 25000 | AO19: 25000 | AP19: 25000 | AQ19: 25000 | AR19: 25000 | AS19: 25000 | AT19: 25000 | AU19: 25000 | AV19: 25000 | AW19: 25000 | AX19: 25000 | AY19: 25000 | AZ19: 25000 | BA19: 25000
A20: Additional Paid-in Capital | B20: =IF(1=Inputs!$B$11,Inputs!$B$10,0)+IF(1=Inputs!$B$13,Inputs!$B$12,0)+IF(1=Inputs!$B$15,Inputs!$B$14,0)+IF(1=Inputs!$B$17,Inputs!$B$16,0) | C20: =B20+IF(2=Inputs!$B$11,Inputs!$B$10,0)+IF(2=Inputs!$B$13,Inputs!$B$12,0)+IF(2=Inputs!$B$15,Inputs!$B$14,0)+IF(2=Inputs!$B$17,Inputs!$B$16,0) | D20: =C20+IF(3=Inputs!$B$11,Inputs!$B$10,0)+IF(3=Inputs!$B$13,Inputs!$B$12,0)+IF(3=Inputs!$B$15,Inputs!$B$14,0)+IF(3=Inputs!$B$17,Inputs!$B$16,0) | E20: =D20+IF(4=Inputs!$B$11,Inputs!$B$10,0)+IF(4=Inputs!$B$13,Inputs!$B$12,0)+IF(4=Inputs!$B$15,Inputs!$B$14,0)+IF(4=Inputs!$B$17,Inputs!$B$16,0) | F20: =E20+IF(5=Inputs!$B$11,Inputs!$B$10,0)+IF(5=Inputs!$B$13,Inputs!$B$12,0)+IF(5=Inputs!$B$15,Inputs!$B$14,0)+IF(5=Inputs!$B$17,Inputs!$B$16,0) | G20: =F20+IF(6=Inputs!$B$11,Inputs!$B$10,0)+IF(6=Inputs!$B$13,Inputs!$B$12,0)+IF(6=Inputs!$B$15,Inputs!$B$14,0)+IF(6=Inputs!$B$17,Inputs!$B$16,0) | H20: =G20+IF(7=Inputs!$B$11,Inputs!$B$10,0)+IF(7=Inputs!$B$13,Inputs!$B$12,0)+IF(7=Inputs!$B$15,Inputs!$B$14,0)+IF(7=Inputs!$B$17,Inputs!$B$16,0) | I20: =H20+IF(8=Inputs!$B$11,Inputs!$B$10,0)+IF(8=Inputs!$B$13,Inputs!$B$12,0)+IF(8=Inputs!$B$15,Inputs!$B$14,0)+IF(8=Inputs!$B$17,Inputs!$B$16,0) | J20: =I20+IF(9=Inputs!$B$11,Inputs!$B$10,0)+IF(9=Inputs!$B$13,Inputs!$B$12,0)+IF(9=Inputs!$B$15,Inputs!$B$14,0)+IF(9=Inputs!$B$17,Inputs!$B$16,0) | K20: =J20+IF(10=Inputs!$B$11,Inputs!$B$10,0)+IF(10=Inputs!$B$13,Inputs!$B$12,0)+IF(10=Inputs!$B$15,Inputs!$B$14,0)+IF(10=Inputs!$B$17,Inputs!$B$16,0) | L20: =K20+IF(11=Inputs!$B$11,Inputs!$B$10,0)+IF(11=Inputs!$B$13,Inputs!$B$12,0)+IF(11=Inputs!$B$15,Inputs!$B$14,0)+IF(11=Inputs!$B$17,Inputs!$B$16,0) | M20: =L20+IF(12=Inputs!$B$11,Inputs!$B$10,0)+IF(12=Inputs!$B$13,Inputs!$B$12,0)+IF(12=Inputs!$B$15,Inputs!$B$14,0)+IF(12=Inputs!$B$17,Inputs!$B$16,0) | N20: =M20+IF(13=Inputs!$B$11,Inputs!$B$10,0)+IF(13=Inputs!$B$13,Inputs!$B$12,0)+IF(13=Inputs!$B$15,Inputs!$B$14,0)+IF(13=Inputs!$B$17,Inputs!$B$16,0) | O20: =N20+IF(14=Inputs!$B$11,Inputs!$B$10,0)+IF(14=Inputs!$B$13,Inputs!$B$12,0)+IF(14=Inputs!$B$15,Inputs!$B$14,0)+IF(14=Inputs!$B$17,Inputs!$B$16,0) | P20: =O20+IF(15=Inputs!$B$11,Inputs!$B$10,0)+IF(15=Inputs!$B$13,Inputs!$B$12,0)+IF(15=Inputs!$B$15,Inputs!$B$14,0)+IF(15=Inputs!$B$17,Inputs!$B$16,0) | Q20: =P20+IF(16=Inputs!$B$11,Inputs!$B$10,0)+IF(16=Inputs!$B$13,Inputs!$B$12,0)+IF(16=Inputs!$B$15,Inputs!$B$14,0)+IF(16=Inputs!$B$17,Inputs!$B$16,0) | R20: =Q20+IF(17=Inputs!$B$11,Inputs!$B$10,0)+IF(17=Inputs!$B$13,Inputs!$B$12,0)+IF(17=Inputs!$B$15,Inputs!$B$14,0)+IF(17=Inputs!$B$17,Inputs!$B$16,0) | S20: =R20+IF(18=Inputs!$B$11,Inputs!$B$10,0)+IF(18=Inputs!$B$13,Inputs!$B$12,0)+IF(18=Inputs!$B$15,Inputs!$B$14,0)+IF(18=Inputs!$B$17,Inputs!$B$16,0) | T20: =S20+IF(19=Inputs!$B$11,Inputs!$B$10,0)+IF(19=Inputs!$B$13,Inputs!$B$12,0)+IF(19=Inputs!$B$15,Inputs!$B$14,0)+IF(19=Inputs!$B$17,Inputs!$B$16,0) | U20: =T20+IF(20=Inputs!$B$11,Inputs!$B$10,0)+IF(20=Inputs!$B$13,Inputs!$B$12,0)+IF(20=Inputs!$B$15,Inputs!$B$14,0)+IF(20=Inputs!$B$17,Inputs!$B$16,0) | V20: =U20+IF(21=Inputs!$B$11,Inputs!$B$10,0)+IF(21=Inputs!$B$13,Inputs!$B$12,0)+IF(21=Inputs!$B$15,Inputs!$B$14,0)+IF(21=Inputs!$B$17,Inputs!$B$16,0) | W20: =V20+IF(22=Inputs!$B$11,Inputs!$B$10,0)+IF(22=Inputs!$B$13,Inputs!$B$12,0)+IF(22=Inputs!$B$15,Inputs!$B$14,0)+IF(22=Inputs!$B$17,Inputs!$B$16,0) | X20: =W20+IF(23=Inputs!$B$11,Inputs!$B$10,0)+IF(23=Inputs!$B$13,Inputs!$B$12,0)+IF(23=Inputs!$B$15,Inputs!$B$14,0)+IF(23=Inputs!$B$17,Inputs!$B$16,0) | Y20: =X20+IF(24=Inputs!$B$11,Inputs!$B$10,0)+IF(24=Inputs!$B$13,Inputs!$B$12,0)+IF(24=Inputs!$B$15,Inputs!$B$14,0)+IF(24=Inputs!$B$17,Inputs!$B$16,0) | Z20: =Y20+IF(25=Inputs!$B$11,Inputs!$B$10,0)+IF(25=Inputs!$B$13,Inputs!$B$12,0)+IF(25=Inputs!$B$15,Inputs!$B$14,0)+IF(25=Inputs!$B$17,Inputs!$B$16,0) | AA20: =Z20+IF(26=Inputs!$B$11,Inputs!$B$10,0)+IF(26=Inputs!$B$13,Inputs!$B$12,0)+IF(26=Inputs!$B$15,Inputs!$B$14,0)+IF(26=Inputs!$B$17,Inputs!$B$16,0) | AB20: =AA20+IF(27=Inputs!$B$11,Inputs!$B$10,0)+IF(27=Inputs!$B$13,Inputs!$B$12,0)+IF(27=Inputs!$B$15,Inputs!$B$14,0)+IF(27=Inputs!$B$17,Inputs!$B$16,0) | AC20: =AB20+IF(28=Inputs!$B$11,Inputs!$B$10,0)+IF(28=Inputs!$B$13,Inputs!$B$12,0)+IF(28=Inputs!$B$15,Inputs!$B$14,0)+IF(28=Inputs!$B$17,Inputs!$B$16,0) | AD20: =AC20+IF(29=Inputs!$B$11,Inputs!$B$10,0)+IF(29=Inputs!$B$13,Inputs!$B$12,0)+IF(29=Inputs!$B$15,Inputs!$B$14,0)+IF(29=Inputs!$B$17,Inputs!$B$16,0) | AE20: =AD20+IF(30=Inputs!$B$11,Inputs!$B$10,0)+IF(30=Inputs!$B$13,Inputs!$B$12,0)+IF(30=Inputs!$B$15,Inputs!$B$14,0)+IF(30=Inputs!$B$17,Inputs!$B$16,0) | AF20: =AE20+IF(31=Inputs!$B$11,Inputs!$B$10,0)+IF(31=Inputs!$B$13,Inputs!$B$12,0)+IF(31=Inputs!$B$15,Inputs!$B$14,0)+IF(31=Inputs!$B$17,Inputs!$B$16,0) | AG20: =AF20+IF(32=Inputs!$B$11,Inputs!$B$10,0)+IF(32=Inputs!$B$13,Inputs!$B$12,0)+IF(32=Inputs!$B$15,Inputs!$B$14,0)+IF(32=Inputs!$B$17,Inputs!$B$16,0) | AH20: =AG20+IF(33=Inputs!$B$11,Inputs!$B$10,0)+IF(33=Inputs!$B$13,Inputs!$B$12,0)+IF(33=Inputs!$B$15,Inputs!$B$14,0)+IF(33=Inputs!$B$17,Inputs!$B$16,0) | AI20: =AH20+IF(34=Inputs!$B$11,Inputs!$B$10,0)+IF(34=Inputs!$B$13,Inputs!$B$12,0)+IF(34=Inputs!$B$15,Inputs!$B$14,0)+IF(34=Inputs!$B$17,Inputs!$B$16,0) | AJ20: =AI20+IF(35=Inputs!$B$11,Inputs!$B$10,0)+IF(35=Inputs!$B$13,Inputs!$B$12,0)+IF(35=Inputs!$B$15,Inputs!$B$14,0)+IF(35=Inputs!$B$17,Inputs!$B$16,0) | AK20: =AJ20+IF(36=Inputs!$B$11,Inputs!$B$10,0)+IF(36=Inputs!$B$13,Inputs!$B$12,0)+IF(36=Inputs!$B$15,Inputs!$B$14,0)+IF(36=Inputs!$B$17,Inputs!$B$16,0) | AL20: =AK20+IF(37=Inputs!$B$11,Inputs!$B$10,0)+IF(37=Inputs!$B$13,Inputs!$B$12,0)+IF(37=Inputs!$B$15,Inputs!$B$14,0)+IF(37=Inputs!$B$17,Inputs!$B$16,0) | AM20: =AL20+IF(38=Inputs!$B$11,Inputs!$B$10,0)+IF(38=Inputs!$B$13,Inputs!$B$12,0)+IF(38=Inputs!$B$15,Inputs!$B$14,0)+IF(38=Inputs!$B$17,Inputs!$B$16,0) | AN20: =AM20+IF(39=Inputs!$B$11,Inputs!$B$10,0)+IF(39=Inputs!$B$13,Inputs!$B$12,0)+IF(39=Inputs!$B$15,Inputs!$B$14,0)+IF(39=Inputs!$B$17,Inputs!$B$16,0) | AO20: =AN20+IF(40=Inputs!$B$11,Inputs!$B$10,0)+IF(40=Inputs!$B$13,Inputs!$B$12,0)+IF(40=Inputs!$B$15,Inputs!$B$14,0)+IF(40=Inputs!$B$17,Inputs!$B$16,0) | AP20: =AO20+IF(41=Inputs!$B$11,Inputs!$B$10,0)+IF(41=Inputs!$B$13,Inputs!$B$12,0)+IF(41=Inputs!$B$15,Inputs!$B$14,0)+IF(41=Inputs!$B$17,Inputs!$B$16,0) | AQ20: =AP20+IF(42=Inputs!$B$11,Inputs!$B$10,0)+IF(42=Inputs!$B$13,Inputs!$B$12,0)+IF(42=Inputs!$B$15,Inputs!$B$14,0)+IF(42=Inputs!$B$17,Inputs!$B$16,0) | AR20: =AQ20+IF(43=Inputs!$B$11,Inputs!$B$10,0)+IF(43=Inputs!$B$13,Inputs!$B$12,0)+IF(43=Inputs!$B$15,Inputs!$B$14,0)+IF(43=Inputs!$B$17,Inputs!$B$16,0) | AS20: =AR20+IF(44=Inputs!$B$11,Inputs!$B$10,0)+IF(44=Inputs!$B$13,Inputs!$B$12,0)+IF(44=Inputs!$B$15,Inputs!$B$14,0)+IF(44=Inputs!$B$17,Inputs!$B$16,0) | AT20: =AS20+IF(45=Inputs!$B$11,Inputs!$B$10,0)+IF(45=Inputs!$B$13,Inputs!$B$12,0)+IF(45=Inputs!$B$15,Inputs!$B$14,0)+IF(45=Inputs!$B$17,Inputs!$B$16,0) | AU20: =AT20+IF(46=Inputs!$B$11,Inputs!$B$10,0)+IF(46=Inputs!$B$13,Inputs!$B$12,0)+IF(46=Inputs!$B$15,Inputs!$B$14,0)+IF(46=Inputs!$B$17,Inputs!$B$16,0) | AV20: =AU20+IF(47=Inputs!$B$11,Inputs!$B$10,0)+IF(47=Inputs!$B$13,Inputs!$B$12,0)+IF(47=Inputs!$B$15,Inputs!$B$14,0)+IF(47=Inputs!$B$17,Inputs!$B$16,0) | AW20: =AV20+IF(48=Inputs!$B$11,Inputs!$B$10,0)+IF(48=Inputs!$B$13,Inputs!$B$12,0)+IF(48=Inputs!$B$15,Inputs!$B$14,0)+IF(48=Inputs!$B$17,Inputs!$B$16,0) | AX20: =AW20+IF(49=Inputs!$B$11,Inputs!$B$10,0)+IF(49=Inputs!$B$13,Inputs!$B$12,0)+IF(49=Inputs!$B$15,Inputs!$B$14,0)+IF(49=Inputs!$B$17,Inputs!$B$16,0) | AY20: =AX20+IF(50=Inputs!$B$11,Inputs!$B$10,0)+IF(50=Inputs!$B$13,Inputs!$B$12,0)+IF(50=Inputs!$B$15,Inputs!$B$14,0)+IF(50=Inputs!$B$17,Inputs!$B$16,0) | AZ20: =AY20+IF(51=Inputs!$B$11,Inputs!$B$10,0)+IF(51=Inputs!$B$13,Inputs!$B$12,0)+IF(51=Inputs!$B$15,Inputs!$B$14,0)+IF(51=Inputs!$B$17,Inputs!$B$16,0) | BA20: =AZ20+IF(52=Inputs!$B$11,Inputs!$B$10,0)+IF(52=Inputs!$B$13,Inputs!$B$12,0)+IF(52=Inputs!$B$15,Inputs!$B$14,0)+IF(52=Inputs!$B$17,Inputs!$B$16,0)
A21: Retained Earnings | B21: ='P&L'!B39 | C21: =B21+'P&L'!C39 | D21: =C21+'P&L'!D39 | E21: =D21+'P&L'!E39 | F21: =E21+'P&L'!F39 | G21: =F21+'P&L'!G39 | H21: =G21+'P&L'!H39 | I21: =H21+'P&L'!I39 | J21: =I21+'P&L'!J39 | ... BA21: =AZ21+'P&L'!BA39
A22: TOTAL EQUITY | B22: =B19+B20+B21 | C22: =C19+C20+C21 | D22: =D19+D20+D21 | E22: =E19+E20+E21 | F22: =F19+F20+F21 | G22: =G19+G20+G21 | H22: =H19+H20+H21 | I22: =I19+I20+I21 | ... BA22: =BA19+BA20+BA21
A24: TOTAL LIABILITIES + EQUITY | B24: =B16+B22 | C24: =C16+C22 | D24: =D16+D22 | E24: =E16+E22 | F24: =F16+F22 | G24: =G16+G22 | H24: =H16+H22 | I24: =I16+I22 | ... BA24: =BA16+BA22
A25: Check (Assets - L&E = 0) | B25: =B10-B24 | C25: =C10-C24 | D25: =D10-D24 | E25: =E10-E24 | F25: =F10-F24 | G25: =G10-G24 | H25: =H10-H24 | I25: =I10-I24 | ... BA25: =BA10-BA24

Sheet Cash Flow
A1: KAPITALFLUSSRECHNUNG (CASH FLOW)
B2: 46113 | C2: 46143 | D2: 46174 | E2: 46204 | F2: 46235 | G2: 46266 | H2: 46296 | I2: 46327 | J2: 46357 | K2: 46388 | L2: 46419 | M2: 46447 | N2: 46478 | O2: 46508 | P2: 46539 | Q2: 46569 | R2: 46600 | S2: 46631 | T2: 46661 | U2: 46692 | V2: 46722 | W2: 46753 | X2: 46784 | Y2: 46813 | Z2: 46844 | AA2: 46874 | AB2: 46905 | AC2: 46935 | AD2: 46966 | AE2: 46997 | AF2: 47027 | AG2: 47058 | AH2: 47088 | AI2: 47119 | AJ2: 47150 | AK2: 47178 | AL2: 47209 | AM2: 47239 | AN2: 47270 | AO2: 47300 | AP2: 47331 | AQ2: 47362 | AR2: 47392 | AS2: 47423 | AT2: 47453 | AU2: 47484 | AV2: 47515 | AW2: 47543 | AX2: 47574 | AY2: 47604 | AZ2: 47635 | BA2: 47665
A3: Startup-Phase | B3: Ideation | C3: Ideation | D3: Ideation | E3: Ideation | F3: Pre-Seed | G3: Pre-Seed | H3: Pre-Seed | I3: Pre-Seed | J3: Pre-Seed | K3: Pre-Seed | L3: Pre-Seed | M3: Pre-Seed | N3: Pre-Seed | O3: Pre-Seed | P3: Pre-Seed | Q3: Pre-Seed | R3: Seed | S3: Seed | T3: Seed | U3: Seed | V3: Seed | W3: Seed | X3: Seed | Y3: Seed | Z3: Seed | AA3: Seed | AB3: Seed | AC3: Seed | AD3: Series A | AE3: Series A | AF3: Series A | AG3: Series A | AH3: Series A | AI3: Series A | AJ3: Series A | AK3: Series A | AL3: Series A | AM3: Series A | AN3: Series A | AO3: Series A | AP3: Series B | AQ3: Series B | AR3: Series B | AS3: Series B | AT3: Series B | AU3: Series B | AV3: Series B | AW3: Series B | AX3: Series B | AY3: Series B | AZ3: Series B | BA3: Series B
A4: Position | B4: M1 | C4: M2 | D4: M3 | E4: M4 | F4: M5 | G4: M6 | H4: M7 | I4: M8 | J4: M9 | K4: M10 | L4: M11 | M4: M12 | N4: M13 | O4: M14 | P4: M15 | Q4: M16 | R4: M17 | S4: M18 | T4: M19 | U4: M20 | V4: M21 | W4: M22 | X4: M23 | Y4: M24 | Z4: M25 | AA4: M26 | AB4: M27 | AC4: M28 | AD4: M29 | AE4: M30 | AF4: M31 | AG4: M32 | AH4: M33 | AI4: M34 | AJ4: M35 | AK4: M36 | AL4: M37 | AM4: M38 | AN4: M39 | AO4: M40 | AP4: M41 | AQ4: M42 | AR4: M43 | AS4: M44 | AT4: M45 | AU4: M46 | AV4: M47 | AW4: M48 | AX4: M49 | AY4: M50 | AZ4: M51 | BA4: M52
A5: OPERATING ACTIVITIES
A6: Net Income | B6: ='P&L'!B39 | C6: ='P&L'!C39 | D6: ='P&L'!D39 | E6: ='P&L'!E39 | F6: ='P&L'!F39 | G6: ='P&L'!G39 | H6: ='P&L'!H39 | I6: ='P&L'!I39 | ... BA6: ='P&L'!BA39
A7: + Depreciation & Amortization | B7: ='P&L'!B32 | C7: ='P&L'!C32 | D7: ='P&L'!D32 | E7: ='P&L'!E32 | F7: ='P&L'!F32 | G7: ='P&L'!G32 | H7: ='P&L'!H32 | I7: ='P&L'!I32 | ... BA7: ='P&L'!BA32
A8: Changes in Working Capital | B8: =-'Balance Sheet'!B7-'Balance Sheet'!B8+'Balance Sheet'!B13+'Balance Sheet'!B14+'Balance Sheet'!B15 | C8: =-('Balance Sheet'!C7-'Balance Sheet'!B7)-('Balance Sheet'!C8-'Balance Sheet'!B8)+('Balance Sheet'!C13-'Balance Sheet'!B13)+('Balance Sheet'!C14-'Balance Sheet'!B14)+('Balance Sheet'!C15-'Balance Sheet'!B15) | D8: =-('Balance Sheet'!D7-'Balance Sheet'!C7)-('Balance Sheet'!D8-'Balance Sheet'!C8)+('Balance Sheet'!D13-'Balance Sheet'!C13)+('Balance Sheet'!D14-'Balance Sheet'!C14)+('Balance Sheet'!D15-'Balance Sheet'!C15) | E8: =-('Balance Sheet'!E7-'Balance Sheet'!D7)-('Balance Sheet'!E8-'Balance Sheet'!D8)+('Balance Sheet'!E13-'Balance Sheet'!D13)+('Balance Sheet'!E14-'Balance Sheet'!D14)+('Balance Sheet'!E15-'Balance Sheet'!D15) | F8: =-('Balance Sheet'!F7-'Balance Sheet'!E7)-('Balance Sheet'!F8-'Balance Sheet'!E8)+('Balance Sheet'!F13-'Balance Sheet'!E13)+('Balance Sheet'!F14-'Balance Sheet'!E14)+('Balance Sheet'!F15-'Balance Sheet'!E15) | G8: =-('Balance Sheet'!G7-'Balance Sheet'!F7)-('Balance Sheet'!G8-'Balance Sheet'!F8)+('Balance Sheet'!G13-'Balance Sheet'!F13)+('Balance Sheet'!G14-'Balance Sheet'!F14)+('Balance Sheet'!G15-'Balance Sheet'!F15) | H8: =-('Balance Sheet'!H7-'Balance Sheet'!G7)-('Balance Sheet'!H8-'Balance Sheet'!G8)+('Balance Sheet'!H13-'Balance Sheet'!G13)+('Balance Sheet'!H14-'Balance Sheet'!G14)+('Balance Sheet'!H15-'Balance Sheet'!G15) | I8: =-('Balance Sheet'!I7-'Balance Sheet'!H7)-('Balance Sheet'!I8-'Balance Sheet'!H8)+('Balance Sheet'!I13-'Balance Sheet'!H13)+('Balance Sheet'!I14-'Balance Sheet'!H14)+('Balance Sheet'!I15-'Balance Sheet'!H15) | J8: =-('Balance Sheet'!J7-'Balance Sheet'!I7)-('Balance Sheet'!J8-'Balance Sheet'!I8)+('Balance Sheet'!J13-'Balance Sheet'!I13)+('Balance Sheet'!J14-'Balance Sheet'!I14)+('Balance Sheet'!J15-'Balance Sheet'!I15) | ... BA8: =-('Balance Sheet'!BA7-'Balance Sheet'!AZ7)-('Balance Sheet'!BA8-'Balance Sheet'!AZ8)+('Balance Sheet'!BA13-'Balance Sheet'!AZ13)+('Balance Sheet'!BA14-'Balance Sheet'!AZ14)+('Balance Sheet'!BA15-'Balance Sheet'!AZ15)
A9: Net Cash from Operations | B9: =B6+B7+B8 | C9: =C6+C7+C8 | D9: =D6+D7+D8 | E9: =E6+E7+E8 | F9: =F6+F7+F8 | G9: =G6+G7+G8 | H9: =H6+H7+H8 | I9: =I6+I7+I8 | ... BA9: =BA6+BA7+BA8
A11: INVESTING ACTIVITIES
A12: Purchase of Equipment | B12: =-(Costs!B91+Inputs!$B$91) | C12: =-Costs!C91 | D12: =-Costs!D91 | E12: =-Costs!E91 | F12: =-Costs!F91 | G12: =-Costs!G91 | H12: =-Costs!H91 | I12: =-Costs!I91 | J12: =-Costs!J91 | ... BA12: =-Costs!BA91
A13: Net Cash from Investing | B13: =B12 | C13: =C12 | D13: =D12 | E13: =E12 | F13: =F12 | G13: =G12 | H13: =H12 | I13: =I12 | ... BA13: =BA12
A15: FINANCING ACTIVITIES
A16: Equity Funding Received | B16: =IF(1=Inputs!$B$11,Inputs!$B$10,0)+IF(1=Inputs!$B$13,Inputs!$B$12,0)+IF(1=Inputs!$B$15,Inputs!$B$14,0)+IF(1=Inputs!$B$17,Inputs!$B$16,0) | C16: =IF(2=Inputs!$B$11,Inputs!$B$10,0)+IF(2=Inputs!$B$13,Inputs!$B$12,0)+IF(2=Inputs!$B$15,Inputs!$B$14,0)+IF(2=Inputs!$B$17,Inputs!$B$16,0) | D16: =IF(3=Inputs!$B$11,Inputs!$B$10,0)+IF(3=Inputs!$B$13,Inputs!$B$12,0)+IF(3=Inputs!$B$15,Inputs!$B$14,0)+IF(3=Inputs!$B$17,Inputs!$B$16,0) | E16: =IF(4=Inputs!$B$11,Inputs!$B$10,0)+IF(4=Inputs!$B$13,Inputs!$B$12,0)+IF(4=Inputs!$B$15,Inputs!$B$14,0)+IF(4=Inputs!$B$17,Inputs!$B$16,0) | F16: =IF(5=Inputs!$B$11,Inputs!$B$10,0)+IF(5=Inputs!$B$13,Inputs!$B$12,0)+IF(5=Inputs!$B$15,Inputs!$B$14,0)+IF(5=Inputs!$B$17,Inputs!$B$16,0) | G16: =IF(6=Inputs!$B$11,Inputs!$B$10,0)+IF(6=Inputs!$B$13,Inputs!$B$12,0)+IF(6=Inputs!$B$15,Inputs!$B$14,0)+IF(6=Inputs!$B$17,Inputs!$B$16,0) | H16: =IF(7=Inputs!$B$11,Inputs!$B$10,0)+IF(7=Inputs!$B$13,Inputs!$B$12,0)+IF(7=Inputs!$B$15,Inputs!$B$14,0)+IF(7=Inputs!$B$17,Inputs!$B$16,0) | I16: =IF(8=Inputs!$B$11,Inputs!$B$10,0)+IF(8=Inputs!$B$13,Inputs!$B$12,0)+IF(8=Inputs!$B$15,Inputs!$B$14,0)+IF(8=Inputs!$B$17,Inputs!$B$16,0) | J16: =IF(9=Inputs!$B$11,Inputs!$B$10,0)+IF(9=Inputs!$B$13,Inputs!$B$12,0)+IF(9=Inputs!$B$15,Inputs!$B$14,0)+IF(9=Inputs!$B$17,Inputs!$B$16,0) | K16: =IF(10=Inputs!$B$11,Inputs!$B$10,0)+IF(10=Inputs!$B$13,Inputs!$B$12,0)+IF(10=Inputs!$B$15,Inputs!$B$14,0)+IF(10=Inputs!$B$17,Inputs!$B$16,0) | L16: =IF(11=Inputs!$B$11,Inputs!$B$10,0)+IF(11=Inputs!$B$13,Inputs!$B$12,0)+IF(11=Inputs!$B$15,Inputs!$B$14,0)+IF(11=Inputs!$B$17,Inputs!$B$16,0) | M16: =IF(12=Inputs!$B$11,Inputs!$B$10,0)+IF(12=Inputs!$B$13,Inputs!$B$12,0)+IF(12=Inputs!$B$15,Inputs!$B$14,0)+IF(12=Inputs!$B$17,Inputs!$B$16,0) | N16: =IF(13=Inputs!$B$11,Inputs!$B$10,0)+IF(13=Inputs!$B$13,Inputs!$B$12,0)+IF(13=Inputs!$B$15,Inputs!$B$14,0)+IF(13=Inputs!$B$17,Inputs!$B$16,0) | O16: =IF(14=Inputs!$B$11,Inputs!$B$10,0)+IF(14=Inputs!$B$13,Inputs!$B$12,0)+IF(14=Inputs!$B$15,Inputs!$B$14,0)+IF(14=Inputs!$B$17,Inputs!$B$16,0) | P16: =IF(15=Inputs!$B$11,Inputs!$B$10,0)+IF(15=Inputs!$B$13,Inputs!$B$12,0)+IF(15=Inputs!$B$15,Inputs!$B$14,0)+IF(15=Inputs!$B$17,Inputs!$B$16,0) | Q16: =IF(16=Inputs!$B$11,Inputs!$B$10,0)+IF(16=Inputs!$B$13,Inputs!$B$12,0)+IF(16=Inputs!$B$15,Inputs!$B$14,0)+IF(16=Inputs!$B$17,Inputs!$B$16,0) | R16: =IF(17=Inputs!$B$11,Inputs!$B$10,0)+IF(17=Inputs!$B$13,Inputs!$B$12,0)+IF(17=Inputs!$B$15,Inputs!$B$14,0)+IF(17=Inputs!$B$17,Inputs!$B$16,0) | S16: =IF(18=Inputs!$B$11,Inputs!$B$10,0)+IF(18=Inputs!$B$13,Inputs!$B$12,0)+IF(18=Inputs!$B$15,Inputs!$B$14,0)+IF(18=Inputs!$B$17,Inputs!$B$16,0) | T16: =IF(19=Inputs!$B$11,Inputs!$B$10,0)+IF(19=Inputs!$B$13,Inputs!$B$12,0)+IF(19=Inputs!$B$15,Inputs!$B$14,0)+IF(19=Inputs!$B$17,Inputs!$B$16,0) | U16: =IF(20=Inputs!$B$11,Inputs!$B$10,0)+IF(20=Inputs!$B$13,Inputs!$B$12,0)+IF(20=Inputs!$B$15,Inputs!$B$14,0)+IF(20=Inputs!$B$17,Inputs!$B$16,0) | V16: =IF(21=Inputs!$B$11,Inputs!$B$10,0)+IF(21=Inputs!$B$13,Inputs!$B$12,0)+IF(21=Inputs!$B$15,Inputs!$B$14,0)+IF(21=Inputs!$B$17,Inputs!$B$16,0) | W16: =IF(22=Inputs!$B$11,Inputs!$B$10,0)+IF(22=Inputs!$B$13,Inputs!$B$12,0)+IF(22=Inputs!$B$15,Inputs!$B$14,0)+IF(22=Inputs!$B$17,Inputs!$B$16,0) | X16: =IF(23=Inputs!$B$11,Inputs!$B$10,0)+IF(23=Inputs!$B$13,Inputs!$B$12,0)+IF(23=Inputs!$B$15,Inputs!$B$14,0)+IF(23=Inputs!$B$17,Inputs!$B$16,0) | Y16: =IF(24=Inputs!$B$11,Inputs!$B$10,0)+IF(24=Inputs!$B$13,Inputs!$B$12,0)+IF(24=Inputs!$B$15,Inputs!$B$14,0)+IF(24=Inputs!$B$17,Inputs!$B$16,0) | Z16: =IF(25=Inputs!$B$11,Inputs!$B$10,0)+IF(25=Inputs!$B$13,Inputs!$B$12,0)+IF(25=Inputs!$B$15,Inputs!$B$14,0)+IF(25=Inputs!$B$17,Inputs!$B$16,0) | AA16: =IF(26=Inputs!$B$11,Inputs!$B$10,0)+IF(26=Inputs!$B$13,Inputs!$B$12,0)+IF(26=Inputs!$B$15,Inputs!$B$14,0)+IF(26=Inputs!$B$17,Inputs!$B$16,0) | AB16: =IF(27=Inputs!$B$11,Inputs!$B$10,0)+IF(27=Inputs!$B$13,Inputs!$B$12,0)+IF(27=Inputs!$B$15,Inputs!$B$14,0)+IF(27=Inputs!$B$17,Inputs!$B$16,0) | AC16: =IF(28=Inputs!$B$11,Inputs!$B$10,0)+IF(28=Inputs!$B$13,Inputs!$B$12,0)+IF(28=Inputs!$B$15,Inputs!$B$14,0)+IF(28=Inputs!$B$17,Inputs!$B$16,0) | AD16: =IF(29=Inputs!$B$11,Inputs!$B$10,0)+IF(29=Inputs!$B$13,Inputs!$B$12,0)+IF(29=Inputs!$B$15,Inputs!$B$14,0)+IF(29=Inputs!$B$17,Inputs!$B$16,0) | AE16: =IF(30=Inputs!$B$11,Inputs!$B$10,0)+IF(30=Inputs!$B$13,Inputs!$B$12,0)+IF(30=Inputs!$B$15,Inputs!$B$14,0)+IF(30=Inputs!$B$17,Inputs!$B$16,0) | AF16: =IF(31=Inputs!$B$11,Inputs!$B$10,0)+IF(31=Inputs!$B$13,Inputs!$B$12,0)+IF(31=Inputs!$B$15,Inputs!$B$14,0)+IF(31=Inputs!$B$17,Inputs!$B$16,0) | AG16: =IF(32=Inputs!$B$11,Inputs!$B$10,0)+IF(32=Inputs!$B$13,Inputs!$B$12,0)+IF(32=Inputs!$B$15,Inputs!$B$14,0)+IF(32=Inputs!$B$17,Inputs!$B$16,0) | AH16: =IF(33=Inputs!$B$11,Inputs!$B$10,0)+IF(33=Inputs!$B$13,Inputs!$B$12,0)+IF(33=Inputs!$B$15,Inputs!$B$14,0)+IF(33=Inputs!$B$17,Inputs!$B$16,0) | AI16: =IF(34=Inputs!$B$11,Inputs!$B$10,0)+IF(34=Inputs!$B$13,Inputs!$B$12,0)+IF(34=Inputs!$B$15,Inputs!$B$14,0)+IF(34=Inputs!$B$17,Inputs!$B$16,0) | AJ16: =IF(35=Inputs!$B$11,Inputs!$B$10,0)+IF(35=Inputs!$B$13,Inputs!$B$12,0)+IF(35=Inputs!$B$15,Inputs!$B$14,0)+IF(35=Inputs!$B$17,Inputs!$B$16,0) | AK16: =IF(36=Inputs!$B$11,Inputs!$B$10,0)+IF(36=Inputs!$B$13,Inputs!$B$12,0)+IF(36=Inputs!$B$15,Inputs!$B$14,0)+IF(36=Inputs!$B$17,Inputs!$B$16,0) | AL16: =IF(37=Inputs!$B$11,Inputs!$B$10,0)+IF(37=Inputs!$B$13,Inputs!$B$12,0)+IF(37=Inputs!$B$15,Inputs!$B$14,0)+IF(37=Inputs!$B$17,Inputs!$B$16,0) | AM16: =IF(38=Inputs!$B$11,Inputs!$B$10,0)+IF(38=Inputs!$B$13,Inputs!$B$12,0)+IF(38=Inputs!$B$15,Inputs!$B$14,0)+IF(38=Inputs!$B$17,Inputs!$B$16,0) | AN16: =IF(39=Inputs!$B$11,Inputs!$B$10,0)+IF(39=Inputs!$B$13,Inputs!$B$12,0)+IF(39=Inputs!$B$15,Inputs!$B$14,0)+IF(39=Inputs!$B$17,Inputs!$B$16,0) | AO16: =IF(40=Inputs!$B$11,Inputs!$B$10,0)+IF(40=Inputs!$B$13,Inputs!$B$12,0)+IF(40=Inputs!$B$15,Inputs!$B$14,0)+IF(40=Inputs!$B$17,Inputs!$B$16,0) | AP16: =IF(41=Inputs!$B$11,Inputs!$B$10,0)+IF(41=Inputs!$B$13,Inputs!$B$12,0)+IF(41=Inputs!$B$15,Inputs!$B$14,0)+IF(41=Inputs!$B$17,Inputs!$B$16,0) | AQ16: =IF(42=Inputs!$B$11,Inputs!$B$10,0)+IF(42=Inputs!$B$13,Inputs!$B$12,0)+IF(42=Inputs!$B$15,Inputs!$B$14,0)+IF(42=Inputs!$B$17,Inputs!$B$16,0) | AR16: =IF(43=Inputs!$B$11,Inputs!$B$10,0)+IF(43=Inputs!$B$13,Inputs!$B$12,0)+IF(43=Inputs!$B$15,Inputs!$B$14,0)+IF(43=Inputs!$B$17,Inputs!$B$16,0) | AS16: =IF(44=Inputs!$B$11,Inputs!$B$10,0)+IF(44=Inputs!$B$13,Inputs!$B$12,0)+IF(44=Inputs!$B$15,Inputs!$B$14,0)+IF(44=Inputs!$B$17,Inputs!$B$16,0) | AT16: =IF(45=Inputs!$B$11,Inputs!$B$10,0)+IF(45=Inputs!$B$13,Inputs!$B$12,0)+IF(45=Inputs!$B$15,Inputs!$B$14,0)+IF(45=Inputs!$B$17,Inputs!$B$16,0) | AU16: =IF(46=Inputs!$B$11,Inputs!$B$10,0)+IF(46=Inputs!$B$13,Inputs!$B$12,0)+IF(46=Inputs!$B$15,Inputs!$B$14,0)+IF(46=Inputs!$B$17,Inputs!$B$16,0) | AV16: =IF(47=Inputs!$B$11,Inputs!$B$10,0)+IF(47=Inputs!$B$13,Inputs!$B$12,0)+IF(47=Inputs!$B$15,Inputs!$B$14,0)+IF(47=Inputs!$B$17,Inputs!$B$16,0) | AW16: =IF(48=Inputs!$B$11,Inputs!$B$10,0)+IF(48=Inputs!$B$13,Inputs!$B$12,0)+IF(48=Inputs!$B$15,Inputs!$B$14,0)+IF(48=Inputs!$B$17,Inputs!$B$16,0) | AX16: =IF(49=Inputs!$B$11,Inputs!$B$10,0)+IF(49=Inputs!$B$13,Inputs!$B$12,0)+IF(49=Inputs!$B$15,Inputs!$B$14,0)+IF(49=Inputs!$B$17,Inputs!$B$16,0) | AY16: =IF(50=Inputs!$B$11,Inputs!$B$10,0)+IF(50=Inputs!$B$13,Inputs!$B$12,0)+IF(50=Inputs!$B$15,Inputs!$B$14,0)+IF(50=Inputs!$B$17,Inputs!$B$16,0) | AZ16: =IF(51=Inputs!$B$11,Inputs!$B$10,0)+IF(51=Inputs!$B$13,Inputs!$B$12,0)+IF(51=Inputs!$B$15,Inputs!$B$14,0)+IF(51=Inputs!$B$17,Inputs!$B$16,0) | BA16: =IF(52=Inputs!$B$11,Inputs!$B$10,0)+IF(52=Inputs!$B$13,Inputs!$B$12,0)+IF(52=Inputs!$B$15,Inputs!$B$14,0)+IF(52=Inputs!$B$17,Inputs!$B$16,0)
A17: Net Cash from Financing | B17: =B16 | C17: =C16 | D17: =D16 | E17: =E16 | F17: =F16 | G17: =G16 | H17: =H16 | I17: =I16 | ... BA17: =BA16
A19: NET CHANGE IN CASH | B19: =B9+B13+B17 | C19: =C9+C13+C17 | D19: =D9+D13+D17 | E19: =E9+E13+E17 | F19: =F9+F13+F17 | G19: =G9+G13+G17 | H19: =H9+H13+H17 | I19: =I9+I13+I17 | ... BA19: =BA9+BA13+BA17
A21: Beginning Cash Balance | B21: 0 | C21: =B23 | D21: =C23 | E21: =D23 | F21: =E23 | G21: =F23 | H21: =G23 | I21: =H23 | J21: =I23 | ... BA21: =AZ23
A22: Net Change | B22: =B19 | C22: =C19 | D22: =D19 | E22: =E19 | F22: =F19 | G22: =G19 | H22: =H19 | I22: =I19 | ... BA22: =BA19
A23: ENDING CASH BALANCE | B23: =B21+B22 | C23: =C21+C22 | D23: =D21+D22 | E23: =E21+E22 | F23: =F21+F22 | G23: =G21+G22 | H23: =H21+H22 | I23: =I21+I22 | ... BA23: =BA21+BA22
A25: KEY METRICS
A26: Monthly Burn Rate | B26: =IF(B19<0,-B19,0) | C26: =IF(C19<0,-C19,0) | D26: =IF(D19<0,-D19,0) | E26: =IF(E19<0,-E19,0) | F26: =IF(F19<0,-F19,0) | G26: =IF(G19<0,-G19,0) | H26: =IF(H19<0,-H19,0) | I26: =IF(I19<0,-I19,0) | ... BA26: =IF(BA19<0,-BA19,0)
A27: Runway (Months) | B27: =IFERROR(IF(B26>0,B23/B26,"∞"),"∞") | C27: =IFERROR(IF(C26>0,C23/C26,"∞"),"∞") | D27: =IFERROR(IF(D26>0,D23/D26,"∞"),"∞") | E27: =IFERROR(IF(E26>0,E23/E26,"∞"),"∞") | F27: =IFERROR(IF(F26>0,F23/F26,"∞"),"∞") | G27: =IFERROR(IF(G26>0,G23/G26,"∞"),"∞") | H27: =IFERROR(IF(H26>0,H23/H26,"∞"),"∞") | I27: =IFERROR(IF(I26>0,I23/I26,"∞"),"∞") | ... BA27: =IFERROR(IF(BA26>0,BA23/BA26,"∞"),"∞")
A28: Cumulative Cash Position | B28: =B23 | C28: =C23 | D28: =D23 | E28: =E23 | F28: =F23 | G28: =G23 | H28: =H23 | I28: =I23 | ... BA28: =BA23
A29: Cash Runway Alert | B29: =IF(ISNUMBER(B27),IF(B27<6,"WARNUNG: <6 Monate!","OK"),"OK") | C29: =IF(ISNUMBER(C27),IF(C27<6,"WARNUNG: <6 Monate!","OK"),"OK") | D29: =IF(ISNUMBER(D27),IF(D27<6,"WARNUNG: <6 Monate!","OK"),"OK") | E29: =IF(ISNUMBER(E27),IF(E27<6,"WARNUNG: <6 Monate!","OK"),"OK") | F29: =IF(ISNUMBER(F27),IF(F27<6,"WARNUNG: <6 Monate!","OK"),"OK") | G29: =IF(ISNUMBER(G27),IF(G27<6,"WARNUNG: <6 Monate!","OK"),"OK") | H29: =IF(ISNUMBER(H27),IF(H27<6,"WARNUNG: <6 Monate!","OK"),"OK") | I29: =IF(ISNUMBER(I27),IF(I27<6,"WARNUNG: <6 Monate!","OK"),"OK") | ... BA29: =IF(ISNUMBER(BA27),IF(BA27<6,"WARNUNG: <6 Monate!","OK"),"OK")

Sheet LFL_Szenario_Erklaerung
A1: LFL FINANCIAL PROJECTIONS — SZENARIO KONSERVATIV
A2: Basis: 260304_LFL-Financial-Planning-and-Carbon-Case.pdf | Erstellt: 04.03.2026 23:13
A4: HINTERGRUND
A5: Dieses Szenario basiert auf dem LFL Financial Planning & Carbon Case Dossier (260304_LFL-Financial-Planning-and-Carbon-Case.pdf, Stand 4. März 2026). Alle Parameter wurden aus den strategischen Meeting-Transkripten von Rene und dem Finanzmodellierer abgeleitet. Externe Annahmen wurden nicht hinzugefügt. Offene Punkte (TBD/OPEN) aus dem Dossier sind im Report-Sheet markiert.
A7: Parameter | B7: Bezeichnung | C7: Baseline | D7: NEU (KONSERVATIV) | E7: Begründung / Zusammenhang
A8: 1. PREISGESTALTUNG — Konservative Positionierung
A9: Sandbox D6 | B9: Preis/Seat/Monat | C9: 800 EUR (gering-Standard) | D9: 200 EUR | E9: Das PDF nennt 350 EUR/Monat als Referenzpreis (→ 4.200 EUR/Seat/Jahr) und 200 EUR als benchmark_low. Im konservativen Szenario wählen wir den Benchmark-Tiefpunkt, um das Preisrisiko in der Marktvalidierung abzubilden. Ein zu hoher Einstiegspreis ohne bewiesenen ROI verlängert den Sales-Zyklus erheblich.
A10: Inputs B21 | B10: Preiserhöhung/Jahr | C10: 8% | D10: 5% | E10: Geringere jährliche Preissteigerung reflektiert schwächere Marktposition und Kundenwiderstand in der Frühphase. Packaging-Kunden (primärer Markt: 2.255 Unternehmen laut Rene) sind preissensitiv.
A11: → Auswirkung | B11: ARR pro Standardkunde (5 Seats): 200 EUR × 5 × 12 = 12.000 EUR/Jahr (vs. 21.000 EUR im PDF-Referenzpreis). Runway und Break-Even verschlechtern sich deutlich. Höheres Funding-Risiko.
A13: 2. KUNDEN-TIMING & WACHSTUM — Langsame Marktdurchdringung
A14: Sandbox D5 | B14: Startmonat erste Kunden | C14: 14 | D14: 17 | E14: Das PDF nennt explizit '~17 months to first revenue'. Im konservativen Szenario halten wir an diesem Planwert fest. Die Pre-Seed-Phase (3-5 Kunden, Sept 2026-Sept 2027) dient reiner Validierung ohne Revenue-Fokus. First paying customer frühestens Monat 17 (September 2027, mit Seed-Close).
A15: Inputs B23 | B15: Initiale Seats | C15: 5 | D15: 3 | E15: PDF nennt 3-5 als Pre-Seed-Kundenzahl. Konservativ: 3 Piloten. Jeder Pilot mit 5 Seats = 15 Seats total.
A16: Inputs B24 | B16: Monatl. Seat-Wachstum | C16: 5% | D16: 3% | E16: Verlangsamtes Wachstum durch längere Sales-Zyklen (packaging/automotive lt. PDF: 'longer lead cycle in automotive'). 3% entspricht ca. 43% Jahreswachstum – konservativ aber realistisch für B2B-Manufacturing.
A17: Inputs B25 | B17: Enterprise-Deals ab Monat | C17: 24 | D17: 30 | E17: Enterprise-Deals starten erst nach Monat 30 – nach erstem erfolgreichen Track Record. PDF: deal_complexity höher als Standard, lead_cycle länger.
A18: → Auswirkung | B18: Seed-Ziel: 50-60 Kunden (PDF) → im Konservativ-Szenario realistisch 25-35 Kunden bis Monat 17-24. Gesamt-ARR M24: deutlich unter 500K EUR. Enterprise-Revenue startet erst ab M30.
A20: 3. CHURN & KUNDENBINDUNG — Höheres Abwanderungsrisiko
A21: Inputs B28 | B21: Jährliche Churn Rate | C21: 8% | D21: 15% | E21: PDF: adoption_probability_low = 10%. Geringe Adoption bedeutet hohes Abwanderungsrisiko sobald Verträge auslaufen. 15% Churn entspricht einem 'gefährdeten' SaaS-Modell in der Early-Stage, typisch für Produkte ohne tiefen Workflow-Lock-in. Causal: Fehlende Onboarding-Qualität + unklarer ROI-Nachweis (wie Olaf betont) führen zu Abwanderung.
A22: Inputs B29 | B22: Net Revenue Retention | C22: 118% | D22: 105% | E22: Ohne starke Expansion durch Upsell oder neue Seats bleibt NRR knapp über 100%. PDF: Keine quantifizierten Upsell-Mechanismen – konservativ daher 105%.
A23: → Auswirkung | B23: ARR-Erosion durch Churn: Bei 100K ARR und 15% Churn verliert das Unternehmen 15K/Jahr. Ohne starkes Neuwachstum schrumpft der Revenue-Pool. NRR von 105% rettet knapp die Nettowachstum-Rate.
A25: 4. FUNDING — Konservative Kapitalstrategie
A26: Inputs B12 | B26: Pre-Seed Betrag | C26: 1.500.000 EUR | D26: 1.500.000 EUR | E26: PDF Lower End: 1,5M EUR. Im Konservativ-Szenario bleibt Pre-Seed beim Minimum. Runway: 12 Monate (Sept 2026 – Sept 2027). Reicht für MVP + 3-5 Pilotkunden.
A27: Inputs B14 | B27: Seed Betrag | C27: 6.000.000 EUR | D27: 4.000.000 EUR | E27: PDF Seed Lower End: 4M EUR. Konservativ, da langsameres Wachstum weniger Kapital verbraucht. Seed-Runway: 12 Monate (Sept 2027 – Sept 2028), für 50-60 Kunden.
A28: Inputs B16 | B28: Series A Betrag | C28: 15.000.000 EUR | D28: 10.000.000 EUR | E28: Reduzierte Series A durch geringeres Wachstumstempo. Schont Verwässerung.
A29: Inputs B17 | B29: Series A Monat | C29: 35 | D29: 36 | E29: Leicht später, da Meilensteine langsamer erreicht werden.
A30: → Auswirkung | B30: Gesamtfinanzierung: 15,5M EUR (vs. 23,5M im Aggressiv). Niedrigerer Cash-Verbrauch durch geringere Headcount- und Marketing-Ausgaben.
A32: 5. HEADCOUNT & KI-HEBEL — Vollständige Personalplanung
A33: Sandbox D10 | B33: AI-Personal-Hebel | C33: 0 Monate (Gering-Standard) | D33: 0 Monate | E33: Konservativ: Kein KI-Delay beim Hiring. Alle Rollen werden zum ursprünglich geplanten Monat eingestellt. Begründung: KI-Werkzeuge sind in der Praxis in Monat 1-24 noch nicht produktionsreif genug, um Hiring zu verzögern. Das Unternehmen baut Standard-Kapazitäten auf.
A34: Inputs B44 | B34: Jährl. Gehaltserhöhung | C34: 5% | D34: 3% | E34: Geringere Lohnsteigerung reflektiert konservatives Budget und weniger Wettbewerb um Talent im konservativen Szenario (kleineres Unternehmen, Berlin-Markt).
A35: → Auswirkung | B35: Konservativ hat MEHR Mitarbeiter als Aggressiv (kein KI-Delay). Personalkosten sind der größte Kostenblock. Typische Entwicklung: M1-5: CEO + CTO (Founder, Eigenfinanzierung) M5-17: +2 Senior Engineers nach Pre-Seed M17-24: +CCO, +1 Sales, +1 Customer Success nach Seed M24-36: +Marketing, +Finance, +2 weitere Engineers M36-52: +2-3 Sales Reps, +2 CS, +1 weitere GESAMT M52: ~18-22 Mitarbeiter
A37: 6. MARKETING & SALES — Budgetdisziplin
A38: Inputs B125 | B38: Events & Messen/Jahr | C38: 25.000 EUR | D38: 25.000 EUR | E38: PDF-Placeholder-Wert beibehalten. Rene betont: Industrie-Konferenzen > Software-Konferenzen. 25K EUR als Baseline für 2-3 Packaging/Machinery-Konferenzen. Im Konservativ-Szenario kein Aufschlag.
A39: Inputs B122 | B39: Paid Ads Initial | C39: 500 EUR/Monat | D39: 300 EUR/Monat | E39: Geringeres Ads-Budget in der Validierungsphase. B2B-Manufacturing kauft nicht über Ads.
A40: Inputs B127 | B40: Sales-Provision | C40: 10% | D40: 8% | E40: Etwas geringere Provision, da weniger aggressives Sales-Ziel.
A41: → Auswirkung | B41: Total Marketing-Spend M1-M52: ~30-40% geringer als Aggressiv. GTM über Konferenzen (primary), Content (sekundär), POCs (Conversion).
A43: VERGLEICH: KONSERVATIV vs. AGGRESSIV
A44: ╔══════════════════════════════════════════════════════════════════════╗ ║ HAUPTUNTERSCHIEDE: KONSERVATIV vs. AGGRESSIV ║ ╠══════════════════════════════════════════════════════════════════════╣ ║ Parameter │ Konservativ │ Aggressiv │ Quelle ║ ╠══════════════════════════════════════════════════════════════════════╣ ║ Preis/Seat/Monat │ 200 EUR │ 500 EUR │ PDF benchmark ║ ║ Preis/Seat/Jahr │ 2.400 EUR │ 6.000 EUR │ ×12 ║ ║ First Revenue Mon. │ 17 │ 9 │ PDF + Anpassung ║ ║ Initiale Seats │ 3 │ 5 │ PDF avg ║ ║ Seat-Wachstum/Mo. │ 3% │ 8% │ Scenario ║ ║ Enterprise ab Mon. │ 30 │ 18 │ Scenario ║ ║ Enterprise ARR │ 25.000 EUR │ 50.000 EUR │ Scenario ║ ║ Deals/Quartal │ 1 │ 2 │ Scenario ║ ║ Churn Rate/Jahr │ 15% │ 6% │ PDF adoption ║ ║ NRR │ 105% │ 125% │ Scenario ║ ║ Pre-Seed │ 1,5M EUR │ 2,0M EUR │ PDF range ║ ║ Seed │ 4,0M EUR │ 6,0M EUR │ PDF range ║ ║ Series A │ 10M EUR │ 20M EUR │ Scenario ║ ║ Headcount M52 │ ~18-22 │ ~10-14 │ KI-Hebel-Effekt ║ ║ Events/Jahr │ 25.000 EUR │ 50.000 EUR │ PDF + ×2 ║ ║ KI-Personal-Hebel │ 0 Monate │ 99 Monate │ Maximaler Effekt║ ║ ARR-Schätzung M24 │ 200-400K │ 600K-1,2M │ Modellschätzung ║ ║ ARR-Schätzung M52 │ 500K-1M │ 5-10M │ Modellschätzung ║ ╚══════════════════════════════════════════════════════════════════════╝
A46: OFFENE PUNKTE (aus PDF Decision Register Part G)
A47: OFFENE PUNKTE AUS DEM PDF (Decision Register Part G): ───────────────────────────────────────────────────── G1.1 HIGH: Timeline-Varianten konsolidieren (Sept 2026 vs. April-Start) G1.3 HIGH: First-Paying-Customer-Timing final festlegen (kritischste Variable) G1.4 MED: Deployment-Standard (Cloud/On-Prem/Hybrid) → beeinflusst Kostenstruktur G1.7 MED: KI-Rollensubstitution quantifizieren (direkt auf Personalkosten) G2.2 HIGH: Conversion-Rate-Annahmen per Kanal definieren G2.3 HIGH: Customer-Success-Skalierungsmodell planen (identifizierter Engpass) G3.1 HIGH: Kausale CO₂-Wirkungskette präzise definieren G3.3 HIGH: Baseline für CO₂-Berechnungen festlegen

Sheet Entwicklungs_Roadmap
A1: LFL – Entwicklungs-Roadmap: Neue Treiber aus Treiber-Matrix (noch nicht modelliert)
A2: Kategorie | B2: Parameter / Treiber | C2: Mögliche Werte (G/N/S) | D2: Auswirkung | E2: Priorität | F2: Nächster Schritt
A3: SaaS-Pricing | B3: Produkt-Tiers (Basic/Pro/Enterprise) | C3: Basic ~5K€/J | Pro ~12K€/J | Ent ~25K€/J | D3: Höhere Preisflexibilität, bessere Marktabdeckung → ARR ↑ | E3: P1 HOCH | F3: Seat-Preis in Sandbox durch Tier-Verteilung ersetzen
A4: SaaS-Umsatz | B4: NRR-Varianten (bereits integriert!) | C4: Gering=105% | Normal=115% | Stark=130% | D4: ✓ In v6 implementiert — Sandbox Z.13 / Szenarien Z.9 | E4: ✓ ERLEDIGT | F4: —
A5: SaaS-Umsatz | B5: Churn-Varianten (bereits integriert!) | C5: Gering=10% | Normal=6% | Stark=3% | D5: ✓ In v6 implementiert — Sandbox Z.14 / Szenarien Z.10 | E5: ✓ ERLEDIGT | F5: —
A6: Marktexpansion | B6: Internationalisierung | C6: Keine | EU Y2 | US Y3 | D6: Multiplikator auf Kundenwachstum ab definiertem Monat → ARR ↑↑ | E6: P2 MITTEL | F6: Revenue: Multiplikator-Zeile ab Monat X; Inputs: Expansion-Startmonat
A7: Personal | B7: Gehaltsniveau-Faktor | C7: 85% | 100% | 115% des Markts | D7: Direkter Hebel auf gesamte Personalkostenbasis → EBITDA ± | E7: P2 MITTEL | F7: Inputs: Faktor auf alle Gehälter in Einstellungsplan
A8: Büro/Facilities | B8: Remote-Work-Strategie | C8: Office-First | Hybrid | Full-Remote | D8: Büromiete 0–4.500€/Monat → Burn Rate ↓ bei Remote | E8: P3 NIEDRIG | F8: Inputs: Büromiete durch Strategie-Faktor (0/0.5/1.0) steuern
A9: Technologie | B9: Technologie-Stack-Strategie | C9: Open-Source -40% | Proprietär | Multi-Provider +15% | D9: AI/ML-API-Kosten direkt → COGS Margin ± | E9: P2 MITTEL | F9: Sandbox: Stack-Faktor auf AI/ML APIs Basis

Sheet Notizen & ToDos
A1: Aus Inputs!A2:
A2: To Do 10.3.26: * Den Begriff Consulting verändern in Implementierungs Support. * Checken ob die wesentlichen Parameter in Bezug auf Kostenhöhe et cetera abgeglichen worden sind mit den Informationen aus der Tabelle für den initialen Startpunkt Funding ideation Phase. * Einen anderen Kostensatz annehmen in Bezug auf Anwaltskosten. * Checken ob die absoluten Kostenhöhen so passen. * Checken welche Annahmen hinter den Produkt Feature Entwicklungen stecken können. * Wie es mit der entsprechenden Mannschaft eine Produktentwicklung und ein Rollout stattfinden kann wie er geplant ist. * Berücksichtigen dass einerseits Produkte gebaut andererseits aber auch Implementierung Projekte geleitet und umgesetzt werden müssen. * Diese Fragen auch auf das Thema Customer Success und Sales beziehungsweise Investor Relations ausrollen. * Prüfen ob Olaf René für diese Aufgaben ausreichend Zeit und Kapazität haben. * Mouaz in der Lage ist in dem verfügbaren Zeitrahmen diese Aufgaben umzusetzen, was realistischerweise berücksichtigt werden muss um diese Aufgaben tatsächlich auch umzusetzen. * Ziel sollte eine Szenario beschreibungs sein der besprochenen Vorgehensweise. * Ziel sollte auch sein hier die entsprechenden Bezüge zu den einzelnen Phasen herzustellen und genau zu beschreiben was in jeder Phase gemacht wird, was in jeder Phase kundenseitig und Revenue-seitig erreicht werden muss, welche Anforderungen damit verbunden sind und wie die Kunden gefunden werden sollen. * Also sprich wie viele Letters of Intent, wie viele Pilot-Kunden brauchen wir, in welchen Branchen und was bedeutet das Final für das Produkt.
A10: Aus Costs!B1 (To-Do):
A11: To do 10.3.2026 - Phasen einfügen anhand der Tabelle, die mit Rene und Mouaz abgesprochen worden ist. - Meilensteine in den Spalten markieren, das heißt wann werden entsprechende Funding-Zahlungen hier fällig? - Außerdem klar schauen ob der Aufwuchs an Personal modelliert werden kann oder ob er hier hart eingegeben werden muss. - Auf jeden Fall deutlich machen wo hier Kostensteigerungen durch den Einsatz von Personal stattfinden.

Sheet Weiterentwicklung
A1: IDEEN & VORSCHLÄGE FÜR KÜNFTIGE ENTWICKLUNG
A2: Stand: 11.03.2026
A4: FEATURE 1: Automatisierte Kundenverteilung über Monate
A5: Status: Vorgemerkt – noch nicht implementiert
A6: Beschreibung:
A7: - Nutzer trägt in Inputs nur die GESAMTANZAHL neuer Kunden pro Phase (Ideation / Pre-Seed / Seed / Series A) ein
A8: - Für SME, Mid Company und Enterprise separat
A9: - Algorithmus verteilt die Kunden gleichmäßig (oder gewichtet) über die Monate der jeweiligen Phase
A10: - Implementierung: neue Zeilen in 00_Input_Sandbox oder Inputs, Verteilungsformel in Revenue-Sheet
A11: - Betrifft Sheets: Inputs, Revenue
A13: FEATURE 2: [Platzhalter für weitere Ideen]
