Workbook

Sheet Anleitung
A1: LoopforgeLab GmbH – Financial Projection Model
A3: Projektionszeitraum: 52 Monate (ca. 4,3 Jahre)
A5: INHALTSVERZEICHNIS
A6: Sheet 1: Anleitung – Diese Seite mit Übersicht und Legende
A7: Sheet 2: Inputs – Zentrale Eingabewerte (HIER STARTEN)
A8: Sheet 3: P&L – Gewinn- und Verlustrechnung (monatlich + jährlich)
A9: Sheet 4: Revenue – Detaillierte Umsatzmodellierung
A10: Sheet 5: Costs – Detaillierte Kostenaufschlüsselung
A11: Sheet 6: Balance Sheet – Vereinfachte Bilanz
A12: Sheet 7: Cash Flow – Kapitalflussrechnung mit Runway
A14: FARBCODIERUNG
A15: Blau | B15: Editierbare Eingabefelder
A16: Schwarz | B16: Formeln – nicht manuell ändern
A17: Grün | B17: Verweise auf andere Sheets
A18: Gelb hinterlegt | B18: Kritische Annahmen
A20: KURZANLEITUNG
A21: 1. Gehen Sie zum Sheet 'Inputs' und passen Sie alle blau markierten Werte an.
A22: 2. Alle anderen Sheets berechnen sich automatisch aus den Inputs.
A23: 3. Prüfen Sie die P&L, Revenue und Cash Flow Sheets auf Plausibilität.
A24: 4. Achten Sie auf rot markierte Warnungen (z.B. Runway < 6 Monate).
A25: 5. Exportieren Sie relevante Sheets als PDF für Investoren-Präsentationen.
A27: DISCLAIMER: Diese Projektion dient ausschließlich der Planung.
A28: Tatsächliche Ergebnisse können erheblich abweichen. Keine Garantie.

Sheet Szenarien_Analyse
A1: Faktor | B1: Referenz (Basis) | C1: Szenario: Gering | D1: Szenario: Normal | E1: Szenario: Stark | F1: DELTA: (Stark vs Nomal) | G1: Argumentation (Lothar.bm & Transkripte)
A2: Fokus: Packaging | B2: 0.3 | C2: 0.1 | D2: 0.6 | E2: 0.8 | F2: =E2-D2 -> 0.2 | G2: Höhere Margen, schnellere Zyklen als Auto.
A3: Fokus: Automotive | B3: 0.7 | C3: 0.9 | D3: 0.4 | E3: 0.2 | F3: =E3-D3 -> -0.2 | G3: Hohe IT-Hürden und Margendruck (Lothar).
A4: Erste zahlende Kunden Monat | B4: 6 | C4: 14 | D4: 8 | E4: 4 | F4: =E4-D4 -> -4 | G4: IT-Integration ist der Flaschenhals.
A5: Consulting Anteil | B5: 0.2 | C5: 0.5 | D5: 0.35 | E5: 0.15 | F5: =E5-D5 -> -0.2 | G5: Consulting ist Enabler für IT-Anbindung.
A6: Startpreis pro Seat/Jahr | B6: 1 | C6: 0.8 | D6: 1 | E6: 1.2 | F6: =E6-D6 -> 0.2 | G6: Value-Pricing eher in Packaging möglich.
A7: Personal (Experten) | B7: 5 FTE | C7: 3 FTE | D7: 7 FTE | E7: 12 FTE | F7: =E7-D7 -> #VALUE! | G7: Bedarf an "Übersetzern" für IT-Landschaft.

Sheet Inputs
A1: ZENTRALE EINGABEWERTE | B1: Wert | C1: Erklärung / Hinweis | D1: Bemerkungen | E1: Einstellungsplan: KI-Strategie | F1: Szenarioauswahl: gering, normal, stark
F2: ='00_Input_Sandbox'!$B$2 -> 4
A3: ALLGEMEINE EINSTELLUNGEN
A4: Firmenname | B4: LoopforgeLab GmbH | C4: Name des Unternehmens
A5: Startdatum | B5: 46113 | C5: Beginn der Projektionen
A6: Währung | B6: EUR | C6: EUR für DACH-Startups
A7: Steuersatz | B7: 0.3 | C7: KSt + GewSt (~30% in DE) | D7: Übernahme des Standardsatzes (KSt + GewSt in Deutschland).
A9: FINANZIERUNGSRUNDEN
A10: Ideation Phase | B10: 90000 | C10: Typisch: 100.000-500.000€ | D10: Phase: 1.4.26 bis 15.7.2026 MVP-Anschubfinanzierung; stellt keine Unternehmensbewertung dar.
A11: Ideation Phase | B11: 1 | C11: Monat der Einzahlung | D11: MVP-Entwicklung und IP-Aufbau starten unmittelbar.
A12: Pre-Seed Betrag | B12: 1500000 | C12: Typisch: 500.000-2.000.000€ | D12: Pre-Seed Phase ab VC Pitch im Juli '26 (1.5M-3M Bewertung).
A13: Pre-Seed Monat | B13: 5 | C13: Typisch: Monat 5 | D13: Juli 2026 entspricht Monat 5 Fokus auf Pilot-Traction.
A14: Seed Betrag | B14: 6000000 | C14: Typisch: 3.000.000-10.000.000€ | D14: Abhängig von Pilotprojekten und Reife des Produktes
A15: Seed Monat | B15: 17 | C15: Typisch: Monat 17 | D15: Geplant für Mitte 2027.
A16: Series A Betrag | B16: 15000000 | C16: Typisch: 10.000.000-25.000.000€ | D16: Vorerst unverändert als langfristige Wachstumsambition.
A17: Series A Monat | B17: 35 | C17: Typisch: Monat 35 | D17: Geplant für Herbst 2028.
A19: REVENUE-ANNAHMEN (SaaS/ARR)
A20: Startpreis pro Seat/Jahr | B20: =VLOOKUP("Startpreis Seat/Jahr", '00_Input_Sandbox'!$B$3:$F$20, '00_Input_Sandbox'!$B$2-1, FALSE) * 12 -> 9600 | C20: Jährliche Lizenzgebühr pro Nutzer | D20: 1. Realistisch? Hängt auch ab vom Business Modell..Pricing basierend auf Wettbewerb oder auf voraussichtlichem Einsparpotential? 2. weitere Erlösquellen? Beratung? Implementierungsaufwand? Hybrid-Modell: Deckt Fixkosten und partizipiert am TCO-Einsparwert. [1] | G20: 2. Regulatory Moat (DPP): JE nach Branche (hier: Annahme von neuen Zielbranche in Bezuf auf DPP Verpflichtung) Die Zielbranchen Batterien und Elektronik unterliegen ab 2027 der DPP-Pflicht. Dies rechtfertigt höhere Preise und eine stärkere NRR, da LFL hiermit zur "Compliance Engine" des Kunden wird. -->"Compliance" könnte aber auch durch andere Benefits ersetzt werden
A21: Preiserhöhung/Jahr | B21: 0.08 | C21: Typisch: 3-5% p.a. | D21: Standard für AI-SaaS 2026 (Kompensation Inferenz/Innovation). [4]
A22: Erste zahlende Kunden Monat | B22: =VLOOKUP("Startmonat Kunden", '00_Input_Sandbox'!$B$3:$F$20, '00_Input_Sandbox'!$B$2-1, FALSE) -> 14 | C22: Wann erster Umsatz? | D22: Erster Umsatz in Monat 8 (Start: 04/26)…Realistisch? Wie lange Lead-Time? Zielkunden? Beachhead-Market? Weitere Begründung: wenn im Automotivebereich: Puffer für Sales-Zyklen (9-12 Mon.) und TISAX im Mittelstand. [1
A23: Initiale Seats | B23: 5 | C23: Anzahl Seats beim ersten Kunden | D23: Realistisch? Hängt von Kundengrösse ab. Implementierungsaufwand je Kunde mit einkalkulieren weitere Aspekte: Kalkulieren mit 1-2 Projekten/ Start mit Pilotprojekten (Werke) zur ROI-Validierung ("Land&Expand")
A24: Monatliche Seat-Wachstumsrate | B24: 0.05 | C24: Wachstum neue Seats/Monat | D24: -->hier eine Annahme bzgll Vertriebsplanung treffen. Wie hoch ist die Zahl der Verkauften Sitze nach 1, 2, 3 Jahren? Gibt es noch andere Erlösströme? ALTERNATIVE: Account-basierte Planng: Wechsel auf "Stufenfunktion" beim Aufbau des Geschäfts (Roll-out pro Werk statt linearer Rate)
A25: Enterprise-Deals ab Monat | B25: 24 | C25: Wann starten große Verträge? Wenn Automotive: Verschiebung durch längere Technical Validation und Compliance-Hürden. | G25: 3. Vertriebsrealismus: Der Start des Umsatzes wurde nach hinten geschoben da der industrielle Mittelstand ("Hidden Champions") langsame Entscheidungsprozesse und hohe Sicherheitsanforderungen (TISAX) hat. Die Zeit bis zum Juli 2026 wird für die Validierung der TCO-Einsparungen (Ausschuss-Reduktion) bei Pilotkunden genutzt.
A26: Durchschnitt Enterprise ARR | B26: 150000 | C26: Typisch: 50.000-200.000€/Jahr | D26: Höheres Volumen durch Tiefe der Integration: hier Annahme von weiteren Benefits wie Einbeziehung von DPP & Sustainability
A27: Enterprise Deals pro Quartal | B27: 1 | C27: Neue Enterprise-Deals pro Quartal
A28: Jährliche Churn Rate | B28: 0.08 | C28: Typisch SaaS: 5-10% | D28: Konservative Planung für komplexe industrielle Buying Center. Plausibel im Mittel (höher im Pilot-Jahr 1; niedriger ab Jahr 3).
A29: Net Revenue Retention | B29: 1.18 | C29: Expansion - Churn, typisch: 100-120% | D29: Erklärung: Realisierbar durch DPP-Zusatzmodule und Material-Analytics-Upgrades, ergo weiteren monetarisierbaren Benefits | F29: das ist schon wieder falsch. Die Gehälter für die Executive-Funktionen stehen nicht in den von dir genannten Zellen B26 bis B28
A31: GEHÄLTER (Brutto/Jahr)
A32: CEO Gehalt | B32: 72000 | C32: Typisch Startup: 60.000-90.000€ | D32: Gründer-Satz Pre-Seed); Anpassung ab Seed-Runde. Muss noch genauer präzisiert werden
A33: CTO Gehalt | B33: 72000 | C33: Typisch Startup: 60.000-90.000€ | D33: Gründer-Satz Pre-Seed); Anpassung ab Seed-Runde. Muss noch genauer präzisiert werden
A34: CCO Gehalt | B34: 72000 | C34: Typisch Startup: 60.000-90.000€ | D34: Gründer-Satz Pre-Seed); Anpassung ab Seed-Runde. Muss noch genauer präzisiert werden
A35: Senior Engineer Gehalt | B35: 90000 | C35: Typisch: 70.000-90.000€ | D35: Berliner Tech-Benchmark 2025/26 für Senior-Fullstack/Backends. [9]
A36: Junior Engineer Gehalt | B36: 60000 | C36: Typisch: 45.000-60.000€ | D36: Anpassung an gestiegene Einstiegsgehälter für Top-Tech-Talente. [9]
A37: ML/AI Engineer Gehalt | B37: 110000 | C37: Typisch: 75.000-100.000€ | D37: Höchste Marktnachfrage; KI-Experten in Berlin deutlich über SWE-Schnitt. [10]
A38: Product Manager Gehalt | B38: 80000 | C38: Typisch: 65.000-85.000€ | D38: Durchschnitt für Technical PMs (Industrial AI) am Standort Berlin
A39: Sales Representative Gehalt | B39: 130000 | C39: Typisch: 50.000-70.000€ + Provision | D39: Split 50/50 (65k fix + 65k var); zwingend für Enterprise-Vertrieb. [12
A40: Marketing Manager Gehalt | B40: 65000 | C40: Typisch: 55.000-75.000€ | D40: Anpassung an Marktniveau für B2B-Industrie-Spezialisten.
A41: Customer Success Gehalt | B41: 65000 | C41: Typisch: 45.000-60.000€ | D41: Shift hin zu Solution Architect Profil (techn. Implementierung). [13]
A42: Office/Admin Gehalt | B42: 45000 | C42: Typisch: 40.000-50.000€ | D42: (marktüblich für Berlin).
A43: Finance Manager | B43: 80000
A44: Jährliche Gehaltserhöhung | B44: 0.05 | C44: Typisch: 3-5% | D44: Berücksichtigt Inflations- und Kompetenzentwicklung im Tech-Sektor.
A45: Lohnnebenkosten | B45: 0.21 | C45: AG-Anteil Sozialversicherung ~20-21% | D45: Übernahme des gesetzlichen AG-Anteils.
A47: EINSTELLUNGSPLAN (Eintrittsmonat) | B47: geplanter Bedarf/ Zeitpunkt des geplanten Eintritts | C47: WICHTIG: KEINE Zeilen löschen. Wenn nicht benötigt, einfach SPALTE B nicht befüllen | E47: KI Strategie | F47: Tatsächlicher Eintritt ins Unternehmen
A48: 1. Senior Engineer | B48: =7 + VLOOKUP("AI-Personal-Hebel", '00_Input_Sandbox'!$B$4:$F$10, '00_Input_Sandbox'!$B$2-1, FALSE) -> 7 | C48: Erste technische Verstärkung | D48: Kern-Dev für MVP-Finalisierung und Deep IP. | E48: Fix (Strategische Rolle, kein Effekt durch KI Einsatz) | F48: =IF(COUNTIF(E48,"*Fix*")>0, B48, IF(COUNTIF(E48,"*KI-Agent*")>0, 99, B48 + VLOOKUP("AI-Personal-Hebel", '00_Input_Sandbox'!$B$4:$F$20, '00_Input_Sandbox'!$B$2-1, FALSE))) -> 7
A49: 2. Senior Engineer | B49: 10 | C49: Zweite technische Verstärkung | D49: Skalierung der Kern-Architektur. | E49: KI-Hebel (KI-Position kann durch KI-Einsatz später eingestellt werden) | F49: =IF(COUNTIF(E49,"*Fix*")>0, B49, IF(COUNTIF(E49,"*KI-Agent*")>0, 99, B49 + VLOOKUP("AI-Personal-Hebel", '00_Input_Sandbox'!$B$4:$F$20, '00_Input_Sandbox'!$B$2-1, FALSE))) -> 10
A50: 1. Junior Engineer | B50: 9 | C50: Junior Developer | D50: Support bei Feature-Entwicklung. Mit KI Hebel könnte Effizienz auf 1,5 Jun Eng angehoben werden | E50: KI-Hebel (KI-Position kann durch KI-Einsatz später eingestellt werden) | F50: =IF(COUNTIF(E50,"*Fix*")>0, B50, IF(COUNTIF(E50,"*KI-Agent*")>0, 99, B50 + VLOOKUP("AI-Personal-Hebel", '00_Input_Sandbox'!$B$4:$F$20, '00_Input_Sandbox'!$B$2-1, FALSE))) -> 9
A51: 1. ML/AI Engineer | B51: 8 | C51: ML/AI Spezialist | D51: Fokus auf agentische Systeme und Design-Algorithmen. | E51: Fix (Strategische Rolle, kein Effekt durch KI Einsatz) | F51: =IF(COUNTIF(E51,"*Fix*")>0, B51, IF(COUNTIF(E51,"*KI-Agent*")>0, 99, B51 + VLOOKUP("AI-Personal-Hebel", '00_Input_Sandbox'!$B$4:$F$20, '00_Input_Sandbox'!$B$2-1, FALSE))) -> 8
A52: 2. ML/AI Engineer | B52: 14 | C52: Zweiter ML Engineer | D52: Vertiefung der Material-Analytics-Funktionen. | E52: KI-Hebel (KI-Position kann durch KI-Einsatz später eingestellt werden) | F52: =IF(COUNTIF(E52,"*Fix*")>0, B52, IF(COUNTIF(E52,"*KI-Agent*")>0, 99, B52 + VLOOKUP("AI-Personal-Hebel", '00_Input_Sandbox'!$B$4:$F$20, '00_Input_Sandbox'!$B$2-1, FALSE))) -> 14
A53: 1. Sales Rep | B53: 3 | C53: Erster Vertriebsmitarbeiter | D53: KI-AGENT Substitution durch AI-SDR (Lead Gen/Outbound) @ ca. 500 EUR/Mo. [14 | E53: KI-Agent (Position kann durch KI-Agenten ersetzt werden/ Hiring wenn überhaupt in ferner Zukunft) | F53: =IF(COUNTIF(E53,"*Fix*")>0, B53, IF(COUNTIF(E53,"*KI-Agent*")>0, 99, B53 + VLOOKUP("AI-Personal-Hebel", '00_Input_Sandbox'!$B$4:$F$20, '00_Input_Sandbox'!$B$2-1, FALSE))) -> 99 | G53: 1. AI-First Economics: Durch den Einsatz von KI-Agenten in der Akquise (SDR) und im Support senken wir die Fixkosten (Burn Rate), müssen aber die variablen Cloud-Kosten (COGS) höher gewichten. Dies führt zu einer realistischeren Bruttomarge von ca. 70 % im Vergleich zu den klassischen 90 % bei Standard-SaaS.
A54: 2. Sales Rep | B54: 18 | C54: Zweiter Vertrieb | D54: Human-in-the-Loop für komplexe Enterprise-Abschlüsse. | E54: KI-Hebel (KI-Position kann durch KI-Einsatz später eingestellt werden) | F54: =IF(COUNTIF(E54,"*Fix*")>0, B54, IF(COUNTIF(E54,"*KI-Agent*")>0, 99, B54 + VLOOKUP("AI-Personal-Hebel", '00_Input_Sandbox'!$B$4:$F$20, '00_Input_Sandbox'!$B$2-1, FALSE))) -> 18
A55: 1. Customer Success | B55: 12 | C55: Erster CS Manager | D55: KI-AGENT Substitution durch Wissens-Agent (RAG) für Support & Doku. [15] | F55: =IF(COUNTIF(E55,"*Fix*")>0, B55, IF(COUNTIF(E55,"*KI-Agent*")>0, 99, B55 + VLOOKUP("AI-Personal-Hebel", '00_Input_Sandbox'!$B$4:$F$20, '00_Input_Sandbox'!$B$2-1, FALSE))) -> 12
A56: 1. Marketing Manager | B56: 11 | C56: Marketing | D56: Fokus auf Content (ROI-Case Studies) und Industry-Partner. | E56: KI-Hebel (KI-Position kann durch KI-Einsatz später eingestellt werden) | F56: =IF(COUNTIF(E56,"*Fix*")>0, B56, IF(COUNTIF(E56,"*KI-Agent*")>0, 99, B56 + VLOOKUP("AI-Personal-Hebel", '00_Input_Sandbox'!$B$4:$F$20, '00_Input_Sandbox'!$B$2-1, FALSE))) -> 11
A57: 1. Product Manager | B57: 13 | C57: Product Management | D57: Überführung der Pilot-Learnings in das Kernprodukt. | E57: KI-Hebel (KI-Position kann durch KI-Einsatz später eingestellt werden) | F57: =IF(COUNTIF(E57,"*Fix*")>0, B57, IF(COUNTIF(E57,"*KI-Agent*")>0, 99, B57 + VLOOKUP("AI-Personal-Hebel", '00_Input_Sandbox'!$B$4:$F$20, '00_Input_Sandbox'!$B$2-1, FALSE))) -> 13
A58: 1. Office Manager | B58: 14 | C58: Admin/Office | D58: Übernahme zur administrativen Entlastung der Gründer. | E58: Fix (Strategische Rolle, kein Effekt durch KI Einsatz) | F58: =IF(COUNTIF(E58,"*Fix*")>0, B58, IF(COUNTIF(E58,"*KI-Agent*")>0, 99, B58 + VLOOKUP("AI-Personal-Hebel", '00_Input_Sandbox'!$B$4:$F$20, '00_Input_Sandbox'!$B$2-1, FALSE))) -> 14
A59: 3. Senior Engineer | B59: 18 | C59: Dritter Senior Engineer | D59: Ausbau der Enterprise-Readiness (SSO; Audit Logs). | E59: Fix (Strategische Rolle, kein Effekt durch KI Einsatz) | F59: =IF(COUNTIF(E59,"*Fix*")>0, B59, IF(COUNTIF(E59,"*KI-Agent*")>0, 99, B59 + VLOOKUP("AI-Personal-Hebel", '00_Input_Sandbox'!$B$4:$F$20, '00_Input_Sandbox'!$B$2-1, FALSE))) -> 18
A60: 4. Senior Engineer | B60: 24 | C60: Vierter Senior Engineer | D60: Zweite Dev-Squad zur Skalierung. | E60: KI-Agent (Position kann durch KI-Agenten ersetzt werden/ Hiring wenn überhaupt in ferner Zukunft) | F60: =IF(COUNTIF(E60,"*Fix*")>0, B60, IF(COUNTIF(E60,"*KI-Agent*")>0, 99, B60 + VLOOKUP("AI-Personal-Hebel", '00_Input_Sandbox'!$B$4:$F$20, '00_Input_Sandbox'!$B$2-1, FALSE))) -> 99
A61: 2. Junior Engineer | B61: 20 | C61: Zweiter Junior | D61: Team-Erweiterung. | E61: KI-Hebel (KI-Position kann durch KI-Einsatz später eingestellt werden) | F61: =IF(COUNTIF(E61,"*Fix*")>0, B61, IF(COUNTIF(E61,"*KI-Agent*")>0, 99, B61 + VLOOKUP("AI-Personal-Hebel", '00_Input_Sandbox'!$B$4:$F$20, '00_Input_Sandbox'!$B$2-1, FALSE))) -> 20
A62: 3. ML/AI Engineer | B62: 22 | C62: Dritter ML Engineer | D62: Optimierung der Inferenzkosten (COGS-Effizienz). | E62: KI-Hebel (KI-Position kann durch KI-Einsatz später eingestellt werden) | F62: =IF(COUNTIF(E62,"*Fix*")>0, B62, IF(COUNTIF(E62,"*KI-Agent*")>0, 99, B62 + VLOOKUP("AI-Personal-Hebel", '00_Input_Sandbox'!$B$4:$F$20, '00_Input_Sandbox'!$B$2-1, FALSE))) -> 22
A63: 3. Sales Rep | B63: 26 | C63: Dritter Vertrieb | D63: Marktausweitung (Batterie- & Elektronik-Sektor). | E63: KI-Agent (Position kann durch KI-Agenten ersetzt werden/ Hiring wenn überhaupt in ferner Zukunft) | F63: =IF(COUNTIF(E63,"*Fix*")>0, B63, IF(COUNTIF(E63,"*KI-Agent*")>0, 99, B63 + VLOOKUP("AI-Personal-Hebel", '00_Input_Sandbox'!$B$4:$F$20, '00_Input_Sandbox'!$B$2-1, FALSE))) -> 99
A64: 2. Customer Success | B64: 24 | C64: Zweiter CS Manager | D64: First Hire für komplexes Solution Architecting vor Ort. [13] | E64: Fix (Strategische Rolle, kein Effekt durch KI Einsatz) | F64: =IF(COUNTIF(E64,"*Fix*")>0, B64, IF(COUNTIF(E64,"*KI-Agent*")>0, 99, B64 + VLOOKUP("AI-Personal-Hebel", '00_Input_Sandbox'!$B$4:$F$20, '00_Input_Sandbox'!$B$2-1, FALSE))) -> 24
A65: 2. Marketing Manager | B65: 28 | C65: Zweiter Marketing | D65: Expansion des Partner-Netzwerks (Engineering Services). | E65: KI-Hebel (KI-Position kann durch KI-Einsatz später eingestellt werden) | F65: =IF(COUNTIF(E65,"*Fix*")>0, B65, IF(COUNTIF(E65,"*KI-Agent*")>0, 99, B65 + VLOOKUP("AI-Personal-Hebel", '00_Input_Sandbox'!$B$4:$F$20, '00_Input_Sandbox'!$B$2-1, FALSE))) -> 28
A66: 5. Senior Engineer | B66: 30 | C66: Fünfter Senior Engineer | D66: Übernahme. | E66: KI-Agent (Position kann durch KI-Agenten ersetzt werden/ Hiring wenn überhaupt in ferner Zukunft) | F66: =IF(COUNTIF(E66,"*Fix*")>0, B66, IF(COUNTIF(E66,"*KI-Agent*")>0, 99, B66 + VLOOKUP("AI-Personal-Hebel", '00_Input_Sandbox'!$B$4:$F$20, '00_Input_Sandbox'!$B$2-1, FALSE))) -> 99
A67: 3. Junior Engineer | B67: 32 | C67: Dritter Junior | D67: Übernahme. | E67: KI-Agent (Position kann durch KI-Agenten ersetzt werden/ Hiring wenn überhaupt in ferner Zukunft) | F67: =IF(COUNTIF(E67,"*Fix*")>0, B67, IF(COUNTIF(E67,"*KI-Agent*")>0, 99, B67 + VLOOKUP("AI-Personal-Hebel", '00_Input_Sandbox'!$B$4:$F$20, '00_Input_Sandbox'!$B$2-1, FALSE))) -> 99
... A70: 4. Sales Rep | B70: 36 | C70: Vierter Vertrieb | D70: Vertriebsskalierung. | E70: KI-Hebel (KI-Position kann durch KI-Einsatz später eingestellt werden) | F70: =IF(COUNTIF(E70,"*Fix*")>0, B70, IF(COUNTIF(E70,"*KI-Agent*")>0, 99, B70 + VLOOKUP("AI-Personal-Hebel", '00_Input_Sandbox'!$B$4:$F$20, '00_Input_Sandbox'!$B$2-1, FALSE))) -> 36
A71: 3. Customer Success | B71: 36 | C71: Dritter CS | E71: KI-Agent (Position kann durch KI-Agenten ersetzt werden/ Hiring wenn überhaupt in ferner Zukunft) | F71: =IF(COUNTIF(E71,"*Fix*")>0, B71, IF(COUNTIF(E71,"*KI-Agent*")>0, 99, B71 + VLOOKUP("AI-Personal-Hebel", '00_Input_Sandbox'!$B$4:$F$20, '00_Input_Sandbox'!$B$2-1, FALSE))) -> 99
A72: Finance Manager | B72: 18 | C72: Finance/Controlling | D72: Notwendig für professionelles Reporting ab Seed-Phase. | E72: Fix (Strategische Rolle, kein Effekt durch KI Einsatz) | F72: =IF(COUNTIF(E72,"*Fix*")>0, B72, IF(COUNTIF(E72,"*KI-Agent*")>0, 99, B72 + VLOOKUP("AI-Personal-Hebel", '00_Input_Sandbox'!$B$4:$F$20, '00_Input_Sandbox'!$B$2-1, FALSE))) -> 18
A73: 6. Senior Engineer | B73: 30 | C73: Sechster Senior | E73: KI-Agent (Position kann durch KI-Agenten ersetzt werden/ Hiring wenn überhaupt in ferner Zukunft) | F73: =IF(COUNTIF(E73,"*Fix*")>0, B73, IF(COUNTIF(E73,"*KI-Agent*")>0, 99, B73 + VLOOKUP("AI-Personal-Hebel", '00_Input_Sandbox'!$B$4:$F$20, '00_Input_Sandbox'!$B$2-1, FALSE))) -> 99
A74: 7. Senior Engineer | B74: 36 | C74: Siebter Senior | E74: KI-Agent (Position kann durch KI-Agenten ersetzt werden/ Hiring wenn überhaupt in ferner Zukunft) | F74: =IF(COUNTIF(E74,"*Fix*")>0, B74, IF(COUNTIF(E74,"*KI-Agent*")>0, 99, B74 + VLOOKUP("AI-Personal-Hebel", '00_Input_Sandbox'!$B$4:$F$20, '00_Input_Sandbox'!$B$2-1, FALSE))) -> 99
A75: 4. Junior Engineer | B75: 30 | C75: Vierter Junior | E75: KI-Agent (Position kann durch KI-Agenten ersetzt werden/ Hiring wenn überhaupt in ferner Zukunft) | F75: =IF(COUNTIF(E75,"*Fix*")>0, B75, IF(COUNTIF(E75,"*KI-Agent*")>0, 99, B75 + VLOOKUP("AI-Personal-Hebel", '00_Input_Sandbox'!$B$4:$F$20, '00_Input_Sandbox'!$B$2-1, FALSE))) -> 99
A76: 5. ML/AI Engineer | B76: 30 | C76: Fünfter ML Engineer | E76: KI-Agent (Position kann durch KI-Agenten ersetzt werden/ Hiring wenn überhaupt in ferner Zukunft) | F76: =IF(COUNTIF(E76,"*Fix*")>0, B76, IF(COUNTIF(E76,"*KI-Agent*")>0, 99, B76 + VLOOKUP("AI-Personal-Hebel", '00_Input_Sandbox'!$B$4:$F$20, '00_Input_Sandbox'!$B$2-1, FALSE))) -> 99
A77: 5. Sales Rep | B77: 34 | C77: Fünfter Vertrieb | E77: KI-Agent (Position kann durch KI-Agenten ersetzt werden/ Hiring wenn überhaupt in ferner Zukunft) | F77: =IF(COUNTIF(E77,"*Fix*")>0, B77, IF(COUNTIF(E77,"*KI-Agent*")>0, 99, B77 + VLOOKUP("AI-Personal-Hebel", '00_Input_Sandbox'!$B$4:$F$20, '00_Input_Sandbox'!$B$2-1, FALSE))) -> 99
A78: 4. Customer Success | B78: 34 | C78: Vierter CS | E78: KI-Agent (Position kann durch KI-Agenten ersetzt werden/ Hiring wenn überhaupt in ferner Zukunft) | F78: =IF(COUNTIF(E78,"*Fix*")>0, B78, IF(COUNTIF(E78,"*KI-Agent*")>0, 99, B78 + VLOOKUP("AI-Personal-Hebel", '00_Input_Sandbox'!$B$4:$F$20, '00_Input_Sandbox'!$B$2-1, FALSE))) -> 99
A79: 3. Marketing Manager | B79: 30 | C79: Dritter Marketing | E79: KI-Agent (Position kann durch KI-Agenten ersetzt werden/ Hiring wenn überhaupt in ferner Zukunft) | F79: =IF(COUNTIF(E79,"*Fix*")>0, B79, IF(COUNTIF(E79,"*KI-Agent*")>0, 99, B79 + VLOOKUP("AI-Personal-Hebel", '00_Input_Sandbox'!$B$4:$F$20, '00_Input_Sandbox'!$B$2-1, FALSE))) -> 99
A81: TECHNOLOGIE & CLOUD KOSTEN
A82: Cloud/Hosting Basis | B82: 1200 | C82: AWS/Azure/GCP Grundkosten €/Monat | D82: Höhere Last durch GPU-Inferenz und Vektordatenbanken.
A83: Cloud Skalierung pro Seat | B83: 50 | C83: Variable Kosten €/Seat/Monat | D83: Wechsel von Seat- auf Projekt-Basis (AI-intensive Rechenlast).
A84: AI/ML APIs Basis | B84: 1000 | C84: OpenAI/Anthropic etc. €/Monat | D84: Nutzung von Frontier Models (GPT-5/Claude) für Design-Logic.
A85: AI Kosten Wachstum/Monat | B85: 0.05 | C85: Steigerung mit Nutzung | D85: Skalierung proportional zur Nutzung und Datentiefe.
A86: SaaS Tools intern Basis | B86: 400 | C86: Slack, Notion, GitHub etc. €/Monat | D86: Slack; Notion; GitHub etc. (unverändert).
A87: SaaS Tools pro MA | B87: 100 | C87: Zusätzliche Lizenzen €/MA/Monat | D87: Inklusive KI-Coding-Tools (Copilot/Cursor) für Dev-Effizienz.
A88: Software-Lizenzen Dev | B88: 5000 | C88: IDE, Frameworks €/Jahr | D88: Spezialisierte Engineering-Tools und Frameworks (IDE).
A89: Sicherheit & Compliance | B89: 3500 | C89: Security Tools €/Monat | D89: Puffer für TISAX-Audits und laufendes Compliance-Monitoring. [17
A91: HARDWARE & EQUIPMENT
A92: Laptop pro MA | B92: 2500 | C92: Typisch: 1.500-3.000€ | D92: High-End Hardware zwingend für KI-Entwicklung (lokale Inferenz).
A93: Monitor & Peripherie | B93: 800 | C93: Typisch: 500-1.000€ | D93: Standard-Setup für Tech-Mitarbeiter.
A94: Ersatz-Zyklus Monate | B94: 36 | C94: Typisch: 36-48 Monate | D94: Branchenüblicher Turnus.
A95: Sonstige IT-Ausstattung/Jahr | B95: 2000 | C95: Server, Netzwerk etc. | D95: Puffer für Serverkomponenten/Netzwerk.
A97: BÜRO & FACILITIES
A98: Büromiete | B98: 1500 | C98: Coworking anfangs €/Monat | D98: Coworking-Fokus in der ersten Phase (Berlin Mitte/Kreuzberg).
A99: Büro-Upgrade ab Monat | B99: 18 | C99: Wann größeres Büro? | D99: Shift analog zur Einstellung von Solution Architects (Teamgröße).
A100: Neue Büromiete | B100: 4500 | C100: Kosten nach Upgrade €/Monat | D100: Anpassung an Berliner Marktpreise für ca. 15-20 Personen.
A101: Nebenkosten | B101: 300 | C101: Strom, Wasser, Heizung €/Monat | D101: Übernahme.
A102: Internet & Telefon | B102: 150 | C102: €/Monat | D102: Übernahme.
A103: Büroausstattung Initial | B103: 5000 | C103: Möbel, Einrichtung € | D103: Möbel und IT-Grundausstattung für Erst-Team.
A104: Bürobedarf pro MA | B104: 30 | C104: Verbrauchsmaterial €/MA/Monat | D104: Verbrauchsmaterial (unverändert).
A106: PROFESSIONAL SERVICES
A107: Rechtsanwalt Basis/Jahr | B107: 8000 | C107: Laufende Beratung €/Jahr
A108: RA pro Finanzierung | B108: 15000 | C108: Zusätzlich bei Funding €
A109: Steuerberater | B109: 800 | C109: Laufende Buchhaltung €/Monat
A110: Wirtschaftsprüfer/Jahr | B110: 12000 | C110: Ab Series A €/Jahr
...

Sheet 00_Input_Sandbox
A1: Aktives Szenario | B1: gering | C1: Einheit | D1: Gering (Auto-Fokus) | E1: Normal (Hybrid) | F1: Stark (Pack-Fokus) | G1: Argumentation / Quelle
A2: Spalten-Index (intern) | B2: =IF(B1="gering", 4, IF(B1="normal", 5, 6)) -> 4
A3: Kategorie | B3: Variable | C3: Einheit | D3: Gering | E3: Normal | F3: Stark | G3: Quelle
A4: Markt-Mix | B4: Anteil Packaging | C4: % | D4: 0.1 | E4: 0.6 | F4: 0.8 | G4: Lothar.bm: Packaging hat schnellere Zyklen.
A5: Vertrieb | B5: Startmonat Kunden | C5: Monate | D5: 14 | E5: 8 | F5: 4 | G5: Lothar.bm: IT-Hürden bei Automotive Tier-1.
A6: Revenue 1 | B6: Startpreis Seat/Jahr | C6: €/Monat | D6: 800 | E6: 1000 | F6: 1200 | G6: Value-based Pricing in Packaging (White Paper).
A7: Revenue 2 | B7: Consulting-Tagessatz | C7: €/Tag | D7: 1200 | E7: 1500 | F7: 1800 | G7: Expertenstatus (Haag/Candemir).
A8: Effizienz | B8: Iterations-Reduktion | C8: Faktor | D8: 1,2x | E8: 2,0x | F8: 3,0x | G8: White Paper: Redesign Trap vermeiden.
A9: Kosten | B9: Onboarding-Aufwand | C9: Stunden | D9: 120 | E9: 60 | F9: 30 | G9: Lothar.bm: Hoher Aufwand bei alten IT-Systemen.
A10: Effizienz | B10: AI-Personal-Hebel | D10: 0 | E10: 6 | F10: 99

Sheet P&L
A1: GEWINN- UND VERLUSTRECHNUNG (P&L)
A3: Position | B3: M1 | C3: M2 | D3: M3 | E3: M4 | F3: M5 | G3: M6 | H3: M7 | I3: M8 | J3: M9 | K3: M10 | L3: M11 | M3: M12 | N3: M13 | O3: M14 | P3: M15 | Q3: M16 | R3: M17 | S3: M18 | T3: M19 | U3: M20 | V3: M21 | W3: M22 | X3: M23 | Y3: M24 | Z3: M25 | AA3: M26 | AB3: M27 | AC3: M28 | AD3: M29 | AE3: M30 | AF3: M31 | AG3: M32 | AH3: M33 | AI3: M34 | AJ3: M35 | AK3: M36 | AL3: M37 | AM3: M38 | AN3: M39 | AO3: M40 | AP3: M41 | AQ3: M42 | AR3: M43 | AS3: M44 | AT3: M45 | AU3: M46 | AV3: M47 | AW3: M48 | AX3: M49 | AY3: M50 | AZ3: M51 | BA3: M52
A4: REVENUE
A5: Subscription Revenue | B5: =Revenue!B9 -> 0 | C5: =Revenue!C9 -> 0 | D5: =Revenue!D9 -> 0 | E5: =Revenue!E9 -> 0 | F5: =Revenue!F9 -> 0 | G5: =Revenue!G9 -> 0 | H5: =Revenue!H9 -> 0 | I5: =Revenue!I9 -> 0 | ... BA5: =Revenue!BA9 -> 5441.9558
A6: Enterprise Revenue | B6: =Revenue!B16 -> 0 | C6: =Revenue!C16 -> 0 | D6: =Revenue!D16 -> 0 | E6: =Revenue!E16 -> 0 | F6: =Revenue!F16 -> 0 | G6: =Revenue!G16 -> 0 | H6: =Revenue!H16 -> 0 | I6: =Revenue!I16 -> 0 | ... BA6: =Revenue!BA16 -> 153055.01
A7: TOTAL REVENUE | B7: =B5+B6 -> 0 | C7: =C5+C6 -> 0 | D7: =D5+D6 -> 0 | E7: =E5+E6 -> 0 | F7: =F5+F6 -> 0 | G7: =G5+G6 -> 0 | H7: =H5+H6 -> 0 | I7: =I5+I6 -> 0 | ... BA7: =BA5+BA6 -> 158496.96
A9: COST OF GOODS SOLD (COGS)
A10: Cloud Hosting (variable) | B10: =Costs!B82 -> 0 | C10: =Costs!C82 -> 0 | D10: =Costs!D82 -> 0 | E10: =Costs!E82 -> 0 | F10: =Costs!F82 -> 0 | G10: =Costs!G82 -> 0 | H10: =Costs!H82 -> 0 | I10: =Costs!I82 -> 0 | ... BA10: =Costs!BA82 -> 250
A11: AI/ML API Kosten | B11: =Costs!B83 -> 1000 | C11: =Costs!C83 -> 1050 | D11: =Costs!D83 -> 1102.5 | E11: =Costs!E83 -> 1157.625 | F11: =Costs!F83 -> 1215.5062 | G11: =Costs!G83 -> 1276.2816 | H11: =Costs!H83 -> 1340.0956 | I11: =Costs!I83 -> 1407.1004 | ... BA11: =Costs!BA83 -> 12040.77
A12: Payment Processing | B12: =Costs!B128 -> 0 | C12: =Costs!C128 -> 0 | D12: =Costs!D128 -> 0 | E12: =Costs!E128 -> 0 | F12: =Costs!F128 -> 0 | G12: =Costs!G128 -> 0 | H12: =Costs!H128 -> 0 | I12: =Costs!I128 -> 0 | ... BA12: =Costs!BA128 -> 3962.4241
A13: TOTAL COGS | B13: =SUM(B10:B12) -> 1000 | C13: =SUM(C10:C12) -> 1050 | D13: =SUM(D10:D12) -> 1102.5 | E13: =SUM(E10:E12) -> 1157.625 | F13: =SUM(F10:F12) -> 1215.5062 | G13: =SUM(G10:G12) -> 1276.2816 | H13: =SUM(H10:H12) -> 1340.0956 | I13: =SUM(I10:I12) -> 1407.1004 | ... BA13: =SUM(BA10:BA12) -> 16253.194
A15: GROSS PROFIT | B15: =B7-B13 -> -1000 | C15: =C7-C13 -> -1050 | D15: =D7-D13 -> -1102.5 | E15: =E7-E13 -> -1157.625 | F15: =F7-F13 -> -1215.5062 | G15: =G7-G13 -> -1276.2816 | H15: =H7-H13 -> -1340.0956 | I15: =I7-I13 -> -1407.1004 | ... BA15: =BA7-BA13 -> 142243.77
A16: Gross Margin % | B16: =IFERROR(B15/B7,0) -> 0 | C16: =IFERROR(C15/C7,0) -> 0 | D16: =IFERROR(D15/D7,0) -> 0 | E16: =IFERROR(E15/E7,0) -> 0 | F16: =IFERROR(F15/F7,0) -> 0 | G16: =IFERROR(G15/G7,0) -> 0 | H16: =IFERROR(H15/H7,0) -> 0 | I16: =IFERROR(I15/I7,0) -> 0 | ... BA16: =IFERROR(BA15/BA7,0) -> 0.89745423
A18: OPERATING EXPENSES
A19: Total Personnel | B19: =Costs!B78 -> 21780 | C19: =Costs!C78 -> 21780 | D19: =Costs!D78 -> 21780 | E19: =Costs!E78 -> 21780 | F19: =Costs!F78 -> 21780 | G19: =Costs!G78 -> 21780 | H19: =Costs!H78 -> 30855 | I19: =Costs!I78 -> 41946.667 | ... BA19: =Costs!BA78 -> 213383.14
A20: Total Technology | B20: =Costs!B87 -> 6816.6667 | C20: =Costs!C87 -> 6866.6667 | D20: =Costs!D87 -> 6919.1667 | E20: =Costs!E87 -> 6974.2917 | F20: =Costs!F87 -> 7032.1729 | G20: =Costs!G87 -> 7092.9482 | H20: =Costs!H87 -> 7256.7623 | I20: =Costs!I87 -> 7423.7671 | ... BA20: =Costs!BA87 -> 19907.436
A21: Total Office/Facilities | B21: =Costs!B94 -> 2040 | C21: =Costs!C94 -> 2040 | D21: =Costs!D94 -> 2040 | E21: =Costs!E94 -> 2040 | F21: =Costs!F94 -> 2040 | G21: =Costs!G94 -> 2040 | H21: =Costs!H94 -> 2070 | I21: =Costs!I94 -> 2100 | ... BA21: =Costs!BA94 -> 5580
A22: Total Professional Services | B22: =Costs!B101 -> 16883.333 | C22: =Costs!C101 -> 1883.3333 | D22: =Costs!D101 -> 1883.3333 | E22: =Costs!E101 -> 1883.3333 | F22: =Costs!F101 -> 16883.333 | G22: =Costs!G101 -> 1883.3333 | H22: =Costs!H101 -> 1883.3333 | I22: =Costs!I101 -> 1883.3333 | ... BA22: =Costs!BA101 -> 2883.3333
A23: Total Insurance & Bank | B23: =Costs!B108 -> 591.66667 | C23: =Costs!C108 -> 591.66667 | D23: =Costs!D108 -> 591.66667 | E23: =Costs!E108 -> 591.66667 | F23: =Costs!F108 -> 591.66667 | G23: =Costs!G108 -> 591.66667 | H23: =Costs!H108 -> 591.66667 | I23: =Costs!I108 -> 591.66667 | ... BA23: =Costs!BA108 -> 591.66667
A24: Total Marketing & Sales | B24: =Costs!B117 -> 4383.3333 | C24: =Costs!C117 -> 4408.3333 | D24: =Costs!D117 -> 4434.5833 | E24: =Costs!E117 -> 4462.1458 | F24: =Costs!F117 -> 4491.0865 | G24: =Costs!G117 -> 4521.4741 | H24: =Costs!H117 -> 4553.3812 | I24: =Costs!I117 -> 4586.8835 | ... BA24: =Costs!BA117 -> 10903.718
A25: Total Other OpEx | B25: =Costs!B125 -> 11191.667 | C25: =Costs!C125 -> 1291.6667 | D25: =Costs!D125 -> 1291.6667 | E25: =Costs!E125 -> 1291.6667 | F25: =Costs!F125 -> 1291.6667 | G25: =Costs!G125 -> 1291.6667 | H25: =Costs!H125 -> 4966.6667 | I25: =Costs!I125 -> 5341.6667 | ... BA25: =Costs!BA125 -> 8041.6667
A26: Contingency/Buffer | B26: =Costs!B130 -> 3184.3333 | C26: =Costs!C130 -> 1943.0833 | D26: =Costs!D130 -> 1947.0208 | E26: =Costs!E130 -> 1951.1552 | F26: =Costs!F130 -> 2705.4963 | G26: =Costs!G130 -> 1960.0545 | H26: =Costs!H130 -> 2608.8405 | I26: =Costs!I130 -> 3193.6992 | ... BA26: =Costs!BA130 -> 13064.548
A27: TOTAL OPERATING EXPENSES | B27: =SUM(B19:B26) -> 66871 | C27: =SUM(C19:C26) -> 40804.75 | D27: =SUM(D19:D26) -> 40887.438 | E27: =SUM(E19:E26) -> 40974.259 | F27: =SUM(F19:F26) -> 56815.422 | G27: =SUM(G19:G26) -> 41161.143 | H27: =SUM(H19:H26) -> 54785.651 | I27: =SUM(I19:I26) -> 67067.683 | ... BA27: =SUM(BA19:BA26) -> 274355.5
A29: EBITDA | B29: =B15-B27 -> -67871 | C29: =C15-C27 -> -41854.75 | D29: =D15-D27 -> -41989.938 | E29: =E15-E27 -> -42131.884 | F29: =F15-F27 -> -58030.929 | G29: =G15-G27 -> -42437.425 | H29: =H15-H27 -> -56125.746 | I29: =I15-I27 -> -68474.784 | ... BA29: =BA15-BA27 -> -132111.73
A30: EBITDA Margin % | B30: =IFERROR(B29/B7,0) -> 0 | C30: =IFERROR(C29/C7,0) -> 0 | D30: =IFERROR(D29/D7,0) -> 0 | E30: =IFERROR(E29/E7,0) -> 0 | F30: =IFERROR(F29/F7,0) -> 0 | G30: =IFERROR(G29/G7,0) -> 0 | H30: =IFERROR(H29/H7,0) -> 0 | I30: =IFERROR(I29/I7,0) -> 0 | ... BA30: =IFERROR(BA29/BA7,0) -> -0.83352849
A32: Depreciation & Amortization | B32: =Costs!B123/Inputs!$B$135/12 -> 275 | C32: =Costs!C123/Inputs!$B$135/12 -> 0 | D32: =Costs!D123/Inputs!$B$135/12 -> 0 | E32: =Costs!E123/Inputs!$B$135/12 -> 0 | F32: =Costs!F123/Inputs!$B$135/12 -> 0 | G32: =Costs!G123/Inputs!$B$135/12 -> 0 | H32: =Costs!H123/Inputs!$B$135/12 -> 91.666667 | I32: =Costs!I123/Inputs!$B$135/12 -> 91.666667 | ... BA32: =Costs!BA123/Inputs!$B$135/12 -> 0
A34: EBIT (Operating Income) | B34: =B29-B32 -> -68146 | C34: =C29-C32 -> -41854.75 | D34: =D29-D32 -> -41989.938 | E34: =E29-E32 -> -42131.884 | F34: =F29-F32 -> -58030.929 | G34: =G29-G32 -> -42437.425 | H34: =H29-H32 -> -56217.413 | I34: =I29-I32 -> -68566.45 | ... BA34: =BA29-BA32 -> -132111.73
A36: EBT (Earnings Before Tax) | B36: =B34 -> -68146 | C36: =C34 -> -41854.75 | D36: =D34 -> -41989.938 | E36: =E34 -> -42131.884 | F36: =F34 -> -58030.929 | G36: =G34 -> -42437.425 | H36: =H34 -> -56217.413 | I36: =I34 -> -68566.45 | ... BA36: =BA34 -> -132111.73
A37: Income Tax | B37: =IF(B36>0,B36*Inputs!$B$7,0) -> 0 | C37: =IF(C36>0,C36*Inputs!$B$7,0) -> 0 | D37: =IF(D36>0,D36*Inputs!$B$7,0) -> 0 | E37: =IF(E36>0,E36*Inputs!$B$7,0) -> 0 | F37: =IF(F36>0,F36*Inputs!$B$7,0) -> 0 | G37: =IF(G36>0,G36*Inputs!$B$7,0) -> 0 | H37: =IF(H36>0,H36*Inputs!$B$7,0) -> 0 | I37: =IF(I36>0,I36*Inputs!$B$7,0) -> 0 | ... BA37: =IF(BA36>0,BA36*Inputs!$B$7,0) -> 0
A39: NET INCOME | B39: =B36-B37 -> -68146 | C39: =C36-C37 -> -41854.75 | D39: =D36-D37 -> -41989.938 | E39: =E36-E37 -> -42131.884 | F39: =F36-F37 -> -58030.929 | G39: =G36-G37 -> -42437.425 | H39: =H36-H37 -> -56217.413 | I39: =I36-I37 -> -68566.45 | ... BA39: =BA36-BA37 -> -132111.73
A40: Net Margin % | B40: =IFERROR(B39/B7,0) -> 0 | C40: =IFERROR(C39/C7,0) -> 0 | D40: =IFERROR(D39/D7,0) -> 0 | E40: =IFERROR(E39/E7,0) -> 0 | F40: =IFERROR(F39/F7,0) -> 0 | G40: =IFERROR(G39/G7,0) -> 0 | H40: =IFERROR(H39/H7,0) -> 0 | I40: =IFERROR(I39/I7,0) -> 0 | ... BA40: =IFERROR(BA39/BA7,0) -> -0.83352849

Sheet Revenue
A1: UMSATZMODELL - Detaillierte Aufschlüsselung
B2: 46113 | C2: 46143 | D2: 46174 | E2: 46204 | F2: 46235 | G2: 46266 | H2: 46296 | I2: 46327 | J2: 46357 | K2: 46388 | L2: 46419 | M2: 46447 | N2: 46478 | O2: 46508 | P2: 46539 | Q2: 46569 | R2: 46600 | S2: 46631 | T2: 46661 | U2: 46692 | V2: 46722 | W2: 46753 | X2: 46784 | Y2: 46813 | Z2: 46844 | AA2: 46874 | AB2: 46905 | AC2: 46935 | AD2: 46966 | AE2: 46997 | AF2: 47027 | AG2: 47058 | AH2: 47088 | AI2: 47119 | AJ2: 47150 | AK2: 47178 | AL2: 47209 | AM2: 47239 | AN2: 47270 | AO2: 47300 | AP2: 47331 | AQ2: 47362 | AR2: 47392 | AS2: 47423 | AT2: 47453 | AU2: 47484 | AV2: 47515 | AW2: 47543 | AX2: 47574 | AY2: 47604 | AZ2: 47635 | BA2: 47665
A3: Kennzahl | B3: M1 | C3: M2 | D3: M3 | E3: M4 | F3: M5 | G3: M6 | H3: M7 | I3: M8 | J3: M9 | K3: M10 | L3: M11 | M3: M12 | N3: M13 | O3: M14 | P3: M15 | Q3: M16 | R3: M17 | S3: M18 | T3: M19 | U3: M20 | V3: M21 | W3: M22 | X3: M23 | Y3: M24 | Z3: M25 | AA3: M26 | AB3: M27 | AC3: M28 | AD3: M29 | AE3: M30 | AF3: M31 | AG3: M32 | AH3: M33 | AI3: M34 | AJ3: M35 | AK3: M36 | AL3: M37 | AM3: M38 | AN3: M39 | AO3: M40 | AP3: M41 | AQ3: M42 | AR3: M43 | AS3: M44 | AT3: M45 | AU3: M46 | AV3: M47 | AW3: M48 | AX3: M49 | AY3: M50 | AZ3: M51 | BA3: M52
A4: Preis pro Seat/Monat (€) | B4: =IFERROR(Inputs!$B$20/12*(1+Inputs!$B$21)^(INT((1-1)/12)),0) -> 800 | C4: =Inputs!$B$20/12*(1+Inputs!$B$21)^INT((2-1)/12) -> 800 | D4: =Inputs!$B$20/12*(1+Inputs!$B$21)^INT((3-1)/12) -> 800 | E4: =Inputs!$B$20/12*(1+Inputs!$B$21)^INT((4-1)/12) -> 800 | F4: =Inputs!$B$20/12*(1+Inputs!$B$21)^INT((5-1)/12) -> 800 | G4: =Inputs!$B$20/12*(1+Inputs!$B$21)^INT((6-1)/12) -> 800 | H4: =Inputs!$B$20/12*(1+Inputs!$B$21)^INT((7-1)/12) -> 800 | I4: =Inputs!$B$20/12*(1+Inputs!$B$21)^INT((8-1)/12) -> 800 | J4: =Inputs!$B$20/12*(1+Inputs!$B$21)^INT((9-1)/12) -> 800 | K4: =Inputs!$B$20/12*(1+Inputs!$B$21)^INT((10-1)/12) -> 800 | L4: =Inputs!$B$20/12*(1+Inputs!$B$21)^INT((11-1)/12) -> 800 | M4: =Inputs!$B$20/12*(1+Inputs!$B$21)^INT((12-1)/12) -> 800 | N4: =Inputs!$B$20/12*(1+Inputs!$B$21)^INT((13-1)/12) -> 864 | O4: =Inputs!$B$20/12*(1+Inputs!$B$21)^INT((14-1)/12) -> 864 | P4: =Inputs!$B$20/12*(1+Inputs!$B$21)^INT((15-1)/12) -> 864 | Q4: =Inputs!$B$20/12*(1+Inputs!$B$21)^INT((16-1)/12) -> 864 | R4: =Inputs!$B$20/12*(1+Inputs!$B$21)^INT((17-1)/12) -> 864 | S4: =Inputs!$B$20/12*(1+Inputs!$B$21)^INT((18-1)/12) -> 864 | T4: =Inputs!$B$20/12*(1+Inputs!$B$21)^INT((19-1)/12) -> 864 | U4: =Inputs!$B$20/12*(1+Inputs!$B$21)^INT((20-1)/12) -> 864 | V4: =Inputs!$B$20/12*(1+Inputs!$B$21)^INT((21-1)/12) -> 864 | W4: =Inputs!$B$20/12*(1+Inputs!$B$21)^INT((22-1)/12) -> 864 | X4: =Inputs!$B$20/12*(1+Inputs!$B$21)^INT((23-1)/12) -> 864 | Y4: =Inputs!$B$20/12*(1+Inputs!$B$21)^INT((24-1)/12) -> 864 | Z4: =Inputs!$B$20/12*(1+Inputs!$B$21)^INT((25-1)/12) -> 933.12 | AA4: =Inputs!$B$20/12*(1+Inputs!$B$21)^INT((26-1)/12) -> 933.12 | AB4: =Inputs!$B$20/12*(1+Inputs!$B$21)^INT((27-1)/12) -> 933.12 | AC4: =Inputs!$B$20/12*(1+Inputs!$B$21)^INT((28-1)/12) -> 933.12 | AD4: =Inputs!$B$20/12*(1+Inputs!$B$21)^INT((29-1)/12) -> 933.12 | AE4: =Inputs!$B$20/12*(1+Inputs!$B$21)^INT((30-1)/12) -> 933.12 | AF4: =Inputs!$B$20/12*(1+Inputs!$B$21)^INT((31-1)/12) -> 933.12 | AG4: =Inputs!$B$20/12*(1+Inputs!$B$21)^INT((32-1)/12) -> 933.12 | AH4: =Inputs!$B$20/12*(1+Inputs!$B$21)^INT((33-1)/12) -> 933.12 | AI4: =Inputs!$B$20/12*(1+Inputs!$B$21)^INT((34-1)/12) -> 933.12 | AJ4: =Inputs!$B$20/12*(1+Inputs!$B$21)^INT((35-1)/12) -> 933.12 | AK4: =Inputs!$B$20/12*(1+Inputs!$B$21)^INT((36-1)/12) -> 933.12 | AL4: =Inputs!$B$20/12*(1+Inputs!$B$21)^INT((37-1)/12) -> 1007.7696 | AM4: =Inputs!$B$20/12*(1+Inputs!$B$21)^INT((38-1)/12) -> 1007.7696 | AN4: =Inputs!$B$20/12*(1+Inputs!$B$21)^INT((39-1)/12) -> 1007.7696 | AO4: =Inputs!$B$20/12*(1+Inputs!$B$21)^INT((40-1)/12) -> 1007.7696 | AP4: =Inputs!$B$20/12*(1+Inputs!$B$21)^INT((41-1)/12) -> 1007.7696 | AQ4: =Inputs!$B$20/12*(1+Inputs!$B$21)^INT((42-1)/12) -> 1007.7696 | AR4: =Inputs!$B$20/12*(1+Inputs!$B$21)^INT((43-1)/12) -> 1007.7696 | AS4: =Inputs!$B$20/12*(1+Inputs!$B$21)^INT((44-1)/12) -> 1007.7696 | AT4: =Inputs!$B$20/12*(1+Inputs!$B$21)^INT((45-1)/12) -> 1007.7696 | AU4: =Inputs!$B$20/12*(1+Inputs!$B$21)^INT((46-1)/12) -> 1007.7696 | AV4: =Inputs!$B$20/12*(1+Inputs!$B$21)^INT((47-1)/12) -> 1007.7696 | AW4: =Inputs!$B$20/12*(1+Inputs!$B$21)^INT((48-1)/12) -> 1007.7696 | AX4: =Inputs!$B$20/12*(1+Inputs!$B$21)^INT((49-1)/12) -> 1088.3912 | AY4: =Inputs!$B$20/12*(1+Inputs!$B$21)^INT((50-1)/12) -> 1088.3912 | AZ4: =Inputs!$B$20/12*(1+Inputs!$B$21)^INT((51-1)/12) -> 1088.3912 | BA4: =Inputs!$B$20/12*(1+Inputs!$B$21)^INT((52-1)/12) -> 1088.3912
A5: Neue Seats | B5: =IF(1>=Inputs!$B$22,Inputs!$B$23,0) -> 0 | C5: =IF(2>=Inputs!$B$22,IF(2=Inputs!$B$22,Inputs!$B$23,ROUND(B8*Inputs!$B$24,0)),0) -> 0 | D5: =IF(3>=Inputs!$B$22,IF(3=Inputs!$B$22,Inputs!$B$23,ROUND(C8*Inputs!$B$24,0)),0) -> 0 | E5: =IF(4>=Inputs!$B$22,IF(4=Inputs!$B$22,Inputs!$B$23,ROUND(D8*Inputs!$B$24,0)),0) -> 0 | F5: =IF(5>=Inputs!$B$22,IF(5=Inputs!$B$22,Inputs!$B$23,ROUND(E8*Inputs!$B$24,0)),0) -> 0 | G5: =IF(6>=Inputs!$B$22,IF(6=Inputs!$B$22,Inputs!$B$23,ROUND(F8*Inputs!$B$24,0)),0) -> 0 | H5: =IF(7>=Inputs!$B$22,IF(7=Inputs!$B$22,Inputs!$B$23,ROUND(G8*Inputs!$B$24,0)),0) -> 0 | I5: =IF(8>=Inputs!$B$22,IF(8=Inputs!$B$22,Inputs!$B$23,ROUND(H8*Inputs!$B$24,0)),0) -> 0 | J5: =IF(9>=Inputs!$B$22,IF(9=Inputs!$B$22,Inputs!$B$23,ROUND(I8*Inputs!$B$24,0)),0) -> 0 | K5: =IF(10>=Inputs!$B$22,IF(10=Inputs!$B$22,Inputs!$B$23,ROUND(J8*Inputs!$B$24,0)),0) -> 0 | L5: =IF(11>=Inputs!$B$22,IF(11=Inputs!$B$22,Inputs!$B$23,ROUND(K8*Inputs!$B$24,0)),0) -> 0 | M5: =IF(12>=Inputs!$B$22,IF(12=Inputs!$B$22,Inputs!$B$23,ROUND(L8*Inputs!$B$24,0)),0) -> 0 | N5: =IF(13>=Inputs!$B$22,IF(13=Inputs!$B$22,Inputs!$B$23,ROUND(M8*Inputs!$B$24,0)),0) -> 0 | O5: =IF(14>=Inputs!$B$22,IF(14=Inputs!$B$22,Inputs!$B$23,ROUND(N8*Inputs!$B$24,0)),0) -> 5 | P5: =IF(15>=Inputs!$B$22,IF(15=Inputs!$B$22,Inputs!$B$23,ROUND(O8*Inputs!$B$24,0)),0) -> 0 | Q5: =IF(16>=Inputs!$B$22,IF(16=Inputs!$B$22,Inputs!$B$23,ROUND(P8*Inputs!$B$24,0)),0) -> 0 | R5: =IF(17>=Inputs!$B$22,IF(17=Inputs!$B$22,Inputs!$B$23,ROUND(Q8*Inputs!$B$24,0)),0) -> 0 | S5: =IF(18>=Inputs!$B$22,IF(18=Inputs!$B$22,Inputs!$B$23,ROUND(R8*Inputs!$B$24,0)),0) -> 0 | T5: =IF(19>=Inputs!$B$22,IF(19=Inputs!$B$22,Inputs!$B$23,ROUND(S8*Inputs!$B$24,0)),0) -> 0 | U5: =IF(20>=Inputs!$B$22,IF(20=Inputs!$B$22,Inputs!$B$23,ROUND(T8*Inputs!$B$24,0)),0) -> 0 | V5: =IF(21>=Inputs!$B$22,IF(21=Inputs!$B$22,Inputs!$B$23,ROUND(U8*Inputs!$B$24,0)),0) -> 0 | W5: =IF(22>=Inputs!$B$22,IF(22=Inputs!$B$22,Inputs!$B$23,ROUND(V8*Inputs!$B$24,0)),0) -> 0 | X5: =IF(23>=Inputs!$B$22,IF(23=Inputs!$B$22,Inputs!$B$23,ROUND(W8*Inputs!$B$24,0)),0) -> 0 | Y5: =IF(24>=Inputs!$B$22,IF(24=Inputs!$B$22,Inputs!$B$23,ROUND(X8*Inputs!$B$24,0)),0) -> 0 | Z5: =IF(25>=Inputs!$B$22,IF(25=Inputs!$B$22,Inputs!$B$23,ROUND(Y8*Inputs!$B$24,0)),0) -> 0 | AA5: =IF(26>=Inputs!$B$22,IF(26=Inputs!$B$22,Inputs!$B$23,ROUND(Z8*Inputs!$B$24,0)),0) -> 0 | AB5: =IF(27>=Inputs!$B$22,IF(27=Inputs!$B$22,Inputs!$B$23,ROUND(AA8*Inputs!$B$24,0)),0) -> 0 | AC5: =IF(28>=Inputs!$B$22,IF(28=Inputs!$B$22,Inputs!$B$23,ROUND(AB8*Inputs!$B$24,0)),0) -> 0 | AD5: =IF(29>=Inputs!$B$22,IF(29=Inputs!$B$22,Inputs!$B$23,ROUND(AC8*Inputs!$B$24,0)),0) -> 0 | AE5: =IF(30>=Inputs!$B$22,IF(30=Inputs!$B$22,Inputs!$B$23,ROUND(AD8*Inputs!$B$24,0)),0) -> 0 | AF5: =IF(31>=Inputs!$B$22,IF(31=Inputs!$B$22,Inputs!$B$23,ROUND(AE8*Inputs!$B$24,0)),0) -> 0 | AG5: =IF(32>=Inputs!$B$22,IF(32=Inputs!$B$22,Inputs!$B$23,ROUND(AF8*Inputs!$B$24,0)),0) -> 0 | AH5: =IF(33>=Inputs!$B$22,IF(33=Inputs!$B$22,Inputs!$B$23,ROUND(AG8*Inputs!$B$24,0)),0) -> 0 | AI5: =IF(34>=Inputs!$B$22,IF(34=Inputs!$B$22,Inputs!$B$23,ROUND(AH8*Inputs!$B$24,0)),0) -> 0 | AJ5: =IF(35>=Inputs!$B$22,IF(35=Inputs!$B$22,Inputs!$B$23,ROUND(AI8*Inputs!$B$24,0)),0) -> 0 | AK5: =IF(36>=Inputs!$B$22,IF(36=Inputs!$B$22,Inputs!$B$23,ROUND(AJ8*Inputs!$B$24,0)),0) -> 0 | AL5: =IF(37>=Inputs!$B$22,IF(37=Inputs!$B$22,Inputs!$B$23,ROUND(AK8*Inputs!$B$24,0)),0) -> 0 | AM5: =IF(38>=Inputs!$B$22,IF(38=Inputs!$B$22,Inputs!$B$23,ROUND(AL8*Inputs!$B$24,0)),0) -> 0 | AN5: =IF(39>=Inputs!$B$22,IF(39=Inputs!$B$22,Inputs!$B$23,ROUND(AM8*Inputs!$B$24,0)),0) -> 0 | AO5: =IF(40>=Inputs!$B$22,IF(40=Inputs!$B$22,Inputs!$B$23,ROUND(AN8*Inputs!$B$24,0)),0) -> 0 | AP5: =IF(41>=Inputs!$B$22,IF(41=Inputs!$B$22,Inputs!$B$23,ROUND(AO8*Inputs!$B$24,0)),0) -> 0 | AQ5: =IF(42>=Inputs!$B$22,IF(42=Inputs!$B$22,Inputs!$B$23,ROUND(AP8*Inputs!$B$24,0)),0) -> 0 | AR5: =IF(43>=Inputs!$B$22,IF(43=Inputs!$B$22,Inputs!$B$23,ROUND(AQ8*Inputs!$B$24,0)),0) -> 0 | AS5: =IF(44>=Inputs!$B$22,IF(44=Inputs!$B$22,Inputs!$B$23,ROUND(AR8*Inputs!$B$24,0)),0) -> 0 | AT5: =IF(45>=Inputs!$B$22,IF(45=Inputs!$B$22,Inputs!$B$23,ROUND(AS8*Inputs!$B$24,0)),0) -> 0 | AU5: =IF(46>=Inputs!$B$22,IF(46=Inputs!$B$22,Inputs!$B$23,ROUND(AT8*Inputs!$B$24,0)),0) -> 0 | AV5: =IF(47>=Inputs!$B$22,IF(47=Inputs!$B$22,Inputs!$B$23,ROUND(AU8*Inputs!$B$24,0)),0) -> 0 | AW5: =IF(48>=Inputs!$B$22,IF(48=Inputs!$B$22,Inputs!$B$23,ROUND(AV8*Inputs!$B$24,0)),0) -> 0 | AX5: =IF(49>=Inputs!$B$22,IF(49=Inputs!$B$22,Inputs!$B$23,ROUND(AW8*Inputs!$B$24,0)),0) -> 0 | AY5: =IF(50>=Inputs!$B$22,IF(50=Inputs!$B$22,Inputs!$B$23,ROUND(AX8*Inputs!$B$24,0)),0) -> 0 | AZ5: =IF(51>=Inputs!$B$22,IF(51=Inputs!$B$22,Inputs!$B$23,ROUND(AY8*Inputs!$B$24,0)),0) -> 0 | BA5: =IF(52>=Inputs!$B$22,IF(52=Inputs!$B$22,Inputs!$B$23,ROUND(AZ8*Inputs!$B$24,0)),0) -> 0
A6: Churned Seats | B6: =0 -> 0 | C6: =IF(B8>0,ROUND(B8*Inputs!$B$28/12,0),0) -> 0 | D6: =IF(C8>0,ROUND(C8*Inputs!$B$28/12,0),0) -> 0 | E6: =IF(D8>0,ROUND(D8*Inputs!$B$28/12,0),0) -> 0 | F6: =IF(E8>0,ROUND(E8*Inputs!$B$28/12,0),0) -> 0 | G6: =IF(F8>0,ROUND(F8*Inputs!$B$28/12,0),0) -> 0 | H6: =IF(G8>0,ROUND(G8*Inputs!$B$28/12,0),0) -> 0 | I6: =IF(H8>0,ROUND(H8*Inputs!$B$28/12,0),0) -> 0 | J6: =IF(I8>0,ROUND(I8*Inputs!$B$28/12,0),0) -> 0 | ... BA6: =IF(AZ8>0,ROUND(AZ8*Inputs!$B$28/12,0),0) -> 0
A7: Net New Seats | B7: =B5-B6 -> 0 | C7: =C5-C6 -> 0 | D7: =D5-D6 -> 0 | E7: =E5-E6 -> 0 | F7: =F5-F6 -> 0 | G7: =G5-G6 -> 0 | H7: =H5-H6 -> 0 | I7: =I5-I6 -> 0 | ... BA7: =BA5-BA6 -> 0
A8: Total Active Seats | B8: =B7 -> 0 | C8: =B8+C7 -> 0 | D8: =C8+D7 -> 0 | E8: =D8+E7 -> 0 | F8: =E8+F7 -> 0 | G8: =F8+G7 -> 0 | H8: =G8+H7 -> 0 | I8: =H8+I7 -> 0 | J8: =I8+J7 -> 0 | ... BA8: =AZ8+BA7 -> 5
A9: Monthly Subscription Revenue (€) | B9: =B8*B4 -> 0 | C9: =C8*C4 -> 0 | D9: =D8*D4 -> 0 | E9: =E8*E4 -> 0 | F9: =F8*F4 -> 0 | G9: =G8*G4 -> 0 | H9: =H8*H4 -> 0 | I9: =I8*I4 -> 0 | ... BA9: =BA8*BA4 -> 5441.9558
A10: Subscription ARR (€) | B10: =B9*12 -> 0 | C10: =C9*12 -> 0 | D10: =D9*12 -> 0 | E10: =E9*12 -> 0 | F10: =F9*12 -> 0 | G10: =G9*12 -> 0 | H10: =H9*12 -> 0 | I10: =I9*12 -> 0 | ... BA10: =BA9*12 -> 65303.47
A11: HIER FEHLT CONSULTING UMSATZ...AUSSERDEM SIND DIE PREISE FÜR SEATS und PRojekte zu gering
A12: 3v | B12: =IF(AND(1>=Inputs!$B$25,MOD(1-Inputs!$B$25,3)=0),Inputs!$B$27,0) -> 0 | C12: =IF(AND(2>=Inputs!$B$25,MOD(2-Inputs!$B$25,3)=0),Inputs!$B$27,0) -> 0 | D12: =IF(AND(3>=Inputs!$B$25,MOD(3-Inputs!$B$25,3)=0),Inputs!$B$27,0) -> 0 | E12: =IF(AND(4>=Inputs!$B$25,MOD(4-Inputs!$B$25,3)=0),Inputs!$B$27,0) -> 0 | F12: =IF(AND(5>=Inputs!$B$25,MOD(5-Inputs!$B$25,3)=0),Inputs!$B$27,0) -> 0 | G12: =IF(AND(6>=Inputs!$B$25,MOD(6-Inputs!$B$25,3)=0),Inputs!$B$27,0) -> 0 | H12: =IF(AND(7>=Inputs!$B$25,MOD(7-Inputs!$B$25,3)=0),Inputs!$B$27,0) -> 0 | I12: =IF(AND(8>=Inputs!$B$25,MOD(8-Inputs!$B$25,3)=0),Inputs!$B$27,0) -> 0 | J12: =IF(AND(9>=Inputs!$B$25,MOD(9-Inputs!$B$25,3)=0),Inputs!$B$27,0) -> 0 | K12: =IF(AND(10>=Inputs!$B$25,MOD(10-Inputs!$B$25,3)=0),Inputs!$B$27,0) -> 0 | L12: =IF(AND(11>=Inputs!$B$25,MOD(11-Inputs!$B$25,3)=0),Inputs!$B$27,0) -> 0 | M12: =IF(AND(12>=Inputs!$B$25,MOD(12-Inputs!$B$25,3)=0),Inputs!$B$27,0) -> 0 | N12: =IF(AND(13>=Inputs!$B$25,MOD(13-Inputs!$B$25,3)=0),Inputs!$B$27,0) -> 0 | O12: =IF(AND(14>=Inputs!$B$25,MOD(14-Inputs!$B$25,3)=0),Inputs!$B$27,0) -> 0 | P12: =IF(AND(15>=Inputs!$B$25,MOD(15-Inputs!$B$25,3)=0),Inputs!$B$27,0) -> 0 | Q12: =IF(AND(16>=Inputs!$B$25,MOD(16-Inputs!$B$25,3)=0),Inputs!$B$27,0) -> 0 | R12: =IF(AND(17>=Inputs!$B$25,MOD(17-Inputs!$B$25,3)=0),Inputs!$B$27,0) -> 0 | S12: =IF(AND(18>=Inputs!$B$25,MOD(18-Inputs!$B$25,3)=0),Inputs!$B$27,0) -> 0 | T12: =IF(AND(19>=Inputs!$B$25,MOD(19-Inputs!$B$25,3)=0),Inputs!$B$27,0) -> 0 | U12: =IF(AND(20>=Inputs!$B$25,MOD(20-Inputs!$B$25,3)=0),Inputs!$B$27,0) -> 0 | V12: =IF(AND(21>=Inputs!$B$25,MOD(21-Inputs!$B$25,3)=0),Inputs!$B$27,0) -> 0 | W12: =IF(AND(22>=Inputs!$B$25,MOD(22-Inputs!$B$25,3)=0),Inputs!$B$27,0) -> 0 | X12: =IF(AND(23>=Inputs!$B$25,MOD(23-Inputs!$B$25,3)=0),Inputs!$B$27,0) -> 0 | Y12: =IF(AND(24>=Inputs!$B$25,MOD(24-Inputs!$B$25,3)=0),Inputs!$B$27,0) -> 1 | Z12: =IF(AND(25>=Inputs!$B$25,MOD(25-Inputs!$B$25,3)=0),Inputs!$B$27,0) -> 0 | AA12: =IF(AND(26>=Inputs!$B$25,MOD(26-Inputs!$B$25,3)=0),Inputs!$B$27,0) -> 0 | AB12: =IF(AND(27>=Inputs!$B$25,MOD(27-Inputs!$B$25,3)=0),Inputs!$B$27,0) -> 1 | AC12: =IF(AND(28>=Inputs!$B$25,MOD(28-Inputs!$B$25,3)=0),Inputs!$B$27,0) -> 0 | AD12: =IF(AND(29>=Inputs!$B$25,MOD(29-Inputs!$B$25,3)=0),Inputs!$B$27,0) -> 0 | AE12: =IF(AND(30>=Inputs!$B$25,MOD(30-Inputs!$B$25,3)=0),Inputs!$B$27,0) -> 1 | AF12: =IF(AND(31>=Inputs!$B$25,MOD(31-Inputs!$B$25,3)=0),Inputs!$B$27,0) -> 0 | AG12: =IF(AND(32>=Inputs!$B$25,MOD(32-Inputs!$B$25,3)=0),Inputs!$B$27,0) -> 0 | AH12: =IF(AND(33>=Inputs!$B$25,MOD(33-Inputs!$B$25,3)=0),Inputs!$B$27,0) -> 1 | AI12: =IF(AND(34>=Inputs!$B$25,MOD(34-Inputs!$B$25,3)=0),Inputs!$B$27,0) -> 0 | AJ12: =IF(AND(35>=Inputs!$B$25,MOD(35-Inputs!$B$25,3)=0),Inputs!$B$27,0) -> 0 | AK12: =IF(AND(36>=Inputs!$B$25,MOD(36-Inputs!$B$25,3)=0),Inputs!$B$27,0) -> 1 | AL12: =IF(AND(37>=Inputs!$B$25,MOD(37-Inputs!$B$25,3)=0),Inputs!$B$27,0) -> 0 | AM12: =IF(AND(38>=Inputs!$B$25,MOD(38-Inputs!$B$25,3)=0),Inputs!$B$27,0) -> 0 | AN12: =IF(AND(39>=Inputs!$B$25,MOD(39-Inputs!$B$25,3)=0),Inputs!$B$27,0) -> 1 | AO12: =IF(AND(40>=Inputs!$B$25,MOD(40-Inputs!$B$25,3)=0),Inputs!$B$27,0) -> 0 | AP12: =IF(AND(41>=Inputs!$B$25,MOD(41-Inputs!$B$25,3)=0),Inputs!$B$27,0) -> 0 | AQ12: =IF(AND(42>=Inputs!$B$25,MOD(42-Inputs!$B$25,3)=0),Inputs!$B$27,0) -> 1 | AR12: =IF(AND(43>=Inputs!$B$25,MOD(43-Inputs!$B$25,3)=0),Inputs!$B$27,0) -> 0 | AS12: =IF(AND(44>=Inputs!$B$25,MOD(44-Inputs!$B$25,3)=0),Inputs!$B$27,0) -> 0 | AT12: =IF(AND(45>=Inputs!$B$25,MOD(45-Inputs!$B$25,3)=0),Inputs!$B$27,0) -> 1 | AU12: =IF(AND(46>=Inputs!$B$25,MOD(46-Inputs!$B$25,3)=0),Inputs!$B$27,0) -> 0 | AV12: =IF(AND(47>=Inputs!$B$25,MOD(47-Inputs!$B$25,3)=0),Inputs!$B$27,0) -> 0 | AW12: =IF(AND(48>=Inputs!$B$25,MOD(48-Inputs!$B$25,3)=0),Inputs!$B$27,0) -> 1 | AX12: =IF(AND(49>=Inputs!$B$25,MOD(49-Inputs!$B$25,3)=0),Inputs!$B$27,0) -> 0 | AY12: =IF(AND(50>=Inputs!$B$25,MOD(50-Inputs!$B$25,3)=0),Inputs!$B$27,0) -> 0 | AZ12: =IF(AND(51>=Inputs!$B$25,MOD(51-Inputs!$B$25,3)=0),Inputs!$B$27,0) -> 1 | BA12: =IF(AND(52>=Inputs!$B$25,MOD(52-Inputs!$B$25,3)=0),Inputs!$B$27,0) -> 0
A13: Churned Enterprise | B13: =0 -> 0 | C13: =IF(B14>0,IF(MOD(2,12)=0,ROUND(B14*Inputs!$B$28,0),0),0) -> 0 | D13: =IF(C14>0,IF(MOD(3,12)=0,ROUND(C14*Inputs!$B$28,0),0),0) -> 0 | E13: =IF(D14>0,IF(MOD(4,12)=0,ROUND(D14*Inputs!$B$28,0),0),0) -> 0 | F13: =IF(E14>0,IF(MOD(5,12)=0,ROUND(E14*Inputs!$B$28,0),0),0) -> 0 | G13: =IF(F14>0,IF(MOD(6,12)=0,ROUND(F14*Inputs!$B$28,0),0),0) -> 0 | H13: =IF(G14>0,IF(MOD(7,12)=0,ROUND(G14*Inputs!$B$28,0),0),0) -> 0 | I13: =IF(H14>0,IF(MOD(8,12)=0,ROUND(H14*Inputs!$B$28,0),0),0) -> 0 | J13: =IF(I14>0,IF(MOD(9,12)=0,ROUND(I14*Inputs!$B$28,0),0),0) -> 0 | K13: =IF(J14>0,IF(MOD(10,12)=0,ROUND(J14*Inputs!$B$28,0),0),0) -> 0 | L13: =IF(K14>0,IF(MOD(11,12)=0,ROUND(K14*Inputs!$B$28,0),0),0) -> 0 | M13: =IF(L14>0,IF(MOD(12,12)=0,ROUND(L14*Inputs!$B$28,0),0),0) -> 0 | N13: =IF(M14>0,IF(MOD(13,12)=0,ROUND(M14*Inputs!$B$28,0),0),0) -> 0 | O13: =IF(N14>0,IF(MOD(14,12)=0,ROUND(N14*Inputs!$B$28,0),0),0) -> 0 | P13: =IF(O14>0,IF(MOD(15,12)=0,ROUND(O14*Inputs!$B$28,0),0),0) -> 0 | Q13: =IF(P14>0,IF(MOD(16,12)=0,ROUND(P14*Inputs!$B$28,0),0),0) -> 0 | R13: =IF(Q14>0,IF(MOD(17,12)=0,ROUND(Q14*Inputs!$B$28,0),0),0) -> 0 | S13: =IF(R14>0,IF(MOD(18,12)=0,ROUND(R14*Inputs!$B$28,0),0),0) -> 0 | T13: =IF(S14>0,IF(MOD(19,12)=0,ROUND(S14*Inputs!$B$28,0),0),0) -> 0 | U13: =IF(T14>0,IF(MOD(20,12)=0,ROUND(T14*Inputs!$B$28,0),0),0) -> 0 | V13: =IF(U14>0,IF(MOD(21,12)=0,ROUND(U14*Inputs!$B$28,0),0),0) -> 0 | W13: =IF(V14>0,IF(MOD(22,12)=0,ROUND(V14*Inputs!$B$28,0),0),0) -> 0 | X13: =IF(W14>0,IF(MOD(23,12)=0,ROUND(W14*Inputs!$B$28,0),0),0) -> 0 | Y13: =IF(X14>0,IF(MOD(24,12)=0,ROUND(X14*Inputs!$B$28,0),0),0) -> 0 | Z13: =IF(Y14>0,IF(MOD(25,12)=0,ROUND(Y14*Inputs!$B$28,0),0),0) -> 0 | AA13: =IF(Z14>0,IF(MOD(26,12)=0,ROUND(Z14*Inputs!$B$28,0),0),0) -> 0 | AB13: =IF(AA14>0,IF(MOD(27,12)=0,ROUND(AA14*Inputs!$B$28,0),0),0) -> 0 | AC13: =IF(AB14>0,IF(MOD(28,12)=0,ROUND(AB14*Inputs!$B$28,0),0),0) -> 0 | AD13: =IF(AC14>0,IF(MOD(29,12)=0,ROUND(AC14*Inputs!$B$28,0),0),0) -> 0 | AE13: =IF(AD14>0,IF(MOD(30,12)=0,ROUND(AD14*Inputs!$B$28,0),0),0) -> 0 | AF13: =IF(AE14>0,IF(MOD(31,12)=0,ROUND(AE14*Inputs!$B$28,0),0),0) -> 0 | AG13: =IF(AF14>0,IF(MOD(32,12)=0,ROUND(AF14*Inputs!$B$28,0),0),0) -> 0 | AH13: =IF(AG14>0,IF(MOD(33,12)=0,ROUND(AG14*Inputs!$B$28,0),0),0) -> 0 | AI13: =IF(AH14>0,IF(MOD(34,12)=0,ROUND(AH14*Inputs!$B$28,0),0),0) -> 0 | AJ13: =IF(AI14>0,IF(MOD(35,12)=0,ROUND(AI14*Inputs!$B$28,0),0),0) -> 0 | AK13: =IF(AJ14>0,IF(MOD(36,12)=0,ROUND(AJ14*Inputs!$B$28,0),0),0) -> 0 | AL13: =IF(AK14>0,IF(MOD(37,12)=0,ROUND(AK14*Inputs!$B$28,0),0),0) -> 0 | AM13: =IF(AL14>0,IF(MOD(38,12)=0,ROUND(AL14*Inputs!$B$28,0),0),0) -> 0 | AN13: =IF(AM14>0,IF(MOD(39,12)=0,ROUND(AM14*Inputs!$B$28,0),0),0) -> 0 | AO13: =IF(AN14>0,IF(MOD(40,12)=0,ROUND(AN14*Inputs!$B$28,0),0),0) -> 0 | AP13: =IF(AO14>0,IF(MOD(41,12)=0,ROUND(AO14*Inputs!$B$28,0),0),0) -> 0 | AQ13: =IF(AP14>0,IF(MOD(42,12)=0,ROUND(AP14*Inputs!$B$28,0),0),0) -> 0 | AR13: =IF(AQ14>0,IF(MOD(43,12)=0,ROUND(AQ14*Inputs!$B$28,0),0),0) -> 0 | AS13: =IF(AR14>0,IF(MOD(44,12)=0,ROUND(AR14*Inputs!$B$28,0),0),0) -> 0 | AT13: =IF(AS14>0,IF(MOD(45,12)=0,ROUND(AS14*Inputs!$B$28,0),0),0) -> 0 | AU13: =IF(AT14>0,IF(MOD(46,12)=0,ROUND(AT14*Inputs!$B$28,0),0),0) -> 0 | AV13: =IF(AU14>0,IF(MOD(47,12)=0,ROUND(AU14*Inputs!$B$28,0),0),0) -> 0 | AW13: =IF(AV14>0,IF(MOD(48,12)=0,ROUND(AV14*Inputs!$B$28,0),0),0) -> 1 | AX13: =IF(AW14>0,IF(MOD(49,12)=0,ROUND(AW14*Inputs!$B$28,0),0),0) -> 0 | AY13: =IF(AX14>0,IF(MOD(50,12)=0,ROUND(AX14*Inputs!$B$28,0),0),0) -> 0 | AZ13: =IF(AY14>0,IF(MOD(51,12)=0,ROUND(AY14*Inputs!$B$28,0),0),0) -> 0 | BA13: =IF(AZ14>0,IF(MOD(52,12)=0,ROUND(AZ14*Inputs!$B$28,0),0),0) -> 0
A14: Active Enterprise Contracts | B14: =B12-B13 -> 0 | C14: =B14+C12-C13 -> 0 | D14: =C14+D12-D13 -> 0 | E14: =D14+E12-E13 -> 0 | F14: =E14+F12-F13 -> 0 | G14: =F14+G12-G13 -> 0 | H14: =G14+H12-H13 -> 0 | I14: =H14+I12-I13 -> 0 | J14: =I14+J12-J13 -> 0 | ... BA14: =AZ14+BA12-BA13 -> 9
A15: Avg Enterprise ACV (€) | B15: =Inputs!$B$26*(1+Inputs!$B$21)^INT((1-1)/12) -> 150000 | C15: =Inputs!$B$26*(1+Inputs!$B$21)^INT((2-1)/12) -> 150000 | D15: =Inputs!$B$26*(1+Inputs!$B$21)^INT((3-1)/12) -> 150000 | E15: =Inputs!$B$26*(1+Inputs!$B$21)^INT((4-1)/12) -> 150000 | F15: =Inputs!$B$26*(1+Inputs!$B$21)^INT((5-1)/12) -> 150000 | G15: =Inputs!$B$26*(1+Inputs!$B$21)^INT((6-1)/12) -> 150000 | H15: =Inputs!$B$26*(1+Inputs!$B$21)^INT((7-1)/12) -> 150000 | I15: =Inputs!$B$26*(1+Inputs!$B$21)^INT((8-1)/12) -> 150000 | J15: =Inputs!$B$26*(1+Inputs!$B$21)^INT((9-1)/12) -> 150000 | K15: =Inputs!$B$26*(1+Inputs!$B$21)^INT((10-1)/12) -> 150000 | L15: =Inputs!$B$26*(1+Inputs!$B$21)^INT((11-1)/12) -> 150000 | M15: =Inputs!$B$26*(1+Inputs!$B$21)^INT((12-1)/12) -> 150000 | N15: =Inputs!$B$26*(1+Inputs!$B$21)^INT((13-1)/12) -> 162000 | O15: =Inputs!$B$26*(1+Inputs!$B$21)^INT((14-1)/12) -> 162000 | P15: =Inputs!$B$26*(1+Inputs!$B$21)^INT((15-1)/12) -> 162000 | Q15: =Inputs!$B$26*(1+Inputs!$B$21)^INT((16-1)/12) -> 162000 | R15: =Inputs!$B$26*(1+Inputs!$B$21)^INT((17-1)/12) -> 162000 | S15: =Inputs!$B$26*(1+Inputs!$B$21)^INT((18-1)/12) -> 162000 | T15: =Inputs!$B$26*(1+Inputs!$B$21)^INT((19-1)/12) -> 162000 | U15: =Inputs!$B$26*(1+Inputs!$B$21)^INT((20-1)/12) -> 162000 | V15: =Inputs!$B$26*(1+Inputs!$B$21)^INT((21-1)/12) -> 162000 | W15: =Inputs!$B$26*(1+Inputs!$B$21)^INT((22-1)/12) -> 162000 | X15: =Inputs!$B$26*(1+Inputs!$B$21)^INT((23-1)/12) -> 162000 | Y15: =Inputs!$B$26*(1+Inputs!$B$21)^INT((24-1)/12) -> 162000 | Z15: =Inputs!$B$26*(1+Inputs!$B$21)^INT((25-1)/12) -> 174960 | AA15: =Inputs!$B$26*(1+Inputs!$B$21)^INT((26-1)/12) -> 174960 | AB15: =Inputs!$B$26*(1+Inputs!$B$21)^INT((27-1)/12) -> 174960 | AC15: =Inputs!$B$26*(1+Inputs!$B$21)^INT((28-1)/12) -> 174960 | AD15: =Inputs!$B$26*(1+Inputs!$B$21)^INT((29-1)/12) -> 174960 | AE15: =Inputs!$B$26*(1+Inputs!$B$21)^INT((30-1)/12) -> 174960 | AF15: =Inputs!$B$26*(1+Inputs!$B$21)^INT((31-1)/12) -> 174960 | AG15: =Inputs!$B$26*(1+Inputs!$B$21)^INT((32-1)/12) -> 174960 | AH15: =Inputs!$B$26*(1+Inputs!$B$21)^INT((33-1)/12) -> 174960 | AI15: =Inputs!$B$26*(1+Inputs!$B$21)^INT((34-1)/12) -> 174960 | AJ15: =Inputs!$B$26*(1+Inputs!$B$21)^INT((35-1)/12) -> 174960 | AK15: =Inputs!$B$26*(1+Inputs!$B$21)^INT((36-1)/12) -> 174960 | AL15: =Inputs!$B$26*(1+Inputs!$B$21)^INT((37-1)/12) -> 188956.8 | AM15: =Inputs!$B$26*(1+Inputs!$B$21)^INT((38-1)/12) -> 188956.8 | AN15: =Inputs!$B$26*(1+Inputs!$B$21)^INT((39-1)/12) -> 188956.8 | AO15: =Inputs!$B$26*(1+Inputs!$B$21)^INT((40-1)/12) -> 188956.8 | AP15: =Inputs!$B$26*(1+Inputs!$B$21)^INT((41-1)/12) -> 188956.8 | AQ15: =Inputs!$B$26*(1+Inputs!$B$21)^INT((42-1)/12) -> 188956.8 | AR15: =Inputs!$B$26*(1+Inputs!$B$21)^INT((43-1)/12) -> 188956.8 | AS15: =Inputs!$B$26*(1+Inputs!$B$21)^INT((44-1)/12) -> 188956.8 | AT15: =Inputs!$B$26*(1+Inputs!$B$21)^INT((45-1)/12) -> 188956.8 | AU15: =Inputs!$B$26*(1+Inputs!$B$21)^INT((46-1)/12) -> 188956.8 | AV15: =Inputs!$B$26*(1+Inputs!$B$21)^INT((47-1)/12) -> 188956.8 | AW15: =Inputs!$B$26*(1+Inputs!$B$21)^INT((48-1)/12) -> 188956.8 | AX15: =Inputs!$B$26*(1+Inputs!$B$21)^INT((49-1)/12) -> 204073.34 | AY15: =Inputs!$B$26*(1+Inputs!$B$21)^INT((50-1)/12) -> 204073.34 | AZ15: =Inputs!$B$26*(1+Inputs!$B$21)^INT((51-1)/12) -> 204073.34 | BA15: =Inputs!$B$26*(1+Inputs!$B$21)^INT((52-1)/12) -> 204073.34
A16: Enterprise Monthly Revenue (€) | B16: =B14*B15/12 -> 0 | C16: =C14*C15/12 -> 0 | D16: =D14*D15/12 -> 0 | E16: =E14*E15/12 -> 0 | F16: =F14*F15/12 -> 0 | G16: =G14*G15/12 -> 0 | H16: =H14*H15/12 -> 0 | I16: =I14*I15/12 -> 0 | ... BA16: =BA14*BA15/12 -> 153055.01
A18: TOTAL MRR (€) | B18: =B9+B16 -> 0 | C18: =C9+C16 -> 0 | D18: =D9+D16 -> 0 | E18: =E9+E16 -> 0 | F18: =F9+F16 -> 0 | G18: =G9+G16 -> 0 | H18: =H9+H16 -> 0 | I18: =I9+I16 -> 0 | ... BA18: =BA9+BA16 -> 158496.96
A19: TOTAL ARR (€) | B19: =B18*12 -> 0 | C19: =C18*12 -> 0 | D19: =D18*12 -> 0 | E19: =E18*12 -> 0 | F19: =F18*12 -> 0 | G19: =G18*12 -> 0 | H19: =H18*12 -> 0 | I19: =I18*12 -> 0 | ... BA19: =BA18*12 -> 1901963.6
A20: Total Monthly Revenue (€) | B20: =B18 -> 0 | C20: =C18 -> 0 | D20: =D18 -> 0 | E20: =E18 -> 0 | F20: =F18 -> 0 | G20: =G18 -> 0 | H20: =H18 -> 0 | I20: =I18 -> 0 | ... BA20: =BA18 -> 158496.96
A21: ARR Growth % (MoM) | B21: ="" | C21: =IFERROR(C19/B19-1,"") | D21: =IFERROR(D19/C19-1,"") | E21: =IFERROR(E19/D19-1,"") | F21: =IFERROR(F19/E19-1,"") | G21: =IFERROR(G19/F19-1,"") | H21: =IFERROR(H19/G19-1,"") | I21: =IFERROR(I19/H19-1,"") | J21: =IFERROR(J19/I19-1,"") | ... BA21: =IFERROR(BA19/AZ19-1,"") -> 0
A22: Net Revenue Retention % | B22: =Inputs!$B$29 -> 1.18 | C22: =Inputs!$B$29 -> 1.18 | D22: =Inputs!$B$29 -> 1.18 | E22: =Inputs!$B$29 -> 1.18 | F22: =Inputs!$B$29 -> 1.18 | G22: =Inputs!$B$29 -> 1.18 | H22: =Inputs!$B$29 -> 1.18 | I22: =Inputs!$B$29 -> 1.18 | ... BA22: =Inputs!$B$29 -> 1.18
A23: Gross New ARR (€) | B23: =B5*B4*12+B12*B15 -> 0 | C23: =C5*C4*12+C12*C15 -> 0 | D23: =D5*D4*12+D12*D15 -> 0 | E23: =E5*E4*12+E12*E15 -> 0 | F23: =F5*F4*12+F12*F15 -> 0 | G23: =G5*G4*12+G12*G15 -> 0 | H23: =H5*H4*12+H12*H15 -> 0 | I23: =I5*I4*12+I12*I15 -> 0 | ... BA23: =BA5*BA4*12+BA12*BA15 -> 0

Sheet Costs
A1: KOSTENDETAILS
B2: 46113 | C2: 46143 | D2: 46174 | E2: 46204 | F2: 46235 | G2: 46266 | H2: 46296 | I2: 46327 | J2: 46357 | K2: 46388 | L2: 46419 | M2: 46447 | N2: 46478 | O2: 46508 | P2: 46539 | Q2: 46569 | R2: 46600 | S2: 46631 | T2: 46661 | U2: 46692 | V2: 46722 | W2: 46753 | X2: 46784 | Y2: 46813 | Z2: 46844 | AA2: 46874 | AB2: 46905 | AC2: 46935 | AD2: 46966 | AE2: 46997 | AF2: 47027 | AG2: 47058 | AH2: 47088 | AI2: 47119 | AJ2: 47150 | AK2: 47178 | AL2: 47209 | AM2: 47239 | AN2: 47270 | AO2: 47300 | AP2: 47331 | AQ2: 47362 | AR2: 47392 | AS2: 47423 | AT2: 47453 | AU2: 47484 | AV2: 47515 | AW2: 47543 | AX2: 47574 | AY2: 47604 | AZ2: 47635 | BA2: 47665
A3: Kostenposition | B3: M1 | C3: M2 | D3: M3 | E3: M4 | F3: M5 | G3: M6 | H3: M7 | I3: M8 | J3: M9 | K3: M10 | L3: M11 | M3: M12 | N3: M13 | O3: M14 | P3: M15 | Q3: M16 | R3: M17 | S3: M18 | T3: M19 | U3: M20 | V3: M21 | W3: M22 | X3: M23 | Y3: M24 | Z3: M25 | AA3: M26 | AB3: M27 | AC3: M28 | AD3: M29 | AE3: M30 | AF3: M31 | AG3: M32 | AH3: M33 | AI3: M34 | AJ3: M35 | AK3: M36 | AL3: M37 | AM3: M38 | AN3: M39 | AO3: M40 | AP3: M41 | AQ3: M42 | AR3: M43 | AS3: M44 | AT3: M45 | AU3: M46 | AV3: M47 | AW3: M48 | AX3: M49 | AY3: M50 | AZ3: M51 | BA3: M52
A4: HEADCOUNT PLAN
A5: Executives (CEO, CTO, CCO) | B5: 3 | C5: 3 | D5: 3 | E5: 3 | F5: 3 | G5: 3 | H5: 3 | I5: 3 | J5: 3 | K5: 3 | L5: 3 | M5: 3 | N5: 3 | O5: 3 | P5: 3 | Q5: 3 | R5: 3 | S5: 3 | T5: 3 | U5: 3 | V5: 3 | W5: 3 | X5: 3 | Y5: 3 | Z5: 3 | AA5: 3 | AB5: 3 | AC5: 3 | AD5: 3 | AE5: 3 | AF5: 3 | AG5: 3 | AH5: 3 | AI5: 3 | AJ5: 3 | AK5: 3 | AL5: 3 | AM5: 3 | AN5: 3 | AO5: 3 | AP5: 3 | AQ5: 3 | AR5: 3 | AS5: 3 | AT5: 3 | AU5: 3 | AV5: 3 | AW5: 3 | AX5: 3 | AY5: 3 | AZ5: 3 | BA5: 3
A6: 1. Senior Engineer | B6: =IF(COLUMNS($B$6:B6) >= Inputs!$F$48, 1, 0) -> 0 | C6: =IF(COLUMNS($B$6:C6) >= Inputs!$F$48, 1, 0) -> 0 | D6: =IF(COLUMNS($B$6:D6) >= Inputs!$F$48, 1, 0) -> 0 | E6: =IF(COLUMNS($B$6:E6) >= Inputs!$F$48, 1, 0) -> 0 | F6: =IF(COLUMNS($B$6:F6) >= Inputs!$F$48, 1, 0) -> 0 | G6: =IF(COLUMNS($B$6:G6) >= Inputs!$F$48, 1, 0) -> 0 | H6: =IF(COLUMNS($B$6:H6) >= Inputs!$F$48, 1, 0) -> 1 | I6: =IF(COLUMNS($B$6:I6) >= Inputs!$F$48, 1, 0) -> 1 | ... BA6: =IF(COLUMNS($B$6:BA6) >= Inputs!$F$48, 1, 0) -> 1
A7: 2. Senior Engineer | B7: =IF(COLUMNS($B$7:B7) >= Inputs!$F49, 1, 0) -> 0 | C7: =IF(COLUMNS($B$7:C7) >= Inputs!$F49, 1, 0) -> 0 | D7: =IF(COLUMNS($B$7:D7) >= Inputs!$F49, 1, 0) -> 0 | E7: =IF(COLUMNS($B$7:E7) >= Inputs!$F49, 1, 0) -> 0 | F7: =IF(COLUMNS($B$7:F7) >= Inputs!$F49, 1, 0) -> 0 | G7: =IF(COLUMNS($B$7:G7) >= Inputs!$F49, 1, 0) -> 0 | H7: =IF(COLUMNS($B$7:H7) >= Inputs!$F49, 1, 0) -> 0 | I7: =IF(COLUMNS($B$7:I7) >= Inputs!$F49, 1, 0) -> 0 | ... BA7: =IF(COLUMNS($B$7:BA7) >= Inputs!$F49, 1, 0) -> 1
A8: 1. Junior Engineer | B8: =IF(COLUMNS($B$8:B8) >= Inputs!$F$50, 1, 0) -> 0 | C8: =IF(COLUMNS($B$8:C8) >= Inputs!$F$50, 1, 0) -> 0 | D8: =IF(COLUMNS($B$8:D8) >= Inputs!$F$50, 1, 0) -> 0 | E8: =IF(COLUMNS($B$8:E8) >= Inputs!$F$50, 1, 0) -> 0 | F8: =IF(COLUMNS($B$8:F8) >= Inputs!$F$50, 1, 0) -> 0 | G8: =IF(COLUMNS($B$8:G8) >= Inputs!$F$50, 1, 0) -> 0 | H8: =IF(COLUMNS($B$8:H8) >= Inputs!$F$50, 1, 0) -> 0 | I8: =IF(COLUMNS($B$8:I8) >= Inputs!$F$50, 1, 0) -> 0 | ... BA8: =IF(COLUMNS($B$8:BA8) >= Inputs!$F$50, 1, 0) -> 1
A9: 1. ML/AI Engineer | B9: =IF(COLUMNS($B$9:B9) >= Inputs!$F$51, 1, 0) -> 0 | C9: =IF(COLUMNS($B$9:C9) >= Inputs!$F$51, 1, 0) -> 0 | D9: =IF(COLUMNS($B$9:D9) >= Inputs!$F$51, 1, 0) -> 0 | E9: =IF(COLUMNS($B$9:E9) >= Inputs!$F$51, 1, 0) -> 0 | F9: =IF(COLUMNS($B$9:F9) >= Inputs!$F$51, 1, 0) -> 0 | G9: =IF(COLUMNS($B$9:G9) >= Inputs!$F$51, 1, 0) -> 0 | H9: =IF(COLUMNS($B$9:H9) >= Inputs!$F$51, 1, 0) -> 0 | I9: =IF(COLUMNS($B$9:I9) >= Inputs!$F$51, 1, 0) -> 1 | ... BA9: =IF(COLUMNS($B$9:BA9) >= Inputs!$F$51, 1, 0) -> 1
A10: 2. ML/AI Engineer | B10: =IF(COLUMNS($B$9:B10) >= Inputs!$F$52, 1, 0) -> 0 | C10: =IF(COLUMNS($B$9:C10) >= Inputs!$F$52, 1, 0) -> 0 | D10: =IF(COLUMNS($B$9:D10) >= Inputs!$F$52, 1, 0) -> 0 | E10: =IF(COLUMNS($B$9:E10) >= Inputs!$F$52, 1, 0) -> 0 | F10: =IF(COLUMNS($B$9:F10) >= Inputs!$F$52, 1, 0) -> 0 | G10: =IF(COLUMNS($B$9:G10) >= Inputs!$F$52, 1, 0) -> 0 | H10: =IF(COLUMNS($B$9:H10) >= Inputs!$F$52, 1, 0) -> 0 | I10: =IF(COLUMNS($B$9:I10) >= Inputs!$F$52, 1, 0) -> 0 | ... BA10: =IF(COLUMNS($B$9:BA10) >= Inputs!$F$52, 1, 0) -> 1
A11: 1. Sales Rep | B11: =IF(COLUMNS($B$11:B11) >= Inputs!$F$53, 1, 0) -> 0 | C11: =IF(COLUMNS($B$11:C11) >= Inputs!$F$53, 1, 0) -> 0 | D11: =IF(COLUMNS($B$11:D11) >= Inputs!$F$53, 1, 0) -> 0 | E11: =IF(COLUMNS($B$11:E11) >= Inputs!$F$53, 1, 0) -> 0 | F11: =IF(COLUMNS($B$11:F11) >= Inputs!$F$53, 1, 0) -> 0 | G11: =IF(COLUMNS($B$11:G11) >= Inputs!$F$53, 1, 0) -> 0 | H11: =IF(COLUMNS($B$11:H11) >= Inputs!$F$53, 1, 0) -> 0 | I11: =IF(COLUMNS($B$11:I11) >= Inputs!$F$53, 1, 0) -> 0 | ... BA11: =IF(COLUMNS($B$11:BA11) >= Inputs!$F$53, 1, 0) -> 0
A12: 2. Sales Rep | B12: =IF(COLUMNS($B$12:B12) >= Inputs!$F$54, 1, 0) -> 0 | C12: =IF(COLUMNS($B$12:C12) >= Inputs!$F$54, 1, 0) -> 0 | D12: =IF(COLUMNS($B$12:D12) >= Inputs!$F$54, 1, 0) -> 0 | E12: =IF(COLUMNS($B$12:E12) >= Inputs!$F$54, 1, 0) -> 0 | F12: =IF(COLUMNS($B$12:F12) >= Inputs!$F$54, 1, 0) -> 0 | G12: =IF(COLUMNS($B$12:G12) >= Inputs!$F$54, 1, 0) -> 0 | H12: =IF(COLUMNS($B$12:H12) >= Inputs!$F$54, 1, 0) -> 0 | I12: =IF(COLUMNS($B$12:I12) >= Inputs!$F$54, 1, 0) -> 0 | ... BA12: =IF(COLUMNS($B$12:BA12) >= Inputs!$F$54, 1, 0) -> 1
A13: 1. Customer Success | B13: =IF(COLUMNS($B$13:B13) >= Inputs!$F$55, 1, 0) -> 0 | C13: =IF(COLUMNS($B$13:C13) >= Inputs!$F$55, 1, 0) -> 0 | D13: =IF(COLUMNS($B$13:D13) >= Inputs!$F$55, 1, 0) -> 0 | E13: =IF(COLUMNS($B$13:E13) >= Inputs!$F$55, 1, 0) -> 0 | F13: =IF(COLUMNS($B$13:F13) >= Inputs!$F$55, 1, 0) -> 0 | G13: =IF(COLUMNS($B$13:G13) >= Inputs!$F$55, 1, 0) -> 0 | H13: =IF(COLUMNS($B$13:H13) >= Inputs!$F$55, 1, 0) -> 0 | I13: =IF(COLUMNS($B$13:I13) >= Inputs!$F$55, 1, 0) -> 0 | ... BA13: =IF(COLUMNS($B$13:BA13) >= Inputs!$F$55, 1, 0) -> 1
A14: 1. Marketing Manager | B14: =IF(COLUMNS($B$14:B14) >= Inputs!$F$56, 1, 0) -> 0 | C14: =IF(COLUMNS($B$14:C14) >= Inputs!$F$56, 1, 0) -> 0 | D14: =IF(COLUMNS($B$14:D14) >= Inputs!$F$56, 1, 0) -> 0 | E14: =IF(COLUMNS($B$14:E14) >= Inputs!$F$56, 1, 0) -> 0 | F14: =IF(COLUMNS($B$14:F14) >= Inputs!$F$56, 1, 0) -> 0 | G14: =IF(COLUMNS($B$14:G14) >= Inputs!$F$56, 1, 0) -> 0 | H14: =IF(COLUMNS($B$14:H14) >= Inputs!$F$56, 1, 0) -> 0 | I14: =IF(COLUMNS($B$14:I14) >= Inputs!$F$56, 1, 0) -> 0 | ... BA14: =IF(COLUMNS($B$14:BA14) >= Inputs!$F$56, 1, 0) -> 1
A15: 1. Product Manager | B15: =IF(COLUMNS($B$15:B15) >= Inputs!$F$57, 1, 0) -> 0 | C15: =IF(COLUMNS($B$15:C15) >= Inputs!$F$57, 1, 0) -> 0 | D15: =IF(COLUMNS($B$15:D15) >= Inputs!$F$57, 1, 0) -> 0 | E15: =IF(COLUMNS($B$15:E15) >= Inputs!$F$57, 1, 0) -> 0 | F15: =IF(COLUMNS($B$15:F15) >= Inputs!$F$57, 1, 0) -> 0 | G15: =IF(COLUMNS($B$15:G15) >= Inputs!$F$57, 1, 0) -> 0 | H15: =IF(COLUMNS($B$15:H15) >= Inputs!$F$57, 1, 0) -> 0 | I15: =IF(COLUMNS($B$15:I15) >= Inputs!$F$57, 1, 0) -> 0 | ... BA15: =IF(COLUMNS($B$15:BA15) >= Inputs!$F$57, 1, 0) -> 1
A16: 1. Office Manager | B16: =IF(COLUMNS($B$16:B16) >= Inputs!$F$58, 1, 0) -> 0 | C16: =IF(COLUMNS($B$16:C16) >= Inputs!$F$58, 1, 0) -> 0 | D16: =IF(COLUMNS($B$16:D16) >= Inputs!$F$58, 1, 0) -> 0 | E16: =IF(COLUMNS($B$16:E16) >= Inputs!$F$58, 1, 0) -> 0 | F16: =IF(COLUMNS($B$16:F16) >= Inputs!$F$58, 1, 0) -> 0 | G16: =IF(COLUMNS($B$16:G16) >= Inputs!$F$58, 1, 0) -> 0 | H16: =IF(COLUMNS($B$16:H16) >= Inputs!$F$58, 1, 0) -> 0 | I16: =IF(COLUMNS($B$16:I16) >= Inputs!$F$58, 1, 0) -> 0 | ... BA16: =IF(COLUMNS($B$16:BA16) >= Inputs!$F$58, 1, 0) -> 1
A17: 3. Senior Engineer | B17: =IF(COLUMNS($B$17:B17) >= Inputs!$F$59, 1, 0) -> 0 | C17: =IF(COLUMNS($B$17:C17) >= Inputs!$F$59, 1, 0) -> 0 | D17: =IF(COLUMNS($B$17:D17) >= Inputs!$F$59, 1, 0) -> 0 | E17: =IF(COLUMNS($B$17:E17) >= Inputs!$F$59, 1, 0) -> 0 | F17: =IF(COLUMNS($B$17:F17) >= Inputs!$F$59, 1, 0) -> 0 | G17: =IF(COLUMNS($B$17:G17) >= Inputs!$F$59, 1, 0) -> 0 | H17: =IF(COLUMNS($B$17:H17) >= Inputs!$F$59, 1, 0) -> 0 | I17: =IF(COLUMNS($B$17:I17) >= Inputs!$F$59, 1, 0) -> 0 | ... BA17: =IF(COLUMNS($B$17:BA17) >= Inputs!$F$59, 1, 0) -> 1
A18: 4. Senior Engineer | B18: =IF(COLUMNS($B$18:B18) >= Inputs!$F$60, 1, 0) -> 0 | C18: =IF(COLUMNS($B$18:C18) >= Inputs!$F$60, 1, 0) -> 0 | D18: =IF(COLUMNS($B$18:D18) >= Inputs!$F$60, 1, 0) -> 0 | E18: =IF(COLUMNS($B$18:E18) >= Inputs!$F$60, 1, 0) -> 0 | F18: =IF(COLUMNS($B$18:F18) >= Inputs!$F$60, 1, 0) -> 0 | G18: =IF(COLUMNS($B$18:G18) >= Inputs!$F$60, 1, 0) -> 0 | H18: =IF(COLUMNS($B$18:H18) >= Inputs!$F$60, 1, 0) -> 0 | I18: =IF(COLUMNS($B$18:I18) >= Inputs!$F$60, 1, 0) -> 0 | ... BA18: =IF(COLUMNS($B$18:BA18) >= Inputs!$F$60, 1, 0) -> 0
A19: 2. Junior Engineer | B19: =IF(COLUMNS($B$19:B19) >= Inputs!$F$61, 1, 0) -> 0 | C19: =IF(COLUMNS($B$19:C19) >= Inputs!$F$61, 1, 0) -> 0 | D19: =IF(COLUMNS($B$19:D19) >= Inputs!$F$61, 1, 0) -> 0 | E19: =IF(COLUMNS($B$19:E19) >= Inputs!$F$61, 1, 0) -> 0 | F19: =IF(COLUMNS($B$19:F19) >= Inputs!$F$61, 1, 0) -> 0 | G19: =IF(COLUMNS($B$19:G19) >= Inputs!$F$61, 1, 0) -> 0 | H19: =IF(COLUMNS($B$19:H19) >= Inputs!$F$61, 1, 0) -> 0 | I19: =IF(COLUMNS($B$19:I19) >= Inputs!$F$61, 1, 0) -> 0 | ... BA19: =IF(COLUMNS($B$19:BA19) >= Inputs!$F$61, 1, 0) -> 1
A20: 3. ML/AI Engineer | B20: =IF(COLUMNS($B$20:B20) >= Inputs!$F$62, 1, 0) -> 0 | C20: =IF(COLUMNS($B$20:C20) >= Inputs!$F$62, 1, 0) -> 0 | D20: =IF(COLUMNS($B$20:D20) >= Inputs!$F$62, 1, 0) -> 0 | E20: =IF(COLUMNS($B$20:E20) >= Inputs!$F$62, 1, 0) -> 0 | F20: =IF(COLUMNS($B$20:F20) >= Inputs!$F$62, 1, 0) -> 0 | G20: =IF(COLUMNS($B$20:G20) >= Inputs!$F$62, 1, 0) -> 0 | H20: =IF(COLUMNS($B$20:H20) >= Inputs!$F$62, 1, 0) -> 0 | I20: =IF(COLUMNS($B$20:I20) >= Inputs!$F$62, 1, 0) -> 0 | ... BA20: =IF(COLUMNS($B$20:BA20) >= Inputs!$F$62, 1, 0) -> 1
A21: 3. Sales Rep | B21: =IF(COLUMNS($B$21:B21) >= Inputs!$F$63, 1, 0) -> 0 | C21: =IF(COLUMNS($B$21:C21) >= Inputs!$F$63, 1, 0) -> 0 | D21: =IF(COLUMNS($B$21:D21) >= Inputs!$F$63, 1, 0) -> 0 | E21: =IF(COLUMNS($B$21:E21) >= Inputs!$F$63, 1, 0) -> 0 | F21: =IF(COLUMNS($B$21:F21) >= Inputs!$F$63, 1, 0) -> 0 | G21: =IF(COLUMNS($B$21:G21) >= Inputs!$F$63, 1, 0) -> 0 | H21: =IF(COLUMNS($B$21:H21) >= Inputs!$F$63, 1, 0) -> 0 | I21: =IF(COLUMNS($B$21:I21) >= Inputs!$F$63, 1, 0) -> 0 | ... BA21: =IF(COLUMNS($B$21:BA21) >= Inputs!$F$63, 1, 0) -> 0
A22: 2. Customer Success | B22: =IF(COLUMNS($B$22:B22) >= Inputs!$F$64, 1, 0) -> 0 | C22: =IF(COLUMNS($B$22:C22) >= Inputs!$F$64, 1, 0) -> 0 | D22: =IF(COLUMNS($B$22:D22) >= Inputs!$F$64, 1, 0) -> 0 | E22: =IF(COLUMNS($B$22:E22) >= Inputs!$F$64, 1, 0) -> 0 | F22: =IF(COLUMNS($B$22:F22) >= Inputs!$F$64, 1, 0) -> 0 | G22: =IF(COLUMNS($B$22:G22) >= Inputs!$F$64, 1, 0) -> 0 | H22: =IF(COLUMNS($B$22:H22) >= Inputs!$F$64, 1, 0) -> 0 | I22: =IF(COLUMNS($B$22:I22) >= Inputs!$F$64, 1, 0) -> 0 | ... BA22: =IF(COLUMNS($B$22:BA22) >= Inputs!$F$64, 1, 0) -> 1
A23: 2. Marketing Manager | B23: =IF(COLUMNS($B$23:B23) >= Inputs!$F$65, 1, 0) -> 0 | C23: =IF(COLUMNS($B$23:C23) >= Inputs!$F$65, 1, 0) -> 0 | D23: =IF(COLUMNS($B$23:D23) >= Inputs!$F$65, 1, 0) -> 0 | E23: =IF(COLUMNS($B$23:E23) >= Inputs!$F$65, 1, 0) -> 0 | F23: =IF(COLUMNS($B$23:F23) >= Inputs!$F$65, 1, 0) -> 0 | G23: =IF(COLUMNS($B$23:G23) >= Inputs!$F$65, 1, 0) -> 0 | H23: =IF(COLUMNS($B$23:H23) >= Inputs!$F$65, 1, 0) -> 0 | I23: =IF(COLUMNS($B$23:I23) >= Inputs!$F$65, 1, 0) -> 0 | ... BA23: =IF(COLUMNS($B$23:BA23) >= Inputs!$F$65, 1, 0) -> 1
A24: 5. Senior Engineer | B24: =IF(COLUMNS($B$24:B24) >= Inputs!$F$66, 1, 0) -> 0 | C24: =IF(COLUMNS($B$24:C24) >= Inputs!$F$66, 1, 0) -> 0 | D24: =IF(COLUMNS($B$24:D24) >= Inputs!$F$66, 1, 0) -> 0 | E24: =IF(COLUMNS($B$24:E24) >= Inputs!$F$66, 1, 0) -> 0 | F24: =IF(COLUMNS($B$24:F24) >= Inputs!$F$66, 1, 0) -> 0 | G24: =IF(COLUMNS($B$24:G24) >= Inputs!$F$66, 1, 0) -> 0 | H24: =IF(COLUMNS($B$24:H24) >= Inputs!$F$66, 1, 0) -> 0 | I24: =IF(COLUMNS($B$24:I24) >= Inputs!$F$66, 1, 0) -> 0 | ... BA24: =IF(COLUMNS($B$24:BA24) >= Inputs!$F$66, 1, 0) -> 0
A25: 3. Junior Engineer | B25: =IF(COLUMNS($B$25:B25) >= Inputs!$F$67, 1, 0) -> 0 | C25: =IF(COLUMNS($B$25:C25) >= Inputs!$F$67, 1, 0) -> 0 | D25: =IF(COLUMNS($B$25:D25) >= Inputs!$F$67, 1, 0) -> 0 | E25: =IF(COLUMNS($B$25:E25) >= Inputs!$F$67, 1, 0) -> 0 | F25: =IF(COLUMNS($B$25:F25) >= Inputs!$F$67, 1, 0) -> 0 | G25: =IF(COLUMNS($B$25:G25) >= Inputs!$F$67, 1, 0) -> 0 | H25: =IF(COLUMNS($B$25:H25) >= Inputs!$F$67, 1, 0) -> 0 | I25: =IF(COLUMNS($B$25:I25) >= Inputs!$F$67, 1, 0) -> 0 | ... BA25: =IF(COLUMNS($B$25:BA25) >= Inputs!$F$67, 1, 0) -> 0
A26: 4. ML/AI Engineer | B26: =IF(COLUMNS($B$26:B26) >= Inputs!$F$68, 1, 0) -> 0 | C26: =IF(COLUMNS($B$26:C26) >= Inputs!$F$68, 1, 0) -> 0 | D26: =IF(COLUMNS($B$26:D26) >= Inputs!$F$68, 1, 0) -> 0 | E26: =IF(COLUMNS($B$26:E26) >= Inputs!$F$68, 1, 0) -> 0 | F26: =IF(COLUMNS($B$26:F26) >= Inputs!$F$68, 1, 0) -> 0 | G26: =IF(COLUMNS($B$26:G26) >= Inputs!$F$68, 1, 0) -> 0 | H26: =IF(COLUMNS($B$26:H26) >= Inputs!$F$68, 1, 0) -> 0 | I26: =IF(COLUMNS($B$26:I26) >= Inputs!$F$68, 1, 0) -> 0 | ... BA26: =IF(COLUMNS($B$26:BA26) >= Inputs!$F$68, 1, 0) -> 0
A27: 2. Product Manager | B27: =IF(COLUMNS($B$27:B27) >= Inputs!$F$69, 1, 0) -> 0 | C27: =IF(COLUMNS($B$27:C27) >= Inputs!$F$69, 1, 0) -> 0 | D27: =IF(COLUMNS($B$27:D27) >= Inputs!$F$69, 1, 0) -> 0 | E27: =IF(COLUMNS($B$27:E27) >= Inputs!$F$69, 1, 0) -> 0 | F27: =IF(COLUMNS($B$27:F27) >= Inputs!$F$69, 1, 0) -> 0 | G27: =IF(COLUMNS($B$27:G27) >= Inputs!$F$69, 1, 0) -> 0 | H27: =IF(COLUMNS($B$27:H27) >= Inputs!$F$69, 1, 0) -> 0 | I27: =IF(COLUMNS($B$27:I27) >= Inputs!$F$69, 1, 0) -> 0 | ... BA27: =IF(COLUMNS($B$27:BA27) >= Inputs!$F$69, 1, 0) -> 1
A28: 4. Sales Rep | B28: =IF(COLUMNS($B$28:B28) >= Inputs!$F$70, 1, 0) -> 0 | C28: =IF(COLUMNS($B$28:C28) >= Inputs!$F$70, 1, 0) -> 0 | D28: =IF(COLUMNS($B$28:D28) >= Inputs!$F$70, 1, 0) -> 0 | E28: =IF(COLUMNS($B$28:E28) >= Inputs!$F$70, 1, 0) -> 0 | F28: =IF(COLUMNS($B$28:F28) >= Inputs!$F$70, 1, 0) -> 0 | G28: =IF(COLUMNS($B$28:G28) >= Inputs!$F$70, 1, 0) -> 0 | H28: =IF(COLUMNS($B$28:H28) >= Inputs!$F$70, 1, 0) -> 0 | I28: =IF(COLUMNS($B$28:I28) >= Inputs!$F$70, 1, 0) -> 0 | ... BA28: =IF(COLUMNS($B$28:BA28) >= Inputs!$F$70, 1, 0) -> 1
A29: 3. Customer Success | B29: =IF(COLUMNS($B$29:B29) >= Inputs!$F$71, 1, 0) -> 0 | C29: =IF(COLUMNS($B$29:C29) >= Inputs!$F$71, 1, 0) -> 0 | D29: =IF(COLUMNS($B$29:D29) >= Inputs!$F$71, 1, 0) -> 0 | E29: =IF(COLUMNS($B$29:E29) >= Inputs!$F$71, 1, 0) -> 0 | F29: =IF(COLUMNS($B$29:F29) >= Inputs!$F$71, 1, 0) -> 0 | G29: =IF(COLUMNS($B$29:G29) >= Inputs!$F$71, 1, 0) -> 0 | H29: =IF(COLUMNS($B$29:H29) >= Inputs!$F$71, 1, 0) -> 0 | I29: =IF(COLUMNS($B$29:I29) >= Inputs!$F$71, 1, 0) -> 0 | ... BA29: =IF(COLUMNS($B$29:BA29) >= Inputs!$F$71, 1, 0) -> 0
A30: Finance Manager | B30: =IF(COLUMNS($B$30:B30) >= Inputs!$F$72, 1, 0) -> 0 | C30: =IF(COLUMNS($B$30:C30) >= Inputs!$F$72, 1, 0) -> 0 | D30: =IF(COLUMNS($B$30:D30) >= Inputs!$F$72, 1, 0) -> 0 | E30: =IF(COLUMNS($B$30:E30) >= Inputs!$F$72, 1, 0) -> 0 | F30: =IF(COLUMNS($B$30:F30) >= Inputs!$F$72, 1, 0) -> 0 | G30: =IF(COLUMNS($B$30:G30) >= Inputs!$F$72, 1, 0) -> 0 | H30: =IF(COLUMNS($B$30:H30) >= Inputs!$F$72, 1, 0) -> 0 | I30: =IF(COLUMNS($B$30:I30) >= Inputs!$F$72, 1, 0) -> 0 | ... BA30: =IF(COLUMNS($B$30:BA30) >= Inputs!$F$72, 1, 0) -> 1
A31: 6. Senior Engineer | B31: =IF(COLUMNS($B$31:B31) >= Inputs!$F$73, 1, 0) -> 0 | C31: =IF(COLUMNS($B$31:C31) >= Inputs!$F$73, 1, 0) -> 0 | D31: =IF(COLUMNS($B$31:D31) >= Inputs!$F$73, 1, 0) -> 0 | E31: =IF(COLUMNS($B$31:E31) >= Inputs!$F$73, 1, 0) -> 0 | F31: =IF(COLUMNS($B$31:F31) >= Inputs!$F$73, 1, 0) -> 0 | G31: =IF(COLUMNS($B$31:G31) >= Inputs!$F$73, 1, 0) -> 0 | H31: =IF(COLUMNS($B$31:H31) >= Inputs!$F$73, 1, 0) -> 0 | I31: =IF(COLUMNS($B$31:I31) >= Inputs!$F$73, 1, 0) -> 0 | ... BA31: =IF(COLUMNS($B$31:BA31) >= Inputs!$F$73, 1, 0) -> 0
A32: 7. Senior Engineer | B32: =IF(COLUMNS($B$32:B32) >= Inputs!$F$74, 1, 0) -> 0 | C32: =IF(COLUMNS($B$32:C32) >= Inputs!$F$74, 1, 0) -> 0 | D32: =IF(COLUMNS($B$32:D32) >= Inputs!$F$74, 1, 0) -> 0 | E32: =IF(COLUMNS($B$32:E32) >= Inputs!$F$74, 1, 0) -> 0 | F32: =IF(COLUMNS($B$32:F32) >= Inputs!$F$74, 1, 0) -> 0 | G32: =IF(COLUMNS($B$32:G32) >= Inputs!$F$74, 1, 0) -> 0 | H32: =IF(COLUMNS($B$32:H32) >= Inputs!$F$74, 1, 0) -> 0 | I32: =IF(COLUMNS($B$32:I32) >= Inputs!$F$74, 1, 0) -> 0 | ... BA32: =IF(COLUMNS($B$32:BA32) >= Inputs!$F$74, 1, 0) -> 0
A33: 4. Junior Engineer | B33: =IF(COLUMNS($B$33:B33) >= Inputs!$F$75, 1, 0) -> 0 | C33: =IF(COLUMNS($B$33:C33) >= Inputs!$F$75, 1, 0) -> 0 | D33: =IF(COLUMNS($B$33:D33) >= Inputs!$F$75, 1, 0) -> 0 | E33: =IF(COLUMNS($B$33:E33) >= Inputs!$F$75, 1, 0) -> 0 | F33: =IF(COLUMNS($B$33:F33) >= Inputs!$F$75, 1, 0) -> 0 | G33: =IF(COLUMNS($B$33:G33) >= Inputs!$F$75, 1, 0) -> 0 | H33: =IF(COLUMNS($B$33:H33) >= Inputs!$F$75, 1, 0) -> 0 | I33: =IF(COLUMNS($B$33:I33) >= Inputs!$F$75, 1, 0) -> 0 | ... BA33: =IF(COLUMNS($B$33:BA33) >= Inputs!$F$75, 1, 0) -> 0
A34: 5. ML/AI Engineer | B34: =IF(COLUMNS($B$34:B34) >= Inputs!$F$76, 1, 0) -> 0 | C34: =IF(COLUMNS($B$34:C34) >= Inputs!$F$76, 1, 0) -> 0 | D34: =IF(COLUMNS($B$34:D34) >= Inputs!$F$76, 1, 0) -> 0 | E34: =IF(COLUMNS($B$34:E34) >= Inputs!$F$76, 1, 0) -> 0 | F34: =IF(COLUMNS($B$34:F34) >= Inputs!$F$76, 1, 0) -> 0 | G34: =IF(COLUMNS($B$34:G34) >= Inputs!$F$76, 1, 0) -> 0 | H34: =IF(COLUMNS($B$34:H34) >= Inputs!$F$76, 1, 0) -> 0 | I34: =IF(COLUMNS($B$34:I34) >= Inputs!$F$76, 1, 0) -> 0 | ... BA34: =IF(COLUMNS($B$34:BA34) >= Inputs!$F$76, 1, 0) -> 0
A35: 5. Sales Rep | B35: =IF(COLUMNS($B$35:B35) >= Inputs!$F$77, 1, 0) -> 0 | C35: =IF(COLUMNS($B$35:C35) >= Inputs!$F$77, 1, 0) -> 0 | D35: =IF(COLUMNS($B$35:D35) >= Inputs!$F$77, 1, 0) -> 0 | E35: =IF(COLUMNS($B$35:E35) >= Inputs!$F$77, 1, 0) -> 0 | F35: =IF(COLUMNS($B$35:F35) >= Inputs!$F$77, 1, 0) -> 0 | G35: =IF(COLUMNS($B$35:G35) >= Inputs!$F$77, 1, 0) -> 0 | H35: =IF(COLUMNS($B$35:H35) >= Inputs!$F$77, 1, 0) -> 0 | I35: =IF(COLUMNS($B$35:I35) >= Inputs!$F$77, 1, 0) -> 0 | ... BA35: =IF(COLUMNS($B$35:BA35) >= Inputs!$F$77, 1, 0) -> 0
A36: 4. Customer Success | B36: =IF(COLUMNS($B$36:B36) >= Inputs!$F$78, 1, 0) -> 0 | C36: =IF(COLUMNS($B$36:C36) >= Inputs!$F$78, 1, 0) -> 0 | D36: =IF(COLUMNS($B$36:D36) >= Inputs!$F$78, 1, 0) -> 0 | E36: =IF(COLUMNS($B$36:E36) >= Inputs!$F$78, 1, 0) -> 0 | F36: =IF(COLUMNS($B$36:F36) >= Inputs!$F$78, 1, 0) -> 0 | G36: =IF(COLUMNS($B$36:G36) >= Inputs!$F$78, 1, 0) -> 0 | H36: =IF(COLUMNS($B$36:H36) >= Inputs!$F$78, 1, 0) -> 0 | I36: =IF(COLUMNS($B$36:I36) >= Inputs!$F$78, 1, 0) -> 0 | ... BA36: =IF(COLUMNS($B$36:BA36) >= Inputs!$F$78, 1, 0) -> 0
A37: 3. Marketing Manager | B37: =IF(COLUMNS($B$37:B37) >= Inputs!$F$79, 1, 0) -> 0 | C37: =IF(COLUMNS($B$37:C37) >= Inputs!$F$79, 1, 0) -> 0 | D37: =IF(COLUMNS($B$37:D37) >= Inputs!$F$79, 1, 0) -> 0 | E37: =IF(COLUMNS($B$37:E37) >= Inputs!$F$79, 1, 0) -> 0 | F37: =IF(COLUMNS($B$37:F37) >= Inputs!$F$79, 1, 0) -> 0 | G37: =IF(COLUMNS($B$37:G37) >= Inputs!$F$79, 1, 0) -> 0 | H37: =IF(COLUMNS($B$37:H37) >= Inputs!$F$79, 1, 0) -> 0 | I37: =IF(COLUMNS($B$37:I37) >= Inputs!$F$79, 1, 0) -> 0 | ... BA37: =IF(COLUMNS($B$37:BA37) >= Inputs!$F$79, 1, 0) -> 0
A38: TOTAL HEADCOUNT | B38: =SUM(B5:B37) -> 3 | C38: =SUM(C5:C37) -> 3 | D38: =SUM(D5:D37) -> 3 | E38: =SUM(E5:E37) -> 3 | F38: =SUM(F5:F37) -> 3 | G38: =SUM(G5:G37) -> 3 | H38: =SUM(H5:H37) -> 4 | I38: =SUM(I5:I37) -> 5 | ... BA38: =SUM(BA5:BA37) -> 21
A40: GEHÄLTER & PERSONALKOSTEN
A41: CEO Gehalt | B41: =B5/3 * (Inputs!$B$32 / 12) * (1 + Inputs!$B$44)^INT((COLUMNS($B$41:B41)-1) / 12) -> 6000 | C41: =C5/3 * (Inputs!$B$32 / 12) * (1 + Inputs!$B$44)^INT((COLUMNS($B$41:C41)-1) / 12) -> 6000 | D41: =D5/3 * (Inputs!$B$32 / 12) * (1 + Inputs!$B$44)^INT((COLUMNS($B$41:D41)-1) / 12) -> 6000 | E41: =E5/3 * (Inputs!$B$32 / 12) * (1 + Inputs!$B$44)^INT((COLUMNS($B$41:E41)-1) / 12) -> 6000 | F41: =F5/3 * (Inputs!$B$32 / 12) * (1 + Inputs!$B$44)^INT((COLUMNS($B$41:F41)-1) / 12) -> 6000 | G41: =G5/3 * (Inputs!$B$32 / 12) * (1 + Inputs!$B$44)^INT((COLUMNS($B$41:G41)-1) / 12) -> 6000 | H41: =H5/3 * (Inputs!$B$32 / 12) * (1 + Inputs!$B$44)^INT((COLUMNS($B$41:H41)-1) / 12) -> 6000 | I41: =I5/3 * (Inputs!$B$32 / 12) * (1 + Inputs!$B$44)^INT((COLUMNS($B$41:I41)-1) / 12) -> 6000 | ... BA41: =BA5/3 * (Inputs!$B$32 / 12) * (1 + Inputs!$B$44)^INT((COLUMNS($B$41:BA41)-1) / 12) -> 7293.0375
A42: CTO Gehalt | B42: =B5/3 * (Inputs!$B$33 / 12) * (1 + Inputs!$B$44)^INT((COLUMNS($B$42:B42)-1) / 12) -> 6000 | C42: =C5/3 * (Inputs!$B$33 / 12) * (1 + Inputs!$B$44)^INT((COLUMNS($B$42:C42)-1) / 12) -> 6000 | D42: =D5/3 * (Inputs!$B$33 / 12) * (1 + Inputs!$B$44)^INT((COLUMNS($B$42:D42)-1) / 12) -> 6000 | E42: =E5/3 * (Inputs!$B$33 / 12) * (1 + Inputs!$B$44)^INT((COLUMNS($B$42:E42)-1) / 12) -> 6000 | F42: =F5/3 * (Inputs!$B$33 / 12) * (1 + Inputs!$B$44)^INT((COLUMNS($B$42:F42)-1) / 12) -> 6000 | G42: =G5/3 * (Inputs!$B$33 / 12) * (1 + Inputs!$B$44)^INT((COLUMNS($B$42:G42)-1) / 12) -> 6000 | H42: =H5/3 * (Inputs!$B$33 / 12) * (1 + Inputs!$B$44)^INT((COLUMNS($B$42:H42)-1) / 12) -> 6000 | I42: =I5/3 * (Inputs!$B$33 / 12) * (1 + Inputs!$B$44)^INT((COLUMNS($B$42:I42)-1) / 12) -> 6000 | ... BA42: =BA5/3 * (Inputs!$B$33 / 12) * (1 + Inputs!$B$44)^INT((COLUMNS($B$42:BA42)-1) / 12) -> 7293.0375
A43: CCO Gehalt | B43: =B5/3 * (Inputs!$B$34 / 12) * (1 + Inputs!$B$44)^INT((COLUMNS($B$43:B43)-1) / 12) -> 6000 | C43: =C5/3 * (Inputs!$B$34 / 12) * (1 + Inputs!$B$44)^INT((COLUMNS($B$43:C43)-1) / 12) -> 6000 | D43: =D5/3 * (Inputs!$B$34 / 12) * (1 + Inputs!$B$44)^INT((COLUMNS($B$43:D43)-1) / 12) -> 6000 | E43: =E5/3 * (Inputs!$B$34 / 12) * (1 + Inputs!$B$44)^INT((COLUMNS($B$43:E43)-1) / 12) -> 6000 | F43: =F5/3 * (Inputs!$B$34 / 12) * (1 + Inputs!$B$44)^INT((COLUMNS($B$43:F43)-1) / 12) -> 6000 | G43: =G5/3 * (Inputs!$B$34 / 12) * (1 + Inputs!$B$44)^INT((COLUMNS($B$43:G43)-1) / 12) -> 6000 | H43: =H5/3 * (Inputs!$B$34 / 12) * (1 + Inputs!$B$44)^INT((COLUMNS($B$43:H43)-1) / 12) -> 6000 | I43: =I5/3 * (Inputs!$B$34 / 12) * (1 + Inputs!$B$44)^INT((COLUMNS($B$43:I43)-1) / 12) -> 6000 | ... BA43: =BA5/3 * (Inputs!$B$34 / 12) * (1 + Inputs!$B$44)^INT((COLUMNS($B$43:BA43)-1) / 12) -> 7293.0375
A44: 1. Senior Engineer Gehalt | B44: =B6 * (Inputs!$B$35 / 12) * (1 + Inputs!$B$44)^INT((COLUMNS($B$44:B44)-1) / 12) -> 0 | C44: =C6 * (Inputs!$B$35 / 12) * (1 + Inputs!$B$44)^INT((COLUMNS($B$44:C44)-1) / 12) -> 0 | D44: =D6 * (Inputs!$B$35 / 12) * (1 + Inputs!$B$44)^INT((COLUMNS($B$44:D44)-1) / 12) -> 0 | E44: =E6 * (Inputs!$B$35 / 12) * (1 + Inputs!$B$44)^INT((COLUMNS($B$44:E44)-1) / 12) -> 0 | F44: =F6 * (Inputs!$B$35 / 12) * (1 + Inputs!$B$44)^INT((COLUMNS($B$44:F44)-1) / 12) -> 0 | G44: =G6 * (Inputs!$B$35 / 12) * (1 + Inputs!$B$44)^INT((COLUMNS($B$44:G44)-1) / 12) -> 0 | H44: =H6 * (Inputs!$B$35 / 12) * (1 + Inputs!$B$44)^INT((COLUMNS($B$44:H44)-1) / 12) -> 7500 | I44: =I6 * (Inputs!$B$35 / 12) * (1 + Inputs!$B$44)^INT((COLUMNS($B$44:I44)-1) / 12) -> 7500 | ... BA44: =BA6 * (Inputs!$B$35 / 12) * (1 + Inputs!$B$44)^INT((COLUMNS($B$44:BA44)-1) / 12) -> 9116.2969
A45: 2. Senior Engineer Gehalt | B45: =B7 * (Inputs!$B$35 / 12) * (1 + Inputs!$B$44)^INT((COLUMNS($B$45:B45)-1) / 12) -> 0 | C45: =C7 * (Inputs!$B$35 / 12) * (1 + Inputs!$B$44)^INT((COLUMNS($B$45:C45)-1) / 12) -> 0 | D45: =D7 * (Inputs!$B$35 / 12) * (1 + Inputs!$B$44)^INT((COLUMNS($B$45:D45)-1) / 12) -> 0 | E45: =E7 * (Inputs!$B$35 / 12) * (1 + Inputs!$B$44)^INT((COLUMNS($B$45:E45)-1) / 12) -> 0 | F45: =F7 * (Inputs!$B$35 / 12) * (1 + Inputs!$B$44)^INT((COLUMNS($B$45:F45)-1) / 12) -> 0 | G45: =G7 * (Inputs!$B$35 / 12) * (1 + Inputs!$B$44)^INT((COLUMNS($B$45:G45)-1) / 12) -> 0 | H45: =H7 * (Inputs!$B$35 / 12) * (1 + Inputs!$B$44)^INT((COLUMNS($B$45:H45)-1) / 12) -> 0 | I45: =I7 * (Inputs!$B$35 / 12) * (1 + Inputs!$B$44)^INT((COLUMNS($B$45:I45)-1) / 12) -> 0 | ... BA45: =BA7 * (Inputs!$B$35 / 12) * (1 + Inputs!$B$44)^INT((COLUMNS($B$45:BA45)-1) / 12) -> 9116.2969
A46: 1. Junior Engineer Gehalt | B46: =B8 * (Inputs!$B$36 / 12) * (1 + Inputs!$B$44)^INT((COLUMNS($B$46:B46)-1) / 12) -> 0 | C46: =C8 * (Inputs!$B$36 / 12) * (1 + Inputs!$B$44)^INT((COLUMNS($B$46:C46)-1) / 12) -> 0 | D46: =D8 * (Inputs!$B$36 / 12) * (1 + Inputs!$B$44)^INT((COLUMNS($B$46:D46)-1) / 12) -> 0 | E46: =E8 * (Inputs!$B$36 / 12) * (1 + Inputs!$B$44)^INT((COLUMNS($B$46:E46)-1) / 12) -> 0 | F46: =F8 * (Inputs!$B$36 / 12) * (1 + Inputs!$B$44)^INT((COLUMNS($B$46:F46)-1) / 12) -> 0 | G46: =G8 * (Inputs!$B$36 / 12) * (1 + Inputs!$B$44)^INT((COLUMNS($B$46:G46)-1) / 12) -> 0 | H46: =H8 * (Inputs!$B$36 / 12) * (1 + Inputs!$B$44)^INT((COLUMNS($B$46:H46)-1) / 12) -> 0 | I46: =I8 * (Inputs!$B$36 / 12) * (1 + Inputs!$B$44)^INT((COLUMNS($B$46:I46)-1) / 12) -> 0 | ... BA46: =BA8 * (Inputs!$B$36 / 12) * (1 + Inputs!$B$44)^INT((COLUMNS($B$46:BA46)-1) / 12) -> 6077.5312
A47: 1. ML/AI Engineer Gehalt | B47: =B9 * (Inputs!$B$37 / 12) * (1 + Inputs!$B$44)^INT((COLUMNS($B$47:B47)-1) / 12) -> 0 | C47: =C9 * (Inputs!$B$37 / 12) * (1 + Inputs!$B$44)^INT((COLUMNS($B$47:C47)-1) / 12) -> 0 | D47: =D9 * (Inputs!$B$37 / 12) * (1 + Inputs!$B$44)^INT((COLUMNS($B$47:D47)-1) / 12) -> 0 | E47: =E9 * (Inputs!$B$37 / 12) * (1 + Inputs!$B$44)^INT((COLUMNS($B$47:E47)-1) / 12) -> 0 | F47: =F9 * (Inputs!$B$37 / 12) * (1 + Inputs!$B$44)^INT((COLUMNS($B$47:F47)-1) / 12) -> 0 | G47: =G9 * (Inputs!$B$37 / 12) * (1 + Inputs!$B$44)^INT((COLUMNS($B$47:G47)-1) / 12) -> 0 | H47: =H9 * (Inputs!$B$37 / 12) * (1 + Inputs!$B$44)^INT((COLUMNS($B$47:H47)-1) / 12) -> 0 | I47: =I9 * (Inputs!$B$37 / 12) * (1 + Inputs!$B$44)^INT((COLUMNS($B$47:I47)-1) / 12) -> 9166.6667 | ... BA47: =BA9 * (Inputs!$B$37 / 12) * (1 + Inputs!$B$44)^INT((COLUMNS($B$47:BA47)-1) / 12) -> 11142.141
A48: 2. ML/AI Engineer Gehalt | B48: =B10 * (Inputs!$B$37 / 12) * (1 + Inputs!$B$44)^INT((COLUMNS($B$48:B48)-1) / 12) -> 0 | C48: =C10 * (Inputs!$B$37 / 12) * (1 + Inputs!$B$44)^INT((COLUMNS($B$48:C48)-1) / 12) -> 0 | D48: =D10 * (Inputs!$B$37 / 12) * (1 + Inputs!$B$44)^INT((COLUMNS($B$48:D48)-1) / 12) -> 0 | E48: =E10 * (Inputs!$B$37 / 12) * (1 + Inputs!$B$44)^INT((COLUMNS($B$48:E48)-1) / 12) -> 0 | F48: =F10 * (Inputs!$B$37 / 12) * (1 + Inputs!$B$44)^INT((COLUMNS($B$48:F48)-1) / 12) -> 0 | G48: =G10 * (Inputs!$B$37 / 12) * (1 + Inputs!$B$44)^INT((COLUMNS($B$48:G48)-1) / 12) -> 0 | H48: =H10 * (Inputs!$B$37 / 12) * (1 + Inputs!$B$44)^INT((COLUMNS($B$48:H48)-1) / 12) -> 0 | I48: =I10 * (Inputs!$B$37 / 12) * (1 + Inputs!$B$44)^INT((COLUMNS($B$48:I48)-1) / 12) -> 0 | ... BA48: =BA10 * (Inputs!$B$37 / 12) * (1 + Inputs!$B$44)^INT((COLUMNS($B$48:BA48)-1) / 12) -> 11142.141
A49: 1. Sales Rep Gehalt | B49: =B11 * (Inputs!$B$39 / 12) * (1 + Inputs!$B$44)^INT((COLUMNS($B$49:B49)-1) / 12) -> 0 | C49: =C11 * (Inputs!$B$39 / 12) * (1 + Inputs!$B$44)^INT((COLUMNS($B$49:C49)-1) / 12) -> 0 | D49: =D11 * (Inputs!$B$39 / 12) * (1 + Inputs!$B$44)^INT((COLUMNS($B$49:D49)-1) / 12) -> 0 | E49: =E11 * (Inputs!$B$39 / 12) * (1 + Inputs!$B$44)^INT((COLUMNS($B$49:E49)-1) / 12) -> 0 | F49: =F11 * (Inputs!$B$39 / 12) * (1 + Inputs!$B$44)^INT((COLUMNS($B$49:F49)-1) / 12) -> 0 | G49: =G11 * (Inputs!$B$39 / 12) * (1 + Inputs!$B$44)^INT((COLUMNS($B$49:G49)-1) / 12) -> 0 | H49: =H11 * (Inputs!$B$39 / 12) * (1 + Inputs!$B$44)^INT((COLUMNS($B$49:H49)-1) / 12) -> 0 | I49: =I11 * (Inputs!$B$39 / 12) * (1 + Inputs!$B$44)^INT((COLUMNS($B$49:I49)-1) / 12) -> 0 | ... BA49: =BA11 * (Inputs!$B$39 / 12) * (1 + Inputs!$B$44)^INT((COLUMNS($B$49:BA49)-1) / 12) -> 0
A50: 2. Sales Rep Gehalt | B50: =B12 * (Inputs!$B$39 / 12) * (1 + Inputs!$B$44)^INT((COLUMNS($B$50:B50)-1) / 12) -> 0 | C50: =C12 * (Inputs!$B$39 / 12) * (1 + Inputs!$B$44)^INT((COLUMNS($B$50:C50)-1) / 12) -> 0 | D50: =D12 * (Inputs!$B$39 / 12) * (1 + Inputs!$B$44)^INT((COLUMNS($B$50:D50)-1) / 12) -> 0 | E50: =E12 * (Inputs!$B$39 / 12) * (1 + Inputs!$B$44)^INT((COLUMNS($B$50:E50)-1) / 12) -> 0 | F50: =F12 * (Inputs!$B$39 / 12) * (1 + Inputs!$B$44)^INT((COLUMNS($B$50:F50)-1) / 12) -> 0 | G50: =G12 * (Inputs!$B$39 / 12) * (1 + Inputs!$B$44)^INT((COLUMNS($B$50:G50)-1) / 12) -> 0 | H50: =H12 * (Inputs!$B$39 / 12) * (1 + Inputs!$B$44)^INT((COLUMNS($B$50:H50)-1) / 12) -> 0 | I50: =I12 * (Inputs!$B$39 / 12) * (1 + Inputs!$B$44)^INT((COLUMNS($B$50:I50)-1) / 12) -> 0 | ... BA50: =BA12 * (Inputs!$B$39 / 12) * (1 + Inputs!$B$44)^INT((COLUMNS($B$50:BA50)-1) / 12) -> 13167.984
A51: 1. Customer Success Gehalt | B51: =B13 * (Inputs!$B$41 / 12) * (1 + Inputs!$B$44)^INT((COLUMNS($B$51:B51)-1) / 12) -> 0 | C51: =C13 * (Inputs!$B$41 / 12) * (1 + Inputs!$B$44)^INT((COLUMNS($B$51:C51)-1) / 12) -> 0 | D51: =D13 * (Inputs!$B$41 / 12) * (1 + Inputs!$B$44)^INT((COLUMNS($B$51:D51)-1) / 12) -> 0 | E51: =E13 * (Inputs!$B$41 / 12) * (1 + Inputs!$B$44)^INT((COLUMNS($B$51:E51)-1) / 12) -> 0 | F51: =F13 * (Inputs!$B$41 / 12) * (1 + Inputs!$B$44)^INT((COLUMNS($B$51:F51)-1) / 12) -> 0 | G51: =G13 * (Inputs!$B$41 / 12) * (1 + Inputs!$B$44)^INT((COLUMNS($B$51:G51)-1) / 12) -> 0 | H51: =H13 * (Inputs!$B$41 / 12) * (1 + Inputs!$B$44)^INT((COLUMNS($B$51:H51)-1) / 12) -> 0 | I51: =I13 * (Inputs!$B$41 / 12) * (1 + Inputs!$B$44)^INT((COLUMNS($B$51:I51)-1) / 12) -> 0 | ... BA51: =BA13 * (Inputs!$B$41 / 12) * (1 + Inputs!$B$44)^INT((COLUMNS($B$51:BA51)-1) / 12) -> 6583.9922
A52: 1. Marketing Manager Gehalt | B52: =B14 * (Inputs!$B$41 / 12) * (1 + Inputs!$B$44)^INT((COLUMNS($B$52:B52)-1) / 12) -> 0 | C52: =C14 * (Inputs!$B$41 / 12) * (1 + Inputs!$B$44)^INT((COLUMNS($B$51:C52)-1) / 12) -> 0 | D52: =D14 * (Inputs!$B$41 / 12) * (1 + Inputs!$B$44)^INT((COLUMNS($B$51:D52)-1) / 12) -> 0 | E52: =E14 * (Inputs!$B$41 / 12) * (1 + Inputs!$B$44)^INT((COLUMNS($B$51:E52)-1) / 12) -> 0 | F52: =F14 * (Inputs!$B$41 / 12) * (1 + Inputs!$B$44)^INT((COLUMNS($B$51:F52)-1) / 12) -> 0 | G52: =G14 * (Inputs!$B$41 / 12) * (1 + Inputs!$B$44)^INT((COLUMNS($B$51:G52)-1) / 12) -> 0 | H52: =H14 * (Inputs!$B$41 / 12) * (1 + Inputs!$B$44)^INT((COLUMNS($B$51:H52)-1) / 12) -> 0 | I52: =I14 * (Inputs!$B$41 / 12) * (1 + Inputs!$B$44)^INT((COLUMNS($B$51:I52)-1) / 12) -> 0 | J52: =J14 * (Inputs!$B$41 / 12) * (1 + Inputs!$B$44)^INT((COLUMNS($B$51:J52)-1) / 12) -> 0 | ... BA52: =BA14 * (Inputs!$B$41 / 12) * (1 + Inputs!$B$44)^INT((COLUMNS($B$51:BA52)-1) / 12) -> 6583.9922
A53: 1. Product Manager Gehalt | B53: =B15 * (Inputs!$B$38 / 12) * (1 + Inputs!$B$44)^INT((COLUMNS($B$53:B53)-1) / 12) -> 0 | C53: =C15 * (Inputs!$B$38 / 12) * (1 + Inputs!$B$44)^INT((COLUMNS($B$53:C53)-1) / 12) -> 0 | D53: =D15 * (Inputs!$B$38 / 12) * (1 + Inputs!$B$44)^INT((COLUMNS($B$53:D53)-1) / 12) -> 0 | E53: =E15 * (Inputs!$B$38 / 12) * (1 + Inputs!$B$44)^INT((COLUMNS($B$53:E53)-1) / 12) -> 0 | F53: =F15 * (Inputs!$B$38 / 12) * (1 + Inputs!$B$44)^INT((COLUMNS($B$53:F53)-1) / 12) -> 0 | G53: =G15 * (Inputs!$B$38 / 12) * (1 + Inputs!$B$44)^INT((COLUMNS($B$53:G53)-1) / 12) -> 0 | H53: =H15 * (Inputs!$B$38 / 12) * (1 + Inputs!$B$44)^INT((COLUMNS($B$53:H53)-1) / 12) -> 0 | I53: =I15 * (Inputs!$B$38 / 12) * (1 + Inputs!$B$44)^INT((COLUMNS($B$53:I53)-1) / 12) -> 0 | ... BA53: =BA15 * (Inputs!$B$38 / 12) * (1 + Inputs!$B$44)^INT((COLUMNS($B$53:BA53)-1) / 12) -> 8103.375
A54: 1. Office Manager Gehalt | B54: =B16 * (Inputs!$B$42 / 12) * (1 + Inputs!$B$44)^INT((COLUMNS($B$54:B54)-1) / 12) -> 0 | C54: =C16 * (Inputs!$B$42 / 12) * (1 + Inputs!$B$44)^INT((COLUMNS($B$54:C54)-1) / 12) -> 0 | D54: =D16 * (Inputs!$B$42 / 12) * (1 + Inputs!$B$44)^INT((COLUMNS($B$54:D54)-1) / 12) -> 0 | E54: =E16 * (Inputs!$B$42 / 12) * (1 + Inputs!$B$44)^INT((COLUMNS($B$54:E54)-1) / 12) -> 0 | F54: =F16 * (Inputs!$B$42 / 12) * (1 + Inputs!$B$44)^INT((COLUMNS($B$54:F54)-1) / 12) -> 0 | G54: =G16 * (Inputs!$B$42 / 12) * (1 + Inputs!$B$44)^INT((COLUMNS($B$54:G54)-1) / 12) -> 0 | H54: =H16 * (Inputs!$B$42 / 12) * (1 + Inputs!$B$44)^INT((COLUMNS($B$54:H54)-1) / 12) -> 0 | I54: =I16 * (Inputs!$B$42 / 12) * (1 + Inputs!$B$44)^INT((COLUMNS($B$54:I54)-1) / 12) -> 0 | ... BA54: =BA16 * (Inputs!$B$42 / 12) * (1 + Inputs!$B$44)^INT((COLUMNS($B$54:BA54)-1) / 12) -> 4558.1484
A55: 3. Senior Engineer Gehalt | B55: =B17 * (Inputs!$B$35 / 12) * (1 + Inputs!$B$44)^INT((COLUMNS($B$55:B55)-1) / 12) -> 0 | C55: =C17 * (Inputs!$B$35 / 12) * (1 + Inputs!$B$44)^INT((COLUMNS($B$55:C55)-1) / 12) -> 0 | D55: =D17 * (Inputs!$B$35 / 12) * (1 + Inputs!$B$44)^INT((COLUMNS($B$55:D55)-1) / 12) -> 0 | E55: =E17 * (Inputs!$B$35 / 12) * (1 + Inputs!$B$44)^INT((COLUMNS($B$55:E55)-1) / 12) -> 0 | F55: =F17 * (Inputs!$B$35 / 12) * (1 + Inputs!$B$44)^INT((COLUMNS($B$55:F55)-1) / 12) -> 0 | G55: =G17 * (Inputs!$B$35 / 12) * (1 + Inputs!$B$44)^INT((COLUMNS($B$55:G55)-1) / 12) -> 0 | H55: =H17 * (Inputs!$B$35 / 12) * (1 + Inputs!$B$44)^INT((COLUMNS($B$55:H55)-1) / 12) -> 0 | I55: =I17 * (Inputs!$B$35 / 12) * (1 + Inputs!$B$44)^INT((COLUMNS($B$55:I55)-1) / 12) -> 0 | ... BA55: =BA17 * (Inputs!$B$35 / 12) * (1 + Inputs!$B$44)^INT((COLUMNS($B$55:BA55)-1) / 12) -> 9116.2969
A56: 4. Senior Engineer Gehalt | B56: =B18 * (Inputs!$B$35 / 12) * (1 + Inputs!$B$44)^INT((COLUMNS($B$56:B56)-1) / 12) -> 0 | C56: =C18 * (Inputs!$B$35 / 12) * (1 + Inputs!$B$44)^INT((COLUMNS($B$56:C56)-1) / 12) -> 0 | D56: =D18 * (Inputs!$B$35 / 12) * (1 + Inputs!$B$44)^INT((COLUMNS($B$56:D56)-1) / 12) -> 0 | E56: =E18 * (Inputs!$B$35 / 12) * (1 + Inputs!$B$44)^INT((COLUMNS($B$56:E56)-1) / 12) -> 0 | F56: =F18 * (Inputs!$B$35 / 12) * (1 + Inputs!$B$44)^INT((COLUMNS($B$56:F56)-1) / 12) -> 0 | G56: =G18 * (Inputs!$B$35 / 12) * (1 + Inputs!$B$44)^INT((COLUMNS($B$56:G56)-1) / 12) -> 0 | H56: =H18 * (Inputs!$B$35 / 12) * (1 + Inputs!$B$44)^INT((COLUMNS($B$56:H56)-1) / 12) -> 0 | I56: =I18 * (Inputs!$B$35 / 12) * (1 + Inputs!$B$44)^INT((COLUMNS($B$56:I56)-1) / 12) -> 0 | ... BA56: =BA18 * (Inputs!$B$35 / 12) * (1 + Inputs!$B$44)^INT((COLUMNS($B$56:BA56)-1) / 12) -> 0
A57: 2. Junior Engineer Gehalt | B57: =B19 * (Inputs!$B$36 / 12) * (1 + Inputs!$B$44)^INT((COLUMNS($B$57:B57)-1) / 12) -> 0 | C57: =C19 * (Inputs!$B$36 / 12) * (1 + Inputs!$B$44)^INT((COLUMNS($B$57:C57)-1) / 12) -> 0 | D57: =D19 * (Inputs!$B$36 / 12) * (1 + Inputs!$B$44)^INT((COLUMNS($B$57:D57)-1) / 12) -> 0 | E57: =E19 * (Inputs!$B$36 / 12) * (1 + Inputs!$B$44)^INT((COLUMNS($B$57:E57)-1) / 12) -> 0 | F57: =F19 * (Inputs!$B$36 / 12) * (1 + Inputs!$B$44)^INT((COLUMNS($B$57:F57)-1) / 12) -> 0 | G57: =G19 * (Inputs!$B$36 / 12) * (1 + Inputs!$B$44)^INT((COLUMNS($B$57:G57)-1) / 12) -> 0 | H57: =H19 * (Inputs!$B$36 / 12) * (1 + Inputs!$B$44)^INT((COLUMNS($B$57:H57)-1) / 12) -> 0 | I57: =I19 * (Inputs!$B$36 / 12) * (1 + Inputs!$B$44)^INT((COLUMNS($B$57:I57)-1) / 12) -> 0 | ... BA57: =BA19 * (Inputs!$B$36 / 12) * (1 + Inputs!$B$44)^INT((COLUMNS($B$57:BA57)-1) / 12) -> 6077.5312
A58: 3. ML/AI Engineer Gehalt | B58: =B20 * (Inputs!$B$37 / 12) * (1 + Inputs!$B$44)^INT((COLUMNS($B$58:B58)-1) / 12) -> 0 | C58: =C20 * (Inputs!$B$37 / 12) * (1 + Inputs!$B$44)^INT((COLUMNS($B$58:C58)-1) / 12) -> 0 | D58: =D20 * (Inputs!$B$37 / 12) * (1 + Inputs!$B$44)^INT((COLUMNS($B$58:D58)-1) / 12) -> 0 | E58: =E20 * (Inputs!$B$37 / 12) * (1 + Inputs!$B$44)^INT((COLUMNS($B$58:E58)-1) / 12) -> 0 | F58: =F20 * (Inputs!$B$37 / 12) * (1 + Inputs!$B$44)^INT((COLUMNS($B$58:F58)-1) / 12) -> 0 | G58: =G20 * (Inputs!$B$37 / 12) * (1 + Inputs!$B$44)^INT((COLUMNS($B$58:G58)-1) / 12) -> 0 | H58: =H20 * (Inputs!$B$37 / 12) * (1 + Inputs!$B$44)^INT((COLUMNS($B$58:H58)-1) / 12) -> 0 | I58: =I20 * (Inputs!$B$37 / 12) * (1 + Inputs!$B$44)^INT((COLUMNS($B$58:I58)-1) / 12) -> 0 | ... BA58: =BA20 * (Inputs!$B$37 / 12) * (1 + Inputs!$B$44)^INT((COLUMNS($B$58:BA58)-1) / 12) -> 11142.141
A59: 3. Sales Rep Gehalt | B59: =B21 * (Inputs!$B$39 / 12) * (1 + Inputs!$B$44)^INT((COLUMNS($B$59:B59)-1) / 12) -> 0 | C59: =C21 * (Inputs!$B$39 / 12) * (1 + Inputs!$B$44)^INT((COLUMNS($B$59:C59)-1) / 12) -> 0 | D59: =D21 * (Inputs!$B$39 / 12) * (1 + Inputs!$B$44)^INT((COLUMNS($B$59:D59)-1) / 12) -> 0 | E59: =E21 * (Inputs!$B$39 / 12) * (1 + Inputs!$B$44)^INT((COLUMNS($B$59:E59)-1) / 12) -> 0 | F59: =F21 * (Inputs!$B$39 / 12) * (1 + Inputs!$B$44)^INT((COLUMNS($B$59:F59)-1) / 12) -> 0 | G59: =G21 * (Inputs!$B$39 / 12) * (1 + Inputs!$B$44)^INT((COLUMNS($B$59:G59)-1) / 12) -> 0 | H59: =H21 * (Inputs!$B$39 / 12) * (1 + Inputs!$B$44)^INT((COLUMNS($B$59:H59)-1) / 12) -> 0 | I59: =I21 * (Inputs!$B$39 / 12) * (1 + Inputs!$B$44)^INT((COLUMNS($B$59:I59)-1) / 12) -> 0 | ... BA59: =BA21 * (Inputs!$B$39 / 12) * (1 + Inputs!$B$44)^INT((COLUMNS($B$59:BA59)-1) / 12) -> 0
A60: 2. Customer Success Gehalt | B60: =B22 * (Inputs!$B$41 / 12) * (1 + Inputs!$B$44)^INT((COLUMNS($B$60:B60)-1) / 12) -> 0 | C60: =C22 * (Inputs!$B$41 / 12) * (1 + Inputs!$B$44)^INT((COLUMNS($B$60:C60)-1) / 12) -> 0 | D60: =D22 * (Inputs!$B$41 / 12) * (1 + Inputs!$B$44)^INT((COLUMNS($B$60:D60)-1) / 12) -> 0 | E60: =E22 * (Inputs!$B$41 / 12) * (1 + Inputs!$B$44)^INT((COLUMNS($B$60:E60)-1) / 12) -> 0 | F60: =F22 * (Inputs!$B$41 / 12) * (1 + Inputs!$B$44)^INT((COLUMNS($B$60:F60)-1) / 12) -> 0 | G60: =G22 * (Inputs!$B$41 / 12) * (1 + Inputs!$B$44)^INT((COLUMNS($B$60:G60)-1) / 12) -> 0 | H60: =H22 * (Inputs!$B$41 / 12) * (1 + Inputs!$B$44)^INT((COLUMNS($B$60:H60)-1) / 12) -> 0 | I60: =I22 * (Inputs!$B$41 / 12) * (1 + Inputs!$B$44)^INT((COLUMNS($B$60:I60)-1) / 12) -> 0 | ... BA60: =BA22 * (Inputs!$B$41 / 12) * (1 + Inputs!$B$44)^INT((COLUMNS($B$60:BA60)-1) / 12) -> 6583.9922
A61: 2. Marketing Manager Gehalt | B61: =B23 * (Inputs!$B$40 / 12) * (1 + Inputs!$B$44)^INT((COLUMNS($B$61:B61)-1) / 12) -> 0 | C61: =C23 * (Inputs!$B$40 / 12) * (1 + Inputs!$B$44)^INT((COLUMNS($B$61:C61)-1) / 12) -> 0 | D61: =D23 * (Inputs!$B$40 / 12) * (1 + Inputs!$B$44)^INT((COLUMNS($B$61:D61)-1) / 12) -> 0 | E61: =E23 * (Inputs!$B$40 / 12) * (1 + Inputs!$B$44)^INT((COLUMNS($B$61:E61)-1) / 12) -> 0 | F61: =F23 * (Inputs!$B$40 / 12) * (1 + Inputs!$B$44)^INT((COLUMNS($B$61:F61)-1) / 12) -> 0 | G61: =G23 * (Inputs!$B$40 / 12) * (1 + Inputs!$B$44)^INT((COLUMNS($B$61:G61)-1) / 12) -> 0 | H61: =H23 * (Inputs!$B$40 / 12) * (1 + Inputs!$B$44)^INT((COLUMNS($B$61:H61)-1) / 12) -> 0 | I61: =I23 * (Inputs!$B$40 / 12) * (1 + Inputs!$B$44)^INT((COLUMNS($B$61:I61)-1) / 12) -> 0 | ... BA61: =BA23 * (Inputs!$B$40 / 12) * (1 + Inputs!$B$44)^INT((COLUMNS($B$61:BA61)-1) / 12) -> 6583.9922
A62: 5. Senior Engineer Gehalt | B62: =B24 * (Inputs!$B$35 / 12) * (1 + Inputs!$B$44)^INT((COLUMNS($B$62:B62)-1) / 12) -> 0 | C62: =C24 * (Inputs!$B$35 / 12) * (1 + Inputs!$B$44)^INT((COLUMNS($B$62:C62)-1) / 12) -> 0 | D62: =D24 * (Inputs!$B$35 / 12) * (1 + Inputs!$B$44)^INT((COLUMNS($B$62:D62)-1) / 12) -> 0 | E62: =E24 * (Inputs!$B$35 / 12) * (1 + Inputs!$B$44)^INT((COLUMNS($B$62:E62)-1) / 12) -> 0 | F62: =F24 * (Inputs!$B$35 / 12) * (1 + Inputs!$B$44)^INT((COLUMNS($B$62:F62)-1) / 12) -> 0 | G62: =G24 * (Inputs!$B$35 / 12) * (1 + Inputs!$B$44)^INT((COLUMNS($B$62:G62)-1) / 12) -> 0 | H62: =H24 * (Inputs!$B$35 / 12) * (1 + Inputs!$B$44)^INT((COLUMNS($B$62:H62)-1) / 12) -> 0 | I62: =I24 * (Inputs!$B$35 / 12) * (1 + Inputs!$B$44)^INT((COLUMNS($B$62:I62)-1) / 12) -> 0 | ... BA62: =BA24 * (Inputs!$B$35 / 12) * (1 + Inputs!$B$44)^INT((COLUMNS($B$62:BA62)-1) / 12) -> 0
A63: 3. Junior Engineer Gehalt | B63: =B25 * (Inputs!$B$36 / 12) * (1 + Inputs!$B$44)^INT((COLUMNS($B$63:B63)-1) / 12) -> 0 | C63: =C25 * (Inputs!$B$36 / 12) * (1 + Inputs!$B$44)^INT((COLUMNS($B$63:C63)-1) / 12) -> 0 | D63: =D25 * (Inputs!$B$36 / 12) * (1 + Inputs!$B$44)^INT((COLUMNS($B$63:D63)-1) / 12) -> 0 | E63: =E25 * (Inputs!$B$36 / 12) * (1 + Inputs!$B$44)^INT((COLUMNS($B$63:E63)-1) / 12) -> 0 | F63: =F25 * (Inputs!$B$36 / 12) * (1 + Inputs!$B$44)^INT((COLUMNS($B$63:F63)-1) / 12) -> 0 | G63: =G25 * (Inputs!$B$36 / 12) * (1 + Inputs!$B$44)^INT((COLUMNS($B$63:G63)-1) / 12) -> 0 | H63: =H25 * (Inputs!$B$36 / 12) * (1 + Inputs!$B$44)^INT((COLUMNS($B$63:H63)-1) / 12) -> 0 | I63: =I25 * (Inputs!$B$36 / 12) * (1 + Inputs!$B$44)^INT((COLUMNS($B$63:I63)-1) / 12) -> 0 | ... BA63: =BA25 * (Inputs!$B$36 / 12) * (1 + Inputs!$B$44)^INT((COLUMNS($B$63:BA63)-1) / 12) -> 0
A64: 4. ML/AI Engineer Gehalt | B64: =B26 * (Inputs!$B$37 / 12) * (1 + Inputs!$B$44)^INT((COLUMNS($B$64:B64)-1) / 12) -> 0 | C64: =C26 * (Inputs!$B$37 / 12) * (1 + Inputs!$B$44)^INT((COLUMNS($B$64:C64)-1) / 12) -> 0 | D64: =D26 * (Inputs!$B$37 / 12) * (1 + Inputs!$B$44)^INT((COLUMNS($B$64:D64)-1) / 12) -> 0 | E64: =E26 * (Inputs!$B$37 / 12) * (1 + Inputs!$B$44)^INT((COLUMNS($B$64:E64)-1) / 12) -> 0 | F64: =F26 * (Inputs!$B$37 / 12) * (1 + Inputs!$B$44)^INT((COLUMNS($B$64:F64)-1) / 12) -> 0 | G64: =G26 * (Inputs!$B$37 / 12) * (1 + Inputs!$B$44)^INT((COLUMNS($B$64:G64)-1) / 12) -> 0 | H64: =H26 * (Inputs!$B$37 / 12) * (1 + Inputs!$B$44)^INT((COLUMNS($B$64:H64)-1) / 12) -> 0 | I64: =I26 * (Inputs!$B$37 / 12) * (1 + Inputs!$B$44)^INT((COLUMNS($B$64:I64)-1) / 12) -> 0 | ... BA64: =BA26 * (Inputs!$B$37 / 12) * (1 + Inputs!$B$44)^INT((COLUMNS($B$64:BA64)-1) / 12) -> 0
A65: 2. Product Manager Gehalt | B65: =B27 * (Inputs!$B$38 / 12) * (1 + Inputs!$B$44)^INT((COLUMNS($B$65:B65)-1) / 12) -> 0 | C65: =C27 * (Inputs!$B$38 / 12) * (1 + Inputs!$B$44)^INT((COLUMNS($B$65:C65)-1) / 12) -> 0 | D65: =D27 * (Inputs!$B$38 / 12) * (1 + Inputs!$B$44)^INT((COLUMNS($B$65:D65)-1) / 12) -> 0 | E65: =E27 * (Inputs!$B$38 / 12) * (1 + Inputs!$B$44)^INT((COLUMNS($B$65:E65)-1) / 12) -> 0 | F65: =F27 * (Inputs!$B$38 / 12) * (1 + Inputs!$B$44)^INT((COLUMNS($B$65:F65)-1) / 12) -> 0 | G65: =G27 * (Inputs!$B$38 / 12) * (1 + Inputs!$B$44)^INT((COLUMNS($B$65:G65)-1) / 12) -> 0 | H65: =H27 * (Inputs!$B$38 / 12) * (1 + Inputs!$B$44)^INT((COLUMNS($B$65:H65)-1) / 12) -> 0 | I65: =I27 * (Inputs!$B$38 / 12) * (1 + Inputs!$B$44)^INT((COLUMNS($B$65:I65)-1) / 12) -> 0 | ... AU65: =AU27 * (Inputs!$B$38 / 12) * (1 + Inputs!$B$44)^INT((COLUMNS($B$65:AU65)-1) / 12) -> 7717.5 | AV65: =AV27*Inputs!$B$38/12*(1+Inputs!$B$44)^INT((47-1)/12) -> 7717.5 | AW65: =AW27*Inputs!$B$38/12*(1+Inputs!$B$44)^INT((48-1)/12) -> 7717.5 | AX65: =AX27*Inputs!$B$38/12*(1+Inputs!$B$44)^INT((49-1)/12) -> 8103.375 | AY65: =AY27*Inputs!$B$38/12*(1+Inputs!$B$44)^INT((50-1)/12) -> 8103.375 | AZ65: =AZ27*Inputs!$B$38/12*(1+Inputs!$B$44)^INT((51-1)/12) -> 8103.375 | BA65: =BA27*Inputs!$B$38/12*(1+Inputs!$B$44)^INT((52-1)/12) -> 8103.375
A66: 4. Sales Rep Gehalt | B66: =B28 * (Inputs!$B$39 / 12) * (1 + Inputs!$B$44)^INT((COLUMNS($B$66:B66)-1) / 12) -> 0 | C66: =C28 * (Inputs!$B$39 / 12) * (1 + Inputs!$B$44)^INT((COLUMNS($B$66:C66)-1) / 12) -> 0 | D66: =D28 * (Inputs!$B$39 / 12) * (1 + Inputs!$B$44)^INT((COLUMNS($B$66:D66)-1) / 12) -> 0 | E66: =E28 * (Inputs!$B$39 / 12) * (1 + Inputs!$B$44)^INT((COLUMNS($B$66:E66)-1) / 12) -> 0 | F66: =F28 * (Inputs!$B$39 / 12) * (1 + Inputs!$B$44)^INT((COLUMNS($B$66:F66)-1) / 12) -> 0 | G66: =G28 * (Inputs!$B$39 / 12) * (1 + Inputs!$B$44)^INT((COLUMNS($B$66:G66)-1) / 12) -> 0 | H66: =H28 * (Inputs!$B$39 / 12) * (1 + Inputs!$B$44)^INT((COLUMNS($B$66:H66)-1) / 12) -> 0 | I66: =I28 * (Inputs!$B$39 / 12) * (1 + Inputs!$B$44)^INT((COLUMNS($B$66:I66)-1) / 12) -> 0 | ... BA66: =BA28 * (Inputs!$B$39 / 12) * (1 + Inputs!$B$44)^INT((COLUMNS($B$66:BA66)-1) / 12) -> 13167.984
A67: 3. Customer Success Gehalt | B67: =B29 * (Inputs!$B$41 / 12) * (1 + Inputs!$B$44)^INT((COLUMNS($B$67:B67)-1) / 12) -> 0 | C67: =C29 * (Inputs!$B$41 / 12) * (1 + Inputs!$B$44)^INT((COLUMNS($B$67:C67)-1) / 12) -> 0 | D67: =D29 * (Inputs!$B$41 / 12) * (1 + Inputs!$B$44)^INT((COLUMNS($B$67:D67)-1) / 12) -> 0 | E67: =E29 * (Inputs!$B$41 / 12) * (1 + Inputs!$B$44)^INT((COLUMNS($B$67:E67)-1) / 12) -> 0 | F67: =F29 * (Inputs!$B$41 / 12) * (1 + Inputs!$B$44)^INT((COLUMNS($B$67:F67)-1) / 12) -> 0 | G67: =G29 * (Inputs!$B$41 / 12) * (1 + Inputs!$B$44)^INT((COLUMNS($B$67:G67)-1) / 12) -> 0 | H67: =H29 * (Inputs!$B$41 / 12) * (1 + Inputs!$B$44)^INT((COLUMNS($B$67:H67)-1) / 12) -> 0 | I67: =I29 * (Inputs!$B$41 / 12) * (1 + Inputs!$B$44)^INT((COLUMNS($B$67:I67)-1) / 12) -> 0 | ... BA67: =BA29 * (Inputs!$B$41 / 12) * (1 + Inputs!$B$44)^INT((COLUMNS($B$67:BA67)-1) / 12) -> 0
A68: Finance Manager Gehalt | B68: =B30 * (Inputs!$B$43 / 12) * (1 + Inputs!$B$44)^INT((COLUMNS($B$68:B68)-1) / 12) -> 0 | C68: =C30 * (Inputs!$B$43 / 12) * (1 + Inputs!$B$44)^INT((COLUMNS($B$68:C68)-1) / 12) -> 0 | D68: =D30 * (Inputs!$B$43 / 12) * (1 + Inputs!$B$44)^INT((COLUMNS($B$68:D68)-1) / 12) -> 0 | E68: =E30 * (Inputs!$B$43 / 12) * (1 + Inputs!$B$44)^INT((COLUMNS($B$68:E68)-1) / 12) -> 0 | F68: =F30 * (Inputs!$B$43 / 12) * (1 + Inputs!$B$44)^INT((COLUMNS($B$68:F68)-1) / 12) -> 0 | G68: =G30 * (Inputs!$B$43 / 12) * (1 + Inputs!$B$44)^INT((COLUMNS($B$68:G68)-1) / 12) -> 0 | H68: =H30 * (Inputs!$B$43 / 12) * (1 + Inputs!$B$44)^INT((COLUMNS($B$68:H68)-1) / 12) -> 0 | I68: =I30 * (Inputs!$B$43 / 12) * (1 + Inputs!$B$44)^INT((COLUMNS($B$68:I68)-1) / 12) -> 0 | ... BA68: =BA30 * (Inputs!$B$43 / 12) * (1 + Inputs!$B$44)^INT((COLUMNS($B$68:BA68)-1) / 12) -> 8103.375
A69: 6. Senior Engineer Gehalt | B69: =B31 * (Inputs!$B$35 / 12) * (1 + Inputs!$B$44)^INT((COLUMNS($B$69:B69)-1) / 12) -> 0 | C69: =C31 * (Inputs!$B$35 / 12) * (1 + Inputs!$B$44)^INT((COLUMNS($B$69:C69)-1) / 12) -> 0 | D69: =D31 * (Inputs!$B$35 / 12) * (1 + Inputs!$B$44)^INT((COLUMNS($B$69:D69)-1) / 12) -> 0 | E69: =E31 * (Inputs!$B$35 / 12) * (1 + Inputs!$B$44)^INT((COLUMNS($B$69:E69)-1) / 12) -> 0 | F69: =F31 * (Inputs!$B$35 / 12) * (1 + Inputs!$B$44)^INT((COLUMNS($B$69:F69)-1) / 12) -> 0 | G69: =G31 * (Inputs!$B$35 / 12) * (1 + Inputs!$B$44)^INT((COLUMNS($B$69:G69)-1) / 12) -> 0 | H69: =H31 * (Inputs!$B$35 / 12) * (1 + Inputs!$B$44)^INT((COLUMNS($B$69:H69)-1) / 12) -> 0 | I69: =I31 * (Inputs!$B$35 / 12) * (1 + Inputs!$B$44)^INT((COLUMNS($B$69:I69)-1) / 12) -> 0 | ... BA69: =BA31 * (Inputs!$B$35 / 12) * (1 + Inputs!$B$44)^INT((COLUMNS($B$69:BA69)-1) / 12) -> 0
A70: 7. Senior Engineer Gehalt | B70: =B32 * (Inputs!$B$35 / 12) * (1 + Inputs!$B$44)^INT((COLUMNS($B$70:B70)-1) / 12) -> 0 | C70: =C32 * (Inputs!$B$35 / 12) * (1 + Inputs!$B$44)^INT((COLUMNS($B$70:C70)-1) / 12) -> 0 | D70: =D32 * (Inputs!$B$35 / 12) * (1 + Inputs!$B$44)^INT((COLUMNS($B$70:D70)-1) / 12) -> 0 | E70: =E32 * (Inputs!$B$35 / 12) * (1 + Inputs!$B$44)^INT((COLUMNS($B$70:E70)-1) / 12) -> 0 | F70: =F32 * (Inputs!$B$35 / 12) * (1 + Inputs!$B$44)^INT((COLUMNS($B$70:F70)-1) / 12) -> 0 | G70: =G32 * (Inputs!$B$35 / 12) * (1 + Inputs!$B$44)^INT((COLUMNS($B$70:G70)-1) / 12) -> 0 | H70: =H32 * (Inputs!$B$35 / 12) * (1 + Inputs!$B$44)^INT((COLUMNS($B$70:H70)-1) / 12) -> 0 | I70: =I32 * (Inputs!$B$35 / 12) * (1 + Inputs!$B$44)^INT((COLUMNS($B$70:I70)-1) / 12) -> 0 | ... BA70: =BA32 * (Inputs!$B$35 / 12) * (1 + Inputs!$B$44)^INT((COLUMNS($B$70:BA70)-1) / 12) -> 0
A71: 4. Junior Engineer Gehalt | B71: =B33 * (Inputs!$B$36 / 12) * (1 + Inputs!$B$44)^INT((COLUMNS($B$71:B71)-1) / 12) -> 0 | C71: =C33 * (Inputs!$B$36 / 12) * (1 + Inputs!$B$44)^INT((COLUMNS($B$71:C71)-1) / 12) -> 0 | D71: =D33 * (Inputs!$B$36 / 12) * (1 + Inputs!$B$44)^INT((COLUMNS($B$71:D71)-1) / 12) -> 0 | E71: =E33 * (Inputs!$B$36 / 12) * (1 + Inputs!$B$44)^INT((COLUMNS($B$71:E71)-1) / 12) -> 0 | F71: =F33 * (Inputs!$B$36 / 12) * (1 + Inputs!$B$44)^INT((COLUMNS($B$71:F71)-1) / 12) -> 0 | G71: =G33 * (Inputs!$B$36 / 12) * (1 + Inputs!$B$44)^INT((COLUMNS($B$71:G71)-1) / 12) -> 0 | H71: =H33 * (Inputs!$B$36 / 12) * (1 + Inputs!$B$44)^INT((COLUMNS($B$71:H71)-1) / 12) -> 0 | I71: =I33 * (Inputs!$B$36 / 12) * (1 + Inputs!$B$44)^INT((COLUMNS($B$71:I71)-1) / 12) -> 0 | ... BA71: =BA33 * (Inputs!$B$36 / 12) * (1 + Inputs!$B$44)^INT((COLUMNS($B$71:BA71)-1) / 12) -> 0
A72: 5. ML/AI Engineer Gehalt | B72: =B34 * (Inputs!$B$37 / 12) * (1 + Inputs!$B$44)^INT((COLUMNS($B$72:B72)-1) / 12) -> 0 | C72: =C34 * (Inputs!$B$37 / 12) * (1 + Inputs!$B$44)^INT((COLUMNS($B$72:C72)-1) / 12) -> 0 | D72: =D34 * (Inputs!$B$37 / 12) * (1 + Inputs!$B$44)^INT((COLUMNS($B$72:D72)-1) / 12) -> 0 | E72: =E34 * (Inputs!$B$37 / 12) * (1 + Inputs!$B$44)^INT((COLUMNS($B$72:E72)-1) / 12) -> 0 | F72: =F34 * (Inputs!$B$37 / 12) * (1 + Inputs!$B$44)^INT((COLUMNS($B$72:F72)-1) / 12) -> 0 | G72: =G34 * (Inputs!$B$37 / 12) * (1 + Inputs!$B$44)^INT((COLUMNS($B$72:G72)-1) / 12) -> 0 | H72: =H34 * (Inputs!$B$37 / 12) * (1 + Inputs!$B$44)^INT((COLUMNS($B$72:H72)-1) / 12) -> 0 | I72: =I34 * (Inputs!$B$37 / 12) * (1 + Inputs!$B$44)^INT((COLUMNS($B$72:I72)-1) / 12) -> 0 | ... BA72: =BA34 * (Inputs!$B$37 / 12) * (1 + Inputs!$B$44)^INT((COLUMNS($B$72:BA72)-1) / 12) -> 0
A73: 5. Sales Rep Gehalt | B73: =B35 * (Inputs!$B$39 / 12) * (1 + Inputs!$B$44)^INT((COLUMNS($B$73:B73)-1) / 12) -> 0 | C73: =C35 * (Inputs!$B$39 / 12) * (1 + Inputs!$B$44)^INT((COLUMNS($B$73:C73)-1) / 12) -> 0 | D73: =D35 * (Inputs!$B$39 / 12) * (1 + Inputs!$B$44)^INT((COLUMNS($B$73:D73)-1) / 12) -> 0 | E73: =E35 * (Inputs!$B$39 / 12) * (1 + Inputs!$B$44)^INT((COLUMNS($B$73:E73)-1) / 12) -> 0 | F73: =F35 * (Inputs!$B$39 / 12) * (1 + Inputs!$B$44)^INT((COLUMNS($B$73:F73)-1) / 12) -> 0 | G73: =G35 * (Inputs!$B$39 / 12) * (1 + Inputs!$B$44)^INT((COLUMNS($B$73:G73)-1) / 12) -> 0 | H73: =H35 * (Inputs!$B$39 / 12) * (1 + Inputs!$B$44)^INT((COLUMNS($B$73:H73)-1) / 12) -> 0 | I73: =I35 * (Inputs!$B$39 / 12) * (1 + Inputs!$B$44)^INT((COLUMNS($B$73:I73)-1) / 12) -> 0 | ... BA73: =BA35 * (Inputs!$B$39 / 12) * (1 + Inputs!$B$44)^INT((COLUMNS($B$73:BA73)-1) / 12) -> 0
A74: 4. Customer Success Gehalt | B74: =B36 * (Inputs!$B$41 / 12) * (1 + Inputs!$B$44)^INT((COLUMNS($B$74:B74)-1) / 12) -> 0 | C74: =C36 * (Inputs!$B$41 / 12) * (1 + Inputs!$B$44)^INT((COLUMNS($B$74:C74)-1) / 12) -> 0 | D74: =D36 * (Inputs!$B$41 / 12) * (1 + Inputs!$B$44)^INT((COLUMNS($B$74:D74)-1) / 12) -> 0 | E74: =E36 * (Inputs!$B$41 / 12) * (1 + Inputs!$B$44)^INT((COLUMNS($B$74:E74)-1) / 12) -> 0 | F74: =F36 * (Inputs!$B$41 / 12) * (1 + Inputs!$B$44)^INT((COLUMNS($B$74:F74)-1) / 12) -> 0 | G74: =G36 * (Inputs!$B$41 / 12) * (1 + Inputs!$B$44)^INT((COLUMNS($B$74:G74)-1) / 12) -> 0 | H74: =H36 * (Inputs!$B$41 / 12) * (1 + Inputs!$B$44)^INT((COLUMNS($B$74:H74)-1) / 12) -> 0 | I74: =I36 * (Inputs!$B$41 / 12) * (1 + Inputs!$B$44)^INT((COLUMNS($B$74:I74)-1) / 12) -> 0 | ... BA74: =BA36 * (Inputs!$B$41 / 12) * (1 + Inputs!$B$44)^INT((COLUMNS($B$74:BA74)-1) / 12) -> 0
A75: 3. Marketing Manager Gehalt | B75: =B37 * (Inputs!$B$40 / 12) * (1 + Inputs!$B$44)^INT((COLUMNS($B$75:B75)-1) / 12) -> 0 | C75: =C37 * (Inputs!$B$40 / 12) * (1 + Inputs!$B$44)^INT((COLUMNS($B$75:C75)-1) / 12) -> 0 | D75: =D37 * (Inputs!$B$40 / 12) * (1 + Inputs!$B$44)^INT((COLUMNS($B$75:D75)-1) / 12) -> 0 | E75: =E37 * (Inputs!$B$40 / 12) * (1 + Inputs!$B$44)^INT((COLUMNS($B$75:E75)-1) / 12) -> 0 | F75: =F37 * (Inputs!$B$40 / 12) * (1 + Inputs!$B$44)^INT((COLUMNS($B$75:F75)-1) / 12) -> 0 | G75: =G37 * (Inputs!$B$40 / 12) * (1 + Inputs!$B$44)^INT((COLUMNS($B$75:G75)-1) / 12) -> 0 | H75: =H37 * (Inputs!$B$40 / 12) * (1 + Inputs!$B$44)^INT((COLUMNS($B$75:H75)-1) / 12) -> 0 | I75: =I37 * (Inputs!$B$40 / 12) * (1 + Inputs!$B$44)^INT((COLUMNS($B$75:I75)-1) / 12) -> 0 | ... BA75: =BA37 * (Inputs!$B$40 / 12) * (1 + Inputs!$B$44)^INT((COLUMNS($B$75:BA75)-1) / 12) -> 0
A76: Subtotal Brutto-Gehälter | B76: =SUM(B41:B75) -> 18000 | C76: =SUM(C41:C75) -> 18000 | D76: =SUM(D41:D75) -> 18000 | E76: =SUM(E41:E75) -> 18000 | F76: =SUM(F41:F75) -> 18000 | G76: =SUM(G41:G75) -> 18000 | H76: =SUM(H41:H75) -> 25500 | I76: =SUM(I41:I75) -> 34666.667 | ... BA76: =SUM(BA41:BA75) -> 176349.7
A77: Lohnnebenkosten (AG-Anteil) | B77: =B76*Inputs!$B$45 -> 3780 | C77: =C76*Inputs!$B$45 -> 3780 | D77: =D76*Inputs!$B$45 -> 3780 | E77: =E76*Inputs!$B$45 -> 3780 | F77: =F76*Inputs!$B$45 -> 3780 | G77: =G76*Inputs!$B$45 -> 3780 | H77: =H76*Inputs!$B$45 -> 5355 | I77: =I76*Inputs!$B$45 -> 7280 | ... BA77: =BA76*Inputs!$B$45 -> 37033.437
A78: TOTAL PERSONALKOSTEN | B78: =B76+B77 -> 21780 | C78: =C76+C77 -> 21780 | D78: =D76+D77 -> 21780 | E78: =E76+E77 -> 21780 | F78: =F76+F77 -> 21780 | G78: =G76+G77 -> 21780 | H78: =H76+H77 -> 30855 | I78: =I76+I77 -> 41946.667 | ... BA78: =BA76+BA77 -> 213383.14
A80: TECHNOLOGIEKOSTEN
A81: Cloud Infrastructure (Basis) | B81: =Inputs!$B$82 -> 1200 | C81: =Inputs!$B$82 -> 1200 | D81: =Inputs!$B$82 -> 1200 | E81: =Inputs!$B$82 -> 1200 | F81: =Inputs!$B$82 -> 1200 | G81: =Inputs!$B$82 -> 1200 | H81: =Inputs!$B$82 -> 1200 | I81: =Inputs!$B$82 -> 1200 | ... BA81: =Inputs!$B$82 -> 1200
A82: Cloud Infrastructure (Variable) | B82: =Revenue!B8*Inputs!$B$83 -> 0 | C82: =Revenue!C8*Inputs!$B$83 -> 0 | D82: =Revenue!D8*Inputs!$B$83 -> 0 | E82: =Revenue!E8*Inputs!$B$83 -> 0 | F82: =Revenue!F8*Inputs!$B$83 -> 0 | G82: =Revenue!G8*Inputs!$B$83 -> 0 | H82: =Revenue!H8*Inputs!$B$83 -> 0 | I82: =Revenue!I8*Inputs!$B$83 -> 0 | ... BA82: =Revenue!BA8*Inputs!$B$83 -> 250
A83: AI/ML API Kosten | B83: =Inputs!$B$84*(1+Inputs!$B$85)^(1-1) -> 1000 | C83: =Inputs!$B$84*(1+Inputs!$B$85)^(2-1) -> 1050 | D83: =Inputs!$B$84*(1+Inputs!$B$85)^(3-1) -> 1102.5 | E83: =Inputs!$B$84*(1+Inputs!$B$85)^(4-1) -> 1157.625 | F83: =Inputs!$B$84*(1+Inputs!$B$85)^(5-1) -> 1215.5062 | G83: =Inputs!$B$84*(1+Inputs!$B$85)^(6-1) -> 1276.2816 | H83: =Inputs!$B$84*(1+Inputs!$B$85)^(7-1) -> 1340.0956 | I83: =Inputs!$B$84*(1+Inputs!$B$85)^(8-1) -> 1407.1004 | J83: =Inputs!$B$84*(1+Inputs!$B$85)^(9-1) -> 1477.4554 | K83: =Inputs!$B$84*(1+Inputs!$B$85)^(10-1) -> 1551.3282 | L83: =Inputs!$B$84*(1+Inputs!$B$85)^(11-1) -> 1628.8946 | M83: =Inputs!$B$84*(1+Inputs!$B$85)^(12-1) -> 1710.3394 | N83: =Inputs!$B$84*(1+Inputs!$B$85)^(13-1) -> 1795.8563 | O83: =Inputs!$B$84*(1+Inputs!$B$85)^(14-1) -> 1885.6491 | P83: =Inputs!$B$84*(1+Inputs!$B$85)^(15-1) -> 1979.9316 | Q83: =Inputs!$B$84*(1+Inputs!$B$85)^(16-1) -> 2078.9282 | R83: =Inputs!$B$84*(1+Inputs!$B$85)^(17-1) -> 2182.8746 | S83: =Inputs!$B$84*(1+Inputs!$B$85)^(18-1) -> 2292.0183 | T83: =Inputs!$B$84*(1+Inputs!$B$85)^(19-1) -> 2406.6192 | U83: =Inputs!$B$84*(1+Inputs!$B$85)^(20-1) -> 2526.9502 | V83: =Inputs!$B$84*(1+Inputs!$B$85)^(21-1) -> 2653.2977 | W83: =Inputs!$B$84*(1+Inputs!$B$85)^(22-1) -> 2785.9626 | X83: =Inputs!$B$84*(1+Inputs!$B$85)^(23-1) -> 2925.2607 | Y83: =Inputs!$B$84*(1+Inputs!$B$85)^(24-1) -> 3071.5238 | Z83: =Inputs!$B$84*(1+Inputs!$B$85)^(25-1) -> 3225.0999 | AA83: =Inputs!$B$84*(1+Inputs!$B$85)^(26-1) -> 3386.3549 | AB83: =Inputs!$B$84*(1+Inputs!$B$85)^(27-1) -> 3555.6727 | AC83: =Inputs!$B$84*(1+Inputs!$B$85)^(28-1) -> 3733.4563 | AD83: =Inputs!$B$84*(1+Inputs!$B$85)^(29-1) -> 3920.1291 | AE83: =Inputs!$B$84*(1+Inputs!$B$85)^(30-1) -> 4116.1356 | AF83: =Inputs!$B$84*(1+Inputs!$B$85)^(31-1) -> 4321.9424 | AG83: =Inputs!$B$84*(1+Inputs!$B$85)^(32-1) -> 4538.0395 | AH83: =Inputs!$B$84*(1+Inputs!$B$85)^(33-1) -> 4764.9415 | AI83: =Inputs!$B$84*(1+Inputs!$B$85)^(34-1) -> 5003.1885 | AJ83: =Inputs!$B$84*(1+Inputs!$B$85)^(35-1) -> 5253.348 | AK83: =Inputs!$B$84*(1+Inputs!$B$85)^(36-1) -> 5516.0154 | AL83: =Inputs!$B$84*(1+Inputs!$B$85)^(37-1) -> 5791.8161 | AM83: =Inputs!$B$84*(1+Inputs!$B$85)^(38-1) -> 6081.4069 | AN83: =Inputs!$B$84*(1+Inputs!$B$85)^(39-1) -> 6385.4773 | AO83: =Inputs!$B$84*(1+Inputs!$B$85)^(40-1) -> 6704.7512 | AP83: =Inputs!$B$84*(1+Inputs!$B$85)^(41-1) -> 7039.9887 | AQ83: =Inputs!$B$84*(1+Inputs!$B$85)^(42-1) -> 7391.9881 | AR83: =Inputs!$B$84*(1+Inputs!$B$85)^(43-1) -> 7761.5876 | AS83: =Inputs!$B$84*(1+Inputs!$B$85)^(44-1) -> 8149.6669 | AT83: =Inputs!$B$84*(1+Inputs!$B$85)^(45-1) -> 8557.1503 | AU83: =Inputs!$B$84*(1+Inputs!$B$85)^(46-1) -> 8985.0078 | AV83: =Inputs!$B$84*(1+Inputs!$B$85)^(47-1) -> 9434.2582 | AW83: =Inputs!$B$84*(1+Inputs!$B$85)^(48-1) -> 9905.9711 | AX83: =Inputs!$B$84*(1+Inputs!$B$85)^(49-1) -> 10401.27 | AY83: =Inputs!$B$84*(1+Inputs!$B$85)^(50-1) -> 10921.333 | AZ83: =Inputs!$B$84*(1+Inputs!$B$85)^(51-1) -> 11467.4 | BA83: =Inputs!$B$84*(1+Inputs!$B$85)^(52-1) -> 12040.77
A84: SaaS Tools intern | B84: =Inputs!$B$86+B38*Inputs!$B$87 -> 700 | C84: =Inputs!$B$86+C38*Inputs!$B$87 -> 700 | D84: =Inputs!$B$86+D38*Inputs!$B$87 -> 700 | E84: =Inputs!$B$86+E38*Inputs!$B$87 -> 700 | F84: =Inputs!$B$86+F38*Inputs!$B$87 -> 700 | G84: =Inputs!$B$86+G38*Inputs!$B$87 -> 700 | H84: =Inputs!$B$86+H38*Inputs!$B$87 -> 800 | I84: =Inputs!$B$86+I38*Inputs!$B$87 -> 900 | ... BA84: =Inputs!$B$86+BA38*Inputs!$B$87 -> 2500
A85: Software-Lizenzen Dev | B85: =Inputs!$B$88/12 -> 416.66667 | C85: =Inputs!$B$88/12 -> 416.66667 | D85: =Inputs!$B$88/12 -> 416.66667 | E85: =Inputs!$B$88/12 -> 416.66667 | F85: =Inputs!$B$88/12 -> 416.66667 | G85: =Inputs!$B$88/12 -> 416.66667 | H85: =Inputs!$B$88/12 -> 416.66667 | I85: =Inputs!$B$88/12 -> 416.66667 | ... BA85: =Inputs!$B$88/12 -> 416.66667
A86: Sicherheit & Compliance | B86: =Inputs!$B$89 -> 3500 | C86: =Inputs!$B$89 -> 3500 | D86: =Inputs!$B$89 -> 3500 | E86: =Inputs!$B$89 -> 3500 | F86: =Inputs!$B$89 -> 3500 | G86: =Inputs!$B$89 -> 3500 | H86: =Inputs!$B$89 -> 3500 | I86: =Inputs!$B$89 -> 3500 | ... BA86: =Inputs!$B$89 -> 3500
A87: TOTAL TECHNOLOGIE | B87: =SUM(B81:B86) -> 6816.6667 | C87: =SUM(C81:C86) -> 6866.6667 | D87: =SUM(D81:D86) -> 6919.1667 | E87: =SUM(E81:E86) -> 6974.2917 | F87: =SUM(F81:F86) -> 7032.1729 | G87: =SUM(G81:G86) -> 7092.9482 | H87: =SUM(H81:H86) -> 7256.7623 | I87: =SUM(I81:I86) -> 7423.7671 | ... BA87: =SUM(BA81:BA86) -> 19907.436
A89: BÜROKOSTEN
A90: Büromiete | B90: =IF(1>=Inputs!$B$99,Inputs!$B$100,Inputs!$B$98) -> 1500 | C90: =IF(2>=Inputs!$B$99,Inputs!$B$100,Inputs!$B$98) -> 1500 | D90: =IF(3>=Inputs!$B$99,Inputs!$B$100,Inputs!$B$98) -> 1500 | E90: =IF(4>=Inputs!$B$99,Inputs!$B$100,Inputs!$B$98) -> 1500 | F90: =IF(5>=Inputs!$B$99,Inputs!$B$100,Inputs!$B$98) -> 1500 | G90: =IF(6>=Inputs!$B$99,Inputs!$B$100,Inputs!$B$98) -> 1500 | H90: =IF(7>=Inputs!$B$99,Inputs!$B$100,Inputs!$B$98) -> 1500 | I90: =IF(8>=Inputs!$B$99,Inputs!$B$100,Inputs!$B$98) -> 1500 | J90: =IF(9>=Inputs!$B$99,Inputs!$B$100,Inputs!$B$98) -> 1500 | K90: =IF(10>=Inputs!$B$99,Inputs!$B$100,Inputs!$B$98) -> 1500 | L90: =IF(11>=Inputs!$B$99,Inputs!$B$100,Inputs!$B$98) -> 1500 | M90: =IF(12>=Inputs!$B$99,Inputs!$B$100,Inputs!$B$98) -> 1500 | N90: =IF(13>=Inputs!$B$99,Inputs!$B$100,Inputs!$B$98) -> 1500 | O90: =IF(14>=Inputs!$B$99,Inputs!$B$100,Inputs!$B$98) -> 1500 | P90: =IF(15>=Inputs!$B$99,Inputs!$B$100,Inputs!$B$98) -> 1500 | Q90: =IF(16>=Inputs!$B$99,Inputs!$B$100,Inputs!$B$98) -> 1500 | R90: =IF(17>=Inputs!$B$99,Inputs!$B$100,Inputs!$B$98) -> 1500 | S90: =IF(18>=Inputs!$B$99,Inputs!$B$100,Inputs!$B$98) -> 4500 | T90: =IF(19>=Inputs!$B$99,Inputs!$B$100,Inputs!$B$98) -> 4500 | U90: =IF(20>=Inputs!$B$99,Inputs!$B$100,Inputs!$B$98) -> 4500 | V90: =IF(21>=Inputs!$B$99,Inputs!$B$100,Inputs!$B$98) -> 4500 | W90: =IF(22>=Inputs!$B$99,Inputs!$B$100,Inputs!$B$98) -> 4500 | X90: =IF(23>=Inputs!$B$99,Inputs!$B$100,Inputs!$B$98) -> 4500 | Y90: =IF(24>=Inputs!$B$99,Inputs!$B$100,Inputs!$B$98) -> 4500 | Z90: =IF(25>=Inputs!$B$99,Inputs!$B$100,Inputs!$B$98) -> 4500 | AA90: =IF(26>=Inputs!$B$99,Inputs!$B$100,Inputs!$B$98) -> 4500 | AB90: =IF(27>=Inputs!$B$99,Inputs!$B$100,Inputs!$B$98) -> 4500 | AC90: =IF(28>=Inputs!$B$99,Inputs!$B$100,Inputs!$B$98) -> 4500 | AD90: =IF(29>=Inputs!$B$99,Inputs!$B$100,Inputs!$B$98) -> 4500 | AE90: =IF(30>=Inputs!$B$99,Inputs!$B$100,Inputs!$B$98) -> 4500 | AF90: =IF(31>=Inputs!$B$99,Inputs!$B$100,Inputs!$B$98) -> 4500 | AG90: =IF(32>=Inputs!$B$99,Inputs!$B$100,Inputs!$B$98) -> 4500 | AH90: =IF(33>=Inputs!$B$99,Inputs!$B$100,Inputs!$B$98) -> 4500 | AI90: =IF(34>=Inputs!$B$99,Inputs!$B$100,Inputs!$B$98) -> 4500 | AJ90: =IF(35>=Inputs!$B$99,Inputs!$B$100,Inputs!$B$98) -> 4500 | AK90: =IF(36>=Inputs!$B$99,Inputs!$B$100,Inputs!$B$98) -> 4500 | AL90: =IF(37>=Inputs!$B$99,Inputs!$B$100,Inputs!$B$98) -> 4500 | AM90: =IF(38>=Inputs!$B$99,Inputs!$B$100,Inputs!$B$98) -> 4500 | AN90: =IF(39>=Inputs!$B$99,Inputs!$B$100,Inputs!$B$98) -> 4500 | AO90: =IF(40>=Inputs!$B$99,Inputs!$B$100,Inputs!$B$98) -> 4500 | AP90: =IF(41>=Inputs!$B$99,Inputs!$B$100,Inputs!$B$98) -> 4500 | AQ90: =IF(42>=Inputs!$B$99,Inputs!$B$100,Inputs!$B$98) -> 4500 | AR90: =IF(43>=Inputs!$B$99,Inputs!$B$100,Inputs!$B$98) -> 4500 | AS90: =IF(44>=Inputs!$B$99,Inputs!$B$100,Inputs!$B$98) -> 4500 | AT90: =IF(45>=Inputs!$B$99,Inputs!$B$100,Inputs!$B$98) -> 4500 | AU90: =IF(46>=Inputs!$B$99,Inputs!$B$100,Inputs!$B$98) -> 4500 | AV90: =IF(47>=Inputs!$B$99,Inputs!$B$100,Inputs!$B$98) -> 4500 | AW90: =IF(48>=Inputs!$B$99,Inputs!$B$100,Inputs!$B$98) -> 4500 | AX90: =IF(49>=Inputs!$B$99,Inputs!$B$100,Inputs!$B$98) -> 4500 | AY90: =IF(50>=Inputs!$B$99,Inputs!$B$100,Inputs!$B$98) -> 4500 | AZ90: =IF(51>=Inputs!$B$99,Inputs!$B$100,Inputs!$B$98) -> 4500 | BA90: =IF(52>=Inputs!$B$99,Inputs!$B$100,Inputs!$B$98) -> 4500
A91: Nebenkosten | B91: =Inputs!$B$101 -> 300 | C91: =Inputs!$B$101 -> 300 | D91: =Inputs!$B$101 -> 300 | E91: =Inputs!$B$101 -> 300 | F91: =Inputs!$B$101 -> 300 | G91: =Inputs!$B$101 -> 300 | H91: =Inputs!$B$101 -> 300 | I91: =Inputs!$B$101 -> 300 | ... BA91: =Inputs!$B$101 -> 300
A92: Internet & Telefon | B92: =Inputs!$B$102 -> 150 | C92: =Inputs!$B$102 -> 150 | D92: =Inputs!$B$102 -> 150 | E92: =Inputs!$B$102 -> 150 | F92: =Inputs!$B$102 -> 150 | G92: =Inputs!$B$102 -> 150 | H92: =Inputs!$B$102 -> 150 | I92: =Inputs!$B$102 -> 150 | ... BA92: =Inputs!$B$102 -> 150
A93: Bürobedarf | B93: =B38*Inputs!$B$104 -> 90 | C93: =C38*Inputs!$B$104 -> 90 | D93: =D38*Inputs!$B$104 -> 90 | E93: =E38*Inputs!$B$104 -> 90 | F93: =F38*Inputs!$B$104 -> 90 | G93: =G38*Inputs!$B$104 -> 90 | H93: =H38*Inputs!$B$104 -> 120 | I93: =I38*Inputs!$B$104 -> 150 | ... BA93: =BA38*Inputs!$B$104 -> 630
A94: TOTAL BÜRO | B94: =SUM(B90:B93) -> 2040 | C94: =SUM(C90:C93) -> 2040 | D94: =SUM(D90:D93) -> 2040 | E94: =SUM(E90:E93) -> 2040 | F94: =SUM(F90:F93) -> 2040 | G94: =SUM(G90:G93) -> 2040 | H94: =SUM(H90:H93) -> 2070 | I94: =SUM(I90:I93) -> 2100 | ... BA94: =SUM(BA90:BA93) -> 5580
A96: PROFESSIONAL SERVICES
A97: Rechtsanwalt (laufend) | B97: =Inputs!$B$107/12+IF(OR(1=Inputs!$B$11,1=Inputs!$B$13,1=Inputs!$B$15,1=Inputs!$B$17),Inputs!$B$108,0) -> 15666.667 | C97: =Inputs!$B$107/12+IF(OR(2=Inputs!$B$11,2=Inputs!$B$13,2=Inputs!$B$15,2=Inputs!$B$17),Inputs!$B$108,0) -> 666.66667 | D97: =Inputs!$B$107/12+IF(OR(3=Inputs!$B$11,3=Inputs!$B$13,3=Inputs!$B$15,3=Inputs!$B$17),Inputs!$B$108,0) -> 666.66667 | E97: =Inputs!$B$107/12+IF(OR(4=Inputs!$B$11,4=Inputs!$B$13,4=Inputs!$B$15,4=Inputs!$B$17),Inputs!$B$108,0) -> 666.66667 | F97: =Inputs!$B$107/12+IF(OR(5=Inputs!$B$11,5=Inputs!$B$13,5=Inputs!$B$15,5=Inputs!$B$17),Inputs!$B$108,0) -> 15666.667 | G97: =Inputs!$B$107/12+IF(OR(6=Inputs!$B$11,6=Inputs!$B$13,6=Inputs!$B$15,6=Inputs!$B$17),Inputs!$B$108,0) -> 666.66667 | H97: =Inputs!$B$107/12+IF(OR(7=Inputs!$B$11,7=Inputs!$B$13,7=Inputs!$B$15,7=Inputs!$B$17),Inputs!$B$108,0) -> 666.66667 | I97: =Inputs!$B$107/12+IF(OR(8=Inputs!$B$11,8=Inputs!$B$13,8=Inputs!$B$15,8=Inputs!$B$17),Inputs!$B$108,0) -> 666.66667 | J97: =Inputs!$B$107/12+IF(OR(9=Inputs!$B$11,9=Inputs!$B$13,9=Inputs!$B$15,9=Inputs!$B$17),Inputs!$B$108,0) -> 666.66667 | K97: =Inputs!$B$107/12+IF(OR(10=Inputs!$B$11,10=Inputs!$B$13,10=Inputs!$B$15,10=Inputs!$B$17),Inputs!$B$108,0) -> 666.66667 | L97: =Inputs!$B$107/12+IF(OR(11=Inputs!$B$11,11=Inputs!$B$13,11=Inputs!$B$15,11=Inputs!$B$17),Inputs!$B$108,0) -> 666.66667 | M97: =Inputs!$B$107/12+IF(OR(12=Inputs!$B$11,12=Inputs!$B$13,12=Inputs!$B$15,12=Inputs!$B$17),Inputs!$B$108,0) -> 666.66667 | N97: =Inputs!$B$107/12+IF(OR(13=Inputs!$B$11,13=Inputs!$B$13,13=Inputs!$B$15,13=Inputs!$B$17),Inputs!$B$108,0) -> 666.66667 | O97: =Inputs!$B$107/12+IF(OR(14=Inputs!$B$11,14=Inputs!$B$13,14=Inputs!$B$15,14=Inputs!$B$17),Inputs!$B$108,0) -> 666.66667 | P97: =Inputs!$B$107/12+IF(OR(15=Inputs!$B$11,15=Inputs!$B$13,15=Inputs!$B$15,15=Inputs!$B$17),Inputs!$B$108,0) -> 666.66667 | Q97: =Inputs!$B$107/12+IF(OR(16=Inputs!$B$11,16=Inputs!$B$13,16=Inputs!$B$15,16=Inputs!$B$17),Inputs!$B$108,0) -> 666.66667 | R97: =Inputs!$B$107/12+IF(OR(17=Inputs!$B$11,17=Inputs!$B$13,17=Inputs!$B$15,17=Inputs!$B$17),Inputs!$B$108,0) -> 15666.667 | S97: =Inputs!$B$107/12+IF(OR(18=Inputs!$B$11,18=Inputs!$B$13,18=Inputs!$B$15,18=Inputs!$B$17),Inputs!$B$108,0) -> 666.66667 | T97: =Inputs!$B$107/12+IF(OR(19=Inputs!$B$11,19=Inputs!$B$13,19=Inputs!$B$15,19=Inputs!$B$17),Inputs!$B$108,0) -> 666.66667 | U97: =Inputs!$B$107/12+IF(OR(20=Inputs!$B$11,20=Inputs!$B$13,20=Inputs!$B$15,20=Inputs!$B$17),Inputs!$B$108,0) -> 666.66667 | V97: =Inputs!$B$107/12+IF(OR(21=Inputs!$B$11,21=Inputs!$B$13,21=Inputs!$B$15,21=Inputs!$B$17),Inputs!$B$108,0) -> 666.66667 | W97: =Inputs!$B$107/12+IF(OR(22=Inputs!$B$11,22=Inputs!$B$13,22=Inputs!$B$15,22=Inputs!$B$17),Inputs!$B$108,0) -> 666.66667 | X97: =Inputs!$B$107/12+IF(OR(23=Inputs!$B$11,23=Inputs!$B$13,23=Inputs!$B$15,23=Inputs!$B$17),Inputs!$B$108,0) -> 666.66667 | Y97: =Inputs!$B$107/12+IF(OR(24=Inputs!$B$11,24=Inputs!$B$13,24=Inputs!$B$15,24=Inputs!$B$17),Inputs!$B$108,0) -> 666.66667 | Z97: =Inputs!$B$107/12+IF(OR(25=Inputs!$B$11,25=Inputs!$B$13,25=Inputs!$B$15,25=Inputs!$B$17),Inputs!$B$108,0) -> 666.66667 | AA97: =Inputs!$B$107/12+IF(OR(26=Inputs!$B$11,26=Inputs!$B$13,26=Inputs!$B$15,26=Inputs!$B$17),Inputs!$B$108,0) -> 666.66667 | AB97: =Inputs!$B$107/12+IF(OR(27=Inputs!$B$11,27=Inputs!$B$13,27=Inputs!$B$15,27=Inputs!$B$17),Inputs!$B$108,0) -> 666.66667 | AC97: =Inputs!$B$107/12+IF(OR(28=Inputs!$B$11,28=Inputs!$B$13,28=Inputs!$B$15,28=Inputs!$B$17),Inputs!$B$108,0) -> 666.66667 | AD97: =Inputs!$B$107/12+IF(OR(29=Inputs!$B$11,29=Inputs!$B$13,29=Inputs!$B$15,29=Inputs!$B$17),Inputs!$B$108,0) -> 666.66667 | AE97: =Inputs!$B$107/12+IF(OR(30=Inputs!$B$11,30=Inputs!$B$13,30=Inputs!$B$15,30=Inputs!$B$17),Inputs!$B$108,0) -> 666.66667 | AF97: =Inputs!$B$107/12+IF(OR(31=Inputs!$B$11,31=Inputs!$B$13,31=Inputs!$B$15,31=Inputs!$B$17),Inputs!$B$108,0) -> 666.66667 | AG97: =Inputs!$B$107/12+IF(OR(32=Inputs!$B$11,32=Inputs!$B$13,32=Inputs!$B$15,32=Inputs!$B$17),Inputs!$B$108,0) -> 666.66667 | AH97: =Inputs!$B$107/12+IF(OR(33=Inputs!$B$11,33=Inputs!$B$13,33=Inputs!$B$15,33=Inputs!$B$17),Inputs!$B$108,0) -> 666.66667 | AI97: =Inputs!$B$107/12+IF(OR(34=Inputs!$B$11,34=Inputs!$B$13,34=Inputs!$B$15,34=Inputs!$B$17),Inputs!$B$108,0) -> 666.66667 | AJ97: =Inputs!$B$107/12+IF(OR(35=Inputs!$B$11,35=Inputs!$B$13,35=Inputs!$B$15,35=Inputs!$B$17),Inputs!$B$108,0) -> 15666.667 | AK97: =Inputs!$B$107/12+IF(OR(36=Inputs!$B$11,36=Inputs!$B$13,36=Inputs!$B$15,36=Inputs!$B$17),Inputs!$B$108,0) -> 666.66667 | AL97: =Inputs!$B$107/12+IF(OR(37=Inputs!$B$11,37=Inputs!$B$13,37=Inputs!$B$15,37=Inputs!$B$17),Inputs!$B$108,0) -> 666.66667 | AM97: =Inputs!$B$107/12+IF(OR(38=Inputs!$B$11,38=Inputs!$B$13,38=Inputs!$B$15,38=Inputs!$B$17),Inputs!$B$108,0) -> 666.66667 | AN97: =Inputs!$B$107/12+IF(OR(39=Inputs!$B$11,39=Inputs!$B$13,39=Inputs!$B$15,39=Inputs!$B$17),Inputs!$B$108,0) -> 666.66667 | AO97: =Inputs!$B$107/12+IF(OR(40=Inputs!$B$11,40=Inputs!$B$13,40=Inputs!$B$15,40=Inputs!$B$17),Inputs!$B$108,0) -> 666.66667 | AP97: =Inputs!$B$107/12+IF(OR(41=Inputs!$B$11,41=Inputs!$B$13,41=Inputs!$B$15,41=Inputs!$B$17),Inputs!$B$108,0) -> 666.66667 | AQ97: =Inputs!$B$107/12+IF(OR(42=Inputs!$B$11,42=Inputs!$B$13,42=Inputs!$B$15,42=Inputs!$B$17),Inputs!$B$108,0) -> 666.66667 | AR97: =Inputs!$B$107/12+IF(OR(43=Inputs!$B$11,43=Inputs!$B$13,43=Inputs!$B$15,43=Inputs!$B$17),Inputs!$B$108,0) -> 666.66667 | AS97: =Inputs!$B$107/12+IF(OR(44=Inputs!$B$11,44=Inputs!$B$13,44=Inputs!$B$15,44=Inputs!$B$17),Inputs!$B$108,0) -> 666.66667 | AT97: =Inputs!$B$107/12+IF(OR(45=Inputs!$B$11,45=Inputs!$B$13,45=Inputs!$B$15,45=Inputs!$B$17),Inputs!$B$108,0) -> 666.66667 | AU97: =Inputs!$B$107/12+IF(OR(46=Inputs!$B$11,46=Inputs!$B$13,46=Inputs!$B$15,46=Inputs!$B$17),Inputs!$B$108,0) -> 666.66667 | AV97: =Inputs!$B$107/12+IF(OR(47=Inputs!$B$11,47=Inputs!$B$13,47=Inputs!$B$15,47=Inputs!$B$17),Inputs!$B$108,0) -> 666.66667 | AW97: =Inputs!$B$107/12+IF(OR(48=Inputs!$B$11,48=Inputs!$B$13,48=Inputs!$B$15,48=Inputs!$B$17),Inputs!$B$108,0) -> 666.66667 | AX97: =Inputs!$B$107/12+IF(OR(49=Inputs!$B$11,49=Inputs!$B$13,49=Inputs!$B$15,49=Inputs!$B$17),Inputs!$B$108,0) -> 666.66667 | AY97: =Inputs!$B$107/12+IF(OR(50=Inputs!$B$11,50=Inputs!$B$13,50=Inputs!$B$15,50=Inputs!$B$17),Inputs!$B$108,0) -> 666.66667 | AZ97: =Inputs!$B$107/12+IF(OR(51=Inputs!$B$11,51=Inputs!$B$13,51=Inputs!$B$15,51=Inputs!$B$17),Inputs!$B$108,0) -> 666.66667 | BA97: =Inputs!$B$107/12+IF(OR(52=Inputs!$B$11,52=Inputs!$B$13,52=Inputs!$B$15,52=Inputs!$B$17),Inputs!$B$108,0) -> 666.66667
A98: Steuerberater | B98: =Inputs!$B$109 -> 800 | C98: =Inputs!$B$109 -> 800 | D98: =Inputs!$B$109 -> 800 | E98: =Inputs!$B$109 -> 800 | F98: =Inputs!$B$109 -> 800 | G98: =Inputs!$B$109 -> 800 | H98: =Inputs!$B$109 -> 800 | I98: =Inputs!$B$109 -> 800 | ... BA98: =Inputs!$B$109 -> 800
A99: Wirtschaftsprüfer | B99: =IF(1>=Inputs!$B$111,Inputs!$B$110/12,0) -> 0 | C99: =IF(2>=Inputs!$B$111,Inputs!$B$110/12,0) -> 0 | D99: =IF(3>=Inputs!$B$111,Inputs!$B$110/12,0) -> 0 | E99: =IF(4>=Inputs!$B$111,Inputs!$B$110/12,0) -> 0 | F99: =IF(5>=Inputs!$B$111,Inputs!$B$110/12,0) -> 0 | G99: =IF(6>=Inputs!$B$111,Inputs!$B$110/12,0) -> 0 | H99: =IF(7>=Inputs!$B$111,Inputs!$B$110/12,0) -> 0 | I99: =IF(8>=Inputs!$B$111,Inputs!$B$110/12,0) -> 0 | J99: =IF(9>=Inputs!$B$111,Inputs!$B$110/12,0) -> 0 | K99: =IF(10>=Inputs!$B$111,Inputs!$B$110/12,0) -> 0 | L99: =IF(11>=Inputs!$B$111,Inputs!$B$110/12,0) -> 0 | M99: =IF(12>=Inputs!$B$111,Inputs!$B$110/12,0) -> 0 | N99: =IF(13>=Inputs!$B$111,Inputs!$B$110/12,0) -> 0 | O99: =IF(14>=Inputs!$B$111,Inputs!$B$110/12,0) -> 0 | P99: =IF(15>=Inputs!$B$111,Inputs!$B$110/12,0) -> 0 | Q99: =IF(16>=Inputs!$B$111,Inputs!$B$110/12,0) -> 0 | R99: =IF(17>=Inputs!$B$111,Inputs!$B$110/12,0) -> 1000 | S99: =IF(18>=Inputs!$B$111,Inputs!$B$110/12,0) -> 1000 | T99: =IF(19>=Inputs!$B$111,Inputs!$B$110/12,0) -> 1000 | U99: =IF(20>=Inputs!$B$111,Inputs!$B$110/12,0) -> 1000 | V99: =IF(21>=Inputs!$B$111,Inputs!$B$110/12,0) -> 1000 | W99: =IF(22>=Inputs!$B$111,Inputs!$B$110/12,0) -> 1000 | X99: =IF(23>=Inputs!$B$111,Inputs!$B$110/12,0) -> 1000 | Y99: =IF(24>=Inputs!$B$111,Inputs!$B$110/12,0) -> 1000 | Z99: =IF(25>=Inputs!$B$111,Inputs!$B$110/12,0) -> 1000 | AA99: =IF(26>=Inputs!$B$111,Inputs!$B$110/12,0) -> 1000 | AB99: =IF(27>=Inputs!$B$111,Inputs!$B$110/12,0) -> 1000 | AC99: =IF(28>=Inputs!$B$111,Inputs!$B$110/12,0) -> 1000 | AD99: =IF(29>=Inputs!$B$111,Inputs!$B$110/12,0) -> 1000 | AE99: =IF(30>=Inputs!$B$111,Inputs!$B$110/12,0) -> 1000 | AF99: =IF(31>=Inputs!$B$111,Inputs!$B$110/12,0) -> 1000 | AG99: =IF(32>=Inputs!$B$111,Inputs!$B$110/12,0) -> 1000 | AH99: =IF(33>=Inputs!$B$111,Inputs!$B$110/12,0) -> 1000 | AI99: =IF(34>=Inputs!$B$111,Inputs!$B$110/12,0) -> 1000 | AJ99: =IF(35>=Inputs!$B$111,Inputs!$B$110/12,0) -> 1000 | AK99: =IF(36>=Inputs!$B$111,Inputs!$B$110/12,0) -> 1000 | AL99: =IF(37>=Inputs!$B$111,Inputs!$B$110/12,0) -> 1000 | AM99: =IF(38>=Inputs!$B$111,Inputs!$B$110/12,0) -> 1000 | AN99: =IF(39>=Inputs!$B$111,Inputs!$B$110/12,0) -> 1000 | AO99: =IF(40>=Inputs!$B$111,Inputs!$B$110/12,0) -> 1000 | AP99: =IF(41>=Inputs!$B$111,Inputs!$B$110/12,0) -> 1000 | AQ99: =IF(42>=Inputs!$B$111,Inputs!$B$110/12,0) -> 1000 | AR99: =IF(43>=Inputs!$B$111,Inputs!$B$110/12,0) -> 1000 | AS99: =IF(44>=Inputs!$B$111,Inputs!$B$110/12,0) -> 1000 | AT99: =IF(45>=Inputs!$B$111,Inputs!$B$110/12,0) -> 1000 | AU99: =IF(46>=Inputs!$B$111,Inputs!$B$110/12,0) -> 1000 | AV99: =IF(47>=Inputs!$B$111,Inputs!$B$110/12,0) -> 1000 | AW99: =IF(48>=Inputs!$B$111,Inputs!$B$110/12,0) -> 1000 | AX99: =IF(49>=Inputs!$B$111,Inputs!$B$110/12,0) -> 1000 | AY99: =IF(50>=Inputs!$B$111,Inputs!$B$110/12,0) -> 1000 | AZ99: =IF(51>=Inputs!$B$111,Inputs!$B$110/12,0) -> 1000 | BA99: =IF(52>=Inputs!$B$111,Inputs!$B$110/12,0) -> 1000
A100: Unternehmensberater | B100: =Inputs!$B$112/12 -> 416.66667 | C100: =Inputs!$B$112/12 -> 416.66667 | D100: =Inputs!$B$112/12 -> 416.66667 | E100: =Inputs!$B$112/12 -> 416.66667 | F100: =Inputs!$B$112/12 -> 416.66667 | G100: =Inputs!$B$112/12 -> 416.66667 | H100: =Inputs!$B$112/12 -> 416.66667 | I100: =Inputs!$B$112/12 -> 416.66667 | ... BA100: =Inputs!$B$112/12 -> 416.66667
A101: TOTAL PROFESSIONAL | B101: =SUM(B97:B100) -> 16883.333 | C101: =SUM(C97:C100) -> 1883.3333 | D101: =SUM(D97:D100) -> 1883.3333 | E101: =SUM(E97:E100) -> 1883.3333 | F101: =SUM(F97:F100) -> 16883.333 | G101: =SUM(G97:G100) -> 1883.3333 | H101: =SUM(H97:H100) -> 1883.3333 | I101: =SUM(I97:I100) -> 1883.3333 | ... BA101: =SUM(BA97:BA100) -> 2883.3333
A103: VERSICHERUNGEN & BANK
A104: D&O Versicherung | B104: =Inputs!$B$115/12 -> 250 | C104: =Inputs!$B$115/12 -> 250 | D104: =Inputs!$B$115/12 -> 250 | E104: =Inputs!$B$115/12 -> 250 | F104: =Inputs!$B$115/12 -> 250 | G104: =Inputs!$B$115/12 -> 250 | H104: =Inputs!$B$115/12 -> 250 | I104: =Inputs!$B$115/12 -> 250 | ... BA104: =Inputs!$B$115/12 -> 250
A105: Betriebshaftpflicht | B105: =Inputs!$B$116/12 -> 125 | C105: =Inputs!$B$116/12 -> 125 | D105: =Inputs!$B$116/12 -> 125 | E105: =Inputs!$B$116/12 -> 125 | F105: =Inputs!$B$116/12 -> 125 | G105: =Inputs!$B$116/12 -> 125 | H105: =Inputs!$B$116/12 -> 125 | I105: =Inputs!$B$116/12 -> 125 | ... BA105: =Inputs!$B$116/12 -> 125
...

Sheet Balance Sheet
A1: BILANZ (Vereinfacht)
B2: 46113 | C2: 46143 | D2: 46174 | E2: 46204 | F2: 46235 | G2: 46266 | H2: 46296 | I2: 46327 | J2: 46357 | K2: 46388 | L2: 46419 | M2: 46447 | N2: 46478 | O2: 46508 | P2: 46539 | Q2: 46569 | R2: 46600 | S2: 46631 | T2: 46661 | U2: 46692 | V2: 46722 | W2: 46753 | X2: 46784 | Y2: 46813 | Z2: 46844 | AA2: 46874 | AB2: 46905 | AC2: 46935 | AD2: 46966 | AE2: 46997 | AF2: 47027 | AG2: 47058 | AH2: 47088 | AI2: 47119 | AJ2: 47150 | AK2: 47178 | AL2: 47209 | AM2: 47239 | AN2: 47270 | AO2: 47300 | AP2: 47331 | AQ2: 47362 | AR2: 47392 | AS2: 47423 | AT2: 47453 | AU2: 47484 | AV2: 47515 | AW2: 47543 | AX2: 47574 | AY2: 47604 | AZ2: 47635 | BA2: 47665
A3: Position | B3: M1 | C3: M2 | D3: M3 | E3: M4 | F3: M5 | G3: M6 | H3: M7 | I3: M8 | J3: M9 | K3: M10 | L3: M11 | M3: M12 | N3: M13 | O3: M14 | P3: M15 | Q3: M16 | R3: M17 | S3: M18 | T3: M19 | U3: M20 | V3: M21 | W3: M22 | X3: M23 | Y3: M24 | Z3: M25 | AA3: M26 | AB3: M27 | AC3: M28 | AD3: M29 | AE3: M30 | AF3: M31 | AG3: M32 | AH3: M33 | AI3: M34 | AJ3: M35 | AK3: M36 | AL3: M37 | AM3: M38 | AN3: M39 | AO3: M40 | AP3: M41 | AQ3: M42 | AR3: M43 | AS3: M44 | AT3: M45 | AU3: M46 | AV3: M47 | AW3: M48 | AX3: M49 | AY3: M50 | AZ3: M51 | BA3: M52
A4: AKTIVA (ASSETS)
A5: Cash & Cash Equivalents | B5: ='Cash Flow'!B22 -> 15658.5 | C5: ='Cash Flow'!C22 -> -28802.875 | D5: ='Cash Flow'!D22 -> -70784.544 | E5: ='Cash Flow'!E22 -> -112907.75 | F5: ='Cash Flow'!F22 -> 1330645.4 | G5: ='Cash Flow'!G22 -> 1286642.6 | H5: ='Cash Flow'!H22 -> 1229305.3 | I5: ='Cash Flow'!I22 -> 1159646 | ... BA5: ='Cash Flow'!BA22 -> 15098842
A6: Accounts Receivable | B6: ='P&L'!B7 -> 0 | C6: ='P&L'!C7 -> 0 | D6: ='P&L'!D7 -> 0 | E6: ='P&L'!E7 -> 0 | F6: ='P&L'!F7 -> 0 | G6: ='P&L'!G7 -> 0 | H6: ='P&L'!H7 -> 0 | I6: ='P&L'!I7 -> 0 | ... BA6: ='P&L'!BA7 -> 158496.96
A7: Prepaid Expenses | B7: 0 | C7: 0 | D7: 0 | E7: 0 | F7: 0 | G7: 0 | H7: 0 | I7: 0 | J7: 0 | K7: 0 | L7: 0 | M7: 0 | N7: 0 | O7: 0 | P7: 0 | Q7: 0 | R7: 0 | S7: 0 | T7: 0 | U7: 0 | V7: 0 | W7: 0 | X7: 0 | Y7: 0 | Z7: 0 | AA7: 0 | AB7: 0 | AC7: 0 | AD7: 0 | AE7: 0 | AF7: 0 | AG7: 0 | AH7: 0 | AI7: 0 | AJ7: 0 | AK7: 0 | AL7: 0 | AM7: 0 | AN7: 0 | AO7: 0 | AP7: 0 | AQ7: 0 | AR7: 0 | AS7: 0 | AT7: 0 | AU7: 0 | AV7: 0 | AW7: 0 | AX7: 0 | AY7: 0 | AZ7: 0 | BA7: 0
A8: Property & Equipment (net) | B8: =Costs!B123+Inputs!$B$103 -> 14900 | C8: =B8+Costs!C123-'P&L'!C32 -> 14900 | D8: =C8+Costs!D123-'P&L'!D32 -> 14900 | E8: =D8+Costs!E123-'P&L'!E32 -> 14900 | F8: =E8+Costs!F123-'P&L'!F32 -> 14900 | G8: =F8+Costs!G123-'P&L'!G32 -> 14900 | H8: =G8+Costs!H123-'P&L'!H32 -> 18108.333 | I8: =H8+Costs!I123-'P&L'!I32 -> 21316.667 | J8: =I8+Costs!J123-'P&L'!J32 -> 24525 | ... BA8: =AZ8+Costs!BA123-'P&L'!BA32 -> 72650
A9: TOTAL ASSETS | B9: =SUM(B5:B8) -> 30558.5 | C9: =SUM(C5:C8) -> -13902.875 | D9: =SUM(D5:D8) -> -55884.544 | E9: =SUM(E5:E8) -> -98007.746 | F9: =SUM(F5:F8) -> 1345545.4 | G9: =SUM(G5:G8) -> 1301542.6 | H9: =SUM(H5:H8) -> 1247413.6 | I9: =SUM(I5:I8) -> 1180962.7 | ... BA9: =SUM(BA5:BA8) -> 15329989
A11: PASSIVA (LIABILITIES)
A12: Accounts Payable | B12: =Costs!B132*0.1 -> 6687.1 | C12: =Costs!C132*0.1 -> 4080.475 | D12: =Costs!D132*0.1 -> 4088.7438 | E12: =Costs!E132*0.1 -> 4097.4259 | F12: =Costs!F132*0.1 -> 5681.5422 | G12: =Costs!G132*0.1 -> 4116.1143 | H12: =Costs!H132*0.1 -> 5478.5651 | I12: =Costs!I132*0.1 -> 6706.7683 | ... BA12: =Costs!BA132*0.1 -> 27435.55
A13: Accrued Expenses | B13: =Costs!B78*0.08 -> 1742.4 | C13: =Costs!C78*0.08 -> 1742.4 | D13: =Costs!D78*0.08 -> 1742.4 | E13: =Costs!E78*0.08 -> 1742.4 | F13: =Costs!F78*0.08 -> 1742.4 | G13: =Costs!G78*0.08 -> 1742.4 | H13: =Costs!H78*0.08 -> 2468.4 | I13: =Costs!I78*0.08 -> 3355.7333 | ... BA13: =Costs!BA78*0.08 -> 17070.651
A14: Deferred Revenue | B14: ='P&L'!B5 -> 0 | C14: ='P&L'!C5 -> 0 | D14: ='P&L'!D5 -> 0 | E14: ='P&L'!E5 -> 0 | F14: ='P&L'!F5 -> 0 | G14: ='P&L'!G5 -> 0 | H14: ='P&L'!H5 -> 0 | I14: ='P&L'!I5 -> 0 | ... BA14: ='P&L'!BA5 -> 5441.9558
A15: TOTAL LIABILITIES | B15: =SUM(B12:B14) -> 8429.5 | C15: =SUM(C12:C14) -> 5822.875 | D15: =SUM(D12:D14) -> 5831.1438 | E15: =SUM(E12:E14) -> 5839.8259 | F15: =SUM(F12:F14) -> 7423.9422 | G15: =SUM(G12:G14) -> 5858.5143 | H15: =SUM(H12:H14) -> 7946.9651 | I15: =SUM(I12:I14) -> 10062.502 | ... BA15: =SUM(BA12:BA14) -> 49948.157
A17: EIGENKAPITAL (EQUITY)
A18: Share Capital | B18: 25000 | C18: 25000 | D18: 25000 | E18: 25000 | F18: 25000 | G18: 25000 | H18: 25000 | I18: 25000 | J18: 25000 | K18: 25000 | L18: 25000 | M18: 25000 | N18: 25000 | O18: 25000 | P18: 25000 | Q18: 25000 | R18: 25000 | S18: 25000 | T18: 25000 | U18: 25000 | V18: 25000 | W18: 25000 | X18: 25000 | Y18: 25000 | Z18: 25000 | AA18: 25000 | AB18: 25000 | AC18: 25000 | AD18: 25000 | AE18: 25000 | AF18: 25000 | AG18: 25000 | AH18: 25000 | AI18: 25000 | AJ18: 25000 | AK18: 25000 | AL18: 25000 | AM18: 25000 | AN18: 25000 | AO18: 25000 | AP18: 25000 | AQ18: 25000 | AR18: 25000 | AS18: 25000 | AT18: 25000 | AU18: 25000 | AV18: 25000 | AW18: 25000 | AX18: 25000 | AY18: 25000 | AZ18: 25000 | BA18: 25000
A19: Additional Paid-in Capital | B19: =IF(1=Inputs!$B$11,Inputs!$B$10,0)+IF(1=Inputs!$B$13,Inputs!$B$12,0)+IF(1=Inputs!$B$15,Inputs!$B$14,0)+IF(1=Inputs!$B$17,Inputs!$B$16,0) -> 90000 | C19: =B19+IF(2=Inputs!$B$11,Inputs!$B$10,0)+IF(2=Inputs!$B$13,Inputs!$B$12,0)+IF(2=Inputs!$B$15,Inputs!$B$14,0)+IF(2=Inputs!$B$17,Inputs!$B$16,0) -> 90000 | D19: =C19+IF(3=Inputs!$B$11,Inputs!$B$10,0)+IF(3=Inputs!$B$13,Inputs!$B$12,0)+IF(3=Inputs!$B$15,Inputs!$B$14,0)+IF(3=Inputs!$B$17,Inputs!$B$16,0) -> 90000 | E19: =D19+IF(4=Inputs!$B$11,Inputs!$B$10,0)+IF(4=Inputs!$B$13,Inputs!$B$12,0)+IF(4=Inputs!$B$15,Inputs!$B$14,0)+IF(4=Inputs!$B$17,Inputs!$B$16,0) -> 90000 | F19: =E19+IF(5=Inputs!$B$11,Inputs!$B$10,0)+IF(5=Inputs!$B$13,Inputs!$B$12,0)+IF(5=Inputs!$B$15,Inputs!$B$14,0)+IF(5=Inputs!$B$17,Inputs!$B$16,0) -> 1590000 | G19: =F19+IF(6=Inputs!$B$11,Inputs!$B$10,0)+IF(6=Inputs!$B$13,Inputs!$B$12,0)+IF(6=Inputs!$B$15,Inputs!$B$14,0)+IF(6=Inputs!$B$17,Inputs!$B$16,0) -> 1590000 | H19: =G19+IF(7=Inputs!$B$11,Inputs!$B$10,0)+IF(7=Inputs!$B$13,Inputs!$B$12,0)+IF(7=Inputs!$B$15,Inputs!$B$14,0)+IF(7=Inputs!$B$17,Inputs!$B$16,0) -> 1590000 | I19: =H19+IF(8=Inputs!$B$11,Inputs!$B$10,0)+IF(8=Inputs!$B$13,Inputs!$B$12,0)+IF(8=Inputs!$B$15,Inputs!$B$14,0)+IF(8=Inputs!$B$17,Inputs!$B$16,0) -> 1590000 | J19: =I19+IF(9=Inputs!$B$11,Inputs!$B$10,0)+IF(9=Inputs!$B$13,Inputs!$B$12,0)+IF(9=Inputs!$B$15,Inputs!$B$14,0)+IF(9=Inputs!$B$17,Inputs!$B$16,0) -> 1590000 | K19: =J19+IF(10=Inputs!$B$11,Inputs!$B$10,0)+IF(10=Inputs!$B$13,Inputs!$B$12,0)+IF(10=Inputs!$B$15,Inputs!$B$14,0)+IF(10=Inputs!$B$17,Inputs!$B$16,0) -> 1590000 | L19: =K19+IF(11=Inputs!$B$11,Inputs!$B$10,0)+IF(11=Inputs!$B$13,Inputs!$B$12,0)+IF(11=Inputs!$B$15,Inputs!$B$14,0)+IF(11=Inputs!$B$17,Inputs!$B$16,0) -> 1590000 | M19: =L19+IF(12=Inputs!$B$11,Inputs!$B$10,0)+IF(12=Inputs!$B$13,Inputs!$B$12,0)+IF(12=Inputs!$B$15,Inputs!$B$14,0)+IF(12=Inputs!$B$17,Inputs!$B$16,0) -> 1590000 | N19: =M19+IF(13=Inputs!$B$11,Inputs!$B$10,0)+IF(13=Inputs!$B$13,Inputs!$B$12,0)+IF(13=Inputs!$B$15,Inputs!$B$14,0)+IF(13=Inputs!$B$17,Inputs!$B$16,0) -> 1590000 | O19: =N19+IF(14=Inputs!$B$11,Inputs!$B$10,0)+IF(14=Inputs!$B$13,Inputs!$B$12,0)+IF(14=Inputs!$B$15,Inputs!$B$14,0)+IF(14=Inputs!$B$17,Inputs!$B$16,0) -> 1590000 | P19: =O19+IF(15=Inputs!$B$11,Inputs!$B$10,0)+IF(15=Inputs!$B$13,Inputs!$B$12,0)+IF(15=Inputs!$B$15,Inputs!$B$14,0)+IF(15=Inputs!$B$17,Inputs!$B$16,0) -> 1590000 | Q19: =P19+IF(16=Inputs!$B$11,Inputs!$B$10,0)+IF(16=Inputs!$B$13,Inputs!$B$12,0)+IF(16=Inputs!$B$15,Inputs!$B$14,0)+IF(16=Inputs!$B$17,Inputs!$B$16,0) -> 1590000 | R19: =Q19+IF(17=Inputs!$B$11,Inputs!$B$10,0)+IF(17=Inputs!$B$13,Inputs!$B$12,0)+IF(17=Inputs!$B$15,Inputs!$B$14,0)+IF(17=Inputs!$B$17,Inputs!$B$16,0) -> 7590000 | S19: =R19+IF(18=Inputs!$B$11,Inputs!$B$10,0)+IF(18=Inputs!$B$13,Inputs!$B$12,0)+IF(18=Inputs!$B$15,Inputs!$B$14,0)+IF(18=Inputs!$B$17,Inputs!$B$16,0) -> 7590000 | T19: =S19+IF(19=Inputs!$B$11,Inputs!$B$10,0)+IF(19=Inputs!$B$13,Inputs!$B$12,0)+IF(19=Inputs!$B$15,Inputs!$B$14,0)+IF(19=Inputs!$B$17,Inputs!$B$16,0) -> 7590000 | U19: =T19+IF(20=Inputs!$B$11,Inputs!$B$10,0)+IF(20=Inputs!$B$13,Inputs!$B$12,0)+IF(20=Inputs!$B$15,Inputs!$B$14,0)+IF(20=Inputs!$B$17,Inputs!$B$16,0) -> 7590000 | V19: =U19+IF(21=Inputs!$B$11,Inputs!$B$10,0)+IF(21=Inputs!$B$13,Inputs!$B$12,0)+IF(21=Inputs!$B$15,Inputs!$B$14,0)+IF(21=Inputs!$B$17,Inputs!$B$16,0) -> 7590000 | W19: =V19+IF(22=Inputs!$B$11,Inputs!$B$10,0)+IF(22=Inputs!$B$13,Inputs!$B$12,0)+IF(22=Inputs!$B$15,Inputs!$B$14,0)+IF(22=Inputs!$B$17,Inputs!$B$16,0) -> 7590000 | X19: =W19+IF(23=Inputs!$B$11,Inputs!$B$10,0)+IF(23=Inputs!$B$13,Inputs!$B$12,0)+IF(23=Inputs!$B$15,Inputs!$B$14,0)+IF(23=Inputs!$B$17,Inputs!$B$16,0) -> 7590000 | Y19: =X19+IF(24=Inputs!$B$11,Inputs!$B$10,0)+IF(24=Inputs!$B$13,Inputs!$B$12,0)+IF(24=Inputs!$B$15,Inputs!$B$14,0)+IF(24=Inputs!$B$17,Inputs!$B$16,0) -> 7590000 | Z19: =Y19+IF(25=Inputs!$B$11,Inputs!$B$10,0)+IF(25=Inputs!$B$13,Inputs!$B$12,0)+IF(25=Inputs!$B$15,Inputs!$B$14,0)+IF(25=Inputs!$B$17,Inputs!$B$16,0) -> 7590000 | AA19: =Z19+IF(26=Inputs!$B$11,Inputs!$B$10,0)+IF(26=Inputs!$B$13,Inputs!$B$12,0)+IF(26=Inputs!$B$15,Inputs!$B$14,0)+IF(26=Inputs!$B$17,Inputs!$B$16,0) -> 7590000 | AB19: =AA19+IF(27=Inputs!$B$11,Inputs!$B$10,0)+IF(27=Inputs!$B$13,Inputs!$B$12,0)+IF(27=Inputs!$B$15,Inputs!$B$14,0)+IF(27=Inputs!$B$17,Inputs!$B$16,0) -> 7590000 | AC19: =AB19+IF(28=Inputs!$B$11,Inputs!$B$10,0)+IF(28=Inputs!$B$13,Inputs!$B$12,0)+IF(28=Inputs!$B$15,Inputs!$B$14,0)+IF(28=Inputs!$B$17,Inputs!$B$16,0) -> 7590000 | AD19: =AC19+IF(29=Inputs!$B$11,Inputs!$B$10,0)+IF(29=Inputs!$B$13,Inputs!$B$12,0)+IF(29=Inputs!$B$15,Inputs!$B$14,0)+IF(29=Inputs!$B$17,Inputs!$B$16,0) -> 7590000 | AE19: =AD19+IF(30=Inputs!$B$11,Inputs!$B$10,0)+IF(30=Inputs!$B$13,Inputs!$B$12,0)+IF(30=Inputs!$B$15,Inputs!$B$14,0)+IF(30=Inputs!$B$17,Inputs!$B$16,0) -> 7590000 | AF19: =AE19+IF(31=Inputs!$B$11,Inputs!$B$10,0)+IF(31=Inputs!$B$13,Inputs!$B$12,0)+IF(31=Inputs!$B$15,Inputs!$B$14,0)+IF(31=Inputs!$B$17,Inputs!$B$16,0) -> 7590000 | AG19: =AF19+IF(32=Inputs!$B$11,Inputs!$B$10,0)+IF(32=Inputs!$B$13,Inputs!$B$12,0)+IF(32=Inputs!$B$15,Inputs!$B$14,0)+IF(32=Inputs!$B$17,Inputs!$B$16,0) -> 7590000 | AH19: =AG19+IF(33=Inputs!$B$11,Inputs!$B$10,0)+IF(33=Inputs!$B$13,Inputs!$B$12,0)+IF(33=Inputs!$B$15,Inputs!$B$14,0)+IF(33=Inputs!$B$17,Inputs!$B$16,0) -> 7590000 | AI19: =AH19+IF(34=Inputs!$B$11,Inputs!$B$10,0)+IF(34=Inputs!$B$13,Inputs!$B$12,0)+IF(34=Inputs!$B$15,Inputs!$B$14,0)+IF(34=Inputs!$B$17,Inputs!$B$16,0) -> 7590000 | AJ19: =AI19+IF(35=Inputs!$B$11,Inputs!$B$10,0)+IF(35=Inputs!$B$13,Inputs!$B$12,0)+IF(35=Inputs!$B$15,Inputs!$B$14,0)+IF(35=Inputs!$B$17,Inputs!$B$16,0) -> 22590000 | AK19: =AJ19+IF(36=Inputs!$B$11,Inputs!$B$10,0)+IF(36=Inputs!$B$13,Inputs!$B$12,0)+IF(36=Inputs!$B$15,Inputs!$B$14,0)+IF(36=Inputs!$B$17,Inputs!$B$16,0) -> 22590000 | AL19: =AK19+IF(37=Inputs!$B$11,Inputs!$B$10,0)+IF(37=Inputs!$B$13,Inputs!$B$12,0)+IF(37=Inputs!$B$15,Inputs!$B$14,0)+IF(37=Inputs!$B$17,Inputs!$B$16,0) -> 22590000 | AM19: =AL19+IF(38=Inputs!$B$11,Inputs!$B$10,0)+IF(38=Inputs!$B$13,Inputs!$B$12,0)+IF(38=Inputs!$B$15,Inputs!$B$14,0)+IF(38=Inputs!$B$17,Inputs!$B$16,0) -> 22590000 | AN19: =AM19+IF(39=Inputs!$B$11,Inputs!$B$10,0)+IF(39=Inputs!$B$13,Inputs!$B$12,0)+IF(39=Inputs!$B$15,Inputs!$B$14,0)+IF(39=Inputs!$B$17,Inputs!$B$16,0) -> 22590000 | AO19: =AN19+IF(40=Inputs!$B$11,Inputs!$B$10,0)+IF(40=Inputs!$B$13,Inputs!$B$12,0)+IF(40=Inputs!$B$15,Inputs!$B$14,0)+IF(40=Inputs!$B$17,Inputs!$B$16,0) -> 22590000 | AP19: =AO19+IF(41=Inputs!$B$11,Inputs!$B$10,0)+IF(41=Inputs!$B$13,Inputs!$B$12,0)+IF(41=Inputs!$B$15,Inputs!$B$14,0)+IF(41=Inputs!$B$17,Inputs!$B$16,0) -> 22590000 | AQ19: =AP19+IF(42=Inputs!$B$11,Inputs!$B$10,0)+IF(42=Inputs!$B$13,Inputs!$B$12,0)+IF(42=Inputs!$B$15,Inputs!$B$14,0)+IF(42=Inputs!$B$17,Inputs!$B$16,0) -> 22590000 | AR19: =AQ19+IF(43=Inputs!$B$11,Inputs!$B$10,0)+IF(43=Inputs!$B$13,Inputs!$B$12,0)+IF(43=Inputs!$B$15,Inputs!$B$14,0)+IF(43=Inputs!$B$17,Inputs!$B$16,0) -> 22590000 | AS19: =AR19+IF(44=Inputs!$B$11,Inputs!$B$10,0)+IF(44=Inputs!$B$13,Inputs!$B$12,0)+IF(44=Inputs!$B$15,Inputs!$B$14,0)+IF(44=Inputs!$B$17,Inputs!$B$16,0) -> 22590000 | AT19: =AS19+IF(45=Inputs!$B$11,Inputs!$B$10,0)+IF(45=Inputs!$B$13,Inputs!$B$12,0)+IF(45=Inputs!$B$15,Inputs!$B$14,0)+IF(45=Inputs!$B$17,Inputs!$B$16,0) -> 22590000 | AU19: =AT19+IF(46=Inputs!$B$11,Inputs!$B$10,0)+IF(46=Inputs!$B$13,Inputs!$B$12,0)+IF(46=Inputs!$B$15,Inputs!$B$14,0)+IF(46=Inputs!$B$17,Inputs!$B$16,0) -> 22590000 | AV19: =AU19+IF(47=Inputs!$B$11,Inputs!$B$10,0)+IF(47=Inputs!$B$13,Inputs!$B$12,0)+IF(47=Inputs!$B$15,Inputs!$B$14,0)+IF(47=Inputs!$B$17,Inputs!$B$16,0) -> 22590000 | AW19: =AV19+IF(48=Inputs!$B$11,Inputs!$B$10,0)+IF(48=Inputs!$B$13,Inputs!$B$12,0)+IF(48=Inputs!$B$15,Inputs!$B$14,0)+IF(48=Inputs!$B$17,Inputs!$B$16,0) -> 22590000 | AX19: =AW19+IF(49=Inputs!$B$11,Inputs!$B$10,0)+IF(49=Inputs!$B$13,Inputs!$B$12,0)+IF(49=Inputs!$B$15,Inputs!$B$14,0)+IF(49=Inputs!$B$17,Inputs!$B$16,0) -> 22590000 | AY19: =AX19+IF(50=Inputs!$B$11,Inputs!$B$10,0)+IF(50=Inputs!$B$13,Inputs!$B$12,0)+IF(50=Inputs!$B$15,Inputs!$B$14,0)+IF(50=Inputs!$B$17,Inputs!$B$16,0) -> 22590000 | AZ19: =AY19+IF(51=Inputs!$B$11,Inputs!$B$10,0)+IF(51=Inputs!$B$13,Inputs!$B$12,0)+IF(51=Inputs!$B$15,Inputs!$B$14,0)+IF(51=Inputs!$B$17,Inputs!$B$16,0) -> 22590000 | BA19: =AZ19+IF(52=Inputs!$B$11,Inputs!$B$10,0)+IF(52=Inputs!$B$13,Inputs!$B$12,0)+IF(52=Inputs!$B$15,Inputs!$B$14,0)+IF(52=Inputs!$B$17,Inputs!$B$16,0) -> 22590000
A20: Retained Earnings | B20: ='P&L'!B39 -> -68146 | C20: =B20+'P&L'!C39 -> -110000.75 | D20: =C20+'P&L'!D39 -> -151990.69 | E20: =D20+'P&L'!E39 -> -194122.57 | F20: =E20+'P&L'!F39 -> -252153.5 | G20: =F20+'P&L'!G39 -> -294590.93 | H20: =G20+'P&L'!H39 -> -350808.34 | I20: =H20+'P&L'!I39 -> -419374.79 | J20: =I20+'P&L'!J39 -> -495005.15 | ... BA20: =AZ20+'P&L'!BA39 -> -7310233.8
A21: TOTAL EQUITY | B21: =B18+B19+B20 -> 46854 | C21: =C18+C19+C20 -> 4999.25 | D21: =D18+D19+D20 -> -36990.688 | E21: =E18+E19+E20 -> -79122.572 | F21: =F18+F19+F20 -> 1362846.5 | G21: =G18+G19+G20 -> 1320409.1 | H21: =H18+H19+H20 -> 1264191.7 | I21: =I18+I19+I20 -> 1195625.2 | ... BA21: =BA18+BA19+BA20 -> 15304766
A23: TOTAL LIABILITIES + EQUITY | B23: =B15+B21 -> 55283.5 | C23: =C15+C21 -> 10822.125 | D23: =D15+D21 -> -31159.544 | E23: =E15+E21 -> -73282.746 | F23: =F15+F21 -> 1370270.4 | G23: =G15+G21 -> 1326267.6 | H23: =H15+H21 -> 1272138.6 | I23: =I15+I21 -> 1205687.7 | ... BA23: =BA15+BA21 -> 15354714
A24: Check (Assets - L&E = 0) | B24: =B9-B23 -> -24725 | C24: =C9-C23 -> -24725 | D24: =D9-D23 -> -24725 | E24: =E9-E23 -> -24725 | F24: =F9-F23 -> -24725 | G24: =G9-G23 -> -24725 | H24: =H9-H23 -> -24725 | I24: =I9-I23 -> -24725 | ... BA24: =BA9-BA23 -> -24725

Sheet Cash Flow
A1: KAPITALFLUSSRECHNUNG (CASH FLOW)
B2: 46113 | C2: 46143 | D2: 46174 | E2: 46204 | F2: 46235 | G2: 46266 | H2: 46296 | I2: 46327 | J2: 46357 | K2: 46388 | L2: 46419 | M2: 46447 | N2: 46478 | O2: 46508 | P2: 46539 | Q2: 46569 | R2: 46600 | S2: 46631 | T2: 46661 | U2: 46692 | V2: 46722 | W2: 46753 | X2: 46784 | Y2: 46813 | Z2: 46844 | AA2: 46874 | AB2: 46905 | AC2: 46935 | AD2: 46966 | AE2: 46997 | AF2: 47027 | AG2: 47058 | AH2: 47088 | AI2: 47119 | AJ2: 47150 | AK2: 47178 | AL2: 47209 | AM2: 47239 | AN2: 47270 | AO2: 47300 | AP2: 47331 | AQ2: 47362 | AR2: 47392 | AS2: 47423 | AT2: 47453 | AU2: 47484 | AV2: 47515 | AW2: 47543 | AX2: 47574 | AY2: 47604 | AZ2: 47635 | BA2: 47665
A3: Position | B3: M1 | C3: M2 | D3: M3 | E3: M4 | F3: M5 | G3: M6 | H3: M7 | I3: M8 | J3: M9 | K3: M10 | L3: M11 | M3: M12 | N3: M13 | O3: M14 | P3: M15 | Q3: M16 | R3: M17 | S3: M18 | T3: M19 | U3: M20 | V3: M21 | W3: M22 | X3: M23 | Y3: M24 | Z3: M25 | AA3: M26 | AB3: M27 | AC3: M28 | AD3: M29 | AE3: M30 | AF3: M31 | AG3: M32 | AH3: M33 | AI3: M34 | AJ3: M35 | AK3: M36 | AL3: M37 | AM3: M38 | AN3: M39 | AO3: M40 | AP3: M41 | AQ3: M42 | AR3: M43 | AS3: M44 | AT3: M45 | AU3: M46 | AV3: M47 | AW3: M48 | AX3: M49 | AY3: M50 | AZ3: M51 | BA3: M52
A4: OPERATING ACTIVITIES
A5: Net Income | B5: ='P&L'!B39 -> -68146 | C5: ='P&L'!C39 -> -41854.75 | D5: ='P&L'!D39 -> -41989.938 | E5: ='P&L'!E39 -> -42131.884 | F5: ='P&L'!F39 -> -58030.929 | G5: ='P&L'!G39 -> -42437.425 | H5: ='P&L'!H39 -> -56217.413 | I5: ='P&L'!I39 -> -68566.45 | ... BA5: ='P&L'!BA39 -> -132111.73
A6: + Depreciation & Amortization | B6: ='P&L'!B32 -> 275 | C6: ='P&L'!C32 -> 0 | D6: ='P&L'!D32 -> 0 | E6: ='P&L'!E32 -> 0 | F6: ='P&L'!F32 -> 0 | G6: ='P&L'!G32 -> 0 | H6: ='P&L'!H32 -> 91.666667 | I6: ='P&L'!I32 -> 91.666667 | ... BA6: ='P&L'!BA32 -> 0
A7: Changes in Working Capital | B7: =-'Balance Sheet'!B6-'Balance Sheet'!B7+'Balance Sheet'!B12+'Balance Sheet'!B13+'Balance Sheet'!B14 -> 8429.5 | C7: =-('Balance Sheet'!C6-'Balance Sheet'!B6)-('Balance Sheet'!C7-'Balance Sheet'!B7)+('Balance Sheet'!C12-'Balance Sheet'!B12)+('Balance Sheet'!C13-'Balance Sheet'!B13)+('Balance Sheet'!C14-'Balance Sheet'!B14) -> -2606.625 | D7: =-('Balance Sheet'!D6-'Balance Sheet'!C6)-('Balance Sheet'!D7-'Balance Sheet'!C7)+('Balance Sheet'!D12-'Balance Sheet'!C12)+('Balance Sheet'!D13-'Balance Sheet'!C13)+('Balance Sheet'!D14-'Balance Sheet'!C14) -> 8.26875 | E7: =-('Balance Sheet'!E6-'Balance Sheet'!D6)-('Balance Sheet'!E7-'Balance Sheet'!D7)+('Balance Sheet'!E12-'Balance Sheet'!D12)+('Balance Sheet'!E13-'Balance Sheet'!D13)+('Balance Sheet'!E14-'Balance Sheet'!D14) -> 8.6821875 | F7: =-('Balance Sheet'!F6-'Balance Sheet'!E6)-('Balance Sheet'!F7-'Balance Sheet'!E7)+('Balance Sheet'!F12-'Balance Sheet'!E12)+('Balance Sheet'!F13-'Balance Sheet'!E13)+('Balance Sheet'!F14-'Balance Sheet'!E14) -> 1584.1163 | G7: =-('Balance Sheet'!G6-'Balance Sheet'!F6)-('Balance Sheet'!G7-'Balance Sheet'!F7)+('Balance Sheet'!G12-'Balance Sheet'!F12)+('Balance Sheet'!G13-'Balance Sheet'!F13)+('Balance Sheet'!G14-'Balance Sheet'!F14) -> -1565.4279 | H7: =-('Balance Sheet'!H6-'Balance Sheet'!G6)-('Balance Sheet'!H7-'Balance Sheet'!G7)+('Balance Sheet'!H12-'Balance Sheet'!G12)+('Balance Sheet'!H13-'Balance Sheet'!G13)+('Balance Sheet'!H14-'Balance Sheet'!G14) -> 2088.4507 | I7: =-('Balance Sheet'!I6-'Balance Sheet'!H6)-('Balance Sheet'!I7-'Balance Sheet'!H7)+('Balance Sheet'!I12-'Balance Sheet'!H12)+('Balance Sheet'!I13-'Balance Sheet'!H13)+('Balance Sheet'!I14-'Balance Sheet'!H14) -> 2115.5366 | J7: =-('Balance Sheet'!J6-'Balance Sheet'!I6)-('Balance Sheet'!J7-'Balance Sheet'!I7)+('Balance Sheet'!J12-'Balance Sheet'!I12)+('Balance Sheet'!J13-'Balance Sheet'!I13)+('Balance Sheet'!J14-'Balance Sheet'!I14) -> 1183.3559 | ... BA7: =-('Balance Sheet'!BA6-'Balance Sheet'!AZ6)-('Balance Sheet'!BA7-'Balance Sheet'!AZ7)+('Balance Sheet'!BA12-'Balance Sheet'!AZ12)+('Balance Sheet'!BA13-'Balance Sheet'!AZ13)+('Balance Sheet'!BA14-'Balance Sheet'!AZ14) -> -88.258403
A8: Net Cash from Operations | B8: =B5+B6+B7 -> -59441.5 | C8: =C5+C6+C7 -> -44461.375 | D8: =D5+D6+D7 -> -41981.669 | E8: =E5+E6+E7 -> -42123.202 | F8: =F5+F6+F7 -> -56446.812 | G8: =G5+G6+G7 -> -44002.853 | H8: =H5+H6+H7 -> -54037.296 | I8: =I5+I6+I7 -> -66359.247 | ... BA8: =BA5+BA6+BA7 -> -132199.99
A10: INVESTING ACTIVITIES
A11: Purchase of Equipment | B11: =-(Costs!B123+Inputs!$B$103) -> -14900 | C11: =-Costs!C123 -> 0 | D11: =-Costs!D123 -> 0 | E11: =-Costs!E123 -> 0 | F11: =-Costs!F123 -> 0 | G11: =-Costs!G123 -> 0 | H11: =-Costs!H123 -> -3300 | I11: =-Costs!I123 -> -3300 | J11: =-Costs!J123 -> -3300 | ... BA11: =-Costs!BA123 -> 0
A12: Net Cash from Investing | B12: =B11 -> -14900 | C12: =C11 -> 0 | D12: =D11 -> 0 | E12: =E11 -> 0 | F12: =F11 -> 0 | G12: =G11 -> 0 | H12: =H11 -> -3300 | I12: =I11 -> -3300 | ... BA12: =BA11 -> 0
A14: FINANCING ACTIVITIES
A15: Equity Funding Received | B15: =IF(1=Inputs!$B$11,Inputs!$B$10,0)+IF(1=Inputs!$B$13,Inputs!$B$12,0)+IF(1=Inputs!$B$15,Inputs!$B$14,0)+IF(1=Inputs!$B$17,Inputs!$B$16,0) -> 90000 | C15: =IF(2=Inputs!$B$11,Inputs!$B$10,0)+IF(2=Inputs!$B$13,Inputs!$B$12,0)+IF(2=Inputs!$B$15,Inputs!$B$14,0)+IF(2=Inputs!$B$17,Inputs!$B$16,0) -> 0 | D15: =IF(3=Inputs!$B$11,Inputs!$B$10,0)+IF(3=Inputs!$B$13,Inputs!$B$12,0)+IF(3=Inputs!$B$15,Inputs!$B$14,0)+IF(3=Inputs!$B$17,Inputs!$B$16,0) -> 0 | E15: =IF(4=Inputs!$B$11,Inputs!$B$10,0)+IF(4=Inputs!$B$13,Inputs!$B$12,0)+IF(4=Inputs!$B$15,Inputs!$B$14,0)+IF(4=Inputs!$B$17,Inputs!$B$16,0) -> 0 | F15: =IF(5=Inputs!$B$11,Inputs!$B$10,0)+IF(5=Inputs!$B$13,Inputs!$B$12,0)+IF(5=Inputs!$B$15,Inputs!$B$14,0)+IF(5=Inputs!$B$17,Inputs!$B$16,0) -> 1500000 | G15: =IF(6=Inputs!$B$11,Inputs!$B$10,0)+IF(6=Inputs!$B$13,Inputs!$B$12,0)+IF(6=Inputs!$B$15,Inputs!$B$14,0)+IF(6=Inputs!$B$17,Inputs!$B$16,0) -> 0 | H15: =IF(7=Inputs!$B$11,Inputs!$B$10,0)+IF(7=Inputs!$B$13,Inputs!$B$12,0)+IF(7=Inputs!$B$15,Inputs!$B$14,0)+IF(7=Inputs!$B$17,Inputs!$B$16,0) -> 0 | I15: =IF(8=Inputs!$B$11,Inputs!$B$10,0)+IF(8=Inputs!$B$13,Inputs!$B$12,0)+IF(8=Inputs!$B$15,Inputs!$B$14,0)+IF(8=Inputs!$B$17,Inputs!$B$16,0) -> 0 | J15: =IF(9=Inputs!$B$11,Inputs!$B$10,0)+IF(9=Inputs!$B$13,Inputs!$B$12,0)+IF(9=Inputs!$B$15,Inputs!$B$14,0)+IF(9=Inputs!$B$17,Inputs!$B$16,0) -> 0 | K15: =IF(10=Inputs!$B$11,Inputs!$B$10,0)+IF(10=Inputs!$B$13,Inputs!$B$12,0)+IF(10=Inputs!$B$15,Inputs!$B$14,0)+IF(10=Inputs!$B$17,Inputs!$B$16,0) -> 0 | L15: =IF(11=Inputs!$B$11,Inputs!$B$10,0)+IF(11=Inputs!$B$13,Inputs!$B$12,0)+IF(11=Inputs!$B$15,Inputs!$B$14,0)+IF(11=Inputs!$B$17,Inputs!$B$16,0) -> 0 | M15: =IF(12=Inputs!$B$11,Inputs!$B$10,0)+IF(12=Inputs!$B$13,Inputs!$B$12,0)+IF(12=Inputs!$B$15,Inputs!$B$14,0)+IF(12=Inputs!$B$17,Inputs!$B$16,0) -> 0 | N15: =IF(13=Inputs!$B$11,Inputs!$B$10,0)+IF(13=Inputs!$B$13,Inputs!$B$12,0)+IF(13=Inputs!$B$15,Inputs!$B$14,0)+IF(13=Inputs!$B$17,Inputs!$B$16,0) -> 0 | O15: =IF(14=Inputs!$B$11,Inputs!$B$10,0)+IF(14=Inputs!$B$13,Inputs!$B$12,0)+IF(14=Inputs!$B$15,Inputs!$B$14,0)+IF(14=Inputs!$B$17,Inputs!$B$16,0) -> 0 | P15: =IF(15=Inputs!$B$11,Inputs!$B$10,0)+IF(15=Inputs!$B$13,Inputs!$B$12,0)+IF(15=Inputs!$B$15,Inputs!$B$14,0)+IF(15=Inputs!$B$17,Inputs!$B$16,0) -> 0 | Q15: =IF(16=Inputs!$B$11,Inputs!$B$10,0)+IF(16=Inputs!$B$13,Inputs!$B$12,0)+IF(16=Inputs!$B$15,Inputs!$B$14,0)+IF(16=Inputs!$B$17,Inputs!$B$16,0) -> 0 | R15: =IF(17=Inputs!$B$11,Inputs!$B$10,0)+IF(17=Inputs!$B$13,Inputs!$B$12,0)+IF(17=Inputs!$B$15,Inputs!$B$14,0)+IF(17=Inputs!$B$17,Inputs!$B$16,0) -> 6000000 | S15: =IF(18=Inputs!$B$11,Inputs!$B$10,0)+IF(18=Inputs!$B$13,Inputs!$B$12,0)+IF(18=Inputs!$B$15,Inputs!$B$14,0)+IF(18=Inputs!$B$17,Inputs!$B$16,0) -> 0 | T15: =IF(19=Inputs!$B$11,Inputs!$B$10,0)+IF(19=Inputs!$B$13,Inputs!$B$12,0)+IF(19=Inputs!$B$15,Inputs!$B$14,0)+IF(19=Inputs!$B$17,Inputs!$B$16,0) -> 0 | U15: =IF(20=Inputs!$B$11,Inputs!$B$10,0)+IF(20=Inputs!$B$13,Inputs!$B$12,0)+IF(20=Inputs!$B$15,Inputs!$B$14,0)+IF(20=Inputs!$B$17,Inputs!$B$16,0) -> 0 | V15: =IF(21=Inputs!$B$11,Inputs!$B$10,0)+IF(21=Inputs!$B$13,Inputs!$B$12,0)+IF(21=Inputs!$B$15,Inputs!$B$14,0)+IF(21=Inputs!$B$17,Inputs!$B$16,0) -> 0 | W15: =IF(22=Inputs!$B$11,Inputs!$B$10,0)+IF(22=Inputs!$B$13,Inputs!$B$12,0)+IF(22=Inputs!$B$15,Inputs!$B$14,0)+IF(22=Inputs!$B$17,Inputs!$B$16,0) -> 0 | X15: =IF(23=Inputs!$B$11,Inputs!$B$10,0)+IF(23=Inputs!$B$13,Inputs!$B$12,0)+IF(23=Inputs!$B$15,Inputs!$B$14,0)+IF(23=Inputs!$B$17,Inputs!$B$16,0) -> 0 | Y15: =IF(24=Inputs!$B$11,Inputs!$B$10,0)+IF(24=Inputs!$B$13,Inputs!$B$12,0)+IF(24=Inputs!$B$15,Inputs!$B$14,0)+IF(24=Inputs!$B$17,Inputs!$B$16,0) -> 0 | Z15: =IF(25=Inputs!$B$11,Inputs!$B$10,0)+IF(25=Inputs!$B$13,Inputs!$B$12,0)+IF(25=Inputs!$B$15,Inputs!$B$14,0)+IF(25=Inputs!$B$17,Inputs!$B$16,0) -> 0 | AA15: =IF(26=Inputs!$B$11,Inputs!$B$10,0)+IF(26=Inputs!$B$13,Inputs!$B$12,0)+IF(26=Inputs!$B$15,Inputs!$B$14,0)+IF(26=Inputs!$B$17,Inputs!$B$16,0) -> 0 | AB15: =IF(27=Inputs!$B$11,Inputs!$B$10,0)+IF(27=Inputs!$B$13,Inputs!$B$12,0)+IF(27=Inputs!$B$15,Inputs!$B$14,0)+IF(27=Inputs!$B$17,Inputs!$B$16,0) -> 0 | AC15: =IF(28=Inputs!$B$11,Inputs!$B$10,0)+IF(28=Inputs!$B$13,Inputs!$B$12,0)+IF(28=Inputs!$B$15,Inputs!$B$14,0)+IF(28=Inputs!$B$17,Inputs!$B$16,0) -> 0 | AD15: =IF(29=Inputs!$B$11,Inputs!$B$10,0)+IF(29=Inputs!$B$13,Inputs!$B$12,0)+IF(29=Inputs!$B$15,Inputs!$B$14,0)+IF(29=Inputs!$B$17,Inputs!$B$16,0) -> 0 | AE15: =IF(30=Inputs!$B$11,Inputs!$B$10,0)+IF(30=Inputs!$B$13,Inputs!$B$12,0)+IF(30=Inputs!$B$15,Inputs!$B$14,0)+IF(30=Inputs!$B$17,Inputs!$B$16,0) -> 0 | AF15: =IF(31=Inputs!$B$11,Inputs!$B$10,0)+IF(31=Inputs!$B$13,Inputs!$B$12,0)+IF(31=Inputs!$B$15,Inputs!$B$14,0)+IF(31=Inputs!$B$17,Inputs!$B$16,0) -> 0 | AG15: =IF(32=Inputs!$B$11,Inputs!$B$10,0)+IF(32=Inputs!$B$13,Inputs!$B$12,0)+IF(32=Inputs!$B$15,Inputs!$B$14,0)+IF(32=Inputs!$B$17,Inputs!$B$16,0) -> 0 | AH15: =IF(33=Inputs!$B$11,Inputs!$B$10,0)+IF(33=Inputs!$B$13,Inputs!$B$12,0)+IF(33=Inputs!$B$15,Inputs!$B$14,0)+IF(33=Inputs!$B$17,Inputs!$B$16,0) -> 0 | AI15: =IF(34=Inputs!$B$11,Inputs!$B$10,0)+IF(34=Inputs!$B$13,Inputs!$B$12,0)+IF(34=Inputs!$B$15,Inputs!$B$14,0)+IF(34=Inputs!$B$17,Inputs!$B$16,0) -> 0 | AJ15: =IF(35=Inputs!$B$11,Inputs!$B$10,0)+IF(35=Inputs!$B$13,Inputs!$B$12,0)+IF(35=Inputs!$B$15,Inputs!$B$14,0)+IF(35=Inputs!$B$17,Inputs!$B$16,0) -> 15000000 | AK15: =IF(36=Inputs!$B$11,Inputs!$B$10,0)+IF(36=Inputs!$B$13,Inputs!$B$12,0)+IF(36=Inputs!$B$15,Inputs!$B$14,0)+IF(36=Inputs!$B$17,Inputs!$B$16,0) -> 0 | AL15: =IF(37=Inputs!$B$11,Inputs!$B$10,0)+IF(37=Inputs!$B$13,Inputs!$B$12,0)+IF(37=Inputs!$B$15,Inputs!$B$14,0)+IF(37=Inputs!$B$17,Inputs!$B$16,0) -> 0 | AM15: =IF(38=Inputs!$B$11,Inputs!$B$10,0)+IF(38=Inputs!$B$13,Inputs!$B$12,0)+IF(38=Inputs!$B$15,Inputs!$B$14,0)+IF(38=Inputs!$B$17,Inputs!$B$16,0) -> 0 | AN15: =IF(39=Inputs!$B$11,Inputs!$B$10,0)+IF(39=Inputs!$B$13,Inputs!$B$12,0)+IF(39=Inputs!$B$15,Inputs!$B$14,0)+IF(39=Inputs!$B$17,Inputs!$B$16,0) -> 0 | AO15: =IF(40=Inputs!$B$11,Inputs!$B$10,0)+IF(40=Inputs!$B$13,Inputs!$B$12,0)+IF(40=Inputs!$B$15,Inputs!$B$14,0)+IF(40=Inputs!$B$17,Inputs!$B$16,0) -> 0 | AP15: =IF(41=Inputs!$B$11,Inputs!$B$10,0)+IF(41=Inputs!$B$13,Inputs!$B$12,0)+IF(41=Inputs!$B$15,Inputs!$B$14,0)+IF(41=Inputs!$B$17,Inputs!$B$16,0) -> 0 | AQ15: =IF(42=Inputs!$B$11,Inputs!$B$10,0)+IF(42=Inputs!$B$13,Inputs!$B$12,0)+IF(42=Inputs!$B$15,Inputs!$B$14,0)+IF(42=Inputs!$B$17,Inputs!$B$16,0) -> 0 | AR15: =IF(43=Inputs!$B$11,Inputs!$B$10,0)+IF(43=Inputs!$B$13,Inputs!$B$12,0)+IF(43=Inputs!$B$15,Inputs!$B$14,0)+IF(43=Inputs!$B$17,Inputs!$B$16,0) -> 0 | AS15: =IF(44=Inputs!$B$11,Inputs!$B$10,0)+IF(44=Inputs!$B$13,Inputs!$B$12,0)+IF(44=Inputs!$B$15,Inputs!$B$14,0)+IF(44=Inputs!$B$17,Inputs!$B$16,0) -> 0 | AT15: =IF(45=Inputs!$B$11,Inputs!$B$10,0)+IF(45=Inputs!$B$13,Inputs!$B$12,0)+IF(45=Inputs!$B$15,Inputs!$B$14,0)+IF(45=Inputs!$B$17,Inputs!$B$16,0) -> 0 | AU15: =IF(46=Inputs!$B$11,Inputs!$B$10,0)+IF(46=Inputs!$B$13,Inputs!$B$12,0)+IF(46=Inputs!$B$15,Inputs!$B$14,0)+IF(46=Inputs!$B$17,Inputs!$B$16,0) -> 0 | AV15: =IF(47=Inputs!$B$11,Inputs!$B$10,0)+IF(47=Inputs!$B$13,Inputs!$B$12,0)+IF(47=Inputs!$B$15,Inputs!$B$14,0)+IF(47=Inputs!$B$17,Inputs!$B$16,0) -> 0 | AW15: =IF(48=Inputs!$B$11,Inputs!$B$10,0)+IF(48=Inputs!$B$13,Inputs!$B$12,0)+IF(48=Inputs!$B$15,Inputs!$B$14,0)+IF(48=Inputs!$B$17,Inputs!$B$16,0) -> 0 | AX15: =IF(49=Inputs!$B$11,Inputs!$B$10,0)+IF(49=Inputs!$B$13,Inputs!$B$12,0)+IF(49=Inputs!$B$15,Inputs!$B$14,0)+IF(49=Inputs!$B$17,Inputs!$B$16,0) -> 0 | AY15: =IF(50=Inputs!$B$11,Inputs!$B$10,0)+IF(50=Inputs!$B$13,Inputs!$B$12,0)+IF(50=Inputs!$B$15,Inputs!$B$14,0)+IF(50=Inputs!$B$17,Inputs!$B$16,0) -> 0 | AZ15: =IF(51=Inputs!$B$11,Inputs!$B$10,0)+IF(51=Inputs!$B$13,Inputs!$B$12,0)+IF(51=Inputs!$B$15,Inputs!$B$14,0)+IF(51=Inputs!$B$17,Inputs!$B$16,0) -> 0 | BA15: =IF(52=Inputs!$B$11,Inputs!$B$10,0)+IF(52=Inputs!$B$13,Inputs!$B$12,0)+IF(52=Inputs!$B$15,Inputs!$B$14,0)+IF(52=Inputs!$B$17,Inputs!$B$16,0) -> 0
A16: Net Cash from Financing | B16: =B15 -> 90000 | C16: =C15 -> 0 | D16: =D15 -> 0 | E16: =E15 -> 0 | F16: =F15 -> 1500000 | G16: =G15 -> 0 | H16: =H15 -> 0 | I16: =I15 -> 0 | ... BA16: =BA15 -> 0
A18: NET CHANGE IN CASH | B18: =B8+B12+B16 -> 15658.5 | C18: =C8+C12+C16 -> -44461.375 | D18: =D8+D12+D16 -> -41981.669 | E18: =E8+E12+E16 -> -42123.202 | F18: =F8+F12+F16 -> 1443553.2 | G18: =G8+G12+G16 -> -44002.853 | H18: =H8+H12+H16 -> -57337.296 | I18: =I8+I12+I16 -> -69659.247 | ... BA18: =BA8+BA12+BA16 -> -132199.99
A20: Beginning Cash Balance | B20: 0 | C20: =B22 -> 15658.5 | D20: =C22 -> -28802.875 | E20: =D22 -> -70784.544 | F20: =E22 -> -112907.75 | G20: =F22 -> 1330645.4 | H20: =G22 -> 1286642.6 | I20: =H22 -> 1229305.3 | J20: =I22 -> 1159646 | ... BA20: =AZ22 -> 15231042
A21: Net Change | B21: =B18 -> 15658.5 | C21: =C18 -> -44461.375 | D21: =D18 -> -41981.669 | E21: =E18 -> -42123.202 | F21: =F18 -> 1443553.2 | G21: =G18 -> -44002.853 | H21: =H18 -> -57337.296 | I21: =I18 -> -69659.247 | ... BA21: =BA18 -> -132199.99
A22: ENDING CASH BALANCE | B22: =B20+B21 -> 15658.5 | C22: =C20+C21 -> -28802.875 | D22: =D20+D21 -> -70784.544 | E22: =E20+E21 -> -112907.75 | F22: =F20+F21 -> 1330645.4 | G22: =G20+G21 -> 1286642.6 | H22: =H20+H21 -> 1229305.3 | I22: =I20+I21 -> 1159646 | ... BA22: =BA20+BA21 -> 15098842
A24: KEY METRICS
A25: Monthly Burn Rate | B25: =IF(B18<0,-B18,0) -> 0 | C25: =IF(C18<0,-C18,0) -> 44461.375 | D25: =IF(D18<0,-D18,0) -> 41981.669 | E25: =IF(E18<0,-E18,0) -> 42123.202 | F25: =IF(F18<0,-F18,0) -> 0 | G25: =IF(G18<0,-G18,0) -> 44002.853 | H25: =IF(H18<0,-H18,0) -> 57337.296 | I25: =IF(I18<0,-I18,0) -> 69659.247 | ... BA25: =IF(BA18<0,-BA18,0) -> 132199.99
A26: Runway (Months) | B26: =IFERROR(IF(B25>0,B22/B25,"∞"),"∞") -> ∞ | C26: =IFERROR(IF(C25>0,C22/C25,"∞"),"∞") -> -0.64781791 | D26: =IFERROR(IF(D25>0,D22/D25,"∞"),"∞") -> -1.6860822 | E26: =IFERROR(IF(E25>0,E22/E25,"∞"),"∞") -> -2.680417 | F26: =IFERROR(IF(F25>0,F22/F25,"∞"),"∞") -> ∞ | G26: =IFERROR(IF(G25>0,G22/G25,"∞"),"∞") -> 29.239981 | H26: =IFERROR(IF(H25>0,H22/H25,"∞"),"∞") -> 21.43989 | I26: =IFERROR(IF(I25>0,I22/I25,"∞"),"∞") -> 16.64741 | ... BA26: =IFERROR(IF(BA25>0,BA22/BA25,"∞"),"∞") -> 114.21213
A27: Cumulative Cash Position | B27: =B22 -> 15658.5 | C27: =C22 -> -28802.875 | D27: =D22 -> -70784.544 | E27: =E22 -> -112907.75 | F27: =F22 -> 1330645.4 | G27: =G22 -> 1286642.6 | H27: =H22 -> 1229305.3 | I27: =I22 -> 1159646 | ... BA27: =BA22 -> 15098842
A28: Cash Runway Alert | B28: =IF(ISNUMBER(B26),IF(B26<6,"WARNUNG: <6 Monate!","OK"),"OK") -> OK | C28: =IF(ISNUMBER(C26),IF(C26<6,"WARNUNG: <6 Monate!","OK"),"OK") -> WARNUNG: <6 Monate! | D28: =IF(ISNUMBER(D26),IF(D26<6,"WARNUNG: <6 Monate!","OK"),"OK") -> WARNUNG: <6 Monate! | E28: =IF(ISNUMBER(E26),IF(E26<6,"WARNUNG: <6 Monate!","OK"),"OK") -> WARNUNG: <6 Monate! | F28: =IF(ISNUMBER(F26),IF(F26<6,"WARNUNG: <6 Monate!","OK"),"OK") -> OK | G28: =IF(ISNUMBER(G26),IF(G26<6,"WARNUNG: <6 Monate!","OK"),"OK") -> OK | H28: =IF(ISNUMBER(H26),IF(H26<6,"WARNUNG: <6 Monate!","OK"),"OK") -> OK | I28: =IF(ISNUMBER(I26),IF(I26<6,"WARNUNG: <6 Monate!","OK"),"OK") -> OK | ... BA28: =IF(ISNUMBER(BA26),IF(BA26<6,"WARNUNG: <6 Monate!","OK"),"OK") -> OK
